{
  "type": "Feature",
  "properties": {
    "gn:admin1_code":"36",
    "gn:admin2_code":"156035.0",
    "gn:asciiname":"Buzad",
    "gn:country_code":"RO",
    "gn:dem":192,
    "gn:feature_class":"P",
    "gn:feature_code":"PPL",
    "gn:name":"Buzad",
    "gn:population":258,
    "gn:timezone":"Europe/Bucharest",
    "iso:country":"RO",
    "wof:name":"Buzad",
    "wof:placetype":"locality",
    "wof:population":258
},
  "geometry": {"coordinates":[21.54737,45.94307],"type":"Point"}
}