{
  "type": "Feature",
  "properties": {
    "gn:gn_country":"RO",
    "gn:gn_fcode":"PPL",
    "gn:gn_pop":0,
    "gn:population":659,
    "iso:country":"RO",
    "name:fra_x_preferred":[
        "Bucium"
    ],
    "name:heb_x_preferred":[
        "\u05d1\u05d5\u05e6'\u05d9\u05d5\u05dd"
    ],
    "name:ita_x_preferred":[
        "Bucium"
    ],
    "name:ron_x_preferred":[
        "Bucium"
    ],
    "qs_pg:aaroncc":"RO",
    "qs_pg:gn_country":"RO",
    "qs_pg:gn_fcode":"PPL",
    "qs_pg:gn_pop":0,
    "qs_pg:name":"Bucium",
    "qs_pg:name_adm0":"Rom\u00e2nia",
    "qs_pg:name_adm1":"Iasi",
    "qs_pg:photos":16,
    "qs_pg:photos_1k":3,
    "qs_pg:photos_9k":1,
    "qs_pg:photos_9r":1,
    "qs_pg:photos_all":16,
    "qs_pg:photos_sr":1,
    "qs_pg:pop_sr":0,
    "qs_pg:qs_pg_placetype":"locality",
    "qs_pg:qs_pg_placetype_gp":"Town",
    "qs_pg:woe_adm0":23424933,
    "woe:adm0_id":23424933,
    "woe:name_adm0":"Rom\u00e2nia",
    "woe:name_adm1":"Iasi",
    "woe:placetype":"Town",
    "wof:name":"Bucium",
    "wof:placetype":"locality",
    "wof:population":659
},
  "geometry": {"coordinates":[27.06667,46.78333],"type":"Point"}
}