{
  "type": "Feature",
  "properties": {
    "gn:admin1_code":"36",
    "gn:admin2_code":"157362.0",
    "gn:asciiname":"Clopodia",
    "gn:cc2":"RO",
    "gn:country_code":"RO",
    "gn:dem":113,
    "gn:feature_class":"P",
    "gn:feature_code":"PPL",
    "gn:name":"Clopodia",
    "gn:population":796,
    "gn:timezone":"Europe/Bucharest",
    "iso:country":"RO",
    "name:und_x_variant":[
        "Klopodia",
        "Clopotia",
        "Klokodia",
        "Klopotyia",
        "Clopodia"
    ],
    "wof:name":"Clopodia",
    "wof:placetype":"locality",
    "wof:population":796
},
  "geometry": {"coordinates":[21.4661,45.28214000000001],"type":"Point"}
}