{
  "type": "Feature",
  "properties": {
    "gn:admin1_code":"16",
    "gn:admin2_code":"66330.0",
    "gn:asciiname":"Magura",
    "gn:cc2":"RO",
    "gn:country_code":"RO",
    "gn:dem":487,
    "gn:feature_class":"P",
    "gn:feature_code":"PPL",
    "gn:name":"M\u0103gura",
    "gn:population":606,
    "gn:timezone":"Europe/Bucharest",
    "iso:country":"RO",
    "name:ceb_x_preferred":[
        "Magura"
    ],
    "name:ces_x_preferred":[
        "Magura"
    ],
    "name:deu_x_preferred":[
        "Magura"
    ],
    "name:epo_x_preferred":[
        "Magura"
    ],
    "name:nld_x_preferred":[
        "Magura"
    ],
    "name:pol_x_preferred":[
        "Magura"
    ],
    "name:ron_x_preferred":[
        "Magura"
    ],
    "name:rus_x_preferred":[
        "\u041c\u0430\u0433\u0443\u0440\u0430"
    ],
    "name:slk_x_preferred":[
        "Magura"
    ],
    "name:srp_x_preferred":[
        "\u041c\u0430\u0433\u0443\u0440\u0430"
    ],
    "name:swe_x_preferred":[
        "Magura"
    ],
    "name:ukr_x_preferred":[
        "\u041c\u0430\u0491\u0443\u0440\u0430"
    ],
    "name:und_x_variant":[
        "M\u0103gura-Bela",
        "M\u0103gura"
    ],
    "wof:name":"Magura",
    "wof:placetype":"locality",
    "wof:population":606
},
  "geometry": {"coordinates":[25.47202,45.127],"type":"Point"}
}