{
  "type": "Feature",
  "properties": {
    "gn:gn_country":"RO",
    "gn:gn_fcode":"PPLA2",
    "gn:gn_pop":2521,
    "gn:population":2521,
    "iso:country":"RO",
    "name:ceb_x_preferred":[
        "Dr\u0103ge\u0219ti"
    ],
    "name:eng_x_preferred":[
        "Dr\u0103ge\u0219ti"
    ],
    "name:fra_x_preferred":[
        "Dr\u0103ge\u0219ti"
    ],
    "name:hun_x_preferred":[
        "Dr\u00e1gcs\u00e9ke"
    ],
    "name:ita_x_preferred":[
        "Dr\u0103ge\u0219ti"
    ],
    "name:nld_x_preferred":[
        "Dr\u0103ge\u0219ti"
    ],
    "name:ron_x_preferred":[
        "Dr\u0103ge\u0219ti"
    ],
    "name:srp_x_preferred":[
        "\u0414\u0440\u0430\u0452\u0435\u0448\u0442\u0438"
    ],
    "name:ukr_x_preferred":[
        "\u0414\u0440\u0435\u0434\u0436\u0435\u0448\u0442\u044c"
    ],
    "qs_pg:aaroncc":"RO",
    "qs_pg:gn_country":"RO",
    "qs_pg:gn_fcode":"PPLA2",
    "qs_pg:gn_pop":2521,
    "qs_pg:name":"Dr\u0103ge\u015fti",
    "qs_pg:photos_9r":0,
    "qs_pg:photos_sr":0,
    "qs_pg:pop_sr":4,
    "qs_pg:qs_pg_placetype":"locality",
    "wof:name":"Dr\u0103ge\u015fti",
    "wof:placetype":"locality",
    "wof:population":2521
},
  "geometry": {"coordinates":[22.13333,46.88333],"type":"Point"}
}