{
  "type": "Feature",
  "properties": {
    "gn:admin1_code":"38",
    "gn:admin2_code":"165185.0",
    "gn:asciiname":"Capotesti",
    "gn:country_code":"RO",
    "gn:dem":82,
    "gn:feature_class":"P",
    "gn:feature_code":"PPL",
    "gn:name":"C\u0103pote\u0219ti",
    "gn:population":142,
    "gn:timezone":"Europe/Bucharest",
    "iso:country":"RO",
    "wof:name":"Capotesti",
    "wof:placetype":"locality",
    "wof:population":142
},
  "geometry": {"coordinates":[28.09864,46.59413],"type":"Point"}
}