{
  "type": "Feature",
  "properties": {
    "gn:admin1_code":"22",
    "gn:admin2_code":"93735.0",
    "gn:asciiname":"Tarlele",
    "gn:country_code":"RO",
    "gn:dem":42,
    "gn:feature_class":"P",
    "gn:feature_code":"PPL",
    "gn:name":"T\u00e2rlele",
    "gn:population":0,
    "gn:timezone":"Europe/Bucharest",
    "iso:country":"RO",
    "wof:lang_x_official":[
        "ron"
    ],
    "wof:lang_x_spoken":[
        "ron"
    ],
    "wof:name":"Tarlele",
    "wof:placetype":"locality"
},
  "geometry": {"coordinates":[27.28333,44.73333],"type":"Point"}
}