{
  "type": "Feature",
  "properties": {
    "gn:admin1_code":"39",
    "gn:admin2_code":"169681.0",
    "gn:asciiname":"Catetu",
    "gn:country_code":"RO",
    "gn:dem":321,
    "gn:feature_class":"P",
    "gn:feature_code":"PPL",
    "gn:name":"C\u0103\u021betu",
    "gn:population":403,
    "gn:timezone":"Europe/Bucharest",
    "iso:country":"RO",
    "wof:name":"Catetu",
    "wof:placetype":"locality",
    "wof:population":403
},
  "geometry": {"coordinates":[23.96667,44.83333],"type":"Point"}
}