{
  "type": "Feature",
  "properties": {
    "gn:admin1_code":"29",
    "gn:admin2_code":"129987.0",
    "gn:asciiname":"Dealu Mare",
    "gn:country_code":"RO",
    "gn:dem":135,
    "gn:feature_class":"P",
    "gn:feature_code":"PPL",
    "gn:name":"Dealu Mare",
    "gn:population":0,
    "gn:timezone":"Europe/Bucharest",
    "iso:country":"RO",
    "name:ceb_x_preferred":[
        "Dealu Mare"
    ],
    "name:deu_x_preferred":[
        "Dealu Mare"
    ],
    "name:epo_x_preferred":[
        "Dealu Mare"
    ],
    "name:ron_x_preferred":[
        "Dealu Mare"
    ],
    "name:srp_x_preferred":[
        "\u0414\u0435\u0430\u043b\u0443 \u041c\u0430\u0440\u0435"
    ],
    "wof:name":"Dealu Mare",
    "wof:placetype":"locality"
},
  "geometry": {"coordinates":[24.55,44.28333],"type":"Point"}
}