{
  "type": "Feature",
  "properties": {
    "gn:admin1_code":"30",
    "gn:admin2_code":"132574.0",
    "gn:asciiname":"Valea Lespezii",
    "gn:country_code":"RO",
    "gn:dem":601,
    "gn:feature_class":"P",
    "gn:feature_code":"PPL",
    "gn:name":"Valea Lespezii",
    "gn:population":484,
    "gn:timezone":"Europe/Bucharest",
    "iso:country":"RO",
    "wof:name":"Valea Lespezii",
    "wof:placetype":"locality",
    "wof:population":484
},
  "geometry": {"coordinates":[26.04266,45.34475],"type":"Point"}
}