{
  "type": "Feature",
  "properties": {
    "gn:admin1_code":"26",
    "gn:admin2_code":"110946.0",
    "gn:asciiname":"Vrancea",
    "gn:cc2":"RO",
    "gn:country_code":"RO",
    "gn:dem":49,
    "gn:feature_class":"P",
    "gn:feature_code":"PPL",
    "gn:name":"Vrancea",
    "gn:population":320,
    "gn:timezone":"Europe/Bucharest",
    "iso:country":"RO",
    "name:ceb_x_preferred":[
        "Vrancea"
    ],
    "name:deu_x_preferred":[
        "Vrancea"
    ],
    "name:hrv_x_preferred":[
        "Vrancea"
    ],
    "name:slk_x_preferred":[
        "Vrancea"
    ],
    "name:und_x_variant":[
        "Vranca"
    ],
    "wof:name":"Vrancea",
    "wof:placetype":"locality",
    "wof:population":320
},
  "geometry": {"coordinates":[22.59942,44.54531],"type":"Point"}
}