{
  "type": "Feature",
  "properties": {
    "gn:admin1_code":"22",
    "gn:admin2_code":"94492.0",
    "gn:asciiname":"Retezatu",
    "gn:cc2":"RO",
    "gn:country_code":"RO",
    "gn:dem":11,
    "gn:feature_class":"P",
    "gn:feature_code":"PPL",
    "gn:name":"Retezatu",
    "gn:population":33,
    "gn:timezone":"Europe/Bucharest",
    "iso:country":"RO",
    "name:und_x_variant":[
        "Misleanu",
        "Retezatu"
    ],
    "wof:name":"Retezatu",
    "wof:placetype":"locality",
    "wof:population":33
},
  "geometry": {"coordinates":[27.89507,44.44182],"type":"Point"}
}