{
  "type": "Feature",
  "properties": {
    "gn:admin1_code":"02",
    "gn:admin2_code":"10453.0",
    "gn:asciiname":"Milova",
    "gn:country_code":"RO",
    "gn:dem":148,
    "gn:feature_class":"P",
    "gn:feature_code":"PPL",
    "gn:name":"Milova",
    "gn:population":560,
    "gn:timezone":"Europe/Bucharest",
    "iso:country":"RO",
    "wof:name":"Milova",
    "wof:placetype":"locality",
    "wof:population":560
},
  "geometry": {"coordinates":[21.80199,46.10594],"type":"Point"}
}