{
  "type": "Feature",
  "properties": {
    "gn:admin1_code":"26",
    "gn:admin2_code":"112995.0",
    "gn:asciiname":"Raiculesti",
    "gn:cc2":"RO",
    "gn:country_code":"RO",
    "gn:dem":575,
    "gn:feature_class":"P",
    "gn:feature_code":"PPL",
    "gn:name":"R\u0103icule\u0219ti",
    "gn:population":117,
    "gn:timezone":"Europe/Bucharest",
    "iso:country":"RO",
    "name:und_x_variant":[
        "Rajkule\u0161ti",
        "R\u0103icule\u015fti"
    ],
    "wof:name":"Raiculesti",
    "wof:placetype":"locality",
    "wof:population":117
},
  "geometry": {"coordinates":[22.77624,44.96836],"type":"Point"}
}