{
  "type": "Feature",
  "properties": {
    "gn:admin1_code":"27",
    "gn:admin2_code":"116171.0",
    "gn:asciiname":"Odrihei",
    "gn:cc2":"RO",
    "gn:country_code":"RO",
    "gn:dem":319,
    "gn:feature_class":"P",
    "gn:feature_code":"PPL",
    "gn:name":"Odrihei",
    "gn:population":514,
    "gn:timezone":"Europe/Bucharest",
    "iso:country":"RO",
    "name:und_x_variant":[
        "Odorheiu",
        "Odriheiu",
        "Odriheiul",
        "Odrihei"
    ],
    "wof:name":"Odrihei",
    "wof:placetype":"locality",
    "wof:population":514
},
  "geometry": {"coordinates":[24.56771,46.40459],"type":"Point"}
}