{
  "type": "Feature",
  "properties": {
    "gn:admin1_code":"12",
    "gn:admin2_code":"53577",
    "gn:asciiname":"Semenic",
    "gn:country_code":"RO",
    "gn:dem":1395,
    "gn:feature_class":"P",
    "gn:feature_code":"PPL",
    "gn:name":"Semenic",
    "gn:population":0,
    "gn:timezone":"Europe/Bucharest",
    "iso:country":"RO",
    "name:deu_x_preferred":[
        "Semenic-Gebirge"
    ],
    "name:hun_x_preferred":[
        "Szemenik-hegys\u00e9g"
    ],
    "name:ron_x_preferred":[
        "Mun\u021bii Semenic"
    ],
    "name:rus_x_preferred":[
        "\u0421\u0435\u043c\u0435\u043d\u0438\u0447"
    ],
    "wof:lang_x_official":[
        "ron"
    ],
    "wof:lang_x_spoken":[
        "ron"
    ],
    "wof:name":"Semenic",
    "wof:placetype":"locality"
},
  "geometry": {"coordinates":[22.0578,45.1778],"type":"Point"}
}