{
  "type": "Feature",
  "properties": {
    "gn:admin1_code":"03",
    "gn:admin2_code":"19793.0",
    "gn:asciiname":"Chitani",
    "gn:country_code":"RO",
    "gn:dem":275,
    "gn:feature_class":"P",
    "gn:feature_code":"PPL",
    "gn:name":"Chi\u021bani",
    "gn:population":357,
    "gn:timezone":"Europe/Bucharest",
    "iso:country":"RO",
    "wof:name":"Chitani",
    "wof:placetype":"locality",
    "wof:population":357
},
  "geometry": {"coordinates":[24.64609,44.74652],"type":"Point"}
}