{
  "type": "Feature",
  "properties": {
    "gn:admin1_code":"14",
    "gn:admin2_code":"62486.0",
    "gn:asciiname":"Strunga",
    "gn:cc2":"RO",
    "gn:country_code":"RO",
    "gn:dem":51,
    "gn:feature_class":"P",
    "gn:feature_code":"PPL",
    "gn:name":"Strunga",
    "gn:population":18,
    "gn:timezone":"Europe/Bucharest",
    "iso:country":"RO",
    "name:und_x_variant":[
        "C\u00ee\u015fla",
        "Strunga"
    ],
    "wof:name":"Strunga",
    "wof:placetype":"locality",
    "wof:population":18
},
  "geometry": {"coordinates":[27.64111,44.12366],"type":"Point"}
}