{
  "type": "Feature",
  "properties": {
    "gn:admin1_code":"14",
    "gn:admin2_code":"62486.0",
    "gn:asciiname":"Strunga",
    "gn:cc2":"RO",
    "gn:country_code":"RO",
    "gn:dem":51,
    "gn:feature_class":"P",
    "gn:feature_code":"PPL",
    "gn:name":"Strunga",
    "gn:population":18,
    "gn:timezone":"Europe/Bucharest",
    "iso:country":"RO",
    "name:ara_x_preferred":[
        "\u0633\u062a\u0631\u0648\u0646\u063a\u0627"
    ],
    "name:ceb_x_preferred":[
        "Comuna Strunga"
    ],
    "name:ita_x_preferred":[
        "Strunga"
    ],
    "name:msa_x_preferred":[
        "Strunga"
    ],
    "name:nld_x_preferred":[
        "Strunga"
    ],
    "name:por_x_preferred":[
        "Strunga"
    ],
    "name:ron_x_preferred":[
        "Comuna Strunga"
    ],
    "name:srp_x_preferred":[
        "\u041e\u043f\u0448\u0442\u0438\u043d\u0430 \u0421\u0442\u0440\u0443\u043d\u0433\u0430"
    ],
    "name:ukr_x_preferred":[
        "\u0421\u0442\u0440\u0443\u043d\u0433\u0430"
    ],
    "name:und_x_variant":[
        "C\u00ee\u015fla",
        "Strunga"
    ],
    "name:vie_x_preferred":[
        "Strunga"
    ],
    "name:vol_x_preferred":[
        "Strunga"
    ],
    "name:zho_x_preferred":[
        "\u65af\u7279\u502b\u52a0\u9109"
    ],
    "wof:name":"Strunga",
    "wof:placetype":"locality",
    "wof:population":18
},
  "geometry": {"coordinates":[27.64111,44.12366],"type":"Point"}
}