{
  "type": "Feature",
  "properties": {
    "gn:admin1_code":"18",
    "gn:admin2_code":"75613.0",
    "gn:asciiname":"Ciuresti",
    "gn:country_code":"RO",
    "gn:dem":145,
    "gn:feature_class":"P",
    "gn:feature_code":"PPL",
    "gn:name":"Ciure\u0219ti",
    "gn:population":508,
    "gn:timezone":"Europe/Bucharest",
    "iso:country":"RO",
    "wof:name":"Ciuresti",
    "wof:placetype":"locality",
    "wof:population":508
},
  "geometry": {"coordinates":[27.63564,46.07856],"type":"Point"}
}