{
  "type": "Feature",
  "properties": {
    "gn:admin1_code":"40",
    "gn:admin2_code":"175983.0",
    "gn:asciiname":"Poienita",
    "gn:country_code":"RO",
    "gn:dem":366,
    "gn:feature_class":"P",
    "gn:feature_code":"PPL",
    "gn:name":"Poieni\u021ba",
    "gn:population":237,
    "gn:timezone":"Europe/Bucharest",
    "iso:country":"RO",
    "wof:name":"Poienita",
    "wof:placetype":"locality",
    "wof:population":237
},
  "geometry": {"coordinates":[26.91392,45.58498],"type":"Point"}
}