{
  "type": "Feature",
  "properties": {
    "gn:gn_country":"RO",
    "gn:gn_fcode":"PPLA2",
    "gn:gn_pop":1844,
    "gn:population":1844,
    "iso:country":"RO",
    "name:dan_x_preferred":[
        "Bl\u0103ge\u0219ti"
    ],
    "name:dut_x_preferred":[
        "Bl\u0103ge\u0219ti"
    ],
    "name:eng_x_preferred":[
        "Bl\u0103ge\u0219ti"
    ],
    "name:fao_x_preferred":[
        "Bl\u0103ge\u0219ti"
    ],
    "name:fre_x_preferred":[
        "Bl\u0103ge\u0219ti"
    ],
    "name:ger_x_preferred":[
        "Bl\u0103ge\u0219ti"
    ],
    "name:ice_x_preferred":[
        "Bl\u0103ge\u0219ti"
    ],
    "name:ita_x_preferred":[
        "Bl\u0103ge\u0219ti"
    ],
    "name:kal_x_preferred":[
        "Bl\u0103ge\u0219ti"
    ],
    "name:may_x_preferred":[
        "Bl\u0103ge\u0219ti"
    ],
    "name:nno_x_preferred":[
        "Bl\u0103ge\u0219ti"
    ],
    "name:nob_x_preferred":[
        "Bl\u0103ge\u0219ti"
    ],
    "name:por_x_preferred":[
        "Bl\u0103ge\u0219ti"
    ],
    "name:rum_x_preferred":[
        "Bl\u0103ge\u0219ti"
    ],
    "name:swe_x_preferred":[
        "Bl\u0103ge\u0219ti"
    ],
    "name:ukr_x_preferred":[
        "\u0411\u043b\u0435\u0434\u0436\u0435\u0448\u0442\u044c"
    ],
    "qs_pg:aaroncc":"RO",
    "qs_pg:gn_country":"RO",
    "qs_pg:gn_fcode":"PPLA2",
    "qs_pg:gn_pop":1844,
    "qs_pg:name":"Bl\u0103ge\u015fti",
    "qs_pg:photos_9r":0,
    "qs_pg:photos_sr":0,
    "qs_pg:pop_sr":3,
    "qs_pg:qs_pg_placetype":"locality",
    "wof:name":"Bl\u0103ge\u015fti",
    "wof:placetype":"locality",
    "wof:population":1844
},
  "geometry": {"coordinates":[28.01306,46.13722],"type":"Point"}
}