{
  "type": "Feature",
  "properties": {
    "gn:admin1_code":"34",
    "gn:admin2_code":"151246.0",
    "gn:asciiname":"Nicani",
    "gn:country_code":"RO",
    "gn:dem":299,
    "gn:feature_class":"P",
    "gn:feature_code":"PPL",
    "gn:name":"Nicani",
    "gn:population":538,
    "gn:timezone":"Europe/Bucharest",
    "iso:country":"RO",
    "wof:name":"Nicani",
    "wof:placetype":"locality",
    "wof:population":538
},
  "geometry": {"coordinates":[26.22755,47.86844],"type":"Point"}
}