{
  "type": "Feature",
  "properties": {
    "gn:admin1_code":"37",
    "gn:admin2_code":"160680.0",
    "gn:asciiname":"Cetatuia",
    "gn:country_code":"RO",
    "gn:dem":27,
    "gn:feature_class":"P",
    "gn:feature_code":"PPL",
    "gn:name":"Cet\u0103\u0163uia",
    "gn:population":0,
    "gn:timezone":"Europe/Bucharest",
    "iso:country":"RO",
    "wof:name":"Cetatuia",
    "wof:placetype":"locality"
},
  "geometry": {"coordinates":[28.26667,45.28333],"type":"Point"}
}