{
  "type": "Feature",
  "properties": {
    "gn:admin1_code":"20",
    "gn:admin2_code":"86133.0",
    "gn:asciiname":"Poiana Veche",
    "gn:country_code":"RO",
    "gn:dem":920,
    "gn:feature_class":"P",
    "gn:feature_code":"PPL",
    "gn:name":"Poiana Veche",
    "gn:population":0,
    "gn:timezone":"Europe/Bucharest",
    "iso:country":"RO",
    "name:und_x_variant":[
        "O-Pojana",
        "Poiana Veche"
    ],
    "wof:lang_x_official":[
        "ron"
    ],
    "wof:lang_x_spoken":[
        "ron"
    ],
    "wof:name":"Poiana Veche",
    "wof:placetype":"locality"
},
  "geometry": {"coordinates":[25.76667,46.95],"type":"Point"}
}