{
  "type": "Feature",
  "properties": {
    "gn:admin1_code":"19",
    "gn:admin2_code":"79237.0",
    "gn:asciiname":"Satu Nou",
    "gn:country_code":"RO",
    "gn:dem":110,
    "gn:feature_class":"P",
    "gn:feature_code":"PPL",
    "gn:name":"Satu Nou",
    "gn:population":0,
    "gn:timezone":"Europe/Bucharest",
    "iso:country":"RO",
    "name:ceb_x_preferred":[
        "Satu Nou"
    ],
    "name:deu_x_preferred":[
        "Satu Nou"
    ],
    "name:epo_x_preferred":[
        "Satu Nou"
    ],
    "name:hun_x_preferred":[
        "Satu Nou"
    ],
    "name:ron_x_preferred":[
        "Satu Nou"
    ],
    "name:srp_x_preferred":[
        "\u041d\u043e\u0432\u043e \u0441\u0435\u043b\u043e"
    ],
    "name:ukr_x_preferred":[
        "\u0421\u0430\u0442\u0443-\u041d\u043e\u0443"
    ],
    "name:und_x_variant":[
        "Satul Nou"
    ],
    "wof:lang_x_official":[
        "ron"
    ],
    "wof:lang_x_spoken":[
        "ron"
    ],
    "wof:name":"Satu Nou",
    "wof:placetype":"locality"
},
  "geometry": {"coordinates":[23.46667,44.61667],"type":"Point"}
}