{
  "type": "Feature",
  "properties": {
    "gn:admin1_code":"26",
    "gn:admin2_code":"112995.0",
    "gn:asciiname":"Ludu",
    "gn:country_code":"RO",
    "gn:dem":562,
    "gn:feature_class":"P",
    "gn:feature_code":"PPL",
    "gn:name":"Ludu",
    "gn:population":118,
    "gn:timezone":"Europe/Bucharest",
    "iso:country":"RO",
    "wof:name":"Ludu",
    "wof:placetype":"locality",
    "wof:population":118
},
  "geometry": {"coordinates":[22.80709,44.95956],"type":"Point"}
}