{
  "type": "Feature",
  "properties": {
    "gn:admin1_code":"29",
    "gn:admin2_code":"125999",
    "gn:asciiname":"Brebeni-Romani",
    "gn:cc2":"RO",
    "gn:country_code":"RO",
    "gn:dem":131,
    "gn:feature_class":"P",
    "gn:feature_code":"PPL",
    "gn:name":"Brebeni-Rom\u00e2ni",
    "gn:population":0,
    "gn:timezone":"Europe/Bucharest",
    "iso:country":"RO",
    "name:und_x_variant":[
        "Brebenii-Rom\u00e2ni",
        "Brebeni-Rom\u00eeni"
    ],
    "wof:name":"Brebeni-Romani",
    "wof:placetype":"locality"
},
  "geometry": {"coordinates":[24.45,44.38333],"type":"Point"}
}