{
  "type": "Feature",
  "properties": {
    "gn:admin1_code":"29",
    "gn:admin2_code":"127386.0",
    "gn:asciiname":"Zidari",
    "gn:country_code":"RO",
    "gn:dem":104,
    "gn:feature_class":"P",
    "gn:feature_code":"PPL",
    "gn:name":"Zidari",
    "gn:population":0,
    "gn:timezone":"Europe/Bucharest",
    "iso:country":"RO",
    "wof:lang_x_official":[
        "ron"
    ],
    "wof:lang_x_spoken":[
        "ron"
    ],
    "wof:name":"Zidari",
    "wof:placetype":"locality"
},
  "geometry": {"coordinates":[24.53333,44.26667],"type":"Point"}
}