{
  "type": "Feature",
  "properties": {
    "gn:population":1499,
    "iso:country":"RO",
    "name:ceb_x_preferred":[
        "Co\u021bofenii din Fa\u021b\u0103"
    ],
    "name:eng_x_preferred":[
        "Co\u021bofenii din Fa\u021b\u0103"
    ],
    "name:fra_x_preferred":[
        "Co\u021bofenii din Fa\u021b\u0103"
    ],
    "name:ita_x_preferred":[
        "Co\u021bofenii din Fa\u021b\u0103"
    ],
    "name:nld_x_preferred":[
        "Co\u021bofenii din Fa\u021b\u0103"
    ],
    "name:por_x_preferred":[
        "Co\u021bofenii din Fa\u021b\u0103"
    ],
    "name:ron_x_preferred":[
        "Co\u021bofenii din Fa\u021b\u0103"
    ],
    "name:srp_x_preferred":[
        "\u041a\u043e\u0446\u043e\u0444\u0435\u043d\u0438\u0458 \u0434\u0438\u043d \u0424\u0430\u0446\u0430"
    ],
    "name:ukr_x_preferred":[
        "\u041a\u043e\u0446\u043e\u0444\u0435\u043d\u0456\u0439-\u0434\u0456\u043d-\u0424\u0430\u0446\u0435"
    ],
    "name:vol_x_preferred":[
        "Co\u021bofenii din Fa\u021b\u0103"
    ],
    "qs:a0":"Rom\u00e2nia",
    "qs:a1":"*Dolj",
    "qs:a1r":"0",
    "qs:adm0":"Rom\u00e2nia",
    "qs:la_lc":"*",
    "qs:level":"locality",
    "qs:loc":"Co\u0163ofenii din Fa\u0163\u0103",
    "qs:loc_alt":"Cotofenii din Fata",
    "qs:pop":0,
    "qs:type":"buffered point",
    "wof:name":"Co\u0163ofenii din Fa\u0163\u0103",
    "wof:placetype":"locality",
    "wof:population":1499
},
  "geometry": {"coordinates":[23.665291,44.460739],"type":"Point"}
}