{
  "type": "Feature",
  "properties": {
    "gn:gn_country":"RO",
    "gn:gn_fcode":"PPL",
    "gn:gn_pop":1542,
    "gn:population":1542,
    "iso:country":"RO",
    "name:dut_x_preferred":[
        "Fildu de Jos"
    ],
    "name:eng_x_preferred":[
        "Fildu de Jos"
    ],
    "name:epo_x_preferred":[
        "Fildu de Jos"
    ],
    "name:fre_x_preferred":[
        "Fildu de Jos"
    ],
    "name:hun_x_preferred":[
        "Als\u00f3f\u00fcld"
    ],
    "name:ita_x_preferred":[
        "Fildu de Jos"
    ],
    "name:may_x_preferred":[
        "Fildu de Jos"
    ],
    "name:por_x_preferred":[
        "Fildu de Jos"
    ],
    "name:rum_x_preferred":[
        "Fildu de Jos"
    ],
    "name:ukr_x_preferred":[
        "\u0424\u0456\u043b\u0434\u0443-\u0434\u0435-\u0416\u043e\u0441"
    ],
    "name:unk_x_variant":[
        "Fildul-de-Jos"
    ],
    "name:vie_x_preferred":[
        "Fildu de Jos"
    ],
    "name:vol_x_preferred":[
        "Fildu de Jos"
    ],
    "qs_pg:aaroncc":"RO",
    "qs_pg:gn_country":"RO",
    "qs_pg:gn_fcode":"PPL",
    "qs_pg:gn_pop":1542,
    "qs_pg:name":"Fildu de Jos",
    "qs_pg:photos_9r":0,
    "qs_pg:photos_sr":0,
    "qs_pg:pop_sr":3,
    "qs_pg:qs_pg_placetype":"locality",
    "wof:name":"Fildu de Jos",
    "wof:placetype":"locality",
    "wof:population":1542
},
  "geometry": {"coordinates":[23.06667,46.93333],"type":"Point"}
}