{
  "type": "Feature",
  "properties": {
    "gn:admin1_code":"20",
    "gn:admin2_code":"83785.0",
    "gn:asciiname":"Cozbertaia",
    "gn:country_code":"RO",
    "gn:dem":637,
    "gn:feature_class":"P",
    "gn:feature_code":"PPL",
    "gn:name":"Cozber\u0163aia",
    "gn:population":0,
    "gn:timezone":"Europe/Bucharest",
    "iso:country":"RO",
    "name:und_x_variant":[
        "K\u00f6zb\u00e8rcalja",
        "Cozler\u0163aia",
        "Cozber\u0163aia"
    ],
    "wof:lang_x_official":[
        "ron"
    ],
    "wof:lang_x_spoken":[
        "ron"
    ],
    "wof:name":"Cozbertaia",
    "wof:placetype":"locality"
},
  "geometry": {"coordinates":[25.03333,46.51667],"type":"Point"}
}