{
  "type": "Feature",
  "properties": {
    "gn:admin1_code":"12",
    "gn:admin2_code":"52785.0",
    "gn:asciiname":"Dezesti",
    "gn:cc2":"RO",
    "gn:country_code":"RO",
    "gn:dem":180,
    "gn:feature_class":"P",
    "gn:feature_code":"PPL",
    "gn:name":"Deze\u0219ti",
    "gn:population":223,
    "gn:timezone":"Europe/Bucharest",
    "iso:country":"RO",
    "name:und_x_variant":[
        "Dezestye",
        "Dezest",
        "Dezesd",
        "Dezesty",
        "Deze\u015fti"
    ],
    "wof:name":"Dezesti",
    "wof:placetype":"locality",
    "wof:population":223
},
  "geometry": {"coordinates":[21.89078,45.4695],"type":"Point"}
}