{
  "type": "Feature",
  "properties": {
    "gn:admin1_code":"12",
    "gn:admin2_code":"54056.0",
    "gn:asciiname":"Ilova",
    "gn:country_code":"RO",
    "gn:dem":425,
    "gn:feature_class":"P",
    "gn:feature_code":"PPL",
    "gn:name":"Ilova",
    "gn:population":972,
    "gn:timezone":"Europe/Bucharest",
    "iso:country":"RO",
    "name:bos_x_preferred":[
        "Ilova"
    ],
    "name:ceb_x_preferred":[
        "Ilova"
    ],
    "name:hun_x_preferred":[
        "Ilova"
    ],
    "name:swe_x_preferred":[
        "Ilova"
    ],
    "wof:name":"Ilova",
    "wof:placetype":"locality",
    "wof:population":972
},
  "geometry": {"coordinates":[22.34151,45.27771],"type":"Point"}
}