{
  "type": "Feature",
  "properties": {
    "gn:admin1_code":"07",
    "gn:admin2_code":"37217.0",
    "gn:asciiname":"Cucuteni-Razesi",
    "gn:country_code":"RO",
    "gn:dem":171,
    "gn:feature_class":"P",
    "gn:feature_code":"PPL",
    "gn:name":"Cucuteni-R\u0103ze\u015fi",
    "gn:population":0,
    "gn:timezone":"Europe/Bucharest",
    "iso:country":"RO",
    "name:und_x_variant":[
        "Cucueni-R\u0103ze\u015fti",
        "Cucuteni-R\u0103ze\u015fi"
    ],
    "wof:name":"Cucuteni-Razesi",
    "wof:placetype":"locality"
},
  "geometry": {"coordinates":[27.11667000000001,47.76667],"type":"Point"}
}