{
  "type": "Feature",
  "properties": {
    "gn:admin1_code":"36",
    "gn:admin2_code":"157781.0",
    "gn:asciiname":"Gaiu Mic",
    "gn:cc2":"RO",
    "gn:country_code":"RO",
    "gn:dem":85,
    "gn:feature_class":"P",
    "gn:feature_code":"PPL",
    "gn:name":"Gaiu Mic",
    "gn:population":208,
    "gn:timezone":"Europe/Bucharest",
    "iso:country":"RO",
    "name:und_x_variant":[
        "Kleingaj",
        "Gajul Mik",
        "Mali-Gaj",
        "Gaiul-Mic",
        "Kisg\u00e1j",
        "Gaiu Mic"
    ],
    "wof:name":"Gaiu Mic",
    "wof:placetype":"locality",
    "wof:population":208
},
  "geometry": {"coordinates":[21.20916,45.29633],"type":"Point"}
}