{
  "type": "Feature",
  "properties": {
    "gn:admin1_code":"18",
    "gn:admin2_code":"76175.0",
    "gn:asciiname":"Ghinghesti",
    "gn:country_code":"RO",
    "gn:dem":186,
    "gn:feature_class":"P",
    "gn:feature_code":"PPL",
    "gn:name":"Ghinghe\u0219ti",
    "gn:population":316,
    "gn:timezone":"Europe/Bucharest",
    "iso:country":"RO",
    "wof:name":"Ghinghesti",
    "wof:placetype":"locality",
    "wof:population":316
},
  "geometry": {"coordinates":[27.76588,46.01349],"type":"Point"}
}