{
  "type": "Feature",
  "properties": {
    "gn:admin1_code":"22",
    "gn:admin2_code":"93600",
    "gn:asciiname":"Gheorghe Doja",
    "gn:country_code":"RO",
    "gn:dem":37,
    "gn:feature_class":"P",
    "gn:feature_code":"PPLA2",
    "gn:name":"Gheorghe Doja",
    "gn:population":2555,
    "gn:timezone":"Europe/Bucharest",
    "iso:country":"RO",
    "name:und_x_variant":[
        "Valea lui \u0218iman",
        "Principesa Elena"
    ],
    "wof:name":"Gheorghe Doja",
    "wof:placetype":"locality",
    "wof:population":2555
},
  "geometry": {"coordinates":[27.1874,44.61622],"type":"Point"}
}