{
  "type": "Feature",
  "properties": {
    "gn:admin1_code":"02",
    "gn:admin2_code":"10701.0",
    "gn:asciiname":"Crocna",
    "gn:country_code":"RO",
    "gn:dem":212,
    "gn:feature_class":"P",
    "gn:feature_code":"PPL",
    "gn:name":"Crocna",
    "gn:population":555,
    "gn:timezone":"Europe/Bucharest",
    "iso:country":"RO",
    "name:ron_x_preferred":[
        "Crocna"
    ],
    "name:und_x_variant":[
        "Als\u00f3 Koroknya",
        "Krogna",
        "Krokna",
        "Koroknya",
        "Fels\u0151-Koroknya"
    ],
    "wof:name":"Crocna",
    "wof:placetype":"locality",
    "wof:population":555
},
  "geometry": {"coordinates":[22.29517,46.32714],"type":"Point"}
}