{
  "type": "Feature",
  "properties": {
    "gn:admin1_code":"21",
    "gn:admin2_code":"91232",
    "gn:asciiname":"Balomir",
    "gn:country_code":"RO",
    "gn:dem":350,
    "gn:feature_class":"P",
    "gn:feature_code":"PPL",
    "gn:name":"Balomir",
    "gn:population":369,
    "gn:timezone":"Europe/Bucharest",
    "iso:country":"RO",
    "wof:name":"Balomir",
    "wof:placetype":"locality",
    "wof:population":369
},
  "geometry": {"coordinates":[22.99963,45.58516],"type":"Point"}
}