{
  "type": "Feature",
  "properties": {
    "gn:admin1_code":"17",
    "gn:admin2_code":"70986.0",
    "gn:asciiname":"Caraiman",
    "gn:country_code":"RO",
    "gn:dem":215,
    "gn:feature_class":"P",
    "gn:feature_code":"PPL",
    "gn:name":"Caraiman",
    "gn:population":0,
    "gn:timezone":"Europe/Bucharest",
    "iso:country":"RO",
    "name:ceb_x_preferred":[
        "Caraiman"
    ],
    "name:deu_x_preferred":[
        "Caraiman"
    ],
    "name:ron_x_preferred":[
        "Caraiman"
    ],
    "wof:name":"Caraiman",
    "wof:placetype":"locality"
},
  "geometry": {"coordinates":[23.38105,44.34737],"type":"Point"}
}