{
  "type": "Feature",
  "properties": {
    "gn:admin1_code":"28",
    "gn:admin2_code":"124938",
    "gn:asciiname":"Agarcia",
    "gn:cc2":"RO",
    "gn:country_code":"RO",
    "gn:dem":332,
    "gn:feature_class":"P",
    "gn:feature_code":"PPL",
    "gn:name":"Ag\u00e2rcia",
    "gn:population":251,
    "gn:timezone":"Europe/Bucharest",
    "iso:country":"RO",
    "name:und_x_variant":[
        "Ag\u00e2rcia",
        "Ag\u00eercia"
    ],
    "wof:name":"Agarcia",
    "wof:placetype":"locality",
    "wof:population":251
},
  "geometry": {"coordinates":[26.29523,46.92653],"type":"Point"}
}