{
  "type": "Feature",
  "properties": {
    "gn:admin1_code":"29",
    "gn:admin2_code":"126718.0",
    "gn:asciiname":"Frasinetu",
    "gn:cc2":"RO",
    "gn:country_code":"RO",
    "gn:dem":114,
    "gn:feature_class":"P",
    "gn:feature_code":"PPL",
    "gn:name":"Fr\u0103sinetu",
    "gn:population":491,
    "gn:timezone":"Europe/Bucharest",
    "iso:country":"RO",
    "name:und_x_variant":[
        "Fr\u0103sinetu P\u0103dure",
        "Fr\u0103sinet",
        "Fr\u0103sinetul",
        "Fr\u0103sinetu"
    ],
    "wof:name":"Frasinetu",
    "wof:placetype":"locality",
    "wof:population":491
},
  "geometry": {"coordinates":[24.32348,44.15704],"type":"Point"}
}