{
  "type": "Feature",
  "properties": {
    "gn:admin1_code":"21",
    "gn:admin2_code":"90805.0",
    "gn:asciiname":"Uibaresti",
    "gn:country_code":"RO",
    "gn:dem":334,
    "gn:feature_class":"P",
    "gn:feature_code":"PPL",
    "gn:name":"Uib\u0103re\u0219ti",
    "gn:population":140,
    "gn:timezone":"Europe/Bucharest",
    "iso:country":"RO",
    "wof:name":"Uibaresti",
    "wof:placetype":"locality",
    "wof:population":140
},
  "geometry": {"coordinates":[22.76298,46.20614000000001],"type":"Point"}
}