{
  "type": "Feature",
  "properties": {
    "gn:admin1_code":"41",
    "gn:admin2_code":"105455.0",
    "gn:asciiname":"Tamadau Mic",
    "gn:cc2":"RO",
    "gn:country_code":"RO",
    "gn:dem":39,
    "gn:feature_class":"P",
    "gn:feature_code":"PPL",
    "gn:name":"T\u0103m\u0103d\u0103u Mic",
    "gn:population":152,
    "gn:timezone":"Europe/Bucharest",
    "iso:country":"RO",
    "name:und_x_variant":[
        "T\u0103m\u0103d\u0103ul-Mic",
        "T\u0103m\u0103d\u0103u Mic"
    ],
    "wof:name":"Tamadau Mic",
    "wof:placetype":"locality",
    "wof:population":152
},
  "geometry": {"coordinates":[26.57065,44.45798],"type":"Point"}
}