{
  "type": "Feature",
  "properties": {
    "gn:admin1_code":"01",
    "gn:admin2_code":"2577.0",
    "gn:asciiname":"Soicesti",
    "gn:country_code":"RO",
    "gn:dem":855,
    "gn:feature_class":"P",
    "gn:feature_code":"PPL",
    "gn:name":"\u0218oice\u0219ti",
    "gn:population":50,
    "gn:timezone":"Europe/Bucharest",
    "iso:country":"RO",
    "wof:name":"Soicesti",
    "wof:placetype":"locality",
    "wof:population":50
},
  "geometry": {"coordinates":[22.82896,46.36332],"type":"Point"}
}