{
  "type": "Feature",
  "properties": {
    "gn:admin1_code":"11",
    "gn:admin2_code":"48557",
    "gn:asciiname":"Badila",
    "gn:cc2":"RO",
    "gn:country_code":"RO",
    "gn:dem":256,
    "gn:feature_class":"P",
    "gn:feature_code":"PPL",
    "gn:name":"Badila",
    "gn:population":767,
    "gn:timezone":"Europe/Bucharest",
    "iso:country":"RO",
    "name:und_x_variant":[
        "Od\u0103ile",
        "B\u0103dila"
    ],
    "wof:name":"Badila",
    "wof:placetype":"locality",
    "wof:population":767
},
  "geometry": {"coordinates":[26.51107,45.26639],"type":"Point"}
}