{
  "type": "Feature",
  "properties": {
    "gn:admin1_code":"01",
    "gn:admin2_code":"7446.0",
    "gn:asciiname":"Robesti",
    "gn:country_code":"RO",
    "gn:dem":786,
    "gn:feature_class":"P",
    "gn:feature_code":"PPL",
    "gn:name":"Robe\u0219ti",
    "gn:population":20,
    "gn:timezone":"Europe/Bucharest",
    "iso:country":"RO",
    "wof:name":"Robesti",
    "wof:placetype":"locality",
    "wof:population":20
},
  "geometry": {"coordinates":[22.9943,46.29671],"type":"Point"}
}