{
  "type": "Feature",
  "properties": {
    "gn:admin1_code":"11",
    "gn:admin2_code":"48487.0",
    "gn:asciiname":"Clondiru de Sus",
    "gn:country_code":"RO",
    "gn:dem":184,
    "gn:feature_class":"P",
    "gn:feature_code":"PPL",
    "gn:name":"Clondiru de Sus",
    "gn:population":255,
    "gn:timezone":"Europe/Bucharest",
    "iso:country":"RO",
    "wof:name":"Clondiru de Sus",
    "wof:placetype":"locality",
    "wof:population":255
},
  "geometry": {"coordinates":[26.59229,45.09808],"type":"Point"}
}