{
  "type": "Feature",
  "properties": {
    "gn:admin1_code":"21",
    "gn:admin2_code":"91116.0",
    "gn:asciiname":"Rau Alb",
    "gn:cc2":"RO",
    "gn:country_code":"RO",
    "gn:dem":410,
    "gn:feature_class":"P",
    "gn:feature_code":"PPL",
    "gn:name":"R\u00e2u Alb",
    "gn:population":222,
    "gn:timezone":"Europe/Bucharest",
    "iso:country":"RO",
    "name:und_x_variant":[
        "R\u00e2ul-Alb",
        "R\u00e2u-Alb",
        "R\u00eeu Alb"
    ],
    "wof:name":"Rau Alb",
    "wof:placetype":"locality",
    "wof:population":222
},
  "geometry": {"coordinates":[23.00587,45.52118],"type":"Point"}
}