{
  "type": "Feature",
  "properties": {
    "gn:admin1_code":"01",
    "gn:admin2_code":"4525.0",
    "gn:asciiname":"Huzaresti",
    "gn:cc2":"RO",
    "gn:country_code":"RO",
    "gn:dem":955,
    "gn:feature_class":"P",
    "gn:feature_code":"PPL",
    "gn:name":"Huz\u0103re\u0219ti",
    "gn:population":111,
    "gn:timezone":"Europe/Bucharest",
    "iso:country":"RO",
    "name:und_x_variant":[
        "Husare\u015fti",
        "Huz\u0103re\u015fti"
    ],
    "wof:name":"Huzaresti",
    "wof:placetype":"locality",
    "wof:population":111
},
  "geometry": {"coordinates":[22.84478,46.44518],"type":"Point"}
}