{
  "type": "Feature",
  "properties": {
    "gn:admin1_code":"15",
    "gn:admin2_code":"64130.0",
    "gn:asciiname":"Hatuica",
    "gn:cc2":"RO",
    "gn:country_code":"RO",
    "gn:dem":542,
    "gn:feature_class":"P",
    "gn:feature_code":"PPL",
    "gn:name":"H\u0103tuica",
    "gn:population":415,
    "gn:timezone":"Europe/Bucharest",
    "iso:country":"RO",
    "name:und_x_variant":[
        "Hatolyka",
        "Hatojka",
        "H\u0103tuica"
    ],
    "wof:name":"Hatuica",
    "wof:placetype":"locality",
    "wof:population":415
},
  "geometry": {"coordinates":[26.1277,45.93995],"type":"Point"}
}