{
  "type": "Feature",
  "properties": {
    "gn:admin1_code":"01",
    "gn:admin2_code":"2915.0",
    "gn:asciiname":"Muncelu",
    "gn:cc2":"RO",
    "gn:country_code":"RO",
    "gn:dem":519,
    "gn:feature_class":"P",
    "gn:feature_code":"PPL",
    "gn:name":"Muncelu",
    "gn:population":421,
    "gn:timezone":"Europe/Bucharest",
    "iso:country":"RO",
    "name:und_x_variant":[
        "Muncel"
    ],
    "wof:name":"Muncelu",
    "wof:placetype":"locality",
    "wof:population":421
},
  "geometry": {"coordinates":[23.25663,46.37485],"type":"Point"}
}