{
  "type": "Feature",
  "properties": {
    "gn:admin1_code":"07",
    "gn:admin2_code":"37057.0",
    "gn:asciiname":"Hulub",
    "gn:country_code":"RO",
    "gn:dem":120,
    "gn:feature_class":"P",
    "gn:feature_code":"PPL",
    "gn:name":"Hulub",
    "gn:population":662,
    "gn:timezone":"Europe/Bucharest",
    "iso:country":"RO",
    "wof:name":"Hulub",
    "wof:placetype":"locality",
    "wof:population":662
},
  "geometry": {"coordinates":[26.96488,47.8258],"type":"Point"}
}