{
  "type": "Feature",
  "properties": {
    "gn:admin1_code":"16",
    "gn:admin2_code":"67773.0",
    "gn:asciiname":"Ciurari",
    "gn:country_code":"RO",
    "gn:dem":253,
    "gn:feature_class":"P",
    "gn:feature_code":"PPL",
    "gn:name":"Ciurari",
    "gn:population":0,
    "gn:timezone":"Europe/Bucharest",
    "iso:country":"RO",
    "wof:name":"Ciurari",
    "wof:placetype":"locality"
},
  "geometry": {"coordinates":[25.43333,44.85],"type":"Point"}
}