{
  "type": "Feature",
  "properties": {
    "gn:admin1_code":"21",
    "gn:admin2_code":"88868.0",
    "gn:asciiname":"Sesuri",
    "gn:country_code":"RO",
    "gn:dem":549,
    "gn:feature_class":"P",
    "gn:feature_code":"PPL",
    "gn:name":"\u0218esuri",
    "gn:population":532,
    "gn:timezone":"Europe/Bucharest",
    "iso:country":"RO",
    "wof:name":"Sesuri",
    "wof:placetype":"locality",
    "wof:population":532
},
  "geometry": {"coordinates":[22.92606,46.09681],"type":"Point"}
}