{
  "type": "Feature",
  "properties": {
    "gn:admin1_code":"08",
    "gn:admin2_code":"43732",
    "gn:asciiname":"Avantu",
    "gn:cc2":"RO",
    "gn:country_code":"RO",
    "gn:dem":23,
    "gn:feature_class":"P",
    "gn:feature_code":"PPL",
    "gn:name":"Av\u00e2ntu",
    "gn:population":0,
    "gn:timezone":"Europe/Bucharest",
    "iso:country":"RO",
    "name:und_x_variant":[
        "Av\u00e2ntul",
        "Av\u00eentu"
    ],
    "wof:name":"Avantu",
    "wof:placetype":"locality"
},
  "geometry": {"coordinates":[27.55,45.28333],"type":"Point"}
}