{
  "type": "Feature",
  "properties": {
    "gn:admin1_code":"05",
    "gn:admin2_code":"28335.0",
    "gn:asciiname":"Ceisoara",
    "gn:country_code":"RO",
    "gn:dem":169,
    "gn:feature_class":"P",
    "gn:feature_code":"PPL",
    "gn:name":"Cei\u0219oara",
    "gn:population":763,
    "gn:timezone":"Europe/Bucharest",
    "iso:country":"RO",
    "wof:name":"Ceisoara",
    "wof:placetype":"locality",
    "wof:population":763
},
  "geometry": {"coordinates":[22.20265,46.85672],"type":"Point"}
}