{
  "type": "Feature",
  "properties": {
    "gn:admin1_code":"19",
    "gn:admin2_code":"79834.0",
    "gn:asciiname":"Dumbraveni",
    "gn:cc2":"RO",
    "gn:country_code":"RO",
    "gn:dem":406,
    "gn:feature_class":"P",
    "gn:feature_code":"PPL",
    "gn:name":"Dumbr\u0103veni",
    "gn:population":668,
    "gn:timezone":"Europe/Bucharest",
    "iso:country":"RO",
    "name:und_x_variant":[
        "Turba\u0163i",
        "Dumbr\u0103veni"
    ],
    "wof:name":"Dumbraveni",
    "wof:placetype":"locality",
    "wof:population":668
},
  "geometry": {"coordinates":[23.5136,45.14956],"type":"Point"}
}