{
  "type": "Feature",
  "properties": {
    "gn:admin1_code":"27",
    "gn:admin2_code":"119858.0",
    "gn:asciiname":"Moara de Jos",
    "gn:country_code":"RO",
    "gn:dem":290,
    "gn:feature_class":"P",
    "gn:feature_code":"PPL",
    "gn:name":"Moara de Jos",
    "gn:population":83,
    "gn:timezone":"Europe/Bucharest",
    "iso:country":"RO",
    "wof:name":"Moara de Jos",
    "wof:placetype":"locality",
    "wof:population":83
},
  "geometry": {"coordinates":[24.09194,46.5645],"type":"Point"}
}