{
  "type": "Feature",
  "properties": {
    "gn:admin1_code":"21",
    "gn:admin2_code":"88788.0",
    "gn:asciiname":"Tarnita",
    "gn:country_code":"RO",
    "gn:dem":516,
    "gn:feature_class":"P",
    "gn:feature_code":"PPL",
    "gn:name":"Tarni\u021ba",
    "gn:population":481,
    "gn:timezone":"Europe/Bucharest",
    "iso:country":"RO",
    "wof:name":"Tarnita",
    "wof:placetype":"locality",
    "wof:population":481
},
  "geometry": {"coordinates":[23.05471,46.17808],"type":"Point"}
}