{
  "type": "Feature",
  "properties": {
    "gn:admin1_code":"27",
    "gn:admin2_code":"118370.0",
    "gn:asciiname":"Groapa Radaii",
    "gn:country_code":"RO",
    "gn:dem":343,
    "gn:feature_class":"P",
    "gn:feature_code":"PPL",
    "gn:name":"Groapa R\u0103d\u0103ii",
    "gn:population":58,
    "gn:timezone":"Europe/Bucharest",
    "iso:country":"RO",
    "wof:name":"Groapa Radaii",
    "wof:placetype":"locality",
    "wof:population":58
},
  "geometry": {"coordinates":[24.23434,46.65809],"type":"Point"}
}