{
  "type": "Feature",
  "properties": {
    "gn:admin1_code":"21",
    "gn:admin2_code":"89428.0",
    "gn:asciiname":"Panc",
    "gn:country_code":"RO",
    "gn:dem":311,
    "gn:feature_class":"P",
    "gn:feature_code":"PPL",
    "gn:name":"Panc",
    "gn:population":206,
    "gn:timezone":"Europe/Bucharest",
    "iso:country":"RO",
    "wof:name":"Panc",
    "wof:placetype":"locality",
    "wof:population":206
},
  "geometry": {"coordinates":[22.52409,45.85626],"type":"Point"}
}