{
  "type": "Feature",
  "properties": {
    "gn:admin1_code":"29",
    "gn:admin2_code":"125490.0",
    "gn:asciiname":"Liiceni",
    "gn:country_code":"RO",
    "gn:dem":125,
    "gn:feature_class":"P",
    "gn:feature_code":"PPL",
    "gn:name":"Liiceni",
    "gn:population":551,
    "gn:timezone":"Europe/Bucharest",
    "iso:country":"RO",
    "wof:name":"Liiceni",
    "wof:placetype":"locality",
    "wof:population":551
},
  "geometry": {"coordinates":[24.27617,44.12339],"type":"Point"}
}