{
  "type": "Feature",
  "properties": {
    "gn:admin1_code":"32",
    "gn:admin2_code":"138208.0",
    "gn:asciiname":"Ghirolt",
    "gn:country_code":"RO",
    "gn:dem":120,
    "gn:feature_class":"P",
    "gn:feature_code":"PPL",
    "gn:name":"Ghirolt",
    "gn:population":144,
    "gn:timezone":"Europe/Bucharest",
    "iso:country":"RO",
    "name:ceb_x_preferred":[
        "Ghirolt"
    ],
    "name:deu_x_preferred":[
        "Ghirolt"
    ],
    "name:epo_x_preferred":[
        "Ghirolt"
    ],
    "name:hun_x_preferred":[
        "Ghirolt"
    ],
    "name:ron_x_preferred":[
        "Ghirolt"
    ],
    "name:srp_x_preferred":[
        "\u0413\u0438\u0440\u043e\u043b\u0442"
    ],
    "wof:name":"Ghirolt",
    "wof:placetype":"locality",
    "wof:population":144
},
  "geometry": {"coordinates":[22.62334,47.60931],"type":"Point"}
}