{
  "type": "Feature",
  "properties": {
    "gn:admin1_code":"02",
    "gn:admin2_code":"10453.0",
    "gn:asciiname":"Chelmac",
    "gn:cc2":"RO",
    "gn:country_code":"RO",
    "gn:dem":136,
    "gn:feature_class":"P",
    "gn:feature_code":"PPL",
    "gn:name":"Chelmac",
    "gn:population":459,
    "gn:timezone":"Europe/Bucharest",
    "iso:country":"RO",
    "name:und_x_variant":[
        "Eperjes",
        "Kelm\u00e1k",
        "Maroseperjes",
        "Chelmac"
    ],
    "wof:name":"Chelmac",
    "wof:placetype":"locality",
    "wof:population":459
},
  "geometry": {"coordinates":[21.88463,46.0818],"type":"Point"}
}