{
  "type": "Feature",
  "properties": {
    "gn:admin1_code":"34",
    "gn:admin2_code":"148006.0",
    "gn:asciiname":"Vamei",
    "gn:country_code":"RO",
    "gn:dem":322,
    "gn:feature_class":"P",
    "gn:feature_code":"PPL",
    "gn:name":"V\u0103mei",
    "gn:population":0,
    "gn:timezone":"Europe/Bucharest",
    "iso:country":"RO",
    "name:und_x_variant":[
        "V\u0103meni",
        "V\u0103mei"
    ],
    "wof:lang_x_official":[
        "ron"
    ],
    "wof:lang_x_spoken":[
        "ron"
    ],
    "wof:name":"Vamei",
    "wof:placetype":"locality"
},
  "geometry": {"coordinates":[26.58333,47.43333],"type":"Point"}
}