{
  "type": "Feature",
  "properties": {
    "gn:country":"RO",
    "gn:fcode":"PPLA2",
    "gn:population":4665,
    "iso:country":"RO",
    "name:ceb_x_preferred":[
        "Horge\u0219ti"
    ],
    "name:eng_x_preferred":[
        "Horge\u0219ti"
    ],
    "name:fra_x_preferred":[
        "Horge\u0219ti"
    ],
    "name:hun_x_preferred":[
        "Horgyest"
    ],
    "name:nld_x_preferred":[
        "Horge\u0219ti"
    ],
    "name:ron_x_preferred":[
        "Horge\u0219ti"
    ],
    "name:srp_x_preferred":[
        "\u0425\u043e\u0440\u0452\u0435\u0448\u0442\u0438"
    ],
    "name:ukr_x_preferred":[
        "\u0425\u043e\u0440\u0434\u0436\u0435\u0448\u0442\u044c"
    ],
    "qs_pg:aaroncc":"RO",
    "qs_pg:gn_country":"RO",
    "qs_pg:gn_fcode":"PPLA2",
    "qs_pg:gn_pop":4665,
    "qs_pg:name":"Horge\u0219ti",
    "qs_pg:name_adm0":"Rom\u00e2nia",
    "qs_pg:name_adm1":"Bacau",
    "qs_pg:photos_9r":0,
    "qs_pg:photos_sr":0,
    "qs_pg:pop_sr":4,
    "qs_pg:qs_pg_placetype":"locality",
    "qs_pg:qs_pg_placetype_gp":"Town",
    "qs_pg:woe_adm0":23424933,
    "woe:adm0_id":23424933,
    "woe:name_adm0":"Rom\u00e2nia",
    "woe:name_adm1":"Bacau",
    "woe:placetype":"Town",
    "wof:name":"Horge\u0219ti",
    "wof:placetype":"locality",
    "wof:population":4665
},
  "geometry": {"coordinates":[27.06667,46.43333],"type":"Point"}
}