{
  "type": "Feature",
  "properties": {
    "gn:admin1_code":"29",
    "gn:admin2_code":"127224.0",
    "gn:asciiname":"Hotaru",
    "gn:cc2":"RO",
    "gn:country_code":"RO",
    "gn:dem":47,
    "gn:feature_class":"P",
    "gn:feature_code":"PPL",
    "gn:name":"Hotaru",
    "gn:population":836,
    "gn:timezone":"Europe/Bucharest",
    "iso:country":"RO",
    "name:deu_x_preferred":[
        "Hotaru"
    ],
    "name:ita_x_preferred":[
        "Hotaru"
    ],
    "name:jpn_x_preferred":[
        "\u30db\u30bf\u30eb"
    ],
    "name:kor_x_preferred":[
        "\ud638\ud0c0\ub8e8"
    ],
    "name:pol_x_preferred":[
        "Hotaru"
    ],
    "name:ron_x_preferred":[
        "Hotaru"
    ],
    "name:srp_x_preferred":[
        "\u0425\u043e\u0442\u0430\u0440\u0443"
    ],
    "name:und_x_variant":[
        "Hotarul",
        "Hotaru"
    ],
    "wof:name":"Hotaru",
    "wof:placetype":"locality",
    "wof:population":836
},
  "geometry": {"coordinates":[24.2514,43.75386],"type":"Point"}
}