{
  "type": "Feature",
  "properties": {
    "gn:admin1_code":"03",
    "gn:admin2_code":"15652.0",
    "gn:asciiname":"Rachitele de Sus",
    "gn:country_code":"RO",
    "gn:dem":455,
    "gn:feature_class":"P",
    "gn:feature_code":"PPL",
    "gn:name":"R\u0103chi\u021bele de Sus",
    "gn:population":539,
    "gn:timezone":"Europe/Bucharest",
    "iso:country":"RO",
    "wof:name":"Rachitele de Sus",
    "wof:placetype":"locality",
    "wof:population":539
},
  "geometry": {"coordinates":[24.65269,44.90574],"type":"Point"}
}