{
  "type": "Feature",
  "properties": {
    "gn:admin1_code":"42",
    "gn:admin2_code":"103309",
    "gn:asciiname":"Ardeleni",
    "gn:country_code":"RO",
    "gn:dem":70,
    "gn:feature_class":"P",
    "gn:feature_code":"PPL",
    "gn:name":"Ardeleni",
    "gn:population":0,
    "gn:timezone":"Europe/Bucharest",
    "iso:country":"RO",
    "name:por_x_preferred":[
        "Rio Ardeleni"
    ],
    "name:ron_x_preferred":[
        "R\u00e2ul Ardeleni"
    ],
    "wof:lang_x_official":[
        "ron"
    ],
    "wof:lang_x_spoken":[
        "ron"
    ],
    "wof:name":"Ardeleni",
    "wof:placetype":"locality"
},
  "geometry": {"coordinates":[25.65,43.83333],"type":"Point"}
}