{
  "type": "Feature",
  "properties": {
    "gn:admin1_code":"05",
    "gn:admin2_code":"32045.0",
    "gn:asciiname":"Reghea",
    "gn:country_code":"RO",
    "gn:dem":169,
    "gn:feature_class":"P",
    "gn:feature_code":"PPL",
    "gn:name":"Reghea",
    "gn:population":103,
    "gn:timezone":"Europe/Bucharest",
    "iso:country":"RO",
    "wof:name":"Reghea",
    "wof:placetype":"locality",
    "wof:population":103
},
  "geometry": {"coordinates":[22.48705,47.37628],"type":"Point"}
}