{
  "type": "Feature",
  "properties": {
    "gn:admin1_code":"21",
    "gn:admin2_code":"91795.0",
    "gn:asciiname":"Ciungani",
    "gn:country_code":"RO",
    "gn:dem":369,
    "gn:feature_class":"P",
    "gn:feature_code":"PPL",
    "gn:name":"Ciungani",
    "gn:population":364,
    "gn:timezone":"Europe/Bucharest",
    "iso:country":"RO",
    "name:ron_x_preferred":[
        "Ciungani"
    ],
    "name:und_x_variant":[
        "Csung\u00e1ny"
    ],
    "wof:name":"Ciungani",
    "wof:placetype":"locality",
    "wof:population":364
},
  "geometry": {"coordinates":[22.50058,46.18582],"type":"Point"}
}