{
  "type": "Feature",
  "properties": {
    "gn:admin1_code":"41",
    "gn:admin2_code":"101083.0",
    "gn:asciiname":"Mariuta",
    "gn:country_code":"RO",
    "gn:dem":56,
    "gn:feature_class":"P",
    "gn:feature_code":"PPL",
    "gn:name":"M\u0103riu\u021ba",
    "gn:population":583,
    "gn:timezone":"Europe/Bucharest",
    "iso:country":"RO",
    "wof:name":"Mariuta",
    "wof:placetype":"locality",
    "wof:population":583
},
  "geometry": {"coordinates":[26.48489,44.53431],"type":"Point"}
}