{
  "type": "Feature",
  "properties": {
    "gn:admin1_code":"20",
    "gn:admin2_code":"84264.0",
    "gn:asciiname":"Tamasu",
    "gn:cc2":"RO",
    "gn:country_code":"RO",
    "gn:dem":528,
    "gn:feature_class":"P",
    "gn:feature_code":"PPL",
    "gn:name":"T\u0103ma\u0219u",
    "gn:population":116,
    "gn:timezone":"Europe/Bucharest",
    "iso:country":"RO",
    "name:und_x_variant":[
        "T\u0103ma\u015ful",
        "Sz\u00e9kelyszenttam\u00e0s",
        "T\u0103ma\u015fu"
    ],
    "wof:name":"Tamasu",
    "wof:placetype":"locality",
    "wof:population":116
},
  "geometry": {"coordinates":[25.28927,46.34831],"type":"Point"}
}