{
  "type": "Feature",
  "properties": {
    "gn:admin1_code":"39",
    "gn:admin2_code":"169039.0",
    "gn:asciiname":"Obarsia",
    "gn:country_code":"RO",
    "gn:dem":439,
    "gn:feature_class":"P",
    "gn:feature_code":"PPL",
    "gn:name":"Ob\u00e2r\u0219ia",
    "gn:population":500,
    "gn:timezone":"Europe/Bucharest",
    "iso:country":"RO",
    "name:und_x_variant":[
        "Ob\u00e2rsia",
        "Ob\u00eer\u015fia"
    ],
    "wof:name":"Obarsia",
    "wof:placetype":"locality",
    "wof:population":500
},
  "geometry": {"coordinates":[23.98333,45.06667],"type":"Point"}
}