{
  "type": "Feature",
  "properties": {
    "gn:admin1_code":"30",
    "gn:admin2_code":"135681.0",
    "gn:asciiname":"Silistea",
    "gn:country_code":"RO",
    "gn:dem":384,
    "gn:feature_class":"P",
    "gn:feature_code":"PPL",
    "gn:name":"Sili\u0219tea",
    "gn:population":228,
    "gn:timezone":"Europe/Bucharest",
    "iso:country":"RO",
    "wof:name":"Silistea",
    "wof:placetype":"locality",
    "wof:population":228
},
  "geometry": {"coordinates":[26.29396,45.10634],"type":"Point"}
}