{
  "type": "Feature",
  "properties": {
    "gn:admin1_code":"04",
    "gn:admin2_code":"25068.0",
    "gn:asciiname":"Contesti",
    "gn:cc2":"RO",
    "gn:country_code":"RO",
    "gn:dem":228,
    "gn:feature_class":"P",
    "gn:feature_code":"PPL",
    "gn:name":"Con\u021be\u0219ti",
    "gn:population":674,
    "gn:timezone":"Europe/Bucharest",
    "iso:country":"RO",
    "name:ceb_x_preferred":[
        "Contesti"
    ],
    "name:deu_x_preferred":[
        "Contesti"
    ],
    "name:spa_x_preferred":[
        "Contesti"
    ],
    "name:und_x_variant":[
        "Con\u0163e\u015ftii",
        "Con\u0163e\u015fti"
    ],
    "wof:name":"Contesti",
    "wof:placetype":"locality",
    "wof:population":674
},
  "geometry": {"coordinates":[27.08477,46.16628],"type":"Point"}
}