{
  "type": "Feature",
  "properties": {
    "gn:gn_country":"RO",
    "gn:gn_fcode":"PPLA2",
    "gn:gn_pop":2854,
    "gn:population":2854,
    "iso:country":"RO",
    "name:ceb_x_preferred":[
        "Constantin Daicoviciu"
    ],
    "name:deu_x_preferred":[
        "Constantin Daicoviciu"
    ],
    "name:eng_x_preferred":[
        "Constantin Daicoviciu"
    ],
    "name:epo_x_preferred":[
        "Constantin Daicoviciu"
    ],
    "name:fra_x_preferred":[
        "Constantin Daicoviciu"
    ],
    "name:hun_x_preferred":[
        "Kavar\u00e1n"
    ],
    "name:ita_x_preferred":[
        "Constantin Daicoviciu"
    ],
    "name:msa_x_preferred":[
        "Constantin Daicoviciu"
    ],
    "name:nld_x_preferred":[
        "Constantin Daicoviciu"
    ],
    "name:por_x_preferred":[
        "Constantin Daicoviciu"
    ],
    "name:ron_x_preferred":[
        "Constantin Daicoviciu"
    ],
    "name:rus_x_preferred":[
        "\u041a\u043e\u043d\u0441\u0442\u0430\u043d\u0442\u0438\u043d-\u0414\u0430\u0439\u043a\u043e\u0432\u0438\u0447\u0443"
    ],
    "name:srp_x_preferred":[
        "\u041a\u043e\u043d\u0441\u0442\u0430\u043d\u0442\u0438\u043d \u0414\u0430\u0438\u043a\u043e\u0432\u0438\u0447\u0443"
    ],
    "name:ukr_x_preferred":[
        "\u041a\u043e\u043d\u0441\u0442\u0430\u043d\u0442\u0456\u043d-\u0414\u0430\u0439\u043a\u043e\u0432\u0456\u0447\u0443"
    ],
    "name:unk_x_variant":[
        "C\u0103v\u0103ran"
    ],
    "name:vol_x_preferred":[
        "Constantin Daicoviciu"
    ],
    "qs_pg:aaroncc":"RO",
    "qs_pg:gn_country":"RO",
    "qs_pg:gn_fcode":"PPLA2",
    "qs_pg:gn_pop":2854,
    "qs_pg:name":"Constantin Daicoviciu",
    "qs_pg:name_adm0":"Rom\u00e2nia",
    "qs_pg:name_adm1":"Caras-Severin",
    "qs_pg:photos_9k":1,
    "qs_pg:photos_9r":1,
    "qs_pg:photos_all":8,
    "qs_pg:photos_sr":0,
    "qs_pg:pop_sr":4,
    "qs_pg:qs_pg_placetype":"locality",
    "qs_pg:qs_pg_placetype_gp":"Town",
    "qs_pg:woe_adm0":23424933,
    "woe:adm0_id":23424933,
    "woe:name_adm0":"Rom\u00e2nia",
    "woe:name_adm1":"Caras-Severin",
    "woe:placetype":"Town",
    "wof:name":"Constantin Daicoviciu",
    "wof:placetype":"locality",
    "wof:population":2854
},
  "geometry": {"coordinates":[22.15,45.55],"type":"Point"}
}