{
  "type": "Feature",
  "properties": {
    "gn:admin1_code":"04",
    "gn:admin2_code":"25932",
    "gn:asciiname":"Bota",
    "gn:country_code":"RO",
    "gn:dem":375,
    "gn:feature_class":"P",
    "gn:feature_code":"PPL",
    "gn:name":"Bota",
    "gn:population":0,
    "gn:timezone":"Europe/Bucharest",
    "iso:country":"RO",
    "wof:name":"Bota",
    "wof:placetype":"locality"
},
  "geometry": {"coordinates":[27.14117,46.52127],"type":"Point"}
}