{
  "type": "Feature",
  "properties": {
    "gn:admin1_code":"04",
    "gn:admin2_code":"21418.0",
    "gn:asciiname":"Moreni",
    "gn:country_code":"RO",
    "gn:dem":352,
    "gn:feature_class":"P",
    "gn:feature_code":"PPL",
    "gn:name":"Moreni",
    "gn:population":0,
    "gn:timezone":"Europe/Bucharest",
    "iso:country":"RO",
    "name:ace_x_preferred":[
        "Moreni"
    ],
    "name:azb_x_preferred":[
        "\u0645\u0648\u0631\u0647 \u060c"
    ],
    "name:ceb_x_preferred":[
        "Municipiul Moreni"
    ],
    "name:deu_x_preferred":[
        "Moreni"
    ],
    "name:fas_x_preferred":[
        "\u0645\u0648\u0631\u0647"
    ],
    "name:fra_x_preferred":[
        "Moreni"
    ],
    "name:hun_x_preferred":[
        "Moreni"
    ],
    "name:ind_x_preferred":[
        "Moreni"
    ],
    "name:ita_x_preferred":[
        "Moreni"
    ],
    "name:jpn_x_preferred":[
        "\u30e2\u30ec\u30cb"
    ],
    "name:lat_x_preferred":[
        "Moreni"
    ],
    "name:lit_x_preferred":[
        "Morenis"
    ],
    "name:min_x_preferred":[
        "Moreni"
    ],
    "name:msa_x_preferred":[
        "Moreni"
    ],
    "name:nld_x_preferred":[
        "Moreni"
    ],
    "name:pol_x_preferred":[
        "Moreni"
    ],
    "name:por_x_preferred":[
        "Moreni"
    ],
    "name:ron_x_preferred":[
        "Moreni"
    ],
    "name:rus_x_preferred":[
        "\u041c\u043e\u0440\u0435\u043d\u0438"
    ],
    "name:spa_x_preferred":[
        "Moreni"
    ],
    "name:srp_x_preferred":[
        "\u041e\u043f\u0448\u0442\u0438\u043d\u0430 \u041c\u043e\u0440\u0435\u043d\u0438"
    ],
    "name:tgk_x_preferred":[
        "\u041c\u043e\u0440\u0435\u043d\u0438"
    ],
    "name:ukr_x_preferred":[
        "\u041c\u043e\u0440\u0435\u043d\u044c"
    ],
    "name:vie_x_preferred":[
        "Moreni"
    ],
    "name:zho_x_preferred":[
        "\u83ab\u96f7\u5c3c"
    ],
    "wof:name":"Moreni",
    "wof:placetype":"locality"
},
  "geometry": {"coordinates":[26.66667,46.41667],"type":"Point"}
}