{
  "type": "Feature",
  "properties": {
    "gn:admin1_code":"04",
    "gn:admin2_code":"21418.0",
    "gn:asciiname":"Moreni",
    "gn:country_code":"RO",
    "gn:dem":352,
    "gn:feature_class":"P",
    "gn:feature_code":"PPL",
    "gn:name":"Moreni",
    "gn:population":0,
    "gn:timezone":"Europe/Bucharest",
    "iso:country":"RO",
    "wof:name":"Moreni",
    "wof:placetype":"locality"
},
  "geometry": {"coordinates":[26.66667,46.41667],"type":"Point"}
}