{
  "type": "Feature",
  "properties": {
    "gn:admin1_code":"02",
    "gn:admin2_code":"12849.0",
    "gn:asciiname":"Crisana",
    "gn:country_code":"RO",
    "gn:dem":85,
    "gn:feature_class":"P",
    "gn:feature_code":"PPL",
    "gn:name":"Cri\u015fana",
    "gn:population":0,
    "gn:timezone":"Europe/Bucharest",
    "iso:country":"RO",
    "wof:name":"Crisana",
    "wof:placetype":"locality"
},
  "geometry": {"coordinates":[21.51667,46.61667],"type":"Point"}
}