{
  "type": "Feature",
  "properties": {
    "gn:admin1_code":"37",
    "gn:admin2_code":"159963.0",
    "gn:asciiname":"Cismeaua Noua",
    "gn:cc2":"RO",
    "gn:country_code":"RO",
    "gn:dem":172,
    "gn:feature_class":"P",
    "gn:feature_code":"PPL",
    "gn:name":"Ci\u0219meaua Nou\u0103",
    "gn:population":109,
    "gn:timezone":"Europe/Bucharest",
    "iso:country":"RO",
    "name:und_x_variant":[
        "Ramazanchioi",
        "Ci\u015fmeaua Nou\u0103"
    ],
    "wof:name":"Cismeaua Noua",
    "wof:placetype":"locality",
    "wof:population":109
},
  "geometry": {"coordinates":[28.33496,44.80052],"type":"Point"}
}