{
  "type": "Feature",
  "properties": {
    "gn:gn_country":"RO",
    "gn:gn_fcode":"PPLA2",
    "gn:gn_pop":1841,
    "gn:population":1841,
    "iso:country":"RO",
    "name:bul_x_preferred":[
        "\u041c\u0438\u0441\u0447\u0438"
    ],
    "name:eng_x_preferred":[
        "Mischii"
    ],
    "name:fra_x_preferred":[
        "Mischii"
    ],
    "name:ita_x_preferred":[
        "Mischii"
    ],
    "name:nld_x_preferred":[
        "Mischii"
    ],
    "name:por_x_preferred":[
        "Mischii"
    ],
    "name:ron_x_preferred":[
        "Mischii"
    ],
    "name:ukr_x_preferred":[
        "\u041c\u0456\u0441\u043a\u0456\u0439"
    ],
    "name:vie_x_preferred":[
        "Mischii"
    ],
    "name:vol_x_preferred":[
        "Mischii"
    ],
    "qs_pg:aaroncc":"RO",
    "qs_pg:gn_country":"RO",
    "qs_pg:gn_fcode":"PPLA2",
    "qs_pg:gn_pop":1841,
    "qs_pg:name":"Mischii",
    "qs_pg:name_adm0":"Rom\u00e2nia",
    "qs_pg:name_adm1":"Dolj",
    "qs_pg:photos_9r":0,
    "qs_pg:photos_sr":0,
    "qs_pg:pop_sr":3,
    "qs_pg:qs_pg_placetype":"locality",
    "qs_pg:qs_pg_placetype_gp":"Town",
    "qs_pg:woe_adm0":23424933,
    "woe:adm0_id":23424933,
    "woe:name_adm0":"Rom\u00e2nia",
    "woe:name_adm1":"Dolj",
    "woe:placetype":"Town",
    "wof:name":"Mischii",
    "wof:placetype":"locality",
    "wof:population":1841
},
  "geometry": {"coordinates":[23.85,44.38333],"type":"Point"}
}