{
  "type": "Feature",
  "properties": {
    "gn:admin1_code":"23",
    "gn:admin2_code":"100219.0",
    "gn:asciiname":"Schitu Stavnic",
    "gn:country_code":"RO",
    "gn:dem":248,
    "gn:feature_class":"P",
    "gn:feature_code":"PPL",
    "gn:name":"Schitu Stavnic",
    "gn:population":438,
    "gn:timezone":"Europe/Bucharest",
    "iso:country":"RO",
    "wof:name":"Schitu Stavnic",
    "wof:placetype":"locality",
    "wof:population":438
},
  "geometry": {"coordinates":[27.39065,47.06637],"type":"Point"}
}