{
  "type": "Feature",
  "properties": {
    "gn:admin1_code":"41",
    "gn:admin2_code":"104635.0",
    "gn:asciiname":"Cucuieti-Moara",
    "gn:cc2":"RO",
    "gn:country_code":"RO",
    "gn:dem":37,
    "gn:feature_class":"P",
    "gn:feature_code":"PPL",
    "gn:name":"Cucuie\u0163i-Moar\u0103",
    "gn:population":0,
    "gn:timezone":"Europe/Bucharest",
    "iso:country":"RO",
    "name:und_x_variant":[
        "Cucue\u0163i-Moara",
        "Cucuetii-Moara",
        "Cucuie\u0163i-Moar\u0103"
    ],
    "wof:lang_x_official":[
        "ron"
    ],
    "wof:lang_x_spoken":[
        "ron"
    ],
    "wof:name":"Cucuieti-Moara",
    "wof:placetype":"locality"
},
  "geometry": {"coordinates":[26.38333,44.33333],"type":"Point"}
}