{
  "type": "Feature",
  "properties": {
    "gn:admin1_code":"20",
    "gn:admin2_code":"86133.0",
    "gn:asciiname":"Recea",
    "gn:cc2":"RO",
    "gn:country_code":"RO",
    "gn:dem":730,
    "gn:feature_class":"P",
    "gn:feature_code":"PPL",
    "gn:name":"Recea",
    "gn:population":163,
    "gn:timezone":"Europe/Bucharest",
    "iso:country":"RO",
    "name:und_x_variant":[
        "Recefalva",
        "Recea Reczefalva",
        "Recea"
    ],
    "wof:name":"Recea",
    "wof:placetype":"locality",
    "wof:population":163
},
  "geometry": {"coordinates":[25.72872000000001,46.90079],"type":"Point"}
}