{
  "type": "Feature",
  "properties": {
    "gn:admin1_code":"20",
    "gn:admin2_code":"86133.0",
    "gn:asciiname":"Recea",
    "gn:cc2":"RO",
    "gn:country_code":"RO",
    "gn:dem":730,
    "gn:feature_class":"P",
    "gn:feature_code":"PPL",
    "gn:name":"Recea",
    "gn:population":163,
    "gn:timezone":"Europe/Bucharest",
    "iso:country":"RO",
    "name:ceb_x_preferred":[
        "Recea"
    ],
    "name:deu_x_preferred":[
        "Recea"
    ],
    "name:epo_x_preferred":[
        "Recea"
    ],
    "name:fra_x_preferred":[
        "Recea"
    ],
    "name:hrv_x_preferred":[
        "Recea"
    ],
    "name:hun_x_preferred":[
        "Recea"
    ],
    "name:ita_x_preferred":[
        "Recea"
    ],
    "name:nld_x_preferred":[
        "Recea"
    ],
    "name:ron_x_preferred":[
        "Recea"
    ],
    "name:rus_x_preferred":[
        "\u0420\u0435\u0447\u0430"
    ],
    "name:srp_x_preferred":[
        "\u0420\u0435\u0447\u0430"
    ],
    "name:swe_x_preferred":[
        "Recea"
    ],
    "name:ukr_x_preferred":[
        "\u0420\u0435\u0447\u0430"
    ],
    "name:und_x_variant":[
        "Recefalva",
        "Recea Reczefalva"
    ],
    "name:vol_x_preferred":[
        "Recea"
    ],
    "wof:name":"Recea",
    "wof:placetype":"locality",
    "wof:population":163
},
  "geometry": {"coordinates":[25.72872000000001,46.90079],"type":"Point"}
}