{
  "type": "Feature",
  "properties": {
    "gn:admin1_code":"09",
    "gn:admin2_code":"40704.0",
    "gn:asciiname":"Viscri",
    "gn:country_code":"RO",
    "gn:dem":532,
    "gn:feature_class":"P",
    "gn:feature_code":"PPL",
    "gn:name":"Viscri",
    "gn:population":2476,
    "gn:timezone":"Europe/Bucharest",
    "iso:country":"RO",
    "name:hun_x_preferred":[
        "Sz\u00e1szfeh\u00e9regyh\u00e1za"
    ],
    "name:rus_x_preferred":[
        "\u0412\u0438\u0441\u043a\u0440\u0438"
    ],
    "wof:name":"Viscri",
    "wof:placetype":"locality",
    "wof:population":2476
},
  "geometry": {"coordinates":[25.09389,46.05522],"type":"Point"}
}