{
  "type": "Feature",
  "properties": {
    "gn:admin1_code":"41",
    "gn:admin2_code":"93281.0",
    "gn:asciiname":"Calarasii Vechi",
    "gn:country_code":"RO",
    "gn:dem":16,
    "gn:feature_class":"P",
    "gn:feature_code":"PPL",
    "gn:name":"C\u0103l\u0103ra\u0219ii Vechi",
    "gn:population":773,
    "gn:timezone":"Europe/Bucharest",
    "iso:country":"RO",
    "wof:name":"Calarasii Vechi",
    "wof:placetype":"locality",
    "wof:population":773
},
  "geometry": {"coordinates":[27.29073,44.27101],"type":"Point"}
}