{
  "type": "Feature",
  "properties": {
    "gn:admin1_code":"20",
    "gn:admin2_code":"85412.0",
    "gn:asciiname":"Martonca",
    "gn:cc2":"RO",
    "gn:country_code":"RO",
    "gn:dem":724,
    "gn:feature_class":"P",
    "gn:feature_code":"PPL",
    "gn:name":"Martonca",
    "gn:population":0,
    "gn:timezone":"Europe/Bucharest",
    "iso:country":"RO",
    "name:und_x_variant":[
        "M\u00e0rtonka",
        "Martonca"
    ],
    "wof:name":"Martonca",
    "wof:placetype":"locality"
},
  "geometry": {"coordinates":[25.4376,46.83123],"type":"Point"}
}