{
  "type": "Feature",
  "properties": {
    "gn:admin1_code":"39",
    "gn:admin2_code":"171628.0",
    "gn:asciiname":"Predesti",
    "gn:cc2":"RO",
    "gn:country_code":"RO",
    "gn:dem":259,
    "gn:feature_class":"P",
    "gn:feature_code":"PPL",
    "gn:name":"Prede\u0219ti",
    "gn:population":556,
    "gn:timezone":"Europe/Bucharest",
    "iso:country":"RO",
    "name:und_x_variant":[
        "Stoiceni",
        "Prede\u015fti"
    ],
    "wof:name":"Predesti",
    "wof:placetype":"locality",
    "wof:population":556
},
  "geometry": {"coordinates":[24.36375,44.96932],"type":"Point"}
}