{
  "type": "Feature",
  "properties": {
    "gn:admin1_code":"23",
    "gn:admin2_code":"98113.0",
    "gn:asciiname":"Hadambu",
    "gn:cc2":"RO",
    "gn:country_code":"RO",
    "gn:dem":204,
    "gn:feature_class":"P",
    "gn:feature_code":"PPL",
    "gn:name":"Had\u00e2mbu",
    "gn:population":968,
    "gn:timezone":"Europe/Bucharest",
    "iso:country":"RO",
    "name:und_x_variant":[
        "Had\u00e2mbu",
        "Had\u00e2mbul",
        "Had\u00eembu"
    ],
    "wof:name":"Hadambu",
    "wof:placetype":"locality",
    "wof:population":968
},
  "geometry": {"coordinates":[27.45864000000001,47.01646],"type":"Point"}
}