{
  "type": "Feature",
  "properties": {
    "gn:admin1_code":"29",
    "gn:admin2_code":"130124.0",
    "gn:asciiname":"Simniceni",
    "gn:country_code":"RO",
    "gn:dem":203,
    "gn:feature_class":"P",
    "gn:feature_code":"PPL",
    "gn:name":"Simniceni",
    "gn:population":118,
    "gn:timezone":"Europe/Bucharest",
    "iso:country":"RO",
    "wof:name":"Simniceni",
    "wof:placetype":"locality",
    "wof:population":118
},
  "geometry": {"coordinates":[23.90081,44.47752],"type":"Point"}
}