{
  "type": "Feature",
  "properties": {
    "gn:admin1_code":"40",
    "gn:admin2_code":"178956.0",
    "gn:asciiname":"Vladuleasa",
    "gn:country_code":"RO",
    "gn:dem":28,
    "gn:feature_class":"P",
    "gn:feature_code":"PPL",
    "gn:name":"Vl\u0103duleasa",
    "gn:population":0,
    "gn:timezone":"Europe/Bucharest",
    "iso:country":"RO",
    "name:und_x_variant":[
        "Vl\u0103duleasu",
        "Vl\u0103duleasa"
    ],
    "wof:name":"Vladuleasa",
    "wof:placetype":"locality"
},
  "geometry": {"coordinates":[27.31667,45.63333],"type":"Point"}
}