{
  "type": "Feature",
  "properties": {
    "gn:admin1_code":"07",
    "gn:admin2_code":"37547.0",
    "gn:asciiname":"Galbeni",
    "gn:cc2":"RO",
    "gn:country_code":"RO",
    "gn:dem":115,
    "gn:feature_class":"P",
    "gn:feature_code":"PPL",
    "gn:name":"Galbeni",
    "gn:population":90,
    "gn:timezone":"Europe/Bucharest",
    "iso:country":"RO",
    "name:ceb_x_preferred":[
        "Galbeni"
    ],
    "name:deu_x_preferred":[
        "Galbeni"
    ],
    "name:hun_x_preferred":[
        "Galbeni"
    ],
    "name:ron_x_preferred":[
        "Galben"
    ],
    "name:srp_x_preferred":[
        "\u0413\u0430\u043b\u0431\u0435\u043d\u0438"
    ],
    "wof:name":"Galbeni",
    "wof:placetype":"locality",
    "wof:population":90
},
  "geometry": {"coordinates":[26.70256,48.03542],"type":"Point"}
}