{
  "type": "Feature",
  "properties": {
    "gn:admin1_code":"07",
    "gn:admin2_code":"37547.0",
    "gn:asciiname":"Galbeni",
    "gn:cc2":"RO",
    "gn:country_code":"RO",
    "gn:dem":115,
    "gn:feature_class":"P",
    "gn:feature_code":"PPL",
    "gn:name":"Galbeni",
    "gn:population":90,
    "gn:timezone":"Europe/Bucharest",
    "iso:country":"RO",
    "name:und_x_variant":[
        "Galben",
        "Galbeni"
    ],
    "wof:name":"Galbeni",
    "wof:placetype":"locality",
    "wof:population":90
},
  "geometry": {"coordinates":[26.70256,48.03542],"type":"Point"}
}