{
  "type": "Feature",
  "properties": {
    "gn:admin1_code":"29",
    "gn:admin2_code":"129246.0",
    "gn:asciiname":"Serbanestii de Sus",
    "gn:cc2":"RO",
    "gn:country_code":"RO",
    "gn:dem":134,
    "gn:feature_class":"P",
    "gn:feature_code":"PPL",
    "gn:name":"\u0218erb\u0103ne\u0219tii de Sus",
    "gn:population":723,
    "gn:timezone":"Europe/Bucharest",
    "iso:country":"RO",
    "name:und_x_variant":[
        "\u015eerb\u0103ne\u015fti-de-Sus",
        "\u015eerb\u0103ne\u015ftii de Sus"
    ],
    "wof:name":"Serbanestii de Sus",
    "wof:placetype":"locality",
    "wof:population":723
},
  "geometry": {"coordinates":[24.68306,44.3366],"type":"Point"}
}