{
  "type": "Feature",
  "properties": {
    "gn:gn_country":"RO",
    "gn:gn_fcode":"PPL",
    "gn:gn_pop":2997,
    "gn:population":2283,
    "iso:country":"RO",
    "name:eng_x_preferred":[
        "Drago\u0219 Vod\u0103"
    ],
    "name:fra_x_preferred":[
        "Drago\u0219 Vod\u0103"
    ],
    "name:ita_x_preferred":[
        "Drago\u0219 Vod\u0103"
    ],
    "name:nld_x_preferred":[
        "Drago\u0219 Vod\u0103"
    ],
    "name:ron_x_preferred":[
        "Drago\u0219 Vod\u0103"
    ],
    "name:srp_x_preferred":[
        "\u0412\u043e\u0434\u0430 \u0414\u0440\u0430\u0433\u043e\u0441"
    ],
    "name:ukr_x_preferred":[
        "\u0414\u0440\u0430\u0433\u043e\u0448-\u0412\u043e\u0434\u0435"
    ],
    "qs_pg:aaroncc":"RO",
    "qs_pg:gn_country":"RO",
    "qs_pg:gn_fcode":"PPL",
    "qs_pg:gn_pop":2997,
    "qs_pg:name":"Vod\u0103 Dragos",
    "qs_pg:photos_9r":0,
    "qs_pg:photos_sr":0,
    "qs_pg:pop_sr":4,
    "qs_pg:qs_pg_placetype":"locality",
    "wof:name":"Vod\u0103 Dragos",
    "wof:placetype":"locality",
    "wof:population":2283
},
  "geometry": {"coordinates":[27.15,44.43333],"type":"Point"}
}