{
  "type": "Feature",
  "properties": {
    "gn:admin1_code":"39",
    "gn:admin2_code":"169896.0",
    "gn:asciiname":"Mosteni",
    "gn:cc2":"RO",
    "gn:country_code":"RO",
    "gn:dem":263,
    "gn:feature_class":"P",
    "gn:feature_code":"PPL",
    "gn:name":"Mo\u0219teni",
    "gn:population":411,
    "gn:timezone":"Europe/Bucharest",
    "iso:country":"RO",
    "name:und_x_variant":[
        "Mo\u015fneni",
        "Mo\u015fteni"
    ],
    "wof:name":"Mosteni",
    "wof:placetype":"locality",
    "wof:population":411
},
  "geometry": {"coordinates":[24.1788,45.03426],"type":"Point"}
}