{
  "type": "Feature",
  "properties": {
    "gn:admin1_code":"01",
    "gn:admin2_code":"6627.0",
    "gn:asciiname":"Valea Manastirii",
    "gn:country_code":"RO",
    "gn:dem":457,
    "gn:feature_class":"P",
    "gn:feature_code":"PPL",
    "gn:name":"Valea M\u0103n\u0103stirii",
    "gn:population":158,
    "gn:timezone":"Europe/Bucharest",
    "iso:country":"RO",
    "wof:name":"Valea Manastirii",
    "wof:placetype":"locality",
    "wof:population":158
},
  "geometry": {"coordinates":[23.52287,46.30146],"type":"Point"}
}