{
  "type": "Feature",
  "properties": {
    "gn:admin1_code":"05",
    "gn:admin2_code":"30719.0",
    "gn:asciiname":"Petreasa",
    "gn:cc2":"RO",
    "gn:country_code":"RO",
    "gn:dem":203,
    "gn:feature_class":"P",
    "gn:feature_code":"PPL",
    "gn:name":"Petreasa",
    "gn:population":454,
    "gn:timezone":"Europe/Bucharest",
    "iso:country":"RO",
    "name:deu_x_preferred":[
        "Petreasa"
    ],
    "name:hun_x_preferred":[
        "Petreasa"
    ],
    "name:ron_x_preferred":[
        "Petreasa"
    ],
    "name:srp_x_preferred":[
        "\u041f\u0435\u0442\u0440\u0435\u0430\u0441\u0430"
    ],
    "name:und_x_variant":[
        "Petroasa"
    ],
    "wof:name":"Petreasa",
    "wof:placetype":"locality",
    "wof:population":454
},
  "geometry": {"coordinates":[22.34817,46.71432],"type":"Point"}
}