{
  "type": "Feature",
  "properties": {
    "gn:admin1_code":"39",
    "gn:admin2_code":"174021.0",
    "gn:asciiname":"Cerna",
    "gn:country_code":"RO",
    "gn:dem":646,
    "gn:feature_class":"P",
    "gn:feature_code":"PPL",
    "gn:name":"Cerna",
    "gn:population":277,
    "gn:timezone":"Europe/Bucharest",
    "iso:country":"RO",
    "wof:name":"Cerna",
    "wof:placetype":"locality",
    "wof:population":277
},
  "geometry": {"coordinates":[23.84885,45.18406],"type":"Point"}
}