{
  "type": "Feature",
  "properties": {
    "gn:admin1_code":"19",
    "gn:admin2_code":"82047.0",
    "gn:asciiname":"Stiucani",
    "gn:country_code":"RO",
    "gn:dem":251,
    "gn:feature_class":"P",
    "gn:feature_code":"PPL",
    "gn:name":"\u0218tiucani",
    "gn:population":73,
    "gn:timezone":"Europe/Bucharest",
    "iso:country":"RO",
    "wof:name":"Stiucani",
    "wof:placetype":"locality",
    "wof:population":73
},
  "geometry": {"coordinates":[23.03333,44.83333],"type":"Point"}
}