{
  "type": "Feature",
  "properties": {
    "gn:country":"RO",
    "gn:fcode":"PPLA2",
    "gn:population":4202,
    "iso:country":"RO",
    "name:arz_x_preferred":[
        "\u0646\u064a\u0631\u064a\u0686\u0648"
    ],
    "name:ceb_x_preferred":[
        "Nereju"
    ],
    "name:eng_x_preferred":[
        "Nereju"
    ],
    "name:fra_x_preferred":[
        "Nereju"
    ],
    "name:hun_x_preferred":[
        "Nereju"
    ],
    "name:ita_x_preferred":[
        "Nereju"
    ],
    "name:nld_x_preferred":[
        "Nereju"
    ],
    "name:ron_x_preferred":[
        "Nereju"
    ],
    "name:srp_x_preferred":[
        "\u041d\u0435\u0440\u0435\u0436\u0443"
    ],
    "name:ukr_x_preferred":[
        "\u041d\u0435\u0440\u0435\u0436\u0443"
    ],
    "qs_pg:aaroncc":"RO",
    "qs_pg:gn_country":"RO",
    "qs_pg:gn_fcode":"PPLA2",
    "qs_pg:gn_pop":4202,
    "qs_pg:name":"Nereju-Mare",
    "qs_pg:name_adm0":"Rom\u00e2nia",
    "qs_pg:name_adm1":"Vrancea",
    "qs_pg:photos_9r":0,
    "qs_pg:photos_sr":0,
    "qs_pg:pop_sr":4,
    "qs_pg:qs_pg_placetype":"locality",
    "qs_pg:qs_pg_placetype_gp":"Town",
    "qs_pg:woe_adm0":23424933,
    "woe:adm0_id":23424933,
    "woe:name_adm0":"Rom\u00e2nia",
    "woe:name_adm1":"Vrancea",
    "woe:placetype":"Town",
    "wof:name":"Nereju-Mare",
    "wof:placetype":"locality",
    "wof:population":4202
},
  "geometry": {"coordinates":[26.71667,45.71667],"type":"Point"}
}