{
  "type": "Feature",
  "properties": {
    "gn:admin1_code":"38",
    "gn:admin2_code":"166235.0",
    "gn:asciiname":"Dumasca",
    "gn:country_code":"RO",
    "gn:dem":219,
    "gn:feature_class":"P",
    "gn:feature_code":"PPL",
    "gn:name":"Dumasca",
    "gn:population":440,
    "gn:timezone":"Europe/Bucharest",
    "iso:country":"RO",
    "wof:name":"Dumasca",
    "wof:placetype":"locality",
    "wof:population":440
},
  "geometry": {"coordinates":[27.71028,46.92431],"type":"Point"}
}