{
  "type": "Feature",
  "properties": {
    "gn:admin1_code":"34",
    "gn:admin2_code":"150766.0",
    "gn:asciiname":"Mesteceni",
    "gn:cc2":"RO",
    "gn:country_code":"RO",
    "gn:dem":384,
    "gn:feature_class":"P",
    "gn:feature_code":"PPL",
    "gn:name":"Mesteceni",
    "gn:population":268,
    "gn:timezone":"Europe/Bucharest",
    "iso:country":"RO",
    "name:und_x_variant":[
        "Mesteci",
        "Mesteceni"
    ],
    "wof:name":"Mesteceni",
    "wof:placetype":"locality",
    "wof:population":268
},
  "geometry": {"coordinates":[26.4196,47.40179000000001],"type":"Point"}
}