{
  "type": "Feature",
  "properties": {
    "gn:admin1_code":"13",
    "gn:admin2_code":"58721.0",
    "gn:asciiname":"Stejeris",
    "gn:cc2":"RO",
    "gn:country_code":"RO",
    "gn:dem":341,
    "gn:feature_class":"P",
    "gn:feature_code":"PPL",
    "gn:name":"Stejeri\u0219",
    "gn:population":237,
    "gn:timezone":"Europe/Bucharest",
    "iso:country":"RO",
    "name:und_x_variant":[
        "C\u00eercedea",
        "Stej\u0103ri\u015f",
        "Stejeri\u015f"
    ],
    "wof:name":"Stejeris",
    "wof:placetype":"locality",
    "wof:population":237
},
  "geometry": {"coordinates":[23.73708,46.4654],"type":"Point"}
}