{
  "type": "Feature",
  "properties": {
    "iso:country":"RO",
    "name:alb_x_preferred":[
        "Sc\u0103ri\u0219oara"
    ],
    "name:ara_x_preferred":[
        "\u0633\u0643\u0627\u0631\u064a\u0634\u0648\u0627\u0631\u0627"
    ],
    "name:dut_x_preferred":[
        "Sc\u0103ri\u0219oara"
    ],
    "name:eng_x_preferred":[
        "Sc\u0103ri\u0219oara"
    ],
    "name:epo_x_preferred":[
        "Sc\u0103ri\u0219oara"
    ],
    "name:ger_x_preferred":[
        "Sc\u0103ri\u0219oara"
    ],
    "name:hrv_x_preferred":[
        "Sc\u0103ri\u0219oara"
    ],
    "name:hun_x_preferred":[
        "Aranyosf\u0151"
    ],
    "name:ita_x_preferred":[
        "Sc\u0103ri\u0219oara"
    ],
    "name:mac_x_preferred":[
        "\u0421\u043a\u0430\u0440\u0438\u0448\u0432\u0430\u0440"
    ],
    "name:may_x_preferred":[
        "Sc\u0103ri\u0219oara"
    ],
    "name:por_x_preferred":[
        "Sc\u0103ri\u0219oara"
    ],
    "name:rum_x_preferred":[
        "Sc\u0103ri\u0219oara"
    ],
    "name:ukr_x_preferred":[
        "\u0421\u043a\u0435\u0440\u0456\u0448\u043e\u0430\u0440\u0430"
    ],
    "name:vie_x_preferred":[
        "Scarisoara"
    ],
    "name:vol_x_preferred":[
        "Sc\u0103ri\u0219oara"
    ],
    "qs_pg:aaroncc":"RO",
    "qs_pg:name":"Sc\u0103ri\u0219oara",
    "qs_pg:name_adm0":"Rom\u00e2nia",
    "qs_pg:name_adm1":"Alba",
    "qs_pg:photos":40,
    "qs_pg:photos_1k":8,
    "qs_pg:photos_9k":1,
    "qs_pg:photos_9r":2,
    "qs_pg:photos_all":40,
    "qs_pg:photos_sr":2,
    "qs_pg:pop_sr":0,
    "qs_pg:qs_pg_placetype":"locality",
    "qs_pg:qs_pg_placetype_gp":"Town",
    "qs_pg:woe_adm0":23424933,
    "woe:adm0_id":23424933,
    "woe:name_adm0":"Rom\u00e2nia",
    "woe:name_adm1":"Alba",
    "woe:placetype":"Town",
    "wof:name":"Sc\u0103ri\u0219oara",
    "wof:placetype":"locality"
},
  "geometry": {"coordinates":[22.84638,46.474189],"type":"Point"}
}