{
  "type": "Feature",
  "properties": {
    "gn:admin1_code":"19",
    "gn:admin2_code":"81095.0",
    "gn:asciiname":"Motru Sec",
    "gn:cc2":"RO",
    "gn:country_code":"RO",
    "gn:dem":372,
    "gn:feature_class":"P",
    "gn:feature_code":"PPL",
    "gn:name":"Motru Sec",
    "gn:population":981,
    "gn:timezone":"Europe/Bucharest",
    "iso:country":"RO",
    "name:und_x_variant":[
        "Motrisor",
        "Motru Sec"
    ],
    "wof:name":"Motru Sec",
    "wof:placetype":"locality",
    "wof:population":981
},
  "geometry": {"coordinates":[22.79262,45.06258],"type":"Point"}
}