{
  "type": "Feature",
  "properties": {
    "gn:admin1_code":"26",
    "gn:admin2_code":"111916",
    "gn:asciiname":"Baltanele",
    "gn:cc2":"RO",
    "gn:country_code":"RO",
    "gn:dem":190,
    "gn:feature_class":"P",
    "gn:feature_code":"PPL",
    "gn:name":"B\u00e2ltanele",
    "gn:population":476,
    "gn:timezone":"Europe/Bucharest",
    "iso:country":"RO",
    "name:und_x_variant":[
        "B\u00e2ltanele",
        "B\u00eeltanele"
    ],
    "wof:name":"Baltanele",
    "wof:placetype":"locality",
    "wof:population":476
},
  "geometry": {"coordinates":[23.14798,44.57865],"type":"Point"}
}