{
  "type": "Feature",
  "properties": {
    "gn:admin1_code":"05",
    "gn:admin2_code":"28335.0",
    "gn:asciiname":"Dusesti",
    "gn:country_code":"RO",
    "gn:dem":162,
    "gn:feature_class":"P",
    "gn:feature_code":"PPL",
    "gn:name":"Du\u0219e\u0219ti",
    "gn:population":640,
    "gn:timezone":"Europe/Bucharest",
    "iso:country":"RO",
    "wof:name":"Dusesti",
    "wof:placetype":"locality",
    "wof:population":640
},
  "geometry": {"coordinates":[22.1789,46.83697],"type":"Point"}
}