{
  "type": "Feature",
  "properties": {
    "gn:admin1_code":"38",
    "gn:admin2_code":"162559.0",
    "gn:asciiname":"Sipeni",
    "gn:cc2":"RO",
    "gn:country_code":"RO",
    "gn:dem":191,
    "gn:feature_class":"P",
    "gn:feature_code":"PPL",
    "gn:name":"Sipeni",
    "gn:population":205,
    "gn:timezone":"Europe/Bucharest",
    "iso:country":"RO",
    "name:und_x_variant":[
        "Spineni",
        "Sipeni"
    ],
    "wof:name":"Sipeni",
    "wof:placetype":"locality",
    "wof:population":205
},
  "geometry": {"coordinates":[27.98275,46.13694],"type":"Point"}
}