{
  "type": "Feature",
  "properties": {
    "gn:admin1_code":"21",
    "gn:admin2_code":"89801",
    "gn:asciiname":"Barsau",
    "gn:cc2":"RO",
    "gn:country_code":"RO",
    "gn:dem":211,
    "gn:feature_class":"P",
    "gn:feature_code":"PPL",
    "gn:name":"B\u00e2rs\u0103u",
    "gn:population":529,
    "gn:timezone":"Europe/Bucharest",
    "iso:country":"RO",
    "name:und_x_variant":[
        "B\u00e2rseu",
        "B\u00e2rseul",
        "B\u00e2rs\u0103u",
        "B\u00eers\u0103u"
    ],
    "wof:name":"Barsau",
    "wof:placetype":"locality",
    "wof:population":529
},
  "geometry": {"coordinates":[22.96164,45.92981],"type":"Point"}
}