{
  "type": "Feature",
  "properties": {
    "gn:admin1_code":"21",
    "gn:admin2_code":"89801",
    "gn:asciiname":"Barsau",
    "gn:cc2":"RO",
    "gn:country_code":"RO",
    "gn:dem":211,
    "gn:feature_class":"P",
    "gn:feature_code":"PPL",
    "gn:name":"B\u00e2rs\u0103u",
    "gn:population":529,
    "gn:timezone":"Europe/Bucharest",
    "iso:country":"RO",
    "name:ceb_x_preferred":[
        "Comuna B\u00e2rs\u0103u"
    ],
    "name:epo_x_preferred":[
        "B\u00e2rs\u0103u"
    ],
    "name:fra_x_preferred":[
        "B\u00e2rs\u0103u"
    ],
    "name:ita_x_preferred":[
        "B\u00e2rs\u0103u"
    ],
    "name:msa_x_preferred":[
        "B\u00e2rs\u0103u"
    ],
    "name:nld_x_preferred":[
        "B\u00e2rs\u0103u"
    ],
    "name:por_x_preferred":[
        "B\u00e2rs\u0103u"
    ],
    "name:ron_x_preferred":[
        "Comuna B\u00e2rs\u0103u"
    ],
    "name:srp_x_preferred":[
        "\u041e\u043f\u0448\u0442\u0438\u043d\u0430 \u0411\u0430\u0440\u0441\u0430\u0443"
    ],
    "name:ukr_x_preferred":[
        "\u0411\u0438\u0440\u0441\u0435\u0443"
    ],
    "name:und_x_variant":[
        "B\u00e2rseu",
        "B\u00e2rseul",
        "B\u00eers\u0103u"
    ],
    "name:vie_x_preferred":[
        "B\u00e2rs\u0103u"
    ],
    "name:vol_x_preferred":[
        "B\u00e2rs\u0103u"
    ],
    "name:zho_x_preferred":[
        "\u4f2f\u723e\u745f\u70cf\u5fb7\u9109"
    ],
    "wof:name":"Barsau",
    "wof:placetype":"locality",
    "wof:population":529
},
  "geometry": {"coordinates":[22.96164,45.92981],"type":"Point"}
}