{
  "type": "Feature",
  "properties": {
    "gn:admin1_code":"21",
    "gn:admin2_code":"89080.0",
    "gn:asciiname":"Tisa",
    "gn:country_code":"RO",
    "gn:dem":167,
    "gn:feature_class":"P",
    "gn:feature_code":"PPL",
    "gn:name":"Tisa",
    "gn:population":188,
    "gn:timezone":"Europe/Bucharest",
    "iso:country":"RO",
    "wof:name":"Tisa",
    "wof:placetype":"locality",
    "wof:population":188
},
  "geometry": {"coordinates":[22.47269,45.95115],"type":"Point"}
}