{
  "type": "Feature",
  "properties": {
    "gn:admin1_code":"17",
    "gn:admin2_code":"69964.0",
    "gn:asciiname":"Carligei",
    "gn:cc2":"RO",
    "gn:country_code":"RO",
    "gn:dem":157,
    "gn:feature_class":"P",
    "gn:feature_code":"PPL",
    "gn:name":"C\u00e2rligei",
    "gn:population":400,
    "gn:timezone":"Europe/Bucharest",
    "iso:country":"RO",
    "name:und_x_variant":[
        "C\u00e2rligei",
        "C\u00eerligei"
    ],
    "wof:name":"Carligei",
    "wof:placetype":"locality",
    "wof:population":400
},
  "geometry": {"coordinates":[23.74718,44.28363],"type":"Point"}
}