{
  "type": "Feature",
  "properties": {
    "gn:admin1_code":"29",
    "gn:admin2_code":"129380.0",
    "gn:asciiname":"Comanita",
    "gn:country_code":"RO",
    "gn:dem":205,
    "gn:feature_class":"P",
    "gn:feature_code":"PPL",
    "gn:name":"Com\u0103ni\u021ba",
    "gn:population":471,
    "gn:timezone":"Europe/Bucharest",
    "iso:country":"RO",
    "wof:name":"Comanita",
    "wof:placetype":"locality",
    "wof:population":471
},
  "geometry": {"coordinates":[24.34767,44.56493],"type":"Point"}
}