{
  "type": "Feature",
  "properties": {
    "gn:admin1_code":"39",
    "gn:admin2_code":"169681.0",
    "gn:asciiname":"Dozesti",
    "gn:country_code":"RO",
    "gn:dem":249,
    "gn:feature_class":"P",
    "gn:feature_code":"PPL",
    "gn:name":"Doze\u0219ti",
    "gn:population":530,
    "gn:timezone":"Europe/Bucharest",
    "iso:country":"RO",
    "wof:name":"Dozesti",
    "wof:placetype":"locality",
    "wof:population":530
},
  "geometry": {"coordinates":[23.96112,44.79596],"type":"Point"}
}