{
  "type": "Feature",
  "properties": {
    "gn:admin1_code":"12",
    "gn:admin2_code":"52758.0",
    "gn:asciiname":"Soceni",
    "gn:cc2":"RO",
    "gn:country_code":"RO",
    "gn:dem":249,
    "gn:feature_class":"P",
    "gn:feature_code":"PPL",
    "gn:name":"Soceni",
    "gn:population":710,
    "gn:timezone":"Europe/Bucharest",
    "iso:country":"RO",
    "name:und_x_variant":[
        "Sz\u00f3cs\u00e1n",
        "Socenii",
        "Soceni"
    ],
    "wof:name":"Soceni",
    "wof:placetype":"locality",
    "wof:population":710
},
  "geometry": {"coordinates":[21.94758,45.37276],"type":"Point"}
}