{
  "type": "Feature",
  "properties": {
    "gn:admin1_code":"38",
    "gn:admin2_code":"163379",
    "gn:asciiname":"Albesti",
    "gn:country_code":"RO",
    "gn:dem":180,
    "gn:feature_class":"P",
    "gn:feature_code":"PPL",
    "gn:name":"Albe\u0219ti",
    "gn:population":239,
    "gn:timezone":"Europe/Bucharest",
    "iso:country":"RO",
    "wof:name":"Albesti",
    "wof:placetype":"locality",
    "wof:population":239
},
  "geometry": {"coordinates":[27.55285,46.69613],"type":"Point"}
}