{
  "type": "Feature",
  "properties": {
    "gn:admin1_code":"38",
    "gn:admin2_code":"163379",
    "gn:asciiname":"Albesti",
    "gn:country_code":"RO",
    "gn:dem":180,
    "gn:feature_class":"P",
    "gn:feature_code":"PPL",
    "gn:name":"Albe\u0219ti",
    "gn:population":239,
    "gn:timezone":"Europe/Bucharest",
    "iso:country":"RO",
    "name:ceb_x_preferred":[
        "Comuna Albe\u0219ti"
    ],
    "name:fas_x_preferred":[
        "\u0627\u0644\u0628\u0634\u062a\u06cc"
    ],
    "name:fra_x_preferred":[
        "Albe\u0219ti"
    ],
    "name:ita_x_preferred":[
        "Albe\u0219ti"
    ],
    "name:msa_x_preferred":[
        "Albe\u0219ti"
    ],
    "name:nld_x_preferred":[
        "Albe\u0219ti"
    ],
    "name:por_x_preferred":[
        "Albe\u0219ti"
    ],
    "name:ron_x_preferred":[
        "Comuna Albe\u0219ti"
    ],
    "name:srp_x_preferred":[
        "\u041e\u043f\u0448\u0442\u0438\u043d\u0430 \u0410\u043b\u0431\u0435\u0448\u0442\u0438"
    ],
    "name:ukr_x_preferred":[
        "\u0410\u043b\u0431\u0435\u0448\u0442\u044c"
    ],
    "name:vie_x_preferred":[
        "Albe\u0219ti"
    ],
    "name:zho_x_preferred":[
        "\u963f\u723e\u8c9d\u4ec0\u8482\u9109"
    ],
    "wof:name":"Albesti",
    "wof:placetype":"locality",
    "wof:population":239
},
  "geometry": {"coordinates":[27.55285,46.69613],"type":"Point"}
}