{
  "type": "Feature",
  "properties": {
    "gn:admin1_code":"04",
    "gn:admin2_code":"24187.0",
    "gn:asciiname":"Motoc",
    "gn:country_code":"RO",
    "gn:dem":191,
    "gn:feature_class":"P",
    "gn:feature_code":"PPL",
    "gn:name":"Motoc",
    "gn:population":133,
    "gn:timezone":"Europe/Bucharest",
    "iso:country":"RO",
    "name:deu_x_preferred":[
        "Motoc"
    ],
    "name:ron_x_preferred":[
        "Motoc"
    ],
    "wof:name":"Motoc",
    "wof:placetype":"locality",
    "wof:population":133
},
  "geometry": {"coordinates":[27.09916,46.36381],"type":"Point"}
}