{
  "type": "Feature",
  "properties": {
    "gn:admin1_code":"28",
    "gn:admin2_code":"124493.0",
    "gn:asciiname":"Schitu-Tarcau",
    "gn:country_code":"RO",
    "gn:dem":399,
    "gn:feature_class":"P",
    "gn:feature_code":"PPL",
    "gn:name":"Schitu-Tarc\u0103u",
    "gn:population":0,
    "gn:timezone":"Europe/Bucharest",
    "iso:country":"RO",
    "name:und_x_variant":[
        "Schit",
        "Schitu-Tarc\u0103u"
    ],
    "wof:name":"Schitu-Tarcau",
    "wof:placetype":"locality"
},
  "geometry": {"coordinates":[26.13333,46.88333],"type":"Point"}
}