{
  "type": "Feature",
  "properties": {
    "gn:admin1_code":"08",
    "gn:admin2_code":"43992.0",
    "gn:asciiname":"Cotu Mihalea",
    "gn:cc2":"RO",
    "gn:country_code":"RO",
    "gn:dem":7,
    "gn:feature_class":"P",
    "gn:feature_code":"PPL",
    "gn:name":"Cotu Mihalea",
    "gn:population":98,
    "gn:timezone":"Europe/Bucharest",
    "iso:country":"RO",
    "name:und_x_variant":[
        "Cotul-Mihalea",
        "Cotu Mihalea"
    ],
    "wof:name":"Cotu Mihalea",
    "wof:placetype":"locality",
    "wof:population":98
},
  "geometry": {"coordinates":[27.83999,45.39707],"type":"Point"}
}