{
  "type": "Feature",
  "properties": {
    "gn:admin1_code":"04",
    "gn:admin2_code":"23494.0",
    "gn:asciiname":"Praja",
    "gn:country_code":"RO",
    "gn:dem":326,
    "gn:feature_class":"P",
    "gn:feature_code":"PPL",
    "gn:name":"Praja",
    "gn:population":209,
    "gn:timezone":"Europe/Bucharest",
    "iso:country":"RO",
    "name:mal_x_preferred":[
        "\u0d2a\u0d4d\u0d30\u0d1c"
    ],
    "wof:name":"Praja",
    "wof:placetype":"locality",
    "wof:population":209
},
  "geometry": {"coordinates":[27.42198,46.33673],"type":"Point"}
}