{
  "type": "Feature",
  "properties": {
    "gn:admin1_code":"39",
    "gn:admin2_code":"173533.0",
    "gn:asciiname":"Dianu",
    "gn:cc2":"RO",
    "gn:country_code":"RO",
    "gn:dem":585,
    "gn:feature_class":"P",
    "gn:feature_code":"PPL",
    "gn:name":"Dianu",
    "gn:population":619,
    "gn:timezone":"Europe/Bucharest",
    "iso:country":"RO",
    "name:und_x_variant":[
        "Dianul",
        "Dianu"
    ],
    "wof:name":"Dianu",
    "wof:placetype":"locality",
    "wof:population":619
},
  "geometry": {"coordinates":[23.94325,45.08614],"type":"Point"}
}