{
  "type": "Feature",
  "properties": {
    "gn:admin1_code":"03",
    "gn:admin2_code":"14405.0",
    "gn:asciiname":"Otelu",
    "gn:cc2":"RO",
    "gn:country_code":"RO",
    "gn:dem":733,
    "gn:feature_class":"P",
    "gn:feature_code":"PPL",
    "gn:name":"O\u021belu",
    "gn:population":130,
    "gn:timezone":"Europe/Bucharest",
    "iso:country":"RO",
    "name:und_x_variant":[
        "O\u0163elul",
        "O\u0163elu"
    ],
    "wof:name":"Otelu",
    "wof:placetype":"locality",
    "wof:population":130
},
  "geometry": {"coordinates":[24.95428,45.2541],"type":"Point"}
}