{
  "type": "Feature",
  "properties": {
    "gn:admin1_code":"30",
    "gn:admin2_code":"132896.0",
    "gn:asciiname":"Poiana Mierlei",
    "gn:country_code":"RO",
    "gn:dem":552,
    "gn:feature_class":"P",
    "gn:feature_code":"PPL",
    "gn:name":"Poiana Mierlei",
    "gn:population":139,
    "gn:timezone":"Europe/Bucharest",
    "iso:country":"RO",
    "wof:name":"Poiana Mierlei",
    "wof:placetype":"locality",
    "wof:population":139
},
  "geometry": {"coordinates":[26.11025,45.26613],"type":"Point"}
}