{
  "type": "Feature",
  "properties": {
    "gn:admin1_code":"15",
    "gn:admin2_code":"63688.0",
    "gn:asciiname":"Lopata",
    "gn:country_code":"RO",
    "gn:dem":687,
    "gn:feature_class":"P",
    "gn:feature_code":"PPL",
    "gn:name":"Lopata",
    "gn:population":0,
    "gn:timezone":"Europe/Bucharest",
    "iso:country":"RO",
    "name:bos_x_preferred":[
        "Lopata"
    ],
    "name:bul_x_preferred":[
        "\u041b\u043e\u043f\u0430\u0442\u0430"
    ],
    "name:ceb_x_preferred":[
        "Lopata"
    ],
    "name:ita_x_preferred":[
        "Lopata"
    ],
    "name:nld_x_preferred":[
        "Lopata"
    ],
    "name:pol_x_preferred":[
        "Lopata"
    ],
    "name:ron_x_preferred":[
        "Lopata"
    ],
    "name:slv_x_preferred":[
        "Lopata"
    ],
    "name:ukr_x_preferred":[
        "\u041b\u043e\u043f\u0430\u0442\u0430"
    ],
    "wof:name":"Lopata",
    "wof:placetype":"locality"
},
  "geometry": {"coordinates":[26.06667,45.65],"type":"Point"}
}