{
  "type": "Feature",
  "properties": {
    "gn:admin1_code":"22",
    "gn:admin2_code":"105026.0",
    "gn:asciiname":"Catrunesti",
    "gn:cc2":"RO",
    "gn:country_code":"RO",
    "gn:dem":73,
    "gn:feature_class":"P",
    "gn:feature_code":"PPL",
    "gn:name":"C\u0103trune\u0219ti",
    "gn:population":355,
    "gn:timezone":"Europe/Bucharest",
    "iso:country":"RO",
    "name:und_x_variant":[
        "C\u0103trune\u015fti-M\u0103ineasca",
        "C\u0103trune\u015ftii",
        "C\u0103trune\u015fti"
    ],
    "wof:name":"Catrunesti",
    "wof:placetype":"locality",
    "wof:population":355
},
  "geometry": {"coordinates":[26.3912,44.55686],"type":"Point"}
}