{
  "type": "Feature",
  "properties": {
    "gn:admin1_code":"11",
    "gn:admin2_code":"48771.0",
    "gn:asciiname":"Zilisteanca",
    "gn:cc2":"RO",
    "gn:country_code":"RO",
    "gn:dem":152,
    "gn:feature_class":"P",
    "gn:feature_code":"PPL",
    "gn:name":"Zili\u0219teanca",
    "gn:population":760,
    "gn:timezone":"Europe/Bucharest",
    "iso:country":"RO",
    "name:und_x_variant":[
        "Zili\u015ftenca",
        "Zili\u015fteanca"
    ],
    "wof:name":"Zilisteanca",
    "wof:placetype":"locality",
    "wof:population":760
},
  "geometry": {"coordinates":[26.87032,45.24955],"type":"Point"}
}