{
  "type": "Feature",
  "properties": {
    "gn:admin1_code":"04",
    "gn:admin2_code":"24631.0",
    "gn:asciiname":"Cornetelu",
    "gn:country_code":"RO",
    "gn:dem":442,
    "gn:feature_class":"P",
    "gn:feature_code":"PPL",
    "gn:name":"Corne\u0163elu",
    "gn:population":0,
    "gn:timezone":"Europe/Bucharest",
    "iso:country":"RO",
    "wof:name":"Cornetelu",
    "wof:placetype":"locality"
},
  "geometry": {"coordinates":[26.56667,46.48333],"type":"Point"}
}