{
  "type": "Feature",
  "properties": {
    "gn:admin1_code":"28",
    "gn:admin2_code":"121055",
    "gn:asciiname":"Humulestii Noi",
    "gn:country_code":"RO",
    "gn:dem":408,
    "gn:feature_class":"P",
    "gn:feature_code":"PPL",
    "gn:name":"Humule\u0219tii Noi",
    "gn:population":481,
    "gn:timezone":"Europe/Bucharest",
    "iso:country":"RO",
    "wof:name":"Humulestii Noi",
    "wof:placetype":"locality",
    "wof:population":481
},
  "geometry": {"coordinates":[26.33568,47.18557],"type":"Point"}
}