{
  "type": "Feature",
  "properties": {
    "gn:admin1_code":"23",
    "gn:admin2_code":"96940.0",
    "gn:asciiname":"Pausesti",
    "gn:country_code":"RO",
    "gn:dem":108,
    "gn:feature_class":"P",
    "gn:feature_code":"PPL",
    "gn:name":"P\u0103u\u0219e\u0219ti",
    "gn:population":1506,
    "gn:timezone":"Europe/Bucharest",
    "iso:country":"RO",
    "wof:name":"Pausesti",
    "wof:placetype":"locality",
    "wof:population":1506
},
  "geometry": {"coordinates":[27.32594,47.1581],"type":"Point"}
}