{
  "type": "Feature",
  "properties": {
    "gn:admin1_code":"28",
    "gn:admin2_code":"124233",
    "gn:asciiname":"Basta",
    "gn:country_code":"RO",
    "gn:dem":182,
    "gn:feature_class":"P",
    "gn:feature_code":"PPL",
    "gn:name":"Ba\u0219ta",
    "gn:population":680,
    "gn:timezone":"Europe/Bucharest",
    "iso:country":"RO",
    "name:ces_x_preferred":[
        "Basta"
    ],
    "name:chv_x_preferred":[
        "\u0411\u0430\u0441\u0442\u0430"
    ],
    "name:dan_x_preferred":[
        "Basta"
    ],
    "name:deu_x_preferred":[
        "Basta"
    ],
    "name:ell_x_preferred":[
        "\u039c\u03c0\u03ac\u03c3\u03c4\u03b1"
    ],
    "name:fra_x_preferred":[
        "Basta"
    ],
    "name:ita_x_preferred":[
        "Basta"
    ],
    "name:nld_x_preferred":[
        "Basta"
    ],
    "name:por_x_preferred":[
        "Basta"
    ],
    "name:rus_x_preferred":[
        "\u0411\u0430\u0441\u0442\u0430"
    ],
    "name:spa_x_preferred":[
        "Basta"
    ],
    "name:ukr_x_preferred":[
        "\u0411\u0430\u0441\u0442\u0430"
    ],
    "wof:name":"Basta",
    "wof:placetype":"locality",
    "wof:population":680
},
  "geometry": {"coordinates":[26.91337,46.86546],"type":"Point"}
}