{
  "type": "Feature",
  "properties": {
    "gn:admin1_code":"28",
    "gn:admin2_code":"124233",
    "gn:asciiname":"Basta",
    "gn:country_code":"RO",
    "gn:dem":182,
    "gn:feature_class":"P",
    "gn:feature_code":"PPL",
    "gn:name":"Ba\u0219ta",
    "gn:population":680,
    "gn:timezone":"Europe/Bucharest",
    "iso:country":"RO",
    "wof:name":"Basta",
    "wof:placetype":"locality",
    "wof:population":680
},
  "geometry": {"coordinates":[26.91337,46.86546],"type":"Point"}
}