{
  "type": "Feature",
  "properties": {
    "gn:admin1_code":"01",
    "gn:admin2_code":"6627.0",
    "gn:asciiname":"Vladesti",
    "gn:cc2":"RO",
    "gn:country_code":"RO",
    "gn:dem":697,
    "gn:feature_class":"P",
    "gn:feature_code":"PPL",
    "gn:name":"Vl\u0103de\u0219ti",
    "gn:population":52,
    "gn:timezone":"Europe/Bucharest",
    "iso:country":"RO",
    "name:und_x_variant":[
        "R\u00e2met Vl\u0103de\u015fti",
        "Vl\u0103de\u015fti"
    ],
    "wof:name":"Vladesti",
    "wof:placetype":"locality",
    "wof:population":52
},
  "geometry": {"coordinates":[23.56063,46.30899],"type":"Point"}
}