{
  "type": "Feature",
  "properties": {
    "gn:admin1_code":"34",
    "gn:admin2_code":"148328.0",
    "gn:asciiname":"Lucacesti",
    "gn:country_code":"RO",
    "gn:dem":450,
    "gn:feature_class":"P",
    "gn:feature_code":"PPL",
    "gn:name":"Luc\u0103ce\u0219ti",
    "gn:population":306,
    "gn:timezone":"Europe/Bucharest",
    "iso:country":"RO",
    "wof:name":"Lucacesti",
    "wof:placetype":"locality",
    "wof:population":306
},
  "geometry": {"coordinates":[26.10681,47.53162],"type":"Point"}
}