{
  "type": "Feature",
  "properties": {
    "gn:admin1_code":"13",
    "gn:admin2_code":"58008.0",
    "gn:asciiname":"Cacova Ierii",
    "gn:country_code":"RO",
    "gn:dem":549,
    "gn:feature_class":"P",
    "gn:feature_code":"PPL",
    "gn:name":"Cacova Ierii",
    "gn:population":592,
    "gn:timezone":"Europe/Bucharest",
    "iso:country":"RO",
    "wof:name":"Cacova Ierii",
    "wof:placetype":"locality",
    "wof:population":592
},
  "geometry": {"coordinates":[23.47456,46.54353],"type":"Point"}
}