{
  "type": "Feature",
  "properties": {
    "gn:admin1_code":"27",
    "gn:admin2_code":"120370.0",
    "gn:asciiname":"Gaura Sangerului",
    "gn:country_code":"RO",
    "gn:dem":304,
    "gn:feature_class":"P",
    "gn:feature_code":"PPL",
    "gn:name":"Gaura S\u00e2ngerului",
    "gn:population":119,
    "gn:timezone":"Europe/Bucharest",
    "iso:country":"RO",
    "wof:name":"Gaura Sangerului",
    "wof:placetype":"locality",
    "wof:population":119
},
  "geometry": {"coordinates":[24.12696,46.60115],"type":"Point"}
}