{
  "type": "Feature",
  "properties": {
    "gn:admin1_code":"05",
    "gn:admin2_code":"30229.0",
    "gn:asciiname":"Ucuris",
    "gn:country_code":"RO",
    "gn:dem":152,
    "gn:feature_class":"P",
    "gn:feature_code":"PPL",
    "gn:name":"Ucuri\u0219",
    "gn:population":647,
    "gn:timezone":"Europe/Bucharest",
    "iso:country":"RO",
    "wof:name":"Ucuris",
    "wof:placetype":"locality",
    "wof:population":647
},
  "geometry": {"coordinates":[21.95763,46.63716],"type":"Point"}
}