{
  "type": "Feature",
  "properties": {
    "gn:admin1_code":"40",
    "gn:admin2_code":"175260.0",
    "gn:asciiname":"Iugani",
    "gn:cc2":"RO",
    "gn:country_code":"RO",
    "gn:dem":135,
    "gn:feature_class":"P",
    "gn:feature_code":"PPL",
    "gn:name":"Iugani",
    "gn:population":256,
    "gn:timezone":"Europe/Bucharest",
    "iso:country":"RO",
    "name:und_x_variant":[
        "Juganii",
        "Iugani"
    ],
    "wof:name":"Iugani",
    "wof:placetype":"locality",
    "wof:population":256
},
  "geometry": {"coordinates":[27.43446,46.14975],"type":"Point"}
}