{
  "type": "Feature",
  "properties": {
    "gn:admin1_code":"31",
    "gn:admin2_code":"139740.0",
    "gn:asciiname":"Motis",
    "gn:country_code":"RO",
    "gn:dem":196,
    "gn:feature_class":"P",
    "gn:feature_code":"PPL",
    "gn:name":"Moti\u015f",
    "gn:population":0,
    "gn:timezone":"Europe/Bucharest",
    "iso:country":"RO",
    "wof:name":"Motis",
    "wof:placetype":"locality"
},
  "geometry": {"coordinates":[23.13772,47.42437],"type":"Point"}
}