{
  "type": "Feature",
  "properties": {
    "gn:admin1_code":"38",
    "gn:admin2_code":"163253.0",
    "gn:asciiname":"Rascani",
    "gn:country_code":"RO",
    "gn:dem":323,
    "gn:feature_class":"P",
    "gn:feature_code":"PPL",
    "gn:name":"R\u0103\u0219cani",
    "gn:population":82,
    "gn:timezone":"Europe/Bucharest",
    "iso:country":"RO",
    "wof:name":"Rascani",
    "wof:placetype":"locality",
    "wof:population":82
},
  "geometry": {"coordinates":[27.63307,46.85606],"type":"Point"}
}