{
  "type": "Feature",
  "properties": {
    "gn:admin1_code":"18",
    "gn:admin2_code":"75515.0",
    "gn:asciiname":"Dorasti",
    "gn:country_code":"RO",
    "gn:dem":27,
    "gn:feature_class":"P",
    "gn:feature_code":"PPL",
    "gn:name":"Dor\u0103\u015fti",
    "gn:population":0,
    "gn:timezone":"Europe/Bucharest",
    "iso:country":"RO",
    "wof:name":"Dorasti",
    "wof:placetype":"locality"
},
  "geometry": {"coordinates":[27.46667,45.76667],"type":"Point"}
}