{
  "type": "Feature",
  "properties": {
    "gn:admin1_code":"38",
    "gn:admin2_code":"166235.0",
    "gn:asciiname":"Focseasca",
    "gn:cc2":"RO",
    "gn:country_code":"RO",
    "gn:dem":214,
    "gn:feature_class":"P",
    "gn:feature_code":"PPL",
    "gn:name":"Foc\u0219ea\u0219ca",
    "gn:population":610,
    "gn:timezone":"Europe/Bucharest",
    "iso:country":"RO",
    "name:und_x_variant":[
        "Foc\u015fasca",
        "Foc\u015feasca"
    ],
    "wof:name":"Focseasca",
    "wof:placetype":"locality",
    "wof:population":610
},
  "geometry": {"coordinates":[27.63297,46.93331],"type":"Point"}
}