{
  "type": "Feature",
  "properties": {
    "gn:country":"RO",
    "gn:fcode":"PPLA2",
    "gn:population":2418,
    "iso:country":"RO",
    "name:ceb_x_preferred":[
        "Dragomire\u0219ti"
    ],
    "name:eng_x_preferred":[
        "Dragomire\u0219ti"
    ],
    "name:fra_x_preferred":[
        "Dragomire\u0219ti"
    ],
    "name:ita_x_preferred":[
        "Dragomire\u0219ti"
    ],
    "name:nld_x_preferred":[
        "Dragomire\u0219ti"
    ],
    "name:por_x_preferred":[
        "Dragomire\u0219ti"
    ],
    "name:ron_x_preferred":[
        "Dragomire\u0219ti"
    ],
    "name:srp_x_preferred":[
        "\u0414\u0440\u0430\u0433\u043e\u043c\u0438\u0440\u0435\u0448\u0442\u0438"
    ],
    "name:ukr_x_preferred":[
        "\u0414\u0440\u0430\u0433\u043e\u043c\u0456\u0440\u0435\u0448\u0442\u044c"
    ],
    "name:und_x_variant":[
        "Dr\u0103gomirosti"
    ],
    "name:vol_x_preferred":[
        "Dragomire\u0219ti"
    ],
    "qs_pg:aaroncc":"RO",
    "qs_pg:gn_country":"RO",
    "qs_pg:gn_fcode":"PPLA2",
    "qs_pg:gn_pop":2418,
    "qs_pg:name":"Dragomire\u015fti",
    "qs_pg:photos_9r":0,
    "qs_pg:photos_sr":0,
    "qs_pg:pop_sr":4,
    "qs_pg:qs_pg_placetype":"locality",
    "wof:name":"Dragomire\u015fti",
    "wof:placetype":"locality",
    "wof:population":2418
},
  "geometry": {"coordinates":[26.53333,47.01667],"type":"Point"}
}