{
  "type": "Feature",
  "properties": {
    "gn:admin1_code":"05",
    "gn:admin2_code":"27846.0",
    "gn:asciiname":"Teleac",
    "gn:country_code":"RO",
    "gn:dem":285,
    "gn:feature_class":"P",
    "gn:feature_code":"PPL",
    "gn:name":"Teleac",
    "gn:population":0,
    "gn:timezone":"Europe/Bucharest",
    "iso:country":"RO",
    "name:ceb_x_preferred":[
        "Teleac"
    ],
    "name:deu_x_preferred":[
        "Teleac"
    ],
    "name:epo_x_preferred":[
        "Teleac"
    ],
    "name:hun_x_preferred":[
        "Teleac"
    ],
    "name:ron_x_preferred":[
        "Teleac"
    ],
    "name:srp_x_preferred":[
        "\u0422\u0435\u0459\u0430\u043a"
    ],
    "name:und_x_variant":[
        "Telek"
    ],
    "wof:name":"Teleac",
    "wof:placetype":"locality"
},
  "geometry": {"coordinates":[22.43333,46.65],"type":"Point"}
}