{
  "type": "Feature",
  "properties": {
    "gn:admin1_code":"28",
    "gn:admin2_code":"124563.0",
    "gn:asciiname":"Neagra",
    "gn:cc2":"RO",
    "gn:country_code":"RO",
    "gn:dem":543,
    "gn:feature_class":"P",
    "gn:feature_code":"PPL",
    "gn:name":"Neagra",
    "gn:population":557,
    "gn:timezone":"Europe/Bucharest",
    "iso:country":"RO",
    "name:ceb_x_preferred":[
        "Neagra"
    ],
    "name:deu_x_preferred":[
        "Neagra"
    ],
    "name:epo_x_preferred":[
        "Neagra"
    ],
    "name:swe_x_preferred":[
        "Neagra"
    ],
    "name:und_x_variant":[
        "Negra",
        "Neagra"
    ],
    "wof:name":"Neagra",
    "wof:placetype":"locality",
    "wof:population":557
},
  "geometry": {"coordinates":[25.98442,46.88046],"type":"Point"}
}