{
  "type": "Feature",
  "properties": {
    "gn:admin1_code":"28",
    "gn:admin2_code":"122025.0",
    "gn:asciiname":"Fartigi",
    "gn:cc2":"RO",
    "gn:country_code":"RO",
    "gn:dem":655,
    "gn:feature_class":"P",
    "gn:feature_code":"PPL",
    "gn:name":"F\u00e2r\u0163igi",
    "gn:population":0,
    "gn:timezone":"Europe/Bucharest",
    "iso:country":"RO",
    "name:und_x_variant":[
        "F\u00e2rt\u00e2gi",
        "F\u00eer\u0163igi"
    ],
    "wof:name":"Fartigi",
    "wof:placetype":"locality"
},
  "geometry": {"coordinates":[26.03333,47.01667],"type":"Point"}
}