{
  "type": "Feature",
  "properties": {
    "gn:admin1_code":"26",
    "gn:admin2_code":"111444",
    "gn:asciiname":"Aurora",
    "gn:country_code":"RO",
    "gn:dem":61,
    "gn:feature_class":"P",
    "gn:feature_code":"PPL",
    "gn:name":"Aurora",
    "gn:population":860,
    "gn:timezone":"Europe/Bucharest",
    "iso:country":"RO",
    "wof:name":"Aurora",
    "wof:placetype":"locality",
    "wof:population":860
},
  "geometry": {"coordinates":[22.93916,44.19285],"type":"Point"}
}