{
  "type": "Feature",
  "properties": {
    "gn:admin1_code":"27",
    "gn:admin2_code":"118753.0",
    "gn:asciiname":"Galateni",
    "gn:cc2":"RO",
    "gn:country_code":"RO",
    "gn:dem":331,
    "gn:feature_class":"P",
    "gn:feature_code":"PPL",
    "gn:name":"G\u0103l\u0103\u0163eni",
    "gn:population":0,
    "gn:timezone":"Europe/Bucharest",
    "iso:country":"RO",
    "name:und_x_variant":[
        "Szentgerice"
    ],
    "wof:name":"Galateni",
    "wof:placetype":"locality"
},
  "geometry": {"coordinates":[24.70602,46.47274],"type":"Point"}
}