{
  "type": "Feature",
  "properties": {
    "gn:admin1_code":"28",
    "gn:admin2_code":"123521",
    "gn:asciiname":"Leghin",
    "gn:country_code":"RO",
    "gn:dem":494,
    "gn:feature_class":"P",
    "gn:feature_code":"PPL",
    "gn:name":"Leghin",
    "gn:population":675,
    "gn:timezone":"Europe/Bucharest",
    "iso:country":"RO",
    "wof:name":"Leghin",
    "wof:placetype":"locality",
    "wof:population":675
},
  "geometry": {"coordinates":[26.19837,47.22521],"type":"Point"}
}