{
  "type": "Feature",
  "properties": {
    "gn:admin1_code":"28",
    "gn:admin2_code":"122828.0",
    "gn:asciiname":"Garcinita",
    "gn:country_code":"RO",
    "gn:dem":587,
    "gn:feature_class":"P",
    "gn:feature_code":"PPL",
    "gn:name":"G\u00e2rcini\u0163a",
    "gn:population":0,
    "gn:timezone":"Europe/Bucharest",
    "iso:country":"RO",
    "wof:name":"Garcinita",
    "wof:placetype":"locality"
},
  "geometry": {"coordinates":[26.33333,46.96667],"type":"Point"}
}