{
  "type": "Feature",
  "properties": {
    "gn:admin1_code":"26",
    "gn:admin2_code":"111097.0",
    "gn:asciiname":"Valea Cosustei",
    "gn:cc2":"RO",
    "gn:country_code":"RO",
    "gn:dem":193,
    "gn:feature_class":"P",
    "gn:feature_code":"PPL",
    "gn:name":"Valea Co\u0219u\u0219tei",
    "gn:population":205,
    "gn:timezone":"Europe/Bucharest",
    "iso:country":"RO",
    "name:und_x_variant":[
        "Valea Rea",
        "Valea Co\u015fu\u015ftei"
    ],
    "wof:name":"Valea Cosustei",
    "wof:placetype":"locality",
    "wof:population":205
},
  "geometry": {"coordinates":[22.91573,44.70729],"type":"Point"}
}