{
  "type": "Feature",
  "properties": {
    "gn:admin1_code":"05",
    "gn:admin2_code":"29662.0",
    "gn:asciiname":"Miersig",
    "gn:country_code":"RO",
    "gn:dem":131,
    "gn:feature_class":"P",
    "gn:feature_code":"PPL",
    "gn:name":"Miersig",
    "gn:population":436,
    "gn:timezone":"Europe/Bucharest",
    "iso:country":"RO",
    "wof:name":"Miersig",
    "wof:placetype":"locality",
    "wof:population":436
},
  "geometry": {"coordinates":[21.84349,46.88635],"type":"Point"}
}