{
  "type": "Feature",
  "properties": {
    "gn:admin1_code":"12",
    "gn:admin2_code":"52160.0",
    "gn:asciiname":"Zbegu",
    "gn:cc2":"RO",
    "gn:country_code":"RO",
    "gn:dem":673,
    "gn:feature_class":"P",
    "gn:feature_code":"PPL",
    "gn:name":"Zbegu",
    "gn:population":193,
    "gn:timezone":"Europe/Bucharest",
    "iso:country":"RO",
    "name:und_x_variant":[
        "Zbeg",
        "Zbegu"
    ],
    "wof:name":"Zbegu",
    "wof:placetype":"locality",
    "wof:population":193
},
  "geometry": {"coordinates":[22.41235,45.09258],"type":"Point"}
}