{
  "type": "Feature",
  "properties": {
    "gn:admin1_code":"17",
    "gn:admin2_code":"72221",
    "gn:asciiname":"Booveni",
    "gn:country_code":"RO",
    "gn:dem":138,
    "gn:feature_class":"P",
    "gn:feature_code":"PPL",
    "gn:name":"Booveni",
    "gn:population":383,
    "gn:timezone":"Europe/Bucharest",
    "iso:country":"RO",
    "wof:name":"Booveni",
    "wof:placetype":"locality",
    "wof:population":383
},
  "geometry": {"coordinates":[23.83333,44.08333],"type":"Point"}
}