{
  "type": "Feature",
  "properties": {
    "iso:country":"RO",
    "name:eng_x_preferred":[
        "Piscul"
    ],
    "name:eng_x_variant":[
        "Piscul"
    ],
    "name:fra_x_preferred":[
        "Piscu"
    ],
    "name:hbs_x_preferred":[
        "Op\u0161tina Piscu"
    ],
    "name:ita_x_preferred":[
        "Piscu"
    ],
    "name:msa_x_preferred":[
        "Piscu"
    ],
    "name:nld_x_preferred":[
        "Piscu"
    ],
    "name:por_x_preferred":[
        "Piscu"
    ],
    "name:ron_x_preferred":[
        "Comuna Piscu"
    ],
    "name:rum_x_preferred":[
        "Piscu"
    ],
    "name:ukr_x_preferred":[
        "\u041f\u0456\u0441\u043a\u0443"
    ],
    "name:unk_x_variant":[
        "Piscul",
        "Piscu"
    ],
    "name:vie_x_preferred":[
        "Piscu"
    ],
    "name:vol_x_preferred":[
        "Piscu"
    ],
    "qs:gn_adm0_cc":"RO",
    "qs:gn_fcode":"PPLX",
    "qs:gn_local":683902,
    "qs:gn_nam_loc":"Braila, Br\u0103ila, RO",
    "qs:gn_namadm1":"00",
    "qs:gn_name":"Piscu",
    "qs:local_max":321,
    "qs:local_sum":530,
    "qs:localhoods":3,
    "qs:name":"Piscu",
    "qs:name_adm0":"Rom\u00e2nia",
    "qs:name_adm1":"Braila",
    "qs:name_en":"Piscul",
    "qs:name_local":"Br\u0103ila",
    "qs:photo_max":69,
    "qs:photo_sum":80,
    "qs:placetype":"Suburb",
    "qs:quad_count":6,
    "qs:woe_adm0":23424933,
    "qs:woe_adm1":2346622,
    "qs:woe_adm2":0,
    "qs:woe_lau":0,
    "qs:woe_local":867987,
    "qs:woe_ver":"7.10.0",
    "wd:wordcount":76,
    "wof:lang":[
        "rum"
    ],
    "wof:name":"Piscu",
    "wof:placetype":"neighbourhood"
},
  "geometry": {"coordinates":[27.962626,45.30306],"type":"Point"}
}