{
  "type": "Feature",
  "properties": {
    "gn:admin1_code":"18",
    "gn:admin2_code":"76317.0",
    "gn:asciiname":"Tamaoani",
    "gn:country_code":"RO",
    "gn:dem":38,
    "gn:feature_class":"P",
    "gn:feature_code":"PPL",
    "gn:name":"T\u0103m\u0103oani",
    "gn:population":950,
    "gn:timezone":"Europe/Bucharest",
    "iso:country":"RO",
    "wof:name":"Tamaoani",
    "wof:placetype":"locality",
    "wof:population":950
},
  "geometry": {"coordinates":[28.07486,45.6795],"type":"Point"}
}