{
  "type": "Feature",
  "properties": {
    "gn:admin1_code":"34",
    "gn:admin2_code":"150702.0",
    "gn:asciiname":"Magura",
    "gn:country_code":"RO",
    "gn:dem":1051,
    "gn:feature_class":"P",
    "gn:feature_code":"PPL",
    "gn:name":"M\u0103gura",
    "gn:population":387,
    "gn:timezone":"Europe/Bucharest",
    "iso:country":"RO",
    "name:ceb_x_preferred":[
        "Magura"
    ],
    "name:ces_x_preferred":[
        "Magura"
    ],
    "name:deu_x_preferred":[
        "Magura"
    ],
    "name:epo_x_preferred":[
        "Magura"
    ],
    "name:nld_x_preferred":[
        "Magura"
    ],
    "name:pol_x_preferred":[
        "Magura"
    ],
    "name:ron_x_preferred":[
        "Magura"
    ],
    "name:rus_x_preferred":[
        "\u041c\u0430\u0433\u0443\u0440\u0430"
    ],
    "name:slk_x_preferred":[
        "Magura"
    ],
    "name:srp_x_preferred":[
        "\u041c\u0430\u0433\u0443\u0440\u0430"
    ],
    "name:swe_x_preferred":[
        "Magura"
    ],
    "name:ukr_x_preferred":[
        "\u041c\u0430\u0491\u0443\u0440\u0430"
    ],
    "wof:name":"Magura",
    "wof:placetype":"locality",
    "wof:population":387
},
  "geometry": {"coordinates":[25.23565,47.82187],"type":"Point"}
}