{
  "type": "Feature",
  "properties": {
    "gn:admin1_code":"19",
    "gn:admin2_code":"81264.0",
    "gn:asciiname":"Sardanesti",
    "gn:country_code":"RO",
    "gn:dem":149,
    "gn:feature_class":"P",
    "gn:feature_code":"PPL",
    "gn:name":"S\u0103rd\u0103ne\u0219ti",
    "gn:population":813,
    "gn:timezone":"Europe/Bucharest",
    "iso:country":"RO",
    "wof:name":"Sardanesti",
    "wof:placetype":"locality",
    "wof:population":813
},
  "geometry": {"coordinates":[23.36087,44.77086],"type":"Point"}
}