{
  "type": "Feature",
  "properties": {
    "gn:admin1_code":"05",
    "gn:admin2_code":"28941.0",
    "gn:asciiname":"Cresuia",
    "gn:country_code":"RO",
    "gn:dem":322,
    "gn:feature_class":"P",
    "gn:feature_code":"PPL",
    "gn:name":"Cresuia",
    "gn:population":542,
    "gn:timezone":"Europe/Bucharest",
    "iso:country":"RO",
    "wof:name":"Cresuia",
    "wof:placetype":"locality",
    "wof:population":542
},
  "geometry": {"coordinates":[22.48121,46.70906],"type":"Point"}
}