{
  "type": "Feature",
  "properties": {
    "gn:admin1_code":"15",
    "gn:admin2_code":"64639.0",
    "gn:asciiname":"Lunca Ozunului",
    "gn:cc2":"RO",
    "gn:country_code":"RO",
    "gn:dem":505,
    "gn:feature_class":"P",
    "gn:feature_code":"PPL",
    "gn:name":"Lunca Ozunului",
    "gn:population":205,
    "gn:timezone":"Europe/Bucharest",
    "iso:country":"RO",
    "name:und_x_variant":[
        "Vessz\u00f3telep",
        "Ozun-Lunca",
        "Lunca Ozunului"
    ],
    "wof:name":"Lunca Ozunului",
    "wof:placetype":"locality",
    "wof:population":205
},
  "geometry": {"coordinates":[25.83061,45.77184000000001],"type":"Point"}
}