{
  "type": "Feature",
  "properties": {
    "gn:admin1_code":"04",
    "gn:admin2_code":"25148.0",
    "gn:asciiname":"Stufu",
    "gn:country_code":"RO",
    "gn:dem":282,
    "gn:feature_class":"P",
    "gn:feature_code":"PPL",
    "gn:name":"Stufu",
    "gn:population":394,
    "gn:timezone":"Europe/Bucharest",
    "iso:country":"RO",
    "wof:name":"Stufu",
    "wof:placetype":"locality",
    "wof:population":394
},
  "geometry": {"coordinates":[26.76865,46.44017],"type":"Point"}
}