{
  "type": "Feature",
  "properties": {
    "gn:admin1_code":"28",
    "gn:admin2_code":"120968.0",
    "gn:asciiname":"Poenari",
    "gn:country_code":"RO",
    "gn:dem":624,
    "gn:feature_class":"P",
    "gn:feature_code":"PPL",
    "gn:name":"Poenari",
    "gn:population":0,
    "gn:timezone":"Europe/Bucharest",
    "iso:country":"RO",
    "name:srp_x_preferred":[
        "\u041f\u043e\u0435\u043d\u0430\u0440\u0438"
    ],
    "wof:lang_x_official":[
        "ron"
    ],
    "wof:lang_x_spoken":[
        "ron"
    ],
    "wof:name":"Poenari",
    "wof:placetype":"locality"
},
  "geometry": {"coordinates":[26.06667,46.96667],"type":"Point"}
}