{
  "type": "Feature",
  "properties": {
    "gn:admin1_code":"05",
    "gn:admin2_code":"31422.0",
    "gn:asciiname":"Codru",
    "gn:country_code":"RO",
    "gn:dem":369,
    "gn:feature_class":"P",
    "gn:feature_code":"PPL",
    "gn:name":"Codru",
    "gn:population":313,
    "gn:timezone":"Europe/Bucharest",
    "iso:country":"RO",
    "name:deu_x_preferred":[
        "Codru"
    ],
    "name:hun_x_preferred":[
        "Codru"
    ],
    "name:ron_x_preferred":[
        "Codru"
    ],
    "name:rus_x_preferred":[
        "\u041a\u043e\u0434\u0440\u044b"
    ],
    "name:srp_x_preferred":[
        "\u041a\u043e\u0434\u0440\u0443"
    ],
    "name:ukr_x_preferred":[
        "\u041a\u043e\u0434\u0440\u0443"
    ],
    "name:und_x_variant":[
        "Dumbr\u0103vi\u0163a de Codru",
        "Havasdombr\u00f3"
    ],
    "wof:name":"Codru",
    "wof:placetype":"locality",
    "wof:population":313
},
  "geometry": {"coordinates":[22.14519,46.6332],"type":"Point"}
}