{
  "type": "Feature",
  "properties": {
    "gn:admin1_code":"07",
    "gn:admin2_code":"39872.0",
    "gn:asciiname":"Chiscovata",
    "gn:country_code":"RO",
    "gn:dem":392,
    "gn:feature_class":"P",
    "gn:feature_code":"PPL",
    "gn:name":"Chiscovat\u0103",
    "gn:population":0,
    "gn:timezone":"Europe/Bucharest",
    "iso:country":"RO",
    "wof:name":"Chiscovata",
    "wof:placetype":"locality"
},
  "geometry": {"coordinates":[26.65,47.56667],"type":"Point"}
}