{
  "type": "Feature",
  "properties": {
    "gn:admin1_code":"01",
    "gn:admin2_code":"6761.0",
    "gn:asciiname":"Ignatesti",
    "gn:country_code":"RO",
    "gn:dem":739,
    "gn:feature_class":"P",
    "gn:feature_code":"PPL",
    "gn:name":"Ign\u0103\u021be\u0219ti",
    "gn:population":102,
    "gn:timezone":"Europe/Bucharest",
    "iso:country":"RO",
    "wof:name":"Ignatesti",
    "wof:placetype":"locality",
    "wof:population":102
},
  "geometry": {"coordinates":[23.08246,46.30815],"type":"Point"}
}