{
  "type": "Feature",
  "properties": {
    "gn:admin1_code":"02",
    "gn:admin2_code":"9832",
    "gn:asciiname":"Barzesti",
    "gn:country_code":"RO",
    "gn:dem":257,
    "gn:feature_class":"P",
    "gn:feature_code":"PPL",
    "gn:name":"B\u00e2rze\u0219ti",
    "gn:population":184,
    "gn:timezone":"Europe/Bucharest",
    "iso:country":"RO",
    "name:hun_x_preferred":[
        "Barzafalva"
    ],
    "name:und_x_variant":[
        "Barzest",
        "B\u00e2rz\u00e2\u015fti",
        "Barzesd",
        "B\u00eerze\u0219ti"
    ],
    "wof:name":"Barzesti",
    "wof:placetype":"locality",
    "wof:population":184
},
  "geometry": {"coordinates":[22.13333,46.48333],"type":"Point"}
}