{
  "type": "Feature",
  "properties": {
    "gn:admin1_code":"27",
    "gn:admin2_code":"119858.0",
    "gn:asciiname":"Fanate",
    "gn:country_code":"RO",
    "gn:dem":285,
    "gn:feature_class":"P",
    "gn:feature_code":"PPL",
    "gn:name":"F\u00e2na\u021be",
    "gn:population":59,
    "gn:timezone":"Europe/Bucharest",
    "iso:country":"RO",
    "name:hun_x_preferred":[
        "Kincst\u00e1ribirtok"
    ],
    "wof:name":"Fanate",
    "wof:placetype":"locality",
    "wof:population":59
},
  "geometry": {"coordinates":[24.08333,46.56667],"type":"Point"}
}