{
  "type": "Feature",
  "properties": {
    "gn:admin1_code":"12",
    "gn:admin2_code":"51449.0",
    "gn:asciiname":"Drencova",
    "gn:cc2":"RO",
    "gn:country_code":"RO",
    "gn:dem":74,
    "gn:feature_class":"P",
    "gn:feature_code":"PPL",
    "gn:name":"Drencova",
    "gn:population":0,
    "gn:timezone":"Europe/Bucharest",
    "iso:country":"RO",
    "name:und_x_variant":[
        "Portul Drencova",
        "Drenkovo",
        "Drencova"
    ],
    "wof:name":"Drencova",
    "wof:placetype":"locality"
},
  "geometry": {"coordinates":[21.97234,44.63777],"type":"Point"}
}