{
  "type": "Feature",
  "properties": {
    "gn:admin1_code":"03",
    "gn:admin2_code":"19793.0",
    "gn:asciiname":"Varsesti",
    "gn:country_code":"RO",
    "gn:dem":348,
    "gn:feature_class":"P",
    "gn:feature_code":"PPL",
    "gn:name":"V\u00e2r\u0219e\u0219ti",
    "gn:population":160,
    "gn:timezone":"Europe/Bucharest",
    "iso:country":"RO",
    "name:und_x_variant":[
        "V\u0103rsesti",
        "V\u00eer\u015fe\u015fti"
    ],
    "wof:name":"Varsesti",
    "wof:placetype":"locality",
    "wof:population":160
},
  "geometry": {"coordinates":[24.6123,44.77761],"type":"Point"}
}