{
  "type": "Feature",
  "properties": {
    "gn:admin1_code":"26",
    "gn:admin2_code":"111006.0",
    "gn:asciiname":"Pluta",
    "gn:country_code":"RO",
    "gn:dem":140,
    "gn:feature_class":"P",
    "gn:feature_code":"PPL",
    "gn:name":"Pluta",
    "gn:population":533,
    "gn:timezone":"Europe/Bucharest",
    "iso:country":"RO",
    "wof:name":"Pluta",
    "wof:placetype":"locality",
    "wof:population":533
},
  "geometry": {"coordinates":[23.33029,44.57488],"type":"Point"}
}