{
  "type": "Feature",
  "properties": {
    "gn:admin1_code":"19",
    "gn:admin2_code":"82243.0",
    "gn:asciiname":"Tereujani",
    "gn:country_code":"RO",
    "gn:dem":364,
    "gn:feature_class":"P",
    "gn:feature_code":"PPL",
    "gn:name":"Tereujani",
    "gn:population":0,
    "gn:timezone":"Europe/Bucharest",
    "iso:country":"RO",
    "wof:lang_x_official":[
        "ron"
    ],
    "wof:lang_x_spoken":[
        "ron"
    ],
    "wof:name":"Tereujani",
    "wof:placetype":"locality"
},
  "geometry": {"coordinates":[23.75,44.88333],"type":"Point"}
}