{
  "type": "Feature",
  "properties": {
    "gn:admin1_code":"06",
    "gn:admin2_code":"35152.0",
    "gn:asciiname":"Strambulici",
    "gn:country_code":"RO",
    "gn:dem":487,
    "gn:feature_class":"P",
    "gn:feature_code":"PPL",
    "gn:name":"Str\u00e2mbulici",
    "gn:population":0,
    "gn:timezone":"Europe/Bucharest",
    "iso:country":"RO",
    "wof:lang_x_official":[
        "ron"
    ],
    "wof:lang_x_spoken":[
        "ron"
    ],
    "wof:name":"Strambulici",
    "wof:placetype":"locality"
},
  "geometry": {"coordinates":[24.18333,47.38333],"type":"Point"}
}