{
  "type": "Feature",
  "properties": {
    "iso:country":"RO",
    "wof:lang_x_official":[
        "ron"
    ],
    "wof:lang_x_spoken":[
        "ron"
    ],
    "wof:name":"Unirii",
    "wof:placetype":"neighbourhood"
},
  "geometry": {"coordinates":[26.105726,44.429028],"type":"Point"}
}