{
  "type": "Feature",
  "properties": {
    "iso:country":"RO",
    "wof:name":"Unirii",
    "wof:placetype":"neighbourhood"
},
  "geometry": {"coordinates":[26.10572617629052,44.4290278484943],"type":"Point"}
}