{
  "type": "Feature",
  "properties": {
    "gn:admin1_code":"12",
    "gn:asciiname":"Vartopu",
    "gn:country_code":"RO",
    "gn:dem":376,
    "gn:feature_class":"P",
    "gn:feature_code":"PPL",
    "gn:name":"V\u00e2rtopu",
    "gn:population":0,
    "gn:timezone":"Europe/Bucharest",
    "iso:country":"RO",
    "wof:name":"Vartopu",
    "wof:placetype":"locality"
},
  "geometry": {"coordinates":[22.04194,44.59222000000001],"type":"Point"}
}