{
  "type": "Feature",
  "properties": {
    "gn:admin1_code":"16",
    "gn:admin2_code":"66955.0",
    "gn:asciiname":"Slobozia",
    "gn:cc2":"RO",
    "gn:country_code":"RO",
    "gn:dem":160,
    "gn:feature_class":"P",
    "gn:feature_code":"PPL",
    "gn:name":"Slobozia",
    "gn:population":129,
    "gn:timezone":"Europe/Bucharest",
    "iso:country":"RO",
    "name:rus_x_preferred":[
        "\u0421\u043b\u043e\u0431\u043e\u0437\u0438\u044f"
    ],
    "name:und_x_variant":[
        "Colentina-Nou\u0103",
        "Slobozia"
    ],
    "wof:name":"Slobozia",
    "wof:placetype":"locality",
    "wof:population":129
},
  "geometry": {"coordinates":[25.7078,44.72322],"type":"Point"}
}