{
  "type": "Feature",
  "properties": {
    "gn:admin1_code":"26",
    "gn:admin2_code":"111275.0",
    "gn:asciiname":"Imoasa",
    "gn:country_code":"RO",
    "gn:dem":189,
    "gn:feature_class":"P",
    "gn:feature_code":"PPL",
    "gn:name":"Imoasa",
    "gn:population":453,
    "gn:timezone":"Europe/Bucharest",
    "iso:country":"RO",
    "wof:name":"Imoasa",
    "wof:placetype":"locality",
    "wof:population":453
},
  "geometry": {"coordinates":[23.04207,44.71812],"type":"Point"}
}