{
  "type": "Feature",
  "properties": {
    "gn:admin1_code":"04",
    "gn:admin2_code":"21891.0",
    "gn:asciiname":"Spria",
    "gn:cc2":"RO",
    "gn:country_code":"RO",
    "gn:dem":273,
    "gn:feature_class":"P",
    "gn:feature_code":"PPL",
    "gn:name":"Spria",
    "gn:population":221,
    "gn:timezone":"Europe/Bucharest",
    "iso:country":"RO",
    "name:und_x_variant":[
        "Spira de Jos",
        "Spria"
    ],
    "wof:name":"Spria",
    "wof:placetype":"locality",
    "wof:population":221
},
  "geometry": {"coordinates":[27.25954,46.60416],"type":"Point"}
}