{
  "type": "Feature",
  "properties": {
    "gn:admin1_code":"27",
    "gn:admin2_code":"118995.0",
    "gn:asciiname":"Caciulata",
    "gn:country_code":"RO",
    "gn:dem":324,
    "gn:feature_class":"P",
    "gn:feature_code":"PPL",
    "gn:name":"C\u0103ciulata",
    "gn:population":189,
    "gn:timezone":"Europe/Bucharest",
    "iso:country":"RO",
    "wof:name":"Caciulata",
    "wof:placetype":"locality",
    "wof:population":189
},
  "geometry": {"coordinates":[24.40602,46.71513],"type":"Point"}
}