{
  "type": "Feature",
  "properties": {
    "gn:admin1_code":"40",
    "gn:admin2_code":"178545.0",
    "gn:asciiname":"Piscu Radului",
    "gn:cc2":"RO",
    "gn:country_code":"RO",
    "gn:dem":401,
    "gn:feature_class":"P",
    "gn:feature_code":"PPL",
    "gn:name":"Piscu Radului",
    "gn:population":503,
    "gn:timezone":"Europe/Bucharest",
    "iso:country":"RO",
    "name:und_x_variant":[
        "Piscul Radului",
        "Piscu Radului"
    ],
    "wof:name":"Piscu Radului",
    "wof:placetype":"locality",
    "wof:population":503
},
  "geometry": {"coordinates":[26.80713,45.96212],"type":"Point"}
}