{
  "type": "Feature",
  "properties": {
    "gn:admin1_code":"25",
    "gn:admin2_code":"108632.0",
    "gn:asciiname":"Costiui",
    "gn:cc2":"RO",
    "gn:country_code":"RO",
    "gn:dem":388,
    "gn:feature_class":"P",
    "gn:feature_code":"PPL",
    "gn:name":"Co\u0219tiui",
    "gn:population":827,
    "gn:timezone":"Europe/Bucharest",
    "iso:country":"RO",
    "name:und_x_variant":[
        "Co\u015ftini",
        "Co\u015ftiui"
    ],
    "wof:name":"Costiui",
    "wof:placetype":"locality",
    "wof:population":827
},
  "geometry": {"coordinates":[24.03032,47.87931],"type":"Point"}
}