{
  "type": "Feature",
  "properties": {
    "gn:admin1_code":"12",
    "gn:admin2_code":"51243.0",
    "gn:asciiname":"Sat Batran",
    "gn:country_code":"RO",
    "gn:dem":379,
    "gn:feature_class":"P",
    "gn:feature_code":"PPL",
    "gn:name":"Sat B\u0103tr\u00e2n",
    "gn:population":391,
    "gn:timezone":"Europe/Bucharest",
    "iso:country":"RO",
    "name:hun_x_preferred":[
        "\u00d3falu"
    ],
    "wof:name":"Sat Batran",
    "wof:placetype":"locality",
    "wof:population":391
},
  "geometry": {"coordinates":[22.33333,45.23333],"type":"Point"}
}