{
  "type": "Feature",
  "properties": {
    "gn:country":"RO",
    "gn:fcode":"PPL",
    "gn:population":9537,
    "iso:country":"RO",
    "name:eng_x_preferred":[
        "1 Decembrie"
    ],
    "name:fra_x_preferred":[
        "1 Decembrie"
    ],
    "name:hun_x_preferred":[
        "1 Decembrie"
    ],
    "name:ita_x_preferred":[
        "1 Decembrie"
    ],
    "name:nld_x_preferred":[
        "1 Decembrie"
    ],
    "name:ron_x_preferred":[
        "1 Decembrie"
    ],
    "name:srp_x_preferred":[
        "\u041f\u0440\u0438\u043c \u0414\u0435\u0447\u0435\u043c\u0431\u0440\u0438\u0458\u0435"
    ],
    "name:und_x_variant":[
        "Cop\u0103cenii de Sus"
    ],
    "qs_pg:aaroncc":"RO",
    "qs_pg:gn_country":"RO",
    "qs_pg:gn_fcode":"PPL",
    "qs_pg:gn_pop":9537,
    "qs_pg:name":"Prim Decembrie",
    "qs_pg:photos_9r":0,
    "qs_pg:photos_sr":0,
    "qs_pg:pop_sr":5,
    "qs_pg:qs_pg_placetype":"locality",
    "wof:name":"Prim Decembrie",
    "wof:placetype":"locality",
    "wof:population":7817
},
  "geometry": {"coordinates":[26.05806,44.29083],"type":"Point"}
}