{
  "type": "Feature",
  "properties": {
    "gn:gn_country":"RO",
    "gn:gn_fcode":"PPL",
    "gn:gn_pop":9537,
    "gn:population":7817,
    "iso:country":"RO",
    "name:dut_x_preferred":[
        "1 Decembrie"
    ],
    "name:eng_x_preferred":[
        "1 Decembrie"
    ],
    "name:fre_x_preferred":[
        "1 Decembrie"
    ],
    "name:hun_x_preferred":[
        "1 Decembrie"
    ],
    "name:ita_x_preferred":[
        "1 Decembrie"
    ],
    "name:rum_x_preferred":[
        "1 Decembrie"
    ],
    "name:unk_x_variant":[
        "Cop\u0103cenii de Sus"
    ],
    "qs_pg:aaroncc":"RO",
    "qs_pg:gn_country":"RO",
    "qs_pg:gn_fcode":"PPL",
    "qs_pg:gn_pop":9537,
    "qs_pg:name":"Prim Decembrie",
    "qs_pg:photos_9r":0,
    "qs_pg:photos_sr":0,
    "qs_pg:pop_sr":5,
    "qs_pg:qs_pg_placetype":"locality",
    "wof:name":"Prim Decembrie",
    "wof:placetype":"locality",
    "wof:population":7817
},
  "geometry": {"coordinates":[26.05806,44.29083],"type":"Point"}
}