{
  "type": "Feature",
  "properties": {
    "gn:admin1_code":"11",
    "gn:admin2_code":"49153.0",
    "gn:asciiname":"Gagenii de Jos",
    "gn:country_code":"RO",
    "gn:dem":94,
    "gn:feature_class":"P",
    "gn:feature_code":"PPL",
    "gn:name":"G\u0103genii de Jos",
    "gn:population":0,
    "gn:timezone":"Europe/Bucharest",
    "iso:country":"RO",
    "wof:lang_x_official":[
        "ron"
    ],
    "wof:lang_x_spoken":[
        "ron"
    ],
    "wof:name":"Gagenii de Jos",
    "wof:placetype":"locality"
},
  "geometry": {"coordinates":[26.56667,45.01667],"type":"Point"}
}