{
  "type": "Feature",
  "properties": {
    "gn:admin1_code":"11",
    "gn:admin2_code":"48771",
    "gn:asciiname":"Aliceni",
    "gn:country_code":"RO",
    "gn:dem":168,
    "gn:feature_class":"P",
    "gn:feature_code":"PPL",
    "gn:name":"Aliceni",
    "gn:population":535,
    "gn:timezone":"Europe/Bucharest",
    "iso:country":"RO",
    "wof:name":"Aliceni",
    "wof:placetype":"locality",
    "wof:population":535
},
  "geometry": {"coordinates":[26.86402,45.26298],"type":"Point"}
}