{
  "type": "Feature",
  "properties": {
    "gn:admin1_code":"05",
    "gn:admin2_code":"27070.0",
    "gn:asciiname":"Iteu Nou",
    "gn:country_code":"RO",
    "gn:dem":136,
    "gn:feature_class":"P",
    "gn:feature_code":"PPL",
    "gn:name":"Iteu Nou",
    "gn:population":184,
    "gn:timezone":"Europe/Bucharest",
    "iso:country":"RO",
    "wof:name":"Iteu Nou",
    "wof:placetype":"locality",
    "wof:population":184
},
  "geometry": {"coordinates":[22.39175,47.3398],"type":"Point"}
}