{
  "type": "Feature",
  "properties": {
    "gn:admin1_code":"39",
    "gn:admin2_code":"171931",
    "gn:asciiname":"Bogdanesti",
    "gn:country_code":"RO",
    "gn:dem":319,
    "gn:feature_class":"P",
    "gn:feature_code":"PPL",
    "gn:name":"Bogd\u0103ne\u0219ti",
    "gn:population":474,
    "gn:timezone":"Europe/Bucharest",
    "iso:country":"RO",
    "wof:name":"Bogdanesti",
    "wof:placetype":"locality",
    "wof:population":474
},
  "geometry": {"coordinates":[24.05193,45.03398],"type":"Point"}
}