{
  "type": "Feature",
  "properties": {
    "gn:admin1_code":"27",
    "gn:admin2_code":"116867.0",
    "gn:asciiname":"Troita",
    "gn:cc2":"RO",
    "gn:country_code":"RO",
    "gn:dem":343,
    "gn:feature_class":"P",
    "gn:feature_code":"PPL",
    "gn:name":"Troi\u021ba",
    "gn:population":855,
    "gn:timezone":"Europe/Bucharest",
    "iso:country":"RO",
    "name:und_x_variant":[
        "Szentharomsag",
        "Troi\u0163a"
    ],
    "wof:name":"Troita",
    "wof:placetype":"locality",
    "wof:population":855
},
  "geometry": {"coordinates":[24.76977,46.48442],"type":"Point"}
}