{
  "type": "Feature",
  "properties": {
    "gn:admin1_code":"29",
    "gn:admin2_code":"129816.0",
    "gn:asciiname":"Cucueti",
    "gn:country_code":"RO",
    "gn:dem":175,
    "gn:feature_class":"P",
    "gn:feature_code":"PPL",
    "gn:name":"Cucue\u021bi",
    "gn:population":383,
    "gn:timezone":"Europe/Bucharest",
    "iso:country":"RO",
    "wof:name":"Cucueti",
    "wof:placetype":"locality",
    "wof:population":383
},
  "geometry": {"coordinates":[24.34658,44.61192],"type":"Point"}
}