{
  "type": "Feature",
  "properties": {
    "gn:admin1_code":"05",
    "gn:admin2_code":"28816",
    "gn:asciiname":"Bucuroaia",
    "gn:country_code":"RO",
    "gn:dem":371,
    "gn:feature_class":"P",
    "gn:feature_code":"PPL",
    "gn:name":"Bucuroaia",
    "gn:population":555,
    "gn:timezone":"Europe/Bucharest",
    "iso:country":"RO",
    "wof:name":"Bucuroaia",
    "wof:placetype":"locality",
    "wof:population":555
},
  "geometry": {"coordinates":[22.18497,46.92885],"type":"Point"}
}