{
  "type": "Feature",
  "properties": {
    "gn:admin1_code":"04",
    "gn:admin2_code":"24524.0",
    "gn:asciiname":"Lehancea",
    "gn:cc2":"RO",
    "gn:country_code":"RO",
    "gn:dem":232,
    "gn:feature_class":"P",
    "gn:feature_code":"PPL",
    "gn:name":"Lehancea",
    "gn:population":359,
    "gn:timezone":"Europe/Bucharest",
    "iso:country":"RO",
    "name:und_x_variant":[
        "Lehacca",
        "Lehancea"
    ],
    "wof:name":"Lehancea",
    "wof:placetype":"locality",
    "wof:population":359
},
  "geometry": {"coordinates":[27.34556,46.19706],"type":"Point"}
}