{
  "type": "Feature",
  "properties": {
    "gn:admin1_code":"12",
    "gn:admin2_code":"51546",
    "gn:asciiname":"Bolvasnita",
    "gn:cc2":"RO",
    "gn:country_code":"RO",
    "gn:dem":293,
    "gn:feature_class":"P",
    "gn:feature_code":"PPLA2",
    "gn:name":"Bolva\u0219ni\u021ba",
    "gn:population":610,
    "gn:timezone":"Europe/Bucharest",
    "iso:country":"RO",
    "name:ceb_x_preferred":[
        "Comuna Bolva\u0219ni\u021ba"
    ],
    "name:deu_x_preferred":[
        "Bolva\u0219ni\u021ba"
    ],
    "name:epo_x_preferred":[
        "Bolva\u0219ni\u021ba"
    ],
    "name:ita_x_preferred":[
        "Bolva\u0219ni\u021ba"
    ],
    "name:msa_x_preferred":[
        "Bolva\u0219ni\u021ba"
    ],
    "name:nld_x_preferred":[
        "Bolva\u0219ni\u021ba"
    ],
    "name:por_x_preferred":[
        "Bolva\u0219ni\u021ba"
    ],
    "name:ron_x_preferred":[
        "Comuna Bolva\u0219ni\u021ba"
    ],
    "name:srp_x_preferred":[
        "\u041e\u043f\u0448\u0442\u0438\u043d\u0430 \u0411\u043e\u043b\u0432\u0430\u0448\u043d\u0438\u0446\u0430"
    ],
    "name:ukr_x_preferred":[
        "\u0411\u043e\u043b\u0432\u0430\u0448\u043d\u0456\u0446\u0430"
    ],
    "name:und_x_variant":[
        "Bolova\u015fni\u0163a"
    ],
    "name:vie_x_preferred":[
        "Bolva\u0219ni\u021ba"
    ],
    "name:vol_x_preferred":[
        "Bolva\u015fni\u0163a"
    ],
    "name:zho_x_preferred":[
        "\u535a\u723e\u74e6\u4ec0\u5c3c\u5bdf\u9109"
    ],
    "wof:name":"Bolvasnita",
    "wof:placetype":"locality",
    "wof:population":610
},
  "geometry": {"coordinates":[22.31012,45.34558],"type":"Point"}
}