{
  "type": "Feature",
  "properties": {
    "gn:admin1_code":"12",
    "gn:admin2_code":"51546",
    "gn:asciiname":"Bolvasnita",
    "gn:cc2":"RO",
    "gn:country_code":"RO",
    "gn:dem":293,
    "gn:feature_class":"P",
    "gn:feature_code":"PPLA2",
    "gn:name":"Bolva\u0219ni\u021ba",
    "gn:population":610,
    "gn:timezone":"Europe/Bucharest",
    "iso:country":"RO",
    "name:und_x_variant":[
        "Bolova\u015fni\u0163a",
        "Bolva\u015fni\u0163a"
    ],
    "wof:name":"Bolvasnita",
    "wof:placetype":"locality",
    "wof:population":610
},
  "geometry": {"coordinates":[22.31012,45.34558],"type":"Point"}
}