{
  "type": "Feature",
  "properties": {
    "gn:admin1_code":"09",
    "gn:admin2_code":"42236.0",
    "gn:asciiname":"Oltet",
    "gn:cc2":"RO",
    "gn:country_code":"RO",
    "gn:dem":412,
    "gn:feature_class":"P",
    "gn:feature_code":"PPL",
    "gn:name":"Olte\u021b",
    "gn:population":663,
    "gn:timezone":"Europe/Bucharest",
    "iso:country":"RO",
    "name:und_x_variant":[
        "Be\u015fimbac",
        "Olte\u0163"
    ],
    "wof:name":"Oltet",
    "wof:placetype":"locality",
    "wof:population":663
},
  "geometry": {"coordinates":[24.76268,45.80478],"type":"Point"}
}