{
  "type": "Feature",
  "properties": {
    "gn:admin1_code":"08",
    "gn:admin2_code":"43073",
    "gn:asciiname":"Bumbacari",
    "gn:country_code":"RO",
    "gn:dem":41,
    "gn:feature_class":"P",
    "gn:feature_code":"PPL",
    "gn:name":"Bumb\u0103cari",
    "gn:population":63,
    "gn:timezone":"Europe/Bucharest",
    "iso:country":"RO",
    "wof:name":"Bumbacari",
    "wof:placetype":"locality",
    "wof:population":63
},
  "geometry": {"coordinates":[27.45401,44.89554],"type":"Point"}
}