{
  "type": "Feature",
  "properties": {
    "gn:admin1_code":"21",
    "gn:admin2_code":"90663",
    "gn:asciiname":"Bobalna",
    "gn:cc2":"RO",
    "gn:country_code":"RO",
    "gn:dem":207,
    "gn:feature_class":"P",
    "gn:feature_code":"PPL",
    "gn:name":"Bob\u00e2lna",
    "gn:population":529,
    "gn:timezone":"Europe/Bucharest",
    "iso:country":"RO",
    "name:und_x_variant":[
        "Bob\u00e2lna",
        "Bob\u00eelna"
    ],
    "wof:name":"Bobalna",
    "wof:placetype":"locality",
    "wof:population":529
},
  "geometry": {"coordinates":[23.13025,45.87566],"type":"Point"}
}