{
  "type": "Feature",
  "properties": {
    "gn:admin1_code":"40",
    "gn:admin2_code":"175509.0",
    "gn:asciiname":"Maracinesti",
    "gn:country_code":"RO",
    "gn:dem":489,
    "gn:feature_class":"P",
    "gn:feature_code":"PPL",
    "gn:name":"M\u0103r\u0103cine\u015fti",
    "gn:population":0,
    "gn:timezone":"Europe/Bucharest",
    "iso:country":"RO",
    "name:und_x_variant":[
        "M\u0103r\u0103cineni",
        "M\u0103r\u0103cine\u015fti"
    ],
    "wof:name":"Maracinesti",
    "wof:placetype":"locality"
},
  "geometry": {"coordinates":[26.86667000000001,45.55],"type":"Point"}
}