{
  "type": "Feature",
  "properties": {
    "gn:admin1_code":"39",
    "gn:admin2_code":"173132.0",
    "gn:asciiname":"Valea Lunga",
    "gn:country_code":"RO",
    "gn:dem":266,
    "gn:feature_class":"P",
    "gn:feature_code":"PPL",
    "gn:name":"Valea Lung\u0103",
    "gn:population":178,
    "gn:timezone":"Europe/Bucharest",
    "iso:country":"RO",
    "wof:name":"Valea Lunga",
    "wof:placetype":"locality",
    "wof:population":178
},
  "geometry": {"coordinates":[24.05214,44.81052],"type":"Point"}
}