{
  "type": "Feature",
  "properties": {
    "gn:admin1_code":"09",
    "gn:admin2_code":"40544.0",
    "gn:asciiname":"Luta",
    "gn:country_code":"RO",
    "gn:dem":450,
    "gn:feature_class":"P",
    "gn:feature_code":"PPL",
    "gn:name":"Lu\u021ba",
    "gn:population":74,
    "gn:timezone":"Europe/Bucharest",
    "iso:country":"RO",
    "wof:name":"Luta",
    "wof:placetype":"locality",
    "wof:population":74
},
  "geometry": {"coordinates":[24.90872,45.79989000000001],"type":"Point"}
}