{
  "type": "Feature",
  "properties": {
    "gn:admin1_code":"11",
    "gn:admin2_code":"47006.0",
    "gn:asciiname":"Zaplazi",
    "gn:cc2":"RO",
    "gn:country_code":"RO",
    "gn:dem":308,
    "gn:feature_class":"P",
    "gn:feature_code":"PPL",
    "gn:name":"Z\u0103plazi",
    "gn:population":100,
    "gn:timezone":"Europe/Bucharest",
    "iso:country":"RO",
    "name:und_x_variant":[
        "Z\u0103plaz",
        "Z\u0103plazi"
    ],
    "wof:name":"Zaplazi",
    "wof:placetype":"locality",
    "wof:population":100
},
  "geometry": {"coordinates":[26.97396,45.40283],"type":"Point"}
}