{
  "type": "Feature",
  "properties": {
    "gn:admin1_code":"27",
    "gn:admin2_code":"116046.0",
    "gn:asciiname":"Grindeni",
    "gn:country_code":"RO",
    "gn:dem":315,
    "gn:feature_class":"P",
    "gn:feature_code":"PPL",
    "gn:name":"Grindeni",
    "gn:population":570,
    "gn:timezone":"Europe/Bucharest",
    "iso:country":"RO",
    "wof:name":"Grindeni",
    "wof:placetype":"locality",
    "wof:population":570
},
  "geometry": {"coordinates":[23.99793,46.50067],"type":"Point"}
}