{
  "type": "Feature",
  "properties": {
    "gn:admin1_code":"34",
    "gn:admin2_code":"150588.0",
    "gn:asciiname":"Chiliseni",
    "gn:country_code":"RO",
    "gn:dem":243,
    "gn:feature_class":"P",
    "gn:feature_code":"PPL",
    "gn:name":"Chili\u0219eni",
    "gn:population":634,
    "gn:timezone":"Europe/Bucharest",
    "iso:country":"RO",
    "wof:name":"Chiliseni",
    "wof:placetype":"locality",
    "wof:population":634
},
  "geometry": {"coordinates":[26.47923,47.56246],"type":"Point"}
}