{
  "type": "Feature",
  "properties": {
    "gn:admin1_code":"20",
    "gn:admin2_code":"86133.0",
    "gn:asciiname":"Hagota",
    "gn:cc2":"RO",
    "gn:country_code":"RO",
    "gn:dem":794,
    "gn:feature_class":"P",
    "gn:feature_code":"PPL",
    "gn:name":"Hagota",
    "gn:population":175,
    "gn:timezone":"Europe/Bucharest",
    "iso:country":"RO",
    "name:und_x_variant":[
        "Hag\u00e0t\u00f6",
        "H\u00e1g\u00f3t\u00f6alja",
        "Hagota"
    ],
    "wof:name":"Hagota",
    "wof:placetype":"locality",
    "wof:population":175
},
  "geometry": {"coordinates":[25.68275,46.87277],"type":"Point"}
}