{
  "type": "Feature",
  "properties": {
    "gn:admin1_code":"03",
    "gn:admin2_code":"19007.0",
    "gn:asciiname":"Padureni",
    "gn:country_code":"RO",
    "gn:dem":252,
    "gn:feature_class":"P",
    "gn:feature_code":"PPL",
    "gn:name":"P\u0103dureni",
    "gn:population":219,
    "gn:timezone":"Europe/Bucharest",
    "iso:country":"RO",
    "wof:name":"Padureni",
    "wof:placetype":"locality",
    "wof:population":219
},
  "geometry": {"coordinates":[24.98638,44.70737],"type":"Point"}
}