{
  "type": "Feature",
  "properties": {
    "gn:gn_country":"RO",
    "gn:gn_fcode":"PPLA2",
    "gn:gn_pop":3805,
    "gn:population":3805,
    "iso:country":"RO",
    "name:dut_x_preferred":[
        "Co\u0219teiu"
    ],
    "name:eng_x_preferred":[
        "Co\u0219teiu"
    ],
    "name:epo_x_preferred":[
        "Co\u0219teiu"
    ],
    "name:fre_x_preferred":[
        "Co\u0219teiu"
    ],
    "name:hun_x_preferred":[
        "Kast\u00e9ly"
    ],
    "name:ita_x_preferred":[
        "Co\u0219teiu"
    ],
    "name:may_x_preferred":[
        "Co\u0219teiu"
    ],
    "name:por_x_preferred":[
        "Co\u0219teiu"
    ],
    "name:rum_x_preferred":[
        "Co\u0219teiu"
    ],
    "name:ukr_x_preferred":[
        "\u041a\u043e\u0448\u0442\u0435\u044e"
    ],
    "name:unk_x_variant":[
        "S\u00eelha"
    ],
    "name:vie_x_preferred":[
        "Costeiu"
    ],
    "name:vol_x_preferred":[
        "Co\u0219teiu"
    ],
    "qs_pg:aaroncc":"RO",
    "qs_pg:gn_country":"RO",
    "qs_pg:gn_fcode":"PPLA2",
    "qs_pg:gn_pop":3805,
    "qs_pg:name":"Co\u0219teiu",
    "qs_pg:name_adm0":"Rom\u00e2nia",
    "qs_pg:name_adm1":"Timis",
    "qs_pg:photos_9k":1,
    "qs_pg:photos_9r":1,
    "qs_pg:photos_all":6,
    "qs_pg:photos_sr":0,
    "qs_pg:pop_sr":4,
    "qs_pg:qs_pg_placetype":"locality",
    "qs_pg:qs_pg_placetype_gp":"Town",
    "qs_pg:woe_adm0":23424933,
    "woe:adm0_id":23424933,
    "woe:name_adm0":"Rom\u00e2nia",
    "woe:name_adm1":"Timis",
    "woe:placetype":"Town",
    "wof:name":"Co\u0219teiu",
    "wof:placetype":"locality",
    "wof:population":3805
},
  "geometry": {"coordinates":[21.84917,45.74111],"type":"Point"}
}