{
  "type": "Feature",
  "properties": {
    "gn:admin1_code":"04",
    "gn:admin2_code":"24187.0",
    "gn:asciiname":"Soci",
    "gn:country_code":"RO",
    "gn:dem":222,
    "gn:feature_class":"P",
    "gn:feature_code":"PPL",
    "gn:name":"Soci",
    "gn:population":589,
    "gn:timezone":"Europe/Bucharest",
    "iso:country":"RO",
    "wof:name":"Soci",
    "wof:placetype":"locality",
    "wof:population":589
},
  "geometry": {"coordinates":[27.13398,46.40796],"type":"Point"}
}