{
  "type": "Feature",
  "properties": {
    "gn:admin1_code":"04",
    "gn:admin2_code":"24187.0",
    "gn:asciiname":"Soci",
    "gn:country_code":"RO",
    "gn:dem":222,
    "gn:feature_class":"P",
    "gn:feature_code":"PPL",
    "gn:name":"Soci",
    "gn:population":589,
    "gn:timezone":"Europe/Bucharest",
    "iso:country":"RO",
    "name:cat_x_preferred":[
        "Soci"
    ],
    "name:ceb_x_preferred":[
        "Soci"
    ],
    "name:deu_x_preferred":[
        "Soci"
    ],
    "name:ita_x_preferred":[
        "Soci"
    ],
    "name:ron_x_preferred":[
        "Soci"
    ],
    "name:srp_x_preferred":[
        "\u0421\u043e\u0447\u0438"
    ],
    "name:swe_x_preferred":[
        "Soci"
    ],
    "wof:name":"Soci",
    "wof:placetype":"locality",
    "wof:population":589
},
  "geometry": {"coordinates":[27.13398,46.40796],"type":"Point"}
}