{
  "type": "Feature",
  "properties": {
    "gn:admin1_code":"38",
    "gn:admin2_code":"163967.0",
    "gn:asciiname":"Poiana lui Matei",
    "gn:country_code":"RO",
    "gn:dem":250,
    "gn:feature_class":"P",
    "gn:feature_code":"PPL",
    "gn:name":"Poiana lui Matei",
    "gn:population":0,
    "gn:timezone":"Europe/Bucharest",
    "iso:country":"RO",
    "name:und_x_variant":[
        "Poiana Matei",
        "Poiana lui Matei"
    ],
    "wof:name":"Poiana lui Matei",
    "wof:placetype":"locality"
},
  "geometry": {"coordinates":[27.55,46.48333],"type":"Point"}
}