{
  "type": "Feature",
  "properties": {
    "gn:admin1_code":"43",
    "gn:admin2_code":"102035.0",
    "gn:asciiname":"Caltuna",
    "gn:cc2":"RO",
    "gn:country_code":"RO",
    "gn:dem":88,
    "gn:feature_class":"P",
    "gn:feature_code":"PPL",
    "gn:name":"C\u0103l\u0163una",
    "gn:population":0,
    "gn:timezone":"Europe/Bucharest",
    "iso:country":"RO",
    "name:und_x_variant":[
        "Domne\u015fti C\u0103l\u0163una",
        "C\u0103l\u0163una"
    ],
    "wof:name":"Caltuna",
    "wof:placetype":"locality"
},
  "geometry": {"coordinates":[25.93333,44.38333],"type":"Point"}
}