{
  "type": "Feature",
  "properties": {
    "gn:admin1_code":"29",
    "gn:admin2_code":"127322.0",
    "gn:asciiname":"Stanislavesti",
    "gn:country_code":"RO",
    "gn:dem":150,
    "gn:feature_class":"P",
    "gn:feature_code":"PPL",
    "gn:name":"St\u0103nisl\u0103ve\u015fti",
    "gn:population":0,
    "gn:timezone":"Europe/Bucharest",
    "iso:country":"RO",
    "wof:name":"Stanislavesti",
    "wof:placetype":"locality"
},
  "geometry": {"coordinates":[24.68333,44.45],"type":"Point"}
}