{
  "type": "Feature",
  "properties": {
    "gn:admin1_code":"27",
    "gn:admin2_code":"119153.0",
    "gn:asciiname":"Maioresti",
    "gn:cc2":"RO",
    "gn:country_code":"RO",
    "gn:dem":425,
    "gn:feature_class":"P",
    "gn:feature_code":"PPL",
    "gn:name":"Maiore\u0219ti",
    "gn:population":262,
    "gn:timezone":"Europe/Bucharest",
    "iso:country":"RO",
    "name:und_x_variant":[
        "Monosfalva",
        "Maiore\u015fti"
    ],
    "wof:name":"Maioresti",
    "wof:placetype":"locality",
    "wof:population":262
},
  "geometry": {"coordinates":[24.81064,46.90746],"type":"Point"}
}