{
  "type": "Feature",
  "properties": {
    "gn:admin1_code":"30",
    "gn:admin2_code":"136241.0",
    "gn:asciiname":"Cocorastii Grind",
    "gn:cc2":"RO",
    "gn:country_code":"RO",
    "gn:dem":169,
    "gn:feature_class":"P",
    "gn:feature_code":"PPL",
    "gn:name":"Cocor\u0103\u0219tii Grind",
    "gn:population":847,
    "gn:timezone":"Europe/Bucharest",
    "iso:country":"RO",
    "name:und_x_variant":[
        "Grindu",
        "Cocorastii-Grind",
        "Cocor\u0103\u015fti-Grind"
    ],
    "wof:name":"Cocorastii Grind",
    "wof:placetype":"locality",
    "wof:population":847
},
  "geometry": {"coordinates":[25.87653,44.84717],"type":"Point"}
}