{
  "type": "Feature",
  "properties": {
    "gn:admin1_code":"18",
    "gn:admin2_code":"76932.0",
    "gn:asciiname":"Slobozia Oancea",
    "gn:country_code":"RO",
    "gn:dem":18,
    "gn:feature_class":"P",
    "gn:feature_code":"PPL",
    "gn:name":"Slobozia Oancea",
    "gn:population":153,
    "gn:timezone":"Europe/Bucharest",
    "iso:country":"RO",
    "wof:name":"Slobozia Oancea",
    "wof:placetype":"locality",
    "wof:population":153
},
  "geometry": {"coordinates":[28.11039,45.89446],"type":"Point"}
}