{
  "type": "Feature",
  "properties": {
    "gn:admin1_code":"03",
    "gn:admin2_code":"15652",
    "gn:asciiname":"Barbatesti",
    "gn:country_code":"RO",
    "gn:dem":363,
    "gn:feature_class":"P",
    "gn:feature_code":"PPL",
    "gn:name":"B\u0103rb\u0103te\u0219ti",
    "gn:population":737,
    "gn:timezone":"Europe/Bucharest",
    "iso:country":"RO",
    "wof:name":"Barbatesti",
    "wof:placetype":"locality",
    "wof:population":737
},
  "geometry": {"coordinates":[24.63275,44.90799000000001],"type":"Point"}
}