{
  "type": "Feature",
  "properties": {
    "gn:admin1_code":"31",
    "gn:admin2_code":"140379",
    "gn:asciiname":"Bodia",
    "gn:country_code":"RO",
    "gn:dem":315,
    "gn:feature_class":"P",
    "gn:feature_code":"PPL",
    "gn:name":"Bodia",
    "gn:population":339,
    "gn:timezone":"Europe/Bucharest",
    "iso:country":"RO",
    "wof:name":"Bodia",
    "wof:placetype":"locality",
    "wof:population":339
},
  "geometry": {"coordinates":[23.06724,47.0598],"type":"Point"}
}