{
  "type": "Feature",
  "properties": {
    "gn:admin1_code":"35",
    "gn:admin2_code":"154415",
    "gn:asciiname":"Bratcovu",
    "gn:country_code":"RO",
    "gn:dem":102,
    "gn:feature_class":"P",
    "gn:feature_code":"PPL",
    "gn:name":"Bratcovu",
    "gn:population":233,
    "gn:timezone":"Europe/Bucharest",
    "iso:country":"RO",
    "wof:name":"Bratcovu",
    "wof:placetype":"locality",
    "wof:population":233
},
  "geometry": {"coordinates":[24.8693,44.15769],"type":"Point"}
}