{
  "type": "Feature",
  "properties": {
    "gn:admin1_code":"04",
    "gn:admin2_code":"24338",
    "gn:asciiname":"Bahnaseni",
    "gn:cc2":"RO",
    "gn:country_code":"RO",
    "gn:dem":340,
    "gn:feature_class":"P",
    "gn:feature_code":"PPL",
    "gn:name":"B\u0103hn\u0103\u0219eni",
    "gn:population":865,
    "gn:timezone":"Europe/Bucharest",
    "iso:country":"RO",
    "name:und_x_variant":[
        "Ple\u015fe\u015fti",
        "B\u0103hn\u0103\u015feni"
    ],
    "wof:name":"Bahnaseni",
    "wof:placetype":"locality",
    "wof:population":865
},
  "geometry": {"coordinates":[26.58184,46.57253],"type":"Point"}
}