{
  "type": "Feature",
  "properties": {
    "gn:admin1_code":"14",
    "gn:admin2_code":"62609.0",
    "gn:asciiname":"Nistoresti",
    "gn:cc2":"RO",
    "gn:country_code":"RO",
    "gn:dem":71,
    "gn:feature_class":"P",
    "gn:feature_code":"PPL",
    "gn:name":"Nistore\u0219ti",
    "gn:population":254,
    "gn:timezone":"Europe/Bucharest",
    "iso:country":"RO",
    "name:und_x_variant":[
        "Cuciuc-Chioi",
        "Kuciukioi",
        "Nistore\u015fti"
    ],
    "wof:name":"Nistoresti",
    "wof:placetype":"locality",
    "wof:population":254
},
  "geometry": {"coordinates":[28.3793,44.62155],"type":"Point"}
}