{
  "type": "Feature",
  "properties": {
    "gn:admin1_code":"11",
    "gn:admin2_code":"49233.0",
    "gn:asciiname":"Valea Stanei",
    "gn:cc2":"RO",
    "gn:country_code":"RO",
    "gn:dem":376,
    "gn:feature_class":"P",
    "gn:feature_code":"PPL",
    "gn:name":"Valea St\u00e2nei",
    "gn:population":237,
    "gn:timezone":"Europe/Bucharest",
    "iso:country":"RO",
    "name:und_x_variant":[
        "Valea St\u00e2nei",
        "Valea St\u00eenei"
    ],
    "wof:name":"Valea Stanei",
    "wof:placetype":"locality",
    "wof:population":237
},
  "geometry": {"coordinates":[26.78255,45.4741],"type":"Point"}
}