{
  "type": "Feature",
  "properties": {
    "gn:admin1_code":"21",
    "gn:admin2_code":"91535.0",
    "gn:asciiname":"Curpenii Silvasului",
    "gn:country_code":"RO",
    "gn:dem":637,
    "gn:feature_class":"P",
    "gn:feature_code":"PPL",
    "gn:name":"Curpenii Silva\u0219ului",
    "gn:population":0,
    "gn:timezone":"Europe/Bucharest",
    "iso:country":"RO",
    "wof:name":"Curpenii Silvasului",
    "wof:placetype":"locality"
},
  "geometry": {"coordinates":[22.82139,45.65486],"type":"Point"}
}