{
  "type": "Feature",
  "properties": {
    "gn:admin1_code":"18",
    "gn:admin2_code":"76969.0",
    "gn:asciiname":"Lupele",
    "gn:country_code":"RO",
    "gn:dem":81,
    "gn:feature_class":"P",
    "gn:feature_code":"PPL",
    "gn:name":"Lupele",
    "gn:population":38,
    "gn:timezone":"Europe/Bucharest",
    "iso:country":"RO",
    "wof:name":"Lupele",
    "wof:placetype":"locality",
    "wof:population":38
},
  "geometry": {"coordinates":[27.85661,45.6612],"type":"Point"}
}