{
  "type": "Feature",
  "properties": {
    "gn:admin1_code":"12",
    "gn:admin2_code":"54350",
    "gn:asciiname":"Bratova",
    "gn:country_code":"RO",
    "gn:dem":282,
    "gn:feature_class":"P",
    "gn:feature_code":"PPL",
    "gn:name":"Bratova",
    "gn:population":11,
    "gn:timezone":"Europe/Bucharest",
    "iso:country":"RO",
    "wof:name":"Bratova",
    "wof:placetype":"locality",
    "wof:population":11
},
  "geometry": {"coordinates":[21.93328,45.3269],"type":"Point"}
}