{
  "type": "Feature",
  "properties": {
    "gn:admin1_code":"27",
    "gn:admin2_code":"115959.0",
    "gn:asciiname":"Sabed",
    "gn:cc2":"RO",
    "gn:country_code":"RO",
    "gn:dem":349,
    "gn:feature_class":"P",
    "gn:feature_code":"PPL",
    "gn:name":"S\u0103bed",
    "gn:population":712,
    "gn:timezone":"Europe/Bucharest",
    "iso:country":"RO",
    "name:und_x_variant":[
        "Szab\u00e8d",
        "S\u0103bed"
    ],
    "wof:name":"Sabed",
    "wof:placetype":"locality",
    "wof:population":712
},
  "geometry": {"coordinates":[24.44632,46.6645],"type":"Point"}
}