{
  "type": "Feature",
  "properties": {
    "gn:admin1_code":"01",
    "gn:admin2_code":"6627.0",
    "gn:asciiname":"Valea Uzei",
    "gn:country_code":"RO",
    "gn:dem":811,
    "gn:feature_class":"P",
    "gn:feature_code":"PPL",
    "gn:name":"Valea Uzei",
    "gn:population":42,
    "gn:timezone":"Europe/Bucharest",
    "iso:country":"RO",
    "name:und_x_variant":[
        "R\u00e2me\u0163 Valea Uzei",
        "R\u00eeme\u0163i-Valea Uzei"
    ],
    "wof:name":"Valea Uzei",
    "wof:placetype":"locality",
    "wof:population":42
},
  "geometry": {"coordinates":[23.51315,46.31683],"type":"Point"}
}