{
  "type": "Feature",
  "properties": {
    "gn:admin1_code":"21",
    "gn:admin2_code":"90119.0",
    "gn:asciiname":"Lunca Cernii de Sus",
    "gn:country_code":"RO",
    "gn:dem":610,
    "gn:feature_class":"P",
    "gn:feature_code":"PPL",
    "gn:name":"Lunca Cernii de Sus",
    "gn:population":344,
    "gn:timezone":"Europe/Bucharest",
    "iso:country":"RO",
    "wof:name":"Lunca Cernii de Sus",
    "wof:placetype":"locality",
    "wof:population":344
},
  "geometry": {"coordinates":[22.58439,45.63941],"type":"Point"}
}