{
  "type": "Feature",
  "properties": {
    "gn:admin1_code":"01",
    "gn:admin2_code":"2577.0",
    "gn:asciiname":"Tarsa",
    "gn:country_code":"RO",
    "gn:dem":799,
    "gn:feature_class":"P",
    "gn:feature_code":"PPL",
    "gn:name":"T\u00e2rsa",
    "gn:population":358,
    "gn:timezone":"Europe/Bucharest",
    "iso:country":"RO",
    "name:srp_x_preferred":[
        "\u0422\u0430\u0440\u0441\u0430"
    ],
    "wof:name":"Tarsa",
    "wof:placetype":"locality",
    "wof:population":358
},
  "geometry": {"coordinates":[22.79808,46.38233],"type":"Point"}
}