{
  "type": "Feature",
  "properties": {
    "gn:admin1_code":"01",
    "gn:admin2_code":"1936.0",
    "gn:asciiname":"Suseni",
    "gn:country_code":"RO",
    "gn:dem":385,
    "gn:feature_class":"P",
    "gn:feature_code":"PPL",
    "gn:name":"Suseni",
    "gn:population":168,
    "gn:timezone":"Europe/Bucharest",
    "iso:country":"RO",
    "wof:name":"Suseni",
    "wof:placetype":"locality",
    "wof:population":168
},
  "geometry": {"coordinates":[23.25331,46.09447],"type":"Point"}
}