{
  "type": "Feature",
  "properties": {
    "gn:admin1_code":"01",
    "gn:admin2_code":"1936.0",
    "gn:asciiname":"Suseni",
    "gn:country_code":"RO",
    "gn:dem":385,
    "gn:feature_class":"P",
    "gn:feature_code":"PPL",
    "gn:name":"Suseni",
    "gn:population":168,
    "gn:timezone":"Europe/Bucharest",
    "iso:country":"RO",
    "name:ceb_x_preferred":[
        "Suseni"
    ],
    "name:deu_x_preferred":[
        "Suseni"
    ],
    "name:epo_x_preferred":[
        "Suseni"
    ],
    "name:fra_x_preferred":[
        "Suseni"
    ],
    "name:hrv_x_preferred":[
        "Suseni"
    ],
    "name:hun_x_preferred":[
        "Suseni"
    ],
    "name:ita_x_preferred":[
        "Suseni"
    ],
    "name:nld_x_preferred":[
        "Suseni"
    ],
    "name:ron_x_preferred":[
        "Suseni"
    ],
    "name:srp_x_preferred":[
        "\u0421\u0443\u0441\u0435\u043d\u0438"
    ],
    "name:vol_x_preferred":[
        "Suseni"
    ],
    "wof:name":"Suseni",
    "wof:placetype":"locality",
    "wof:population":168
},
  "geometry": {"coordinates":[23.25331,46.09447],"type":"Point"}
}