{
  "type": "Feature",
  "properties": {
    "gn:admin1_code":"31",
    "gn:admin2_code":"141580.0",
    "gn:asciiname":"Perii Vadului",
    "gn:country_code":"RO",
    "gn:dem":228,
    "gn:feature_class":"P",
    "gn:feature_code":"PPL",
    "gn:name":"Perii Vadului",
    "gn:population":188,
    "gn:timezone":"Europe/Bucharest",
    "iso:country":"RO",
    "wof:name":"Perii Vadului",
    "wof:placetype":"locality",
    "wof:population":188
},
  "geometry": {"coordinates":[23.56682,47.34993],"type":"Point"}
}