{
  "type": "Feature",
  "properties": {
    "gn:admin1_code":"13",
    "gn:admin2_code":"57831.0",
    "gn:asciiname":"Lacu",
    "gn:cc2":"RO",
    "gn:country_code":"RO",
    "gn:dem":309,
    "gn:feature_class":"P",
    "gn:feature_code":"PPL",
    "gn:name":"Lacu",
    "gn:population":353,
    "gn:timezone":"Europe/Bucharest",
    "iso:country":"RO",
    "name:und_x_variant":[
        "Lacul",
        "Lacu"
    ],
    "wof:name":"Lacu",
    "wof:placetype":"locality",
    "wof:population":353
},
  "geometry": {"coordinates":[24.10756,46.88505],"type":"Point"}
}