{
  "type": "Feature",
  "properties": {
    "gn:admin1_code":"23",
    "gn:admin2_code":"98373.0",
    "gn:asciiname":"Cositeni",
    "gn:country_code":"RO",
    "gn:dem":95,
    "gn:feature_class":"P",
    "gn:feature_code":"PPL",
    "gn:name":"Cosi\u021beni",
    "gn:population":284,
    "gn:timezone":"Europe/Bucharest",
    "iso:country":"RO",
    "wof:name":"Cositeni",
    "wof:placetype":"locality",
    "wof:population":284
},
  "geometry": {"coordinates":[27.23755,47.20242],"type":"Point"}
}