{
  "type": "Feature",
  "properties": {
    "gn:admin1_code":"39",
    "gn:admin2_code":"174085.0",
    "gn:asciiname":"Margineni",
    "gn:cc2":"RO",
    "gn:country_code":"RO",
    "gn:dem":263,
    "gn:feature_class":"P",
    "gn:feature_code":"PPL",
    "gn:name":"M\u0103rgineni",
    "gn:population":594,
    "gn:timezone":"Europe/Bucharest",
    "iso:country":"RO",
    "name:und_x_variant":[
        "Gluge\u015fti",
        "M\u0103rgineni"
    ],
    "wof:name":"Margineni",
    "wof:placetype":"locality",
    "wof:population":594
},
  "geometry": {"coordinates":[24.00613,44.69504000000001],"type":"Point"}
}