{
  "type": "Feature",
  "properties": {
    "gn:admin1_code":"29",
    "gn:admin2_code":"129816.0",
    "gn:asciiname":"Valea Fetei",
    "gn:country_code":"RO",
    "gn:dem":199,
    "gn:feature_class":"P",
    "gn:feature_code":"PPL",
    "gn:name":"Valea Fetei",
    "gn:population":279,
    "gn:timezone":"Europe/Bucharest",
    "iso:country":"RO",
    "wof:name":"Valea Fetei",
    "wof:placetype":"locality",
    "wof:population":279
},
  "geometry": {"coordinates":[24.33995,44.63166],"type":"Point"}
}