{
  "type": "Feature",
  "properties": {
    "gn:admin1_code":"23",
    "gn:admin2_code":"97919.0",
    "gn:asciiname":"Vorovesti",
    "gn:cc2":"RO",
    "gn:country_code":"RO",
    "gn:dem":76,
    "gn:feature_class":"P",
    "gn:feature_code":"PPL",
    "gn:name":"Vorove\u0219ti",
    "gn:population":557,
    "gn:timezone":"Europe/Bucharest",
    "iso:country":"RO",
    "name:und_x_variant":[
        "Vorove\u015ftii",
        "Vorove\u015fti"
    ],
    "wof:name":"Vorovesti",
    "wof:placetype":"locality",
    "wof:population":557
},
  "geometry": {"coordinates":[27.46426,47.13984],"type":"Point"}
}