{
  "type": "Feature",
  "properties": {
    "gn:admin1_code":"04",
    "gn:admin2_code":"25745.0",
    "gn:asciiname":"Ungureni",
    "gn:cc2":"RO",
    "gn:country_code":"RO",
    "gn:dem":200,
    "gn:feature_class":"P",
    "gn:feature_code":"PPL",
    "gn:name":"Ungureni",
    "gn:population":100,
    "gn:timezone":"Europe/Bucharest",
    "iso:country":"RO",
    "name:und_x_variant":[
        "Ungurenii",
        "Ungureni"
    ],
    "wof:name":"Ungureni",
    "wof:placetype":"locality",
    "wof:population":100
},
  "geometry": {"coordinates":[27.21461,46.20502000000001],"type":"Point"}
}