{
  "type": "Feature",
  "properties": {
    "gn:admin1_code":"04",
    "gn:admin2_code":"25745.0",
    "gn:asciiname":"Ungureni",
    "gn:cc2":"RO",
    "gn:country_code":"RO",
    "gn:dem":200,
    "gn:feature_class":"P",
    "gn:feature_code":"PPL",
    "gn:name":"Ungureni",
    "gn:population":100,
    "gn:timezone":"Europe/Bucharest",
    "iso:country":"RO",
    "name:ceb_x_preferred":[
        "Ungureni"
    ],
    "name:deu_x_preferred":[
        "Ungureni"
    ],
    "name:fra_x_preferred":[
        "Ungureni"
    ],
    "name:hun_x_preferred":[
        "Ungureni"
    ],
    "name:ita_x_preferred":[
        "Ungureni"
    ],
    "name:nld_x_preferred":[
        "Ungureni"
    ],
    "name:ron_x_preferred":[
        "Ungureni"
    ],
    "name:srp_x_preferred":[
        "\u0423\u043d\u0433\u0443\u0440\u0435\u043d\u0438"
    ],
    "name:und_x_variant":[
        "Ungurenii"
    ],
    "name:vol_x_preferred":[
        "Ungureni"
    ],
    "wof:name":"Ungureni",
    "wof:placetype":"locality",
    "wof:population":100
},
  "geometry": {"coordinates":[27.21461,46.20502000000001],"type":"Point"}
}