{
  "type": "Feature",
  "properties": {
    "gn:admin1_code":"40",
    "gn:admin2_code":"175509.0",
    "gn:asciiname":"Lojnita",
    "gn:country_code":"RO",
    "gn:dem":606,
    "gn:feature_class":"P",
    "gn:feature_code":"PPL",
    "gn:name":"Lojni\u021ba",
    "gn:population":136,
    "gn:timezone":"Europe/Bucharest",
    "iso:country":"RO",
    "wof:name":"Lojnita",
    "wof:placetype":"locality",
    "wof:population":136
},
  "geometry": {"coordinates":[26.83689,45.58561],"type":"Point"}
}