{
  "type": "Feature",
  "properties": {
    "gn:admin1_code":"36",
    "gn:admin2_code":"156927.0",
    "gn:asciiname":"Zolt",
    "gn:country_code":"RO",
    "gn:dem":292,
    "gn:feature_class":"P",
    "gn:feature_code":"PPL",
    "gn:name":"Zolt",
    "gn:population":258,
    "gn:timezone":"Europe/Bucharest",
    "iso:country":"RO",
    "wof:name":"Zolt",
    "wof:placetype":"locality",
    "wof:population":258
},
  "geometry": {"coordinates":[22.25693,45.75612],"type":"Point"}
}