{
  "type": "Feature",
  "properties": {
    "gn:admin1_code":"19",
    "gn:admin2_code":"79157.0",
    "gn:asciiname":"Miluta",
    "gn:country_code":"RO",
    "gn:dem":200,
    "gn:feature_class":"P",
    "gn:feature_code":"PPL",
    "gn:name":"Miluta",
    "gn:population":686,
    "gn:timezone":"Europe/Bucharest",
    "iso:country":"RO",
    "wof:name":"Miluta",
    "wof:placetype":"locality",
    "wof:population":686
},
  "geometry": {"coordinates":[23.17324,44.70343],"type":"Point"}
}