{
  "type": "Feature",
  "properties": {
    "gn:admin1_code":"01",
    "gn:admin2_code":"1936.0",
    "gn:asciiname":"Rusi",
    "gn:country_code":"RO",
    "gn:dem":934,
    "gn:feature_class":"P",
    "gn:feature_code":"PPL",
    "gn:name":"Ru\u0219i",
    "gn:population":66,
    "gn:timezone":"Europe/Bucharest",
    "iso:country":"RO",
    "name:bul_x_preferred":[
        "\u0420\u0443\u0441\u0438"
    ],
    "name:ceb_x_preferred":[
        "Ru\u0219i"
    ],
    "name:deu_x_preferred":[
        "Ru\u0219i"
    ],
    "name:epo_x_preferred":[
        "Ru\u0219i"
    ],
    "name:fin_x_preferred":[
        "Rusi"
    ],
    "name:hun_x_preferred":[
        "Ru\u0219i"
    ],
    "name:ron_x_preferred":[
        "Ru\u0219i"
    ],
    "name:srp_x_preferred":[
        "\u0420\u0443\u0441\u0438"
    ],
    "wof:name":"Rusi",
    "wof:placetype":"locality",
    "wof:population":66
},
  "geometry": {"coordinates":[23.10962,46.2126],"type":"Point"}
}