{
  "type": "Feature",
  "properties": {
    "gn:gn_country":"RO",
    "gn:gn_fcode":"PPLA2",
    "gn:gn_pop":3291,
    "gn:population":3291,
    "iso:country":"RO",
    "name:ceb_x_preferred":[
        "Cornereva"
    ],
    "name:eng_x_preferred":[
        "Cornereva"
    ],
    "name:epo_x_preferred":[
        "Cornereva"
    ],
    "name:fra_x_preferred":[
        "Cornereva"
    ],
    "name:hun_x_preferred":[
        "Somosr\u00e9ve"
    ],
    "name:ita_x_preferred":[
        "Cornereva"
    ],
    "name:msa_x_preferred":[
        "Cornereva"
    ],
    "name:nld_x_preferred":[
        "Cornereva"
    ],
    "name:por_x_preferred":[
        "Cornereva"
    ],
    "name:ron_x_preferred":[
        "Cornereva"
    ],
    "name:srp_x_preferred":[
        "\u041a\u043e\u0440\u043d\u0435\u0440\u0435\u0432\u0430"
    ],
    "name:ukr_x_preferred":[
        "\u041a\u043e\u0440\u043d\u0435\u0440\u0435\u0432\u0430"
    ],
    "name:vie_x_preferred":[
        "Cornereva"
    ],
    "name:vol_x_preferred":[
        "Cornereva"
    ],
    "qs_pg:aaroncc":"RO",
    "qs_pg:gn_country":"RO",
    "qs_pg:gn_fcode":"PPLA2",
    "qs_pg:gn_pop":3291,
    "qs_pg:name":"Cornereva",
    "qs_pg:name_adm0":"Rom\u00e2nia",
    "qs_pg:name_adm1":"Caras-Severin",
    "qs_pg:photos_9r":0,
    "qs_pg:photos_sr":0,
    "qs_pg:pop_sr":4,
    "qs_pg:qs_pg_placetype":"locality",
    "qs_pg:qs_pg_placetype_gp":"Town",
    "qs_pg:woe_adm0":23424933,
    "woe:adm0_id":23424933,
    "woe:name_adm0":"Rom\u00e2nia",
    "woe:name_adm1":"Caras-Severin",
    "woe:placetype":"Town",
    "wof:name":"Cornereva",
    "wof:placetype":"locality",
    "wof:population":3291
},
  "geometry": {"coordinates":[22.41667,45.06667],"type":"Point"}
}