{
  "type": "Feature",
  "properties": {
    "gn:admin1_code":"27",
    "gn:admin2_code":"114970.0",
    "gn:asciiname":"Gaiesti",
    "gn:country_code":"RO",
    "gn:dem":417,
    "gn:feature_class":"P",
    "gn:feature_code":"PPL",
    "gn:name":"G\u0103ie\u0219ti",
    "gn:population":427,
    "gn:timezone":"Europe/Bucharest",
    "iso:country":"RO",
    "name:hun_x_preferred":[
        "G\u00f6cs"
    ],
    "wof:name":"Gaiesti",
    "wof:placetype":"locality",
    "wof:population":427
},
  "geometry": {"coordinates":[24.66667,46.41667],"type":"Point"}
}