{
  "type": "Feature",
  "properties": {
    "gn:admin1_code":"29",
    "gn:admin2_code":"130302.0",
    "gn:asciiname":"Damburile",
    "gn:cc2":"RO",
    "gn:country_code":"RO",
    "gn:dem":168,
    "gn:feature_class":"P",
    "gn:feature_code":"PPL",
    "gn:name":"D\u00e2mburile",
    "gn:population":138,
    "gn:timezone":"Europe/Bucharest",
    "iso:country":"RO",
    "name:und_x_variant":[
        "Str\u00e2mba",
        "Str\u00eemba",
        "D\u00eemburile"
    ],
    "wof:name":"Damburile",
    "wof:placetype":"locality",
    "wof:population":138
},
  "geometry": {"coordinates":[24.00722,44.40607],"type":"Point"}
}