{
  "type": "Feature",
  "properties": {
    "gn:admin1_code":"27",
    "gn:admin2_code":"118281.0",
    "gn:asciiname":"Mosuni",
    "gn:cc2":"RO",
    "gn:country_code":"RO",
    "gn:dem":376,
    "gn:feature_class":"P",
    "gn:feature_code":"PPL",
    "gn:name":"Mo\u0219uni",
    "gn:population":316,
    "gn:timezone":"Europe/Bucharest",
    "iso:country":"RO",
    "name:und_x_variant":[
        "Moson",
        "Mo\u015funi"
    ],
    "wof:name":"Mosuni",
    "wof:placetype":"locality",
    "wof:population":316
},
  "geometry": {"coordinates":[24.74331,46.56914],"type":"Point"}
}