{
  "type": "Feature",
  "properties": {
    "gn:admin1_code":"40",
    "gn:admin2_code":"178313.0",
    "gn:asciiname":"Prisaca",
    "gn:country_code":"RO",
    "gn:dem":310,
    "gn:feature_class":"P",
    "gn:feature_code":"PPL",
    "gn:name":"Prisaca",
    "gn:population":226,
    "gn:timezone":"Europe/Bucharest",
    "iso:country":"RO",
    "name:ceb_x_preferred":[
        "Prisaca"
    ],
    "name:deu_x_preferred":[
        "Prisaca"
    ],
    "name:epo_x_preferred":[
        "Prisaca"
    ],
    "name:ron_x_preferred":[
        "Prisaca"
    ],
    "name:srp_x_preferred":[
        "\u041f\u0440\u0438\u0441\u0430\u043a\u0430"
    ],
    "wof:name":"Prisaca",
    "wof:placetype":"locality",
    "wof:population":226
},
  "geometry": {"coordinates":[26.78256,45.8636],"type":"Point"}
}