{
  "type": "Feature",
  "properties": {
    "iso:country":"RO",
    "name:eng_x_preferred":[
        "Iris"
    ],
    "name:ron_x_preferred":[
        "Iris"
    ],
    "wof:name":"Iris",
    "wof:placetype":"neighbourhood"
},
  "geometry": {"coordinates":[23.60636478986211,46.79525756741579],"type":"Point"}
}