{
  "type": "Feature",
  "properties": {
    "iso:country":"RO",
    "name:eng_x_preferred":[
        "Iris"
    ],
    "name:ron_x_preferred":[
        "Iris"
    ],
    "wof:lang_x_official":[
        "ron"
    ],
    "wof:lang_x_spoken":[
        "ron"
    ],
    "wof:name":"Iris",
    "wof:placetype":"neighbourhood"
},
  "geometry": {"coordinates":[23.606365,46.795258],"type":"Point"}
}