{
  "type": "Feature",
  "properties": {
    "gn:admin1_code":"06",
    "gn:admin2_code":"34903.0",
    "gn:asciiname":"Sintereag-Gara",
    "gn:cc2":"RO",
    "gn:country_code":"RO",
    "gn:dem":269,
    "gn:feature_class":"P",
    "gn:feature_code":"PPL",
    "gn:name":"\u0218intereag-Gar\u0103",
    "gn:population":144,
    "gn:timezone":"Europe/Bucharest",
    "iso:country":"RO",
    "name:und_x_variant":[
        "Gara \u015eintereag",
        "\u015eintereag-Gar\u0103"
    ],
    "wof:name":"Sintereag-Gara",
    "wof:placetype":"locality",
    "wof:population":144
},
  "geometry": {"coordinates":[24.2726,47.17761],"type":"Point"}
}