{
  "type": "Feature",
  "properties": {
    "gn:admin1_code":"07",
    "gn:admin2_code":"37397.0",
    "gn:asciiname":"Popeni",
    "gn:country_code":"RO",
    "gn:dem":166,
    "gn:feature_class":"P",
    "gn:feature_code":"PPL",
    "gn:name":"Popeni",
    "gn:population":487,
    "gn:timezone":"Europe/Bucharest",
    "iso:country":"RO",
    "wof:name":"Popeni",
    "wof:placetype":"locality",
    "wof:population":487
},
  "geometry": {"coordinates":[26.46731,48.02444000000001],"type":"Point"}
}