{
  "type": "Feature",
  "properties": {
    "gn:admin1_code":"19",
    "gn:admin2_code":"82396.0",
    "gn:asciiname":"Valea Serpilor",
    "gn:country_code":"RO",
    "gn:dem":190,
    "gn:feature_class":"P",
    "gn:feature_code":"PPL",
    "gn:name":"Valea \u015eerpilor",
    "gn:population":0,
    "gn:timezone":"Europe/Bucharest",
    "iso:country":"RO",
    "wof:name":"Valea Serpilor",
    "wof:placetype":"locality"
},
  "geometry": {"coordinates":[23.08333,45.01667],"type":"Point"}
}