{
  "type": "Feature",
  "properties": {
    "gn:admin1_code":"21",
    "gn:admin2_code":"89561.0",
    "gn:asciiname":"Homorod",
    "gn:country_code":"RO",
    "gn:dem":244,
    "gn:feature_class":"P",
    "gn:feature_code":"PPL",
    "gn:name":"Homorod",
    "gn:population":472,
    "gn:timezone":"Europe/Bucharest",
    "iso:country":"RO",
    "name:ceb_x_preferred":[
        "Homorod"
    ],
    "name:epo_x_preferred":[
        "Homorod"
    ],
    "name:hun_x_preferred":[
        "Homor\u00f3d"
    ],
    "name:ron_x_preferred":[
        "Homorod"
    ],
    "name:srp_x_preferred":[
        "\u0425\u043e\u043c\u043e\u0440\u043e\u0434"
    ],
    "name:swe_x_preferred":[
        "Homorod"
    ],
    "name:vie_x_preferred":[
        "Homorod"
    ],
    "wof:name":"Homorod",
    "wof:placetype":"locality",
    "wof:population":472
},
  "geometry": {"coordinates":[23.24815,45.94003],"type":"Point"}
}