{
  "type": "Feature",
  "properties": {
    "gn:admin1_code":"38",
    "gn:admin2_code":"164749.0",
    "gn:asciiname":"Otetoaia",
    "gn:country_code":"RO",
    "gn:dem":34,
    "gn:feature_class":"P",
    "gn:feature_code":"PPL",
    "gn:name":"O\u021betoaia",
    "gn:population":837,
    "gn:timezone":"Europe/Bucharest",
    "iso:country":"RO",
    "wof:name":"Otetoaia",
    "wof:placetype":"locality",
    "wof:population":837
},
  "geometry": {"coordinates":[28.17681,46.58149],"type":"Point"}
}