{
  "type": "Feature",
  "properties": {
    "gn:admin1_code":"39",
    "gn:admin2_code":"173935.0",
    "gn:asciiname":"Lunca",
    "gn:country_code":"RO",
    "gn:dem":468,
    "gn:feature_class":"P",
    "gn:feature_code":"PPL",
    "gn:name":"Lunca",
    "gn:population":0,
    "gn:timezone":"Europe/Bucharest",
    "iso:country":"RO",
    "wof:name":"Lunca",
    "wof:placetype":"locality"
},
  "geometry": {"coordinates":[24.01667,45.15],"type":"Point"}
}