{
  "type": "Feature",
  "properties": {
    "gn:admin1_code":"11",
    "gn:admin2_code":"46554",
    "gn:asciiname":"Anini",
    "gn:cc2":"RO",
    "gn:country_code":"RO",
    "gn:dem":321,
    "gn:feature_class":"P",
    "gn:feature_code":"PPL",
    "gn:name":"Anini",
    "gn:population":99,
    "gn:timezone":"Europe/Bucharest",
    "iso:country":"RO",
    "name:und_x_variant":[
        "Valea Iepei",
        "Valea Epei",
        "Anini"
    ],
    "wof:name":"Anini",
    "wof:placetype":"locality",
    "wof:population":99
},
  "geometry": {"coordinates":[26.47503,45.35263],"type":"Point"}
}