{
  "type": "Feature",
  "properties": {
    "gn:admin1_code":"11",
    "gn:admin2_code":"46554",
    "gn:asciiname":"Anini",
    "gn:cc2":"RO",
    "gn:country_code":"RO",
    "gn:dem":321,
    "gn:feature_class":"P",
    "gn:feature_code":"PPL",
    "gn:name":"Anini",
    "gn:population":99,
    "gn:timezone":"Europe/Bucharest",
    "iso:country":"RO",
    "name:fra_x_preferred":[
        "Anini"
    ],
    "name:guj_x_preferred":[
        "\u0a85\u0aa8\u0ac0\u0aa8\u0ac0"
    ],
    "name:hin_x_preferred":[
        "\u0905\u0928\u093f\u0928\u0940"
    ],
    "name:ita_x_preferred":[
        "Anini"
    ],
    "name:lit_x_preferred":[
        "Aninis"
    ],
    "name:mar_x_preferred":[
        "\u0905\u0928\u093f\u0928\u0940"
    ],
    "name:mlg_x_preferred":[
        "Anini"
    ],
    "name:rus_x_preferred":[
        "\u0410\u043d\u0438\u043d\u0438"
    ],
    "name:spa_x_preferred":[
        "Anini"
    ],
    "name:tgl_x_preferred":[
        "Anini"
    ],
    "name:und_x_variant":[
        "Valea Iepei",
        "Valea Epei"
    ],
    "name:urd_x_preferred":[
        "\u0627\u0646\u06cc\u0646\u06cc"
    ],
    "name:zho_x_preferred":[
        "\u963f\u5c3c\u5c3c"
    ],
    "wof:name":"Anini",
    "wof:placetype":"locality",
    "wof:population":99
},
  "geometry": {"coordinates":[26.47503,45.35263],"type":"Point"}
}