{
  "type": "Feature",
  "properties": {
    "gn:admin1_code":"06",
    "gn:admin2_code":"34477.0",
    "gn:asciiname":"Salcuta",
    "gn:country_code":"RO",
    "gn:dem":358,
    "gn:feature_class":"P",
    "gn:feature_code":"PPL",
    "gn:name":"S\u0103lcu\u021ba",
    "gn:population":195,
    "gn:timezone":"Europe/Bucharest",
    "iso:country":"RO",
    "wof:name":"Salcuta",
    "wof:placetype":"locality",
    "wof:population":195
},
  "geometry": {"coordinates":[24.30286,46.91738],"type":"Point"}
}