{
  "type": "Feature",
  "properties": {
    "gn:admin1_code":"34",
    "gn:admin2_code":"147205",
    "gn:asciiname":"Breaza de Sus",
    "gn:cc2":"RO",
    "gn:country_code":"RO",
    "gn:dem":900,
    "gn:feature_class":"P",
    "gn:feature_code":"PPL",
    "gn:name":"Breaza de Sus",
    "gn:population":0,
    "gn:timezone":"Europe/Bucharest",
    "iso:country":"RO",
    "name:und_x_variant":[
        "Porcescu",
        "Porcescul",
        "Breaza de Sus"
    ],
    "wof:name":"Breaza de Sus",
    "wof:placetype":"locality"
},
  "geometry": {"coordinates":[25.30872,47.64908],"type":"Point"}
}