{
  "type": "Feature",
  "properties": {
    "gn:admin1_code":"31",
    "gn:admin2_code":"140869.0",
    "gn:asciiname":"Petrindu",
    "gn:cc2":"RO",
    "gn:country_code":"RO",
    "gn:dem":326,
    "gn:feature_class":"P",
    "gn:feature_code":"PPL",
    "gn:name":"Petrindu",
    "gn:population":597,
    "gn:timezone":"Europe/Bucharest",
    "iso:country":"RO",
    "name:hun_x_preferred":[
        "Nagypetri"
    ],
    "name:und_x_variant":[
        "Petrindul",
        "Petrindu"
    ],
    "wof:name":"Petrindu",
    "wof:placetype":"locality",
    "wof:population":597
},
  "geometry": {"coordinates":[23.18518,46.92022],"type":"Point"}
}