{
  "type": "Feature",
  "properties": {
    "gn:admin1_code":"15",
    "gn:admin2_code":"63394.0",
    "gn:asciiname":"Sfantu-Gheorghe",
    "gn:country_code":"RO",
    "gn:dem":552,
    "gn:feature_class":"P",
    "gn:feature_code":"PPLA",
    "gn:name":"Sf\u00e2ntu-Gheorghe",
    "gn:population":60677,
    "gn:timezone":"Europe/Bucharest",
    "iso:country":"RO",
    "name:hun_x_preferred":[
        "Sepsiszentgy\u00f6rgy"
    ],
    "name:ron_x_preferred":[
        "Sf\u00e2ntu Gheorghe"
    ],
    "name:rus_x_preferred":[
        "\u0421\u0444\u044d\u043d\u0442\u0443-\u0413\u0435\u043e\u0440\u0433"
    ],
    "name:yid_x_preferred":[
        "\u05e1\u05e0\u05d8 \u05d3\u05e9\u05d6\u05d0\u05e8\u05d3\u05d6\u05e9"
    ],
    "wof:name":"Sfantu-Gheorghe",
    "wof:placetype":"locality",
    "wof:population":60677
},
  "geometry": {"coordinates":[25.78333,45.86667],"type":"Point"}
}