{
  "type": "Feature",
  "properties": {
    "gn:admin1_code":"20",
    "gn:admin2_code":"85984.0",
    "gn:asciiname":"Tarcesti",
    "gn:cc2":"RO",
    "gn:country_code":"RO",
    "gn:dem":493,
    "gn:feature_class":"P",
    "gn:feature_code":"PPL",
    "gn:name":"T\u0103rce\u0219ti",
    "gn:population":200,
    "gn:timezone":"Europe/Bucharest",
    "iso:country":"RO",
    "name:und_x_variant":[
        "T\u00e0rcsafalva",
        "T\u0103rce\u015fti"
    ],
    "wof:name":"Tarcesti",
    "wof:placetype":"locality",
    "wof:population":200
},
  "geometry": {"coordinates":[25.13296,46.37637],"type":"Point"}
}