{
  "type": "Feature",
  "properties": {
    "gn:admin1_code":"28",
    "gn:admin2_code":"121466.0",
    "gn:asciiname":"Certieni",
    "gn:country_code":"RO",
    "gn:dem":312,
    "gn:feature_class":"P",
    "gn:feature_code":"PPL",
    "gn:name":"Certieni",
    "gn:population":144,
    "gn:timezone":"Europe/Bucharest",
    "iso:country":"RO",
    "wof:name":"Certieni",
    "wof:placetype":"locality",
    "wof:population":144
},
  "geometry": {"coordinates":[26.66667,46.96667],"type":"Point"}
}