{
  "type": "Feature",
  "properties": {
    "gn:admin1_code":"34",
    "gn:admin2_code":"147072.0",
    "gn:asciiname":"Moisa",
    "gn:country_code":"RO",
    "gn:dem":385,
    "gn:feature_class":"P",
    "gn:feature_code":"PPL",
    "gn:name":"Moi\u0219a",
    "gn:population":725,
    "gn:timezone":"Europe/Bucharest",
    "iso:country":"RO",
    "wof:name":"Moisa",
    "wof:placetype":"locality",
    "wof:population":725
},
  "geometry": {"coordinates":[26.28703,47.33257],"type":"Point"}
}