{
  "type": "Feature",
  "properties": {
    "gn:admin1_code":"13",
    "gn:admin2_code":"57948.0",
    "gn:asciiname":"Garbau",
    "gn:cc2":"RO",
    "gn:country_code":"RO",
    "gn:dem":411,
    "gn:feature_class":"P",
    "gn:feature_code":"PPLA2",
    "gn:name":"G\u00e2rb\u0103u",
    "gn:population":763,
    "gn:timezone":"Europe/Bucharest",
    "iso:country":"RO",
    "name:und_x_variant":[
        "G\u00e2rb\u0103ul",
        "G\u0103rb\u0103u",
        "G\u00eerb\u0103u"
    ],
    "wof:name":"Garbau",
    "wof:placetype":"locality",
    "wof:population":763
},
  "geometry": {"coordinates":[23.3524,46.83305],"type":"Point"}
}