{
  "type": "Feature",
  "properties": {
    "gn:admin1_code":"13",
    "gn:admin2_code":"57948.0",
    "gn:asciiname":"Garbau",
    "gn:cc2":"RO",
    "gn:country_code":"RO",
    "gn:dem":411,
    "gn:feature_class":"P",
    "gn:feature_code":"PPLA2",
    "gn:name":"G\u00e2rb\u0103u",
    "gn:population":763,
    "gn:timezone":"Europe/Bucharest",
    "iso:country":"RO",
    "name:ceb_x_preferred":[
        "Comuna G\u00e2rb\u0103u"
    ],
    "name:deu_x_preferred":[
        "G\u00e2rb\u0103u"
    ],
    "name:epo_x_preferred":[
        "G\u00e2rb\u0103u"
    ],
    "name:est_x_preferred":[
        "G\u00e2rb\u0103u vald"
    ],
    "name:fra_x_preferred":[
        "G\u00e2rb\u0103u"
    ],
    "name:hun_x_preferred":[
        "Magyargorb\u00f3 k\u00f6zs\u00e9g"
    ],
    "name:ita_x_preferred":[
        "G\u00e2rb\u0103u"
    ],
    "name:msa_x_preferred":[
        "G\u00e2rb\u0103u"
    ],
    "name:nld_x_preferred":[
        "G\u00e2rb\u0103u"
    ],
    "name:por_x_preferred":[
        "G\u00e2rb\u0103u"
    ],
    "name:ron_x_preferred":[
        "Comuna G\u00e2rb\u0103u"
    ],
    "name:spa_x_preferred":[
        "G\u00e2rb\u0103u"
    ],
    "name:srp_x_preferred":[
        "\u041e\u043f\u0448\u0442\u0438\u043d\u0430 \u0413\u0430\u0440\u0431\u0430\u0443"
    ],
    "name:ukr_x_preferred":[
        "\u0413\u0438\u0440\u0431\u0435\u0443"
    ],
    "name:und_x_variant":[
        "G\u00e2rb\u0103ul",
        "G\u0103rb\u0103u",
        "G\u00eerb\u0103u"
    ],
    "name:vol_x_preferred":[
        "G\u00e2rb\u0103u"
    ],
    "wof:name":"Garbau",
    "wof:placetype":"locality",
    "wof:population":763
},
  "geometry": {"coordinates":[23.3524,46.83305],"type":"Point"}
}