{
  "type": "Feature",
  "properties": {
    "iso:country":"RO",
    "name:deu_x_preferred":[
        "Vi\u0219eu de Sus"
    ],
    "name:epo_x_preferred":[
        "Vi\u0219eu de Sus"
    ],
    "name:fas_x_preferred":[
        "\u0648\u0634\u0626\u0648 \u062f\u0647 \u0633\u0648\u0633"
    ],
    "name:fra_x_preferred":[
        "Vi\u0219eu de Sus"
    ],
    "name:heb_x_preferred":[
        "\u05d5\u05d9\u05e9\u05d0\u05d5 \u05d3\u05d4 \u05e1\u05d5\u05e1"
    ],
    "name:hun_x_preferred":[
        "Fels\u0151vis\u00f3"
    ],
    "name:ind_x_preferred":[
        "Vi\u015feu de Sus"
    ],
    "name:ita_x_preferred":[
        "Vi\u0219eu de Sus"
    ],
    "name:min_x_preferred":[
        "Vi\u0219eu de Sus"
    ],
    "name:rum_x_colloquial":[
        "Radeasa",
        "Raedeasa"
    ],
    "name:rum_x_preferred":[
        "R\u0103deasa"
    ],
    "name:spa_x_preferred":[
        "Vi\u0219eu de Sus"
    ],
    "name:unk_x_variant":[
        "R\u0103deasa"
    ],
    "qs:gn_fcode":"PPLX",
    "qs:gn_local":0,
    "qs:gn_namadm1":"00",
    "qs:gn_name":"R\u0103deasa",
    "qs:local_max":25,
    "qs:local_sum":25,
    "qs:localhoods":1,
    "qs:name":"R\u0103deasa",
    "qs:name_adm0":"Rom\u00e2nia",
    "qs:name_adm1":"Maramures",
    "qs:name_local":"Vi\u0219eu de Sus",
    "qs:photo_max":6,
    "qs:photo_sum":25,
    "qs:placetype":"Suburb",
    "qs:quad_count":7,
    "qs:woe_adm0":23424933,
    "qs:woe_adm1":2346638,
    "qs:woe_adm2":0,
    "qs:woe_lau":0,
    "qs:woe_local":883678,
    "qs:woe_ver":"7.10.0",
    "wof:lang":[
        "rum"
    ],
    "wof:name":"R\u0103deasa",
    "wof:placetype":"neighbourhood"
},
  "geometry": {"coordinates":[24.454138,47.719002],"type":"Point"}
}