{
  "type": "Feature",
  "properties": {
    "gn:admin1_code":"38",
    "gn:admin2_code":"163618",
    "gn:asciiname":"Soparleni",
    "gn:country_code":"RO",
    "gn:dem":40,
    "gn:feature_class":"P",
    "gn:feature_code":"PPL",
    "gn:name":"\u0218op\u00e2rleni",
    "gn:population":27,
    "gn:timezone":"Europe/Bucharest",
    "iso:country":"RO",
    "name:und_x_variant":[
        "\u0218op\u00eerleni"
    ],
    "wof:name":"Soparleni",
    "wof:placetype":"locality",
    "wof:population":27
},
  "geometry": {"coordinates":[28.11722,46.76045],"type":"Point"}
}