{
  "type": "Feature",
  "properties": {
    "gn:admin1_code":"17",
    "gn:admin2_code":"72276.0",
    "gn:asciiname":"Plopu Amarasti",
    "gn:cc2":"RO",
    "gn:country_code":"RO",
    "gn:dem":171,
    "gn:feature_class":"P",
    "gn:feature_code":"PPL",
    "gn:name":"Plopu Am\u0103r\u0103\u0219ti",
    "gn:population":118,
    "gn:timezone":"Europe/Bucharest",
    "iso:country":"RO",
    "name:und_x_variant":[
        "Plop",
        "Plopul",
        "Plopu Am\u0103r\u0103\u015fti"
    ],
    "wof:name":"Plopu Amarasti",
    "wof:placetype":"locality",
    "wof:population":118
},
  "geometry": {"coordinates":[23.73677,44.61028],"type":"Point"}
}