{
  "type": "Feature",
  "properties": {
    "gn:admin1_code":"39",
    "gn:admin2_code":"173374.0",
    "gn:asciiname":"Malu",
    "gn:cc2":"RO",
    "gn:country_code":"RO",
    "gn:dem":357,
    "gn:feature_class":"P",
    "gn:feature_code":"PPL",
    "gn:name":"Malu",
    "gn:population":143,
    "gn:timezone":"Europe/Bucharest",
    "iso:country":"RO",
    "name:cat_x_preferred":[
        "Malu"
    ],
    "name:ell_x_preferred":[
        "\u039c\u03b1\u03bb\u03bf\u03cd"
    ],
    "name:fra_x_preferred":[
        "Malu"
    ],
    "name:hrv_x_preferred":[
        "Malu"
    ],
    "name:new_x_preferred":[
        "\u092e\u093e\u0932\u0941"
    ],
    "name:und_x_variant":[
        "Malul",
        "Malu"
    ],
    "wof:name":"Malu",
    "wof:placetype":"locality",
    "wof:population":143
},
  "geometry": {"coordinates":[24.35136,44.93325],"type":"Point"}
}