{
  "type": "Feature",
  "properties": {
    "gn:admin1_code":"36",
    "gn:admin2_code":"157317.0",
    "gn:asciiname":"Ivanda",
    "gn:cc2":"RO",
    "gn:country_code":"RO",
    "gn:dem":76,
    "gn:feature_class":"P",
    "gn:feature_code":"PPL",
    "gn:name":"Ivanda",
    "gn:population":539,
    "gn:timezone":"Europe/Bucharest",
    "iso:country":"RO",
    "name:und_x_variant":[
        "Iwanda",
        "Iv\u00e1nd",
        "Ivanda"
    ],
    "wof:name":"Ivanda",
    "wof:placetype":"locality",
    "wof:population":539
},
  "geometry": {"coordinates":[20.94171,45.56578],"type":"Point"}
}