{
  "type": "Feature",
  "properties": {
    "gn:admin1_code":"26",
    "gn:admin2_code":"112030.0",
    "gn:asciiname":"Poiana Gruii",
    "gn:cc2":"RO",
    "gn:country_code":"RO",
    "gn:dem":102,
    "gn:feature_class":"P",
    "gn:feature_code":"PPL",
    "gn:name":"Poiana Gruii",
    "gn:population":320,
    "gn:timezone":"Europe/Bucharest",
    "iso:country":"RO",
    "name:und_x_variant":[
        "Baciu",
        "Poiana Cioarii",
        "Poiana Ciorii",
        "Poiana Gruii"
    ],
    "wof:name":"Poiana Gruii",
    "wof:placetype":"locality",
    "wof:population":320
},
  "geometry": {"coordinates":[22.81671,44.2794],"type":"Point"}
}