{
  "type": "Feature",
  "properties": {
    "gn:admin1_code":"02",
    "gn:admin2_code":"9832.0",
    "gn:asciiname":"Nermis",
    "gn:country_code":"RO",
    "gn:dem":193,
    "gn:feature_class":"P",
    "gn:feature_code":"PPL",
    "gn:name":"Nermi\u0219",
    "gn:population":242,
    "gn:timezone":"Europe/Bucharest",
    "iso:country":"RO",
    "name:ron_x_preferred":[
        "Nermi\u0219"
    ],
    "name:und_x_variant":[
        "Nermegy",
        "Nyermegy"
    ],
    "wof:name":"Nermis",
    "wof:placetype":"locality",
    "wof:population":242
},
  "geometry": {"coordinates":[22.08293,46.47252],"type":"Point"}
}