{
  "type": "Feature",
  "properties": {
    "gn:country":"RO",
    "gn:fcode":"PPLX",
    "gn:population":4719,
    "iso:country":"RO",
    "name:und_x_variant":[
        "Dr\u00eenceni-Sat"
    ],
    "qs_pg:aaroncc":"RO",
    "qs_pg:gn_country":"RO",
    "qs_pg:gn_fcode":"PPLX",
    "qs_pg:gn_pop":4719,
    "qs_pg:name":"B\u0103ile Dr\u00e2nceni",
    "qs_pg:photos_9r":0,
    "qs_pg:photos_sr":0,
    "qs_pg:pop_sr":4,
    "qs_pg:qs_pg_placetype":"neighbourhood",
    "wof:lang_x_official":[
        "ron"
    ],
    "wof:lang_x_spoken":[
        "ron"
    ],
    "wof:name":"B\u0103ile Dr\u00e2nceni",
    "wof:placetype":"neighbourhood",
    "wof:population":4719
},
  "geometry": {"coordinates":[28.10083,46.81361],"type":"Point"}
}