{
  "type": "Feature",
  "properties": {
    "gn:admin1_code":"15",
    "gn:admin2_code":"64390.0",
    "gn:asciiname":"Iaras",
    "gn:cc2":"RO",
    "gn:country_code":"RO",
    "gn:dem":543,
    "gn:feature_class":"P",
    "gn:feature_code":"PPL",
    "gn:name":"Iar\u0103\u0219",
    "gn:population":480,
    "gn:timezone":"Europe/Bucharest",
    "iso:country":"RO",
    "name:und_x_variant":[
        "Iar\u0103\u015fi",
        "Iar\u0103\u015f"
    ],
    "wof:name":"Iaras",
    "wof:placetype":"locality",
    "wof:population":480
},
  "geometry": {"coordinates":[25.59828,45.86981],"type":"Point"}
}