{
  "type": "Feature",
  "properties": {
    "gn:admin1_code":"15",
    "gn:admin2_code":"64390.0",
    "gn:asciiname":"Iaras",
    "gn:cc2":"RO",
    "gn:country_code":"RO",
    "gn:dem":543,
    "gn:feature_class":"P",
    "gn:feature_code":"PPL",
    "gn:name":"Iar\u0103\u0219",
    "gn:population":480,
    "gn:timezone":"Europe/Bucharest",
    "iso:country":"RO",
    "name:bpy_x_preferred":[
        "\u0987\u09af\u09bc\u09be\u09b0\u09be\u09b8"
    ],
    "name:epo_x_preferred":[
        "Iaras"
    ],
    "name:eus_x_preferred":[
        "Iaras"
    ],
    "name:fra_x_preferred":[
        "Iaras"
    ],
    "name:ita_x_preferred":[
        "Iaras"
    ],
    "name:kaz_x_preferred":[
        "\u0418\u0430\u0440\u0430\u0441"
    ],
    "name:mlg_x_preferred":[
        "Iaras"
    ],
    "name:nld_x_preferred":[
        "Iaras"
    ],
    "name:nor_x_preferred":[
        "Iaras"
    ],
    "name:pol_x_preferred":[
        "Iaras"
    ],
    "name:por_x_preferred":[
        "Iaras"
    ],
    "name:ron_x_preferred":[
        "Iaras"
    ],
    "name:rus_x_preferred":[
        "\u0418\u0430\u0440\u0430\u0441"
    ],
    "name:spa_x_preferred":[
        "Iaras"
    ],
    "name:und_x_variant":[
        "Iar\u0103\u015fi",
        "Iar\u0103\u015f"
    ],
    "name:vie_x_preferred":[
        "Iaras"
    ],
    "name:vol_x_preferred":[
        "Iaras"
    ],
    "name:war_x_preferred":[
        "Iaras"
    ],
    "name:zho_x_preferred":[
        "\u4e9a\u62c9\u65af"
    ],
    "wof:name":"Iaras",
    "wof:placetype":"locality",
    "wof:population":480
},
  "geometry": {"coordinates":[25.59828,45.86981],"type":"Point"}
}