{
  "type": "Feature",
  "properties": {
    "iso:country":"RO",
    "name:eng_x_preferred":[
        "V\u0103c\u0103re\u0219ti"
    ],
    "name:ron_x_preferred":[
        "V\u0103c\u0103re\u0219ti"
    ],
    "name:rus_x_preferred":[
        "V\u0103c\u0103re\u015fti"
    ],
    "name:spa_x_preferred":[
        "V\u0103c\u0103re\u0219ti"
    ],
    "wof:lang_x_official":[
        "ron"
    ],
    "wof:lang_x_spoken":[
        "ron"
    ],
    "wof:name":"Vacaresti",
    "wof:placetype":"neighbourhood"
},
  "geometry": {"coordinates":[26.116437,44.402827],"type":"Point"}
}