{
  "type": "Feature",
  "properties": {
    "iso:country":"RO",
    "name:eng_x_preferred":[
        "V\u0103c\u0103re\u0219ti"
    ],
    "name:rum_x_preferred":[
        "V\u0103c\u0103re\u0219ti"
    ],
    "name:rus_x_preferred":[
        "V\u0103c\u0103re\u015fti"
    ],
    "name:spa_x_preferred":[
        "V\u0103c\u0103re\u0219ti"
    ],
    "wof:name":"Vacaresti",
    "wof:placetype":"neighbourhood"
},
  "geometry": {"coordinates":[26.11643713634596,44.40282676893449],"type":"Point"}
}