{
  "type": "Feature",
  "properties": {
    "gn:admin1_code":"01",
    "gn:admin2_code":"5577",
    "gn:asciiname":"Ampoita",
    "gn:country_code":"RO",
    "gn:dem":341,
    "gn:feature_class":"P",
    "gn:feature_code":"PPL",
    "gn:name":"Ampoi\u021ba",
    "gn:population":700,
    "gn:timezone":"Europe/Bucharest",
    "iso:country":"RO",
    "wof:name":"Ampoita",
    "wof:placetype":"locality",
    "wof:population":700
},
  "geometry": {"coordinates":[23.45011,46.11761],"type":"Point"}
}