{
  "type": "Feature",
  "properties": {
    "gn:admin1_code":"30",
    "gn:admin2_code":"134942.0",
    "gn:asciiname":"Moara",
    "gn:country_code":"RO",
    "gn:dem":107,
    "gn:feature_class":"P",
    "gn:feature_code":"PPL",
    "gn:name":"Moara",
    "gn:population":532,
    "gn:timezone":"Europe/Bucharest",
    "iso:country":"RO",
    "name:deu_x_preferred":[
        "Moara"
    ],
    "name:fra_x_preferred":[
        "Moara"
    ],
    "name:ita_x_preferred":[
        "Moara"
    ],
    "name:ron_x_preferred":[
        "Moara"
    ],
    "name:vie_x_preferred":[
        "Moara"
    ],
    "wof:name":"Moara",
    "wof:placetype":"locality",
    "wof:population":532
},
  "geometry": {"coordinates":[26.06839,44.83387000000001],"type":"Point"}
}