{
  "type": "Feature",
  "properties": {
    "gn:admin1_code":"03",
    "gn:admin2_code":"14673",
    "gn:asciiname":"Balabani",
    "gn:country_code":"RO",
    "gn:dem":638,
    "gn:feature_class":"P",
    "gn:feature_code":"PPL",
    "gn:name":"Balabani",
    "gn:population":320,
    "gn:timezone":"Europe/Bucharest",
    "iso:country":"RO",
    "wof:name":"Balabani",
    "wof:placetype":"locality",
    "wof:population":320
},
  "geometry": {"coordinates":[25.13598,45.16442],"type":"Point"}
}