{
  "type": "Feature",
  "properties": {
    "gn:admin1_code":"27",
    "gn:admin2_code":"118469.0",
    "gn:asciiname":"Tigmandru",
    "gn:cc2":"RO",
    "gn:country_code":"RO",
    "gn:dem":350,
    "gn:feature_class":"P",
    "gn:feature_code":"PPL",
    "gn:name":"\u021aigmandru",
    "gn:population":859,
    "gn:timezone":"Europe/Bucharest",
    "iso:country":"RO",
    "name:und_x_variant":[
        "Ciucmandru",
        "\u0162igmandrul",
        "Ticmandru",
        "\u0162igmandru"
    ],
    "wof:name":"Tigmandru",
    "wof:placetype":"locality",
    "wof:population":859
},
  "geometry": {"coordinates":[24.71788,46.35516],"type":"Point"}
}