{
  "type": "Feature",
  "properties": {
    "gn:admin1_code":"17",
    "gn:admin2_code":"70174.0",
    "gn:asciiname":"Dudovicesti",
    "gn:country_code":"RO",
    "gn:dem":113,
    "gn:feature_class":"P",
    "gn:feature_code":"PPL",
    "gn:name":"Dudovice\u0219ti",
    "gn:population":385,
    "gn:timezone":"Europe/Bucharest",
    "iso:country":"RO",
    "wof:name":"Dudovicesti",
    "wof:placetype":"locality",
    "wof:population":385
},
  "geometry": {"coordinates":[23.78122,44.38511],"type":"Point"}
}