{
  "type": "Feature",
  "properties": {
    "gn:admin1_code":"27",
    "gn:admin2_code":"115236.0",
    "gn:asciiname":"Maldaoci",
    "gn:country_code":"RO",
    "gn:dem":428,
    "gn:feature_class":"P",
    "gn:feature_code":"PPL",
    "gn:name":"Maldaoci",
    "gn:population":0,
    "gn:timezone":"Europe/Bucharest",
    "iso:country":"RO",
    "wof:name":"Maldaoci",
    "wof:placetype":"locality"
},
  "geometry": {"coordinates":[24.03977,46.41133],"type":"Point"}
}