{
  "type": "Feature",
  "properties": {
    "gn:admin1_code":"30",
    "gn:admin2_code":"134755.0",
    "gn:asciiname":"Saratel",
    "gn:cc2":"RO",
    "gn:country_code":"RO",
    "gn:dem":346,
    "gn:feature_class":"P",
    "gn:feature_code":"PPL",
    "gn:name":"S\u0103r\u0103\u021bel",
    "gn:population":141,
    "gn:timezone":"Europe/Bucharest",
    "iso:country":"RO",
    "name:und_x_variant":[
        "S\u0103ratelui",
        "S\u0103r\u0103\u0163elu"
    ],
    "wof:name":"Saratel",
    "wof:placetype":"locality",
    "wof:population":141
},
  "geometry": {"coordinates":[26.08967,45.17316],"type":"Point"}
}