{
  "type": "Feature",
  "properties": {
    "gn:admin1_code":"09",
    "gn:admin2_code":"42101.0",
    "gn:asciiname":"Feldioara",
    "gn:country_code":"RO",
    "gn:dem":410,
    "gn:feature_class":"P",
    "gn:feature_code":"PPL",
    "gn:name":"Feldioara",
    "gn:population":245,
    "gn:timezone":"Europe/Bucharest",
    "iso:country":"RO",
    "wof:name":"Feldioara",
    "wof:placetype":"locality",
    "wof:population":245
},
  "geometry": {"coordinates":[24.68964,45.80577],"type":"Point"}
}