{
  "type": "Feature",
  "properties": {
    "gn:admin1_code":"09",
    "gn:admin2_code":"42101.0",
    "gn:asciiname":"Feldioara",
    "gn:country_code":"RO",
    "gn:dem":410,
    "gn:feature_class":"P",
    "gn:feature_code":"PPL",
    "gn:name":"Feldioara",
    "gn:population":245,
    "gn:timezone":"Europe/Bucharest",
    "iso:country":"RO",
    "name:ceb_x_preferred":[
        "Comuna Feldioara"
    ],
    "name:deu_x_preferred":[
        "Feldioara"
    ],
    "name:epo_x_preferred":[
        "Feldioara"
    ],
    "name:fra_x_preferred":[
        "Feldioara"
    ],
    "name:ita_x_preferred":[
        "Feldioara"
    ],
    "name:nld_x_preferred":[
        "Feldioara"
    ],
    "name:por_x_preferred":[
        "Feldioara"
    ],
    "name:ron_x_preferred":[
        "Comuna Feldioara"
    ],
    "name:spa_x_preferred":[
        "Feldioara"
    ],
    "name:srp_x_preferred":[
        "\u041e\u043f\u0448\u0442\u0438\u043d\u0430 \u0424\u0435\u043b\u0434\u0438\u043e\u0430\u0440\u0430"
    ],
    "name:ukr_x_preferred":[
        "\u0424\u0435\u043b\u0434\u0456\u043e\u0430\u0440\u0430"
    ],
    "name:vie_x_preferred":[
        "Feldioara"
    ],
    "name:vol_x_preferred":[
        "Feldioara"
    ],
    "name:zho_x_preferred":[
        "\u8cbb\u723e\u8fea\u74e6\u62c9\u9109"
    ],
    "wof:name":"Feldioara",
    "wof:placetype":"locality",
    "wof:population":245
},
  "geometry": {"coordinates":[24.68964,45.80577],"type":"Point"}
}