{
  "type": "Feature",
  "properties": {
    "gn:admin1_code":"31",
    "gn:admin2_code":"140672",
    "gn:asciiname":"Borza",
    "gn:country_code":"RO",
    "gn:dem":208,
    "gn:feature_class":"P",
    "gn:feature_code":"PPL",
    "gn:name":"Borza",
    "gn:population":245,
    "gn:timezone":"Europe/Bucharest",
    "iso:country":"RO",
    "name:ceb_x_preferred":[
        "Borza"
    ],
    "name:deu_x_preferred":[
        "Borza"
    ],
    "name:epo_x_preferred":[
        "Borza"
    ],
    "name:swe_x_preferred":[
        "Borza"
    ],
    "wof:name":"Borza",
    "wof:placetype":"locality",
    "wof:population":245
},
  "geometry": {"coordinates":[23.27348,47.2198],"type":"Point"}
}