{
  "type": "Feature",
  "properties": {
    "gn:admin1_code":"01",
    "gn:admin2_code":"3459.0",
    "gn:asciiname":"Cerbu",
    "gn:cc2":"RO",
    "gn:country_code":"RO",
    "gn:dem":657,
    "gn:feature_class":"P",
    "gn:feature_code":"PPL",
    "gn:name":"Cerbu",
    "gn:population":126,
    "gn:timezone":"Europe/Bucharest",
    "iso:country":"RO",
    "name:ceb_x_preferred":[
        "Cerbu"
    ],
    "name:deu_x_preferred":[
        "Cerbu"
    ],
    "name:ron_x_preferred":[
        "Cerbu"
    ],
    "name:srp_x_preferred":[
        "\u0427\u0435\u0440\u0431\u0443"
    ],
    "name:und_x_variant":[
        "Bucium Cerbu",
        "Cerbu"
    ],
    "wof:name":"Cerbu",
    "wof:placetype":"locality",
    "wof:population":126
},
  "geometry": {"coordinates":[23.10696,46.24694],"type":"Point"}
}