{
  "type": "Feature",
  "properties": {
    "gn:admin1_code":"06",
    "gn:admin2_code":"33765.0",
    "gn:asciiname":"Magurele",
    "gn:country_code":"RO",
    "gn:dem":372,
    "gn:feature_class":"P",
    "gn:feature_code":"PPL",
    "gn:name":"M\u0103gurele",
    "gn:population":304,
    "gn:timezone":"Europe/Bucharest",
    "iso:country":"RO",
    "wof:name":"Magurele",
    "wof:placetype":"locality",
    "wof:population":304
},
  "geometry": {"coordinates":[24.50995,47.01461],"type":"Point"}
}