{
  "type": "Feature",
  "properties": {
    "gn:admin1_code":"02",
    "gn:admin2_code":"10943.0",
    "gn:asciiname":"Iosas",
    "gn:country_code":"RO",
    "gn:dem":181,
    "gn:feature_class":"P",
    "gn:feature_code":"PPL",
    "gn:name":"Iosa\u0219",
    "gn:population":273,
    "gn:timezone":"Europe/Bucharest",
    "iso:country":"RO",
    "name:ron_x_preferred":[
        "Iosa\u0219"
    ],
    "name:und_x_variant":[
        "Iosa\u015fi",
        "J\u00f3sz\u00e1s"
    ],
    "wof:name":"Iosas",
    "wof:placetype":"locality",
    "wof:population":273
},
  "geometry": {"coordinates":[22.33546,46.28358],"type":"Point"}
}