{
  "type": "Feature",
  "properties": {
    "gn:admin1_code":"04",
    "gn:admin2_code":"24338.0",
    "gn:asciiname":"Hemieni",
    "gn:cc2":"RO",
    "gn:country_code":"RO",
    "gn:dem":323,
    "gn:feature_class":"P",
    "gn:feature_code":"PPL",
    "gn:name":"Hemieni",
    "gn:population":0,
    "gn:timezone":"Europe/Bucharest",
    "iso:country":"RO",
    "name:und_x_variant":[
        "Hemeeni"
    ],
    "wof:name":"Hemieni",
    "wof:placetype":"locality"
},
  "geometry": {"coordinates":[26.62633,46.558],"type":"Point"}
}