{
  "type": "Feature",
  "properties": {
    "gn:admin1_code":"01",
    "gn:admin2_code":"7446.0",
    "gn:asciiname":"Gura Sohodol",
    "gn:country_code":"RO",
    "gn:dem":575,
    "gn:feature_class":"P",
    "gn:feature_code":"PPL",
    "gn:name":"Gura Sohodol",
    "gn:population":202,
    "gn:timezone":"Europe/Bucharest",
    "iso:country":"RO",
    "wof:name":"Gura Sohodol",
    "wof:placetype":"locality",
    "wof:population":202
},
  "geometry": {"coordinates":[23.03067,46.35463],"type":"Point"}
}