{
  "type": "Feature",
  "properties": {
    "gn:country":"RO",
    "gn:fcode":"PPLA2",
    "gn:population":3713,
    "iso:country":"RO",
    "name:ceb_x_preferred":[
        "Comuna Bahna"
    ],
    "name:fra_x_preferred":[
        "Bahna"
    ],
    "name:ita_x_preferred":[
        "Bahna"
    ],
    "name:msa_x_preferred":[
        "Bahna"
    ],
    "name:nld_x_preferred":[
        "Bahna"
    ],
    "name:por_x_preferred":[
        "Bahna"
    ],
    "name:ron_x_preferred":[
        "Comuna Bahna"
    ],
    "name:srp_x_preferred":[
        "\u041e\u043f\u0448\u0442\u0438\u043d\u0430 \u0411\u0430\u0445\u043d\u0430"
    ],
    "name:ukr_x_preferred":[
        "\u0411\u0430\u0445\u043d\u0430"
    ],
    "name:und_x_variant":[
        "Vasile Gheorghe Mor\u0163un"
    ],
    "name:vie_x_preferred":[
        "Bahna"
    ],
    "name:vol_x_preferred":[
        "Bahna"
    ],
    "name:zho_x_preferred":[
        "\u5df4\u8d6b\u7d0d\u9109"
    ],
    "qs_pg:aaroncc":"RO",
    "qs_pg:gn_country":"RO",
    "qs_pg:gn_fcode":"PPLA2",
    "qs_pg:gn_pop":3713,
    "qs_pg:name":"Bahna",
    "qs_pg:name_adm0":"Rom\u00e2nia",
    "qs_pg:name_adm1":"Neamt",
    "qs_pg:photos_9r":0,
    "qs_pg:photos_sr":0,
    "qs_pg:pop_sr":4,
    "qs_pg:qs_pg_placetype":"locality",
    "qs_pg:qs_pg_placetype_gp":"Town",
    "qs_pg:woe_adm0":23424933,
    "woe:adm0_id":23424933,
    "woe:name_adm0":"Rom\u00e2nia",
    "woe:name_adm1":"Neamt",
    "woe:placetype":"Town",
    "wof:name":"Bahna",
    "wof:placetype":"locality",
    "wof:population":3713
},
  "geometry": {"coordinates":[26.78333,46.78333],"type":"Point"}
}