{
  "type": "Feature",
  "properties": {
    "gn:gn_country":"RO",
    "gn:gn_fcode":"PPLA2",
    "gn:gn_pop":3713,
    "gn:population":3713,
    "iso:country":"RO",
    "name:unk_x_variant":[
        "Vasile Gheorghe Mor\u0163un"
    ],
    "qs_pg:aaroncc":"RO",
    "qs_pg:gn_country":"RO",
    "qs_pg:gn_fcode":"PPLA2",
    "qs_pg:gn_pop":3713,
    "qs_pg:name":"Bahna",
    "qs_pg:name_adm0":"Rom\u00e2nia",
    "qs_pg:name_adm1":"Neamt",
    "qs_pg:photos_9r":0,
    "qs_pg:photos_sr":0,
    "qs_pg:pop_sr":4,
    "qs_pg:qs_pg_placetype":"locality",
    "qs_pg:qs_pg_placetype_gp":"Town",
    "qs_pg:woe_adm0":23424933,
    "woe:adm0_id":23424933,
    "woe:name_adm0":"Rom\u00e2nia",
    "woe:name_adm1":"Neamt",
    "woe:placetype":"Town",
    "wof:name":"Bahna",
    "wof:placetype":"locality",
    "wof:population":3713
},
  "geometry": {"coordinates":[26.78333,46.78333],"type":"Point"}
}