{
  "type": "Feature",
  "properties": {
    "gn:admin1_code":"17",
    "gn:admin2_code":"70940.0",
    "gn:asciiname":"Goicea Mica",
    "gn:country_code":"RO",
    "gn:dem":41,
    "gn:feature_class":"P",
    "gn:feature_code":"PPL",
    "gn:name":"Goicea Mic\u0103",
    "gn:population":0,
    "gn:timezone":"Europe/Bucharest",
    "iso:country":"RO",
    "wof:name":"Goicea Mica",
    "wof:placetype":"locality"
},
  "geometry": {"coordinates":[23.61667000000001,43.95],"type":"Point"}
}