{
  "type": "Feature",
  "properties": {
    "gn:admin1_code":"07",
    "gn:admin2_code":"38982.0",
    "gn:asciiname":"Oroftiana de Jos",
    "gn:country_code":"RO",
    "gn:dem":125,
    "gn:feature_class":"P",
    "gn:feature_code":"PPL",
    "gn:name":"Oroftiana de Jos",
    "gn:population":0,
    "gn:timezone":"Europe/Bucharest",
    "iso:country":"RO",
    "name:und_x_variant":[
        "Orofreana-de-Jos",
        "Orofteana de Jos",
        "Oroftiana de Jos"
    ],
    "wof:lang_x_official":[
        "ron"
    ],
    "wof:lang_x_spoken":[
        "ron"
    ],
    "wof:name":"Oroftiana de Jos",
    "wof:placetype":"locality"
},
  "geometry": {"coordinates":[26.36667,48.18333],"type":"Point"}
}