{
  "type": "Feature",
  "properties": {
    "gn:admin1_code":"03",
    "gn:admin2_code":"16132.0",
    "gn:asciiname":"Stanicei",
    "gn:country_code":"RO",
    "gn:dem":489,
    "gn:feature_class":"P",
    "gn:feature_code":"PPL",
    "gn:name":"St\u0103nicei",
    "gn:population":48,
    "gn:timezone":"Europe/Bucharest",
    "iso:country":"RO",
    "wof:name":"Stanicei",
    "wof:placetype":"locality",
    "wof:population":48
},
  "geometry": {"coordinates":[24.50092,44.97039],"type":"Point"}
}