{
  "type": "Feature",
  "properties": {
    "gn:admin1_code":"36",
    "gn:admin2_code":"155724.0",
    "gn:asciiname":"Cherestur",
    "gn:cc2":"RO",
    "gn:country_code":"RO",
    "gn:dem":79,
    "gn:feature_class":"P",
    "gn:feature_code":"PPL",
    "gn:name":"Cherestur",
    "gn:population":503,
    "gn:timezone":"Europe/Bucharest",
    "iso:country":"RO",
    "name:und_x_variant":[
        "Kereszt\u00far",
        "Pusztakereszt\u00far",
        "Pustakerestur",
        "Cherestur"
    ],
    "wof:name":"Cherestur",
    "wof:placetype":"locality",
    "wof:population":503
},
  "geometry": {"coordinates":[20.38301,46.12605],"type":"Point"}
}