{
  "type": "Feature",
  "properties": {
    "gn:gn_country":"RO",
    "gn:gn_fcode":"PPLA2",
    "gn:gn_pop":2252,
    "gn:population":2252,
    "iso:country":"RO",
    "name:ceb_x_preferred":[
        "P\u0103cure\u021bi"
    ],
    "name:eng_x_preferred":[
        "P\u0103cure\u021bi"
    ],
    "name:fra_x_preferred":[
        "P\u0103cure\u021bi"
    ],
    "name:hun_x_preferred":[
        "P\u0103cure\u021bi"
    ],
    "name:ita_x_preferred":[
        "P\u0103cure\u021bi"
    ],
    "name:nld_x_preferred":[
        "P\u0103cure\u021bi"
    ],
    "name:ron_x_preferred":[
        "P\u0103cure\u021bi"
    ],
    "name:srp_x_preferred":[
        "\u041f\u0430\u043a\u0443\u0440\u0435\u0446\u0438"
    ],
    "name:ukr_x_preferred":[
        "\u041f\u0435\u043a\u0443\u0440\u0435\u0446\u044c"
    ],
    "qs_pg:aaroncc":"RO",
    "qs_pg:gn_country":"RO",
    "qs_pg:gn_fcode":"PPLA2",
    "qs_pg:gn_pop":2252,
    "qs_pg:name":"P\u0103cure\u0163i",
    "qs_pg:photos_9r":0,
    "qs_pg:photos_sr":0,
    "qs_pg:pop_sr":4,
    "qs_pg:qs_pg_placetype":"locality",
    "wof:name":"P\u0103cure\u0163i",
    "wof:placetype":"locality",
    "wof:population":2252
},
  "geometry": {"coordinates":[26.13333,45.15],"type":"Point"}
}