{
  "type": "Feature",
  "properties": {
    "gn:admin1_code":"39",
    "gn:admin2_code":"173230.0",
    "gn:asciiname":"Dobriceni",
    "gn:country_code":"RO",
    "gn:dem":445,
    "gn:feature_class":"P",
    "gn:feature_code":"PPL",
    "gn:name":"Dobriceni",
    "gn:population":0,
    "gn:timezone":"Europe/Bucharest",
    "iso:country":"RO",
    "name:deu_x_preferred":[
        "Dobriceni"
    ],
    "name:ron_x_preferred":[
        "Dobriceni"
    ],
    "name:und_x_variant":[
        "Dooriceni"
    ],
    "wof:name":"Dobriceni",
    "wof:placetype":"locality"
},
  "geometry": {"coordinates":[24.13333,45.15],"type":"Point"}
}