{
  "type": "Feature",
  "properties": {
    "gn:admin1_code":"28",
    "gn:admin2_code":"125123.0",
    "gn:asciiname":"Munteni",
    "gn:country_code":"RO",
    "gn:dem":261,
    "gn:feature_class":"P",
    "gn:feature_code":"PPL",
    "gn:name":"Munteni",
    "gn:population":371,
    "gn:timezone":"Europe/Bucharest",
    "iso:country":"RO",
    "name:ceb_x_preferred":[
        "Comuna Munteni"
    ],
    "name:ita_x_preferred":[
        "Munteni"
    ],
    "name:msa_x_preferred":[
        "Munteni"
    ],
    "name:nld_x_preferred":[
        "Munteni"
    ],
    "name:por_x_preferred":[
        "Munteni"
    ],
    "name:ron_x_preferred":[
        "Comuna Munteni"
    ],
    "name:srp_x_preferred":[
        "\u041e\u043f\u0448\u0442\u0438\u043d\u0430 \u041c\u0443\u043d\u0442\u0435\u043d\u0438"
    ],
    "name:ukr_x_preferred":[
        "\u041c\u0443\u043d\u0442\u0435\u043d\u044c"
    ],
    "name:und_x_variant":[
        "Munteni V\u0103leni"
    ],
    "name:vie_x_preferred":[
        "Munteni"
    ],
    "name:vol_x_preferred":[
        "Munteni"
    ],
    "name:zho_x_preferred":[
        "\u8499\u6cf0\u5c3c\u9109"
    ],
    "wof:name":"Munteni",
    "wof:placetype":"locality",
    "wof:population":371
},
  "geometry": {"coordinates":[26.76667,47.01667],"type":"Point"}
}