{
  "type": "Feature",
  "properties": {
    "gn:admin1_code":"28",
    "gn:admin2_code":"125123.0",
    "gn:asciiname":"Munteni",
    "gn:country_code":"RO",
    "gn:dem":261,
    "gn:feature_class":"P",
    "gn:feature_code":"PPL",
    "gn:name":"Munteni",
    "gn:population":371,
    "gn:timezone":"Europe/Bucharest",
    "iso:country":"RO",
    "name:und_x_variant":[
        "Munteni V\u0103leni"
    ],
    "wof:name":"Munteni",
    "wof:placetype":"locality",
    "wof:population":371
},
  "geometry": {"coordinates":[26.76667,47.01667],"type":"Point"}
}