{
  "type": "Feature",
  "properties": {
    "gn:admin1_code":"25",
    "gn:admin2_code":"107733.0",
    "gn:asciiname":"Curtuiusu Mic",
    "gn:cc2":"RO",
    "gn:country_code":"RO",
    "gn:dem":215,
    "gn:feature_class":"P",
    "gn:feature_code":"PPL",
    "gn:name":"Curtuiu\u0219u Mic",
    "gn:population":281,
    "gn:timezone":"Europe/Bucharest",
    "iso:country":"RO",
    "name:und_x_variant":[
        "Curtuiusul Mic",
        "Curtuiu\u015fu Mic"
    ],
    "wof:name":"Curtuiusu Mic",
    "wof:placetype":"locality",
    "wof:population":281
},
  "geometry": {"coordinates":[23.62531,47.54299],"type":"Point"}
}