{
  "type": "Feature",
  "properties": {
    "gn:admin1_code":"38",
    "gn:admin2_code":"167179.0",
    "gn:asciiname":"Manastirea Bujorani",
    "gn:country_code":"RO",
    "gn:dem":70,
    "gn:feature_class":"P",
    "gn:feature_code":"PPL",
    "gn:name":"M\u00e2n\u0103stirea Bujor\u0103ni",
    "gn:population":0,
    "gn:timezone":"Europe/Bucharest",
    "iso:country":"RO",
    "wof:name":"Manastirea Bujorani",
    "wof:placetype":"locality"
},
  "geometry": {"coordinates":[27.71667,46.26667],"type":"Point"}
}