{
  "type": "Feature",
  "properties": {
    "gn:admin1_code":"01",
    "gn:admin2_code":"8425.0",
    "gn:asciiname":"Pitarcesti",
    "gn:country_code":"RO",
    "gn:dem":724,
    "gn:feature_class":"P",
    "gn:feature_code":"PPL",
    "gn:name":"Pit\u0103rce\u0219ti",
    "gn:population":42,
    "gn:timezone":"Europe/Bucharest",
    "iso:country":"RO",
    "wof:name":"Pitarcesti",
    "wof:placetype":"locality",
    "wof:population":42
},
  "geometry": {"coordinates":[23.0006,46.37044],"type":"Point"}
}