{
  "type": "Feature",
  "properties": {
    "gn:admin1_code":"31",
    "gn:admin2_code":"141081.0",
    "gn:asciiname":"Fildu de Mijloc",
    "gn:cc2":"RO",
    "gn:country_code":"RO",
    "gn:dem":393,
    "gn:feature_class":"P",
    "gn:feature_code":"PPL",
    "gn:name":"Fildu de Mijloc",
    "gn:population":522,
    "gn:timezone":"Europe/Bucharest",
    "iso:country":"RO",
    "name:und_x_variant":[
        "Fildul-de-Mijloc",
        "Fildu de Mijloc"
    ],
    "wof:name":"Fildu de Mijloc",
    "wof:placetype":"locality",
    "wof:population":522
},
  "geometry": {"coordinates":[22.99674,46.92372],"type":"Point"}
}