{
  "type": "Feature",
  "properties": {
    "gn:admin1_code":"16",
    "gn:admin2_code":"67014.0",
    "gn:asciiname":"Frasinu",
    "gn:cc2":"RO",
    "gn:country_code":"RO",
    "gn:dem":144,
    "gn:feature_class":"P",
    "gn:feature_code":"PPL",
    "gn:name":"Frasinu",
    "gn:population":741,
    "gn:timezone":"Europe/Bucharest",
    "iso:country":"RO",
    "name:ceb_x_preferred":[
        "Frasinu"
    ],
    "name:deu_x_preferred":[
        "Frasinu"
    ],
    "name:ron_x_preferred":[
        "Frasinu"
    ],
    "name:srp_x_preferred":[
        "\u0424\u0440\u0430\u0441\u0438\u043d\u0443"
    ],
    "name:und_x_variant":[
        "Frasinul",
        "Frasinu"
    ],
    "wof:name":"Frasinu",
    "wof:placetype":"locality",
    "wof:population":741
},
  "geometry": {"coordinates":[25.86287,44.79121],"type":"Point"}
}