{
  "type": "Feature",
  "properties": {
    "gn:admin1_code":"06",
    "gn:admin2_code":"34690.0",
    "gn:asciiname":"Chintelnic",
    "gn:country_code":"RO",
    "gn:dem":294,
    "gn:feature_class":"P",
    "gn:feature_code":"PPL",
    "gn:name":"Chintelnic",
    "gn:population":544,
    "gn:timezone":"Europe/Bucharest",
    "iso:country":"RO",
    "wof:name":"Chintelnic",
    "wof:placetype":"locality",
    "wof:population":544
},
  "geometry": {"coordinates":[24.3372,47.10114],"type":"Point"}
}