{
  "type": "Feature",
  "properties": {
    "gn:admin1_code":"37",
    "gn:admin2_code":"160779.0",
    "gn:asciiname":"Ilganii de Sus",
    "gn:country_code":"RO",
    "gn:dem":2,
    "gn:feature_class":"P",
    "gn:feature_code":"PPL",
    "gn:name":"Ilganii de Sus",
    "gn:population":68,
    "gn:timezone":"Europe/Bucharest",
    "iso:country":"RO",
    "wof:name":"Ilganii de Sus",
    "wof:placetype":"locality",
    "wof:population":68
},
  "geometry": {"coordinates":[28.95085,45.19473],"type":"Point"}
}