{
  "type": "Feature",
  "properties": {
    "gn:admin1_code":"29",
    "gn:admin2_code":"129914.0",
    "gn:asciiname":"Bulimanu",
    "gn:cc2":"RO",
    "gn:country_code":"RO",
    "gn:dem":418,
    "gn:feature_class":"P",
    "gn:feature_code":"PPL",
    "gn:name":"Bulimanu",
    "gn:population":406,
    "gn:timezone":"Europe/Bucharest",
    "iso:country":"RO",
    "name:und_x_variant":[
        "Bulimanul",
        "Bulimanu"
    ],
    "wof:name":"Bulimanu",
    "wof:placetype":"locality",
    "wof:population":406
},
  "geometry": {"coordinates":[24.41577,44.88739],"type":"Point"}
}