{
  "type": "Feature",
  "properties": {
    "gn:admin1_code":"37",
    "gn:admin2_code":"161348.0",
    "gn:asciiname":"Vasile Alecsandri",
    "gn:cc2":"RO",
    "gn:country_code":"RO",
    "gn:dem":242,
    "gn:feature_class":"P",
    "gn:feature_code":"PPL",
    "gn:name":"Vasile Alecsandri",
    "gn:population":695,
    "gn:timezone":"Europe/Bucharest",
    "iso:country":"RO",
    "name:und_x_variant":[
        "Alexandri",
        "Tistimelu",
        "Vasile-Alexandri",
        "Vasile Alecsandri"
    ],
    "wof:name":"Vasile Alecsandri",
    "wof:placetype":"locality",
    "wof:population":695
},
  "geometry": {"coordinates":[28.50685,44.79555],"type":"Point"}
}