{
  "type": "Feature",
  "properties": {
    "gn:admin1_code":"37",
    "gn:admin2_code":"161348.0",
    "gn:asciiname":"Vasile Alecsandri",
    "gn:cc2":"RO",
    "gn:country_code":"RO",
    "gn:dem":242,
    "gn:feature_class":"P",
    "gn:feature_code":"PPL",
    "gn:name":"Vasile Alecsandri",
    "gn:population":695,
    "gn:timezone":"Europe/Bucharest",
    "iso:country":"RO",
    "name:ara_x_preferred":[
        "\u0641\u0627\u0633\u064a\u0644\u064a \u0623\u0644\u064a\u0643\u0633\u0627\u0646\u062f\u0631\u064a"
    ],
    "name:bul_x_preferred":[
        "\u0412\u0430\u0441\u0438\u043b\u0435 \u0410\u043b\u0435\u043a\u0441\u0430\u043d\u0434\u0440\u0438"
    ],
    "name:cat_x_preferred":[
        "Vasile Alecsandri"
    ],
    "name:ces_x_preferred":[
        "Vasile Alecsandri"
    ],
    "name:deu_x_preferred":[
        "Vasile Alecsandri"
    ],
    "name:ell_x_preferred":[
        "\u0392\u03b1\u03c3\u03af\u03bb\u03b5 \u0391\u03bb\u03b5\u03be\u03b1\u03bd\u03c4\u03c1\u03af"
    ],
    "name:epo_x_preferred":[
        "Vasile Alecsandri"
    ],
    "name:fra_x_preferred":[
        "Vasile Alecsandri"
    ],
    "name:heb_x_preferred":[
        "\u05d5\u05e1\u05d9\u05dc\u05d4 \u05d0\u05dc\u05db\u05e1\u05e0\u05d3\u05e8\u05d9"
    ],
    "name:hun_x_preferred":[
        "Vasile Alecsandri"
    ],
    "name:hye_x_preferred":[
        "\u054e\u0561\u057d\u056b\u056c\u0565 \u0531\u056c\u0565\u0584\u057d\u0561\u0576\u0564\u0580\u056b"
    ],
    "name:ind_x_preferred":[
        "Vasile Alecsandri"
    ],
    "name:ita_x_preferred":[
        "Vasile Alecsandri"
    ],
    "name:jpn_x_preferred":[
        "\u30f4\u30a1\u30b7\u30ec\u30fb\u30a2\u30ec\u30af\u30b5\u30f3\u30c9\u30ea"
    ],
    "name:kan_x_preferred":[
        "\u0c85\u0cb2\u0cc6\u0c95\u0ccd\u0cb8\u0cbe\u0c82\u0ca6\u0ccd\u0cb0\u0cbf \u0cb5\u0ccd\u0caf\u0cb8\u0cbf\u0cb2\u0cbf"
    ],
    "name:lat_x_preferred":[
        "Vasile Alecsandri"
    ],
    "name:lav_x_preferred":[
        "Vasile Aleksandri"
    ],
    "name:pol_x_preferred":[
        "Vasile Alecsandri"
    ],
    "name:por_x_preferred":[
        "Vasile Alecsandri"
    ],
    "name:ron_x_preferred":[
        "Vasile Alecsandri"
    ],
    "name:rus_x_preferred":[
        "\u0410\u043b\u0435\u043a\u0441\u0430\u043d\u0434\u0440\u0438"
    ],
    "name:spa_x_preferred":[
        "Vasile Alecsandri"
    ],
    "name:swe_x_preferred":[
        "Vasile Alecsandri"
    ],
    "name:tur_x_preferred":[
        "Vasile Alecsandri"
    ],
    "name:ukr_x_preferred":[
        "\u0412\u0430\u0441\u0456\u043b\u0435 \u0410\u043b\u0435\u043a\u0441\u0430\u043d\u0434\u0440\u0456"
    ],
    "name:und_x_variant":[
        "Alexandri",
        "Tistimelu",
        "Vasile-Alexandri",
        "Vasile Alecsandri"
    ],
    "wof:name":"Vasile Alecsandri",
    "wof:placetype":"locality",
    "wof:population":695
},
  "geometry": {"coordinates":[28.50685,44.79555],"type":"Point"}
}