{
  "type": "Feature",
  "properties": {
    "gn:admin1_code":"13",
    "gn:admin2_code":"56265.0",
    "gn:asciiname":"Ciumafaia",
    "gn:country_code":"RO",
    "gn:dem":328,
    "gn:feature_class":"P",
    "gn:feature_code":"PPL",
    "gn:name":"Cium\u0103faia",
    "gn:population":190,
    "gn:timezone":"Europe/Bucharest",
    "iso:country":"RO",
    "wof:name":"Ciumafaia",
    "wof:placetype":"locality",
    "wof:population":190
},
  "geometry": {"coordinates":[23.62272,46.94372],"type":"Point"}
}