{
  "type": "Feature",
  "properties": {
    "gn:admin1_code":"26",
    "gn:admin2_code":"112370.0",
    "gn:asciiname":"Draghesti",
    "gn:cc2":"RO",
    "gn:country_code":"RO",
    "gn:dem":542,
    "gn:feature_class":"P",
    "gn:feature_code":"PPL",
    "gn:name":"Dr\u0103ghe\u0219ti",
    "gn:population":238,
    "gn:timezone":"Europe/Bucharest",
    "iso:country":"RO",
    "name:und_x_variant":[
        "Dr\u0103ghie\u015fti",
        "Dr\u0103ghe\u015fti"
    ],
    "wof:name":"Draghesti",
    "wof:placetype":"locality",
    "wof:population":238
},
  "geometry": {"coordinates":[22.67628,44.98626],"type":"Point"}
}