{
  "type": "Feature",
  "properties": {
    "gn:admin1_code":"02",
    "gn:admin2_code":"11174.0",
    "gn:asciiname":"Luncsoara",
    "gn:country_code":"RO",
    "gn:dem":433,
    "gn:feature_class":"P",
    "gn:feature_code":"PPL",
    "gn:name":"Lunc\u0219oara",
    "gn:population":644,
    "gn:timezone":"Europe/Bucharest",
    "iso:country":"RO",
    "name:ron_x_preferred":[
        "Lunc\u0219oara"
    ],
    "name:und_x_variant":[
        "Lunksora",
        "Hossz\u00fasor",
        "Vo\u015fdoci Lung\u015foara",
        "Lungsora"
    ],
    "wof:name":"Luncsoara",
    "wof:placetype":"locality",
    "wof:population":644
},
  "geometry": {"coordinates":[22.62773,46.32113],"type":"Point"}
}