{
  "type": "Feature",
  "properties": {
    "gn:admin1_code":"28",
    "gn:admin2_code":"122551.0",
    "gn:asciiname":"Stejaru",
    "gn:cc2":"RO",
    "gn:country_code":"RO",
    "gn:dem":563,
    "gn:feature_class":"P",
    "gn:feature_code":"PPL",
    "gn:name":"Stejaru",
    "gn:population":752,
    "gn:timezone":"Europe/Bucharest",
    "iso:country":"RO",
    "name:ceb_x_preferred":[
        "Stejaru"
    ],
    "name:deu_x_preferred":[
        "Stejaru"
    ],
    "name:ita_x_preferred":[
        "Stejaru"
    ],
    "name:ron_x_preferred":[
        "Stejaru"
    ],
    "name:srp_x_preferred":[
        "\u0421\u0442\u0435\u0436\u0430\u0440\u0443"
    ],
    "name:und_x_variant":[
        "Stejarul",
        "Stejaru"
    ],
    "wof:name":"Stejaru",
    "wof:placetype":"locality",
    "wof:population":752
},
  "geometry": {"coordinates":[25.82422,47.15892],"type":"Point"}
}