{
  "type": "Feature",
  "properties": {
    "gn:admin1_code":"17",
    "gn:admin2_code":"70174.0",
    "gn:asciiname":"Milesti",
    "gn:country_code":"RO",
    "gn:dem":159,
    "gn:feature_class":"P",
    "gn:feature_code":"PPL",
    "gn:name":"Mile\u0219ti",
    "gn:population":651,
    "gn:timezone":"Europe/Bucharest",
    "iso:country":"RO",
    "wof:name":"Milesti",
    "wof:placetype":"locality",
    "wof:population":651
},
  "geometry": {"coordinates":[23.78633,44.45018],"type":"Point"}
}