{
  "type": "Feature",
  "properties": {
    "gn:admin1_code":"29",
    "gn:admin2_code":"130026.0",
    "gn:asciiname":"Vladila Noua",
    "gn:country_code":"RO",
    "gn:dem":99,
    "gn:feature_class":"P",
    "gn:feature_code":"PPL",
    "gn:name":"Vl\u0103dila Nou\u0103",
    "gn:population":498,
    "gn:timezone":"Europe/Bucharest",
    "iso:country":"RO",
    "wof:name":"Vladila Noua",
    "wof:placetype":"locality",
    "wof:population":498
},
  "geometry": {"coordinates":[24.40883,44.00368],"type":"Point"}
}