{
  "type": "Feature",
  "properties": {
    "gn:admin1_code":"23",
    "gn:admin2_code":"96940",
    "gn:asciiname":"Banu",
    "gn:cc2":"RO",
    "gn:country_code":"RO",
    "gn:dem":54,
    "gn:feature_class":"P",
    "gn:feature_code":"PPL",
    "gn:name":"Banu",
    "gn:population":326,
    "gn:timezone":"Europe/Bucharest",
    "iso:country":"RO",
    "name:bre_x_preferred":[
        "Banu"
    ],
    "name:deu_x_preferred":[
        "Banu"
    ],
    "name:rus_x_preferred":[
        "\u0411\u0430\u043d\u0443"
    ],
    "name:und_x_variant":[
        "C\u0103c\u0103rezeni"
    ],
    "wof:name":"Banu",
    "wof:placetype":"locality",
    "wof:population":326
},
  "geometry": {"coordinates":[27.37219,47.1904],"type":"Point"}
}