{
  "type": "Feature",
  "properties": {
    "gn:gn_country":"RO",
    "gn:gn_fcode":"PPLA2",
    "gn:gn_pop":4650,
    "gn:population":4650,
    "iso:country":"RO",
    "name:eng_x_preferred":[
        "Dorna Candrenilor"
    ],
    "name:fra_x_preferred":[
        "Dorna Candrenilor"
    ],
    "name:hun_x_preferred":[
        "Dorna Candrenilor"
    ],
    "name:ita_x_preferred":[
        "Dorna Candrenilor"
    ],
    "name:nld_x_preferred":[
        "Dorna Candrenilor"
    ],
    "name:por_x_preferred":[
        "Dorna Candrenilor"
    ],
    "name:ron_x_preferred":[
        "Dorna Candrenilor"
    ],
    "name:srp_x_preferred":[
        "\u0414\u043e\u0440\u043d\u0430 \u041a\u0430\u043d\u0434\u0440\u0435\u043d\u0438\u043b\u043e\u0440"
    ],
    "name:ukr_x_preferred":[
        "\u0414\u043e\u0440\u043d\u0430-\u041a\u0430\u043d\u0434\u0440\u0435\u043d\u0456\u043b\u043e\u0440"
    ],
    "name:unk_x_variant":[
        "Dorna-C\u00e2ndrenilor"
    ],
    "name:vol_x_preferred":[
        "Dorna Candrenilor"
    ],
    "qs_pg:aaroncc":"RO",
    "qs_pg:gn_country":"RO",
    "qs_pg:gn_fcode":"PPLA2",
    "qs_pg:gn_pop":4650,
    "qs_pg:name":"Dorna C\u00e2ndrenilor",
    "qs_pg:photos_9r":0,
    "qs_pg:photos_sr":0,
    "qs_pg:pop_sr":4,
    "qs_pg:qs_pg_placetype":"locality",
    "wof:name":"Dorna C\u00e2ndrenilor",
    "wof:placetype":"locality",
    "wof:population":4650
},
  "geometry": {"coordinates":[25.25,47.35],"type":"Point"}
}