{
  "type": "Feature",
  "properties": {
    "gn:admin1_code":"07",
    "gn:admin2_code":"37397.0",
    "gn:asciiname":"Cracalia",
    "gn:country_code":"RO",
    "gn:dem":148,
    "gn:feature_class":"P",
    "gn:feature_code":"PPL",
    "gn:name":"Cracalia",
    "gn:population":0,
    "gn:timezone":"Europe/Bucharest",
    "iso:country":"RO",
    "wof:name":"Cracalia",
    "wof:placetype":"locality"
},
  "geometry": {"coordinates":[26.51667,48.01667],"type":"Point"}
}