{
  "type": "Feature",
  "properties": {
    "gn:admin1_code":"11",
    "gn:admin2_code":"46484.0",
    "gn:asciiname":"Spataru",
    "gn:country_code":"RO",
    "gn:dem":83,
    "gn:feature_class":"P",
    "gn:feature_code":"PPL",
    "gn:name":"Sp\u0103taru",
    "gn:population":874,
    "gn:timezone":"Europe/Bucharest",
    "iso:country":"RO",
    "wof:name":"Spataru",
    "wof:placetype":"locality",
    "wof:population":874
},
  "geometry": {"coordinates":[26.77895,45.0851],"type":"Point"}
}