{
  "type": "Feature",
  "properties": {
    "gn:admin1_code":"25",
    "gn:admin2_code":"107733.0",
    "gn:asciiname":"Vad",
    "gn:country_code":"RO",
    "gn:dem":278,
    "gn:feature_class":"P",
    "gn:feature_code":"PPL",
    "gn:name":"Vad",
    "gn:population":389,
    "gn:timezone":"Europe/Bucharest",
    "iso:country":"RO",
    "wof:name":"Vad",
    "wof:placetype":"locality",
    "wof:population":389
},
  "geometry": {"coordinates":[23.71161,47.52146],"type":"Point"}
}