{
  "type": "Feature",
  "properties": {
    "gn:admin1_code":"25",
    "gn:admin2_code":"107733.0",
    "gn:asciiname":"Vad",
    "gn:country_code":"RO",
    "gn:dem":278,
    "gn:feature_class":"P",
    "gn:feature_code":"PPL",
    "gn:name":"Vad",
    "gn:population":389,
    "gn:timezone":"Europe/Bucharest",
    "iso:country":"RO",
    "name:ceb_x_preferred":[
        "Vad"
    ],
    "name:deu_x_preferred":[
        "Vad"
    ],
    "name:hun_x_preferred":[
        "Vad"
    ],
    "name:nld_x_preferred":[
        "Vad"
    ],
    "name:nor_x_preferred":[
        "Vad"
    ],
    "name:por_x_preferred":[
        "Vad"
    ],
    "name:ron_x_preferred":[
        "Vad"
    ],
    "name:srp_x_preferred":[
        "\u0412\u0430\u0434"
    ],
    "name:swe_x_preferred":[
        "Vad"
    ],
    "name:vie_x_preferred":[
        "Vad"
    ],
    "wof:name":"Vad",
    "wof:placetype":"locality",
    "wof:population":389
},
  "geometry": {"coordinates":[23.71161,47.52146],"type":"Point"}
}