{
  "type": "Feature",
  "properties": {
    "gn:admin1_code":"39",
    "gn:admin2_code":"168372.0",
    "gn:asciiname":"Capu Dealului",
    "gn:cc2":"RO",
    "gn:country_code":"RO",
    "gn:dem":207,
    "gn:feature_class":"P",
    "gn:feature_code":"PPL",
    "gn:name":"Capu Dealului",
    "gn:population":245,
    "gn:timezone":"Europe/Bucharest",
    "iso:country":"RO",
    "name:und_x_variant":[
        "Capul Dealului",
        "Capu Dealului"
    ],
    "wof:name":"Capu Dealului",
    "wof:placetype":"locality",
    "wof:population":245
},
  "geometry": {"coordinates":[24.24355,44.98964],"type":"Point"}
}