{
  "type": "Feature",
  "properties": {
    "gn:admin1_code":"39",
    "gn:admin2_code":"168372.0",
    "gn:asciiname":"Capu Dealului",
    "gn:cc2":"RO",
    "gn:country_code":"RO",
    "gn:dem":207,
    "gn:feature_class":"P",
    "gn:feature_code":"PPL",
    "gn:name":"Capu Dealului",
    "gn:population":245,
    "gn:timezone":"Europe/Bucharest",
    "iso:country":"RO",
    "name:ceb_x_preferred":[
        "Capu Dealului"
    ],
    "name:deu_x_preferred":[
        "Capu Dealului"
    ],
    "name:ron_x_preferred":[
        "Capu Dealului"
    ],
    "name:srp_x_preferred":[
        "\u041a\u0430\u043f\u0443 \u0414\u0435\u0430\u043b\u0443\u043b\u0443\u0458"
    ],
    "name:und_x_variant":[
        "Capul Dealului"
    ],
    "wof:name":"Capu Dealului",
    "wof:placetype":"locality",
    "wof:population":245
},
  "geometry": {"coordinates":[24.24355,44.98964],"type":"Point"}
}