{
  "type": "Feature",
  "properties": {
    "gn:country":"RO",
    "gn:fcode":"PPLA2",
    "gn:population":3286,
    "iso:country":"RO",
    "name:ceb_x_preferred":[
        "Bolbo\u0219i"
    ],
    "name:eng_x_preferred":[
        "Bolbo\u0219i"
    ],
    "name:fra_x_preferred":[
        "Bolbo\u0219i"
    ],
    "name:ita_x_preferred":[
        "Bolbo\u0219i"
    ],
    "name:msa_x_preferred":[
        "Bolbo\u0219i"
    ],
    "name:nld_x_preferred":[
        "Bolbo\u0219i"
    ],
    "name:por_x_preferred":[
        "Bolbo\u0219i"
    ],
    "name:ron_x_preferred":[
        "Bolbo\u0219i"
    ],
    "name:srp_x_preferred":[
        "\u0411\u043e\u043b\u0431\u043e\u0448\u0438"
    ],
    "name:ukr_x_preferred":[
        "\u0411\u043e\u043b\u0431\u043e\u0448\u0456"
    ],
    "name:und_x_variant":[
        "Bolbo\u015fi"
    ],
    "name:vie_x_preferred":[
        "Bolbosi"
    ],
    "name:vol_x_preferred":[
        "Bolbo\u0219i"
    ],
    "qs_pg:aaroncc":"RO",
    "qs_pg:gn_country":"RO",
    "qs_pg:gn_fcode":"PPLA2",
    "qs_pg:gn_pop":3286,
    "qs_pg:name":"Bolbo\u0219i",
    "qs_pg:name_adm0":"Rom\u00e2nia",
    "qs_pg:name_adm1":"Gorj",
    "qs_pg:photos_9r":0,
    "qs_pg:photos_sr":0,
    "qs_pg:pop_sr":4,
    "qs_pg:qs_pg_placetype":"locality",
    "qs_pg:qs_pg_placetype_gp":"Town",
    "qs_pg:woe_adm0":23424933,
    "woe:adm0_id":23424933,
    "woe:name_adm0":"Rom\u00e2nia",
    "woe:name_adm1":"Gorj",
    "woe:placetype":"Town",
    "wof:name":"Bolbo\u0219i",
    "wof:placetype":"locality",
    "wof:population":3286
},
  "geometry": {"coordinates":[23.21667,44.75],"type":"Point"}
}