{
  "type": "Feature",
  "properties": {
    "gn:admin1_code":"03",
    "gn:admin2_code":"19392.0",
    "gn:asciiname":"Miercani",
    "gn:cc2":"RO",
    "gn:country_code":"RO",
    "gn:dem":471,
    "gn:feature_class":"P",
    "gn:feature_code":"PPL",
    "gn:name":"Miercani",
    "gn:population":224,
    "gn:timezone":"Europe/Bucharest",
    "iso:country":"RO",
    "name:und_x_variant":[
        "Mercani",
        "Miercani"
    ],
    "wof:name":"Miercani",
    "wof:placetype":"locality",
    "wof:population":224
},
  "geometry": {"coordinates":[24.58687,44.9262],"type":"Point"}
}