{
  "type": "Feature",
  "properties": {
    "gn:admin1_code":"26",
    "gn:admin2_code":"110571.0",
    "gn:asciiname":"Petra",
    "gn:country_code":"RO",
    "gn:dem":246,
    "gn:feature_class":"P",
    "gn:feature_code":"PPL",
    "gn:name":"Petra",
    "gn:population":366,
    "gn:timezone":"Europe/Bucharest",
    "iso:country":"RO",
    "wof:name":"Petra",
    "wof:placetype":"locality",
    "wof:population":366
},
  "geometry": {"coordinates":[23.09516,44.45889],"type":"Point"}
}