{
  "type": "Feature",
  "properties": {
    "gn:country":"RO",
    "gn:fcode":"PPL",
    "gn:population":0,
    "iso:country":"RO",
    "name:arz_x_preferred":[
        "\u0645\u0627\u0631\u0643\u0627 \u0647\u0648\u062a\u0627"
    ],
    "name:eng_x_preferred":[
        "Marca-Huta"
    ],
    "name:epo_x_preferred":[
        "Marca-Huta"
    ],
    "name:fra_x_preferred":[
        "Marca-Huta"
    ],
    "name:hun_x_preferred":[
        "Bulyovszkytelep"
    ],
    "name:nld_x_preferred":[
        "Marca-Huta"
    ],
    "name:ron_x_preferred":[
        "Marca-Huta"
    ],
    "name:srp_x_preferred":[
        "\u041c\u0430\u0440\u043a\u0430 \u0425\u0443\u0442\u0430"
    ],
    "name:ukr_x_preferred":[
        "\u041c\u0430\u0440\u043a\u0430-\u0425\u0443\u0442\u0430"
    ],
    "qs_pg:aaroncc":"RO",
    "qs_pg:gn_country":"RO",
    "qs_pg:gn_fcode":"PPL",
    "qs_pg:gn_pop":0,
    "qs_pg:name":"Marca Huta",
    "qs_pg:name_adm0":"Rom\u00e2nia",
    "qs_pg:name_adm1":"Salaj",
    "qs_pg:photos":16,
    "qs_pg:photos_1k":3,
    "qs_pg:photos_9k":1,
    "qs_pg:photos_9r":1,
    "qs_pg:photos_all":16,
    "qs_pg:photos_sr":1,
    "qs_pg:pop_sr":0,
    "qs_pg:qs_pg_placetype":"locality",
    "qs_pg:qs_pg_placetype_gp":"Town",
    "qs_pg:woe_adm0":23424933,
    "woe:adm0_id":23424933,
    "woe:name_adm0":"Rom\u00e2nia",
    "woe:name_adm1":"Salaj",
    "woe:placetype":"Town",
    "wof:name":"Marca Huta",
    "wof:placetype":"locality",
    "wof:population":80
},
  "geometry": {"coordinates":[22.55,47.21667],"type":"Point"}
}