{
  "type": "Feature",
  "properties": {
    "gn:admin1_code":"30",
    "gn:admin2_code":"130785.0",
    "gn:asciiname":"Valea Orlei",
    "gn:cc2":"RO",
    "gn:country_code":"RO",
    "gn:dem":175,
    "gn:feature_class":"P",
    "gn:feature_code":"PPL",
    "gn:name":"Valea Orlei",
    "gn:population":148,
    "gn:timezone":"Europe/Bucharest",
    "iso:country":"RO",
    "name:und_x_variant":[
        "Valea Orli\u0163ei",
        "Valea Orlei"
    ],
    "wof:name":"Valea Orlei",
    "wof:placetype":"locality",
    "wof:population":148
},
  "geometry": {"coordinates":[26.12477,44.97089],"type":"Point"}
}