{
  "type": "Feature",
  "properties": {
    "gn:admin1_code":"32",
    "gn:admin2_code":"138805.0",
    "gn:asciiname":"Chisau",
    "gn:country_code":"RO",
    "gn:dem":147,
    "gn:feature_class":"P",
    "gn:feature_code":"PPL",
    "gn:name":"Chis\u0103u",
    "gn:population":131,
    "gn:timezone":"Europe/Bucharest",
    "iso:country":"RO",
    "wof:name":"Chisau",
    "wof:placetype":"locality",
    "wof:population":131
},
  "geometry": {"coordinates":[22.4446,47.46145],"type":"Point"}
}