{
  "type": "Feature",
  "properties": {
    "gn:admin1_code":"18",
    "gn:admin2_code":"77331.0",
    "gn:asciiname":"Tatarca",
    "gn:country_code":"RO",
    "gn:dem":30,
    "gn:feature_class":"P",
    "gn:feature_code":"PPL",
    "gn:name":"T\u0103tarca",
    "gn:population":839,
    "gn:timezone":"Europe/Bucharest",
    "iso:country":"RO",
    "wof:name":"Tatarca",
    "wof:placetype":"locality",
    "wof:population":839
},
  "geometry": {"coordinates":[28.05177,45.59875],"type":"Point"}
}