{
  "type": "Feature",
  "properties": {
    "gn:admin1_code":"26",
    "gn:admin2_code":"110296.0",
    "gn:asciiname":"Vidimiresti",
    "gn:country_code":"RO",
    "gn:dem":237,
    "gn:feature_class":"P",
    "gn:feature_code":"PPL",
    "gn:name":"Vidimire\u0219ti",
    "gn:population":223,
    "gn:timezone":"Europe/Bucharest",
    "iso:country":"RO",
    "wof:name":"Vidimiresti",
    "wof:placetype":"locality",
    "wof:population":223
},
  "geometry": {"coordinates":[22.82538,44.85967],"type":"Point"}
}