{
  "type": "Feature",
  "properties": {
    "gn:admin1_code":"41",
    "gn:admin2_code":"105455.0",
    "gn:asciiname":"Seinoiu",
    "gn:cc2":"RO",
    "gn:country_code":"RO",
    "gn:dem":60,
    "gn:feature_class":"P",
    "gn:feature_code":"PPL",
    "gn:name":"\u0218einoiu",
    "gn:population":286,
    "gn:timezone":"Europe/Bucharest",
    "iso:country":"RO",
    "name:und_x_variant":[
        "Seinoiul",
        "\u015eeinoiu"
    ],
    "wof:name":"Seinoiu",
    "wof:placetype":"locality",
    "wof:population":286
},
  "geometry": {"coordinates":[26.57875,44.44081],"type":"Point"}
}