{
  "type": "Feature",
  "properties": {
    "gn:admin1_code":"05",
    "gn:admin2_code":"28415.0",
    "gn:asciiname":"Susturogi",
    "gn:cc2":"RO",
    "gn:country_code":"RO",
    "gn:dem":200,
    "gn:feature_class":"P",
    "gn:feature_code":"PPL",
    "gn:name":"\u0218u\u0219turogi",
    "gn:population":384,
    "gn:timezone":"Europe/Bucharest",
    "iso:country":"RO",
    "name:und_x_variant":[
        "\u015eu\u015ftorog",
        "\u015eu\u015fturoj",
        "Su\u015fturoi",
        "\u015eu\u015fturogi"
    ],
    "wof:name":"Susturogi",
    "wof:placetype":"locality",
    "wof:population":384
},
  "geometry": {"coordinates":[22.11206,47.14125],"type":"Point"}
}