{
  "type": "Feature",
  "properties": {
    "gn:gn_country":"RO",
    "gn:gn_fcode":"PPLA2",
    "gn:gn_pop":1333,
    "gn:population":1333,
    "iso:country":"RO",
    "name:alb_x_preferred":[
        "Ciuruleasa"
    ],
    "name:ara_x_preferred":[
        "\u062a\u0634\u0648\u0631\u0648\u0644\u064a\u0627\u0633\u0627"
    ],
    "name:dut_x_preferred":[
        "Ciuruleasa"
    ],
    "name:eng_x_preferred":[
        "Ciuruleasa"
    ],
    "name:epo_x_preferred":[
        "Ciuruleasa"
    ],
    "name:fre_x_preferred":[
        "Ciuruleasa"
    ],
    "name:ger_x_preferred":[
        "Ciuruleasa"
    ],
    "name:hun_x_preferred":[
        "Csuruly\u00e1sza"
    ],
    "name:ita_x_preferred":[
        "Ciuruleasa"
    ],
    "name:mac_x_preferred":[
        "\u0427\u0443\u0440\u0443\u043b\u0435\u0430\u0441\u0430"
    ],
    "name:may_x_preferred":[
        "Ciuruleasa"
    ],
    "name:por_x_preferred":[
        "Ciuruleasa"
    ],
    "name:rum_x_preferred":[
        "Ciuruleasa"
    ],
    "name:ukr_x_preferred":[
        "\u0427\u0443\u0440\u0443\u043b\u044f\u0441\u0430"
    ],
    "name:unk_x_variant":[
        "Abrud-Sat-Ciuruleasa"
    ],
    "name:vie_x_preferred":[
        "Ciuruleasa"
    ],
    "name:vol_x_preferred":[
        "Ciuruleasa"
    ],
    "qs_pg:aaroncc":"RO",
    "qs_pg:gn_country":"RO",
    "qs_pg:gn_fcode":"PPLA2",
    "qs_pg:gn_pop":1333,
    "qs_pg:name":"Ciuruleasa",
    "qs_pg:name_adm0":"Rom\u00e2nia",
    "qs_pg:name_adm1":"Alba",
    "qs_pg:photos_9r":0,
    "qs_pg:photos_sr":0,
    "qs_pg:pop_sr":3,
    "qs_pg:qs_pg_placetype":"locality",
    "qs_pg:qs_pg_placetype_gp":"Town",
    "qs_pg:woe_adm0":23424933,
    "woe:adm0_id":23424933,
    "woe:name_adm0":"Rom\u00e2nia",
    "woe:name_adm1":"Alba",
    "woe:placetype":"Town",
    "wof:name":"Ciuruleasa",
    "wof:placetype":"locality",
    "wof:population":1333
},
  "geometry": {"coordinates":[23.03333,46.25],"type":"Point"}
}