{
  "type": "Feature",
  "properties": {
    "gn:admin1_code":"18",
    "gn:admin2_code":"75864.0",
    "gn:asciiname":"Comanesti",
    "gn:country_code":"RO",
    "gn:dem":165,
    "gn:feature_class":"P",
    "gn:feature_code":"PPL",
    "gn:name":"Com\u0103ne\u0219ti",
    "gn:population":286,
    "gn:timezone":"Europe/Bucharest",
    "iso:country":"RO",
    "wof:name":"Comanesti",
    "wof:placetype":"locality",
    "wof:population":286
},
  "geometry": {"coordinates":[27.9671,46.09924],"type":"Point"}
}