{
  "type": "Feature",
  "properties": {
    "gn:admin1_code":"27",
    "gn:admin2_code":"118637.0",
    "gn:asciiname":"Dobra",
    "gn:country_code":"RO",
    "gn:dem":427,
    "gn:feature_class":"P",
    "gn:feature_code":"PPL",
    "gn:name":"Dobra",
    "gn:population":69,
    "gn:timezone":"Europe/Bucharest",
    "iso:country":"RO",
    "wof:name":"Dobra",
    "wof:placetype":"locality",
    "wof:population":69
},
  "geometry": {"coordinates":[24.23735,46.58142],"type":"Point"}
}