{
  "type": "Feature",
  "properties": {
    "gn:admin1_code":"18",
    "gn:admin2_code":"75356.0",
    "gn:asciiname":"Onciu",
    "gn:cc2":"RO",
    "gn:country_code":"RO",
    "gn:dem":180,
    "gn:feature_class":"P",
    "gn:feature_code":"PPL",
    "gn:name":"Onciu",
    "gn:population":44,
    "gn:timezone":"Europe/Bucharest",
    "iso:country":"RO",
    "name:und_x_variant":[
        "Onciul",
        "Onciu"
    ],
    "wof:name":"Onciu",
    "wof:placetype":"locality",
    "wof:population":44
},
  "geometry": {"coordinates":[27.9501,46.05588],"type":"Point"}
}