{
  "type": "Feature",
  "properties": {
    "gn:population":1295,
    "iso:country":"RO",
    "name:dut_x_preferred":[
        "Telci\u0219or"
    ],
    "name:eng_x_preferred":[
        "Telci\u0219or"
    ],
    "name:fre_x_preferred":[
        "Telci\u0219or"
    ],
    "name:hun_x_preferred":[
        "Telci\u0219or"
    ],
    "name:ita_x_preferred":[
        "Telci\u0219or"
    ],
    "name:rum_x_preferred":[
        "Telci\u0219or"
    ],
    "name:ukr_x_preferred":[
        "\u0422\u0435\u043b\u0447\u0438\u0448\u043e\u0440"
    ],
    "qs:a0":"Rom\u00e2nia",
    "qs:a1":"*Bistrita-Nasaud",
    "qs:a1r":"0",
    "qs:adm0":"Rom\u00e2nia",
    "qs:la_lc":"*",
    "qs:level":"locality",
    "qs:loc":"Telci\u015for",
    "qs:loc_alt":"Telcisor",
    "qs:pop":0,
    "qs:type":"buffered point",
    "wof:name":"Telci\u015for",
    "wof:placetype":"locality",
    "wof:population":1295
},
  "geometry": {"coordinates":[24.430029,47.447465],"type":"Point"}
}