{
  "type": "Feature",
  "properties": {
    "gn:admin1_code":"23",
    "gn:admin2_code":"98505.0",
    "gn:asciiname":"Cuza Voda",
    "gn:country_code":"RO",
    "gn:dem":84,
    "gn:feature_class":"P",
    "gn:feature_code":"PPL",
    "gn:name":"Cuza Vod\u0103",
    "gn:population":478,
    "gn:timezone":"Europe/Bucharest",
    "iso:country":"RO",
    "wof:name":"Cuza Voda",
    "wof:placetype":"locality",
    "wof:population":478
},
  "geometry": {"coordinates":[27.57393,47.23639],"type":"Point"}
}