{
  "type": "Feature",
  "properties": {
    "gn:admin1_code":"08",
    "gn:admin2_code":"43019.0",
    "gn:asciiname":"Vultureni",
    "gn:cc2":"RO",
    "gn:country_code":"RO",
    "gn:dem":44,
    "gn:feature_class":"P",
    "gn:feature_code":"PPL",
    "gn:name":"Vultureni",
    "gn:population":704,
    "gn:timezone":"Europe/Bucharest",
    "iso:country":"RO",
    "name:ceb_x_preferred":[
        "Vultureni"
    ],
    "name:deu_x_preferred":[
        "Vultureni"
    ],
    "name:hun_x_preferred":[
        "Vultureni"
    ],
    "name:ita_x_preferred":[
        "Vultureni"
    ],
    "name:ron_x_preferred":[
        "Vultureni"
    ],
    "name:srp_x_preferred":[
        "\u0412\u0443\u043b\u0442\u0443\u0440\u0435\u043d\u0438"
    ],
    "name:und_x_variant":[
        "Grigorescu",
        "Colonel Anastase Grigorescu"
    ],
    "wof:name":"Vultureni",
    "wof:placetype":"locality",
    "wof:population":704
},
  "geometry": {"coordinates":[27.3648,44.94008],"type":"Point"}
}