{
  "type": "Feature",
  "properties": {
    "gn:admin1_code":"05",
    "gn:admin2_code":"27971",
    "gn:asciiname":"Bradet",
    "gn:country_code":"RO",
    "gn:dem":321,
    "gn:feature_class":"P",
    "gn:feature_code":"PPL",
    "gn:name":"Br\u0103det",
    "gn:population":739,
    "gn:timezone":"Europe/Bucharest",
    "iso:country":"RO",
    "name:ron_x_preferred":[
        "Br\u0103det"
    ],
    "name:und_x_variant":[
        "Biharfenyves",
        "Bragyet"
    ],
    "wof:name":"Bradet",
    "wof:placetype":"locality",
    "wof:population":739
},
  "geometry": {"coordinates":[22.53213,46.58302],"type":"Point"}
}