{
  "type": "Feature",
  "properties": {
    "gn:admin1_code":"21",
    "gn:admin2_code":"88546.0",
    "gn:asciiname":"Rovina",
    "gn:cc2":"RO",
    "gn:country_code":"RO",
    "gn:dem":205,
    "gn:feature_class":"P",
    "gn:feature_code":"PPL",
    "gn:name":"Rovina",
    "gn:population":219,
    "gn:timezone":"Europe/Bucharest",
    "iso:country":"RO",
    "name:und_x_variant":[
        "Bicheu",
        "Bic\u0103u",
        "Rovina"
    ],
    "wof:name":"Rovina",
    "wof:placetype":"locality",
    "wof:population":219
},
  "geometry": {"coordinates":[22.78842,45.92627],"type":"Point"}
}