{
  "type": "Feature",
  "properties": {
    "gn:admin1_code":"21",
    "gn:admin2_code":"88546.0",
    "gn:asciiname":"Rovina",
    "gn:cc2":"RO",
    "gn:country_code":"RO",
    "gn:dem":205,
    "gn:feature_class":"P",
    "gn:feature_code":"PPL",
    "gn:name":"Rovina",
    "gn:population":219,
    "gn:timezone":"Europe/Bucharest",
    "iso:country":"RO",
    "name:ceb_x_preferred":[
        "Rovina"
    ],
    "name:ces_x_preferred":[
        "Rovina"
    ],
    "name:deu_x_preferred":[
        "Rovina"
    ],
    "name:epo_x_preferred":[
        "Rovina"
    ],
    "name:heb_x_preferred":[
        "\u05e8\u05d5\u05d1\u05d9\u05e0\u05d0"
    ],
    "name:rus_x_preferred":[
        "\u0420\u043e\u0432\u0438\u043d\u0430"
    ],
    "name:slk_x_preferred":[
        "Rovina"
    ],
    "name:srp_x_preferred":[
        "Rovina"
    ],
    "name:swe_x_preferred":[
        "Rovina"
    ],
    "name:und_x_variant":[
        "Bicheu",
        "Bic\u0103u"
    ],
    "wof:name":"Rovina",
    "wof:placetype":"locality",
    "wof:population":219
},
  "geometry": {"coordinates":[22.78842,45.92627],"type":"Point"}
}