{
  "type": "Feature",
  "properties": {
    "gn:admin1_code":"11",
    "gn:admin2_code":"45815.0",
    "gn:asciiname":"Vizireni",
    "gn:country_code":"RO",
    "gn:dem":47,
    "gn:feature_class":"P",
    "gn:feature_code":"PPL",
    "gn:name":"Vizireni",
    "gn:population":474,
    "gn:timezone":"Europe/Bucharest",
    "iso:country":"RO",
    "wof:name":"Vizireni",
    "wof:placetype":"locality",
    "wof:population":474
},
  "geometry": {"coordinates":[27.19693,45.04965],"type":"Point"}
}