{
  "type": "Feature",
  "properties": {
    "gn:admin1_code":"29",
    "gn:admin2_code":"127625.0",
    "gn:asciiname":"Morunesti",
    "gn:country_code":"RO",
    "gn:dem":180,
    "gn:feature_class":"P",
    "gn:feature_code":"PPL",
    "gn:name":"Morune\u0219ti",
    "gn:population":409,
    "gn:timezone":"Europe/Bucharest",
    "iso:country":"RO",
    "wof:name":"Morunesti",
    "wof:placetype":"locality",
    "wof:population":409
},
  "geometry": {"coordinates":[24.12624,44.47992],"type":"Point"}
}