{
  "type": "Feature",
  "properties": {
    "gn:admin1_code":"27",
    "gn:admin2_code":"119466.0",
    "gn:asciiname":"Chirileu",
    "gn:cc2":"RO",
    "gn:country_code":"RO",
    "gn:dem":291,
    "gn:feature_class":"P",
    "gn:feature_code":"PPL",
    "gn:name":"Chirileu",
    "gn:population":582,
    "gn:timezone":"Europe/Bucharest",
    "iso:country":"RO",
    "name:und_x_variant":[
        "Chirileul",
        "Chirileu"
    ],
    "wof:name":"Chirileu",
    "wof:placetype":"locality",
    "wof:population":582
},
  "geometry": {"coordinates":[24.38296,46.47664],"type":"Point"}
}