{
  "type": "Feature",
  "properties": {
    "gn:admin1_code":"07",
    "gn:admin2_code":"36373.0",
    "gn:asciiname":"Pristesti",
    "gn:country_code":"RO",
    "gn:dem":270,
    "gn:feature_class":"P",
    "gn:feature_code":"PPL",
    "gn:name":"Priste\u015fti",
    "gn:population":0,
    "gn:timezone":"Europe/Bucharest",
    "iso:country":"RO",
    "wof:lang_x_official":[
        "ron"
    ],
    "wof:lang_x_spoken":[
        "ron"
    ],
    "wof:name":"Pristesti",
    "wof:placetype":"locality"
},
  "geometry": {"coordinates":[26.43333,47.85],"type":"Point"}
}