{
  "type": "Feature",
  "properties": {
    "gn:admin1_code":"03",
    "gn:admin2_code":"16757.0",
    "gn:asciiname":"Ciolcesti",
    "gn:country_code":"RO",
    "gn:dem":258,
    "gn:feature_class":"P",
    "gn:feature_code":"PPL",
    "gn:name":"Ciolce\u0219ti",
    "gn:population":163,
    "gn:timezone":"Europe/Bucharest",
    "iso:country":"RO",
    "wof:name":"Ciolcesti",
    "wof:placetype":"locality",
    "wof:population":163
},
  "geometry": {"coordinates":[25.1997,44.79844],"type":"Point"}
}