{
  "type": "Feature",
  "properties": {
    "gn:admin1_code":"17",
    "gn:admin2_code":"72533.0",
    "gn:asciiname":"Curmatura",
    "gn:country_code":"RO",
    "gn:dem":64,
    "gn:feature_class":"P",
    "gn:feature_code":"PPL",
    "gn:name":"Curm\u0103tura",
    "gn:population":688,
    "gn:timezone":"Europe/Bucharest",
    "iso:country":"RO",
    "wof:name":"Curmatura",
    "wof:placetype":"locality",
    "wof:population":688
},
  "geometry": {"coordinates":[23.63884,44.0031],"type":"Point"}
}