{
  "type": "Feature",
  "properties": {
    "iso:country":"RO",
    "qs_pg:aaroncc":"RO",
    "qs_pg:name":"Rom\u00eene\u0219ti",
    "qs_pg:name_adm0":"Rom\u00e2nia",
    "qs_pg:name_adm1":"Sibiu",
    "qs_pg:photos":103,
    "qs_pg:photos_1k":21,
    "qs_pg:photos_9k":1,
    "qs_pg:photos_9r":3,
    "qs_pg:photos_all":103,
    "qs_pg:photos_sr":3,
    "qs_pg:pop_sr":0,
    "qs_pg:qs_pg_placetype":"locality",
    "qs_pg:qs_pg_placetype_gp":"Town",
    "qs_pg:woe_adm0":23424933,
    "woe:adm0_id":23424933,
    "woe:name_adm0":"Rom\u00e2nia",
    "woe:name_adm1":"Sibiu",
    "woe:placetype":"Town",
    "wof:name":"Rom\u00eene\u0219ti",
    "wof:placetype":"locality"
},
  "geometry": {"coordinates":[24.304847,46.195873],"type":"Point"}
}