{
  "type": "Feature",
  "properties": {
    "gn:admin1_code":"26",
    "gn:admin2_code":"112600.0",
    "gn:asciiname":"Petris",
    "gn:cc2":"RO",
    "gn:country_code":"RO",
    "gn:dem":179,
    "gn:feature_class":"P",
    "gn:feature_code":"PPL",
    "gn:name":"Petri\u0219",
    "gn:population":163,
    "gn:timezone":"Europe/Bucharest",
    "iso:country":"RO",
    "name:und_x_variant":[
        "Petri\u015fu",
        "Petri\u015ful",
        "Petri\u015f"
    ],
    "wof:name":"Petris",
    "wof:placetype":"locality",
    "wof:population":163
},
  "geometry": {"coordinates":[22.86191,44.53923],"type":"Point"}
}