{
  "type": "Feature",
  "properties": {
    "gn:admin1_code":"01",
    "gn:admin2_code":"3459.0",
    "gn:asciiname":"Valcea",
    "gn:country_code":"RO",
    "gn:dem":758,
    "gn:feature_class":"P",
    "gn:feature_code":"PPL",
    "gn:name":"V\u00e2lcea",
    "gn:population":45,
    "gn:timezone":"Europe/Bucharest",
    "iso:country":"RO",
    "wof:name":"Valcea",
    "wof:placetype":"locality",
    "wof:population":45
},
  "geometry": {"coordinates":[23.16365,46.26622],"type":"Point"}
}