{
  "type": "Feature",
  "properties": {
    "gn:admin1_code":"27",
    "gn:admin2_code":"117426",
    "gn:asciiname":"Arsita",
    "gn:country_code":"RO",
    "gn:dem":661,
    "gn:feature_class":"P",
    "gn:feature_code":"PPL",
    "gn:name":"Ar\u0219i\u021ba",
    "gn:population":74,
    "gn:timezone":"Europe/Bucharest",
    "iso:country":"RO",
    "name:ara_x_preferred":[
        "\u0623\u0631\u0633\u064a\u062a\u0627"
    ],
    "name:azb_x_preferred":[
        "\u0622\u0631\u0633\u06cc\u062a\u0627"
    ],
    "name:bcl_x_preferred":[
        "Arsita"
    ],
    "name:bel_x_preferred":[
        "\u0410\u0440\u0441\u0456\u0442\u0430"
    ],
    "name:bul_x_preferred":[
        "\u0410\u0440\u0441\u0438\u0442\u0430"
    ],
    "name:ceb_x_preferred":[
        "Arsita"
    ],
    "name:deu_x_preferred":[
        "Arsita"
    ],
    "name:epo_x_preferred":[
        "Arsita"
    ],
    "name:eus_x_preferred":[
        "Arsita"
    ],
    "name:fas_x_preferred":[
        "\u0622\u0631\u0633\u06cc\u062a\u0627"
    ],
    "name:fra_x_preferred":[
        "Arsita"
    ],
    "name:glg_x_preferred":[
        "Arsita"
    ],
    "name:hun_x_preferred":[
        "\u00c1rsica"
    ],
    "name:hun_x_variant":[
        "Arsita"
    ],
    "name:hye_x_preferred":[
        "\u0531\u0580\u057d\u056b\u057f\u0561"
    ],
    "name:ina_x_preferred":[
        "Arsita"
    ],
    "name:ita_x_preferred":[
        "Arsita"
    ],
    "name:jpn_x_preferred":[
        "\u30a2\u30eb\u30b7\u30fc\u30bf"
    ],
    "name:kaz_x_preferred":[
        "\u0410\u0440\u0441\u0438\u0442\u0430"
    ],
    "name:kor_x_preferred":[
        "\uc544\ub974\uc2dc\ud0c0"
    ],
    "name:lat_x_preferred":[
        "Bacucchum"
    ],
    "name:lmo_x_preferred":[
        "Arsita"
    ],
    "name:msa_x_preferred":[
        "Arsita"
    ],
    "name:nap_x_preferred":[
        "Arsita"
    ],
    "name:nld_x_preferred":[
        "Arsita"
    ],
    "name:nor_x_preferred":[
        "Arsita"
    ],
    "name:pms_x_preferred":[
        "Arsita"
    ],
    "name:pol_x_preferred":[
        "Arsita"
    ],
    "name:por_x_preferred":[
        "Arsita"
    ],
    "name:ron_x_preferred":[
        "Arsita"
    ],
    "name:rus_x_preferred":[
        "\u0410\u0440\u0441\u0438\u0442\u0430"
    ],
    "name:scn_x_preferred":[
        "Arsita"
    ],
    "name:spa_x_preferred":[
        "Arsita"
    ],
    "name:srp_x_preferred":[
        "\u0410\u0440\u0441\u0438\u0442\u0430"
    ],
    "name:tgl_x_preferred":[
        "Arsita"
    ],
    "name:ukr_x_preferred":[
        "\u0410\u0440\u0441\u0456\u0442\u0430"
    ],
    "name:uzb_x_preferred":[
        "Arsita"
    ],
    "name:vie_x_preferred":[
        "Arsita"
    ],
    "name:vol_x_preferred":[
        "Arsita"
    ],
    "name:war_x_preferred":[
        "Arsita"
    ],
    "name:zho_x_preferred":[
        "\u963f\u5c14\u897f\u5854"
    ],
    "wof:name":"Arsita",
    "wof:placetype":"locality",
    "wof:population":74
},
  "geometry": {"coordinates":[24.99571,46.78737],"type":"Point"}
}