{
  "type": "Feature",
  "properties": {
    "gn:admin1_code":"27",
    "gn:admin2_code":"117426",
    "gn:asciiname":"Arsita",
    "gn:country_code":"RO",
    "gn:dem":661,
    "gn:feature_class":"P",
    "gn:feature_code":"PPL",
    "gn:name":"Ar\u0219i\u021ba",
    "gn:population":74,
    "gn:timezone":"Europe/Bucharest",
    "iso:country":"RO",
    "name:hun_x_preferred":[
        "\u00c1rsica"
    ],
    "wof:name":"Arsita",
    "wof:placetype":"locality",
    "wof:population":74
},
  "geometry": {"coordinates":[24.99571,46.78737],"type":"Point"}
}