{
  "type": "Feature",
  "properties": {
    "gn:admin1_code":"18",
    "gn:admin2_code":"76497.0",
    "gn:asciiname":"Posta",
    "gn:cc2":"RO",
    "gn:country_code":"RO",
    "gn:dem":50,
    "gn:feature_class":"P",
    "gn:feature_code":"PPL",
    "gn:name":"Po\u0219ta",
    "gn:population":232,
    "gn:timezone":"Europe/Bucharest",
    "iso:country":"RO",
    "name:cat_x_preferred":[
        "Posta"
    ],
    "name:ceb_x_preferred":[
        "Posta"
    ],
    "name:deu_x_preferred":[
        "Posta"
    ],
    "name:hun_x_preferred":[
        "Posta"
    ],
    "name:ita_x_preferred":[
        "Posta"
    ],
    "name:kaz_x_preferred":[
        "\u041f\u043e\u0441\u0442\u0430"
    ],
    "name:por_x_preferred":[
        "Posta"
    ],
    "name:rus_x_preferred":[
        "\u041f\u043e\u0441\u0442\u0430"
    ],
    "name:srp_x_preferred":[
        "Posta"
    ],
    "name:swe_x_preferred":[
        "Posta"
    ],
    "name:und_x_variant":[
        "Berhecu",
        "Po\u015fta"
    ],
    "wof:name":"Posta",
    "wof:placetype":"locality",
    "wof:population":232
},
  "geometry": {"coordinates":[27.44435,45.98494],"type":"Point"}
}