{
  "type": "Feature",
  "properties": {
    "gn:admin1_code":"06",
    "gn:admin2_code":"33122.0",
    "gn:asciiname":"Piatra",
    "gn:country_code":"RO",
    "gn:dem":283,
    "gn:feature_class":"P",
    "gn:feature_code":"PPL",
    "gn:name":"Piatra",
    "gn:population":551,
    "gn:timezone":"Europe/Bucharest",
    "iso:country":"RO",
    "wof:name":"Piatra",
    "wof:placetype":"locality",
    "wof:population":551
},
  "geometry": {"coordinates":[24.2657,47.24875],"type":"Point"}
}