{
  "type": "Feature",
  "properties": {
    "gn:admin1_code":"15",
    "gn:admin2_code":"63688.0",
    "gn:asciiname":"Crasna",
    "gn:cc2":"RO",
    "gn:country_code":"RO",
    "gn:dem":660,
    "gn:feature_class":"P",
    "gn:feature_code":"PPL",
    "gn:name":"Crasna",
    "gn:population":585,
    "gn:timezone":"Europe/Bucharest",
    "iso:country":"RO",
    "name:ceb_x_preferred":[
        "Crasna"
    ],
    "name:deu_x_preferred":[
        "Crasna"
    ],
    "name:epo_x_preferred":[
        "Crasna"
    ],
    "name:fra_x_preferred":[
        "Crasna"
    ],
    "name:ita_x_preferred":[
        "Crasna"
    ],
    "name:nld_x_preferred":[
        "Crasna"
    ],
    "name:por_x_preferred":[
        "Crasna"
    ],
    "name:ron_x_preferred":[
        "Crasna"
    ],
    "name:swe_x_preferred":[
        "Crasna"
    ],
    "name:und_x_variant":[
        "Kraszna",
        "Grasna"
    ],
    "name:vol_x_preferred":[
        "Crasna"
    ],
    "wof:name":"Crasna",
    "wof:placetype":"locality",
    "wof:population":585
},
  "geometry": {"coordinates":[26.14445,45.58996],"type":"Point"}
}