{
  "type": "Feature",
  "properties": {
    "gn:admin1_code":"09",
    "gn:admin2_code":"41417.0",
    "gn:asciiname":"Ileni",
    "gn:country_code":"RO",
    "gn:dem":470,
    "gn:feature_class":"P",
    "gn:feature_code":"PPL",
    "gn:name":"Ileni",
    "gn:population":818,
    "gn:timezone":"Europe/Bucharest",
    "iso:country":"RO",
    "wof:name":"Ileni",
    "wof:placetype":"locality",
    "wof:population":818
},
  "geometry": {"coordinates":[25.00141,45.78758],"type":"Point"}
}