{
  "type": "Feature",
  "properties": {
    "gn:admin1_code":"23",
    "gn:admin2_code":"98435.0",
    "gn:asciiname":"Padureni",
    "gn:country_code":"RO",
    "gn:dem":143,
    "gn:feature_class":"P",
    "gn:feature_code":"PPL",
    "gn:name":"P\u0103dureni",
    "gn:population":55,
    "gn:timezone":"Europe/Bucharest",
    "iso:country":"RO",
    "wof:name":"Padureni",
    "wof:placetype":"locality",
    "wof:population":55
},
  "geometry": {"coordinates":[27.31639,47.10996],"type":"Point"}
}