{
  "type": "Feature",
  "properties": {
    "gn:admin1_code":"20",
    "gn:admin2_code":"84825.0",
    "gn:asciiname":"Pauleni",
    "gn:cc2":"RO",
    "gn:country_code":"RO",
    "gn:dem":811,
    "gn:feature_class":"P",
    "gn:feature_code":"PPL",
    "gn:name":"P\u0103uleni",
    "gn:population":0,
    "gn:timezone":"Europe/Bucharest",
    "iso:country":"RO",
    "name:und_x_variant":[
        "Sz\u00e8kelyp\u00e0lfalva"
    ],
    "wof:name":"Pauleni",
    "wof:placetype":"locality"
},
  "geometry": {"coordinates":[25.18234,46.427],"type":"Point"}
}