{
  "type": "Feature",
  "properties": {
    "gn:admin1_code":"16",
    "gn:admin2_code":"67014",
    "gn:asciiname":"Bujoreanca",
    "gn:country_code":"RO",
    "gn:dem":130,
    "gn:feature_class":"P",
    "gn:feature_code":"PPL",
    "gn:name":"Bujoreanca",
    "gn:population":614,
    "gn:timezone":"Europe/Bucharest",
    "iso:country":"RO",
    "wof:name":"Bujoreanca",
    "wof:placetype":"locality",
    "wof:population":614
},
  "geometry": {"coordinates":[25.89181,44.73079],"type":"Point"}
}