{
  "type": "Feature",
  "properties": {
    "gn:admin1_code":"25",
    "gn:admin2_code":"107234.0",
    "gn:asciiname":"Ciuta",
    "gn:country_code":"RO",
    "gn:dem":188,
    "gn:feature_class":"P",
    "gn:feature_code":"PPL",
    "gn:name":"Ciuta",
    "gn:population":284,
    "gn:timezone":"Europe/Bucharest",
    "iso:country":"RO",
    "name:ceb_x_preferred":[
        "Ciuta"
    ],
    "name:deu_x_preferred":[
        "Ciuta"
    ],
    "name:epo_x_preferred":[
        "Ciuta"
    ],
    "name:ron_x_preferred":[
        "Ciuta"
    ],
    "name:srp_x_preferred":[
        "\u0427\u0443\u0442\u0430"
    ],
    "wof:name":"Ciuta",
    "wof:placetype":"locality",
    "wof:population":284
},
  "geometry": {"coordinates":[22.98833,47.44714000000001],"type":"Point"}
}