{
  "type": "Feature",
  "properties": {
    "gn:admin1_code":"31",
    "gn:admin2_code":"140547",
    "gn:asciiname":"Boianu-Crasnei",
    "gn:country_code":"RO",
    "gn:dem":348,
    "gn:feature_class":"P",
    "gn:feature_code":"PPL",
    "gn:name":"Boianu-Crasnei",
    "gn:population":0,
    "gn:timezone":"Europe/Bucharest",
    "iso:country":"RO",
    "name:und_x_variant":[
        "Boian",
        "Boianu-Crasnei"
    ],
    "wof:name":"Boianu-Crasnei",
    "wof:placetype":"locality"
},
  "geometry": {"coordinates":[22.88333,47.06667],"type":"Point"}
}