{
  "type": "Feature",
  "properties": {
    "gn:admin1_code":"26",
    "gn:admin2_code":"109924.0",
    "gn:asciiname":"Dealu Mare",
    "gn:cc2":"RO",
    "gn:country_code":"RO",
    "gn:dem":534,
    "gn:feature_class":"P",
    "gn:feature_code":"PPL",
    "gn:name":"Dealu Mare",
    "gn:population":99,
    "gn:timezone":"Europe/Bucharest",
    "iso:country":"RO",
    "name:und_x_variant":[
        "Dealul Mare",
        "Dealu Mare"
    ],
    "wof:name":"Dealu Mare",
    "wof:placetype":"locality",
    "wof:population":99
},
  "geometry": {"coordinates":[22.81419,44.98412],"type":"Point"}
}