{
  "type": "Feature",
  "properties": {
    "gn:admin1_code":"02",
    "gn:admin2_code":"10532.0",
    "gn:asciiname":"Ciuntesti",
    "gn:country_code":"RO",
    "gn:dem":248,
    "gn:feature_class":"P",
    "gn:feature_code":"PPL",
    "gn:name":"Ciunte\u015fti",
    "gn:population":0,
    "gn:timezone":"Europe/Bucharest",
    "iso:country":"RO",
    "name:ron_x_preferred":[
        "Ciunte\u015fti"
    ],
    "name:und_x_variant":[
        "Ciunt\u0103haza",
        "Csontah\u00e1z",
        "Csontah\u00e1za-Val\u00e1ny",
        "Csontah\u00e1za"
    ],
    "wof:name":"Ciuntesti",
    "wof:placetype":"locality"
},
  "geometry": {"coordinates":[22.05,46.61667],"type":"Point"}
}