{
  "type": "Feature",
  "properties": {
    "gn:admin1_code":"30",
    "gn:admin2_code":"133919.0",
    "gn:asciiname":"Glod",
    "gn:cc2":"RO",
    "gn:country_code":"RO",
    "gn:dem":260,
    "gn:feature_class":"P",
    "gn:feature_code":"PPL",
    "gn:name":"Glod",
    "gn:population":162,
    "gn:timezone":"Europe/Bucharest",
    "iso:country":"RO",
    "name:ceb_x_preferred":[
        "Glod"
    ],
    "name:deu_x_preferred":[
        "Glod"
    ],
    "name:epo_x_preferred":[
        "Glod"
    ],
    "name:hun_x_preferred":[
        "Glod"
    ],
    "name:ron_x_preferred":[
        "Glod"
    ],
    "name:srp_x_preferred":[
        "\u0413\u043b\u043e\u0434"
    ],
    "name:und_x_variant":[
        "Glodul",
        "Gloduri",
        "Glodu"
    ],
    "wof:name":"Glod",
    "wof:placetype":"locality",
    "wof:population":162
},
  "geometry": {"coordinates":[26.44863,45.14058],"type":"Point"}
}