{
  "type": "Feature",
  "properties": {
    "gn:admin1_code":"43",
    "gn:admin2_code":"179347.0",
    "gn:asciiname":"Manolache",
    "gn:country_code":"RO",
    "gn:dem":64,
    "gn:feature_class":"P",
    "gn:feature_code":"PPL",
    "gn:name":"Manolache",
    "gn:population":249,
    "gn:timezone":"Europe/Bucharest",
    "iso:country":"RO",
    "name:deu_x_preferred":[
        "Manolache"
    ],
    "wof:name":"Manolache",
    "wof:placetype":"locality",
    "wof:population":249
},
  "geometry": {"coordinates":[26.2486,44.40475],"type":"Point"}
}