{
  "type": "Feature",
  "properties": {
    "gn:admin1_code":"26",
    "gn:admin2_code":"113233.0",
    "gn:asciiname":"Cervenita",
    "gn:cc2":"RO",
    "gn:country_code":"RO",
    "gn:dem":244,
    "gn:feature_class":"P",
    "gn:feature_code":"PPL",
    "gn:name":"Cerveni\u021ba",
    "gn:population":408,
    "gn:timezone":"Europe/Bucharest",
    "iso:country":"RO",
    "name:und_x_variant":[
        "Degera\u0163i",
        "Cerveni\u0163a"
    ],
    "wof:name":"Cervenita",
    "wof:placetype":"locality",
    "wof:population":408
},
  "geometry": {"coordinates":[22.96827,44.63835],"type":"Point"}
}