{
  "type": "Feature",
  "properties": {
    "gn:admin1_code":"31",
    "gn:admin2_code":"139740.0",
    "gn:asciiname":"Horoatu Cehului",
    "gn:cc2":"RO",
    "gn:country_code":"RO",
    "gn:dem":216,
    "gn:feature_class":"P",
    "gn:feature_code":"PPL",
    "gn:name":"Horoatu Cehului",
    "gn:population":241,
    "gn:timezone":"Europe/Bucharest",
    "iso:country":"RO",
    "name:und_x_variant":[
        "Horoat",
        "Horoatul Crasnei",
        "Horatu Cehului",
        "Horoatu Cehului"
    ],
    "wof:name":"Horoatu Cehului",
    "wof:placetype":"locality",
    "wof:population":241
},
  "geometry": {"coordinates":[23.24522,47.40412],"type":"Point"}
}