{
  "type": "Feature",
  "properties": {
    "gn:admin1_code":"26",
    "gn:admin2_code":"110116.0",
    "gn:asciiname":"Motruleni",
    "gn:cc2":"RO",
    "gn:country_code":"RO",
    "gn:dem":228,
    "gn:feature_class":"P",
    "gn:feature_code":"PPL",
    "gn:name":"Motruleni",
    "gn:population":235,
    "gn:timezone":"Europe/Bucharest",
    "iso:country":"RO",
    "name:und_x_variant":[
        "Robe\u015fti",
        "Motruleni"
    ],
    "wof:name":"Motruleni",
    "wof:placetype":"locality",
    "wof:population":235
},
  "geometry": {"coordinates":[23.18771,44.66496],"type":"Point"}
}