{
  "type": "Feature",
  "properties": {
    "gn:admin1_code":"01",
    "gn:admin2_code":"4703.0",
    "gn:asciiname":"Spalnaca",
    "gn:country_code":"RO",
    "gn:dem":316,
    "gn:feature_class":"P",
    "gn:feature_code":"PPL",
    "gn:name":"\u0218p\u0103lnaca",
    "gn:population":329,
    "gn:timezone":"Europe/Bucharest",
    "iso:country":"RO",
    "wof:name":"Spalnaca",
    "wof:placetype":"locality",
    "wof:population":329
},
  "geometry": {"coordinates":[23.90833,46.34123],"type":"Point"}
}