{
  "type": "Feature",
  "properties": {
    "gn:admin1_code":"15",
    "gn:admin2_code":"64602.0",
    "gn:asciiname":"Hilib",
    "gn:country_code":"RO",
    "gn:dem":604,
    "gn:feature_class":"P",
    "gn:feature_code":"PPL",
    "gn:name":"Hilib",
    "gn:population":317,
    "gn:timezone":"Europe/Bucharest",
    "iso:country":"RO",
    "wof:name":"Hilib",
    "wof:placetype":"locality",
    "wof:population":317
},
  "geometry": {"coordinates":[26.23731,45.97048],"type":"Point"}
}