{
  "type": "Feature",
  "properties": {
    "gn:admin1_code":"28",
    "gn:admin2_code":"123790.0",
    "gn:asciiname":"Paraul Fagului",
    "gn:country_code":"RO",
    "gn:dem":672,
    "gn:feature_class":"P",
    "gn:feature_code":"PPL",
    "gn:name":"P\u00e2r\u00e2ul Fagului",
    "gn:population":242,
    "gn:timezone":"Europe/Bucharest",
    "iso:country":"RO",
    "name:und_x_variant":[
        "P\u00eer\u00eeul Fagului"
    ],
    "wof:name":"Paraul Fagului",
    "wof:placetype":"locality",
    "wof:population":242
},
  "geometry": {"coordinates":[25.88333,47.13333],"type":"Point"}
}