{
  "type": "Feature",
  "properties": {
    "gn:admin1_code":"34",
    "gn:admin2_code":"151157.0",
    "gn:asciiname":"Plesesti",
    "gn:cc2":"RO",
    "gn:country_code":"RO",
    "gn:dem":314,
    "gn:feature_class":"P",
    "gn:feature_code":"PPL",
    "gn:name":"Ple\u0219e\u0219ti",
    "gn:population":704,
    "gn:timezone":"Europe/Bucharest",
    "iso:country":"RO",
    "name:und_x_variant":[
        "Ple\u015fe\u015fti-Centru",
        "Ple\u015fe\u015fti"
    ],
    "wof:name":"Plesesti",
    "wof:placetype":"locality",
    "wof:population":704
},
  "geometry": {"coordinates":[26.38152,47.52224],"type":"Point"}
}