{
  "type": "Feature",
  "properties": {
    "gn:country":"RO",
    "gn:fcode":"PPL",
    "gn:population":0,
    "iso:country":"RO",
    "name:arz_x_preferred":[
        "\u06a4\u0648\u0644\u062a\u0648\u0631\u0648"
    ],
    "name:eng_x_preferred":[
        "Vulturu"
    ],
    "name:nld_x_preferred":[
        "Vulturu"
    ],
    "name:ron_x_preferred":[
        "Vulturu"
    ],
    "name:srp_x_preferred":[
        "\u0412\u0443\u043b\u0442\u0443\u0440\u0443"
    ],
    "name:ukr_x_preferred":[
        "\u0412\u0443\u043b\u0442\u0443\u0440\u0443"
    ],
    "qs_pg:aaroncc":"RO",
    "qs_pg:gn_country":"RO",
    "qs_pg:gn_fcode":"PPL",
    "qs_pg:gn_pop":0,
    "qs_pg:name":"Vulturu",
    "qs_pg:name_adm0":"Rom\u00e2nia",
    "qs_pg:name_adm1":"Tulcea",
    "qs_pg:photos":90,
    "qs_pg:photos_1k":18,
    "qs_pg:photos_9k":1,
    "qs_pg:photos_9r":3,
    "qs_pg:photos_all":90,
    "qs_pg:photos_sr":3,
    "qs_pg:pop_sr":0,
    "qs_pg:qs_pg_placetype":"locality",
    "qs_pg:qs_pg_placetype_gp":"Town",
    "qs_pg:woe_adm0":23424933,
    "woe:adm0_id":23424933,
    "woe:name_adm0":"Rom\u00e2nia",
    "woe:name_adm1":"Tulcea",
    "woe:placetype":"Town",
    "wof:name":"Vulturu",
    "wof:placetype":"locality",
    "wof:population":80
},
  "geometry": {"coordinates":[29.16667,45.18333],"type":"Point"}
}