{
  "type": "Feature",
  "properties": {
    "gn:admin1_code":"28",
    "gn:admin2_code":"122132.0",
    "gn:asciiname":"Manoaia",
    "gn:country_code":"RO",
    "gn:dem":231,
    "gn:feature_class":"P",
    "gn:feature_code":"PPL",
    "gn:name":"M\u0103noaia",
    "gn:population":930,
    "gn:timezone":"Europe/Bucharest",
    "iso:country":"RO",
    "wof:name":"Manoaia",
    "wof:placetype":"locality",
    "wof:population":930
},
  "geometry": {"coordinates":[26.63067,46.76434],"type":"Point"}
}