{
  "type": "Feature",
  "properties": {
    "gn:admin1_code":"26",
    "gn:admin2_code":"111916.0",
    "gn:asciiname":"Valea Petrii",
    "gn:cc2":"RO",
    "gn:country_code":"RO",
    "gn:dem":248,
    "gn:feature_class":"P",
    "gn:feature_code":"PPL",
    "gn:name":"Valea Petrii",
    "gn:population":65,
    "gn:timezone":"Europe/Bucharest",
    "iso:country":"RO",
    "name:und_x_variant":[
        "Valea Petrei",
        "Valea Petrii"
    ],
    "wof:name":"Valea Petrii",
    "wof:placetype":"locality",
    "wof:population":65
},
  "geometry": {"coordinates":[23.09359,44.58302],"type":"Point"}
}