{
  "type": "Feature",
  "properties": {
    "gn:gn_country":"RO",
    "gn:gn_fcode":"PPLA2",
    "gn:gn_pop":4254,
    "gn:population":4254,
    "iso:country":"RO",
    "name:eng_x_preferred":[
        "Ru\u0219e\u021bu"
    ],
    "name:fra_x_preferred":[
        "Ru\u0219e\u021bu"
    ],
    "name:ita_x_preferred":[
        "Ru\u0219e\u021bu"
    ],
    "name:nld_x_preferred":[
        "Ru\u0219e\u021bu"
    ],
    "name:ron_x_preferred":[
        "Ru\u0219e\u021bu"
    ],
    "name:ukr_x_preferred":[
        "\u0420\u0443\u0448\u0435\u0446\u0443"
    ],
    "name:unk_x_variant":[
        "Ru\u015fe\u0163ul"
    ],
    "qs_pg:aaroncc":"RO",
    "qs_pg:gn_country":"RO",
    "qs_pg:gn_fcode":"PPLA2",
    "qs_pg:gn_pop":4254,
    "qs_pg:name":"Ru\u015fe\u0163u",
    "qs_pg:photos_9r":0,
    "qs_pg:photos_sr":0,
    "qs_pg:pop_sr":4,
    "qs_pg:qs_pg_placetype":"locality",
    "wof:name":"Ru\u015fe\u0163u",
    "wof:placetype":"locality",
    "wof:population":4254
},
  "geometry": {"coordinates":[27.21667,44.95],"type":"Point"}
}