{
  "type": "Feature",
  "properties": {
    "gn:admin1_code":"03",
    "gn:admin2_code":"20048.0",
    "gn:asciiname":"Raca Noua",
    "gn:cc2":"RO",
    "gn:country_code":"RO",
    "gn:dem":161,
    "gn:feature_class":"P",
    "gn:feature_code":"PPL",
    "gn:name":"R\u00e2ca Nou\u0103",
    "gn:population":0,
    "gn:timezone":"Europe/Bucharest",
    "iso:country":"RO",
    "name:und_x_variant":[
        "R\u00e2ca Nou\u0103",
        "R\u00eeca Nou\u0103"
    ],
    "wof:lang_x_official":[
        "ron"
    ],
    "wof:lang_x_spoken":[
        "ron"
    ],
    "wof:name":"Raca Noua",
    "wof:placetype":"locality"
},
  "geometry": {"coordinates":[25.05,44.41667],"type":"Point"}
}