{
  "type": "Feature",
  "properties": {
    "gn:admin1_code":"14",
    "gn:admin2_code":"62609.0",
    "gn:asciiname":"Runcu",
    "gn:cc2":"RO",
    "gn:country_code":"RO",
    "gn:dem":71,
    "gn:feature_class":"P",
    "gn:feature_code":"PPL",
    "gn:name":"Runcu",
    "gn:population":449,
    "gn:timezone":"Europe/Bucharest",
    "iso:country":"RO",
    "name:und_x_variant":[
        "Terzichioi",
        "Runcul",
        "Terzi-Chiol",
        "Runcu"
    ],
    "wof:name":"Runcu",
    "wof:placetype":"locality",
    "wof:population":449
},
  "geometry": {"coordinates":[28.32813,44.59869000000001],"type":"Point"}
}