{
  "type": "Feature",
  "properties": {
    "gn:admin1_code":"21",
    "gn:admin2_code":"91232.0",
    "gn:asciiname":"Sacel",
    "gn:country_code":"RO",
    "gn:dem":377,
    "gn:feature_class":"P",
    "gn:feature_code":"PPL",
    "gn:name":"S\u0103cel",
    "gn:population":515,
    "gn:timezone":"Europe/Bucharest",
    "iso:country":"RO",
    "wof:name":"Sacel",
    "wof:placetype":"locality",
    "wof:population":515
},
  "geometry": {"coordinates":[22.91902,45.55914],"type":"Point"}
}