{
  "type": "Feature",
  "properties": {
    "gn:admin1_code":"21",
    "gn:admin2_code":"89687.0",
    "gn:asciiname":"Campuri de Sus",
    "gn:cc2":"RO",
    "gn:country_code":"RO",
    "gn:dem":339,
    "gn:feature_class":"P",
    "gn:feature_code":"PPL",
    "gn:name":"C\u00e2mpuri de Sus",
    "gn:population":157,
    "gn:timezone":"Europe/Bucharest",
    "iso:country":"RO",
    "name:und_x_variant":[
        "C\u00e2mpuri de-Sus",
        "C\u00eempuri de Sus"
    ],
    "wof:name":"Campuri de Sus",
    "wof:placetype":"locality",
    "wof:population":157
},
  "geometry": {"coordinates":[22.55325,45.95647],"type":"Point"}
}