{
  "type": "Feature",
  "properties": {
    "gn:admin1_code":"39",
    "gn:admin2_code":"168452.0",
    "gn:asciiname":"Oculesti",
    "gn:country_code":"RO",
    "gn:dem":231,
    "gn:feature_class":"P",
    "gn:feature_code":"PPL",
    "gn:name":"Ocule\u015fti",
    "gn:population":0,
    "gn:timezone":"Europe/Bucharest",
    "iso:country":"RO",
    "wof:lang_x_official":[
        "ron"
    ],
    "wof:lang_x_spoken":[
        "ron"
    ],
    "wof:name":"Oculesti",
    "wof:placetype":"locality"
},
  "geometry": {"coordinates":[23.96667,44.56667],"type":"Point"}
}