{
  "type": "Feature",
  "properties": {
    "gn:admin1_code":"27",
    "gn:admin2_code":"115307",
    "gn:asciiname":"Bernadea",
    "gn:cc2":"RO",
    "gn:country_code":"RO",
    "gn:dem":328,
    "gn:feature_class":"P",
    "gn:feature_code":"PPL",
    "gn:name":"Bernadea",
    "gn:population":194,
    "gn:timezone":"Europe/Bucharest",
    "iso:country":"RO",
    "name:und_x_variant":[
        "Bernadia",
        "Bernadea"
    ],
    "wof:name":"Bernadea",
    "wof:placetype":"locality",
    "wof:population":194
},
  "geometry": {"coordinates":[24.45847,46.37407],"type":"Point"}
}