{
  "type": "Feature",
  "properties": {
    "gn:admin1_code":"04",
    "gn:admin2_code":"22237.0",
    "gn:asciiname":"Gradesti",
    "gn:cc2":"RO",
    "gn:country_code":"RO",
    "gn:dem":141,
    "gn:feature_class":"P",
    "gn:feature_code":"PPL",
    "gn:name":"Gr\u0103de\u0219ti",
    "gn:population":17,
    "gn:timezone":"Europe/Bucharest",
    "iso:country":"RO",
    "name:und_x_variant":[
        "Grade\u015ftii",
        "Gr\u0103de\u015fti"
    ],
    "wof:name":"Gradesti",
    "wof:placetype":"locality",
    "wof:population":17
},
  "geometry": {"coordinates":[27.27908,46.29767],"type":"Point"}
}