{
  "type": "Feature",
  "properties": {
    "gn:admin1_code":"29",
    "gn:admin2_code":"129139.0",
    "gn:asciiname":"Colibasi",
    "gn:cc2":"RO",
    "gn:country_code":"RO",
    "gn:dem":123,
    "gn:feature_class":"P",
    "gn:feature_code":"PPL",
    "gn:name":"Coliba\u0219i",
    "gn:population":605,
    "gn:timezone":"Europe/Bucharest",
    "iso:country":"RO",
    "name:und_x_variant":[
        "Coliba\u015fu",
        "Coliba\u015ful",
        "Coliba\u015fi"
    ],
    "wof:name":"Colibasi",
    "wof:placetype":"locality",
    "wof:population":605
},
  "geometry": {"coordinates":[24.27517000000001,44.50613],"type":"Point"}
}