{
  "type": "Feature",
  "properties": {
    "gn:gn_country":"RO",
    "gn:gn_fcode":"PPLA2",
    "gn:gn_pop":2574,
    "gn:population":2574,
    "iso:country":"RO",
    "name:dut_x_preferred":[
        "Pripone\u0219ti"
    ],
    "name:eng_x_preferred":[
        "Pripone\u0219ti"
    ],
    "name:fre_x_preferred":[
        "Pripone\u0219ti"
    ],
    "name:ita_x_preferred":[
        "Pripone\u0219ti"
    ],
    "name:rum_x_preferred":[
        "Pripone\u0219ti"
    ],
    "name:ukr_x_preferred":[
        "\u041f\u0440\u0456\u043f\u043e\u043d\u0435\u0448\u0442\u044c"
    ],
    "name:unk_x_variant":[
        "Pripone\u015ftii de Sus"
    ],
    "qs_pg:aaroncc":"RO",
    "qs_pg:gn_country":"RO",
    "qs_pg:gn_fcode":"PPLA2",
    "qs_pg:gn_pop":2574,
    "qs_pg:name":"Pripone\u015fti",
    "qs_pg:photos_9r":0,
    "qs_pg:photos_sr":0,
    "qs_pg:pop_sr":4,
    "qs_pg:qs_pg_placetype":"locality",
    "wof:name":"Pripone\u015fti",
    "wof:placetype":"locality",
    "wof:population":2574
},
  "geometry": {"coordinates":[27.43333,46.08333],"type":"Point"}
}