{
  "type": "Feature",
  "properties": {
    "gn:admin1_code":"39",
    "gn:admin2_code":"171628.0",
    "gn:asciiname":"Ginerica",
    "gn:country_code":"RO",
    "gn:dem":421,
    "gn:feature_class":"P",
    "gn:feature_code":"PPL",
    "gn:name":"Ginerica",
    "gn:population":33,
    "gn:timezone":"Europe/Bucharest",
    "iso:country":"RO",
    "wof:name":"Ginerica",
    "wof:placetype":"locality",
    "wof:population":33
},
  "geometry": {"coordinates":[24.49677,45.00237],"type":"Point"}
}