{
  "type": "Feature",
  "properties": {
    "gn:admin1_code":"27",
    "gn:admin2_code":"115897.0",
    "gn:asciiname":"Idicel",
    "gn:country_code":"RO",
    "gn:dem":508,
    "gn:feature_class":"P",
    "gn:feature_code":"PPL",
    "gn:name":"Idicel",
    "gn:population":0,
    "gn:timezone":"Europe/Bucharest",
    "iso:country":"RO",
    "name:und_x_variant":[
        "Idecspatak",
        "Idicel"
    ],
    "wof:name":"Idicel",
    "wof:placetype":"locality"
},
  "geometry": {"coordinates":[24.83333,46.85],"type":"Point"}
}