{
  "type": "Feature",
  "properties": {
    "gn:admin1_code":"15",
    "gn:admin2_code":"64906.0",
    "gn:asciiname":"Calnic",
    "gn:country_code":"RO",
    "gn:dem":623,
    "gn:feature_class":"P",
    "gn:feature_code":"PPL",
    "gn:name":"Calnic",
    "gn:population":517,
    "gn:timezone":"Europe/Bucharest",
    "iso:country":"RO",
    "name:hun_x_preferred":[
        "K\u00e1lnok"
    ],
    "wof:name":"Calnic",
    "wof:placetype":"locality",
    "wof:population":517
},
  "geometry": {"coordinates":[25.78333,45.93333],"type":"Point"}
}