{
  "type": "Feature",
  "properties": {
    "gn:admin1_code":"33",
    "gn:admin2_code":"144795",
    "gn:asciiname":"Armeni",
    "gn:country_code":"RO",
    "gn:dem":362,
    "gn:feature_class":"P",
    "gn:feature_code":"PPL",
    "gn:name":"Armeni",
    "gn:population":794,
    "gn:timezone":"Europe/Bucharest",
    "iso:country":"RO",
    "name:cat_x_preferred":[
        "Armeni"
    ],
    "name:ceb_x_preferred":[
        "Armeni"
    ],
    "name:deu_x_preferred":[
        "Armeni"
    ],
    "name:fin_x_preferred":[
        "Arm\u00e9noi"
    ],
    "name:nld_x_preferred":[
        "Armeni"
    ],
    "name:por_x_preferred":[
        "Arm\u00e9ni"
    ],
    "name:ron_x_preferred":[
        "Armeni"
    ],
    "name:srp_x_preferred":[
        "\u0410\u0440\u043c\u0435\u043d\u0438"
    ],
    "name:swe_x_preferred":[
        "Armeni"
    ],
    "wof:name":"Armeni",
    "wof:placetype":"locality",
    "wof:population":794
},
  "geometry": {"coordinates":[23.97527,45.96616],"type":"Point"}
}