{
  "type": "Feature",
  "properties": {
    "gn:admin1_code":"11",
    "gn:admin2_code":"47916.0",
    "gn:asciiname":"Curmatura",
    "gn:country_code":"RO",
    "gn:dem":526,
    "gn:feature_class":"P",
    "gn:feature_code":"PPL",
    "gn:name":"Curm\u0103tura",
    "gn:population":301,
    "gn:timezone":"Europe/Bucharest",
    "iso:country":"RO",
    "wof:name":"Curmatura",
    "wof:placetype":"locality",
    "wof:population":301
},
  "geometry": {"coordinates":[26.29671,45.3809],"type":"Point"}
}