{
  "type": "Feature",
  "properties": {
    "gn:admin1_code":"31",
    "gn:admin2_code":"142612.0",
    "gn:asciiname":"Sag",
    "gn:cc2":"RO",
    "gn:country_code":"RO",
    "gn:dem":352,
    "gn:feature_class":"P",
    "gn:feature_code":"PPLA2",
    "gn:name":"S\u00e2g",
    "gn:population":851,
    "gn:timezone":"Europe/Bucharest",
    "iso:country":"RO",
    "name:und_x_variant":[
        "S\u00e2g",
        "S\u00eeg"
    ],
    "wof:name":"Sag",
    "wof:placetype":"locality",
    "wof:population":851
},
  "geometry": {"coordinates":[22.78084,47.07545],"type":"Point"}
}