{
  "type": "Feature",
  "properties": {
    "gn:admin1_code":"31",
    "gn:admin2_code":"142612.0",
    "gn:asciiname":"Sag",
    "gn:cc2":"RO",
    "gn:country_code":"RO",
    "gn:dem":352,
    "gn:feature_class":"P",
    "gn:feature_code":"PPLA2",
    "gn:name":"S\u00e2g",
    "gn:population":851,
    "gn:timezone":"Europe/Bucharest",
    "iso:country":"RO",
    "name:ceb_x_preferred":[
        "Comuna S\u00e2g"
    ],
    "name:deu_x_preferred":[
        "S\u00e2g"
    ],
    "name:epo_x_preferred":[
        "S\u00e2g"
    ],
    "name:fra_x_preferred":[
        "S\u00e2g"
    ],
    "name:ita_x_preferred":[
        "S\u00e2g"
    ],
    "name:msa_x_preferred":[
        "S\u00e2g"
    ],
    "name:nld_x_preferred":[
        "S\u00e2g"
    ],
    "name:por_x_preferred":[
        "S\u00e2g"
    ],
    "name:ron_x_preferred":[
        "Comuna S\u00e2g"
    ],
    "name:srp_x_preferred":[
        "\u041e\u043f\u0448\u0442\u0438\u043d\u0430 \u0421\u0430\u0433"
    ],
    "name:ukr_x_preferred":[
        "\u0421\u0438\u0433"
    ],
    "name:und_x_variant":[
        "S\u00e2g",
        "S\u00eeg"
    ],
    "name:vol_x_preferred":[
        "S\u00e2g"
    ],
    "name:zho_x_preferred":[
        "\u745f\u683c\u9109"
    ],
    "wof:name":"Sag",
    "wof:placetype":"locality",
    "wof:population":851
},
  "geometry": {"coordinates":[22.78084,47.07545],"type":"Point"}
}