{
  "type": "Feature",
  "properties": {
    "iso:country":"RO",
    "qs_pg:aaroncc":"RO",
    "qs_pg:name":"Podu D\u00eembovi\u021bei",
    "qs_pg:name_adm0":"Rom\u00e2nia",
    "qs_pg:name_adm1":"Arges",
    "qs_pg:photos":90,
    "qs_pg:photos_1k":18,
    "qs_pg:photos_9k":1,
    "qs_pg:photos_9r":3,
    "qs_pg:photos_all":90,
    "qs_pg:photos_sr":3,
    "qs_pg:pop_sr":0,
    "qs_pg:qs_pg_placetype":"locality",
    "qs_pg:qs_pg_placetype_gp":"Town",
    "qs_pg:woe_adm0":23424933,
    "woe:adm0_id":23424933,
    "woe:name_adm0":"Rom\u00e2nia",
    "woe:name_adm1":"Arges",
    "woe:placetype":"Town",
    "wof:lang_x_official":[
        "ron"
    ],
    "wof:lang_x_spoken":[
        "ron"
    ],
    "wof:name":"Podu D\u00eembovi\u021bei",
    "wof:placetype":"locality"
},
  "geometry": {"coordinates":[25.22429,45.412278],"type":"Point"}
}