{
  "type": "Feature",
  "properties": {
    "gn:admin1_code":"37",
    "gn:admin2_code":"161384.0",
    "gn:asciiname":"Fagarasu Nou",
    "gn:cc2":"RO",
    "gn:country_code":"RO",
    "gn:dem":118,
    "gn:feature_class":"P",
    "gn:feature_code":"PPL",
    "gn:name":"F\u0103g\u0103ra\u0219u Nou",
    "gn:population":787,
    "gn:timezone":"Europe/Bucharest",
    "iso:country":"RO",
    "name:und_x_variant":[
        "F\u0103g\u0103ra\u015ful-Nou",
        "F\u0103g\u0103ra\u015fu Nou"
    ],
    "wof:name":"Fagarasu Nou",
    "wof:placetype":"locality",
    "wof:population":787
},
  "geometry": {"coordinates":[28.28088,44.85757],"type":"Point"}
}