{
  "type": "Feature",
  "properties": {
    "gn:population":4036,
    "iso:country":"RO",
    "name:ara_x_preferred":[
        "\u0628\u0627\u0648\u0644\u064a\u0634"
    ],
    "name:ceb_x_preferred":[
        "P\u0103uli\u0219"
    ],
    "name:deu_x_preferred":[
        "P\u0103uli\u0219"
    ],
    "name:eng_x_preferred":[
        "P\u0103uli\u0219"
    ],
    "name:epo_x_preferred":[
        "P\u0103uli\u0219"
    ],
    "name:fra_x_preferred":[
        "P\u0103uli\u0219"
    ],
    "name:hun_x_preferred":[
        "\u00d3p\u00e1los"
    ],
    "name:ita_x_preferred":[
        "P\u0103uli\u0219"
    ],
    "name:msa_x_preferred":[
        "P\u0103uli\u0219"
    ],
    "name:nld_x_preferred":[
        "P\u0103uli\u0219"
    ],
    "name:por_x_preferred":[
        "P\u0103uli\u0219"
    ],
    "name:ron_x_preferred":[
        "P\u0103uli\u0219"
    ],
    "name:sqi_x_preferred":[
        "P\u0103uli\u0219"
    ],
    "name:srp_x_preferred":[
        "\u041f\u0430\u0443\u043b\u0438\u0448"
    ],
    "name:ukr_x_preferred":[
        "\u041f\u0435\u0443\u043b\u0456\u0448"
    ],
    "name:unk_x_variant":[
        "Alt-Paulisch"
    ],
    "name:vie_x_preferred":[
        "Paulis"
    ],
    "name:vol_x_preferred":[
        "P\u0103uli\u0219"
    ],
    "qs:a0":"Rom\u00e2nia",
    "qs:a1":"*Arad",
    "qs:a1r":"0",
    "qs:adm0":"Rom\u00e2nia",
    "qs:la_lc":"*",
    "qs:level":"locality",
    "qs:loc":"P\u0103uli\u015f",
    "qs:loc_alt":"Paulis",
    "qs:pop":0,
    "qs:type":"buffered point",
    "wof:name":"P\u0103uli\u015f",
    "wof:placetype":"locality",
    "wof:population":4036
},
  "geometry": {"coordinates":[21.601875,46.115178],"type":"Point"}
}