{
  "type": "Feature",
  "properties": {
    "gn:admin1_code":"29",
    "gn:admin2_code":"129380.0",
    "gn:asciiname":"Cherlestii din Deal",
    "gn:cc2":"RO",
    "gn:country_code":"RO",
    "gn:dem":160,
    "gn:feature_class":"P",
    "gn:feature_code":"PPL",
    "gn:name":"Cherle\u0219tii din Deal",
    "gn:population":397,
    "gn:timezone":"Europe/Bucharest",
    "iso:country":"RO",
    "name:und_x_variant":[
        "Cherle\u015fti Vale",
        "Cherlesti-din Vale",
        "Cherle\u015ftii din Vale"
    ],
    "wof:name":"Cherlestii din Deal",
    "wof:placetype":"locality",
    "wof:population":397
},
  "geometry": {"coordinates":[24.3376,44.52207],"type":"Point"}
}