{
  "type": "Feature",
  "properties": {
    "gn:admin1_code":"39",
    "gn:admin2_code":"172894.0",
    "gn:asciiname":"Patesti",
    "gn:country_code":"RO",
    "gn:dem":553,
    "gn:feature_class":"P",
    "gn:feature_code":"PPL",
    "gn:name":"P\u0103te\u0219ti",
    "gn:population":169,
    "gn:timezone":"Europe/Bucharest",
    "iso:country":"RO",
    "wof:name":"Patesti",
    "wof:placetype":"locality",
    "wof:population":169
},
  "geometry": {"coordinates":[24.39168,45.27916],"type":"Point"}
}