{
  "type": "Feature",
  "properties": {
    "gn:admin1_code":"28",
    "gn:admin2_code":"124411.0",
    "gn:asciiname":"Soci",
    "gn:country_code":"RO",
    "gn:dem":487,
    "gn:feature_class":"P",
    "gn:feature_code":"PPL",
    "gn:name":"Soci",
    "gn:population":163,
    "gn:timezone":"Europe/Bucharest",
    "iso:country":"RO",
    "name:cat_x_preferred":[
        "Soci"
    ],
    "name:ceb_x_preferred":[
        "Soci"
    ],
    "name:deu_x_preferred":[
        "Soci"
    ],
    "name:ita_x_preferred":[
        "Soci"
    ],
    "name:ron_x_preferred":[
        "Soci"
    ],
    "name:srp_x_preferred":[
        "\u0421\u043e\u0447\u0438"
    ],
    "name:swe_x_preferred":[
        "Soci"
    ],
    "wof:name":"Soci",
    "wof:placetype":"locality",
    "wof:population":163
},
  "geometry": {"coordinates":[26.50467,47.02751],"type":"Point"}
}