{
  "type": "Feature",
  "properties": {
    "gn:admin1_code":"03",
    "gn:admin2_code":"14165.0",
    "gn:asciiname":"Manicesti",
    "gn:cc2":"RO",
    "gn:country_code":"RO",
    "gn:dem":344,
    "gn:feature_class":"P",
    "gn:feature_code":"PPL",
    "gn:name":"M\u0103nice\u0219ti",
    "gn:population":508,
    "gn:timezone":"Europe/Bucharest",
    "iso:country":"RO",
    "name:und_x_variant":[
        "Minice\u015ftii",
        "M\u0103nice\u015fti"
    ],
    "wof:name":"Manicesti",
    "wof:placetype":"locality",
    "wof:population":508
},
  "geometry": {"coordinates":[24.71474,45.02163],"type":"Point"}
}