{
  "type": "Feature",
  "properties": {
    "gn:admin1_code":"38",
    "gn:admin2_code":"165069.0",
    "gn:asciiname":"Vinetesti",
    "gn:country_code":"RO",
    "gn:dem":129,
    "gn:feature_class":"P",
    "gn:feature_code":"PPL",
    "gn:name":"Vine\u021be\u0219ti",
    "gn:population":782,
    "gn:timezone":"Europe/Bucharest",
    "iso:country":"RO",
    "wof:name":"Vinetesti",
    "wof:placetype":"locality",
    "wof:population":782
},
  "geometry": {"coordinates":[27.90064000000001,46.62965],"type":"Point"}
}