{
  "type": "Feature",
  "properties": {
    "gn:admin1_code":"06",
    "gn:admin2_code":"32483.0",
    "gn:asciiname":"Rusu de Jos",
    "gn:cc2":"RO",
    "gn:country_code":"RO",
    "gn:dem":267,
    "gn:feature_class":"P",
    "gn:feature_code":"PPL",
    "gn:name":"Rusu de Jos",
    "gn:population":353,
    "gn:timezone":"Europe/Bucharest",
    "iso:country":"RO",
    "name:und_x_variant":[
        "Rusul-de-Jos",
        "Rusu de Jos"
    ],
    "wof:name":"Rusu de Jos",
    "wof:placetype":"locality",
    "wof:population":353
},
  "geometry": {"coordinates":[24.17224,47.14438],"type":"Point"}
}