{
  "type": "Feature",
  "properties": {
    "gn:admin1_code":"18",
    "gn:admin2_code":"76638.0",
    "gn:asciiname":"Zarnesti",
    "gn:country_code":"RO",
    "gn:dem":118,
    "gn:feature_class":"P",
    "gn:feature_code":"PPL",
    "gn:name":"Z\u0103rne\u0219ti",
    "gn:population":383,
    "gn:timezone":"Europe/Bucharest",
    "iso:country":"RO",
    "wof:name":"Zarnesti",
    "wof:placetype":"locality",
    "wof:population":383
},
  "geometry": {"coordinates":[27.85412,46.01801],"type":"Point"}
}