{
  "type": "Feature",
  "properties": {
    "gn:admin1_code":"02",
    "gn:admin2_code":"9832.0",
    "gn:asciiname":"Groseni",
    "gn:country_code":"RO",
    "gn:dem":246,
    "gn:feature_class":"P",
    "gn:feature_code":"PPL",
    "gn:name":"Gro\u0219eni",
    "gn:population":982,
    "gn:timezone":"Europe/Bucharest",
    "iso:country":"RO",
    "name:ron_x_preferred":[
        "Gro\u0219eni"
    ],
    "name:und_x_variant":[
        "Gro\u015fi",
        "Gross",
        "Gr\u00f3s",
        "T\u00f6nk\u00f6d"
    ],
    "wof:name":"Groseni",
    "wof:placetype":"locality",
    "wof:population":982
},
  "geometry": {"coordinates":[22.11833,46.49754],"type":"Point"}
}