{
  "type": "Feature",
  "properties": {
    "gn:admin1_code":"12",
    "gn:admin2_code":"54617.0",
    "gn:asciiname":"23 August",
    "gn:cc2":"RO",
    "gn:country_code":"RO",
    "gn:dem":300,
    "gn:feature_class":"P",
    "gn:feature_code":"PPL",
    "gn:name":"23 August",
    "gn:population":674,
    "gn:timezone":"Europe/Bucharest",
    "iso:country":"RO",
    "name:und_x_variant":[
        "Colonia Ipeil",
        "Ion Br\u0103tianu",
        "Ion C. Br\u0103tianu",
        "Bratianu",
        "Dou\u0103zeci \u015fi Trei August",
        "23 August"
    ],
    "wof:name":"23 August",
    "wof:placetype":"locality",
    "wof:population":674
},
  "geometry": {"coordinates":[22.3993,45.52303],"type":"Point"}
}