{
  "type": "Feature",
  "properties": {
    "gn:admin1_code":"21",
    "gn:admin2_code":"89954",
    "gn:asciiname":"Bastea",
    "gn:country_code":"RO",
    "gn:dem":251,
    "gn:feature_class":"P",
    "gn:feature_code":"PPL",
    "gn:name":"Ba\u0219tea",
    "gn:population":5,
    "gn:timezone":"Europe/Bucharest",
    "iso:country":"RO",
    "wof:name":"Bastea",
    "wof:placetype":"locality",
    "wof:population":5
},
  "geometry": {"coordinates":[22.41108,45.8776],"type":"Point"}
}