{
  "type": "Feature",
  "properties": {
    "gn:admin1_code":"17",
    "gn:admin2_code":"73371.0",
    "gn:asciiname":"Busteni",
    "gn:country_code":"RO",
    "gn:dem":191,
    "gn:feature_class":"P",
    "gn:feature_code":"PPL",
    "gn:name":"Bu\u0219teni",
    "gn:population":281,
    "gn:timezone":"Europe/Bucharest",
    "iso:country":"RO",
    "wof:name":"Busteni",
    "wof:placetype":"locality",
    "wof:population":281
},
  "geometry": {"coordinates":[23.8337,44.5323],"type":"Point"}
}