{
  "type": "Feature",
  "properties": {
    "gn:admin1_code":"12",
    "gn:admin2_code":"52570.0",
    "gn:asciiname":"Prislop",
    "gn:country_code":"RO",
    "gn:dem":346,
    "gn:feature_class":"P",
    "gn:feature_code":"PPL",
    "gn:name":"Prislop",
    "gn:population":26,
    "gn:timezone":"Europe/Bucharest",
    "iso:country":"RO",
    "name:ceb_x_preferred":[
        "Prislop"
    ],
    "name:deu_x_preferred":[
        "Prislop"
    ],
    "name:epo_x_preferred":[
        "Prislop"
    ],
    "name:hun_x_preferred":[
        "Prislop"
    ],
    "name:pol_x_preferred":[
        "Prislop"
    ],
    "name:ron_x_preferred":[
        "Prislop"
    ],
    "name:srp_x_preferred":[
        "\u041f\u0440\u0438\u0441\u043b\u043e\u043f"
    ],
    "wof:name":"Prislop",
    "wof:placetype":"locality",
    "wof:population":26
},
  "geometry": {"coordinates":[21.93513,44.83595],"type":"Point"}
}