{
  "type": "Feature",
  "properties": {
    "gn:admin1_code":"17",
    "gn:admin2_code":"74931.0",
    "gn:asciiname":"Frasin",
    "gn:country_code":"RO",
    "gn:dem":203,
    "gn:feature_class":"P",
    "gn:feature_code":"PPL",
    "gn:name":"Frasin",
    "gn:population":161,
    "gn:timezone":"Europe/Bucharest",
    "iso:country":"RO",
    "name:ceb_x_preferred":[
        "Ora\u0219 Frasin"
    ],
    "name:deu_x_preferred":[
        "Frasin"
    ],
    "name:fas_x_preferred":[
        "\u0641\u0631\u0633\u06cc\u0646"
    ],
    "name:fra_x_preferred":[
        "Frasin"
    ],
    "name:heb_x_preferred":[
        "\u05e4\u05e8\u05d0\u05e1\u05d9\u05df"
    ],
    "name:hun_x_preferred":[
        "Frasin"
    ],
    "name:ita_x_preferred":[
        "Frasin"
    ],
    "name:msa_x_preferred":[
        "Frasin"
    ],
    "name:nld_x_preferred":[
        "Frasin"
    ],
    "name:pol_x_preferred":[
        "Frasin"
    ],
    "name:ron_x_preferred":[
        "Frasin"
    ],
    "name:rus_x_preferred":[
        "\u0424\u0440\u0430\u0441\u0438\u043d"
    ],
    "name:spa_x_preferred":[
        "Frasin"
    ],
    "name:srp_x_preferred":[
        "\u041e\u043f\u0448\u0442\u0438\u043d\u0430 \u0424\u0440\u0430\u0441\u0438\u043d"
    ],
    "name:ukr_x_preferred":[
        "\u0424\u0440\u0430\u0441\u0456\u043d"
    ],
    "name:vie_x_preferred":[
        "Frasin"
    ],
    "name:zho_x_preferred":[
        "\u5f17\u62c9\u8f9b"
    ],
    "wof:name":"Frasin",
    "wof:placetype":"locality",
    "wof:population":161
},
  "geometry": {"coordinates":[23.49588,44.35812],"type":"Point"}
}