{
  "type": "Feature",
  "properties": {
    "gn:admin1_code":"17",
    "gn:admin2_code":"74931.0",
    "gn:asciiname":"Frasin",
    "gn:country_code":"RO",
    "gn:dem":203,
    "gn:feature_class":"P",
    "gn:feature_code":"PPL",
    "gn:name":"Frasin",
    "gn:population":161,
    "gn:timezone":"Europe/Bucharest",
    "iso:country":"RO",
    "wof:name":"Frasin",
    "wof:placetype":"locality",
    "wof:population":161
},
  "geometry": {"coordinates":[23.49588,44.35812],"type":"Point"}
}