{
  "type": "Feature",
  "properties": {
    "gn:admin1_code":"14",
    "gn:admin2_code":"61559.0",
    "gn:asciiname":"Siriu",
    "gn:cc2":"RO",
    "gn:country_code":"RO",
    "gn:dem":83,
    "gn:feature_class":"P",
    "gn:feature_code":"PPL",
    "gn:name":"\u0218iriu",
    "gn:population":297,
    "gn:timezone":"Europe/Bucharest",
    "iso:country":"RO",
    "name:und_x_variant":[
        "Sublocotenent M\u0103ndiou",
        "\u015eiriul",
        "Siriu"
    ],
    "wof:name":"Siriu",
    "wof:placetype":"locality",
    "wof:population":297
},
  "geometry": {"coordinates":[28.18794,44.62912],"type":"Point"}
}