{
  "type": "Feature",
  "properties": {
    "gn:admin1_code":"14",
    "gn:admin2_code":"61559.0",
    "gn:asciiname":"Siriu",
    "gn:cc2":"RO",
    "gn:country_code":"RO",
    "gn:dem":83,
    "gn:feature_class":"P",
    "gn:feature_code":"PPL",
    "gn:name":"\u0218iriu",
    "gn:population":297,
    "gn:timezone":"Europe/Bucharest",
    "iso:country":"RO",
    "name:ceb_x_preferred":[
        "Comuna Siriu"
    ],
    "name:ita_x_preferred":[
        "Siriu"
    ],
    "name:msa_x_preferred":[
        "Siriu"
    ],
    "name:nld_x_preferred":[
        "Siriu"
    ],
    "name:por_x_preferred":[
        "Siriu"
    ],
    "name:ron_x_preferred":[
        "Comuna Siriu"
    ],
    "name:srp_x_preferred":[
        "\u041e\u043f\u0448\u0442\u0438\u043d\u0430 \u0421\u0438\u0440\u0438\u0443"
    ],
    "name:ukr_x_preferred":[
        "\u0421\u0456\u0440\u0456\u0443"
    ],
    "name:und_x_variant":[
        "Sublocotenent M\u0103ndiou",
        "\u015eiriul",
        "Siriu"
    ],
    "name:vie_x_preferred":[
        "Siriu"
    ],
    "name:vol_x_preferred":[
        "Siriu"
    ],
    "name:zho_x_preferred":[
        "\u932b\u91cc\u70cf\u9109"
    ],
    "wof:name":"Siriu",
    "wof:placetype":"locality",
    "wof:population":297
},
  "geometry": {"coordinates":[28.18794,44.62912],"type":"Point"}
}