{
  "type": "Feature",
  "properties": {
    "gn:admin1_code":"38",
    "gn:admin2_code":"163967.0",
    "gn:asciiname":"Lunca",
    "gn:country_code":"RO",
    "gn:dem":176,
    "gn:feature_class":"P",
    "gn:feature_code":"PPL",
    "gn:name":"Lunca",
    "gn:population":425,
    "gn:timezone":"Europe/Bucharest",
    "iso:country":"RO",
    "name:ceb_x_preferred":[
        "Lunca"
    ],
    "name:deu_x_preferred":[
        "Lunca"
    ],
    "name:epo_x_preferred":[
        "Lunca"
    ],
    "name:fra_x_preferred":[
        "Lunca"
    ],
    "name:hun_x_preferred":[
        "Lunca"
    ],
    "name:ita_x_preferred":[
        "Lunca"
    ],
    "name:nld_x_preferred":[
        "Lunca"
    ],
    "name:ron_x_preferred":[
        "Lunca"
    ],
    "name:srp_x_preferred":[
        "\u041b\u0443\u043d\u043a\u0430"
    ],
    "name:vol_x_preferred":[
        "Lunca"
    ],
    "wof:name":"Lunca",
    "wof:placetype":"locality",
    "wof:population":425
},
  "geometry": {"coordinates":[27.54669,46.45567],"type":"Point"}
}