{
  "type": "Feature",
  "properties": {
    "gn:admin1_code":"39",
    "gn:admin2_code":"171931.0",
    "gn:asciiname":"Carstanesti",
    "gn:cc2":"RO",
    "gn:country_code":"RO",
    "gn:dem":445,
    "gn:feature_class":"P",
    "gn:feature_code":"PPL",
    "gn:name":"C\u00e2rst\u0103ne\u015fti",
    "gn:population":0,
    "gn:timezone":"Europe/Bucharest",
    "iso:country":"RO",
    "name:und_x_variant":[
        "C\u00e2rst\u0103ne\u015fti",
        "C\u00eerst\u0103ne\u015fti"
    ],
    "wof:name":"Carstanesti",
    "wof:placetype":"locality"
},
  "geometry": {"coordinates":[24.05,45.05],"type":"Point"}
}