{
  "type": "Feature",
  "properties": {
    "gn:admin1_code":"11",
    "gn:admin2_code":"45539.0",
    "gn:asciiname":"Pinu",
    "gn:cc2":"RO",
    "gn:country_code":"RO",
    "gn:dem":528,
    "gn:feature_class":"P",
    "gn:feature_code":"PPL",
    "gn:name":"Pinu",
    "gn:population":346,
    "gn:timezone":"Europe/Bucharest",
    "iso:country":"RO",
    "name:und_x_variant":[
        "Pinul",
        "Pinu"
    ],
    "wof:name":"Pinu",
    "wof:placetype":"locality",
    "wof:population":346
},
  "geometry": {"coordinates":[26.49449000000001,45.41959],"type":"Point"}
}