{
  "type": "Feature",
  "properties": {
    "gn:admin1_code":"43",
    "gn:admin2_code":"102473.0",
    "gn:asciiname":"Merisasca",
    "gn:country_code":"RO",
    "gn:dem":83,
    "gn:feature_class":"P",
    "gn:feature_code":"PPL",
    "gn:name":"Meri\u015fasca",
    "gn:population":0,
    "gn:timezone":"Europe/Bucharest",
    "iso:country":"RO",
    "name:und_x_variant":[
        "Meri\u015fanca",
        "Meri\u015fasca"
    ],
    "wof:name":"Merisasca",
    "wof:placetype":"locality"
},
  "geometry": {"coordinates":[26.23333,44.61667],"type":"Point"}
}