{
  "type": "Feature",
  "properties": {
    "gn:admin1_code":"13",
    "gn:admin2_code":"56425.0",
    "gn:asciiname":"Calarasi-Gara",
    "gn:cc2":"RO",
    "gn:country_code":"RO",
    "gn:dem":325,
    "gn:feature_class":"P",
    "gn:feature_code":"PPL",
    "gn:name":"C\u0103l\u0103ra\u0219i-Gar\u0103",
    "gn:population":382,
    "gn:timezone":"Europe/Bucharest",
    "iso:country":"RO",
    "name:und_x_variant":[
        "H\u0103r\u0103ste\u015f Gara",
        "C\u0103l\u0103ra\u015fi Turda",
        "C\u0103l\u0103ra\u015fi-Gar\u0103"
    ],
    "wof:name":"Calarasi-Gara",
    "wof:placetype":"locality",
    "wof:population":382
},
  "geometry": {"coordinates":[23.88886,46.4859],"type":"Point"}
}