{
  "type": "Feature",
  "properties": {
    "gn:admin1_code":"19",
    "gn:admin2_code":"78016.0",
    "gn:asciiname":"Dambova",
    "gn:cc2":"RO",
    "gn:country_code":"RO",
    "gn:dem":203,
    "gn:feature_class":"P",
    "gn:feature_code":"PPL",
    "gn:name":"D\u00e2mbova",
    "gn:population":473,
    "gn:timezone":"Europe/Bucharest",
    "iso:country":"RO",
    "name:und_x_variant":[
        "D\u00e2mbova",
        "D\u00eembova"
    ],
    "wof:name":"Dambova",
    "wof:placetype":"locality",
    "wof:population":473
},
  "geometry": {"coordinates":[23.20383,44.94751],"type":"Point"}
}