{
  "type": "Feature",
  "properties": {
    "gn:admin1_code":"38",
    "gn:admin2_code":"164062.0",
    "gn:asciiname":"Dumbraveni",
    "gn:country_code":"RO",
    "gn:dem":273,
    "gn:feature_class":"P",
    "gn:feature_code":"PPL",
    "gn:name":"Dumbr\u0103veni",
    "gn:population":284,
    "gn:timezone":"Europe/Bucharest",
    "iso:country":"RO",
    "wof:name":"Dumbraveni",
    "wof:placetype":"locality",
    "wof:population":284
},
  "geometry": {"coordinates":[27.34714,46.76375],"type":"Point"}
}