{
  "type": "Feature",
  "properties": {
    "gn:admin1_code":"34",
    "gn:admin2_code":"148514.0",
    "gn:asciiname":"Tolesti",
    "gn:country_code":"RO",
    "gn:dem":345,
    "gn:feature_class":"P",
    "gn:feature_code":"PPL",
    "gn:name":"\u021aole\u0219ti",
    "gn:population":461,
    "gn:timezone":"Europe/Bucharest",
    "iso:country":"RO",
    "wof:name":"Tolesti",
    "wof:placetype":"locality",
    "wof:population":461
},
  "geometry": {"coordinates":[26.48631,47.37833],"type":"Point"}
}