{
  "type": "Feature",
  "properties": {
    "gn:admin1_code":"39",
    "gn:admin2_code":"170444.0",
    "gn:asciiname":"Magureni",
    "gn:country_code":"RO",
    "gn:dem":196,
    "gn:feature_class":"P",
    "gn:feature_code":"PPL",
    "gn:name":"M\u0103gureni",
    "gn:population":246,
    "gn:timezone":"Europe/Bucharest",
    "iso:country":"RO",
    "wof:name":"Magureni",
    "wof:placetype":"locality",
    "wof:population":246
},
  "geometry": {"coordinates":[24.1519,44.70012],"type":"Point"}
}