{
  "type": "Feature",
  "properties": {
    "gn:admin1_code":"03",
    "gn:admin2_code":"18581.0",
    "gn:asciiname":"Martesti",
    "gn:cc2":"RO",
    "gn:country_code":"RO",
    "gn:dem":251,
    "gn:feature_class":"P",
    "gn:feature_code":"PPLA2",
    "gn:name":"M\u00e2r\u0163e\u015fti",
    "gn:population":0,
    "gn:timezone":"Europe/Bucharest",
    "iso:country":"RO",
    "name:und_x_variant":[
        "M\u00eer\u0163e\u015fti-Mor\u0103re\u015fti",
        "M\u00eer\u0163e\u015fti"
    ],
    "wof:name":"Martesti",
    "wof:placetype":"locality"
},
  "geometry": {"coordinates":[24.75,44.71667],"type":"Point"}
}