{
  "type": "Feature",
  "properties": {
    "gn:admin1_code":"07",
    "gn:admin2_code":"39417.0",
    "gn:asciiname":"Durnesti",
    "gn:country_code":"RO",
    "gn:dem":91,
    "gn:feature_class":"P",
    "gn:feature_code":"PPL",
    "gn:name":"Durne\u0219ti",
    "gn:population":272,
    "gn:timezone":"Europe/Bucharest",
    "iso:country":"RO",
    "name:ita_x_preferred":[
        "Durne\u015fti"
    ],
    "name:por_x_preferred":[
        "Durne\u015fti"
    ],
    "name:ron_x_preferred":[
        "Durne\u0219ti"
    ],
    "name:ukr_x_preferred":[
        "\u0414\u0443\u0440\u043d\u0435\u0448\u0442\u044c"
    ],
    "name:vie_x_preferred":[
        "Durnesti"
    ],
    "name:vol_x_preferred":[
        "Durne\u015fti"
    ],
    "wof:name":"Durnesti",
    "wof:placetype":"locality",
    "wof:population":272
},
  "geometry": {"coordinates":[26.77462,47.8938],"type":"Point"}
}