{
  "type": "Feature",
  "properties": {
    "gn:admin1_code":"28",
    "gn:admin2_code":"123175.0",
    "gn:asciiname":"Itrinesti",
    "gn:country_code":"RO",
    "gn:dem":389,
    "gn:feature_class":"P",
    "gn:feature_code":"PPL",
    "gn:name":"Itrine\u0219ti",
    "gn:population":371,
    "gn:timezone":"Europe/Bucharest",
    "iso:country":"RO",
    "wof:name":"Itrinesti",
    "wof:placetype":"locality",
    "wof:population":371
},
  "geometry": {"coordinates":[26.62925,46.92535],"type":"Point"}
}