{
  "type": "Feature",
  "properties": {
    "gn:gn_country":"RO",
    "gn:gn_fcode":"PPLA2",
    "gn:gn_pop":4283,
    "gn:population":4283,
    "iso:country":"RO",
    "name:ara_x_preferred":[
        "\u062a\u0633\u063a\u0627\u0646\u0627\u0634\u064a"
    ],
    "name:dut_x_preferred":[
        "\u021aig\u0103na\u0219i"
    ],
    "name:eng_x_preferred":[
        "\u021aig\u0103na\u0219i"
    ],
    "name:fre_x_preferred":[
        "\u021aig\u0103na\u0219i"
    ],
    "name:ita_x_preferred":[
        "\u021aig\u0103na\u0219i"
    ],
    "name:may_x_preferred":[
        "\u021aig\u0103na\u0219i"
    ],
    "name:por_x_preferred":[
        "\u021aig\u0103na\u0219i"
    ],
    "name:rum_x_preferred":[
        "\u021aig\u0103na\u0219i"
    ],
    "name:srp_x_preferred":[
        "\u0426\u0438\u0433\u0430\u043d\u0430\u0448\u0438"
    ],
    "name:ukr_x_preferred":[
        "\u0426\u0438\u0433\u0435\u043d\u0430\u0448\u0456"
    ],
    "name:unk_x_variant":[
        "Tig\u0103nesti"
    ],
    "name:vie_x_preferred":[
        "Tiganasi"
    ],
    "name:vol_x_preferred":[
        "\u021aig\u0103na\u0219i"
    ],
    "qs_pg:aaroncc":"RO",
    "qs_pg:gn_country":"RO",
    "qs_pg:gn_fcode":"PPLA2",
    "qs_pg:gn_pop":4283,
    "qs_pg:name":"\u0162ig\u0103na\u0219i",
    "qs_pg:name_adm0":"Rom\u00e2nia",
    "qs_pg:name_adm1":"Iasi",
    "qs_pg:photos_9r":0,
    "qs_pg:photos_sr":0,
    "qs_pg:pop_sr":4,
    "qs_pg:qs_pg_placetype":"locality",
    "qs_pg:qs_pg_placetype_gp":"Town",
    "qs_pg:woe_adm0":23424933,
    "woe:adm0_id":23424933,
    "woe:name_adm0":"Rom\u00e2nia",
    "woe:name_adm1":"Iasi",
    "woe:placetype":"Town",
    "wof:name":"\u0162ig\u0103na\u0219i",
    "wof:placetype":"locality",
    "wof:population":4283
},
  "geometry": {"coordinates":[27.46667,47.33333],"type":"Point"}
}