{
  "type": "Feature",
  "properties": {
    "gn:admin1_code":"29",
    "gn:admin2_code":"128436",
    "gn:asciiname":"Buicesti",
    "gn:country_code":"RO",
    "gn:dem":181,
    "gn:feature_class":"P",
    "gn:feature_code":"PPL",
    "gn:name":"Buice\u0219ti",
    "gn:population":498,
    "gn:timezone":"Europe/Bucharest",
    "iso:country":"RO",
    "wof:name":"Buicesti",
    "wof:placetype":"locality",
    "wof:population":498
},
  "geometry": {"coordinates":[24.431,44.49369],"type":"Point"}
}