{
  "type": "Feature",
  "properties": {
    "gn:admin1_code":"38",
    "gn:admin2_code":"162791.0",
    "gn:asciiname":"Coroiesti",
    "gn:country_code":"RO",
    "gn:dem":144,
    "gn:feature_class":"P",
    "gn:feature_code":"PPL",
    "gn:name":"Coroie\u0219ti",
    "gn:population":249,
    "gn:timezone":"Europe/Bucharest",
    "iso:country":"RO",
    "wof:name":"Coroiesti",
    "wof:placetype":"locality",
    "wof:population":249
},
  "geometry": {"coordinates":[27.67243,46.43931],"type":"Point"}
}