{
  "type": "Feature",
  "properties": {
    "gn:admin1_code":"07",
    "gn:admin2_code":"39051.0",
    "gn:asciiname":"Poenita",
    "gn:country_code":"RO",
    "gn:dem":112,
    "gn:feature_class":"P",
    "gn:feature_code":"PPL",
    "gn:name":"Poeni\u0163a",
    "gn:population":0,
    "gn:timezone":"Europe/Bucharest",
    "iso:country":"RO",
    "wof:lang_x_official":[
        "ron"
    ],
    "wof:lang_x_spoken":[
        "ron"
    ],
    "wof:name":"Poenita",
    "wof:placetype":"locality"
},
  "geometry": {"coordinates":[26.91667,47.65],"type":"Point"}
}