{
  "type": "Feature",
  "properties": {
    "gn:admin1_code":"39",
    "gn:admin2_code":"173935.0",
    "gn:asciiname":"Folestii de Sus",
    "gn:country_code":"RO",
    "gn:dem":381,
    "gn:feature_class":"P",
    "gn:feature_code":"PPL",
    "gn:name":"Fole\u0219tii de Sus",
    "gn:population":767,
    "gn:timezone":"Europe/Bucharest",
    "iso:country":"RO",
    "wof:name":"Folestii de Sus",
    "wof:placetype":"locality",
    "wof:population":767
},
  "geometry": {"coordinates":[24.05971,45.09488],"type":"Point"}
}