{
  "type": "Feature",
  "properties": {
    "gn:admin1_code":"11",
    "gn:admin2_code":"47079.0",
    "gn:asciiname":"Vadu Oii",
    "gn:country_code":"RO",
    "gn:dem":594,
    "gn:feature_class":"P",
    "gn:feature_code":"PPL",
    "gn:name":"Vadu Oii",
    "gn:population":103,
    "gn:timezone":"Europe/Bucharest",
    "iso:country":"RO",
    "name:ceb_x_preferred":[
        "Vadu Oii"
    ],
    "name:deu_x_preferred":[
        "Vadu Oii"
    ],
    "name:ron_x_preferred":[
        "Vadu Oii"
    ],
    "name:srp_x_preferred":[
        "\u0412\u0430\u0434\u0443 \u041e\u0438\u0458"
    ],
    "wof:name":"Vadu Oii",
    "wof:placetype":"locality",
    "wof:population":103
},
  "geometry": {"coordinates":[26.47544000000001,45.53419],"type":"Point"}
}