{
  "type": "Feature",
  "properties": {
    "gn:admin1_code":"08",
    "gn:admin2_code":"43411.0",
    "gn:asciiname":"Maru Rosu",
    "gn:country_code":"RO",
    "gn:dem":33,
    "gn:feature_class":"P",
    "gn:feature_code":"PPL",
    "gn:name":"M\u0103ru Ro\u0219u",
    "gn:population":104,
    "gn:timezone":"Europe/Bucharest",
    "iso:country":"RO",
    "wof:name":"Maru Rosu",
    "wof:placetype":"locality",
    "wof:population":104
},
  "geometry": {"coordinates":[27.65409,44.90119],"type":"Point"}
}