{
  "type": "Feature",
  "properties": {
    "gn:admin1_code":"39",
    "gn:admin2_code":"172377.0",
    "gn:asciiname":"Firijba",
    "gn:country_code":"RO",
    "gn:dem":345,
    "gn:feature_class":"P",
    "gn:feature_code":"PPL",
    "gn:name":"Firijba",
    "gn:population":57,
    "gn:timezone":"Europe/Bucharest",
    "iso:country":"RO",
    "wof:name":"Firijba",
    "wof:placetype":"locality",
    "wof:population":57
},
  "geometry": {"coordinates":[24.13147,44.98958],"type":"Point"}
}