{
  "type": "Feature",
  "properties": {
    "gn:admin1_code":"13",
    "gn:admin2_code":"57644.0",
    "gn:asciiname":"Sacalaia",
    "gn:country_code":"RO",
    "gn:dem":316,
    "gn:feature_class":"P",
    "gn:feature_code":"PPL",
    "gn:name":"S\u0103c\u0103laia",
    "gn:population":253,
    "gn:timezone":"Europe/Bucharest",
    "iso:country":"RO",
    "wof:name":"Sacalaia",
    "wof:placetype":"locality",
    "wof:population":253
},
  "geometry": {"coordinates":[23.92055,46.96452],"type":"Point"}
}