{
  "type": "Feature",
  "properties": {
    "gn:admin1_code":"11",
    "gn:admin2_code":"44863.0",
    "gn:asciiname":"Lunca",
    "gn:cc2":"RO",
    "gn:country_code":"RO",
    "gn:dem":76,
    "gn:feature_class":"P",
    "gn:feature_code":"PPL",
    "gn:name":"Lunca",
    "gn:population":215,
    "gn:timezone":"Europe/Bucharest",
    "iso:country":"RO",
    "name:ceb_x_preferred":[
        "Lunca"
    ],
    "name:deu_x_preferred":[
        "Lunca"
    ],
    "name:epo_x_preferred":[
        "Lunca"
    ],
    "name:fra_x_preferred":[
        "Lunca"
    ],
    "name:hun_x_preferred":[
        "Lunca"
    ],
    "name:ita_x_preferred":[
        "Lunca"
    ],
    "name:nld_x_preferred":[
        "Lunca"
    ],
    "name:ron_x_preferred":[
        "Lunca"
    ],
    "name:srp_x_preferred":[
        "\u041b\u0443\u043d\u043a\u0430"
    ],
    "name:und_x_variant":[
        "Miro\u015fi"
    ],
    "name:vol_x_preferred":[
        "Lunca"
    ],
    "wof:name":"Lunca",
    "wof:placetype":"locality",
    "wof:population":215
},
  "geometry": {"coordinates":[26.64052,44.95795],"type":"Point"}
}