{
  "type": "Feature",
  "properties": {
    "gn:population":1345,
    "iso:country":"RO",
    "name:dut_x_preferred":[
        "Uioara de Jos"
    ],
    "name:eng_x_preferred":[
        "Uioara de Jos"
    ],
    "name:epo_x_preferred":[
        "Uioara de Jos"
    ],
    "name:hun_x_preferred":[
        "Csongva"
    ],
    "name:rum_x_preferred":[
        "Uioara de Jos"
    ],
    "name:ukr_x_preferred":[
        "\u0423\u0439\u043e\u0430\u0440\u0430-\u0434\u0435-\u0416\u043e\u0441"
    ],
    "name:unk_x_variant":[
        "Ciunga"
    ],
    "qs:a0":"Rom\u00e2nia",
    "qs:a1":"*Alba",
    "qs:a1r":"0",
    "qs:adm0":"Rom\u00e2nia",
    "qs:la_lc":"*",
    "qs:level":"locality",
    "qs:loc":"Uioara de Jos",
    "qs:loc_alt":"Uioara de Jos",
    "qs:pop":0,
    "qs:type":"buffered point",
    "wof:name":"Uioara de Jos",
    "wof:placetype":"locality",
    "wof:population":1345
},
  "geometry": {"coordinates":[23.828867,46.382283],"type":"Point"}
}