{
  "type": "Feature",
  "properties": {
    "gn:admin1_code":"05",
    "gn:admin2_code":"27631.0",
    "gn:asciiname":"Santaul Mic",
    "gn:cc2":"RO",
    "gn:country_code":"RO",
    "gn:dem":101,
    "gn:feature_class":"P",
    "gn:feature_code":"PPL",
    "gn:name":"Sant\u0103ul Mic",
    "gn:population":403,
    "gn:timezone":"Europe/Bucharest",
    "iso:country":"RO",
    "name:und_x_variant":[
        "S\u00e2nt\u0103ul-Mic",
        "S\u00eent\u0103u Mic",
        "Sant\u0103u Mic"
    ],
    "wof:name":"Santaul Mic",
    "wof:placetype":"locality",
    "wof:population":403
},
  "geometry": {"coordinates":[21.83322,47.14248],"type":"Point"}
}