{
  "type": "Feature",
  "properties": {
    "gn:admin1_code":"36",
    "gn:admin2_code":"158010.0",
    "gn:asciiname":"Cornesti",
    "gn:cc2":"RO",
    "gn:country_code":"RO",
    "gn:dem":126,
    "gn:feature_class":"P",
    "gn:feature_code":"PPL",
    "gn:name":"Corne\u0219ti",
    "gn:population":537,
    "gn:timezone":"Europe/Bucharest",
    "iso:country":"RO",
    "name:und_x_variant":[
        "Mez\u0151zsad\u00e1ny",
        "Zsad\u00e1ny",
        "Jadani",
        "Corne\u015fti"
    ],
    "wof:name":"Cornesti",
    "wof:placetype":"locality",
    "wof:population":537
},
  "geometry": {"coordinates":[21.2258,45.91236],"type":"Point"}
}