{
  "type": "Feature",
  "properties": {
    "gn:admin1_code":"13",
    "gn:admin2_code":"57350.0",
    "gn:asciiname":"Moristi",
    "gn:country_code":"RO",
    "gn:dem":365,
    "gn:feature_class":"P",
    "gn:feature_code":"PPL",
    "gn:name":"Mori\u0219ti",
    "gn:population":21,
    "gn:timezone":"Europe/Bucharest",
    "iso:country":"RO",
    "wof:name":"Moristi",
    "wof:placetype":"locality",
    "wof:population":21
},
  "geometry": {"coordinates":[23.79624,46.77468],"type":"Point"}
}