{
  "type": "Feature",
  "properties": {
    "gn:admin1_code":"26",
    "gn:admin2_code":"113395.0",
    "gn:asciiname":"Cearangu",
    "gn:cc2":"RO",
    "gn:country_code":"RO",
    "gn:dem":112,
    "gn:feature_class":"P",
    "gn:feature_code":"PPL",
    "gn:name":"Cear\u00e2ngu",
    "gn:population":271,
    "gn:timezone":"Europe/Bucharest",
    "iso:country":"RO",
    "name:und_x_variant":[
        "Cear\u00eengu",
        "Cear\u00e2ngul",
        "Cear\u00e2ngu"
    ],
    "wof:name":"Cearangu",
    "wof:placetype":"locality",
    "wof:population":271
},
  "geometry": {"coordinates":[22.98181,44.28187],"type":"Point"}
}