{
  "type": "Feature",
  "properties": {
    "gn:admin1_code":"30",
    "gn:admin2_code":"134390.0",
    "gn:asciiname":"Galmeia",
    "gn:country_code":"RO",
    "gn:dem":363,
    "gn:feature_class":"P",
    "gn:feature_code":"PPL",
    "gn:name":"G\u00e2lmeia",
    "gn:population":244,
    "gn:timezone":"Europe/Bucharest",
    "iso:country":"RO",
    "wof:name":"Galmeia",
    "wof:placetype":"locality",
    "wof:population":244
},
  "geometry": {"coordinates":[26.10043,45.03583],"type":"Point"}
}