{
  "type": "Feature",
  "properties": {
    "gn:admin1_code":"31",
    "gn:admin2_code":"142499.0",
    "gn:asciiname":"Fantanele-Rus",
    "gn:cc2":"RO",
    "gn:country_code":"RO",
    "gn:dem":292,
    "gn:feature_class":"P",
    "gn:feature_code":"PPL",
    "gn:name":"F\u00e2nt\u00e2nele-Rus",
    "gn:population":0,
    "gn:timezone":"Europe/Bucharest",
    "iso:country":"RO",
    "name:und_x_variant":[
        "Iapa",
        "F\u00eent\u00eenele-Rus",
        "F\u00eent\u00eenele"
    ],
    "wof:name":"Fantanele-Rus",
    "wof:placetype":"locality"
},
  "geometry": {"coordinates":[23.55,47.25],"type":"Point"}
}