{
  "type": "Feature",
  "properties": {
    "gn:admin1_code":"17",
    "gn:admin2_code":"74411.0",
    "gn:asciiname":"Urieni",
    "gn:country_code":"RO",
    "gn:dem":128,
    "gn:feature_class":"P",
    "gn:feature_code":"PPL",
    "gn:name":"Urieni",
    "gn:population":0,
    "gn:timezone":"Europe/Bucharest",
    "iso:country":"RO",
    "wof:name":"Urieni",
    "wof:placetype":"locality"
},
  "geometry": {"coordinates":[24.14658,44.21722000000001],"type":"Point"}
}