{
  "type": "Feature",
  "properties": {
    "gn:admin1_code":"35",
    "gn:admin2_code":"154585.0",
    "gn:asciiname":"Obartu",
    "gn:cc2":"RO",
    "gn:country_code":"RO",
    "gn:dem":103,
    "gn:feature_class":"P",
    "gn:feature_code":"PPL",
    "gn:name":"Ob\u00e2rtu",
    "gn:population":47,
    "gn:timezone":"Europe/Bucharest",
    "iso:country":"RO",
    "name:und_x_variant":[
        "Ob\u00e2rt",
        "Ob\u00eertu"
    ],
    "wof:name":"Obartu",
    "wof:placetype":"locality",
    "wof:population":47
},
  "geometry": {"coordinates":[25.19082,44.31985],"type":"Point"}
}