{
  "type": "Feature",
  "properties": {
    "gn:admin1_code":"19",
    "gn:admin2_code":"79077.0",
    "gn:asciiname":"Miclosu",
    "gn:cc2":"RO",
    "gn:country_code":"RO",
    "gn:dem":187,
    "gn:feature_class":"P",
    "gn:feature_code":"PPL",
    "gn:name":"Miclosu",
    "gn:population":244,
    "gn:timezone":"Europe/Bucharest",
    "iso:country":"RO",
    "name:und_x_variant":[
        "Miclosiu",
        "Miclo\u015fu"
    ],
    "wof:name":"Miclosu",
    "wof:placetype":"locality",
    "wof:population":244
},
  "geometry": {"coordinates":[23.22277,44.73991],"type":"Point"}
}