{
  "type": "Feature",
  "properties": {
    "gn:gn_country":"RO",
    "gn:gn_fcode":"PPLA2",
    "gn:gn_pop":943,
    "gn:population":943,
    "iso:country":"RO",
    "name:ara_x_preferred":[
        "\u0634\u064a\u0644\u064a\u0646\u062f\u064a\u0627"
    ],
    "name:ceb_x_preferred":[
        "\u0218ilindia"
    ],
    "name:eng_x_preferred":[
        "\u0218ilindia"
    ],
    "name:epo_x_preferred":[
        "\u0218ilindia"
    ],
    "name:fra_x_preferred":[
        "\u0218ilindia"
    ],
    "name:hun_x_preferred":[
        "Sel\u00e9nd"
    ],
    "name:ita_x_preferred":[
        "\u0218ilindia"
    ],
    "name:msa_x_preferred":[
        "\u0218ilindia"
    ],
    "name:nld_x_preferred":[
        "\u0218ilindia"
    ],
    "name:por_x_preferred":[
        "\u0218ilindia"
    ],
    "name:ron_x_preferred":[
        "\u0218ilindia"
    ],
    "name:sqi_x_preferred":[
        "\u0218ilindia"
    ],
    "name:srp_x_preferred":[
        "\u0428\u0438\u043b\u0438\u043d\u0434\u0438\u0458\u0430"
    ],
    "name:ukr_x_preferred":[
        "\u0428\u0438\u043b\u0456\u043d\u0434\u0456\u044f"
    ],
    "name:vie_x_preferred":[
        "Silindia"
    ],
    "name:vol_x_preferred":[
        "\u0218ilindia"
    ],
    "qs_pg:aaroncc":"RO",
    "qs_pg:gn_country":"RO",
    "qs_pg:gn_fcode":"PPLA2",
    "qs_pg:gn_pop":943,
    "qs_pg:name":"\u015eilindia",
    "qs_pg:name_adm0":"Rom\u00e2nia",
    "qs_pg:name_adm1":"Arad",
    "qs_pg:photos_9r":0,
    "qs_pg:photos_sr":0,
    "qs_pg:pop_sr":2,
    "qs_pg:qs_pg_placetype":"locality",
    "qs_pg:qs_pg_placetype_gp":"Town",
    "qs_pg:woe_adm0":23424933,
    "woe:adm0_id":23424933,
    "woe:name_adm0":"Rom\u00e2nia",
    "woe:name_adm1":"Arad",
    "woe:placetype":"Town",
    "wof:name":"\u015eilindia",
    "wof:placetype":"locality",
    "wof:population":943
},
  "geometry": {"coordinates":[21.91667,46.35],"type":"Point"}
}