{
  "type": "Feature",
  "properties": {
    "gn:admin1_code":"11",
    "gn:admin2_code":"47453.0",
    "gn:asciiname":"Ograzile",
    "gn:country_code":"RO",
    "gn:dem":117,
    "gn:feature_class":"P",
    "gn:feature_code":"PPL",
    "gn:name":"Ogr\u0103zile",
    "gn:population":757,
    "gn:timezone":"Europe/Bucharest",
    "iso:country":"RO",
    "wof:name":"Ograzile",
    "wof:placetype":"locality",
    "wof:population":757
},
  "geometry": {"coordinates":[26.67993,45.11703],"type":"Point"}
}