{
  "type": "Feature",
  "properties": {
    "gn:country":"RO",
    "gn:fcode":"PPLA2",
    "gn:population":2435,
    "iso:country":"RO",
    "name:ceb_x_preferred":[
        "C\u0103preni"
    ],
    "name:eng_x_preferred":[
        "C\u0103preni"
    ],
    "name:fra_x_preferred":[
        "C\u0103preni"
    ],
    "name:ita_x_preferred":[
        "C\u0103preni"
    ],
    "name:msa_x_preferred":[
        "C\u0103preni"
    ],
    "name:nld_x_preferred":[
        "C\u0103preni"
    ],
    "name:por_x_preferred":[
        "C\u0103preni"
    ],
    "name:ron_x_preferred":[
        "C\u0103preni"
    ],
    "name:srp_x_preferred":[
        "\u041a\u0430\u043f\u0440\u0435\u043d\u0438"
    ],
    "name:ukr_x_preferred":[
        "\u041a\u0435\u043f\u0440\u0435\u043d\u044c"
    ],
    "name:und_x_variant":[
        "C\u0103prenii de Myloc"
    ],
    "name:vol_x_preferred":[
        "C\u0103preni"
    ],
    "qs_pg:aaroncc":"RO",
    "qs_pg:gn_country":"RO",
    "qs_pg:gn_fcode":"PPLA2",
    "qs_pg:gn_pop":2435,
    "qs_pg:name":"C\u0103preni",
    "qs_pg:name_adm0":"Rom\u00e2nia",
    "qs_pg:name_adm1":"Gorj",
    "qs_pg:photos_9r":0,
    "qs_pg:photos_sr":0,
    "qs_pg:pop_sr":4,
    "qs_pg:qs_pg_placetype":"locality",
    "qs_pg:qs_pg_placetype_gp":"Town",
    "qs_pg:woe_adm0":23424933,
    "woe:adm0_id":23424933,
    "woe:name_adm0":"Rom\u00e2nia",
    "woe:name_adm1":"Gorj",
    "woe:placetype":"Town",
    "wof:name":"C\u0103preni",
    "wof:placetype":"locality",
    "wof:population":2435
},
  "geometry": {"coordinates":[23.61667,44.75],"type":"Point"}
}