{
  "type": "Feature",
  "properties": {
    "gn:admin1_code":"23",
    "gn:admin2_code":"97722.0",
    "gn:asciiname":"Goesti",
    "gn:country_code":"RO",
    "gn:dem":110,
    "gn:feature_class":"P",
    "gn:feature_code":"PPL",
    "gn:name":"Goe\u0219ti",
    "gn:population":1160,
    "gn:timezone":"Europe/Bucharest",
    "iso:country":"RO",
    "wof:name":"Goesti",
    "wof:placetype":"locality",
    "wof:population":1160
},
  "geometry": {"coordinates":[27.13659,47.15654],"type":"Point"}
}