{
  "type": "Feature",
  "properties": {
    "gn:admin1_code":"31",
    "gn:admin2_code":"140958.0",
    "gn:asciiname":"Naimon",
    "gn:country_code":"RO",
    "gn:dem":205,
    "gn:feature_class":"P",
    "gn:feature_code":"PPL",
    "gn:name":"Naimon",
    "gn:population":95,
    "gn:timezone":"Europe/Bucharest",
    "iso:country":"RO",
    "wof:name":"Naimon",
    "wof:placetype":"locality",
    "wof:population":95
},
  "geometry": {"coordinates":[23.11765,47.32744],"type":"Point"}
}