{
  "type": "Feature",
  "properties": {
    "gn:admin1_code":"23",
    "gn:admin2_code":"98827.0",
    "gn:asciiname":"Satu Nou",
    "gn:country_code":"RO",
    "gn:dem":171,
    "gn:feature_class":"P",
    "gn:feature_code":"PPL",
    "gn:name":"Satu Nou",
    "gn:population":545,
    "gn:timezone":"Europe/Bucharest",
    "iso:country":"RO",
    "name:ceb_x_preferred":[
        "Satu Nou"
    ],
    "name:deu_x_preferred":[
        "Satu Nou"
    ],
    "name:epo_x_preferred":[
        "Satu Nou"
    ],
    "name:hun_x_preferred":[
        "Satu Nou"
    ],
    "name:ron_x_preferred":[
        "Satu Nou"
    ],
    "name:srp_x_preferred":[
        "\u041d\u043e\u0432\u043e \u0441\u0435\u043b\u043e"
    ],
    "name:ukr_x_preferred":[
        "\u0421\u0430\u0442\u0443-\u041d\u043e\u0443"
    ],
    "wof:name":"Satu Nou",
    "wof:placetype":"locality",
    "wof:population":545
},
  "geometry": {"coordinates":[27.81211,46.96352],"type":"Point"}
}