{
  "type": "Feature",
  "properties": {
    "gn:admin1_code":"06",
    "gn:admin2_code":"35312.0",
    "gn:asciiname":"Coseriu",
    "gn:country_code":"RO",
    "gn:dem":380,
    "gn:feature_class":"P",
    "gn:feature_code":"PPL",
    "gn:name":"Co\u0219eriu",
    "gn:population":99,
    "gn:timezone":"Europe/Bucharest",
    "iso:country":"RO",
    "wof:name":"Coseriu",
    "wof:placetype":"locality",
    "wof:population":99
},
  "geometry": {"coordinates":[24.3787,46.81573],"type":"Point"}
}