{
  "type": "Feature",
  "properties": {
    "gn:gn_country":"RO",
    "gn:gn_fcode":"PPLA2",
    "gn:gn_pop":2381,
    "gn:population":679,
    "iso:country":"RO",
    "name:dut_x_preferred":[
        "R\u0103zboieni"
    ],
    "name:eng_x_preferred":[
        "R\u0103zboieni"
    ],
    "name:fre_x_preferred":[
        "R\u0103zboieni"
    ],
    "name:hun_x_preferred":[
        "R\u0103zboieni"
    ],
    "name:ita_x_preferred":[
        "R\u0103zboieni"
    ],
    "name:por_x_preferred":[
        "R\u0103zboieni"
    ],
    "name:rum_x_preferred":[
        "R\u0103zboieni"
    ],
    "name:ukr_x_preferred":[
        "\u0420\u0435\u0437\u0431\u043e\u0454\u043d\u044c"
    ],
    "name:vie_x_preferred":[
        "Razboieni"
    ],
    "name:vol_x_preferred":[
        "R\u0103zboieni"
    ],
    "qs_pg:aaroncc":"RO",
    "qs_pg:gn_country":"RO",
    "qs_pg:gn_fcode":"PPLA2",
    "qs_pg:gn_pop":2381,
    "qs_pg:name":"R\u0103zboeni",
    "qs_pg:name_adm0":"Rom\u00e2nia",
    "qs_pg:name_adm1":"Neamt",
    "qs_pg:photos_9r":0,
    "qs_pg:photos_sr":0,
    "qs_pg:pop_sr":4,
    "qs_pg:qs_pg_placetype":"locality",
    "qs_pg:qs_pg_placetype_gp":"Town",
    "qs_pg:woe_adm0":23424933,
    "woe:adm0_id":23424933,
    "woe:name_adm0":"Rom\u00e2nia",
    "woe:name_adm1":"Neamt",
    "woe:placetype":"Town",
    "wof:name":"R\u0103zboeni",
    "wof:placetype":"locality",
    "wof:population":679
},
  "geometry": {"coordinates":[26.53333,47.08333],"type":"Point"}
}