{
  "type": "Feature",
  "properties": {
    "gn:admin1_code":"08",
    "gn:admin2_code":"43180.0",
    "gn:asciiname":"Drogu",
    "gn:cc2":"RO",
    "gn:country_code":"RO",
    "gn:dem":48,
    "gn:feature_class":"P",
    "gn:feature_code":"PPL",
    "gn:name":"Drogu",
    "gn:population":972,
    "gn:timezone":"Europe/Bucharest",
    "iso:country":"RO",
    "name:und_x_variant":[
        "Drogul",
        "Drogu"
    ],
    "wof:name":"Drogu",
    "wof:placetype":"locality",
    "wof:population":972
},
  "geometry": {"coordinates":[27.23174,45.18264],"type":"Point"}
}