{
  "type": "Feature",
  "properties": {
    "gn:gn_country":"RO",
    "gn:gn_fcode":"PPLA2",
    "gn:gn_pop":2298,
    "gn:population":2298,
    "iso:country":"RO",
    "name:alb_x_preferred":[
        "Mir\u0103sl\u0103u"
    ],
    "name:ara_x_preferred":[
        "\u0645\u064a\u0631\u0627\u0633\u0644\u0627\u0648"
    ],
    "name:dut_x_preferred":[
        "Mir\u0103sl\u0103u"
    ],
    "name:eng_x_preferred":[
        "Mir\u0103sl\u0103u"
    ],
    "name:epo_x_preferred":[
        "Mir\u0103sl\u0103u"
    ],
    "name:fre_x_preferred":[
        "Mir\u0103sl\u0103u"
    ],
    "name:ger_x_preferred":[
        "Mir\u0103sl\u0103u"
    ],
    "name:hun_x_preferred":[
        "Miriszl\u00f3"
    ],
    "name:ita_x_preferred":[
        "Mir\u0103sl\u0103u"
    ],
    "name:mac_x_preferred":[
        "\u041c\u0438\u0440\u0430\u0441\u043b\u0430\u0443"
    ],
    "name:may_x_preferred":[
        "Mir\u0103sl\u0103u"
    ],
    "name:por_x_preferred":[
        "Mir\u0103sl\u0103u"
    ],
    "name:rum_x_preferred":[
        "Mir\u0103sl\u0103u"
    ],
    "name:ukr_x_preferred":[
        "\u041c\u0456\u0440\u0435\u0441\u043b\u0435\u0443"
    ],
    "name:unk_x_variant":[
        "Mirisl\u0103u"
    ],
    "name:vol_x_preferred":[
        "Mir\u0103sl\u0103u"
    ],
    "qs_pg:aaroncc":"RO",
    "qs_pg:gn_country":"RO",
    "qs_pg:gn_fcode":"PPLA2",
    "qs_pg:gn_pop":2298,
    "qs_pg:name":"Mir\u0103sl\u0103u",
    "qs_pg:name_adm0":"Rom\u00e2nia",
    "qs_pg:name_adm1":"Alba",
    "qs_pg:photos_9r":0,
    "qs_pg:photos_sr":0,
    "qs_pg:pop_sr":4,
    "qs_pg:qs_pg_placetype":"locality",
    "qs_pg:qs_pg_placetype_gp":"Town",
    "qs_pg:woe_adm0":23424933,
    "woe:adm0_id":23424933,
    "woe:name_adm0":"Rom\u00e2nia",
    "woe:name_adm1":"Alba",
    "woe:placetype":"Town",
    "wof:name":"Mir\u0103sl\u0103u",
    "wof:placetype":"locality",
    "wof:population":2298
},
  "geometry": {"coordinates":[23.71667,46.36667],"type":"Point"}
}