{
  "type": "Feature",
  "properties": {
    "gn:admin1_code":"39",
    "gn:admin2_code":"171272.0",
    "gn:asciiname":"Rosoveni",
    "gn:country_code":"RO",
    "gn:dem":586,
    "gn:feature_class":"P",
    "gn:feature_code":"PPL",
    "gn:name":"Ro\u0219oveni",
    "gn:population":8,
    "gn:timezone":"Europe/Bucharest",
    "iso:country":"RO",
    "wof:name":"Rosoveni",
    "wof:placetype":"locality",
    "wof:population":8
},
  "geometry": {"coordinates":[23.99077,45.09447],"type":"Point"}
}