{
  "type": "Feature",
  "properties": {
    "gn:admin1_code":"42",
    "gn:admin2_code":"105972.0",
    "gn:asciiname":"Poiana lui Stanga",
    "gn:cc2":"RO",
    "gn:country_code":"RO",
    "gn:dem":130,
    "gn:feature_class":"P",
    "gn:feature_code":"PPL",
    "gn:name":"Poiana lui St\u00e2ng\u0103",
    "gn:population":707,
    "gn:timezone":"Europe/Bucharest",
    "iso:country":"RO",
    "name:und_x_variant":[
        "Poiana lui St\u00eeng\u0103",
        "Poiana lui St\u00e2nga"
    ],
    "wof:name":"Poiana lui Stanga",
    "wof:placetype":"locality",
    "wof:population":707
},
  "geometry": {"coordinates":[25.58605,44.51141],"type":"Point"}
}