{
  "type": "Feature",
  "properties": {
    "gn:admin1_code":"21",
    "gn:admin2_code":"90878.0",
    "gn:asciiname":"Ostrovu Mic",
    "gn:country_code":"RO",
    "gn:dem":450,
    "gn:feature_class":"P",
    "gn:feature_code":"PPL",
    "gn:name":"Ostrovu Mic",
    "gn:population":118,
    "gn:timezone":"Europe/Bucharest",
    "iso:country":"RO",
    "wof:name":"Ostrovu Mic",
    "wof:placetype":"locality",
    "wof:population":118
},
  "geometry": {"coordinates":[22.84474,45.51596],"type":"Point"}
}