{
  "type": "Feature",
  "properties": {
    "gn:admin1_code":"39",
    "gn:admin2_code":"172457",
    "gn:asciiname":"Barbuceni",
    "gn:cc2":"RO",
    "gn:country_code":"RO",
    "gn:dem":170,
    "gn:feature_class":"P",
    "gn:feature_code":"PPL",
    "gn:name":"B\u0103rbuceni",
    "gn:population":571,
    "gn:timezone":"Europe/Bucharest",
    "iso:country":"RO",
    "name:und_x_variant":[
        "B\u0103rbucea",
        "B\u0103rbuceni"
    ],
    "wof:name":"Barbuceni",
    "wof:placetype":"locality",
    "wof:population":571
},
  "geometry": {"coordinates":[24.24482,44.74639000000001],"type":"Point"}
}