{
  "type": "Feature",
  "properties": {
    "gn:admin1_code":"08",
    "gn:admin2_code":"43493.0",
    "gn:asciiname":"Scanteia",
    "gn:country_code":"RO",
    "gn:dem":4,
    "gn:feature_class":"P",
    "gn:feature_code":"PPL",
    "gn:name":"Sc\u00e2nteia",
    "gn:population":0,
    "gn:timezone":"Europe/Bucharest",
    "iso:country":"RO",
    "wof:name":"Scanteia",
    "wof:placetype":"locality"
},
  "geometry": {"coordinates":[27.95,44.85],"type":"Point"}
}