{
  "type": "Feature",
  "properties": {
    "gn:admin1_code":"04",
    "gn:admin2_code":"24427",
    "gn:asciiname":"Budesti",
    "gn:country_code":"RO",
    "gn:dem":216,
    "gn:feature_class":"P",
    "gn:feature_code":"PPL",
    "gn:name":"Bude\u0219ti",
    "gn:population":391,
    "gn:timezone":"Europe/Bucharest",
    "iso:country":"RO",
    "wof:name":"Budesti",
    "wof:placetype":"locality",
    "wof:population":391
},
  "geometry": {"coordinates":[27.24988,46.65812],"type":"Point"}
}