{
  "type": "Feature",
  "properties": {
    "gn:admin1_code":"12",
    "gn:admin2_code":"51387.0",
    "gn:asciiname":"Rusova Veche",
    "gn:cc2":"RO",
    "gn:country_code":"RO",
    "gn:dem":103,
    "gn:feature_class":"P",
    "gn:feature_code":"PPL",
    "gn:name":"Rusova Veche",
    "gn:population":89,
    "gn:timezone":"Europe/Bucharest",
    "iso:country":"RO",
    "name:und_x_variant":[
        "Stara-Rusova",
        "Rusova Veche"
    ],
    "wof:name":"Rusova Veche",
    "wof:placetype":"locality",
    "wof:population":89
},
  "geometry": {"coordinates":[21.50728,44.9782],"type":"Point"}
}