{
  "type": "Feature",
  "properties": {
    "gn:admin1_code":"13",
    "gn:admin2_code":"58008.0",
    "gn:asciiname":"Buru",
    "gn:cc2":"RO",
    "gn:country_code":"RO",
    "gn:dem":368,
    "gn:feature_class":"P",
    "gn:feature_code":"PPL",
    "gn:name":"Buru",
    "gn:population":280,
    "gn:timezone":"Europe/Bucharest",
    "iso:country":"RO",
    "name:und_x_variant":[
        "Burul",
        "Buru"
    ],
    "wof:name":"Buru",
    "wof:placetype":"locality",
    "wof:population":280
},
  "geometry": {"coordinates":[23.60255,46.50622],"type":"Point"}
}