{
  "type": "Feature",
  "properties": {
    "gn:admin1_code":"38",
    "gn:admin2_code":"162595.0",
    "gn:asciiname":"Lacu Babei",
    "gn:country_code":"RO",
    "gn:dem":415,
    "gn:feature_class":"P",
    "gn:feature_code":"PPL",
    "gn:name":"Lacu Babei",
    "gn:population":265,
    "gn:timezone":"Europe/Bucharest",
    "iso:country":"RO",
    "wof:name":"Lacu Babei",
    "wof:placetype":"locality",
    "wof:population":265
},
  "geometry": {"coordinates":[27.59016,46.58559],"type":"Point"}
}