{
  "type": "Feature",
  "properties": {
    "gn:admin1_code":"01",
    "gn:admin2_code":"4302.0",
    "gn:asciiname":"Medves",
    "gn:country_code":"RO",
    "gn:dem":360,
    "gn:feature_class":"P",
    "gn:feature_code":"PPL",
    "gn:name":"Medve\u0219",
    "gn:population":263,
    "gn:timezone":"Europe/Bucharest",
    "iso:country":"RO",
    "wof:name":"Medves",
    "wof:placetype":"locality",
    "wof:population":263
},
  "geometry": {"coordinates":[24.06467,46.30582],"type":"Point"}
}