{
  "type": "Feature",
  "properties": {
    "gn:admin1_code":"11",
    "gn:admin2_code":"47186",
    "gn:asciiname":"Basceni",
    "gn:cc2":"RO",
    "gn:country_code":"RO",
    "gn:dem":420,
    "gn:feature_class":"P",
    "gn:feature_code":"PPL",
    "gn:name":"B\u00e2sceni",
    "gn:population":0,
    "gn:timezone":"Europe/Bucharest",
    "iso:country":"RO",
    "name:und_x_variant":[
        "B\u00eesceni"
    ],
    "wof:lang_x_official":[
        "ron"
    ],
    "wof:lang_x_spoken":[
        "ron"
    ],
    "wof:name":"Basceni",
    "wof:placetype":"locality"
},
  "geometry": {"coordinates":[26.61667,45.48333],"type":"Point"}
}