{
  "type": "Feature",
  "properties": {
    "gn:gn_country":"RO",
    "gn:gn_fcode":"PPLA2",
    "gn:gn_pop":1552,
    "gn:population":1552,
    "iso:country":"RO",
    "name:fra_x_preferred":[
        "Corl\u0103\u021bel"
    ],
    "name:ita_x_preferred":[
        "Corl\u0103\u0163el"
    ],
    "name:nld_x_preferred":[
        "Corl\u0103\u021bel"
    ],
    "name:por_x_preferred":[
        "Corl\u0103\u0163el"
    ],
    "name:ron_x_preferred":[
        "Corl\u0103\u021bel"
    ],
    "name:ukr_x_preferred":[
        "\u041a\u043e\u0440\u043b\u0435\u0446\u0435\u043b"
    ],
    "name:unk_x_variant":[
        "Corl\u0103\u0163elu"
    ],
    "name:vie_x_preferred":[
        "Corlatel"
    ],
    "name:vol_x_preferred":[
        "Corl\u0103\u0163el"
    ],
    "qs_pg:aaroncc":"RO",
    "qs_pg:gn_country":"RO",
    "qs_pg:gn_fcode":"PPLA2",
    "qs_pg:gn_pop":1552,
    "qs_pg:name":"Corl\u0103\u0163el",
    "qs_pg:photos_9r":0,
    "qs_pg:photos_sr":0,
    "qs_pg:pop_sr":3,
    "qs_pg:qs_pg_placetype":"locality",
    "wof:name":"Corl\u0103\u0163el",
    "wof:placetype":"locality",
    "wof:population":1552
},
  "geometry": {"coordinates":[22.93306,44.39861],"type":"Point"}
}