{
  "type": "Feature",
  "properties": {
    "gn:admin1_code":"21",
    "gn:admin2_code":"89561.0",
    "gn:asciiname":"Vantulesti",
    "gn:country_code":"RO",
    "gn:dem":423,
    "gn:feature_class":"P",
    "gn:feature_code":"PPL",
    "gn:name":"V\u00e2ntule\u015fti",
    "gn:population":0,
    "gn:timezone":"Europe/Bucharest",
    "iso:country":"RO",
    "wof:name":"Vantulesti",
    "wof:placetype":"locality"
},
  "geometry": {"coordinates":[23.25,45.95],"type":"Point"}
}