{
  "type": "Feature",
  "properties": {
    "gn:admin1_code":"05",
    "gn:admin2_code":"29519.0",
    "gn:asciiname":"Santelec",
    "gn:cc2":"RO",
    "gn:country_code":"RO",
    "gn:dem":208,
    "gn:feature_class":"P",
    "gn:feature_code":"PPL",
    "gn:name":"S\u00e2ntelec",
    "gn:population":379,
    "gn:timezone":"Europe/Bucharest",
    "iso:country":"RO",
    "name:und_x_variant":[
        "S\u00e2ntelec",
        "S\u00eentelec"
    ],
    "wof:name":"Santelec",
    "wof:placetype":"locality",
    "wof:population":379
},
  "geometry": {"coordinates":[22.06468,46.95822],"type":"Point"}
}