{
  "type": "Feature",
  "properties": {
    "gn:admin1_code":"32",
    "gn:admin2_code":"136848.0",
    "gn:asciiname":"Gerausa",
    "gn:country_code":"RO",
    "gn:dem":149,
    "gn:feature_class":"P",
    "gn:feature_code":"PPL",
    "gn:name":"Ger\u0103u\u0219a",
    "gn:population":661,
    "gn:timezone":"Europe/Bucharest",
    "iso:country":"RO",
    "wof:name":"Gerausa",
    "wof:placetype":"locality",
    "wof:population":661
},
  "geometry": {"coordinates":[22.94038,47.6083],"type":"Point"}
}