{
  "type": "Feature",
  "properties": {
    "gn:admin1_code":"01",
    "gn:admin2_code":"2577.0",
    "gn:asciiname":"Plai",
    "gn:country_code":"RO",
    "gn:dem":1038,
    "gn:feature_class":"P",
    "gn:feature_code":"PPL",
    "gn:name":"Plai",
    "gn:population":75,
    "gn:timezone":"Europe/Bucharest",
    "iso:country":"RO",
    "wof:name":"Plai",
    "wof:placetype":"locality",
    "wof:population":75
},
  "geometry": {"coordinates":[22.77406,46.39842],"type":"Point"}
}