{
  "type": "Feature",
  "properties": {
    "gn:admin1_code":"01",
    "gn:admin2_code":"2577.0",
    "gn:asciiname":"Plai",
    "gn:country_code":"RO",
    "gn:dem":1038,
    "gn:feature_class":"P",
    "gn:feature_code":"PPL",
    "gn:name":"Plai",
    "gn:population":75,
    "gn:timezone":"Europe/Bucharest",
    "iso:country":"RO",
    "name:ceb_x_preferred":[
        "Plai"
    ],
    "name:deu_x_preferred":[
        "Plai"
    ],
    "name:hun_x_preferred":[
        "Plai"
    ],
    "name:ron_x_preferred":[
        "Plai"
    ],
    "name:srp_x_preferred":[
        "\u041f\u043b\u0430\u0458"
    ],
    "wof:name":"Plai",
    "wof:placetype":"locality",
    "wof:population":75
},
  "geometry": {"coordinates":[22.77406,46.39842],"type":"Point"}
}