{
  "type": "Feature",
  "properties": {
    "gn:admin1_code":"39",
    "gn:admin2_code":"169681.0",
    "gn:asciiname":"Stanculesti",
    "gn:cc2":"RO",
    "gn:country_code":"RO",
    "gn:dem":282,
    "gn:feature_class":"P",
    "gn:feature_code":"PPL",
    "gn:name":"St\u00e2ncule\u015fti",
    "gn:population":0,
    "gn:timezone":"Europe/Bucharest",
    "iso:country":"RO",
    "name:und_x_variant":[
        "St\u00e2ncule\u015fti",
        "St\u00eencule\u015fti"
    ],
    "wof:name":"Stanculesti",
    "wof:placetype":"locality"
},
  "geometry": {"coordinates":[23.96667,44.78333],"type":"Point"}
}