{
  "type": "Feature",
  "properties": {
    "gn:admin1_code":"01",
    "gn:admin2_code":"3039.0",
    "gn:asciiname":"Ratitis",
    "gn:country_code":"RO",
    "gn:dem":701,
    "gn:feature_class":"P",
    "gn:feature_code":"PPL",
    "gn:name":"R\u0103titi\u0219",
    "gn:population":120,
    "gn:timezone":"Europe/Bucharest",
    "iso:country":"RO",
    "wof:name":"Ratitis",
    "wof:placetype":"locality",
    "wof:population":120
},
  "geometry": {"coordinates":[23.09124,46.40632],"type":"Point"}
}