{
  "type": "Feature",
  "properties": {
    "gn:country":"RO",
    "gn:fcode":"PPLA2",
    "gn:population":2862,
    "iso:country":"RO",
    "name:cat_x_preferred":[
        "B\u0103ile Govora"
    ],
    "name:ceb_x_preferred":[
        "B\u0103ile Govora"
    ],
    "name:dan_x_preferred":[
        "B\u0103ile Govora"
    ],
    "name:deu_x_preferred":[
        "B\u0103ile Govora"
    ],
    "name:eng_x_preferred":[
        "B\u0103ile Govora"
    ],
    "name:epo_x_preferred":[
        "B\u0103ile Govora"
    ],
    "name:est_x_preferred":[
        "B\u0103ile Govora"
    ],
    "name:fas_x_preferred":[
        "\u0628\u06cc\u0644\u0647 \u06af\u0648\u0648\u0631\u0627"
    ],
    "name:fra_x_preferred":[
        "B\u0103ile Govora"
    ],
    "name:gle_x_preferred":[
        "B\u0103ile Govora"
    ],
    "name:hun_x_preferred":[
        "B\u0103ile Govora"
    ],
    "name:hye_x_preferred":[
        "\u0532\u0565\u0575\u056c\u0565 \u0533\u0578\u057e\u0578\u0580\u0561"
    ],
    "name:ind_x_preferred":[
        "B\u0103ile Govora"
    ],
    "name:ita_x_preferred":[
        "B\u0103ile Govora"
    ],
    "name:min_x_preferred":[
        "B\u0103ile Govora"
    ],
    "name:msa_x_preferred":[
        "B\u0103ile Govora"
    ],
    "name:nld_x_preferred":[
        "B\u0103ile Govora"
    ],
    "name:pol_x_preferred":[
        "B\u0103ile Govora"
    ],
    "name:por_x_preferred":[
        "B\u0103ile Govora"
    ],
    "name:ron_x_preferred":[
        "B\u0103ile Govora"
    ],
    "name:rus_x_preferred":[
        "\u0411\u044d\u0438\u043b\u0435-\u0413\u043e\u0432\u043e\u0440\u0430"
    ],
    "name:spa_x_preferred":[
        "B\u0103ile Govora"
    ],
    "name:srp_x_preferred":[
        "\u041e\u043f\u0448\u0442\u0438\u043d\u0430 \u0411\u0430\u0458\u0438\u043b\u0435 \u0413\u043e\u0432\u043e\u0440\u0430"
    ],
    "name:tgk_x_preferred":[
        "\u0411\u044d\u0438\u043b\u0435-\u0413\u043e\u0432\u043e\u0440\u0430"
    ],
    "name:ukr_x_preferred":[
        "\u0411\u0435\u0457\u043b\u0435-\u0413\u043e\u0432\u043e\u0440\u0430"
    ],
    "name:vie_x_preferred":[
        "Baile Govora"
    ],
    "name:zho_x_preferred":[
        "\u4f2f\u4f0a\u840a\u6208\u6c83\u62c9"
    ],
    "qs_pg:aaroncc":"RO",
    "qs_pg:gn_country":"RO",
    "qs_pg:gn_fcode":"PPLA2",
    "qs_pg:gn_pop":2862,
    "qs_pg:name":"B\u0103ile Govora",
    "qs_pg:name_adm0":"Rom\u00e2nia",
    "qs_pg:name_adm1":"Valcea",
    "qs_pg:photos_9k":1,
    "qs_pg:photos_9r":2,
    "qs_pg:photos_all":27,
    "qs_pg:photos_sr":0,
    "qs_pg:pop_sr":4,
    "qs_pg:qs_pg_placetype":"locality",
    "qs_pg:qs_pg_placetype_gp":"Town",
    "qs_pg:woe_adm0":23424933,
    "woe:adm0_id":23424933,
    "woe:name_adm0":"Rom\u00e2nia",
    "woe:name_adm1":"Valcea",
    "woe:placetype":"Town",
    "wof:lang_x_official":[
        "ron"
    ],
    "wof:lang_x_spoken":[
        "ron"
    ],
    "wof:name":"B\u0103ile Govora",
    "wof:placetype":"locality",
    "wof:population":2862
},
  "geometry": {"coordinates":[24.18333,45.08333],"type":"Point"}
}