{
  "type": "Feature",
  "properties": {
    "gn:admin1_code":"33",
    "gn:admin2_code":"145220",
    "gn:asciiname":"Brosteni",
    "gn:country_code":"RO",
    "gn:dem":312,
    "gn:feature_class":"P",
    "gn:feature_code":"PPL",
    "gn:name":"Bro\u0219teni",
    "gn:population":425,
    "gn:timezone":"Europe/Bucharest",
    "iso:country":"RO",
    "wof:name":"Brosteni",
    "wof:placetype":"locality",
    "wof:population":425
},
  "geometry": {"coordinates":[23.95421,46.03158],"type":"Point"}
}