{
  "type": "Feature",
  "properties": {
    "gn:admin1_code":"04",
    "gn:admin2_code":"25291.0",
    "gn:asciiname":"Floresti",
    "gn:country_code":"RO",
    "gn:dem":289,
    "gn:feature_class":"P",
    "gn:feature_code":"PPL",
    "gn:name":"Flore\u0219ti",
    "gn:population":613,
    "gn:timezone":"Europe/Bucharest",
    "iso:country":"RO",
    "wof:name":"Floresti",
    "wof:placetype":"locality",
    "wof:population":613
},
  "geometry": {"coordinates":[26.66654,46.52426],"type":"Point"}
}