{
  "type": "Feature",
  "properties": {
    "gn:admin1_code":"03",
    "gn:admin2_code":"14085.0",
    "gn:asciiname":"Cotmenita",
    "gn:country_code":"RO",
    "gn:dem":359,
    "gn:feature_class":"P",
    "gn:feature_code":"PPL",
    "gn:name":"Cotmeni\u021ba",
    "gn:population":335,
    "gn:timezone":"Europe/Bucharest",
    "iso:country":"RO",
    "wof:name":"Cotmenita",
    "wof:placetype":"locality",
    "wof:population":335
},
  "geometry": {"coordinates":[24.71172,44.89779],"type":"Point"}
}