{
  "type": "Feature",
  "properties": {
    "gn:admin1_code":"02",
    "gn:admin2_code":"11478.0",
    "gn:asciiname":"Ranusa",
    "gn:country_code":"RO",
    "gn:dem":249,
    "gn:feature_class":"P",
    "gn:feature_code":"PPL",
    "gn:name":"R\u0103nu\u0219a",
    "gn:population":327,
    "gn:timezone":"Europe/Bucharest",
    "iso:country":"RO",
    "name:ron_x_preferred":[
        "R\u0103nu\u0219a"
    ],
    "name:und_x_variant":[
        "Kisr\u00f3na",
        "Ravna"
    ],
    "wof:name":"Ranusa",
    "wof:placetype":"locality",
    "wof:population":327
},
  "geometry": {"coordinates":[22.25463,46.43096],"type":"Point"}
}