{
  "type": "Feature",
  "properties": {
    "gn:admin1_code":"03",
    "gn:admin2_code":"18411.0",
    "gn:asciiname":"Deagu de Sus",
    "gn:cc2":"RO",
    "gn:country_code":"RO",
    "gn:dem":184,
    "gn:feature_class":"P",
    "gn:feature_code":"PPL",
    "gn:name":"Deagu de Sus",
    "gn:population":628,
    "gn:timezone":"Europe/Bucharest",
    "iso:country":"RO",
    "name:und_x_variant":[
        "Deagurile-de-Sus",
        "Deagul-de-Sus",
        "Deagu de Sus"
    ],
    "wof:name":"Deagu de Sus",
    "wof:placetype":"locality",
    "wof:population":628
},
  "geometry": {"coordinates":[25.00627,44.56427],"type":"Point"}
}