{
  "type": "Feature",
  "properties": {
    "gn:country":"RO",
    "gn:fcode":"PPL",
    "gn:population":0,
    "iso:country":"RO",
    "name:ace_x_preferred":[
        "Olteni\u0163a"
    ],
    "name:azb_x_preferred":[
        "\u0627\u0648\u0644\u062a\u0646\u06cc\u062a\u0633\u0627"
    ],
    "name:bel_x_preferred":[
        "\u0410\u043b\u0442\u044d\u043d\u0456\u0446\u0430"
    ],
    "name:bul_x_preferred":[
        "\u041e\u043b\u0442\u0435\u043d\u0438\u0446\u0430"
    ],
    "name:ceb_x_preferred":[
        "Municipiul Olteni\u021ba"
    ],
    "name:deu_x_preferred":[
        "Olteni\u021ba"
    ],
    "name:fas_x_preferred":[
        "\u0627\u0648\u0644\u062a\u0646\u06cc\u062a\u0633\u0627"
    ],
    "name:fra_x_preferred":[
        "Olteni\u021ba"
    ],
    "name:heb_x_preferred":[
        "\u05d0\u05d5\u05dc\u05d8\u05e0\u05d9\u05e6\u05d4"
    ],
    "name:hun_x_preferred":[
        "Olteni\u021ba"
    ],
    "name:ind_x_preferred":[
        "Olteni\u0163a"
    ],
    "name:ita_x_preferred":[
        "Olteni\u021ba"
    ],
    "name:jpn_x_preferred":[
        "\u30aa\u30eb\u30c6\u30cb\u30c4\u30a1"
    ],
    "name:kor_x_preferred":[
        "\uc62c\ud14c\ub2c8\ucc28"
    ],
    "name:lat_x_preferred":[
        "Constantiana Daphne"
    ],
    "name:lit_x_preferred":[
        "Oltenica"
    ],
    "name:min_x_preferred":[
        "Olteni\u021ba"
    ],
    "name:msa_x_preferred":[
        "Olteni\u0163a"
    ],
    "name:nld_x_preferred":[
        "Olteni\u021ba"
    ],
    "name:pol_x_preferred":[
        "Olteni\u021ba"
    ],
    "name:por_x_preferred":[
        "Olteni\u021ba"
    ],
    "name:ron_x_preferred":[
        "Olteni\u021ba"
    ],
    "name:rus_x_preferred":[
        "\u041e\u043b\u0442\u0435\u043d\u0438\u0446\u0430"
    ],
    "name:spa_x_preferred":[
        "Olteni\u021ba"
    ],
    "name:srp_x_preferred":[
        "\u041e\u043f\u0448\u0442\u0438\u043d\u0430 \u041e\u043b\u0442\u0435\u043d\u0438\u0446\u0430"
    ],
    "name:tgk_x_preferred":[
        "\u041e\u043b\u0442\u0435\u043d\u0438\u0442\u0441\u0430"
    ],
    "name:ukr_x_preferred":[
        "\u041e\u043b\u0442\u0435\u043d\u0456\u0446\u0430"
    ],
    "name:vie_x_preferred":[
        "Oltenita"
    ],
    "name:zho_x_preferred":[
        "\u5965\u5c14\u6cf0\u5c3c\u5bdf"
    ],
    "qs_pg:aaroncc":"RO",
    "qs_pg:gn_country":"RO",
    "qs_pg:gn_fcode":"PPL",
    "qs_pg:gn_pop":0,
    "qs_pg:name":"Olteni\u021ba",
    "qs_pg:name_adm0":"Rom\u00e2nia",
    "qs_pg:name_adm1":"Calarasi",
    "qs_pg:photos":93,
    "qs_pg:photos_1k":19,
    "qs_pg:photos_9k":1,
    "qs_pg:photos_9r":3,
    "qs_pg:photos_all":116,
    "qs_pg:photos_sr":3,
    "qs_pg:pop_sr":0,
    "qs_pg:qs_pg_placetype":"locality",
    "qs_pg:qs_pg_placetype_gp":"Town",
    "qs_pg:woe_adm0":23424933,
    "woe:adm0_id":23424933,
    "woe:name_adm0":"Rom\u00e2nia",
    "woe:name_adm1":"Calarasi",
    "woe:placetype":"Town",
    "wof:name":"Olteni\u021ba",
    "wof:placetype":"locality",
    "wof:population":1022
},
  "geometry": {"coordinates":[25.94667,44.39667],"type":"Point"}
}