{
  "type": "Feature",
  "properties": {
    "gn:admin1_code":"16",
    "gn:admin2_code":"179926.0",
    "gn:asciiname":"Draghineasa",
    "gn:country_code":"RO",
    "gn:dem":174,
    "gn:feature_class":"P",
    "gn:feature_code":"PPL",
    "gn:name":"Dr\u0103ghineasa",
    "gn:population":0,
    "gn:timezone":"Europe/Bucharest",
    "iso:country":"RO",
    "name:und_x_variant":[
        "Dr\u0103ghineasca",
        "Dr\u0103ghineasa"
    ],
    "wof:lang_x_official":[
        "ron"
    ],
    "wof:lang_x_spoken":[
        "ron"
    ],
    "wof:name":"Draghineasa",
    "wof:placetype":"locality"
},
  "geometry": {"coordinates":[25.28333,44.58333],"type":"Point"}
}