{
  "type": "Feature",
  "properties": {
    "gn:admin1_code":"11",
    "gn:admin2_code":"49769.0",
    "gn:asciiname":"Draghesti",
    "gn:country_code":"RO",
    "gn:dem":240,
    "gn:feature_class":"P",
    "gn:feature_code":"PPL",
    "gn:name":"Dr\u0103ghe\u015fti",
    "gn:population":0,
    "gn:timezone":"Europe/Bucharest",
    "iso:country":"RO",
    "name:und_x_variant":[
        "Dr\u0103ghie\u015fti",
        "Dr\u0103ghe\u015fti"
    ],
    "wof:lang_x_official":[
        "ron"
    ],
    "wof:lang_x_spoken":[
        "ron"
    ],
    "wof:name":"Draghesti",
    "wof:placetype":"locality"
},
  "geometry": {"coordinates":[26.98333,45.43333],"type":"Point"}
}