{
  "type": "Feature",
  "properties": {
    "gn:admin1_code":"05",
    "gn:admin2_code":"31976.0",
    "gn:asciiname":"Topa de Cris",
    "gn:country_code":"RO",
    "gn:dem":278,
    "gn:feature_class":"P",
    "gn:feature_code":"PPL",
    "gn:name":"Topa de Cri\u0219",
    "gn:population":513,
    "gn:timezone":"Europe/Bucharest",
    "iso:country":"RO",
    "wof:name":"Topa de Cris",
    "wof:placetype":"locality",
    "wof:population":513
},
  "geometry": {"coordinates":[22.53342,47.00211],"type":"Point"}
}