{
  "type": "Feature",
  "properties": {
    "gn:admin1_code":"14",
    "gn:admin2_code":"60570.0",
    "gn:asciiname":"Statiunea Zoologica Marina Agigea",
    "gn:country_code":"RO",
    "gn:dem":12,
    "gn:feature_class":"P",
    "gn:feature_code":"PPL",
    "gn:name":"Sta\u021biunea Zoologic\u0103 Marin\u0103 Agigea",
    "gn:population":84,
    "gn:timezone":"Europe/Bucharest",
    "iso:country":"RO",
    "wof:name":"Statiunea Zoologica Marina Agigea",
    "wof:placetype":"locality",
    "wof:population":84
},
  "geometry": {"coordinates":[28.64201,44.08916],"type":"Point"}
}