{
  "type": "Feature",
  "properties": {
    "gn:admin1_code":"01",
    "gn:admin2_code":"7197.0",
    "gn:asciiname":"Lespezea",
    "gn:country_code":"RO",
    "gn:dem":1020,
    "gn:feature_class":"P",
    "gn:feature_code":"PPL",
    "gn:name":"Lespezea",
    "gn:population":71,
    "gn:timezone":"Europe/Bucharest",
    "iso:country":"RO",
    "wof:name":"Lespezea",
    "wof:placetype":"locality",
    "wof:population":71
},
  "geometry": {"coordinates":[22.90094,46.47592],"type":"Point"}
}