{
  "type": "Feature",
  "properties": {
    "gn:admin1_code":"39",
    "gn:admin2_code":"171325.0",
    "gn:asciiname":"Vulpuesti",
    "gn:cc2":"RO",
    "gn:country_code":"RO",
    "gn:dem":249,
    "gn:feature_class":"P",
    "gn:feature_code":"PPL",
    "gn:name":"Vulpue\u0219ti",
    "gn:population":411,
    "gn:timezone":"Europe/Bucharest",
    "iso:country":"RO",
    "name:und_x_variant":[
        "Vulpe\u015fti",
        "Vulpue\u015fti"
    ],
    "wof:name":"Vulpuesti",
    "wof:placetype":"locality",
    "wof:population":411
},
  "geometry": {"coordinates":[24.22685,45.06519],"type":"Point"}
}