{
  "type": "Feature",
  "properties": {
    "gn:admin1_code":"28",
    "gn:admin2_code":"124723",
    "gn:asciiname":"Branisteni",
    "gn:country_code":"RO",
    "gn:dem":280,
    "gn:feature_class":"P",
    "gn:feature_code":"PPL",
    "gn:name":"Br\u0103ni\u015fteni",
    "gn:population":0,
    "gn:timezone":"Europe/Bucharest",
    "iso:country":"RO",
    "wof:lang_x_official":[
        "ron"
    ],
    "wof:lang_x_spoken":[
        "ron"
    ],
    "wof:name":"Branisteni",
    "wof:placetype":"locality"
},
  "geometry": {"coordinates":[26.78333,46.91667],"type":"Point"}
}