{
  "type": "Feature",
  "properties": {
    "gn:admin1_code":"27",
    "gn:admin2_code":"118511.0",
    "gn:asciiname":"Vadas",
    "gn:cc2":"RO",
    "gn:country_code":"RO",
    "gn:dem":387,
    "gn:feature_class":"P",
    "gn:feature_code":"PPL",
    "gn:name":"V\u0103da\u0219",
    "gn:population":389,
    "gn:timezone":"Europe/Bucharest",
    "iso:country":"RO",
    "name:hun_x_preferred":[
        "Vadasd"
    ],
    "name:und_x_variant":[
        "V\u0103da\u015f"
    ],
    "wof:name":"Vadas",
    "wof:placetype":"locality",
    "wof:population":389
},
  "geometry": {"coordinates":[24.81939,46.4559],"type":"Point"}
}