{
  "type": "Feature",
  "properties": {
    "gn:admin1_code":"06",
    "gn:admin2_code":"33989.0",
    "gn:asciiname":"Floresti",
    "gn:country_code":"RO",
    "gn:dem":279,
    "gn:feature_class":"P",
    "gn:feature_code":"PPL",
    "gn:name":"Flore\u0219ti",
    "gn:population":409,
    "gn:timezone":"Europe/Bucharest",
    "iso:country":"RO",
    "wof:name":"Floresti",
    "wof:placetype":"locality",
    "wof:population":409
},
  "geometry": {"coordinates":[24.27962,47.2384],"type":"Point"}
}