{
  "type": "Feature",
  "properties": {
    "gn:admin1_code":"16",
    "gn:admin2_code":"66580.0",
    "gn:asciiname":"Craciunesti",
    "gn:country_code":"RO",
    "gn:dem":240,
    "gn:feature_class":"P",
    "gn:feature_code":"PPL",
    "gn:name":"Cr\u0103ciune\u0219ti",
    "gn:population":356,
    "gn:timezone":"Europe/Bucharest",
    "iso:country":"RO",
    "wof:name":"Craciunesti",
    "wof:placetype":"locality",
    "wof:population":356
},
  "geometry": {"coordinates":[25.34403,44.81139],"type":"Point"}
}