{
  "type": "Feature",
  "properties": {
    "gn:admin1_code":"16",
    "gn:admin2_code":"68253.0",
    "gn:asciiname":"Neajlovu",
    "gn:cc2":"RO",
    "gn:country_code":"RO",
    "gn:dem":188,
    "gn:feature_class":"P",
    "gn:feature_code":"PPL",
    "gn:name":"Neajlovu",
    "gn:population":544,
    "gn:timezone":"Europe/Bucharest",
    "iso:country":"RO",
    "name:ceb_x_preferred":[
        "Neajlovu"
    ],
    "name:deu_x_preferred":[
        "Neajlovu"
    ],
    "name:ron_x_preferred":[
        "Neajlovu"
    ],
    "name:und_x_variant":[
        "Cacova",
        "Cocova",
        "Neajlovu"
    ],
    "wof:name":"Neajlovu",
    "wof:placetype":"locality",
    "wof:population":544
},
  "geometry": {"coordinates":[25.26635,44.65928],"type":"Point"}
}