{
  "type": "Feature",
  "properties": {
    "gn:admin1_code":"07",
    "gn:admin2_code":"39612.0",
    "gn:asciiname":"Saucenita",
    "gn:country_code":"RO",
    "gn:dem":203,
    "gn:feature_class":"P",
    "gn:feature_code":"PPL",
    "gn:name":"Sauceni\u021ba",
    "gn:population":932,
    "gn:timezone":"Europe/Bucharest",
    "iso:country":"RO",
    "wof:name":"Saucenita",
    "wof:placetype":"locality",
    "wof:population":932
},
  "geometry": {"coordinates":[26.39724,47.89378],"type":"Point"}
}