{
  "type": "Feature",
  "properties": {
    "gn:admin1_code":"26",
    "gn:admin2_code":"111480.0",
    "gn:asciiname":"Securicea",
    "gn:country_code":"RO",
    "gn:dem":107,
    "gn:feature_class":"P",
    "gn:feature_code":"PPL",
    "gn:name":"Securicea",
    "gn:population":0,
    "gn:timezone":"Europe/Bucharest",
    "iso:country":"RO",
    "wof:name":"Securicea",
    "wof:placetype":"locality"
},
  "geometry": {"coordinates":[22.71806,44.47194],"type":"Point"}
}