{
  "type": "Feature",
  "properties": {
    "gn:admin1_code":"07",
    "gn:admin2_code":"38161.0",
    "gn:asciiname":"Vladeni",
    "gn:country_code":"RO",
    "gn:dem":341,
    "gn:feature_class":"P",
    "gn:feature_code":"PPL",
    "gn:name":"Vl\u0103deni",
    "gn:population":0,
    "gn:timezone":"Europe/Bucharest",
    "iso:country":"RO",
    "wof:name":"Vladeni",
    "wof:placetype":"locality"
},
  "geometry": {"coordinates":[26.16667,47.98333],"type":"Point"}
}