{
  "type": "Feature",
  "properties": {
    "gn:admin1_code":"13",
    "gn:admin2_code":"56844.0",
    "gn:asciiname":"Dosu Napului",
    "gn:cc2":"RO",
    "gn:country_code":"RO",
    "gn:dem":337,
    "gn:feature_class":"P",
    "gn:feature_code":"PPL",
    "gn:name":"Dosu Napului",
    "gn:population":159,
    "gn:timezone":"Europe/Bucharest",
    "iso:country":"RO",
    "name:und_x_variant":[
        "Dosul Napului",
        "Dosu Napului"
    ],
    "wof:name":"Dosu Napului",
    "wof:placetype":"locality",
    "wof:population":159
},
  "geometry": {"coordinates":[23.9092,46.66441],"type":"Point"}
}