{
  "type": "Feature",
  "properties": {
    "gn:admin1_code":"13",
    "gn:admin2_code":"56461.0",
    "gn:asciiname":"Valeni",
    "gn:cc2":"RO",
    "gn:country_code":"RO",
    "gn:dem":689,
    "gn:feature_class":"P",
    "gn:feature_code":"PPL",
    "gn:name":"V\u0103leni",
    "gn:population":455,
    "gn:timezone":"Europe/Bucharest",
    "iso:country":"RO",
    "name:und_x_variant":[
        "V\u0103lc\u0103u Unguresc",
        "V\u0103leni"
    ],
    "wof:name":"Valeni",
    "wof:placetype":"locality",
    "wof:population":455
},
  "geometry": {"coordinates":[23.03426,46.78153],"type":"Point"}
}