{
  "type": "Feature",
  "properties": {
    "gn:admin1_code":"38",
    "gn:admin2_code":"163486.0",
    "gn:asciiname":"Doagele",
    "gn:cc2":"RO",
    "gn:country_code":"RO",
    "gn:dem":198,
    "gn:feature_class":"P",
    "gn:feature_code":"PPL",
    "gn:name":"Doagele",
    "gn:population":918,
    "gn:timezone":"Europe/Bucharest",
    "iso:country":"RO",
    "name:und_x_variant":[
        "Doagele-Vasiliu",
        "Doaga Vasiliu",
        "Doagele"
    ],
    "wof:name":"Doagele",
    "wof:placetype":"locality",
    "wof:population":918
},
  "geometry": {"coordinates":[27.33246,46.67069],"type":"Point"}
}