{
  "type": "Feature",
  "properties": {
    "gn:admin1_code":"12",
    "gn:admin2_code":"51118",
    "gn:asciiname":"Bradisoru de Jos",
    "gn:cc2":"RO",
    "gn:country_code":"RO",
    "gn:dem":170,
    "gn:feature_class":"P",
    "gn:feature_code":"PPL",
    "gn:name":"Br\u0103di\u0219oru de Jos",
    "gn:population":654,
    "gn:timezone":"Europe/Bucharest",
    "iso:country":"RO",
    "name:und_x_variant":[
        "Maidan",
        "Majdan",
        "Br\u0103di\u015foru de Jos"
    ],
    "wof:name":"Bradisoru de Jos",
    "wof:placetype":"locality",
    "wof:population":654
},
  "geometry": {"coordinates":[21.71466,45.07858],"type":"Point"}
}