{
  "type": "Feature",
  "properties": {
    "gn:admin1_code":"20",
    "gn:admin2_code":"84754.0",
    "gn:asciiname":"Comiat",
    "gn:cc2":"RO",
    "gn:country_code":"RO",
    "gn:dem":966,
    "gn:feature_class":"P",
    "gn:feature_code":"PPL",
    "gn:name":"Comiat",
    "gn:population":386,
    "gn:timezone":"Europe/Bucharest",
    "iso:country":"RO",
    "name:und_x_variant":[
        "Komj\u00e0t Pataka",
        "Comiat"
    ],
    "wof:name":"Comiat",
    "wof:placetype":"locality",
    "wof:population":386
},
  "geometry": {"coordinates":[25.94339,46.49296],"type":"Point"}
}