{
  "type": "Feature",
  "properties": {
    "gn:admin1_code":"06",
    "gn:admin2_code":"33435.0",
    "gn:asciiname":"Tigau",
    "gn:cc2":"RO",
    "gn:country_code":"RO",
    "gn:dem":364,
    "gn:feature_class":"P",
    "gn:feature_code":"PPL",
    "gn:name":"\u021aig\u0103u",
    "gn:population":482,
    "gn:timezone":"Europe/Bucharest",
    "iso:country":"RO",
    "name:und_x_variant":[
        "\u0162ig\u0103ul",
        "\u0162ig\u0103u"
    ],
    "wof:name":"Tigau",
    "wof:placetype":"locality",
    "wof:population":482
},
  "geometry": {"coordinates":[24.33354,47.07046],"type":"Point"}
}