{
  "type": "Feature",
  "properties": {
    "iso:country":"RO",
    "name:eng_x_preferred":[
        "Mehala"
    ],
    "name:ron_x_preferred":[
        "Mehala"
    ],
    "wof:name":"Mehala",
    "wof:placetype":"neighbourhood"
},
  "geometry": {"coordinates":[21.20396261062917,45.76526378091111],"type":"Point"}
}