{
  "type": "Feature",
  "properties": {
    "iso:country":"RO",
    "name:eng_x_preferred":[
        "Mehala"
    ],
    "name:ron_x_preferred":[
        "Mehala"
    ],
    "wof:lang_x_official":[
        "ron"
    ],
    "wof:lang_x_spoken":[
        "ron"
    ],
    "wof:name":"Mehala",
    "wof:placetype":"neighbourhood"
},
  "geometry": {"coordinates":[21.203963,45.765264],"type":"Point"}
}