{
  "type": "Feature",
  "properties": {
    "gn:admin1_code":"23",
    "gn:admin2_code":"100004.0",
    "gn:asciiname":"Frasuleni",
    "gn:country_code":"RO",
    "gn:dem":43,
    "gn:feature_class":"P",
    "gn:feature_code":"PPL",
    "gn:name":"Fr\u0103suleni",
    "gn:population":263,
    "gn:timezone":"Europe/Bucharest",
    "iso:country":"RO",
    "wof:name":"Frasuleni",
    "wof:placetype":"locality",
    "wof:population":263
},
  "geometry": {"coordinates":[27.5912,47.33562],"type":"Point"}
}