{
  "type": "Feature",
  "properties": {
    "gn:admin1_code":"29",
    "gn:admin2_code":"126022.0",
    "gn:asciiname":"Margheni",
    "gn:country_code":"RO",
    "gn:dem":98,
    "gn:feature_class":"P",
    "gn:feature_code":"PPL",
    "gn:name":"M\u0103rgheni",
    "gn:population":868,
    "gn:timezone":"Europe/Bucharest",
    "iso:country":"RO",
    "wof:name":"Margheni",
    "wof:placetype":"locality",
    "wof:population":868
},
  "geometry": {"coordinates":[24.3521,44.33074000000001],"type":"Point"}
}