{
  "type": "Feature",
  "properties": {
    "gn:admin1_code":"40",
    "gn:admin2_code":"176212.0",
    "gn:asciiname":"Strajescu",
    "gn:cc2":"RO",
    "gn:country_code":"RO",
    "gn:dem":54,
    "gn:feature_class":"P",
    "gn:feature_code":"PPL",
    "gn:name":"Str\u0103jescu",
    "gn:population":294,
    "gn:timezone":"Europe/Bucharest",
    "iso:country":"RO",
    "name:und_x_variant":[
        "Strejescu",
        "Str\u0103jescu"
    ],
    "wof:name":"Strajescu",
    "wof:placetype":"locality",
    "wof:population":294
},
  "geometry": {"coordinates":[27.28779,45.81777],"type":"Point"}
}