{
  "type": "Feature",
  "properties": {
    "gn:gn_country":"RO",
    "gn:gn_fcode":"PPLA2",
    "gn:gn_pop":3374,
    "gn:population":3374,
    "iso:country":"RO",
    "name:eng_x_preferred":[
        "Scor\u021boasa"
    ],
    "name:fra_x_preferred":[
        "Scor\u021boasa"
    ],
    "name:ita_x_preferred":[
        "Scor\u021boasa"
    ],
    "name:nld_x_preferred":[
        "Scor\u021boasa"
    ],
    "name:ron_x_preferred":[
        "Scor\u021boasa"
    ],
    "name:ukr_x_preferred":[
        "\u0421\u043a\u043e\u0440\u0446\u043e\u0430\u0441\u0430"
    ],
    "qs_pg:aaroncc":"RO",
    "qs_pg:gn_country":"RO",
    "qs_pg:gn_fcode":"PPLA2",
    "qs_pg:gn_pop":3374,
    "qs_pg:name":"Scor\u0163oasa",
    "qs_pg:photos_9r":0,
    "qs_pg:photos_sr":0,
    "qs_pg:pop_sr":4,
    "qs_pg:qs_pg_placetype":"locality",
    "wof:name":"Scor\u0163oasa",
    "wof:placetype":"locality",
    "wof:population":3374
},
  "geometry": {"coordinates":[26.66116,45.36403],"type":"Point"}
}