{
  "type": "Feature",
  "properties": {
    "gn:admin1_code":"01",
    "gn:admin2_code":"4008",
    "gn:asciiname":"Bodresti",
    "gn:country_code":"RO",
    "gn:dem":897,
    "gn:feature_class":"P",
    "gn:feature_code":"PPL",
    "gn:name":"Bodre\u0219ti",
    "gn:population":57,
    "gn:timezone":"Europe/Bucharest",
    "iso:country":"RO",
    "wof:name":"Bodresti",
    "wof:placetype":"locality",
    "wof:population":57
},
  "geometry": {"coordinates":[22.97239,46.27345],"type":"Point"}
}