{
  "type": "Feature",
  "properties": {
    "gn:gn_country":"RO",
    "gn:gn_fcode":"PPLA2",
    "gn:gn_pop":2420,
    "gn:population":2420,
    "iso:country":"RO",
    "name:eng_x_preferred":[
        "D\u0103ne\u0219ti"
    ],
    "name:ita_x_preferred":[
        "D\u0103ne\u0219ti"
    ],
    "name:msa_x_preferred":[
        "D\u0103ne\u0219ti"
    ],
    "name:nld_x_preferred":[
        "D\u0103ne\u0219ti"
    ],
    "name:por_x_preferred":[
        "D\u0103ne\u0219ti"
    ],
    "name:ron_x_preferred":[
        "D\u0103ne\u0219ti"
    ],
    "name:ukr_x_preferred":[
        "\u0414\u0435\u043d\u0435\u0448\u0442\u044c"
    ],
    "name:vie_x_preferred":[
        "Danesti"
    ],
    "qs_pg:aaroncc":"RO",
    "qs_pg:gn_country":"RO",
    "qs_pg:gn_fcode":"PPLA2",
    "qs_pg:gn_pop":2420,
    "qs_pg:name":"D\u0103ne\u015fti",
    "qs_pg:photos_9r":0,
    "qs_pg:photos_sr":0,
    "qs_pg:pop_sr":4,
    "qs_pg:qs_pg_placetype":"locality",
    "wof:name":"D\u0103ne\u015fti",
    "wof:placetype":"locality",
    "wof:population":2420
},
  "geometry": {"coordinates":[27.66667,46.85],"type":"Point"}
}