{
  "type": "Feature",
  "properties": {
    "gn:admin1_code":"22",
    "gn:admin2_code":"94429.0",
    "gn:asciiname":"Victoria Marasesti",
    "gn:country_code":"RO",
    "gn:dem":30,
    "gn:feature_class":"P",
    "gn:feature_code":"PPL",
    "gn:name":"Victoria M\u0103r\u0103\u015fe\u015fti",
    "gn:population":0,
    "gn:timezone":"Europe/Bucharest",
    "iso:country":"RO",
    "wof:lang_x_official":[
        "ron"
    ],
    "wof:lang_x_spoken":[
        "ron"
    ],
    "wof:name":"Victoria Marasesti",
    "wof:placetype":"locality"
},
  "geometry": {"coordinates":[27.41667,44.73333],"type":"Point"}
}