{
  "type": "Feature",
  "properties": {
    "gn:admin1_code":"02",
    "gn:admin2_code":"12572.0",
    "gn:asciiname":"Lupesti",
    "gn:country_code":"RO",
    "gn:dem":231,
    "gn:feature_class":"P",
    "gn:feature_code":"PPL",
    "gn:name":"Lupe\u0219ti",
    "gn:population":365,
    "gn:timezone":"Europe/Bucharest",
    "iso:country":"RO",
    "name:ron_x_preferred":[
        "Lupe\u0219ti"
    ],
    "name:und_x_variant":[
        "Farkash\u00e1za",
        "Lupest"
    ],
    "wof:name":"Lupesti",
    "wof:placetype":"locality",
    "wof:population":365
},
  "geometry": {"coordinates":[22.21888,46.06938],"type":"Point"}
}