{
  "type": "Feature",
  "properties": {
    "gn:country":"RO",
    "gn:fcode":"PPLA2",
    "gn:population":1131,
    "iso:country":"RO",
    "name:fra_x_preferred":[
        "B\u00e2lv\u0103ne\u0219ti"
    ],
    "name:ita_x_preferred":[
        "B\u00e2lv\u0103ne\u015fti"
    ],
    "name:nld_x_preferred":[
        "B\u00e2lv\u0103ne\u0219ti"
    ],
    "name:por_x_preferred":[
        "B\u00e2lv\u0103ne\u015fti"
    ],
    "name:ron_x_preferred":[
        "B\u00e2lv\u0103ne\u0219ti"
    ],
    "name:ukr_x_preferred":[
        "\u0411\u0438\u043b\u0432\u0435\u043d\u0435\u0448\u0442\u044c"
    ],
    "name:und_x_variant":[
        "B\u00eelv\u0103ne\u015fti"
    ],
    "name:vol_x_preferred":[
        "B\u00e2lv\u0103ne\u015fti"
    ],
    "qs_pg:aaroncc":"RO",
    "qs_pg:gn_country":"RO",
    "qs_pg:gn_fcode":"PPLA2",
    "qs_pg:gn_pop":1131,
    "qs_pg:name":"B\u00e2lv\u0103ne\u015fti",
    "qs_pg:photos_9r":0,
    "qs_pg:photos_sr":0,
    "qs_pg:pop_sr":3,
    "qs_pg:qs_pg_placetype":"locality",
    "wof:name":"B\u00e2lv\u0103ne\u015fti",
    "wof:placetype":"locality",
    "wof:population":1131
},
  "geometry": {"coordinates":[22.68028,44.7975],"type":"Point"}
}