{
  "type": "Feature",
  "properties": {
    "gn:admin1_code":"14",
    "gn:admin2_code":"61069.0",
    "gn:asciiname":"Faurei",
    "gn:cc2":"RO",
    "gn:country_code":"RO",
    "gn:dem":96,
    "gn:feature_class":"P",
    "gn:feature_code":"PPL",
    "gn:name":"F\u0103urei",
    "gn:population":878,
    "gn:timezone":"Europe/Bucharest",
    "iso:country":"RO",
    "name:und_x_variant":[
        "Calaicea",
        "Caluici",
        "F\u0103urei"
    ],
    "wof:name":"Faurei",
    "wof:placetype":"locality",
    "wof:population":878
},
  "geometry": {"coordinates":[27.69806,44.04092],"type":"Point"}
}