{
  "type": "Feature",
  "properties": {
    "gn:admin1_code":"03",
    "gn:admin2_code":"14940.0",
    "gn:asciiname":"Tomsanca",
    "gn:country_code":"RO",
    "gn:dem":231,
    "gn:feature_class":"P",
    "gn:feature_code":"PPL",
    "gn:name":"Tom\u0219anca",
    "gn:population":422,
    "gn:timezone":"Europe/Bucharest",
    "iso:country":"RO",
    "wof:name":"Tomsanca",
    "wof:placetype":"locality",
    "wof:population":422
},
  "geometry": {"coordinates":[24.94017,44.62251],"type":"Point"}
}