{
  "type": "Feature",
  "properties": {
    "gn:admin1_code":"26",
    "gn:admin2_code":"110296",
    "gn:asciiname":"Bala de Sus",
    "gn:country_code":"RO",
    "gn:dem":283,
    "gn:feature_class":"P",
    "gn:feature_code":"PPL",
    "gn:name":"Bala de Sus",
    "gn:population":660,
    "gn:timezone":"Europe/Bucharest",
    "iso:country":"RO",
    "wof:name":"Bala de Sus",
    "wof:placetype":"locality",
    "wof:population":660
},
  "geometry": {"coordinates":[22.81346,44.89834000000001],"type":"Point"}
}