{
  "type": "Feature",
  "properties": {
    "gn:admin1_code":"02",
    "gn:admin2_code":"10943.0",
    "gn:asciiname":"Iosasel",
    "gn:country_code":"RO",
    "gn:dem":278,
    "gn:feature_class":"P",
    "gn:feature_code":"PPL",
    "gn:name":"Ios\u0103\u015fel",
    "gn:population":0,
    "gn:timezone":"Europe/Bucharest",
    "iso:country":"RO",
    "wof:name":"Iosasel",
    "wof:placetype":"locality"
},
  "geometry": {"coordinates":[22.35,46.28333],"type":"Point"}
}