{
  "type": "Feature",
  "properties": {
    "gn:admin1_code":"21",
    "gn:admin2_code":"88644",
    "gn:asciiname":"Bretea Streiului",
    "gn:country_code":"RO",
    "gn:dem":262,
    "gn:feature_class":"P",
    "gn:feature_code":"PPL",
    "gn:name":"Bretea Streiului",
    "gn:population":282,
    "gn:timezone":"Europe/Bucharest",
    "iso:country":"RO",
    "wof:name":"Bretea Streiului",
    "wof:placetype":"locality",
    "wof:population":282
},
  "geometry": {"coordinates":[23.00369,45.66031],"type":"Point"}
}