{
  "type": "Feature",
  "properties": {
    "gn:admin1_code":"23",
    "gn:admin2_code":"96815.0",
    "gn:asciiname":"Leahu-Nacu",
    "gn:cc2":"RO",
    "gn:country_code":"RO",
    "gn:dem":86,
    "gn:feature_class":"P",
    "gn:feature_code":"PPL",
    "gn:name":"Leahu-Nacu",
    "gn:population":99,
    "gn:timezone":"Europe/Bucharest",
    "iso:country":"RO",
    "name:und_x_variant":[
        "Nacu",
        "Leahu-Nacu"
    ],
    "wof:name":"Leahu-Nacu",
    "wof:placetype":"locality",
    "wof:population":99
},
  "geometry": {"coordinates":[26.96011,47.49341],"type":"Point"}
}