{
  "type": "Feature",
  "properties": {
    "gn:admin1_code":"40",
    "gn:admin2_code":"177726.0",
    "gn:asciiname":"Jiliste",
    "gn:cc2":"RO",
    "gn:country_code":"RO",
    "gn:dem":42,
    "gn:feature_class":"P",
    "gn:feature_code":"PPL",
    "gn:name":"Jili\u0219te",
    "gn:population":699,
    "gn:timezone":"Europe/Bucharest",
    "iso:country":"RO",
    "name:und_x_variant":[
        "Zili\u015ftea",
        "Jilistea",
        "Jili\u015fte"
    ],
    "wof:name":"Jiliste",
    "wof:placetype":"locality",
    "wof:population":699
},
  "geometry": {"coordinates":[27.24156,45.60094],"type":"Point"}
}