{
  "type": "Feature",
  "properties": {
    "gn:admin1_code":"19",
    "gn:admin2_code":"82680",
    "gn:asciiname":"Arpadia",
    "gn:country_code":"RO",
    "gn:dem":188,
    "gn:feature_class":"P",
    "gn:feature_code":"PPL",
    "gn:name":"Arpadia",
    "gn:population":93,
    "gn:timezone":"Europe/Bucharest",
    "iso:country":"RO",
    "wof:name":"Arpadia",
    "wof:placetype":"locality",
    "wof:population":93
},
  "geometry": {"coordinates":[23.57604,44.63882],"type":"Point"}
}