{
  "type": "Feature",
  "properties": {
    "gn:admin1_code":"39",
    "gn:admin2_code":"171325.0",
    "gn:asciiname":"Stuparei",
    "gn:cc2":"RO",
    "gn:country_code":"RO",
    "gn:dem":211,
    "gn:feature_class":"P",
    "gn:feature_code":"PPL",
    "gn:name":"Stup\u0103rei",
    "gn:population":614,
    "gn:timezone":"Europe/Bucharest",
    "iso:country":"RO",
    "name:und_x_variant":[
        "Stup\u0103rei",
        "Stup\u0103rai",
        "Stup\u0103reni"
    ],
    "wof:name":"Stuparei",
    "wof:placetype":"locality",
    "wof:population":614
},
  "geometry": {"coordinates":[24.28004,45.01736],"type":"Point"}
}