{
  "type": "Feature",
  "properties": {
    "gn:admin1_code":"04",
    "gn:admin2_code":"25148.0",
    "gn:asciiname":"Mateiesti",
    "gn:country_code":"RO",
    "gn:dem":267,
    "gn:feature_class":"P",
    "gn:feature_code":"PPL",
    "gn:name":"Mateie\u0219ti",
    "gn:population":66,
    "gn:timezone":"Europe/Bucharest",
    "iso:country":"RO",
    "wof:name":"Mateiesti",
    "wof:placetype":"locality",
    "wof:population":66
},
  "geometry": {"coordinates":[26.72059,46.42414],"type":"Point"}
}