{
  "type": "Feature",
  "properties": {
    "gn:gn_country":"RO",
    "gn:gn_fcode":"PPLA2",
    "gn:gn_pop":3175,
    "gn:population":3175,
    "iso:country":"RO",
    "name:eng_x_preferred":[
        "G\u0103l\u0103teni"
    ],
    "name:fra_x_preferred":[
        "G\u0103l\u0103teni"
    ],
    "name:ita_x_preferred":[
        "G\u0103l\u0103teni"
    ],
    "name:msa_x_preferred":[
        "G\u0103l\u0103teni"
    ],
    "name:nld_x_preferred":[
        "G\u0103l\u0103teni"
    ],
    "name:por_x_preferred":[
        "G\u0103l\u0103teni"
    ],
    "name:ron_x_preferred":[
        "G\u0103l\u0103teni"
    ],
    "name:ukr_x_preferred":[
        "\u0413\u0435\u043b\u0435\u0442\u0435\u043d\u044c"
    ],
    "name:unk_x_variant":[
        "G\u0103leteni"
    ],
    "name:vie_x_preferred":[
        "Galateni"
    ],
    "name:vol_x_preferred":[
        "G\u0103l\u0103teni"
    ],
    "qs_pg:aaroncc":"RO",
    "qs_pg:gn_country":"RO",
    "qs_pg:gn_fcode":"PPLA2",
    "qs_pg:gn_pop":3175,
    "qs_pg:name":"G\u0103l\u0103\u021beni",
    "qs_pg:name_adm0":"Rom\u00e2nia",
    "qs_pg:name_adm1":"Teleorman",
    "qs_pg:photos_9k":1,
    "qs_pg:photos_9r":1,
    "qs_pg:photos_all":9,
    "qs_pg:photos_sr":0,
    "qs_pg:pop_sr":4,
    "qs_pg:qs_pg_placetype":"locality",
    "qs_pg:qs_pg_placetype_gp":"Town",
    "qs_pg:woe_adm0":23424933,
    "woe:adm0_id":23424933,
    "woe:name_adm0":"Rom\u00e2nia",
    "woe:name_adm1":"Teleorman",
    "woe:placetype":"Town",
    "wof:name":"G\u0103l\u0103\u021beni",
    "wof:placetype":"locality",
    "wof:population":3175
},
  "geometry": {"coordinates":[25.35,44.21667],"type":"Point"}
}