{
  "type": "Feature",
  "properties": {
    "gn:admin1_code":"25",
    "gn:admin2_code":"108035.0",
    "gn:asciiname":"Carbunari",
    "gn:cc2":"RO",
    "gn:country_code":"RO",
    "gn:dem":213,
    "gn:feature_class":"P",
    "gn:feature_code":"PPL",
    "gn:name":"C\u0103rbunari",
    "gn:population":617,
    "gn:timezone":"Europe/Bucharest",
    "iso:country":"RO",
    "name:und_x_variant":[
        "C\u0103rbunar",
        "C\u0103rbunari"
    ],
    "wof:name":"Carbunari",
    "wof:placetype":"locality",
    "wof:population":617
},
  "geometry": {"coordinates":[23.64403,47.57516],"type":"Point"}
}