{
  "type": "Feature",
  "properties": {
    "gn:admin1_code":"38",
    "gn:admin2_code":"162595.0",
    "gn:asciiname":"Ursari",
    "gn:country_code":"RO",
    "gn:dem":258,
    "gn:feature_class":"P",
    "gn:feature_code":"PPL",
    "gn:name":"Ursari",
    "gn:population":0,
    "gn:timezone":"Europe/Bucharest",
    "iso:country":"RO",
    "name:heb_x_preferred":[
        "\u05d0\u05d5\u05e8\u05e1\u05e8\u05d9"
    ],
    "name:ita_x_preferred":[
        "Ursari"
    ],
    "name:jpn_x_preferred":[
        "\u30a6\u30eb\u30b5\u30ea"
    ],
    "name:ron_x_preferred":[
        "Ursari"
    ],
    "name:rus_x_preferred":[
        "\u0423\u0440\u0441\u0430\u0440\u044b"
    ],
    "wof:name":"Ursari",
    "wof:placetype":"locality"
},
  "geometry": {"coordinates":[27.61667000000001,46.55],"type":"Point"}
}