{
  "type": "Feature",
  "properties": {
    "gn:admin1_code":"23",
    "gn:admin2_code":"96717.0",
    "gn:asciiname":"Piscu Rusului",
    "gn:country_code":"RO",
    "gn:dem":250,
    "gn:feature_class":"P",
    "gn:feature_code":"PPL",
    "gn:name":"Piscu Rusului",
    "gn:population":406,
    "gn:timezone":"Europe/Bucharest",
    "iso:country":"RO",
    "wof:name":"Piscu Rusului",
    "wof:placetype":"locality",
    "wof:population":406
},
  "geometry": {"coordinates":[27.1478,46.95622],"type":"Point"}
}