{
  "type": "Feature",
  "properties": {
    "gn:admin1_code":"04",
    "gn:admin2_code":"20670.0",
    "gn:asciiname":"Negoiesti",
    "gn:cc2":"RO",
    "gn:country_code":"RO",
    "gn:dem":173,
    "gn:feature_class":"P",
    "gn:feature_code":"PPL",
    "gn:name":"Negoie\u0219ti",
    "gn:population":878,
    "gn:timezone":"Europe/Bucharest",
    "iso:country":"RO",
    "name:und_x_variant":[
        "Negoe\u015ftii",
        "Negoe\u015fti"
    ],
    "wof:name":"Negoiesti",
    "wof:placetype":"locality",
    "wof:population":878
},
  "geometry": {"coordinates":[26.88869,46.20043],"type":"Point"}
}