{
  "type": "Feature",
  "properties": {
    "gn:admin1_code":"09",
    "gn:admin2_code":"41346.0",
    "gn:asciiname":"Pojorta",
    "gn:country_code":"RO",
    "gn:dem":514,
    "gn:feature_class":"P",
    "gn:feature_code":"PPL",
    "gn:name":"Pojorta",
    "gn:population":155,
    "gn:timezone":"Europe/Bucharest",
    "iso:country":"RO",
    "name:hun_x_preferred":[
        "Posorta"
    ],
    "name:und_x_variant":[
        "Pojor\u00eeta"
    ],
    "wof:name":"Pojorta",
    "wof:placetype":"locality",
    "wof:population":155
},
  "geometry": {"coordinates":[24.86667000000001,45.75],"type":"Point"}
}