{
  "type": "Feature",
  "properties": {
    "gn:admin1_code":"02",
    "gn:admin2_code":"11539",
    "gn:asciiname":"Baratca",
    "gn:country_code":"RO",
    "gn:dem":127,
    "gn:feature_class":"P",
    "gn:feature_code":"PPL",
    "gn:name":"Bara\u021bca",
    "gn:population":309,
    "gn:timezone":"Europe/Bucharest",
    "iso:country":"RO",
    "name:ita_x_preferred":[
        "Baratca"
    ],
    "wof:name":"Baratca",
    "wof:placetype":"locality",
    "wof:population":309
},
  "geometry": {"coordinates":[21.63227,46.1072],"type":"Point"}
}