{
  "type": "Feature",
  "properties": {
    "gn:country":"RO",
    "gn:fcode":"PPL",
    "gn:population":0,
    "iso:country":"RO",
    "name:eng_x_preferred":[
        "Munun\u0103"
    ],
    "name:fra_x_preferred":[
        "Munun\u0103"
    ],
    "name:hun_x_preferred":[
        "Mununa"
    ],
    "name:ita_x_preferred":[
        "Munun\u0103"
    ],
    "name:nld_x_preferred":[
        "Munun\u0103"
    ],
    "name:ron_x_preferred":[
        "Munun\u0103"
    ],
    "name:srp_x_preferred":[
        "\u041c\u0443\u043d\u0443\u043d\u0430"
    ],
    "name:ukr_x_preferred":[
        "\u041c\u0443\u043d\u0443\u043d\u0435"
    ],
    "qs_pg:aaroncc":"RO",
    "qs_pg:gn_country":"RO",
    "qs_pg:gn_fcode":"PPL",
    "qs_pg:gn_pop":0,
    "qs_pg:name":"Munun\u0103",
    "qs_pg:name_adm0":"Rom\u00e2nia",
    "qs_pg:name_adm1":"Alba",
    "qs_pg:photos":33,
    "qs_pg:photos_1k":7,
    "qs_pg:photos_9k":1,
    "qs_pg:photos_9r":2,
    "qs_pg:photos_all":33,
    "qs_pg:photos_sr":2,
    "qs_pg:pop_sr":0,
    "qs_pg:qs_pg_placetype":"locality",
    "qs_pg:qs_pg_placetype_gp":"Town",
    "qs_pg:woe_adm0":23424933,
    "woe:adm0_id":23424933,
    "woe:name_adm0":"Rom\u00e2nia",
    "woe:name_adm1":"Alba",
    "woe:placetype":"Town",
    "wof:name":"Munun\u0103",
    "wof:placetype":"locality",
    "wof:population":92
},
  "geometry": {"coordinates":[22.83333,46.46667],"type":"Point"}
}