{
  "type": "Feature",
  "properties": {
    "gn:admin1_code":"19",
    "gn:admin2_code":"81576.0",
    "gn:asciiname":"Runcu",
    "gn:country_code":"RO",
    "gn:dem":282,
    "gn:feature_class":"P",
    "gn:feature_code":"PPLA2",
    "gn:name":"Runcu",
    "gn:population":5760,
    "gn:timezone":"Europe/Bucharest",
    "iso:country":"RO",
    "name:und_x_variant":[
        "Runcur",
        "Runcu"
    ],
    "wof:name":"Runcu",
    "wof:placetype":"locality",
    "wof:population":5760
},
  "geometry": {"coordinates":[23.13333,45.11667],"type":"Point"}
}