{
  "type": "Feature",
  "properties": {
    "gn:admin1_code":"19",
    "gn:admin2_code":"81576.0",
    "gn:asciiname":"Runcu",
    "gn:country_code":"RO",
    "gn:dem":282,
    "gn:feature_class":"P",
    "gn:feature_code":"PPLA2",
    "gn:name":"Runcu",
    "gn:population":5760,
    "gn:timezone":"Europe/Bucharest",
    "iso:country":"RO",
    "name:ceb_x_preferred":[
        "Comuna Runcu"
    ],
    "name:ita_x_preferred":[
        "Runcu"
    ],
    "name:msa_x_preferred":[
        "Runcu"
    ],
    "name:por_x_preferred":[
        "Runcu"
    ],
    "name:ron_x_preferred":[
        "Comuna Runcu"
    ],
    "name:srp_x_preferred":[
        "\u041e\u043f\u0448\u0442\u0438\u043d\u0430 \u0420\u0443\u043d\u043a\u0443"
    ],
    "name:ukr_x_preferred":[
        "\u0420\u0443\u043d\u043a\u0443"
    ],
    "name:und_x_variant":[
        "Runcur"
    ],
    "name:vie_x_preferred":[
        "Runcu"
    ],
    "name:vol_x_preferred":[
        "Runcu"
    ],
    "name:zho_x_preferred":[
        "\u502b\u5eab\u9109"
    ],
    "wof:name":"Runcu",
    "wof:placetype":"locality",
    "wof:population":5760
},
  "geometry": {"coordinates":[23.13333,45.11667],"type":"Point"}
}