{
  "type": "Feature",
  "properties": {
    "gn:admin1_code":"40",
    "gn:admin2_code":"178689",
    "gn:asciiname":"Beciu",
    "gn:country_code":"RO",
    "gn:dem":206,
    "gn:feature_class":"P",
    "gn:feature_code":"PPL",
    "gn:name":"Beciu",
    "gn:population":489,
    "gn:timezone":"Europe/Bucharest",
    "iso:country":"RO",
    "name:ceb_x_preferred":[
        "Comuna Beciu"
    ],
    "name:ita_x_preferred":[
        "Beciu"
    ],
    "name:msa_x_preferred":[
        "Beciu"
    ],
    "name:nld_x_preferred":[
        "Beciu"
    ],
    "name:por_x_preferred":[
        "Beciu"
    ],
    "name:ron_x_preferred":[
        "Comuna Beciu"
    ],
    "name:srp_x_preferred":[
        "\u041e\u043f\u0448\u0442\u0438\u043d\u0430 \u0411\u0435\u0447\u0443"
    ],
    "name:ukr_x_preferred":[
        "\u0411\u0435\u0447\u0443"
    ],
    "name:vol_x_preferred":[
        "Beciu"
    ],
    "name:zho_x_preferred":[
        "\u8c9d\u4e18\u9109"
    ],
    "wof:name":"Beciu",
    "wof:placetype":"locality",
    "wof:population":489
},
  "geometry": {"coordinates":[27.05158,45.73889000000001],"type":"Point"}
}