{
  "type": "Feature",
  "properties": {
    "gn:admin1_code":"11",
    "gn:admin2_code":"45389.0",
    "gn:asciiname":"Ulmet",
    "gn:country_code":"RO",
    "gn:dem":373,
    "gn:feature_class":"P",
    "gn:feature_code":"PPL",
    "gn:name":"Ulmet",
    "gn:population":95,
    "gn:timezone":"Europe/Bucharest",
    "iso:country":"RO",
    "wof:name":"Ulmet",
    "wof:placetype":"locality",
    "wof:population":95
},
  "geometry": {"coordinates":[26.47277,45.3689],"type":"Point"}
}