{
  "type": "Feature",
  "properties": {
    "gn:admin1_code":"31",
    "gn:admin2_code":"141580.0",
    "gn:asciiname":"Podisu",
    "gn:cc2":"RO",
    "gn:country_code":"RO",
    "gn:dem":213,
    "gn:feature_class":"P",
    "gn:feature_code":"PPL",
    "gn:name":"Podi\u0219u",
    "gn:population":198,
    "gn:timezone":"Europe/Bucharest",
    "iso:country":"RO",
    "name:und_x_variant":[
        "Ciumeni",
        "Podi\u015fu"
    ],
    "wof:name":"Podisu",
    "wof:placetype":"locality",
    "wof:population":198
},
  "geometry": {"coordinates":[23.59747,47.31924],"type":"Point"}
}