{
  "type": "Feature",
  "properties": {
    "gn:admin1_code":"02",
    "gn:admin2_code":"10239.0",
    "gn:asciiname":"Secas",
    "gn:country_code":"RO",
    "gn:dem":236,
    "gn:feature_class":"P",
    "gn:feature_code":"PPL",
    "gn:name":"Seca\u0219",
    "gn:population":515,
    "gn:timezone":"Europe/Bucharest",
    "iso:country":"RO",
    "name:ron_x_preferred":[
        "Seca\u0219"
    ],
    "name:und_x_variant":[
        "Szak\u00e1cs",
        "Als\u00f3szak\u00e1cs"
    ],
    "wof:name":"Secas",
    "wof:placetype":"locality",
    "wof:population":515
},
  "geometry": {"coordinates":[22.30461,46.22894],"type":"Point"}
}