{
  "type": "Feature",
  "properties": {
    "gn:admin1_code":"33",
    "gn:admin2_code":"144232.0",
    "gn:asciiname":"Ighisu Vechi",
    "gn:cc2":"RO",
    "gn:country_code":"RO",
    "gn:dem":450,
    "gn:feature_class":"P",
    "gn:feature_code":"PPL",
    "gn:name":"Ighi\u0219u Vechi",
    "gn:population":378,
    "gn:timezone":"Europe/Bucharest",
    "iso:country":"RO",
    "name:und_x_variant":[
        "Ighi\u015fdorfu Rom\u00een",
        "Ighi\u015ful-Vechi",
        "Ighi\u015fu Vechi"
    ],
    "wof:name":"Ighisu Vechi",
    "wof:placetype":"locality",
    "wof:population":378
},
  "geometry": {"coordinates":[24.48817,45.98942],"type":"Point"}
}