{
  "type": "Feature",
  "properties": {
    "gn:admin1_code":"04",
    "gn:admin2_code":"25228.0",
    "gn:asciiname":"Siretu",
    "gn:cc2":"RO",
    "gn:country_code":"RO",
    "gn:dem":161,
    "gn:feature_class":"P",
    "gn:feature_code":"PPL",
    "gn:name":"Siretu",
    "gn:population":630,
    "gn:timezone":"Europe/Bucharest",
    "iso:country":"RO",
    "name:ceb_x_preferred":[
        "Siretu"
    ],
    "name:deu_x_preferred":[
        "Siretu"
    ],
    "name:ron_x_preferred":[
        "Siretu"
    ],
    "name:srp_x_preferred":[
        "\u0421\u0438\u0440\u0435\u0442\u0443"
    ],
    "name:und_x_variant":[
        "C\u0103\u0163ele\u015fti",
        "Siretu"
    ],
    "wof:name":"Siretu",
    "wof:placetype":"locality",
    "wof:population":630
},
  "geometry": {"coordinates":[26.93174,46.67163],"type":"Point"}
}