{
  "type": "Feature",
  "properties": {
    "gn:admin1_code":"01",
    "gn:admin2_code":"5336.0",
    "gn:asciiname":"Dupa Deal",
    "gn:country_code":"RO",
    "gn:dem":710,
    "gn:feature_class":"P",
    "gn:feature_code":"PPL",
    "gn:name":"Dup\u0103 Deal",
    "gn:population":92,
    "gn:timezone":"Europe/Bucharest",
    "iso:country":"RO",
    "wof:name":"Dupa Deal",
    "wof:placetype":"locality",
    "wof:population":92
},
  "geometry": {"coordinates":[23.16296,46.33607],"type":"Point"}
}