{
  "type": "Feature",
  "properties": {
    "gn:admin1_code":"38",
    "gn:admin2_code":"161856.0",
    "gn:asciiname":"Parpanita",
    "gn:cc2":"RO",
    "gn:country_code":"RO",
    "gn:dem":120,
    "gn:feature_class":"P",
    "gn:feature_code":"PPL",
    "gn:name":"Parpani\u021ba",
    "gn:population":534,
    "gn:timezone":"Europe/Bucharest",
    "iso:country":"RO",
    "name:und_x_variant":[
        "Rediu-Parpani\u0163a",
        "Parpani\u0163a"
    ],
    "wof:name":"Parpanita",
    "wof:placetype":"locality",
    "wof:population":534
},
  "geometry": {"coordinates":[27.48857000000001,46.83221],"type":"Point"}
}