{
  "type": "Feature",
  "properties": {
    "gn:admin1_code":"04",
    "gn:admin2_code":"23494.0",
    "gn:asciiname":"Fantanele",
    "gn:cc2":"RO",
    "gn:country_code":"RO",
    "gn:dem":223,
    "gn:feature_class":"P",
    "gn:feature_code":"PPL",
    "gn:name":"F\u00e2nt\u00e2nele",
    "gn:population":365,
    "gn:timezone":"Europe/Bucharest",
    "iso:country":"RO",
    "name:und_x_variant":[
        "F\u0103t\u0103ciuni",
        "F\u00eent\u00eenele"
    ],
    "wof:name":"Fantanele",
    "wof:placetype":"locality",
    "wof:population":365
},
  "geometry": {"coordinates":[27.44404,46.33795],"type":"Point"}
}