{
  "type": "Feature",
  "properties": {
    "gn:admin1_code":"26",
    "gn:admin2_code":"111275.0",
    "gn:asciiname":"Vladasesti",
    "gn:country_code":"RO",
    "gn:dem":204,
    "gn:feature_class":"P",
    "gn:feature_code":"PPL",
    "gn:name":"Vl\u0103d\u0103\u0219e\u0219ti",
    "gn:population":227,
    "gn:timezone":"Europe/Bucharest",
    "iso:country":"RO",
    "wof:name":"Vladasesti",
    "wof:placetype":"locality",
    "wof:population":227
},
  "geometry": {"coordinates":[23.13285,44.64992],"type":"Point"}
}