{
  "type": "Feature",
  "properties": {
    "gn:admin1_code":"13",
    "gn:admin2_code":"57644.0",
    "gn:asciiname":"Nicula",
    "gn:country_code":"RO",
    "gn:dem":304,
    "gn:feature_class":"P",
    "gn:feature_code":"PPL",
    "gn:name":"Nicula",
    "gn:population":543,
    "gn:timezone":"Europe/Bucharest",
    "iso:country":"RO",
    "wof:name":"Nicula",
    "wof:placetype":"locality",
    "wof:population":543
},
  "geometry": {"coordinates":[23.94179,47.00799],"type":"Point"}
}