{
  "type": "Feature",
  "properties": {
    "gn:admin1_code":"39",
    "gn:admin2_code":"172947",
    "gn:asciiname":"Avramesti",
    "gn:country_code":"RO",
    "gn:dem":272,
    "gn:feature_class":"P",
    "gn:feature_code":"PPL",
    "gn:name":"Avr\u0103me\u0219ti",
    "gn:population":593,
    "gn:timezone":"Europe/Bucharest",
    "iso:country":"RO",
    "wof:name":"Avramesti",
    "wof:placetype":"locality",
    "wof:population":593
},
  "geometry": {"coordinates":[24.16735,44.85591],"type":"Point"}
}