{
  "type": "Feature",
  "properties": {
    "gn:admin1_code":"39",
    "gn:admin2_code":"173230.0",
    "gn:asciiname":"Piscu Mare",
    "gn:country_code":"RO",
    "gn:dem":476,
    "gn:feature_class":"P",
    "gn:feature_code":"PPL",
    "gn:name":"Piscu Mare",
    "gn:population":0,
    "gn:timezone":"Europe/Bucharest",
    "iso:country":"RO",
    "name:und_x_variant":[
        "Cacova",
        "Piscu Mare"
    ],
    "wof:name":"Piscu Mare",
    "wof:placetype":"locality"
},
  "geometry": {"coordinates":[24.18333,45.15],"type":"Point"}
}