{
  "type": "Feature",
  "properties": {
    "gn:admin1_code":"07",
    "gn:admin2_code":"36373.0",
    "gn:asciiname":"Poiana",
    "gn:country_code":"RO",
    "gn:dem":222,
    "gn:feature_class":"P",
    "gn:feature_code":"PPL",
    "gn:name":"Poiana",
    "gn:population":526,
    "gn:timezone":"Europe/Bucharest",
    "iso:country":"RO",
    "wof:name":"Poiana",
    "wof:placetype":"locality",
    "wof:population":526
},
  "geometry": {"coordinates":[26.4244,47.84524],"type":"Point"}
}