{
  "type": "Feature",
  "properties": {
    "gn:admin1_code":"21",
    "gn:admin2_code":"88644",
    "gn:asciiname":"Bretea Romana",
    "gn:cc2":"RO",
    "gn:country_code":"RO",
    "gn:dem":262,
    "gn:feature_class":"P",
    "gn:feature_code":"PPLA2",
    "gn:name":"Bretea Rom\u00e2n\u0103",
    "gn:population":301,
    "gn:timezone":"Europe/Bucharest",
    "iso:country":"RO",
    "name:und_x_variant":[
        "Bretea-Rom\u00e2n\u0103",
        "Bretea Rom\u00een\u0103"
    ],
    "wof:name":"Bretea Romana",
    "wof:placetype":"locality",
    "wof:population":301
},
  "geometry": {"coordinates":[23.01739,45.66085],"type":"Point"}
}