{
  "type": "Feature",
  "properties": {
    "gn:admin1_code":"21",
    "gn:admin2_code":"88644",
    "gn:asciiname":"Bretea Romana",
    "gn:cc2":"RO",
    "gn:country_code":"RO",
    "gn:dem":262,
    "gn:feature_class":"P",
    "gn:feature_code":"PPLA2",
    "gn:name":"Bretea Rom\u00e2n\u0103",
    "gn:population":301,
    "gn:timezone":"Europe/Bucharest",
    "iso:country":"RO",
    "name:ceb_x_preferred":[
        "Comuna Bretea Rom\u00e2n\u0103"
    ],
    "name:deu_x_preferred":[
        "Bretea Rom\u00e2n\u0103"
    ],
    "name:epo_x_preferred":[
        "Bretea Rom\u00e2n\u0103"
    ],
    "name:ita_x_preferred":[
        "Bretea Rom\u00e2n\u0103"
    ],
    "name:msa_x_preferred":[
        "Bretea Rom\u00e2n\u0103"
    ],
    "name:nld_x_preferred":[
        "Bretea Rom\u00e2n\u0103"
    ],
    "name:por_x_preferred":[
        "Bretea Rom\u00e2n\u0103"
    ],
    "name:ron_x_preferred":[
        "Comuna Bretea Rom\u00e2n\u0103"
    ],
    "name:srp_x_preferred":[
        "\u041e\u043f\u0448\u0442\u0438\u043d\u0430 \u0411\u0440\u0435\u0442\u0435\u0430 \u0420\u043e\u043c\u0430\u043d\u0430"
    ],
    "name:ukr_x_preferred":[
        "\u0411\u0440\u0435\u0442\u044f-\u0420\u043e\u043c\u0438\u043d\u0435"
    ],
    "name:und_x_variant":[
        "Bretea-Rom\u00e2n\u0103",
        "Bretea Rom\u00een\u0103"
    ],
    "name:vie_x_preferred":[
        "Bretea Rom\u00e2n\u0103"
    ],
    "name:vol_x_preferred":[
        "Bretea Rom\u00e2n\u0103"
    ],
    "name:zho_x_preferred":[
        "\u5e03\u96f7\u6cf0\u4e9e\u7f85\u99ac\u8a25\u9109"
    ],
    "wof:name":"Bretea Romana",
    "wof:placetype":"locality",
    "wof:population":301
},
  "geometry": {"coordinates":[23.01739,45.66085],"type":"Point"}
}