{
  "type": "Feature",
  "properties": {
    "gn:admin1_code":"13",
    "gn:admin2_code":"56844",
    "gn:asciiname":"Boldut",
    "gn:country_code":"RO",
    "gn:dem":318,
    "gn:feature_class":"P",
    "gn:feature_code":"PPL",
    "gn:name":"Boldu\u021b",
    "gn:population":813,
    "gn:timezone":"Europe/Bucharest",
    "iso:country":"RO",
    "wof:name":"Boldut",
    "wof:placetype":"locality",
    "wof:population":813
},
  "geometry": {"coordinates":[23.95176,46.62185],"type":"Point"}
}