{
  "type": "Feature",
  "properties": {
    "gn:admin1_code":"29",
    "gn:admin2_code":"130124.0",
    "gn:asciiname":"Pescaresti",
    "gn:country_code":"RO",
    "gn:dem":162,
    "gn:feature_class":"P",
    "gn:feature_code":"PPL",
    "gn:name":"Pesc\u0103re\u0219ti",
    "gn:population":502,
    "gn:timezone":"Europe/Bucharest",
    "iso:country":"RO",
    "wof:name":"Pescaresti",
    "wof:placetype":"locality",
    "wof:population":502
},
  "geometry": {"coordinates":[23.93909,44.44668],"type":"Point"}
}