{
  "type": "Feature",
  "properties": {
    "gn:admin1_code":"14",
    "gn:admin2_code":"63294.0",
    "gn:asciiname":"Lanurile",
    "gn:cc2":"RO",
    "gn:country_code":"RO",
    "gn:dem":97,
    "gn:feature_class":"P",
    "gn:feature_code":"PPL",
    "gn:name":"Lanurile",
    "gn:population":885,
    "gn:timezone":"Europe/Bucharest",
    "iso:country":"RO",
    "name:und_x_variant":[
        "Canurile",
        "Ebichioi",
        "Ebechioi",
        "Lanurile"
    ],
    "wof:name":"Lanurile",
    "wof:placetype":"locality",
    "wof:population":885
},
  "geometry": {"coordinates":[28.37794,44.06923],"type":"Point"}
}