{
  "type": "Feature",
  "properties": {
    "gn:admin1_code":"20",
    "gn:admin2_code":"86366.0",
    "gn:asciiname":"Poiana Tarnavei",
    "gn:country_code":"RO",
    "gn:dem":825,
    "gn:feature_class":"P",
    "gn:feature_code":"PPL",
    "gn:name":"Poiana T\u00e2rnavei",
    "gn:population":39,
    "gn:timezone":"Europe/Bucharest",
    "iso:country":"RO",
    "name:hun_x_preferred":[
        "K\u00fck\u00fcll\u0151mez\u0151"
    ],
    "name:und_x_variant":[
        "Poiana T\u00eernavei"
    ],
    "wof:name":"Poiana Tarnavei",
    "wof:placetype":"locality",
    "wof:population":39
},
  "geometry": {"coordinates":[25.38854,46.5086],"type":"Point"}
}