{
  "type": "Feature",
  "properties": {
    "gn:admin1_code":"28",
    "gn:admin2_code":"123013.0",
    "gn:asciiname":"Tabara",
    "gn:country_code":"RO",
    "gn:dem":272,
    "gn:feature_class":"P",
    "gn:feature_code":"PPL",
    "gn:name":"Tab\u0103ra",
    "gn:population":125,
    "gn:timezone":"Europe/Bucharest",
    "iso:country":"RO",
    "name:ceb_x_preferred":[
        "Tabara"
    ],
    "name:fra_x_preferred":[
        "Tabara"
    ],
    "name:srp_x_preferred":[
        "\u0422\u0430\u0431\u0430\u0440\u0430"
    ],
    "name:swe_x_preferred":[
        "Tabara"
    ],
    "wof:name":"Tabara",
    "wof:placetype":"locality",
    "wof:population":125
},
  "geometry": {"coordinates":[27.03925,46.82048],"type":"Point"}
}