{
  "type": "Feature",
  "properties": {
    "gn:admin1_code":"18",
    "gn:admin2_code":"75356.0",
    "gn:asciiname":"Prodanesti",
    "gn:cc2":"RO",
    "gn:country_code":"RO",
    "gn:dem":185,
    "gn:feature_class":"P",
    "gn:feature_code":"PPL",
    "gn:name":"Prod\u0103ne\u0219ti",
    "gn:population":209,
    "gn:timezone":"Europe/Bucharest",
    "iso:country":"RO",
    "name:und_x_variant":[
        "Regele-Ferdinand",
        "Prod\u0103ne\u015fti"
    ],
    "wof:name":"Prodanesti",
    "wof:placetype":"locality",
    "wof:population":209
},
  "geometry": {"coordinates":[27.9532,46.10997],"type":"Point"}
}