{
  "type": "Feature",
  "properties": {
    "gn:admin1_code":"20",
    "gn:admin2_code":"86133.0",
    "gn:asciiname":"Noghirez",
    "gn:country_code":"RO",
    "gn:dem":703,
    "gn:feature_class":"P",
    "gn:feature_code":"PPL",
    "gn:name":"Noghirez",
    "gn:population":0,
    "gn:timezone":"Europe/Bucharest",
    "iso:country":"RO",
    "name:und_x_variant":[
        "Naghirez",
        "Nagyreszpatak",
        "N\u00e0gyrez",
        "Noghirez"
    ],
    "wof:name":"Noghirez",
    "wof:placetype":"locality"
},
  "geometry": {"coordinates":[25.73333,46.93333],"type":"Point"}
}