{
  "type": "Feature",
  "properties": {
    "gn:admin1_code":"19",
    "gn:admin2_code":"80980",
    "gn:asciiname":"Artanu",
    "gn:cc2":"RO",
    "gn:country_code":"RO",
    "gn:dem":191,
    "gn:feature_class":"P",
    "gn:feature_code":"PPL",
    "gn:name":"Artanu",
    "gn:population":706,
    "gn:timezone":"Europe/Bucharest",
    "iso:country":"RO",
    "name:und_x_variant":[
        "Arianu",
        "Artanu"
    ],
    "wof:name":"Artanu",
    "wof:placetype":"locality",
    "wof:population":706
},
  "geometry": {"coordinates":[23.22223,44.78736],"type":"Point"}
}