{
  "type": "Feature",
  "properties": {
    "gn:admin1_code":"26",
    "gn:admin2_code":"112904.0",
    "gn:asciiname":"Eibenthal",
    "gn:cc2":"RO",
    "gn:country_code":"RO",
    "gn:dem":400,
    "gn:feature_class":"P",
    "gn:feature_code":"PPL",
    "gn:name":"Eibenthal",
    "gn:population":375,
    "gn:timezone":"Europe/Bucharest",
    "iso:country":"RO",
    "name:und_x_variant":[
        "Ajbental",
        "Eibental",
        "Eibenthal"
    ],
    "wof:name":"Eibenthal",
    "wof:placetype":"locality",
    "wof:population":375
},
  "geometry": {"coordinates":[22.16359,44.54529],"type":"Point"}
}