{
  "type": "Feature",
  "properties": {
    "gn:admin1_code":"29",
    "gn:admin2_code":"128711.0",
    "gn:asciiname":"Piscani",
    "gn:cc2":"RO",
    "gn:country_code":"RO",
    "gn:dem":208,
    "gn:feature_class":"P",
    "gn:feature_code":"PPL",
    "gn:name":"Piscani",
    "gn:population":280,
    "gn:timezone":"Europe/Bucharest",
    "iso:country":"RO",
    "name:ceb_x_preferred":[
        "Piscani"
    ],
    "name:deu_x_preferred":[
        "Piscani"
    ],
    "name:ron_x_preferred":[
        "Piscani"
    ],
    "name:und_x_variant":[
        "Piscanie\u015fti",
        "Piscani"
    ],
    "wof:name":"Piscani",
    "wof:placetype":"locality",
    "wof:population":280
},
  "geometry": {"coordinates":[24.55378,44.56708],"type":"Point"}
}