{
  "type": "Feature",
  "properties": {
    "gn:admin1_code":"12",
    "gn:admin2_code":"52570",
    "gn:asciiname":"Boina",
    "gn:country_code":"RO",
    "gn:dem":241,
    "gn:feature_class":"P",
    "gn:feature_code":"PPL",
    "gn:name":"Boina",
    "gn:population":19,
    "gn:timezone":"Europe/Bucharest",
    "iso:country":"RO",
    "name:dan_x_preferred":[
        "Boina"
    ],
    "name:fra_x_preferred":[
        "Boina"
    ],
    "name:slk_x_preferred":[
        "Boina"
    ],
    "name:spa_x_preferred":[
        "Boina"
    ],
    "wof:name":"Boina",
    "wof:placetype":"locality",
    "wof:population":19
},
  "geometry": {"coordinates":[21.89084,44.82094],"type":"Point"}
}