{
  "type": "Feature",
  "properties": {
    "gn:admin1_code":"23",
    "gn:admin2_code":"98505.0",
    "gn:asciiname":"Vulturi",
    "gn:cc2":"RO",
    "gn:country_code":"RO",
    "gn:dem":65,
    "gn:feature_class":"P",
    "gn:feature_code":"PPL",
    "gn:name":"Vulturi",
    "gn:population":763,
    "gn:timezone":"Europe/Bucharest",
    "iso:country":"RO",
    "name:und_x_variant":[
        "Vulturu",
        "Vulturul",
        "Vultur",
        "Vulturi"
    ],
    "wof:name":"Vulturi",
    "wof:placetype":"locality",
    "wof:population":763
},
  "geometry": {"coordinates":[27.53807,47.24854000000001],"type":"Point"}
}