{
  "type": "Feature",
  "properties": {
    "gn:admin1_code":"35",
    "gn:admin2_code":"154585.0",
    "gn:asciiname":"Zlotesti",
    "gn:country_code":"RO",
    "gn:dem":107,
    "gn:feature_class":"P",
    "gn:feature_code":"PPL",
    "gn:name":"Zlote\u015fti",
    "gn:population":0,
    "gn:timezone":"Europe/Bucharest",
    "iso:country":"RO",
    "name:und_x_variant":[
        "Zolte\u015fti",
        "Zlote\u015fti"
    ],
    "wof:lang_x_official":[
        "ron"
    ],
    "wof:lang_x_spoken":[
        "ron"
    ],
    "wof:name":"Zlotesti",
    "wof:placetype":"locality"
},
  "geometry": {"coordinates":[25.18333,44.35],"type":"Point"}
}