{
  "type": "Feature",
  "properties": {
    "iso:country":"RO",
    "name:eng_x_preferred":[
        "Schitu Gole\u0219ti"
    ],
    "name:fra_x_preferred":[
        "Schitu Gole\u0219ti"
    ],
    "name:ita_x_preferred":[
        "Schitu Gole\u0219ti"
    ],
    "name:nld_x_preferred":[
        "Schitu Gole\u0219ti"
    ],
    "name:ron_x_preferred":[
        "Schitu Gole\u0219ti"
    ],
    "name:srp_x_preferred":[
        "\u0421\u043a\u0438\u0442\u0443-\u0413\u043e\u043b\u0435\u0448\u0442\u0438"
    ],
    "name:ukr_x_preferred":[
        "\u0421\u043a\u0456\u0442\u0443-\u0413\u043e\u043b\u0435\u0448\u0442\u044c"
    ],
    "qs_pg:aaroncc":"RO",
    "qs_pg:name":"Schitu-Gole\u0219ti",
    "qs_pg:name_adm0":"Rom\u00e2nia",
    "qs_pg:name_adm1":"Arges",
    "qs_pg:photos":8,
    "qs_pg:photos_1k":2,
    "qs_pg:photos_9k":1,
    "qs_pg:photos_9r":1,
    "qs_pg:photos_all":8,
    "qs_pg:photos_sr":1,
    "qs_pg:pop_sr":0,
    "qs_pg:qs_pg_placetype":"locality",
    "qs_pg:qs_pg_placetype_gp":"Town",
    "qs_pg:woe_adm0":23424933,
    "woe:adm0_id":23424933,
    "woe:name_adm0":"Rom\u00e2nia",
    "woe:name_adm1":"Arges",
    "woe:placetype":"Town",
    "wof:name":"Schitu-Gole\u0219ti",
    "wof:placetype":"locality"
},
  "geometry": {"coordinates":[24.9950495,45.2155985],"type":"Point"}
}