{
  "type": "Feature",
  "properties": {
    "gn:admin1_code":"06",
    "gn:admin2_code":"34770",
    "gn:asciiname":"Agrisu de Sus",
    "gn:cc2":"RO",
    "gn:country_code":"RO",
    "gn:dem":360,
    "gn:feature_class":"P",
    "gn:feature_code":"PPL",
    "gn:name":"Agri\u0219u de Sus",
    "gn:population":221,
    "gn:timezone":"Europe/Bucharest",
    "iso:country":"RO",
    "name:und_x_variant":[
        "Agri\u015ful de Sus",
        "Agri\u015fu de Sus"
    ],
    "wof:name":"Agrisu de Sus",
    "wof:placetype":"locality",
    "wof:population":221
},
  "geometry": {"coordinates":[24.22982,47.15106],"type":"Point"}
}