{
  "type": "Feature",
  "properties": {
    "gn:admin1_code":"19",
    "gn:admin2_code":"78329.0",
    "gn:asciiname":"Carbunesti-Sat",
    "gn:cc2":"RO",
    "gn:country_code":"RO",
    "gn:dem":267,
    "gn:feature_class":"P",
    "gn:feature_code":"PPL",
    "gn:name":"C\u0103rbune\u0219ti-Sat",
    "gn:population":869,
    "gn:timezone":"Europe/Bucharest",
    "iso:country":"RO",
    "name:und_x_variant":[
        "C\u0103rbune\u015fti",
        "C\u0103rbune\u015fti-Sat"
    ],
    "wof:name":"Carbunesti-Sat",
    "wof:placetype":"locality",
    "wof:population":869
},
  "geometry": {"coordinates":[23.54681,44.95071],"type":"Point"}
}