{
  "type": "Feature",
  "properties": {
    "gn:gn_country":"RO",
    "gn:gn_fcode":"PPL",
    "gn:gn_pop":0,
    "gn:population":1371,
    "iso:country":"RO",
    "name:deu_x_preferred":[
        "Giarmata-Vii"
    ],
    "name:eng_x_preferred":[
        "Giarmata-Vii"
    ],
    "name:epo_x_preferred":[
        "Giarmata Vii"
    ],
    "name:fra_x_preferred":[
        "Giarmata-Vii"
    ],
    "name:hun_x_preferred":[
        "Kisgyarmatapuszta"
    ],
    "name:nld_x_preferred":[
        "Giarmata-Vii"
    ],
    "name:ron_x_preferred":[
        "Giarmata-Vii"
    ],
    "name:ukr_x_preferred":[
        "\u0414\u0436\u0430\u0440\u043c\u0430\u0442\u0430-\u0412\u0456\u0439"
    ],
    "qs_pg:aaroncc":"RO",
    "qs_pg:gn_country":"RO",
    "qs_pg:gn_fcode":"PPL",
    "qs_pg:gn_pop":0,
    "qs_pg:name":"Giarmata Vii",
    "qs_pg:name_adm0":"Rom\u00e2nia",
    "qs_pg:name_adm1":"Timis",
    "qs_pg:photos":17,
    "qs_pg:photos_1k":3,
    "qs_pg:photos_9k":1,
    "qs_pg:photos_9r":1,
    "qs_pg:photos_all":17,
    "qs_pg:photos_sr":1,
    "qs_pg:pop_sr":0,
    "qs_pg:qs_pg_placetype":"locality",
    "qs_pg:qs_pg_placetype_gp":"Town",
    "qs_pg:woe_adm0":23424933,
    "woe:adm0_id":23424933,
    "woe:name_adm0":"Rom\u00e2nia",
    "woe:name_adm1":"Timis",
    "woe:placetype":"Town",
    "wof:name":"Giarmata Vii",
    "wof:placetype":"locality",
    "wof:population":1371
},
  "geometry": {"coordinates":[21.31667,45.83333],"type":"Point"}
}