{
  "type": "Feature",
  "properties": {
    "gn:admin1_code":"33",
    "gn:admin2_code":"144376.0",
    "gn:asciiname":"Retis",
    "gn:cc2":"RO",
    "gn:country_code":"RO",
    "gn:dem":512,
    "gn:feature_class":"P",
    "gn:feature_code":"PPL",
    "gn:name":"Reti\u0219",
    "gn:population":587,
    "gn:timezone":"Europe/Bucharest",
    "iso:country":"RO",
    "name:und_x_variant":[
        "Reti\u015ful",
        "Reti\u015fu"
    ],
    "wof:name":"Retis",
    "wof:placetype":"locality",
    "wof:population":587
},
  "geometry": {"coordinates":[24.8512,46.04337],"type":"Point"}
}