{
  "type": "Feature",
  "properties": {
    "gn:admin1_code":"09",
    "gn:admin2_code":"42236.0",
    "gn:asciiname":"Vistisoara",
    "gn:country_code":"RO",
    "gn:dem":684,
    "gn:feature_class":"P",
    "gn:feature_code":"PPL",
    "gn:name":"Vi\u0219ti\u0219oara",
    "gn:population":27,
    "gn:timezone":"Europe/Bucharest",
    "iso:country":"RO",
    "wof:name":"Vistisoara",
    "wof:placetype":"locality",
    "wof:population":27
},
  "geometry": {"coordinates":[24.76291,45.6929],"type":"Point"}
}