{
  "type": "Feature",
  "properties": {
    "gn:admin1_code":"40",
    "gn:admin2_code":"174922.0",
    "gn:asciiname":"Padureni",
    "gn:cc2":"RO",
    "gn:country_code":"RO",
    "gn:dem":65,
    "gn:feature_class":"P",
    "gn:feature_code":"PPL",
    "gn:name":"P\u0103dureni",
    "gn:population":535,
    "gn:timezone":"Europe/Bucharest",
    "iso:country":"RO",
    "name:und_x_variant":[
        "P\u0103durenii",
        "P\u0103dureni"
    ],
    "wof:name":"Padureni",
    "wof:placetype":"locality",
    "wof:population":535
},
  "geometry": {"coordinates":[27.23152,45.93729],"type":"Point"}
}