{
  "type": "Feature",
  "properties": {
    "gn:admin1_code":"32",
    "gn:admin2_code":"138084.0",
    "gn:asciiname":"Medies-Raturi",
    "gn:country_code":"RO",
    "gn:dem":133,
    "gn:feature_class":"P",
    "gn:feature_code":"PPL",
    "gn:name":"Medie\u0219-R\u00e2turi",
    "gn:population":303,
    "gn:timezone":"Europe/Bucharest",
    "iso:country":"RO",
    "name:hun_x_preferred":[
        "Meggyesfordul\u00f3"
    ],
    "wof:name":"Medies-Raturi",
    "wof:placetype":"locality",
    "wof:population":303
},
  "geometry": {"coordinates":[23.19893,47.80659],"type":"Point"}
}