{
  "type": "Feature",
  "properties": {
    "gn:admin1_code":"13",
    "gn:admin2_code":"55687.0",
    "gn:asciiname":"Sub Coasta",
    "gn:country_code":"RO",
    "gn:dem":304,
    "gn:feature_class":"P",
    "gn:feature_code":"PPL",
    "gn:name":"Sub Coast\u0103",
    "gn:population":0,
    "gn:timezone":"Europe/Bucharest",
    "iso:country":"RO",
    "wof:name":"Sub Coasta",
    "wof:placetype":"locality"
},
  "geometry": {"coordinates":[23.71219,46.79703],"type":"Point"}
}