{
  "type": "Feature",
  "properties": {
    "gn:admin1_code":"07",
    "gn:admin2_code":"37217",
    "gn:asciiname":"Brosteni",
    "gn:country_code":"RO",
    "gn:dem":162,
    "gn:feature_class":"P",
    "gn:feature_code":"PPL",
    "gn:name":"Bro\u0219teni",
    "gn:population":278,
    "gn:timezone":"Europe/Bucharest",
    "iso:country":"RO",
    "wof:name":"Brosteni",
    "wof:placetype":"locality",
    "wof:population":278
},
  "geometry": {"coordinates":[27.08836,47.75403],"type":"Point"}
}