{
  "type": "Feature",
  "properties": {
    "gn:admin1_code":"04",
    "gn:admin2_code":"22834.0",
    "gn:asciiname":"Muncelu",
    "gn:cc2":"RO",
    "gn:country_code":"RO",
    "gn:dem":268,
    "gn:feature_class":"P",
    "gn:feature_code":"PPL",
    "gn:name":"Muncelu",
    "gn:population":309,
    "gn:timezone":"Europe/Bucharest",
    "iso:country":"RO",
    "name:und_x_variant":[
        "Muncelul",
        "Muncelu"
    ],
    "wof:name":"Muncelu",
    "wof:placetype":"locality",
    "wof:population":309
},
  "geometry": {"coordinates":[27.34606,46.26644],"type":"Point"}
}