{
  "type": "Feature",
  "properties": {
    "gn:admin1_code":"38",
    "gn:admin2_code":"163832",
    "gn:asciiname":"Bogdanesti",
    "gn:country_code":"RO",
    "gn:dem":16,
    "gn:feature_class":"P",
    "gn:feature_code":"PPL",
    "gn:name":"Bogd\u0103ne\u0219ti",
    "gn:population":712,
    "gn:timezone":"Europe/Bucharest",
    "iso:country":"RO",
    "wof:name":"Bogdanesti",
    "wof:placetype":"locality",
    "wof:population":712
},
  "geometry": {"coordinates":[28.11501,46.26212],"type":"Point"}
}