{
  "type": "Feature",
  "properties": {
    "gn:admin1_code":"37",
    "gn:admin2_code":"160831.0",
    "gn:asciiname":"Satu Nou",
    "gn:cc2":"RO",
    "gn:country_code":"RO",
    "gn:dem":19,
    "gn:feature_class":"P",
    "gn:feature_code":"PPL",
    "gn:name":"Satu Nou",
    "gn:population":762,
    "gn:timezone":"Europe/Bucharest",
    "iso:country":"RO",
    "name:ceb_x_preferred":[
        "Satu Nou"
    ],
    "name:deu_x_preferred":[
        "Satu Nou"
    ],
    "name:epo_x_preferred":[
        "Satu Nou"
    ],
    "name:hun_x_preferred":[
        "Satu Nou"
    ],
    "name:ron_x_preferred":[
        "Satu Nou"
    ],
    "name:srp_x_preferred":[
        "\u041d\u043e\u0432\u043e \u0441\u0435\u043b\u043e"
    ],
    "name:ukr_x_preferred":[
        "\u0421\u0430\u0442\u0443-\u041d\u043e\u0443"
    ],
    "name:und_x_variant":[
        "Satul Nou",
        "Satunov"
    ],
    "wof:name":"Satu Nou",
    "wof:placetype":"locality",
    "wof:population":762
},
  "geometry": {"coordinates":[28.68408,44.9562],"type":"Point"}
}