{
  "type": "Feature",
  "properties": {
    "gn:admin1_code":"37",
    "gn:admin2_code":"160831.0",
    "gn:asciiname":"Satu Nou",
    "gn:cc2":"RO",
    "gn:country_code":"RO",
    "gn:dem":19,
    "gn:feature_class":"P",
    "gn:feature_code":"PPL",
    "gn:name":"Satu Nou",
    "gn:population":762,
    "gn:timezone":"Europe/Bucharest",
    "iso:country":"RO",
    "name:und_x_variant":[
        "Satul Nou",
        "Satunov",
        "Satu Nou"
    ],
    "wof:name":"Satu Nou",
    "wof:placetype":"locality",
    "wof:population":762
},
  "geometry": {"coordinates":[28.68408,44.9562],"type":"Point"}
}