{
  "type": "Feature",
  "properties": {
    "gn:admin1_code":"40",
    "gn:admin2_code":"177842.0",
    "gn:asciiname":"Dimaci",
    "gn:country_code":"RO",
    "gn:dem":25,
    "gn:feature_class":"P",
    "gn:feature_code":"PPL",
    "gn:name":"Dimaci",
    "gn:population":0,
    "gn:timezone":"Europe/Bucharest",
    "iso:country":"RO",
    "name:und_x_variant":[
        "Dimaciu",
        "Dimaci"
    ],
    "wof:name":"Dimaci",
    "wof:placetype":"locality"
},
  "geometry": {"coordinates":[27.36667,45.68333],"type":"Point"}
}