{
  "type": "Feature",
  "properties": {
    "gn:admin1_code":"19",
    "gn:admin2_code":"81816.0",
    "gn:asciiname":"Dolcesti",
    "gn:country_code":"RO",
    "gn:dem":167,
    "gn:feature_class":"P",
    "gn:feature_code":"PPL",
    "gn:name":"Dolce\u0219ti",
    "gn:population":385,
    "gn:timezone":"Europe/Bucharest",
    "iso:country":"RO",
    "wof:name":"Dolcesti",
    "wof:placetype":"locality",
    "wof:population":385
},
  "geometry": {"coordinates":[23.50495,44.81561],"type":"Point"}
}