{
  "type": "Feature",
  "properties": {
    "gn:admin1_code":"13",
    "gn:admin2_code":"55687.0",
    "gn:asciiname":"Corpadea",
    "gn:country_code":"RO",
    "gn:dem":351,
    "gn:feature_class":"P",
    "gn:feature_code":"PPL",
    "gn:name":"Corpadea",
    "gn:population":529,
    "gn:timezone":"Europe/Bucharest",
    "iso:country":"RO",
    "wof:name":"Corpadea",
    "wof:placetype":"locality",
    "wof:population":529
},
  "geometry": {"coordinates":[23.8281,46.79195],"type":"Point"}
}