{
  "type": "Feature",
  "properties": {
    "gn:admin1_code":"28",
    "gn:admin2_code":"123790.0",
    "gn:asciiname":"Topoliceni",
    "gn:cc2":"RO",
    "gn:country_code":"RO",
    "gn:dem":510,
    "gn:feature_class":"P",
    "gn:feature_code":"PPL",
    "gn:name":"Topoliceni",
    "gn:population":310,
    "gn:timezone":"Europe/Bucharest",
    "iso:country":"RO",
    "name:und_x_variant":[
        "Topoliceni de Jos",
        "Topliceni",
        "Topolicenii de Jos"
    ],
    "wof:name":"Topoliceni",
    "wof:placetype":"locality",
    "wof:population":310
},
  "geometry": {"coordinates":[25.93509,47.11023],"type":"Point"}
}