{
  "type": "Feature",
  "properties": {
    "gn:admin1_code":"41",
    "gn:admin2_code":"104886.0",
    "gn:asciiname":"Magureni",
    "gn:cc2":"RO",
    "gn:country_code":"RO",
    "gn:dem":31,
    "gn:feature_class":"P",
    "gn:feature_code":"PPL",
    "gn:name":"M\u0103gureni",
    "gn:population":75,
    "gn:timezone":"Europe/Bucharest",
    "iso:country":"RO",
    "name:und_x_variant":[
        "P\u00e2rlita",
        "Ion Gheorghe Duca",
        "P\u00eerlita",
        "M\u0103gureni"
    ],
    "wof:name":"Magureni",
    "wof:placetype":"locality",
    "wof:population":75
},
  "geometry": {"coordinates":[26.62868,44.41369],"type":"Point"}
}