{
  "type": "Feature",
  "properties": {
    "gn:admin1_code":"03",
    "gn:admin2_code":"16944.0",
    "gn:asciiname":"Marghia de Jos",
    "gn:cc2":"RO",
    "gn:country_code":"RO",
    "gn:dem":245,
    "gn:feature_class":"P",
    "gn:feature_code":"PPL",
    "gn:name":"M\u00e2rghia de Jos",
    "gn:population":386,
    "gn:timezone":"Europe/Bucharest",
    "iso:country":"RO",
    "name:und_x_variant":[
        "M\u00e2rghia-de Jos",
        "M\u00eerghia de Jos"
    ],
    "wof:name":"Marghia de Jos",
    "wof:placetype":"locality",
    "wof:population":386
},
  "geometry": {"coordinates":[24.71807,44.68159],"type":"Point"}
}