{
  "type": "Feature",
  "properties": {
    "gn:admin1_code":"19",
    "gn:admin2_code":"81380.0",
    "gn:asciiname":"Racovita",
    "gn:cc2":"RO",
    "gn:country_code":"RO",
    "gn:dem":526,
    "gn:feature_class":"P",
    "gn:feature_code":"PPL",
    "gn:name":"Racovi\u021ba",
    "gn:population":580,
    "gn:timezone":"Europe/Bucharest",
    "iso:country":"RO",
    "name:und_x_variant":[
        "Racovita Cerna",
        "Racovi\u0163a"
    ],
    "wof:name":"Racovita",
    "wof:placetype":"locality",
    "wof:population":580
},
  "geometry": {"coordinates":[23.83763,45.16925],"type":"Point"}
}