{
  "type": "Feature",
  "properties": {
    "gn:admin1_code":"11",
    "gn:admin2_code":"46439.0",
    "gn:asciiname":"Muscelu Caramanesti",
    "gn:country_code":"RO",
    "gn:dem":665,
    "gn:feature_class":"P",
    "gn:feature_code":"PPL",
    "gn:name":"Muscelu C\u0103r\u0103m\u0103ne\u0219ti",
    "gn:population":223,
    "gn:timezone":"Europe/Bucharest",
    "iso:country":"RO",
    "wof:name":"Muscelu Caramanesti",
    "wof:placetype":"locality",
    "wof:population":223
},
  "geometry": {"coordinates":[26.43211,45.38393],"type":"Point"}
}