{
  "type": "Feature",
  "properties": {
    "gn:admin1_code":"01",
    "gn:admin2_code":"3459",
    "gn:asciiname":"Bucium",
    "gn:cc2":"RO",
    "gn:country_code":"RO",
    "gn:dem":755,
    "gn:feature_class":"P",
    "gn:feature_code":"PPLA2",
    "gn:name":"Bucium",
    "gn:population":119,
    "gn:timezone":"Europe/Bucharest",
    "iso:country":"RO",
    "name:ara_x_preferred":[
        "\u0628\u0648\u062a\u0634\u064a\u0648\u0645"
    ],
    "name:ceb_x_preferred":[
        "Comuna Bucium"
    ],
    "name:deu_x_preferred":[
        "Bucium"
    ],
    "name:epo_x_preferred":[
        "Bucium"
    ],
    "name:fra_x_preferred":[
        "Bucium"
    ],
    "name:hrv_x_preferred":[
        "Bucium"
    ],
    "name:hun_x_preferred":[
        "Bucsony k\u00f6zs\u00e9g"
    ],
    "name:ita_x_preferred":[
        "Bucium"
    ],
    "name:mkd_x_preferred":[
        "\u0411\u0443\u0447\u0443\u043c"
    ],
    "name:msa_x_preferred":[
        "Bucium"
    ],
    "name:nld_x_preferred":[
        "Bucium"
    ],
    "name:pol_x_preferred":[
        "Gmina Bucium"
    ],
    "name:por_x_preferred":[
        "Bucium"
    ],
    "name:ron_x_preferred":[
        "Comuna Bucium"
    ],
    "name:sqi_x_preferred":[
        "Bucium"
    ],
    "name:srp_x_preferred":[
        "\u041e\u043f\u0448\u0442\u0438\u043d\u0430 \u0411\u0443\u0447\u0443\u043c"
    ],
    "name:ukr_x_preferred":[
        "\u0411\u0443\u0447\u0443\u043c"
    ],
    "name:und_x_variant":[
        "\u015easa",
        "Bucium \u015easa"
    ],
    "name:vie_x_preferred":[
        "Bucium"
    ],
    "name:vol_x_preferred":[
        "Bucium"
    ],
    "name:zho_x_preferred":[
        "\u5e03\u4e18\u59c6\u9109"
    ],
    "wof:name":"Bucium",
    "wof:placetype":"locality",
    "wof:population":119
},
  "geometry": {"coordinates":[23.1791,46.26402],"type":"Point"}
}