{
  "type": "Feature",
  "properties": {
    "gn:admin1_code":"01",
    "gn:admin2_code":"3459",
    "gn:asciiname":"Bucium",
    "gn:cc2":"RO",
    "gn:country_code":"RO",
    "gn:dem":755,
    "gn:feature_class":"P",
    "gn:feature_code":"PPLA2",
    "gn:name":"Bucium",
    "gn:population":119,
    "gn:timezone":"Europe/Bucharest",
    "iso:country":"RO",
    "name:und_x_variant":[
        "\u015easa",
        "Bucium \u015easa",
        "Bucium"
    ],
    "wof:name":"Bucium",
    "wof:placetype":"locality",
    "wof:population":119
},
  "geometry": {"coordinates":[23.1791,46.26402],"type":"Point"}
}