{
  "type": "Feature",
  "properties": {
    "gn:admin1_code":"21",
    "gn:admin2_code":"90878.0",
    "gn:asciiname":"Ostrovel",
    "gn:country_code":"RO",
    "gn:dem":474,
    "gn:feature_class":"P",
    "gn:feature_code":"PPL",
    "gn:name":"Ostrovel",
    "gn:population":197,
    "gn:timezone":"Europe/Bucharest",
    "iso:country":"RO",
    "wof:name":"Ostrovel",
    "wof:placetype":"locality",
    "wof:population":197
},
  "geometry": {"coordinates":[22.85518,45.50523],"type":"Point"}
}