{
  "type": "Feature",
  "properties": {
    "gn:admin1_code":"34",
    "gn:admin2_code":"150588.0",
    "gn:asciiname":"Stirbat",
    "gn:country_code":"RO",
    "gn:dem":241,
    "gn:feature_class":"P",
    "gn:feature_code":"PPL",
    "gn:name":"\u0218tirb\u0103\u021b",
    "gn:population":640,
    "gn:timezone":"Europe/Bucharest",
    "iso:country":"RO",
    "wof:name":"Stirbat",
    "wof:placetype":"locality",
    "wof:population":640
},
  "geometry": {"coordinates":[26.49256,47.55542],"type":"Point"}
}