{
  "type": "Feature",
  "properties": {
    "gn:admin1_code":"11",
    "gn:admin2_code":"46377.0",
    "gn:asciiname":"Satu Nou",
    "gn:country_code":"RO",
    "gn:dem":85,
    "gn:feature_class":"P",
    "gn:feature_code":"PPL",
    "gn:name":"Satu Nou",
    "gn:population":0,
    "gn:timezone":"Europe/Bucharest",
    "iso:country":"RO",
    "wof:name":"Satu Nou",
    "wof:placetype":"locality"
},
  "geometry": {"coordinates":[27.03333,45.21667],"type":"Point"}
}