{
  "type": "Feature",
  "properties": {
    "gn:admin1_code":"26",
    "gn:admin2_code":"110820.0",
    "gn:asciiname":"Magheru",
    "gn:cc2":"RO",
    "gn:country_code":"RO",
    "gn:dem":112,
    "gn:feature_class":"P",
    "gn:feature_code":"PPL",
    "gn:name":"Magheru",
    "gn:population":877,
    "gn:timezone":"Europe/Bucharest",
    "iso:country":"RO",
    "name:und_x_variant":[
        "Mageru",
        "Magheru"
    ],
    "wof:name":"Magheru",
    "wof:placetype":"locality",
    "wof:population":877
},
  "geometry": {"coordinates":[22.63102,44.65467],"type":"Point"}
}