{
  "type": "Feature",
  "properties": {
    "gn:admin1_code":"03",
    "gn:admin2_code":"15313.0",
    "gn:asciiname":"Valea Magurei",
    "gn:country_code":"RO",
    "gn:dem":459,
    "gn:feature_class":"P",
    "gn:feature_code":"PPL",
    "gn:name":"Valea M\u0103gurei",
    "gn:population":163,
    "gn:timezone":"Europe/Bucharest",
    "iso:country":"RO",
    "wof:name":"Valea Magurei",
    "wof:placetype":"locality",
    "wof:population":163
},
  "geometry": {"coordinates":[24.5562,45.19457],"type":"Point"}
}