{
  "type": "Feature",
  "properties": {
    "gn:admin1_code":"29",
    "gn:admin2_code":"125873",
    "gn:asciiname":"Bechet",
    "gn:cc2":"RO",
    "gn:country_code":"RO",
    "gn:dem":165,
    "gn:feature_class":"P",
    "gn:feature_code":"PPL",
    "gn:name":"Bechet",
    "gn:population":424,
    "gn:timezone":"Europe/Bucharest",
    "iso:country":"RO",
    "name:bul_x_preferred":[
        "\u0411\u0435\u043a\u0435\u0442"
    ],
    "name:ceb_x_preferred":[
        "Ora\u0219 Bechet"
    ],
    "name:deu_x_preferred":[
        "Bechet"
    ],
    "name:est_x_preferred":[
        "Bechet"
    ],
    "name:fas_x_preferred":[
        "\u0628\u06a9\u0647"
    ],
    "name:fra_x_preferred":[
        "Bechet"
    ],
    "name:hun_x_preferred":[
        "Bechet"
    ],
    "name:ita_x_preferred":[
        "Bechet"
    ],
    "name:kor_x_preferred":[
        "\ubca0\ucf00\ud2b8"
    ],
    "name:lat_x_preferred":[
        "Bechet"
    ],
    "name:lit_x_preferred":[
        "Beketas"
    ],
    "name:msa_x_preferred":[
        "Bechet"
    ],
    "name:nld_x_preferred":[
        "Bechet"
    ],
    "name:pol_x_preferred":[
        "Bechet"
    ],
    "name:ron_x_preferred":[
        "Bechet"
    ],
    "name:rus_x_preferred":[
        "\u0411\u0435\u043a\u0435\u0442"
    ],
    "name:spa_x_preferred":[
        "Bechet"
    ],
    "name:srp_x_preferred":[
        "\u041e\u043f\u0448\u0442\u0438\u043d\u0430 \u0411\u0435\u043a\u0435\u0442"
    ],
    "name:ukr_x_preferred":[
        "\u0411\u0435\u043a\u0435\u0442"
    ],
    "name:und_x_variant":[
        "Bechetu"
    ],
    "name:vie_x_preferred":[
        "Bechet"
    ],
    "name:zho_x_preferred":[
        "\u8c9d\u51f1\u7279"
    ],
    "wof:name":"Bechet",
    "wof:placetype":"locality",
    "wof:population":424
},
  "geometry": {"coordinates":[24.17959,44.39472],"type":"Point"}
}