{
  "type": "Feature",
  "properties": {
    "gn:admin1_code":"29",
    "gn:admin2_code":"125873",
    "gn:asciiname":"Bechet",
    "gn:cc2":"RO",
    "gn:country_code":"RO",
    "gn:dem":165,
    "gn:feature_class":"P",
    "gn:feature_code":"PPL",
    "gn:name":"Bechet",
    "gn:population":424,
    "gn:timezone":"Europe/Bucharest",
    "iso:country":"RO",
    "name:und_x_variant":[
        "Bechetu"
    ],
    "wof:name":"Bechet",
    "wof:placetype":"locality",
    "wof:population":424
},
  "geometry": {"coordinates":[24.17959,44.39472],"type":"Point"}
}