{
  "type": "Feature",
  "properties": {
    "gn:admin1_code":"01",
    "gn:admin2_code":"5826.0",
    "gn:asciiname":"Valea Tupilor",
    "gn:country_code":"RO",
    "gn:dem":834,
    "gn:feature_class":"P",
    "gn:feature_code":"PPL",
    "gn:name":"Valea \u021aupilor",
    "gn:population":69,
    "gn:timezone":"Europe/Bucharest",
    "iso:country":"RO",
    "wof:name":"Valea Tupilor",
    "wof:placetype":"locality",
    "wof:population":69
},
  "geometry": {"coordinates":[23.26362,46.26334],"type":"Point"}
}