{
  "type": "Feature",
  "properties": {
    "gn:admin1_code":"40",
    "gn:admin2_code":"178894.0",
    "gn:asciiname":"Schitu",
    "gn:country_code":"RO",
    "gn:dem":83,
    "gn:feature_class":"P",
    "gn:feature_code":"PPL",
    "gn:name":"Schitu",
    "gn:population":0,
    "gn:timezone":"Europe/Bucharest",
    "iso:country":"RO",
    "name:ceb_x_preferred":[
        "Schitu"
    ],
    "name:deu_x_preferred":[
        "Schitu"
    ],
    "name:ita_x_preferred":[
        "Schitu"
    ],
    "name:nld_x_preferred":[
        "Schitu"
    ],
    "name:ron_x_preferred":[
        "Schitu"
    ],
    "name:und_x_variant":[
        "Schitu-Sihas",
        "Schitu"
    ],
    "name:vol_x_preferred":[
        "Schitu"
    ],
    "wof:name":"Schitu",
    "wof:placetype":"locality"
},
  "geometry": {"coordinates":[27.26667,46.06667],"type":"Point"}
}