{
  "type": "Feature",
  "properties": {
    "gn:admin1_code":"16",
    "gn:admin2_code":"66857.0",
    "gn:asciiname":"Moara din Groapa",
    "gn:country_code":"RO",
    "gn:dem":142,
    "gn:feature_class":"P",
    "gn:feature_code":"PPL",
    "gn:name":"Moara din Groap\u0103",
    "gn:population":206,
    "gn:timezone":"Europe/Bucharest",
    "iso:country":"RO",
    "wof:name":"Moara din Groapa",
    "wof:placetype":"locality",
    "wof:population":206
},
  "geometry": {"coordinates":[25.47445,44.5346],"type":"Point"}
}