{
  "type": "Feature",
  "properties": {
    "gn:admin1_code":"34",
    "gn:admin2_code":"151488.0",
    "gn:asciiname":"Spataresti",
    "gn:cc2":"RO",
    "gn:country_code":"RO",
    "gn:dem":403,
    "gn:feature_class":"P",
    "gn:feature_code":"PPL",
    "gn:name":"Sp\u0103t\u0103re\u0219ti",
    "gn:population":373,
    "gn:timezone":"Europe/Bucharest",
    "iso:country":"RO",
    "name:und_x_variant":[
        "Sp\u0103l\u0103re\u015fti",
        "Sp\u0103t\u0103re\u015fti"
    ],
    "wof:name":"Spataresti",
    "wof:placetype":"locality",
    "wof:population":373
},
  "geometry": {"coordinates":[26.30653,47.42916],"type":"Point"}
}