{
  "type": "Feature",
  "properties": {
    "gn:admin1_code":"38",
    "gn:admin2_code":"163137.0",
    "gn:asciiname":"Puntiseni",
    "gn:cc2":"RO",
    "gn:country_code":"RO",
    "gn:dem":207,
    "gn:feature_class":"P",
    "gn:feature_code":"PPL",
    "gn:name":"Punti\u0219eni",
    "gn:population":349,
    "gn:timezone":"Europe/Bucharest",
    "iso:country":"RO",
    "name:und_x_variant":[
        "Punti\u015fcni",
        "Punti\u015feni"
    ],
    "wof:name":"Puntiseni",
    "wof:placetype":"locality",
    "wof:population":349
},
  "geometry": {"coordinates":[27.76615,46.47838],"type":"Point"}
}