{
  "type": "Feature",
  "properties": {
    "gn:admin1_code":"08",
    "gn:admin2_code":"42968.0",
    "gn:asciiname":"Movilele",
    "gn:country_code":"RO",
    "gn:dem":50,
    "gn:feature_class":"P",
    "gn:feature_code":"PPL",
    "gn:name":"Movilele",
    "gn:population":0,
    "gn:timezone":"Europe/Bucharest",
    "iso:country":"RO",
    "wof:name":"Movilele",
    "wof:placetype":"locality"
},
  "geometry": {"coordinates":[27.25,44.81667],"type":"Point"}
}