{
  "type": "Feature",
  "properties": {
    "gn:admin1_code":"40",
    "gn:admin2_code":"176338.0",
    "gn:asciiname":"Sesu cu Plopi",
    "gn:country_code":"RO",
    "gn:dem":192,
    "gn:feature_class":"P",
    "gn:feature_code":"PPL",
    "gn:name":"\u015eesu cu Plopi",
    "gn:population":0,
    "gn:timezone":"Europe/Bucharest",
    "iso:country":"RO",
    "wof:lang_x_official":[
        "ron"
    ],
    "wof:lang_x_spoken":[
        "ron"
    ],
    "wof:name":"Sesu cu Plopi",
    "wof:placetype":"locality"
},
  "geometry": {"coordinates":[26.96667,45.63333],"type":"Point"}
}