{
  "type": "Feature",
  "properties": {
    "gn:admin1_code":"34",
    "gn:admin2_code":"146432.0",
    "gn:asciiname":"Conacu",
    "gn:country_code":"RO",
    "gn:dem":307,
    "gn:feature_class":"P",
    "gn:feature_code":"PPL",
    "gn:name":"Conacu",
    "gn:population":0,
    "gn:timezone":"Europe/Bucharest",
    "iso:country":"RO",
    "wof:name":"Conacu",
    "wof:placetype":"locality"
},
  "geometry": {"coordinates":[26.23333,47.65],"type":"Point"}
}