{
  "type": "Feature",
  "properties": {
    "gn:admin1_code":"03",
    "gn:admin2_code":"19338.0",
    "gn:asciiname":"Valea Manastirii",
    "gn:country_code":"RO",
    "gn:dem":408,
    "gn:feature_class":"P",
    "gn:feature_code":"PPL",
    "gn:name":"Valea M\u0103n\u0103stirii",
    "gn:population":850,
    "gn:timezone":"Europe/Bucharest",
    "iso:country":"RO",
    "wof:name":"Valea Manastirii",
    "wof:placetype":"locality",
    "wof:population":850
},
  "geometry": {"coordinates":[25.0123,45.0256],"type":"Point"}
}