{
  "type": "Feature",
  "properties": {
    "gn:admin1_code":"22",
    "gn:admin2_code":"92765.0",
    "gn:asciiname":"Tandarei-Gara",
    "gn:country_code":"RO",
    "gn:dem":18,
    "gn:feature_class":"P",
    "gn:feature_code":"PPL",
    "gn:name":"\u0162\u0103nd\u0103rei-Gar\u0103",
    "gn:population":0,
    "gn:timezone":"Europe/Bucharest",
    "iso:country":"RO",
    "wof:name":"Tandarei-Gara",
    "wof:placetype":"locality"
},
  "geometry": {"coordinates":[27.65,44.65],"type":"Point"}
}