{
  "type": "Feature",
  "properties": {
    "gn:admin1_code":"29",
    "gn:admin2_code":"127493.0",
    "gn:asciiname":"Malu Rosu",
    "gn:cc2":"RO",
    "gn:country_code":"RO",
    "gn:dem":97,
    "gn:feature_class":"P",
    "gn:feature_code":"PPL",
    "gn:name":"Malu Ro\u0219u",
    "gn:population":186,
    "gn:timezone":"Europe/Bucharest",
    "iso:country":"RO",
    "name:und_x_variant":[
        "Malul Ro\u015fu",
        "Malu Ro\u015fu"
    ],
    "wof:name":"Malu Rosu",
    "wof:placetype":"locality",
    "wof:population":186
},
  "geometry": {"coordinates":[24.44507,44.24609],"type":"Point"}
}