{
  "type": "Feature",
  "properties": {
    "gn:admin1_code":"36",
    "gn:admin2_code":"155840.0",
    "gn:asciiname":"Cladova",
    "gn:cc2":"RO",
    "gn:country_code":"RO",
    "gn:dem":146,
    "gn:feature_class":"P",
    "gn:feature_code":"PPL",
    "gn:name":"Cladova",
    "gn:population":537,
    "gn:timezone":"Europe/Bucharest",
    "iso:country":"RO",
    "name:und_x_variant":[
        "Kladova",
        "B\u00e9gakalodva",
        "Cladova"
    ],
    "wof:name":"Cladova",
    "wof:placetype":"locality",
    "wof:population":537
},
  "geometry": {"coordinates":[21.97198,45.86438],"type":"Point"}
}