{
  "type": "Feature",
  "properties": {
    "gn:admin1_code":"36",
    "gn:admin2_code":"155840.0",
    "gn:asciiname":"Cladova",
    "gn:cc2":"RO",
    "gn:country_code":"RO",
    "gn:dem":146,
    "gn:feature_class":"P",
    "gn:feature_code":"PPL",
    "gn:name":"Cladova",
    "gn:population":537,
    "gn:timezone":"Europe/Bucharest",
    "iso:country":"RO",
    "name:ceb_x_preferred":[
        "Cladova"
    ],
    "name:deu_x_preferred":[
        "Cladova"
    ],
    "name:epo_x_preferred":[
        "Cladova"
    ],
    "name:hun_x_preferred":[
        "Cladova"
    ],
    "name:ron_x_preferred":[
        "Cladova"
    ],
    "name:srp_x_preferred":[
        "\u041a\u043b\u0430\u0434\u043e\u0432\u0430"
    ],
    "name:und_x_variant":[
        "Kladova",
        "B\u00e9gakalodva"
    ],
    "wof:name":"Cladova",
    "wof:placetype":"locality",
    "wof:population":537
},
  "geometry": {"coordinates":[21.97198,45.86438],"type":"Point"}
}