{
  "type": "Feature",
  "properties": {
    "gn:admin1_code":"39",
    "gn:admin2_code":"169681.0",
    "gn:asciiname":"Rusanesti",
    "gn:country_code":"RO",
    "gn:dem":217,
    "gn:feature_class":"P",
    "gn:feature_code":"PPL",
    "gn:name":"Rus\u0103ne\u0219ti",
    "gn:population":459,
    "gn:timezone":"Europe/Bucharest",
    "iso:country":"RO",
    "wof:name":"Rusanesti",
    "wof:placetype":"locality",
    "wof:population":459
},
  "geometry": {"coordinates":[23.98344,44.72247],"type":"Point"}
}