{
  "type": "Feature",
  "properties": {
    "gn:admin1_code":"01",
    "gn:admin2_code":"5577.0",
    "gn:asciiname":"Presaca Ampoiului",
    "gn:cc2":"RO",
    "gn:country_code":"RO",
    "gn:dem":353,
    "gn:feature_class":"P",
    "gn:feature_code":"PPL",
    "gn:name":"Presaca Ampoiului",
    "gn:population":464,
    "gn:timezone":"Europe/Bucharest",
    "iso:country":"RO",
    "name:und_x_variant":[
        "Prisaca-Ampoiului",
        "Presaca Ampoiului"
    ],
    "wof:name":"Presaca Ampoiului",
    "wof:placetype":"locality",
    "wof:population":464
},
  "geometry": {"coordinates":[23.32987,46.09681],"type":"Point"}
}