{
  "type": "Feature",
  "properties": {
    "gn:admin1_code":"30",
    "gn:admin2_code":"134942.0",
    "gn:asciiname":"Puchenii Mici",
    "gn:country_code":"RO",
    "gn:dem":112,
    "gn:feature_class":"P",
    "gn:feature_code":"PPL",
    "gn:name":"Puchenii Mici",
    "gn:population":559,
    "gn:timezone":"Europe/Bucharest",
    "iso:country":"RO",
    "wof:name":"Puchenii Mici",
    "wof:placetype":"locality",
    "wof:population":559
},
  "geometry": {"coordinates":[26.05164,44.82882],"type":"Point"}
}