{
  "type": "Feature",
  "properties": {
    "gn:admin1_code":"01",
    "gn:admin2_code":"7446.0",
    "gn:asciiname":"Toci",
    "gn:country_code":"RO",
    "gn:dem":842,
    "gn:feature_class":"P",
    "gn:feature_code":"PPL",
    "gn:name":"Toci",
    "gn:population":14,
    "gn:timezone":"Europe/Bucharest",
    "iso:country":"RO",
    "name:fas_x_preferred":[
        "\u062a\u0648\u0633\u06cc"
    ],
    "name:fra_x_preferred":[
        "Toci"
    ],
    "name:hrv_x_preferred":[
        "Tosi"
    ],
    "name:ita_x_preferred":[
        "Teteoinnan"
    ],
    "name:pol_x_preferred":[
        "Toci"
    ],
    "name:por_x_preferred":[
        "Toci"
    ],
    "name:rus_x_preferred":[
        "\u0422\u043e\u0441\u0438"
    ],
    "name:sco_x_preferred":[
        "Toci"
    ],
    "name:spa_x_preferred":[
        "Toci"
    ],
    "name:swe_x_preferred":[
        "Toci"
    ],
    "wof:name":"Toci",
    "wof:placetype":"locality",
    "wof:population":14
},
  "geometry": {"coordinates":[22.97945,46.29439],"type":"Point"}
}