{
  "type": "Feature",
  "properties": {
    "gn:admin1_code":"39",
    "gn:admin2_code":"173132.0",
    "gn:asciiname":"Suiesti",
    "gn:country_code":"RO",
    "gn:dem":367,
    "gn:feature_class":"P",
    "gn:feature_code":"PPL",
    "gn:name":"Suie\u0219ti",
    "gn:population":79,
    "gn:timezone":"Europe/Bucharest",
    "iso:country":"RO",
    "wof:name":"Suiesti",
    "wof:placetype":"locality",
    "wof:population":79
},
  "geometry": {"coordinates":[24.06667,44.86667],"type":"Point"}
}