{
  "type": "Feature",
  "properties": {
    "gn:admin1_code":"38",
    "gn:admin2_code":"167071.0",
    "gn:asciiname":"Uncesti",
    "gn:country_code":"RO",
    "gn:dem":185,
    "gn:feature_class":"P",
    "gn:feature_code":"PPL",
    "gn:name":"Unce\u0219ti",
    "gn:population":256,
    "gn:timezone":"Europe/Bucharest",
    "iso:country":"RO",
    "wof:name":"Uncesti",
    "wof:placetype":"locality",
    "wof:population":256
},
  "geometry": {"coordinates":[27.60047,46.79884000000001],"type":"Point"}
}