{
  "type": "Feature",
  "properties": {
    "gn:admin1_code":"30",
    "gn:admin2_code":"134559.0",
    "gn:asciiname":"Poienarii Vechi",
    "gn:cc2":"RO",
    "gn:country_code":"RO",
    "gn:dem":106,
    "gn:feature_class":"P",
    "gn:feature_code":"PPL",
    "gn:name":"Poienarii Vechi",
    "gn:population":131,
    "gn:timezone":"Europe/Bucharest",
    "iso:country":"RO",
    "name:und_x_variant":[
        "Poenarii Vechi",
        "Poenari Vechi"
    ],
    "wof:name":"Poienarii Vechi",
    "wof:placetype":"locality",
    "wof:population":131
},
  "geometry": {"coordinates":[26.06585,44.75291],"type":"Point"}
}