{
  "type": "Feature",
  "properties": {
    "gn:admin1_code":"28",
    "gn:admin2_code":"124331.0",
    "gn:asciiname":"Vladnicele",
    "gn:country_code":"RO",
    "gn:dem":306,
    "gn:feature_class":"P",
    "gn:feature_code":"PPL",
    "gn:name":"Vl\u0103dnicele",
    "gn:population":107,
    "gn:timezone":"Europe/Bucharest",
    "iso:country":"RO",
    "wof:name":"Vladnicele",
    "wof:placetype":"locality",
    "wof:population":107
},
  "geometry": {"coordinates":[27.16202,46.99806],"type":"Point"}
}