{
  "type": "Feature",
  "properties": {
    "iso:country":"RO",
    "name:rum_x_preferred":[
        "Blaj-Sat"
    ],
    "name:unk_x_variant":[
        "Blaj-Sat"
    ],
    "qs:gn_adm0_cc":"RO",
    "qs:gn_fcode":"PPLX",
    "qs:gn_local":684612,
    "qs:gn_nam_loc":"Blaj, Alba, RO",
    "qs:gn_namadm1":"00",
    "qs:gn_name":"Blaj-Sat",
    "qs:local_max":48,
    "qs:local_sum":48,
    "qs:localhoods":1,
    "qs:name":"Blaj-Sat",
    "qs:name_adm0":"Rom\u00e2nia",
    "qs:name_adm1":"Alba",
    "qs:name_local":"Blaj",
    "qs:photo_max":14,
    "qs:photo_sum":48,
    "qs:placetype":"Suburb",
    "qs:quad_count":14,
    "qs:woe_adm0":23424933,
    "qs:woe_adm1":2346615,
    "qs:woe_adm2":0,
    "qs:woe_lau":0,
    "qs:woe_local":867463,
    "qs:woe_ver":"7.10.0",
    "wof:lang":[
        "rum"
    ],
    "wof:name":"Blaj-Sat",
    "wof:placetype":"neighbourhood"
},
  "geometry": {"coordinates":[23.919411,46.178088],"type":"Point"}
}