{
  "type": "Feature",
  "properties": {
    "gn:admin1_code":"20",
    "gn:admin2_code":"84923.0",
    "gn:asciiname":"Ghipes",
    "gn:cc2":"RO",
    "gn:country_code":"RO",
    "gn:dem":573,
    "gn:feature_class":"P",
    "gn:feature_code":"PPL",
    "gn:name":"Ghipe\u0219",
    "gn:population":176,
    "gn:timezone":"Europe/Bucharest",
    "iso:country":"RO",
    "name:und_x_variant":[
        "Gyepes",
        "Ghipe\u015f"
    ],
    "wof:name":"Ghipes",
    "wof:placetype":"locality",
    "wof:population":176
},
  "geometry": {"coordinates":[25.40459,46.26167],"type":"Point"}
}