{
  "type": "Feature",
  "properties": {
    "gn:admin1_code":"21",
    "gn:admin2_code":"91795",
    "gn:asciiname":"Brotuna",
    "gn:country_code":"RO",
    "gn:dem":241,
    "gn:feature_class":"P",
    "gn:feature_code":"PPL",
    "gn:name":"Brotuna",
    "gn:population":312,
    "gn:timezone":"Europe/Bucharest",
    "iso:country":"RO",
    "wof:name":"Brotuna",
    "wof:placetype":"locality",
    "wof:population":312
},
  "geometry": {"coordinates":[22.60554,46.19884],"type":"Point"}
}