{
  "type": "Feature",
  "properties": {
    "gn:admin1_code":"01",
    "gn:admin2_code":"7384.0",
    "gn:asciiname":"Totoi",
    "gn:cc2":"RO",
    "gn:country_code":"RO",
    "gn:dem":223,
    "gn:feature_class":"P",
    "gn:feature_code":"PPL",
    "gn:name":"Totoi",
    "gn:population":561,
    "gn:timezone":"Europe/Bucharest",
    "iso:country":"RO",
    "name:und_x_variant":[
        "Totoiul",
        "Totoiu"
    ],
    "wof:name":"Totoi",
    "wof:placetype":"locality",
    "wof:population":561
},
  "geometry": {"coordinates":[23.65759,46.11491],"type":"Point"}
}