{
  "type": "Feature",
  "properties": {
    "gn:admin1_code":"05",
    "gn:admin2_code":"29038.0",
    "gn:asciiname":"Sacalasau",
    "gn:cc2":"RO",
    "gn:country_code":"RO",
    "gn:dem":170,
    "gn:feature_class":"P",
    "gn:feature_code":"PPL",
    "gn:name":"Sacalas\u0103u",
    "gn:population":786,
    "gn:timezone":"Europe/Bucharest",
    "iso:country":"RO",
    "name:und_x_variant":[
        "Sacala\u015fu",
        "S\u0103c\u0103l\u0103\u015f\u0103u Vechi",
        "S\u0103c\u0103l\u0103\u015f\u0103u"
    ],
    "wof:name":"Sacalasau",
    "wof:placetype":"locality",
    "wof:population":786
},
  "geometry": {"coordinates":[22.28625,47.1968],"type":"Point"}
}