{
  "type": "Feature",
  "properties": {
    "gn:admin1_code":"09",
    "gn:admin2_code":"41248.0",
    "gn:asciiname":"Mercheasa",
    "gn:country_code":"RO",
    "gn:dem":468,
    "gn:feature_class":"P",
    "gn:feature_code":"PPL",
    "gn:name":"Merchea\u0219a",
    "gn:population":501,
    "gn:timezone":"Europe/Bucharest",
    "iso:country":"RO",
    "wof:name":"Mercheasa",
    "wof:placetype":"locality",
    "wof:population":501
},
  "geometry": {"coordinates":[25.33619,46.06661],"type":"Point"}
}