{
  "type": "Feature",
  "properties": {
    "gn:admin1_code":"37",
    "gn:admin2_code":"161231.0",
    "gn:asciiname":"Ivancea Mare",
    "gn:country_code":"RO",
    "gn:dem":0,
    "gn:feature_class":"P",
    "gn:feature_code":"PPL",
    "gn:name":"Ivancea Mare",
    "gn:population":0,
    "gn:timezone":"Europe/Bucharest",
    "iso:country":"RO",
    "wof:name":"Ivancea Mare",
    "wof:placetype":"locality"
},
  "geometry": {"coordinates":[29.46667,44.96667],"type":"Point"}
}