{
  "type": "Feature",
  "properties": {
    "gn:admin1_code":"19",
    "gn:admin2_code":"82779.0",
    "gn:asciiname":"Carciu",
    "gn:cc2":"RO",
    "gn:country_code":"RO",
    "gn:dem":190,
    "gn:feature_class":"P",
    "gn:feature_code":"PPL",
    "gn:name":"C\u00e2rciu",
    "gn:population":370,
    "gn:timezone":"Europe/Bucharest",
    "iso:country":"RO",
    "name:und_x_variant":[
        "C\u00e2rciul",
        "C\u00eerciu"
    ],
    "wof:name":"Carciu",
    "wof:placetype":"locality",
    "wof:population":370
},
  "geometry": {"coordinates":[23.05942000000001,44.74028],"type":"Point"}
}