{
  "type": "Feature",
  "properties": {
    "gn:admin1_code":"09",
    "gn:admin2_code":"41738.0",
    "gn:asciiname":"Gura Vaii",
    "gn:cc2":"RO",
    "gn:country_code":"RO",
    "gn:dem":555,
    "gn:feature_class":"P",
    "gn:feature_code":"PPL",
    "gn:name":"Gura V\u0103ii",
    "gn:population":451,
    "gn:timezone":"Europe/Bucharest",
    "iso:country":"RO",
    "name:und_x_variant":[
        "Netotu",
        "Netot",
        "Netotul",
        "Gura V\u0103ii"
    ],
    "wof:name":"Gura Vaii",
    "wof:placetype":"locality",
    "wof:population":451
},
  "geometry": {"coordinates":[24.90477000000001,45.72871],"type":"Point"}
}