{
  "type": "Feature",
  "properties": {
    "gn:gn_country":"RO",
    "gn:gn_fcode":"PPLA2",
    "gn:gn_pop":787,
    "gn:population":787,
    "iso:country":"RO",
    "name:ceb_x_preferred":[
        "C\u00e2rji\u021bi"
    ],
    "name:eng_x_preferred":[
        "C\u00e2rji\u021bi"
    ],
    "name:fra_x_preferred":[
        "C\u00e2rji\u021bi"
    ],
    "name:hun_x_preferred":[
        "Kersec"
    ],
    "name:ita_x_preferred":[
        "C\u00e2rji\u021bi"
    ],
    "name:nld_x_preferred":[
        "C\u00e2rji\u021bi"
    ],
    "name:ron_x_preferred":[
        "C\u00e2rji\u021bi"
    ],
    "name:srp_x_preferred":[
        "\u041a\u0430\u0440\u0436\u0438\u0446\u0438"
    ],
    "name:ukr_x_preferred":[
        "\u041a\u0438\u0440\u0436\u0438\u0446\u044c"
    ],
    "name:unk_x_variant":[
        "C\u00e2rjiti"
    ],
    "qs_pg:aaroncc":"RO",
    "qs_pg:gn_country":"RO",
    "qs_pg:gn_fcode":"PPLA2",
    "qs_pg:gn_pop":787,
    "qs_pg:name":"C\u00e2rji\u0163i",
    "qs_pg:photos_9r":0,
    "qs_pg:photos_sr":0,
    "qs_pg:pop_sr":2,
    "qs_pg:qs_pg_placetype":"locality",
    "wof:name":"C\u00e2rji\u0163i",
    "wof:placetype":"locality",
    "wof:population":787
},
  "geometry": {"coordinates":[22.83333,45.85],"type":"Point"}
}