{
  "type": "Feature",
  "properties": {
    "gn:admin1_code":"22",
    "gn:admin2_code":"92836.0",
    "gn:asciiname":"Motalva",
    "gn:cc2":"RO",
    "gn:country_code":"RO",
    "gn:dem":41,
    "gn:feature_class":"P",
    "gn:feature_code":"PPL",
    "gn:name":"Mot\u00e2lva",
    "gn:population":0,
    "gn:timezone":"Europe/Bucharest",
    "iso:country":"RO",
    "name:und_x_variant":[
        "Mot\u00e2lva",
        "Mot\u00eelva"
    ],
    "wof:lang_x_official":[
        "ron"
    ],
    "wof:lang_x_spoken":[
        "ron"
    ],
    "wof:name":"Motalva",
    "wof:placetype":"locality"
},
  "geometry": {"coordinates":[27.28333,44.63333],"type":"Point"}
}