{
  "type": "Feature",
  "properties": {
    "gn:admin1_code":"13",
    "gn:admin2_code":"59764.0",
    "gn:asciiname":"Micesti",
    "gn:cc2":"RO",
    "gn:country_code":"RO",
    "gn:dem":557,
    "gn:feature_class":"P",
    "gn:feature_code":"PPL",
    "gn:name":"Mice\u0219ti",
    "gn:population":560,
    "gn:timezone":"Europe/Bucharest",
    "iso:country":"RO",
    "name:hun_x_preferred":[
        "Kaszoly"
    ],
    "name:und_x_variant":[
        "Micu\u015f",
        "Mice\u015fti"
    ],
    "wof:name":"Micesti",
    "wof:placetype":"locality",
    "wof:population":560
},
  "geometry": {"coordinates":[23.61775,46.64261],"type":"Point"}
}