{
  "type": "Feature",
  "properties": {
    "gn:gn_country":"RO",
    "gn:gn_fcode":"PPL",
    "gn:gn_pop":5170,
    "gn:population":1482,
    "iso:country":"RO",
    "name:alb_x_preferred":[
        "Giri\u0219u de Cri\u0219"
    ],
    "name:dut_x_preferred":[
        "Giri\u0219u de Cri\u0219"
    ],
    "name:eng_x_preferred":[
        "Giri\u0219u de Cri\u0219"
    ],
    "name:epo_x_preferred":[
        "Giri\u0219u de Cri\u0219"
    ],
    "name:fre_x_preferred":[
        "Giri\u0219u de Cri\u0219"
    ],
    "name:ger_x_preferred":[
        "Giri\u0219u de Cri\u0219"
    ],
    "name:hun_x_preferred":[
        "K\u00f6r\u00f6sgy\u00e9res"
    ],
    "name:ita_x_preferred":[
        "Giri\u0219u de Cri\u0219"
    ],
    "name:may_x_preferred":[
        "Giri\u0219u de Cri\u0219"
    ],
    "name:por_x_preferred":[
        "Giri\u0219u de Cri\u0219"
    ],
    "name:rum_x_preferred":[
        "Giri\u0219u de Cri\u0219"
    ],
    "name:ukr_x_preferred":[
        "\u0414\u0436\u0438\u0440\u0456\u0448\u0443-\u0434\u0435-\u041a\u0440\u0456\u0448"
    ],
    "name:unk_x_variant":[
        "Giri\u015ful-de-Cri\u015f"
    ],
    "name:vie_x_preferred":[
        "Girisu de Cris"
    ],
    "name:vol_x_preferred":[
        "Giri\u0219u de Cri\u0219"
    ],
    "qs_pg:aaroncc":"RO",
    "qs_pg:gn_country":"RO",
    "qs_pg:gn_fcode":"PPL",
    "qs_pg:gn_pop":5170,
    "qs_pg:name":"Giri\u015fu de Cri\u015f / K\u0151r\u00f6sgy\u00edres",
    "qs_pg:photos_9r":0,
    "qs_pg:photos_sr":0,
    "qs_pg:pop_sr":5,
    "qs_pg:qs_pg_placetype":"locality",
    "wof:name":"Giri\u015fu de Cri\u015f / K\u0151r\u00f6sgy\u00edres",
    "wof:placetype":"locality",
    "wof:population":1482
},
  "geometry": {"coordinates":[21.76108,47.06416],"type":"Point"}
}