{
  "type": "Feature",
  "properties": {
    "gn:admin1_code":"01",
    "gn:admin2_code":"8229.0",
    "gn:asciiname":"Popestii de Sus",
    "gn:country_code":"RO",
    "gn:dem":760,
    "gn:feature_class":"P",
    "gn:feature_code":"PPL",
    "gn:name":"Pope\u0219tii de Sus",
    "gn:population":159,
    "gn:timezone":"Europe/Bucharest",
    "iso:country":"RO",
    "wof:name":"Popestii de Sus",
    "wof:placetype":"locality",
    "wof:population":159
},
  "geometry": {"coordinates":[22.93835,46.41449],"type":"Point"}
}