{
  "type": "Feature",
  "properties": {
    "gn:admin1_code":"02",
    "gn:admin2_code":"10104.0",
    "gn:asciiname":"Monorostia",
    "gn:country_code":"RO",
    "gn:dem":148,
    "gn:feature_class":"P",
    "gn:feature_code":"PPL",
    "gn:name":"Monoro\u0219tia",
    "gn:population":292,
    "gn:timezone":"Europe/Bucharest",
    "iso:country":"RO",
    "name:ron_x_preferred":[
        "Monoro\u0219tia"
    ],
    "name:und_x_variant":[
        "Monaro\u015ftia",
        "Monorostia",
        "Monorostya",
        "Marosmonyor\u00f3"
    ],
    "wof:name":"Monorostia",
    "wof:placetype":"locality",
    "wof:population":292
},
  "geometry": {"coordinates":[22.01378,46.10476],"type":"Point"}
}