{
  "type": "Feature",
  "properties": {
    "gn:admin1_code":"33",
    "gn:admin2_code":"144232.0",
    "gn:asciiname":"Vecerd",
    "gn:cc2":"RO",
    "gn:country_code":"RO",
    "gn:dem":438,
    "gn:feature_class":"P",
    "gn:feature_code":"PPL",
    "gn:name":"Vecerd",
    "gn:population":161,
    "gn:timezone":"Europe/Bucharest",
    "iso:country":"RO",
    "name:und_x_variant":[
        "Veceru",
        "Vecerd"
    ],
    "wof:name":"Vecerd",
    "wof:placetype":"locality",
    "wof:population":161
},
  "geometry": {"coordinates":[24.45549,45.98401],"type":"Point"}
}