{
  "type": "Feature",
  "properties": {
    "gn:country":"RO",
    "gn:fcode":"PPLA2",
    "gn:population":3667,
    "iso:country":"RO",
    "name:ceb_x_preferred":[
        "George Enescu"
    ],
    "name:dan_x_preferred":[
        "George Enescu"
    ],
    "name:deu_x_preferred":[
        "George Enescu"
    ],
    "name:eng_x_preferred":[
        "George Enescu"
    ],
    "name:fra_x_preferred":[
        "George Enescu"
    ],
    "name:hun_x_preferred":[
        "George Enescu"
    ],
    "name:hye_x_preferred":[
        "\u054b\u0578\u0580\u057b\u0565 \u0537\u0576\u0565\u057d\u056f\u0578\u0582"
    ],
    "name:ita_x_preferred":[
        "George Enescu"
    ],
    "name:nld_x_preferred":[
        "George Enescu"
    ],
    "name:por_x_preferred":[
        "George Enescu"
    ],
    "name:ron_x_preferred":[
        "George Enescu"
    ],
    "name:srp_x_preferred":[
        "\u0402\u0435\u043e\u0440\u0452\u0435 \u0415\u043d\u0435\u0441\u043a\u0443"
    ],
    "name:ukr_x_preferred":[
        "\u0414\u0436\u043e\u0440\u0434\u0436\u0435-\u0415\u043d\u0435\u0441\u043a\u0443"
    ],
    "name:und_x_variant":[
        "Liveni V\u00eernav"
    ],
    "name:vol_x_preferred":[
        "George Enescu"
    ],
    "qs_pg:aaroncc":"RO",
    "qs_pg:gn_country":"RO",
    "qs_pg:gn_fcode":"PPLA2",
    "qs_pg:gn_pop":3667,
    "qs_pg:name":"George Enescu",
    "qs_pg:name_adm0":"Rom\u00e2nia",
    "qs_pg:name_adm1":"Botosani",
    "qs_pg:photos_9r":0,
    "qs_pg:photos_sr":0,
    "qs_pg:pop_sr":4,
    "qs_pg:qs_pg_placetype":"locality",
    "qs_pg:qs_pg_placetype_gp":"Town",
    "qs_pg:woe_adm0":23424933,
    "woe:adm0_id":23424933,
    "woe:name_adm0":"Rom\u00e2nia",
    "woe:name_adm1":"Botosani",
    "woe:placetype":"Town",
    "wof:name":"George Enescu",
    "wof:placetype":"locality",
    "wof:population":3667
},
  "geometry": {"coordinates":[26.48333,48.03333],"type":"Point"}
}