{
  "type": "Feature",
  "properties": {
    "gn:admin1_code":"14",
    "gn:admin2_code":"62057.0",
    "gn:asciiname":"Canlia",
    "gn:country_code":"RO",
    "gn:dem":56,
    "gn:feature_class":"P",
    "gn:feature_code":"PPL",
    "gn:name":"Canlia",
    "gn:population":651,
    "gn:timezone":"Europe/Bucharest",
    "iso:country":"RO",
    "wof:name":"Canlia",
    "wof:placetype":"locality",
    "wof:population":651
},
  "geometry": {"coordinates":[27.52933,44.12583],"type":"Point"}
}