{
  "type": "Feature",
  "properties": {
    "gn:admin1_code":"39",
    "gn:admin2_code":"169351.0",
    "gn:asciiname":"Daesti",
    "gn:country_code":"RO",
    "gn:dem":296,
    "gn:feature_class":"P",
    "gn:feature_code":"PPLA2",
    "gn:name":"D\u0103e\u0219ti",
    "gn:population":920,
    "gn:timezone":"Europe/Bucharest",
    "iso:country":"RO",
    "wof:name":"Daesti",
    "wof:placetype":"locality",
    "wof:population":920
},
  "geometry": {"coordinates":[24.38684,45.20107],"type":"Point"}
}