{
  "type": "Feature",
  "properties": {
    "gn:admin1_code":"05",
    "gn:admin2_code":"28335",
    "gn:asciiname":"Bucium",
    "gn:country_code":"RO",
    "gn:dem":174,
    "gn:feature_class":"P",
    "gn:feature_code":"PPL",
    "gn:name":"Bucium",
    "gn:population":279,
    "gn:timezone":"Europe/Bucharest",
    "iso:country":"RO",
    "name:fra_x_preferred":[
        "Bucium"
    ],
    "name:heb_x_preferred":[
        "\u05d1\u05d5\u05e6'\u05d9\u05d5\u05dd"
    ],
    "name:ita_x_preferred":[
        "Bucium"
    ],
    "name:ron_x_preferred":[
        "Bucium"
    ],
    "wof:name":"Bucium",
    "wof:placetype":"locality",
    "wof:population":279
},
  "geometry": {"coordinates":[22.15357,46.87954000000001],"type":"Point"}
}