{
  "type": "Feature",
  "properties": {
    "gn:admin1_code":"05",
    "gn:admin2_code":"28335",
    "gn:asciiname":"Bucium",
    "gn:country_code":"RO",
    "gn:dem":174,
    "gn:feature_class":"P",
    "gn:feature_code":"PPL",
    "gn:name":"Bucium",
    "gn:population":279,
    "gn:timezone":"Europe/Bucharest",
    "iso:country":"RO",
    "wof:name":"Bucium",
    "wof:placetype":"locality",
    "wof:population":279
},
  "geometry": {"coordinates":[22.15357,46.87954000000001],"type":"Point"}
}