{
  "type": "Feature",
  "properties": {
    "gn:gn_country":"RO",
    "gn:gn_fcode":"PPL",
    "gn:gn_pop":2748,
    "gn:population":2748,
    "iso:country":"RO",
    "name:dut_x_preferred":[
        "S\u0103la\u0219u de Sus"
    ],
    "name:eng_x_preferred":[
        "S\u0103la\u0219u de Sus"
    ],
    "name:fre_x_preferred":[
        "S\u0103la\u0219u de Sus"
    ],
    "name:hun_x_preferred":[
        "Fels\u0151sz\u00e1ll\u00e1spatak"
    ],
    "name:ita_x_preferred":[
        "S\u0103la\u0219u de Sus"
    ],
    "name:rum_x_preferred":[
        "S\u0103la\u0219u de Sus"
    ],
    "name:ukr_x_preferred":[
        "\u0421\u0435\u043b\u0430\u0448\u0443-\u0434\u0435-\u0421\u0443\u0441"
    ],
    "name:unk_x_variant":[
        "S\u0103la\u015ful-Superior"
    ],
    "qs_pg:aaroncc":"RO",
    "qs_pg:gn_country":"RO",
    "qs_pg:gn_fcode":"PPL",
    "qs_pg:gn_pop":2748,
    "qs_pg:name":"S\u0103la\u0219u de Sus",
    "qs_pg:name_adm0":"Rom\u00e2nia",
    "qs_pg:name_adm1":"Hunedoara",
    "qs_pg:photos_9k":1,
    "qs_pg:photos_9r":1,
    "qs_pg:photos_all":10,
    "qs_pg:photos_sr":0,
    "qs_pg:pop_sr":4,
    "qs_pg:qs_pg_placetype":"locality",
    "qs_pg:qs_pg_placetype_gp":"Town",
    "qs_pg:woe_adm0":23424933,
    "woe:adm0_id":23424933,
    "woe:name_adm0":"Rom\u00e2nia",
    "woe:name_adm1":"Hunedoara",
    "woe:placetype":"Town",
    "wof:name":"S\u0103la\u0219u de Sus",
    "wof:placetype":"locality",
    "wof:population":2748
},
  "geometry": {"coordinates":[22.95,45.51667],"type":"Point"}
}