{
  "type": "Feature",
  "properties": {
    "gn:admin1_code":"07",
    "gn:admin2_code":"39612.0",
    "gn:asciiname":"Gorovei",
    "gn:cc2":"RO",
    "gn:country_code":"RO",
    "gn:dem":312,
    "gn:feature_class":"P",
    "gn:feature_code":"PPL",
    "gn:name":"Gorovei",
    "gn:population":60,
    "gn:timezone":"Europe/Bucharest",
    "iso:country":"RO",
    "name:und_x_variant":[
        "Gorovei-Schit",
        "Gorovei"
    ],
    "wof:name":"Gorovei",
    "wof:placetype":"locality",
    "wof:population":60
},
  "geometry": {"coordinates":[26.34488,47.87694000000001],"type":"Point"}
}