{
  "type": "Feature",
  "properties": {
    "gn:admin1_code":"05",
    "gn:admin2_code":"30229.0",
    "gn:asciiname":"Hodisel",
    "gn:country_code":"RO",
    "gn:dem":331,
    "gn:feature_class":"P",
    "gn:feature_code":"PPL",
    "gn:name":"Hodi\u0219el",
    "gn:population":462,
    "gn:timezone":"Europe/Bucharest",
    "iso:country":"RO",
    "name:ron_x_preferred":[
        "Hodi\u0219el"
    ],
    "name:und_x_variant":[
        "Pusztahodisel",
        "Pusztah\u00f3dos",
        "Hodosel"
    ],
    "wof:name":"Hodisel",
    "wof:placetype":"locality",
    "wof:population":462
},
  "geometry": {"coordinates":[22.06356,46.64615],"type":"Point"}
}