{
  "type": "Feature",
  "properties": {
    "gn:admin1_code":"39",
    "gn:admin2_code":"171101.0",
    "gn:asciiname":"Zavoieni",
    "gn:country_code":"RO",
    "gn:dem":252,
    "gn:feature_class":"P",
    "gn:feature_code":"PPL",
    "gn:name":"Z\u0103voieni",
    "gn:population":292,
    "gn:timezone":"Europe/Bucharest",
    "iso:country":"RO",
    "wof:name":"Zavoieni",
    "wof:placetype":"locality",
    "wof:population":292
},
  "geometry": {"coordinates":[24.02219,44.77634000000001],"type":"Point"}
}