{
  "type": "Feature",
  "properties": {
    "gn:admin1_code":"03",
    "gn:admin2_code":"19392.0",
    "gn:asciiname":"Chiritesti",
    "gn:country_code":"RO",
    "gn:dem":343,
    "gn:feature_class":"P",
    "gn:feature_code":"PPL",
    "gn:name":"Chiri\u021be\u0219ti",
    "gn:population":181,
    "gn:timezone":"Europe/Bucharest",
    "iso:country":"RO",
    "wof:name":"Chiritesti",
    "wof:placetype":"locality",
    "wof:population":181
},
  "geometry": {"coordinates":[24.59816,44.84278],"type":"Point"}
}