{
  "type": "Feature",
  "properties": {
    "gn:admin1_code":"02",
    "gn:admin2_code":"10765.0",
    "gn:asciiname":"Patars",
    "gn:country_code":"RO",
    "gn:dem":289,
    "gn:feature_class":"P",
    "gn:feature_code":"PPL",
    "gn:name":"P\u0103t\u00e2r\u0219",
    "gn:population":67,
    "gn:timezone":"Europe/Bucharest",
    "iso:country":"RO",
    "name:hun_x_preferred":[
        "Petercse"
    ],
    "name:und_x_variant":[
        "Petirs",
        "Petris",
        "P\u0103t\u00eer\u015f"
    ],
    "wof:name":"Patars",
    "wof:placetype":"locality",
    "wof:population":67
},
  "geometry": {"coordinates":[21.85,45.98333],"type":"Point"}
}