{
  "type": "Feature",
  "properties": {
    "gn:admin1_code":"23",
    "gn:admin2_code":"100219.0",
    "gn:asciiname":"Lungani",
    "gn:country_code":"RO",
    "gn:dem":108,
    "gn:feature_class":"P",
    "gn:feature_code":"PPL",
    "gn:name":"Lungani",
    "gn:population":491,
    "gn:timezone":"Europe/Bucharest",
    "iso:country":"RO",
    "wof:name":"Lungani",
    "wof:placetype":"locality",
    "wof:population":491
},
  "geometry": {"coordinates":[27.40109,47.09402],"type":"Point"}
}