{
  "type": "Feature",
  "properties": {
    "gn:admin1_code":"23",
    "gn:admin2_code":"100219.0",
    "gn:asciiname":"Lungani",
    "gn:country_code":"RO",
    "gn:dem":108,
    "gn:feature_class":"P",
    "gn:feature_code":"PPL",
    "gn:name":"Lungani",
    "gn:population":491,
    "gn:timezone":"Europe/Bucharest",
    "iso:country":"RO",
    "name:ara_x_preferred":[
        "\u0644\u0648\u0646\u063a\u0627\u0646\u064a"
    ],
    "name:ceb_x_preferred":[
        "Comuna Lungani"
    ],
    "name:ita_x_preferred":[
        "Lungani"
    ],
    "name:msa_x_preferred":[
        "Lungani"
    ],
    "name:nld_x_preferred":[
        "Lungani"
    ],
    "name:por_x_preferred":[
        "Lungani"
    ],
    "name:ron_x_preferred":[
        "Comuna Lungani"
    ],
    "name:srp_x_preferred":[
        "\u041e\u043f\u0448\u0442\u0438\u043d\u0430 \u041b\u0443\u043d\u0433\u0430\u043d\u0438"
    ],
    "name:ukr_x_preferred":[
        "\u041b\u0443\u043d\u0433\u0430\u043d\u044c"
    ],
    "name:vie_x_preferred":[
        "Lungani"
    ],
    "name:vol_x_preferred":[
        "Lungani"
    ],
    "name:zho_x_preferred":[
        "\u502b\u52a0\u5c3c\u9109"
    ],
    "wof:name":"Lungani",
    "wof:placetype":"locality",
    "wof:population":491
},
  "geometry": {"coordinates":[27.40109,47.09402],"type":"Point"}
}