{
  "type": "Feature",
  "properties": {
    "gn:admin1_code":"26",
    "gn:admin2_code":"112469.0",
    "gn:asciiname":"Putinei",
    "gn:cc2":"RO",
    "gn:country_code":"RO",
    "gn:dem":80,
    "gn:feature_class":"P",
    "gn:feature_code":"PPL",
    "gn:name":"Pu\u021binei",
    "gn:population":268,
    "gn:timezone":"Europe/Bucharest",
    "iso:country":"RO",
    "name:und_x_variant":[
        "Pucinej",
        "Pu\u0163inei"
    ],
    "wof:name":"Putinei",
    "wof:placetype":"locality",
    "wof:population":268
},
  "geometry": {"coordinates":[22.70323,44.68102],"type":"Point"}
}