{
  "type": "Feature",
  "properties": {
    "gn:admin1_code":"11",
    "gn:admin2_code":"50228",
    "gn:asciiname":"Bodinesti",
    "gn:cc2":"RO",
    "gn:country_code":"RO",
    "gn:dem":333,
    "gn:feature_class":"P",
    "gn:feature_code":"PPL",
    "gn:name":"Bodine\u0219ti",
    "gn:population":97,
    "gn:timezone":"Europe/Bucharest",
    "iso:country":"RO",
    "name:und_x_variant":[
        "Bodine\u015fti",
        "B\u0103dine\u015fti"
    ],
    "wof:name":"Bodinesti",
    "wof:placetype":"locality",
    "wof:population":97
},
  "geometry": {"coordinates":[26.72609000000001,45.46724],"type":"Point"}
}