{
  "type": "Feature",
  "properties": {
    "gn:admin1_code":"17",
    "gn:admin2_code":"74554.0",
    "gn:asciiname":"Urzica Mare",
    "gn:country_code":"RO",
    "gn:dem":53,
    "gn:feature_class":"P",
    "gn:feature_code":"PPL",
    "gn:name":"Urzica Mare",
    "gn:population":630,
    "gn:timezone":"Europe/Bucharest",
    "iso:country":"RO",
    "wof:name":"Urzica Mare",
    "wof:placetype":"locality",
    "wof:population":630
},
  "geometry": {"coordinates":[23.59722,44.01615],"type":"Point"}
}