{
  "type": "Feature",
  "properties": {
    "gn:admin1_code":"39",
    "gn:admin2_code":"172082.0",
    "gn:asciiname":"Ulmetel",
    "gn:country_code":"RO",
    "gn:dem":601,
    "gn:feature_class":"P",
    "gn:feature_code":"PPL",
    "gn:name":"Ulme\u021bel",
    "gn:population":464,
    "gn:timezone":"Europe/Bucharest",
    "iso:country":"RO",
    "wof:name":"Ulmetel",
    "wof:placetype":"locality",
    "wof:population":464
},
  "geometry": {"coordinates":[24.23333,45.11667],"type":"Point"}
}