{
  "type": "Feature",
  "properties": {
    "gn:admin1_code":"13",
    "gn:admin2_code":"56522.0",
    "gn:asciiname":"Fagadau",
    "gn:country_code":"RO",
    "gn:dem":334,
    "gn:feature_class":"P",
    "gn:feature_code":"PPL",
    "gn:name":"F\u0103g\u0103d\u0103u",
    "gn:population":0,
    "gn:timezone":"Europe/Bucharest",
    "iso:country":"RO",
    "wof:lang_x_official":[
        "ron"
    ],
    "wof:lang_x_spoken":[
        "ron"
    ],
    "wof:name":"Fagadau",
    "wof:placetype":"locality"
},
  "geometry": {"coordinates":[24.13333,46.78333],"type":"Point"}
}