{
  "type": "Feature",
  "properties": {
    "gn:admin1_code":"31",
    "gn:admin2_code":"141081.0",
    "gn:asciiname":"Fildu de Sus",
    "gn:cc2":"RO",
    "gn:country_code":"RO",
    "gn:dem":461,
    "gn:feature_class":"P",
    "gn:feature_code":"PPL",
    "gn:name":"Fildu de Sus",
    "gn:population":525,
    "gn:timezone":"Europe/Bucharest",
    "iso:country":"RO",
    "name:und_x_variant":[
        "Fildul-de-Sus",
        "Fildu de Sus"
    ],
    "wof:name":"Fildu de Sus",
    "wof:placetype":"locality",
    "wof:population":525
},
  "geometry": {"coordinates":[22.96376,46.93319],"type":"Point"}
}