{
  "type": "Feature",
  "properties": {
    "gn:admin1_code":"26",
    "gn:admin2_code":"113698.0",
    "gn:asciiname":"Studina",
    "gn:country_code":"RO",
    "gn:dem":337,
    "gn:feature_class":"P",
    "gn:feature_code":"PPL",
    "gn:name":"Studina",
    "gn:population":178,
    "gn:timezone":"Europe/Bucharest",
    "iso:country":"RO",
    "name:ceb_x_preferred":[
        "Comuna Studina"
    ],
    "name:ita_x_preferred":[
        "Studina"
    ],
    "name:msa_x_preferred":[
        "Studina"
    ],
    "name:nld_x_preferred":[
        "Studina"
    ],
    "name:por_x_preferred":[
        "Studina"
    ],
    "name:ron_x_preferred":[
        "Comuna Studina"
    ],
    "name:srp_x_preferred":[
        "\u041e\u043f\u0448\u0442\u0438\u043d\u0430 \u0421\u0442\u0443\u0434\u0438\u043d\u0430"
    ],
    "name:ukr_x_preferred":[
        "\u0421\u0442\u0443\u0434\u0456\u043d\u0430"
    ],
    "name:vie_x_preferred":[
        "Studina"
    ],
    "name:vol_x_preferred":[
        "Studina"
    ],
    "name:zho_x_preferred":[
        "\u65af\u5716\u8fea\u7d0d\u9109"
    ],
    "wof:name":"Studina",
    "wof:placetype":"locality",
    "wof:population":178
},
  "geometry": {"coordinates":[22.78224,44.84259],"type":"Point"}
}