{
  "type": "Feature",
  "properties": {
    "gn:admin1_code":"26",
    "gn:admin2_code":"113698.0",
    "gn:asciiname":"Studina",
    "gn:country_code":"RO",
    "gn:dem":337,
    "gn:feature_class":"P",
    "gn:feature_code":"PPL",
    "gn:name":"Studina",
    "gn:population":178,
    "gn:timezone":"Europe/Bucharest",
    "iso:country":"RO",
    "wof:name":"Studina",
    "wof:placetype":"locality",
    "wof:population":178
},
  "geometry": {"coordinates":[22.78224,44.84259],"type":"Point"}
}