{
  "type": "Feature",
  "properties": {
    "gn:admin1_code":"38",
    "gn:admin2_code":"163057.0",
    "gn:asciiname":"Mireni",
    "gn:country_code":"RO",
    "gn:dem":174,
    "gn:feature_class":"P",
    "gn:feature_code":"PPL",
    "gn:name":"Mireni",
    "gn:population":513,
    "gn:timezone":"Europe/Bucharest",
    "iso:country":"RO",
    "wof:name":"Mireni",
    "wof:placetype":"locality",
    "wof:population":513
},
  "geometry": {"coordinates":[27.49007000000001,46.31562],"type":"Point"}
}