{
  "type": "Feature",
  "properties": {
    "gn:admin1_code":"30",
    "gn:admin2_code":"134443.0",
    "gn:asciiname":"Podu lui Galben",
    "gn:country_code":"RO",
    "gn:dem":190,
    "gn:feature_class":"P",
    "gn:feature_code":"PPL",
    "gn:name":"Podu lui Galben",
    "gn:population":312,
    "gn:timezone":"Europe/Bucharest",
    "iso:country":"RO",
    "wof:name":"Podu lui Galben",
    "wof:placetype":"locality",
    "wof:population":312
},
  "geometry": {"coordinates":[26.15263,45.11429],"type":"Point"}
}