{
  "type": "Feature",
  "properties": {
    "gn:admin1_code":"07",
    "gn:admin2_code":"37459.0",
    "gn:asciiname":"Siliscani",
    "gn:country_code":"RO",
    "gn:dem":99,
    "gn:feature_class":"P",
    "gn:feature_code":"PPL",
    "gn:name":"Sili\u0219cani",
    "gn:population":350,
    "gn:timezone":"Europe/Bucharest",
    "iso:country":"RO",
    "wof:name":"Siliscani",
    "wof:placetype":"locality",
    "wof:population":350
},
  "geometry": {"coordinates":[26.85481,47.7294],"type":"Point"}
}