{
  "type": "Feature",
  "properties": {
    "gn:admin1_code":"01",
    "gn:admin2_code":"7197.0",
    "gn:asciiname":"Floresti",
    "gn:country_code":"RO",
    "gn:dem":1163,
    "gn:feature_class":"P",
    "gn:feature_code":"PPL",
    "gn:name":"Flore\u0219ti",
    "gn:population":64,
    "gn:timezone":"Europe/Bucharest",
    "iso:country":"RO",
    "wof:name":"Floresti",
    "wof:placetype":"locality",
    "wof:population":64
},
  "geometry": {"coordinates":[22.89769,46.44155],"type":"Point"}
}