{
  "type": "Feature",
  "properties": {
    "gn:admin1_code":"07",
    "gn:admin2_code":"37958.0",
    "gn:asciiname":"Loturi",
    "gn:country_code":"RO",
    "gn:dem":113,
    "gn:feature_class":"P",
    "gn:feature_code":"PPL",
    "gn:name":"Loturi",
    "gn:population":221,
    "gn:timezone":"Europe/Bucharest",
    "iso:country":"RO",
    "wof:name":"Loturi",
    "wof:placetype":"locality",
    "wof:population":221
},
  "geometry": {"coordinates":[27.07064,48.04521],"type":"Point"}
}