{
  "type": "Feature",
  "properties": {
    "gn:admin1_code":"30",
    "gn:admin2_code":"134194.0",
    "gn:asciiname":"Comanacu",
    "gn:country_code":"RO",
    "gn:dem":193,
    "gn:feature_class":"P",
    "gn:feature_code":"PPL",
    "gn:name":"Comanacu",
    "gn:population":0,
    "gn:timezone":"Europe/Bucharest",
    "iso:country":"RO",
    "name:und_x_variant":[
        "C\u0103tinca",
        "Com\u0103nacul",
        "Comanacu"
    ],
    "wof:lang_x_official":[
        "ron"
    ],
    "wof:lang_x_spoken":[
        "ron"
    ],
    "wof:name":"Comanacu",
    "wof:placetype":"locality"
},
  "geometry": {"coordinates":[25.83333,44.88333],"type":"Point"}
}