{
  "type": "Feature",
  "properties": {
    "gn:admin1_code":"20",
    "gn:admin2_code":"86222.0",
    "gn:asciiname":"Obranesti",
    "gn:cc2":"RO",
    "gn:country_code":"RO",
    "gn:dem":596,
    "gn:feature_class":"P",
    "gn:feature_code":"PPL",
    "gn:name":"Obr\u0103ne\u0219ti",
    "gn:population":16,
    "gn:timezone":"Europe/Bucharest",
    "iso:country":"RO",
    "name:und_x_variant":[
        "Abr\u00e0nfalva",
        "Obr\u0103ne\u015fti"
    ],
    "wof:name":"Obranesti",
    "wof:placetype":"locality",
    "wof:population":16
},
  "geometry": {"coordinates":[25.29393,46.2278],"type":"Point"}
}