{
  "type": "Feature",
  "properties": {
    "gn:admin1_code":"06",
    "gn:admin2_code":"33275",
    "gn:asciiname":"Albestii Bistritei",
    "gn:country_code":"RO",
    "gn:dem":341,
    "gn:feature_class":"P",
    "gn:feature_code":"PPL",
    "gn:name":"Albe\u0219tii Bistri\u021bei",
    "gn:population":193,
    "gn:timezone":"Europe/Bucharest",
    "iso:country":"RO",
    "wof:name":"Albestii Bistritei",
    "wof:placetype":"locality",
    "wof:population":193
},
  "geometry": {"coordinates":[24.45114,46.99301],"type":"Point"}
}