{
  "type": "Feature",
  "properties": {
    "iso:country":"RO",
    "name:ron_x_preferred":[
        "Izvoarele de Sus"
    ],
    "qs:gn_adm0_cc":"RO",
    "qs:gn_fcode":"PPLX",
    "qs:gn_local":685948,
    "qs:gn_nam_loc":"Bac\u0103u, Bacau, RO",
    "qs:gn_namadm1":"00",
    "qs:gn_name":"Izvoarele de Sus",
    "qs:local_max":559,
    "qs:local_sum":1083,
    "qs:localhoods":4,
    "qs:name":"Izvoarele de Sus",
    "qs:name_adm0":"Rom\u00e2nia",
    "qs:name_adm1":"Bacau",
    "qs:name_local":"Bac\u0103u",
    "qs:photo_max":439,
    "qs:photo_sum":472,
    "qs:placetype":"Suburb",
    "qs:quad_count":11,
    "qs:woe_adm0":23424933,
    "qs:woe_adm1":2346618,
    "qs:woe_adm2":0,
    "qs:woe_lau":0,
    "qs:woe_local":866528,
    "qs:woe_ver":"7.10.0",
    "wof:lang_x_official":[
        "ron"
    ],
    "wof:lang_x_spoken":[
        "ron"
    ],
    "wof:name":"Izvoarele de Sus",
    "wof:placetype":"neighbourhood"
},
  "geometry": {"coordinates":[26.915235,46.543824],"type":"Point"}
}