{
  "type": "Feature",
  "properties": {
    "gn:admin1_code":"17",
    "gn:admin2_code":"72604.0",
    "gn:asciiname":"Gogosita",
    "gn:cc2":"RO",
    "gn:country_code":"RO",
    "gn:dem":202,
    "gn:feature_class":"P",
    "gn:feature_code":"PPL",
    "gn:name":"Gogo\u0219i\u021ba",
    "gn:population":425,
    "gn:timezone":"Europe/Bucharest",
    "iso:country":"RO",
    "name:und_x_variant":[
        "Gogo\u015fi\u0163u",
        "Gogo\u015fi\u0163a"
    ],
    "wof:name":"Gogosita",
    "wof:placetype":"locality",
    "wof:population":425
},
  "geometry": {"coordinates":[23.35914,44.399],"type":"Point"}
}