{
  "type": "Feature",
  "properties": {
    "gn:gn_country":"RO",
    "gn:gn_fcode":"PPLA2",
    "gn:gn_pop":1824,
    "gn:population":1824,
    "iso:country":"RO",
    "name:deu_x_preferred":[
        "D\u0103b\u00e2ca"
    ],
    "name:eng_x_preferred":[
        "D\u0103b\u00e2ca"
    ],
    "name:epo_x_preferred":[
        "D\u0103b\u00e2ca"
    ],
    "name:fra_x_preferred":[
        "D\u0103b\u00e2ca"
    ],
    "name:hun_x_preferred":[
        "Doboka"
    ],
    "name:ita_x_preferred":[
        "D\u0103b\u00e2ca"
    ],
    "name:msa_x_preferred":[
        "D\u0103b\u00e2ca"
    ],
    "name:nld_x_preferred":[
        "D\u0103b\u00e2ca"
    ],
    "name:por_x_preferred":[
        "D\u0103b\u00e2ca"
    ],
    "name:ron_x_preferred":[
        "D\u0103b\u00e2ca"
    ],
    "name:spa_x_preferred":[
        "D\u0103b\u00e2ca"
    ],
    "name:ukr_x_preferred":[
        "\u0414\u0435\u0431\u0438\u043a\u0430"
    ],
    "name:unk_x_variant":[
        "Dob\u00e2ca"
    ],
    "name:vol_x_preferred":[
        "D\u0103b\u00e2ca"
    ],
    "qs_pg:aaroncc":"RO",
    "qs_pg:gn_country":"RO",
    "qs_pg:gn_fcode":"PPLA2",
    "qs_pg:gn_pop":1824,
    "qs_pg:name":"D\u0103b\u00e2ca",
    "qs_pg:photos_9r":0,
    "qs_pg:photos_sr":0,
    "qs_pg:pop_sr":3,
    "qs_pg:qs_pg_placetype":"locality",
    "wof:name":"D\u0103b\u00e2ca",
    "wof:placetype":"locality",
    "wof:population":1824
},
  "geometry": {"coordinates":[23.66667,46.98333],"type":"Point"}
}