{
  "type": "Feature",
  "properties": {
    "gn:admin1_code":"26",
    "gn:admin2_code":"111587.0",
    "gn:asciiname":"Rocsoreni",
    "gn:country_code":"RO",
    "gn:dem":273,
    "gn:feature_class":"P",
    "gn:feature_code":"PPL",
    "gn:name":"Roc\u0219oreni",
    "gn:population":198,
    "gn:timezone":"Europe/Bucharest",
    "iso:country":"RO",
    "wof:name":"Rocsoreni",
    "wof:placetype":"locality",
    "wof:population":198
},
  "geometry": {"coordinates":[23.0668,44.53183],"type":"Point"}
}