{
  "type": "Feature",
  "properties": {
    "gn:admin1_code":"05",
    "gn:admin2_code":"27971.0",
    "gn:asciiname":"Saud",
    "gn:country_code":"RO",
    "gn:dem":278,
    "gn:feature_class":"P",
    "gn:feature_code":"PPL",
    "gn:name":"S\u0103ud",
    "gn:population":448,
    "gn:timezone":"Europe/Bucharest",
    "iso:country":"RO",
    "name:ron_x_preferred":[
        "S\u0103ud"
    ],
    "name:und_x_variant":[
        "Sz\u00f3od",
        "Sz\u00f3d"
    ],
    "wof:name":"Saud",
    "wof:placetype":"locality",
    "wof:population":448
},
  "geometry": {"coordinates":[22.49564,46.61977],"type":"Point"}
}