{
  "type": "Feature",
  "properties": {
    "gn:gn_country":"RO",
    "gn:gn_fcode":"PPLA2",
    "gn:gn_pop":2239,
    "gn:population":2239,
    "iso:country":"RO",
    "name:ara_x_preferred":[
        "\u0633\u064a\u0645\u064a\u0646\u064a"
    ],
    "name:bul_x_preferred":[
        "\u0421\u0435\u0438\u043c\u0435\u043d\u0438"
    ],
    "name:dut_x_preferred":[
        "Seimeni"
    ],
    "name:eng_x_preferred":[
        "Seimeni"
    ],
    "name:fre_x_preferred":[
        "Seimeni"
    ],
    "name:hun_x_preferred":[
        "Seimeni"
    ],
    "name:ita_x_preferred":[
        "Seimeni"
    ],
    "name:por_x_preferred":[
        "Seimeni"
    ],
    "name:rum_x_preferred":[
        "Seimeni"
    ],
    "name:ukr_x_preferred":[
        "\u0421\u0435\u0439\u043c\u0435\u043d\u044c"
    ],
    "name:unk_x_variant":[
        "Seimenii Mari"
    ],
    "name:vie_x_preferred":[
        "Seimeni"
    ],
    "name:vol_x_preferred":[
        "Seimeni"
    ],
    "qs_pg:aaroncc":"RO",
    "qs_pg:gn_country":"RO",
    "qs_pg:gn_fcode":"PPLA2",
    "qs_pg:gn_pop":2239,
    "qs_pg:name":"Seimeni",
    "qs_pg:name_adm0":"Rom\u00e2nia",
    "qs_pg:name_adm1":"Constanta",
    "qs_pg:photos_9k":1,
    "qs_pg:photos_9r":1,
    "qs_pg:photos_all":3,
    "qs_pg:photos_sr":0,
    "qs_pg:pop_sr":4,
    "qs_pg:qs_pg_placetype":"locality",
    "qs_pg:qs_pg_placetype_gp":"Town",
    "qs_pg:woe_adm0":23424933,
    "woe:adm0_id":23424933,
    "woe:name_adm0":"Rom\u00e2nia",
    "woe:name_adm1":"Constanta",
    "woe:placetype":"Town",
    "wof:name":"Seimeni",
    "wof:placetype":"locality",
    "wof:population":2239
},
  "geometry": {"coordinates":[28.06667,44.38333],"type":"Point"}
}