{
  "type": "Feature",
  "properties": {
    "gn:admin1_code":"14",
    "gn:admin2_code":"61871.0",
    "gn:asciiname":"Tufani",
    "gn:cc2":"RO",
    "gn:country_code":"RO",
    "gn:dem":87,
    "gn:feature_class":"P",
    "gn:feature_code":"PPL",
    "gn:name":"Tufani",
    "gn:population":422,
    "gn:timezone":"Europe/Bucharest",
    "iso:country":"RO",
    "name:und_x_variant":[
        "Cardaol",
        "Cara Aaci",
        "Caraaci",
        "Tufani"
    ],
    "wof:name":"Tufani",
    "wof:placetype":"locality",
    "wof:population":422
},
  "geometry": {"coordinates":[28.00882,43.99333],"type":"Point"}
}