{
  "type": "Feature",
  "properties": {
    "gn:admin1_code":"36",
    "gn:admin2_code":"158314.0",
    "gn:asciiname":"Lighet",
    "gn:country_code":"RO",
    "gn:dem":141,
    "gn:feature_class":"P",
    "gn:feature_code":"PPL",
    "gn:name":"Lighet",
    "gn:population":0,
    "gn:timezone":"Europe/Bucharest",
    "iso:country":"RO",
    "wof:lang_x_official":[
        "ron"
    ],
    "wof:lang_x_spoken":[
        "ron"
    ],
    "wof:name":"Lighet",
    "wof:placetype":"locality"
},
  "geometry": {"coordinates":[21.56667,45.86667],"type":"Point"}
}