{
  "type": "Feature",
  "properties": {
    "gn:admin1_code":"18",
    "gn:admin2_code":"75114.0",
    "gn:asciiname":"Serbestii Vechi",
    "gn:country_code":"RO",
    "gn:dem":9,
    "gn:feature_class":"P",
    "gn:feature_code":"PPL",
    "gn:name":"\u0218erbe\u0219tii Vechi",
    "gn:population":814,
    "gn:timezone":"Europe/Bucharest",
    "iso:country":"RO",
    "wof:name":"Serbestii Vechi",
    "wof:placetype":"locality",
    "wof:population":814
},
  "geometry": {"coordinates":[27.87814,45.42098],"type":"Point"}
}