{
  "type": "Feature",
  "properties": {
    "gn:admin1_code":"13",
    "gn:admin2_code":"59327.0",
    "gn:asciiname":"Hasdate",
    "gn:cc2":"RO",
    "gn:country_code":"RO",
    "gn:dem":617,
    "gn:feature_class":"P",
    "gn:feature_code":"PPL",
    "gn:name":"H\u0103\u0219date",
    "gn:population":653,
    "gn:timezone":"Europe/Bucharest",
    "iso:country":"RO",
    "name:und_x_variant":[
        "H\u0103jdate",
        "H\u0103\u015fdate"
    ],
    "wof:name":"Hasdate",
    "wof:placetype":"locality",
    "wof:population":653
},
  "geometry": {"coordinates":[23.42857,46.64376],"type":"Point"}
}