{
  "type": "Feature",
  "properties": {
    "gn:admin1_code":"19",
    "gn:admin2_code":"81415.0",
    "gn:asciiname":"Zorlesti",
    "gn:country_code":"RO",
    "gn:dem":332,
    "gn:feature_class":"P",
    "gn:feature_code":"PPL",
    "gn:name":"Zorle\u0219ti",
    "gn:population":558,
    "gn:timezone":"Europe/Bucharest",
    "iso:country":"RO",
    "wof:name":"Zorlesti",
    "wof:placetype":"locality",
    "wof:population":558
},
  "geometry": {"coordinates":[23.72013,45.09136],"type":"Point"}
}