{
  "type": "Feature",
  "properties": {
    "gn:country":"RO",
    "gn:fcode":"PPLA2",
    "gn:population":2534,
    "iso:country":"RO",
    "name:ceb_x_preferred":[
        "M\u0103ri\u0219elu"
    ],
    "name:eng_x_preferred":[
        "M\u0103ri\u0219elu"
    ],
    "name:epo_x_preferred":[
        "M\u0103ri\u0219elu"
    ],
    "name:fra_x_preferred":[
        "M\u0103ri\u0219elu"
    ],
    "name:hun_x_preferred":[
        "Saj\u00f3nagyfalu"
    ],
    "name:ita_x_preferred":[
        "M\u0103ri\u0219elu"
    ],
    "name:msa_x_preferred":[
        "M\u0103ri\u0219elu"
    ],
    "name:nld_x_preferred":[
        "M\u0103ri\u0219elu"
    ],
    "name:por_x_preferred":[
        "M\u0103ri\u0219elu"
    ],
    "name:ron_x_preferred":[
        "M\u0103ri\u0219elu"
    ],
    "name:sqi_x_preferred":[
        "M\u0103ri\u0219elu"
    ],
    "name:srp_x_preferred":[
        "\u041c\u0430\u0440\u0438\u0448\u0435\u043b\u0443"
    ],
    "name:ukr_x_preferred":[
        "\u041c\u0435\u0440\u0456\u0448\u0435\u043b\u0443"
    ],
    "name:und_x_variant":[
        "M\u0103ri\u015felul"
    ],
    "name:vie_x_preferred":[
        "Mariselu"
    ],
    "name:vol_x_preferred":[
        "M\u0103ri\u0219elu"
    ],
    "qs_pg:aaroncc":"RO",
    "qs_pg:gn_country":"RO",
    "qs_pg:gn_fcode":"PPLA2",
    "qs_pg:gn_pop":2534,
    "qs_pg:name":"M\u0103ri\u015felu",
    "qs_pg:photos_9r":0,
    "qs_pg:photos_sr":0,
    "qs_pg:pop_sr":4,
    "qs_pg:qs_pg_placetype":"locality",
    "wof:name":"M\u0103ri\u015felu",
    "wof:placetype":"locality",
    "wof:population":2534
},
  "geometry": {"coordinates":[24.51667,47.01667],"type":"Point"}
}