{
  "type": "Feature",
  "properties": {
    "gn:admin1_code":"39",
    "gn:admin2_code":"170792",
    "gn:asciiname":"Beresti",
    "gn:country_code":"RO",
    "gn:dem":348,
    "gn:feature_class":"P",
    "gn:feature_code":"PPL",
    "gn:name":"Bere\u0219ti",
    "gn:population":403,
    "gn:timezone":"Europe/Bucharest",
    "iso:country":"RO",
    "wof:name":"Beresti",
    "wof:placetype":"locality",
    "wof:population":403
},
  "geometry": {"coordinates":[24.03279,44.93600000000001],"type":"Point"}
}