{
  "type": "Feature",
  "properties": {
    "gn:admin1_code":"27",
    "gn:admin2_code":"118691.0",
    "gn:asciiname":"Cuiesd",
    "gn:cc2":"RO",
    "gn:country_code":"RO",
    "gn:dem":360,
    "gn:feature_class":"P",
    "gn:feature_code":"PPL",
    "gn:name":"Cuie\u015fd",
    "gn:population":0,
    "gn:timezone":"Europe/Bucharest",
    "iso:country":"RO",
    "name:und_x_variant":[
        "K\u00f6vesd"
    ],
    "wof:name":"Cuiesd",
    "wof:placetype":"locality"
},
  "geometry": {"coordinates":[24.47625,46.60063],"type":"Point"}
}