{
  "type": "Feature",
  "properties": {
    "gn:admin1_code":"32",
    "gn:admin2_code":"138280",
    "gn:asciiname":"Berindan",
    "gn:country_code":"RO",
    "gn:dem":126,
    "gn:feature_class":"P",
    "gn:feature_code":"PPL",
    "gn:name":"Berindan",
    "gn:population":100,
    "gn:timezone":"Europe/Bucharest",
    "iso:country":"RO",
    "wof:name":"Berindan",
    "wof:placetype":"locality",
    "wof:population":100
},
  "geometry": {"coordinates":[23.01222000000001,47.78516],"type":"Point"}
}