{
  "type": "Feature",
  "properties": {
    "gn:admin1_code":"26",
    "gn:admin2_code":"113732.0",
    "gn:asciiname":"Cremenea",
    "gn:cc2":"RO",
    "gn:country_code":"RO",
    "gn:dem":214,
    "gn:feature_class":"P",
    "gn:feature_code":"PPL",
    "gn:name":"Cremenea",
    "gn:population":412,
    "gn:timezone":"Europe/Bucharest",
    "iso:country":"RO",
    "name:und_x_variant":[
        "Cremenea de Jos",
        "Cremenea"
    ],
    "wof:name":"Cremenea",
    "wof:placetype":"locality",
    "wof:population":412
},
  "geometry": {"coordinates":[23.01869,44.60688],"type":"Point"}
}