{
  "type": "Feature",
  "properties": {
    "gn:admin1_code":"06",
    "gn:admin2_code":"35312.0",
    "gn:asciiname":"Sopteriu",
    "gn:cc2":"RO",
    "gn:country_code":"RO",
    "gn:dem":372,
    "gn:feature_class":"P",
    "gn:feature_code":"PPL",
    "gn:name":"\u0218opteriu",
    "gn:population":503,
    "gn:timezone":"Europe/Bucharest",
    "iso:country":"RO",
    "name:und_x_variant":[
        "\u015eopteriul",
        "\u015eopteriu"
    ],
    "wof:name":"Sopteriu",
    "wof:placetype":"locality",
    "wof:population":503
},
  "geometry": {"coordinates":[24.3476,46.7978],"type":"Point"}
}