{
  "type": "Feature",
  "properties": {
    "gn:admin1_code":"39",
    "gn:admin2_code":"168452.0",
    "gn:asciiname":"Carlogani",
    "gn:cc2":"RO",
    "gn:country_code":"RO",
    "gn:dem":213,
    "gn:feature_class":"P",
    "gn:feature_code":"PPL",
    "gn:name":"C\u00e2rlogani",
    "gn:population":345,
    "gn:timezone":"Europe/Bucharest",
    "iso:country":"RO",
    "name:und_x_variant":[
        "C\u00e2rlogani",
        "C\u00eerlogani"
    ],
    "wof:name":"Carlogani",
    "wof:placetype":"locality",
    "wof:population":345
},
  "geometry": {"coordinates":[23.92194,44.68279],"type":"Point"}
}