{
  "type": "Feature",
  "properties": {
    "gn:admin1_code":"27",
    "gn:admin2_code":"114603.0",
    "gn:asciiname":"Valea Sapartocului",
    "gn:country_code":"RO",
    "gn:dem":441,
    "gn:feature_class":"P",
    "gn:feature_code":"PPL",
    "gn:name":"Valea \u0218apartocului",
    "gn:population":6,
    "gn:timezone":"Europe/Bucharest",
    "iso:country":"RO",
    "wof:name":"Valea Sapartocului",
    "wof:placetype":"locality",
    "wof:population":6
},
  "geometry": {"coordinates":[24.85021,46.20631],"type":"Point"}
}