{
  "type": "Feature",
  "properties": {
    "gn:admin1_code":"12",
    "gn:admin2_code":"53577",
    "gn:asciiname":"Dalmele Prigorului",
    "gn:country_code":"RO",
    "gn:dem":348,
    "gn:feature_class":"P",
    "gn:feature_code":"PPL",
    "gn:name":"D\u00e2lmele Prigorului",
    "gn:population":0,
    "gn:timezone":"Europe/Bucharest",
    "iso:country":"RO",
    "wof:name":"Dalmele Prigorului",
    "wof:placetype":"locality"
},
  "geometry": {"coordinates":[22.11028,44.945],"type":"Point"}
}