{
  "type": "Feature",
  "properties": {
    "gn:admin1_code":"27",
    "gn:admin2_code":"114970.0",
    "gn:asciiname":"Stejeris",
    "gn:country_code":"RO",
    "gn:dem":314,
    "gn:feature_class":"P",
    "gn:feature_code":"PPL",
    "gn:name":"Stejeri\u0219",
    "gn:population":324,
    "gn:timezone":"Europe/Bucharest",
    "iso:country":"RO",
    "name:hun_x_preferred":[
        "Cserefalva"
    ],
    "wof:name":"Stejeris",
    "wof:placetype":"locality",
    "wof:population":324
},
  "geometry": {"coordinates":[24.61719,46.47759],"type":"Point"}
}