{
  "type": "Feature",
  "properties": {
    "gn:admin1_code":"04",
    "gn:admin2_code":"23207.0",
    "gn:asciiname":"Valea Marului",
    "gn:country_code":"RO",
    "gn:dem":320,
    "gn:feature_class":"P",
    "gn:feature_code":"PPL",
    "gn:name":"Valea M\u0103rului",
    "gn:population":37,
    "gn:timezone":"Europe/Bucharest",
    "iso:country":"RO",
    "wof:name":"Valea Marului",
    "wof:placetype":"locality",
    "wof:population":37
},
  "geometry": {"coordinates":[27.20567,46.73964],"type":"Point"}
}