{
  "type": "Feature",
  "properties": {
    "gn:admin1_code":"31",
    "gn:admin2_code":"140672",
    "gn:asciiname":"Brebi",
    "gn:cc2":"RO",
    "gn:country_code":"RO",
    "gn:dem":262,
    "gn:feature_class":"P",
    "gn:feature_code":"PPL",
    "gn:name":"Brebi",
    "gn:population":614,
    "gn:timezone":"Europe/Bucharest",
    "iso:country":"RO",
    "name:und_x_variant":[
        "Brebu",
        "Brebi"
    ],
    "wof:name":"Brebi",
    "wof:placetype":"locality",
    "wof:population":614
},
  "geometry": {"coordinates":[23.1969,47.20775],"type":"Point"}
}