{
  "type": "Feature",
  "properties": {
    "gn:admin1_code":"13",
    "gn:admin2_code":"57742.0",
    "gn:asciiname":"Olariu",
    "gn:country_code":"RO",
    "gn:dem":359,
    "gn:feature_class":"P",
    "gn:feature_code":"PPL",
    "gn:name":"Ol\u0103riu",
    "gn:population":198,
    "gn:timezone":"Europe/Bucharest",
    "iso:country":"RO",
    "wof:name":"Olariu",
    "wof:placetype":"locality",
    "wof:population":198
},
  "geometry": {"coordinates":[24.06918,46.69273],"type":"Point"}
}