{
  "type": "Feature",
  "properties": {
    "gn:admin1_code":"03",
    "gn:admin2_code":"14753.0",
    "gn:asciiname":"Cosaci",
    "gn:cc2":"RO",
    "gn:country_code":"RO",
    "gn:dem":598,
    "gn:feature_class":"P",
    "gn:feature_code":"PPL",
    "gn:name":"Cosaci",
    "gn:population":180,
    "gn:timezone":"Europe/Bucharest",
    "iso:country":"RO",
    "name:und_x_variant":[
        "Cosacii",
        "Cosaci"
    ],
    "wof:name":"Cosaci",
    "wof:placetype":"locality",
    "wof:population":180
},
  "geometry": {"coordinates":[24.78523,45.27684],"type":"Point"}
}