{
  "type": "Feature",
  "properties": {
    "gn:admin1_code":"17",
    "gn:admin2_code":"72677.0",
    "gn:asciiname":"Fantani",
    "gn:country_code":"RO",
    "gn:dem":121,
    "gn:feature_class":"P",
    "gn:feature_code":"PPL",
    "gn:name":"F\u00e2nt\u00e2ni",
    "gn:population":272,
    "gn:timezone":"Europe/Bucharest",
    "iso:country":"RO",
    "wof:name":"Fantani",
    "wof:placetype":"locality",
    "wof:population":272
},
  "geometry": {"coordinates":[23.76667,44.46667],"type":"Point"}
}