{
  "type": "Feature",
  "properties": {
    "gn:admin1_code":"38",
    "gn:admin2_code":"163486",
    "gn:asciiname":"Babuta",
    "gn:cc2":"RO",
    "gn:country_code":"RO",
    "gn:dem":158,
    "gn:feature_class":"P",
    "gn:feature_code":"PPL",
    "gn:name":"B\u0103bu\u021ba",
    "gn:population":107,
    "gn:timezone":"Europe/Bucharest",
    "iso:country":"RO",
    "name:und_x_variant":[
        "M\u0103ne\u015fti",
        "B\u0103bu\u0163a"
    ],
    "wof:name":"Babuta",
    "wof:placetype":"locality",
    "wof:population":107
},
  "geometry": {"coordinates":[27.35521,46.60969],"type":"Point"}
}