{
  "type": "Feature",
  "properties": {
    "gn:admin1_code":"07",
    "gn:admin2_code":"39983.0",
    "gn:asciiname":"Cerchejeni",
    "gn:country_code":"RO",
    "gn:dem":88,
    "gn:feature_class":"P",
    "gn:feature_code":"PPL",
    "gn:name":"Cerchejeni",
    "gn:population":975,
    "gn:timezone":"Europe/Bucharest",
    "iso:country":"RO",
    "wof:name":"Cerchejeni",
    "wof:placetype":"locality",
    "wof:population":975
},
  "geometry": {"coordinates":[26.88252,47.69195],"type":"Point"}
}