{
  "type": "Feature",
  "properties": {
    "gn:admin1_code":"07",
    "gn:admin2_code":"39532.0",
    "gn:asciiname":"Burla",
    "gn:country_code":"RO",
    "gn:dem":120,
    "gn:feature_class":"P",
    "gn:feature_code":"PPL",
    "gn:name":"Burla",
    "gn:population":122,
    "gn:timezone":"Europe/Bucharest",
    "iso:country":"RO",
    "name:ben_x_preferred":[
        "\u09ac\u09c1\u09b0\u09b2\u09be"
    ],
    "name:bpy_x_preferred":[
        "\u09ac\u09c1\u09b0\u09b2\u09be"
    ],
    "name:ceb_x_preferred":[
        "Burla"
    ],
    "name:deu_x_preferred":[
        "Burla"
    ],
    "name:hun_x_preferred":[
        "Burla"
    ],
    "name:ita_x_preferred":[
        "Burla"
    ],
    "name:new_x_preferred":[
        "\u092c\u0941\u0930\u094d\u0932\u093e"
    ],
    "name:nld_x_preferred":[
        "Burla"
    ],
    "name:ron_x_preferred":[
        "Burla"
    ],
    "name:rus_x_preferred":[
        "\u0411\u0443\u0440\u043b\u0430"
    ],
    "name:srp_x_preferred":[
        "\u0411\u0443\u0440\u043b\u0430"
    ],
    "name:swe_x_preferred":[
        "Burla"
    ],
    "name:ukr_x_preferred":[
        "\u0411\u0443\u0440\u043b\u0430"
    ],
    "wof:name":"Burla",
    "wof:placetype":"locality",
    "wof:population":122
},
  "geometry": {"coordinates":[26.80074,47.785],"type":"Point"}
}