{
  "type": "Feature",
  "properties": {
    "gn:admin1_code":"07",
    "gn:admin2_code":"39532.0",
    "gn:asciiname":"Burla",
    "gn:country_code":"RO",
    "gn:dem":120,
    "gn:feature_class":"P",
    "gn:feature_code":"PPL",
    "gn:name":"Burla",
    "gn:population":122,
    "gn:timezone":"Europe/Bucharest",
    "iso:country":"RO",
    "wof:name":"Burla",
    "wof:placetype":"locality",
    "wof:population":122
},
  "geometry": {"coordinates":[26.80074,47.785],"type":"Point"}
}