{
  "type": "Feature",
  "properties": {
    "gn:admin1_code":"17",
    "gn:admin2_code":"74028.0",
    "gn:asciiname":"Plopsor",
    "gn:cc2":"RO",
    "gn:country_code":"RO",
    "gn:dem":166,
    "gn:feature_class":"P",
    "gn:feature_code":"PPL",
    "gn:name":"Plop\u0219or",
    "gn:population":828,
    "gn:timezone":"Europe/Bucharest",
    "iso:country":"RO",
    "name:und_x_variant":[
        "Plop\u015forul",
        "Plop\u015for",
        "Plop\u015foru"
    ],
    "wof:name":"Plopsor",
    "wof:placetype":"locality",
    "wof:population":828
},
  "geometry": {"coordinates":[23.41401,44.2499],"type":"Point"}
}