{
  "type": "Feature",
  "properties": {
    "gn:gn_country":"RO",
    "gn:gn_fcode":"PPL",
    "gn:gn_pop":0,
    "gn:population":433,
    "iso:country":"RO",
    "name:dut_x_preferred":[
        "C\u00e2rlibaba Nou\u0103"
    ],
    "name:eng_x_preferred":[
        "C\u00e2rlibaba Nou\u0103"
    ],
    "name:fre_x_preferred":[
        "C\u00e2rlibaba Nou\u0103"
    ],
    "name:hun_x_preferred":[
        "Radnalajosfalva"
    ],
    "name:ita_x_preferred":[
        "C\u00e2rlibaba Nou\u0103"
    ],
    "name:rum_x_preferred":[
        "C\u00e2rlibaba Nou\u0103"
    ],
    "name:ukr_x_preferred":[
        "\u041a\u0438\u0440\u043b\u0456\u0431\u0430\u0431\u0430-\u041d\u043e\u0443\u0435"
    ],
    "name:unk_x_variant":[
        "C\u00e2rlibaba Noua"
    ],
    "qs_pg:aaroncc":"RO",
    "qs_pg:gn_country":"RO",
    "qs_pg:gn_fcode":"PPL",
    "qs_pg:gn_pop":0,
    "qs_pg:name":"C\u00eerlibaba Nou\u0103",
    "qs_pg:name_adm0":"Rom\u00e2nia",
    "qs_pg:name_adm1":"Suceava",
    "qs_pg:photos":53,
    "qs_pg:photos_1k":11,
    "qs_pg:photos_9k":1,
    "qs_pg:photos_9r":2,
    "qs_pg:photos_all":53,
    "qs_pg:photos_sr":2,
    "qs_pg:pop_sr":0,
    "qs_pg:qs_pg_placetype":"locality",
    "qs_pg:qs_pg_placetype_gp":"Town",
    "qs_pg:woe_adm0":23424933,
    "woe:adm0_id":23424933,
    "woe:name_adm0":"Rom\u00e2nia",
    "woe:name_adm1":"Suceava",
    "woe:placetype":"Town",
    "wof:name":"C\u00eerlibaba Nou\u0103",
    "wof:placetype":"locality",
    "wof:population":433
},
  "geometry": {"coordinates":[25.13333,47.56667],"type":"Point"}
}