{
  "type": "Feature",
  "properties": {
    "gn:admin1_code":"31",
    "gn:admin2_code":"140501",
    "gn:asciiname":"Colonia Sighetu Silvaniei",
    "gn:country_code":"RO",
    "gn:dem":191,
    "gn:feature_class":"P",
    "gn:feature_code":"PPL",
    "gn:name":"Colonia Sighetu Silvaniei",
    "gn:population":75,
    "gn:timezone":"Europe/Bucharest",
    "iso:country":"RO",
    "name:hun_x_preferred":[
        "Szil\u00e1gyszigettelep"
    ],
    "wof:name":"Colonia Sighetu Silvaniei",
    "wof:placetype":"locality",
    "wof:population":75
},
  "geometry": {"coordinates":[22.91248,47.36253],"type":"Point"}
}