{
  "type": "Feature",
  "properties": {
    "gn:admin1_code":"40",
    "gn:admin2_code":"176551.0",
    "gn:asciiname":"Magura",
    "gn:country_code":"RO",
    "gn:dem":633,
    "gn:feature_class":"P",
    "gn:feature_code":"PPL",
    "gn:name":"M\u0103gura",
    "gn:population":378,
    "gn:timezone":"Europe/Bucharest",
    "iso:country":"RO",
    "name:ceb_x_preferred":[
        "Magura"
    ],
    "name:ces_x_preferred":[
        "Magura"
    ],
    "name:deu_x_preferred":[
        "Magura"
    ],
    "name:epo_x_preferred":[
        "Magura"
    ],
    "name:nld_x_preferred":[
        "Magura"
    ],
    "name:pol_x_preferred":[
        "Magura"
    ],
    "name:ron_x_preferred":[
        "Magura"
    ],
    "name:rus_x_preferred":[
        "\u041c\u0430\u0433\u0443\u0440\u0430"
    ],
    "name:slk_x_preferred":[
        "Magura"
    ],
    "name:srp_x_preferred":[
        "\u041c\u0430\u0433\u0443\u0440\u0430"
    ],
    "name:swe_x_preferred":[
        "Magura"
    ],
    "name:ukr_x_preferred":[
        "\u041c\u0430\u0491\u0443\u0440\u0430"
    ],
    "wof:name":"Magura",
    "wof:placetype":"locality",
    "wof:population":378
},
  "geometry": {"coordinates":[26.74367,45.60166],"type":"Point"}
}