{
  "type": "Feature",
  "properties": {
    "gn:admin1_code":"40",
    "gn:admin2_code":"176551.0",
    "gn:asciiname":"Magura",
    "gn:country_code":"RO",
    "gn:dem":633,
    "gn:feature_class":"P",
    "gn:feature_code":"PPL",
    "gn:name":"M\u0103gura",
    "gn:population":378,
    "gn:timezone":"Europe/Bucharest",
    "iso:country":"RO",
    "wof:name":"Magura",
    "wof:placetype":"locality",
    "wof:population":378
},
  "geometry": {"coordinates":[26.74367,45.60166],"type":"Point"}
}