{
  "type": "Feature",
  "properties": {
    "gn:admin1_code":"27",
    "gn:admin2_code":"117319.0",
    "gn:asciiname":"Larga",
    "gn:country_code":"RO",
    "gn:dem":518,
    "gn:feature_class":"P",
    "gn:feature_code":"PPL",
    "gn:name":"Larga",
    "gn:population":119,
    "gn:timezone":"Europe/Bucharest",
    "iso:country":"RO",
    "name:ceb_x_preferred":[
        "Larga"
    ],
    "name:chv_x_preferred":[
        "\u041b\u0430\u0440\u0433\u0430"
    ],
    "name:deu_x_preferred":[
        "Larga"
    ],
    "name:epo_x_preferred":[
        "Larga"
    ],
    "name:fra_x_preferred":[
        "Larga"
    ],
    "name:ron_x_preferred":[
        "Larga"
    ],
    "name:rus_x_preferred":[
        "\u041b\u0430\u0440\u0433\u0430"
    ],
    "name:srp_x_preferred":[
        "\u041b\u0430\u0440\u0433\u0430"
    ],
    "name:swe_x_preferred":[
        "Larga"
    ],
    "name:ukr_x_preferred":[
        "\u041b\u0430\u0440\u0433\u0430"
    ],
    "wof:name":"Larga",
    "wof:placetype":"locality",
    "wof:population":119
},
  "geometry": {"coordinates":[24.91843,46.82387],"type":"Point"}
}