{
  "type": "Feature",
  "properties": {
    "gn:admin1_code":"40",
    "gn:admin2_code":"176338.0",
    "gn:asciiname":"Cocosari",
    "gn:country_code":"RO",
    "gn:dem":180,
    "gn:feature_class":"P",
    "gn:feature_code":"PPL",
    "gn:name":"Coco\u0219ari",
    "gn:population":138,
    "gn:timezone":"Europe/Bucharest",
    "iso:country":"RO",
    "wof:name":"Cocosari",
    "wof:placetype":"locality",
    "wof:population":138
},
  "geometry": {"coordinates":[26.96039,45.61428],"type":"Point"}
}