{
  "type": "Feature",
  "properties": {
    "gn:admin1_code":"28",
    "gn:admin2_code":"125132.0",
    "gn:asciiname":"Soimaresti",
    "gn:country_code":"RO",
    "gn:dem":304,
    "gn:feature_class":"P",
    "gn:feature_code":"PPL",
    "gn:name":"\u0218oim\u0103re\u0219ti",
    "gn:population":357,
    "gn:timezone":"Europe/Bucharest",
    "iso:country":"RO",
    "wof:name":"Soimaresti",
    "wof:placetype":"locality",
    "wof:population":357
},
  "geometry": {"coordinates":[26.44308,47.3083],"type":"Point"}
}