{
  "type": "Feature",
  "properties": {
    "gn:admin1_code":"06",
    "gn:admin2_code":"35429.0",
    "gn:asciiname":"Perisor",
    "gn:country_code":"RO",
    "gn:dem":545,
    "gn:feature_class":"P",
    "gn:feature_code":"PPL",
    "gn:name":"Peri\u0219or",
    "gn:population":785,
    "gn:timezone":"Europe/Bucharest",
    "iso:country":"RO",
    "wof:name":"Perisor",
    "wof:placetype":"locality",
    "wof:population":785
},
  "geometry": {"coordinates":[24.22719,47.31417],"type":"Point"}
}