{
  "type": "Feature",
  "properties": {
    "gn:admin1_code":"06",
    "gn:admin2_code":"33881.0",
    "gn:asciiname":"Dupa Deal",
    "gn:country_code":"RO",
    "gn:dem":351,
    "gn:feature_class":"P",
    "gn:feature_code":"PPL",
    "gn:name":"Dupa Deal",
    "gn:population":73,
    "gn:timezone":"Europe/Bucharest",
    "iso:country":"RO",
    "wof:name":"Dupa Deal",
    "wof:placetype":"locality",
    "wof:population":73
},
  "geometry": {"coordinates":[24.45068,46.80639],"type":"Point"}
}