{
  "type": "Feature",
  "properties": {
    "gn:admin1_code":"28",
    "gn:admin2_code":"124411",
    "gn:asciiname":"Bordea",
    "gn:country_code":"RO",
    "gn:dem":495,
    "gn:feature_class":"P",
    "gn:feature_code":"PPL",
    "gn:name":"Bordea",
    "gn:population":228,
    "gn:timezone":"Europe/Bucharest",
    "iso:country":"RO",
    "wof:name":"Bordea",
    "wof:placetype":"locality",
    "wof:population":228
},
  "geometry": {"coordinates":[26.49182,47.03362],"type":"Point"}
}