{
  "type": "Feature",
  "properties": {
    "gn:admin1_code":"03",
    "gn:admin2_code":"19793.0",
    "gn:asciiname":"Vedea",
    "gn:country_code":"RO",
    "gn:dem":298,
    "gn:feature_class":"P",
    "gn:feature_code":"PPLA2",
    "gn:name":"Vedea",
    "gn:population":4243,
    "gn:timezone":"Europe/Bucharest",
    "iso:country":"RO",
    "name:und_x_variant":[
        "Gura-Boului",
        "Gera Boului",
        "Vedea"
    ],
    "wof:name":"Vedea",
    "wof:placetype":"locality",
    "wof:population":4243
},
  "geometry": {"coordinates":[24.61667000000001,44.78333],"type":"Point"}
}