{
  "type": "Feature",
  "properties": {
    "gn:admin1_code":"03",
    "gn:admin2_code":"19793.0",
    "gn:asciiname":"Vedea",
    "gn:country_code":"RO",
    "gn:dem":298,
    "gn:feature_class":"P",
    "gn:feature_code":"PPLA2",
    "gn:name":"Vedea",
    "gn:population":4243,
    "gn:timezone":"Europe/Bucharest",
    "iso:country":"RO",
    "name:ceb_x_preferred":[
        "Comuna Vedea"
    ],
    "name:fas_x_preferred":[
        "\u0648\u062f\u06cc"
    ],
    "name:ita_x_preferred":[
        "Vedea"
    ],
    "name:mkd_x_preferred":[
        "\u0412\u0435\u0434\u0435\u0430"
    ],
    "name:msa_x_preferred":[
        "Vedea"
    ],
    "name:nld_x_preferred":[
        "Vedea"
    ],
    "name:por_x_preferred":[
        "Vedea"
    ],
    "name:ron_x_preferred":[
        "Comuna Vedea"
    ],
    "name:sqi_x_preferred":[
        "Vedea"
    ],
    "name:srp_x_preferred":[
        "\u041e\u043f\u0448\u0442\u0438\u043d\u0430 \u0412\u0435\u0434\u0435\u0430"
    ],
    "name:ukr_x_preferred":[
        "\u0412\u0435\u0434\u044f"
    ],
    "name:und_x_variant":[
        "Gura-Boului",
        "Gera Boului",
        "Vedea"
    ],
    "name:vie_x_preferred":[
        "Vedea"
    ],
    "name:vol_x_preferred":[
        "Vedea"
    ],
    "name:zho_x_preferred":[
        "\u97cb\u4ee3\u4e9e\u9109"
    ],
    "wof:name":"Vedea",
    "wof:placetype":"locality",
    "wof:population":4243
},
  "geometry": {"coordinates":[24.61667000000001,44.78333],"type":"Point"}
}