{
  "type": "Feature",
  "properties": {
    "gn:admin1_code":"26",
    "gn:admin2_code":"113974.0",
    "gn:asciiname":"Sperlesti",
    "gn:country_code":"RO",
    "gn:dem":251,
    "gn:feature_class":"P",
    "gn:feature_code":"PPL",
    "gn:name":"Sperle\u0219ti",
    "gn:population":114,
    "gn:timezone":"Europe/Bucharest",
    "iso:country":"RO",
    "wof:name":"Sperlesti",
    "wof:placetype":"locality",
    "wof:population":114
},
  "geometry": {"coordinates":[23.00988,44.64914],"type":"Point"}
}