{
  "type": "Feature",
  "properties": {
    "gn:population":71,
    "iso:country":"RO",
    "name:arz_x_preferred":[
        "\u062c\u0631\u0648\u0634"
    ],
    "name:eng_x_preferred":[
        "Gro\u0219"
    ],
    "name:fra_x_preferred":[
        "Gro\u0219"
    ],
    "name:hun_x_preferred":[
        "Gr\u00f3s"
    ],
    "name:ita_x_preferred":[
        "Gro\u0219"
    ],
    "name:nld_x_preferred":[
        "Gro\u0219"
    ],
    "name:ron_x_preferred":[
        "Gro\u0219i"
    ],
    "name:ron_x_variant":[
        "Gro\u0219"
    ],
    "name:rum_x_colloquial":[
        "Gros",
        "Grosi"
    ],
    "name:rum_x_variant":[
        "Gro\u0219"
    ],
    "name:ukr_x_preferred":[
        "\u0413\u0440\u043e\u0448"
    ],
    "qs:gn_adm0_cc":"RO",
    "qs:gn_fcode":"PPLX",
    "qs:gn_local":675918,
    "qs:gn_nam_loc":"Hunedoara, Hunedoara, RO",
    "qs:gn_namadm1":"00",
    "qs:gn_name":"Gro\u015fi",
    "qs:local_max":550,
    "qs:local_sum":550,
    "qs:localhoods":1,
    "qs:name":"Gro\u0219i",
    "qs:name_adm0":"Rom\u00e2nia",
    "qs:name_adm1":"Hunedoara",
    "qs:name_local":"Hunedoara",
    "qs:photo_max":131,
    "qs:photo_sum":550,
    "qs:placetype":"Suburb",
    "qs:quad_count":37,
    "qs:woe_adm0":23424933,
    "qs:woe_adm1":2346635,
    "qs:woe_adm2":0,
    "qs:woe_lau":0,
    "qs:woe_local":873842,
    "qs:woe_ver":"7.10.0",
    "wof:lang_x_official":[
        "ron"
    ],
    "wof:lang_x_spoken":[
        "ron"
    ],
    "wof:name":"Gro\u0219i",
    "wof:placetype":"neighbourhood",
    "wof:population":71
},
  "geometry": {"coordinates":[22.892731,45.75298],"type":"Point"}
}