{
  "type": "Feature",
  "properties": {
    "gn:gn_country":"RO",
    "gn:gn_fcode":"PPL",
    "gn:gn_pop":4434,
    "gn:population":4434,
    "iso:country":"RO",
    "name:ceb_x_preferred":[
        "Ib\u0103ne\u0219ti"
    ],
    "name:eng_x_preferred":[
        "Ib\u0103ne\u0219ti"
    ],
    "name:epo_x_preferred":[
        "Ib\u0103ne\u0219ti"
    ],
    "name:fra_x_preferred":[
        "Ib\u0103ne\u0219ti"
    ],
    "name:hun_x_preferred":[
        "Lib\u00e1nfalva"
    ],
    "name:ita_x_preferred":[
        "Ib\u0103ne\u0219ti"
    ],
    "name:msa_x_preferred":[
        "Ib\u0103ne\u0219ti"
    ],
    "name:nld_x_preferred":[
        "Ib\u0103ne\u0219ti"
    ],
    "name:por_x_preferred":[
        "Ib\u0103ne\u0219ti"
    ],
    "name:ron_x_preferred":[
        "Ib\u0103ne\u0219ti"
    ],
    "name:srp_x_preferred":[
        "\u0418\u0431\u0430\u043d\u0435\u0448\u0442\u0438"
    ],
    "name:ukr_x_preferred":[
        "\u0406\u0431\u0435\u043d\u0435\u0448\u0442\u044c"
    ],
    "name:unk_x_variant":[
        "Lib\u00e0nfalva"
    ],
    "name:vol_x_preferred":[
        "Ib\u0103ne\u0219ti"
    ],
    "qs_pg:aaroncc":"RO",
    "qs_pg:gn_country":"RO",
    "qs_pg:gn_fcode":"PPL",
    "qs_pg:gn_pop":4434,
    "qs_pg:name":"Ib\u0103ne\u0219ti",
    "qs_pg:name_adm0":"Rom\u00e2nia",
    "qs_pg:name_adm1":"Mures",
    "qs_pg:photos_9k":1,
    "qs_pg:photos_9r":1,
    "qs_pg:photos_all":2,
    "qs_pg:photos_sr":0,
    "qs_pg:pop_sr":4,
    "qs_pg:qs_pg_placetype":"locality",
    "qs_pg:qs_pg_placetype_gp":"Town",
    "qs_pg:woe_adm0":23424933,
    "woe:adm0_id":23424933,
    "woe:name_adm0":"Rom\u00e2nia",
    "woe:name_adm1":"Mures",
    "woe:placetype":"Town",
    "wof:name":"Ib\u0103ne\u0219ti",
    "wof:placetype":"locality",
    "wof:population":4434
},
  "geometry": {"coordinates":[24.93333,46.76667],"type":"Point"}
}