{
  "type": "Feature",
  "properties": {
    "gn:admin1_code":"04",
    "gn:admin2_code":"21418",
    "gn:asciiname":"Buda",
    "gn:country_code":"RO",
    "gn:dem":446,
    "gn:feature_class":"P",
    "gn:feature_code":"PPL",
    "gn:name":"Buda",
    "gn:population":512,
    "gn:timezone":"Europe/Bucharest",
    "iso:country":"RO",
    "wof:name":"Buda",
    "wof:placetype":"locality",
    "wof:population":512
},
  "geometry": {"coordinates":[26.59107,46.42276],"type":"Point"}
}