{
  "type": "Feature",
  "properties": {
    "gn:admin1_code":"17",
    "gn:admin2_code":"73102.0",
    "gn:asciiname":"Popesti",
    "gn:country_code":"RO",
    "gn:dem":196,
    "gn:feature_class":"P",
    "gn:feature_code":"PPL",
    "gn:name":"Pope\u0219ti",
    "gn:population":32,
    "gn:timezone":"Europe/Bucharest",
    "iso:country":"RO",
    "wof:name":"Popesti",
    "wof:placetype":"locality",
    "wof:population":32
},
  "geometry": {"coordinates":[23.6889,44.57115],"type":"Point"}
}