{
  "type": "Feature",
  "properties": {
    "gn:admin1_code":"32",
    "gn:admin2_code":"137611.0",
    "gn:asciiname":"Dacia",
    "gn:country_code":"RO",
    "gn:dem":114,
    "gn:feature_class":"P",
    "gn:feature_code":"PPL",
    "gn:name":"Dacia",
    "gn:population":250,
    "gn:timezone":"Europe/Bucharest",
    "iso:country":"RO",
    "wof:name":"Dacia",
    "wof:placetype":"locality",
    "wof:population":250
},
  "geometry": {"coordinates":[22.6567,47.73337],"type":"Point"}
}