{
  "type": "Feature",
  "properties": {
    "gn:admin1_code":"32",
    "gn:admin2_code":"137611.0",
    "gn:asciiname":"Dacia",
    "gn:country_code":"RO",
    "gn:dem":114,
    "gn:feature_class":"P",
    "gn:feature_code":"PPL",
    "gn:name":"Dacia",
    "gn:population":250,
    "gn:timezone":"Europe/Bucharest",
    "iso:country":"RO",
    "name:ara_x_preferred":[
        "\u062f\u0627\u0642\u064a\u0629"
    ],
    "name:arg_x_preferred":[
        "Dacia"
    ],
    "name:arz_x_preferred":[
        "\u062f\u0627\u062a\u0634\u064a\u0627"
    ],
    "name:azb_x_preferred":[
        "\u062f\u0627\u06a9\u06cc\u0647"
    ],
    "name:bel_x_preferred":[
        "\u0414\u0430\u043a\u0456\u044f"
    ],
    "name:bos_x_preferred":[
        "Dakija"
    ],
    "name:bre_x_preferred":[
        "Dakia"
    ],
    "name:bul_x_preferred":[
        "\u0414\u0430\u043a\u0438\u044f"
    ],
    "name:cat_x_preferred":[
        "D\u00e0cia"
    ],
    "name:ces_x_preferred":[
        "D\u00e1cie"
    ],
    "name:cym_x_preferred":[
        "Dacia"
    ],
    "name:dan_x_preferred":[
        "Dakien"
    ],
    "name:ell_x_preferred":[
        "\u0394\u03b1\u03ba\u03af\u03b1"
    ],
    "name:epo_x_preferred":[
        "Dakio"
    ],
    "name:est_x_preferred":[
        "Daakia"
    ],
    "name:eus_x_preferred":[
        "Dazia"
    ],
    "name:fas_x_preferred":[
        "\u062f\u0627\u06a9\u06cc\u0647"
    ],
    "name:fin_x_preferred":[
        "Daakia"
    ],
    "name:fra_x_preferred":[
        "Dacie"
    ],
    "name:fry_x_preferred":[
        "Daasje"
    ],
    "name:heb_x_preferred":[
        "\u05d3\u05d0\u05e7\u05d9\u05d4"
    ],
    "name:hrv_x_preferred":[
        "Dacija"
    ],
    "name:hye_x_preferred":[
        "\u0534\u0561\u056f\u056b\u0561"
    ],
    "name:ido_x_preferred":[
        "Dacia"
    ],
    "name:ind_x_preferred":[
        "Dacia"
    ],
    "name:ita_x_preferred":[
        "Dacia"
    ],
    "name:jpn_x_preferred":[
        "\u30c0\u30ad\u30a2"
    ],
    "name:kat_x_preferred":[
        "\u10d3\u10d0\u10d9\u10d8\u10d0"
    ],
    "name:kor_x_preferred":[
        "\ub2e4\ud0a4\uc544"
    ],
    "name:lav_x_preferred":[
        "D\u0101kija"
    ],
    "name:lit_x_preferred":[
        "Dakija"
    ],
    "name:msa_x_preferred":[
        "Dacia"
    ],
    "name:nld_x_preferred":[
        "Daci\u00eb"
    ],
    "name:nor_x_preferred":[
        "Dakia"
    ],
    "name:pol_x_preferred":[
        "Dacja"
    ],
    "name:por_x_preferred":[
        "D\u00e1cia"
    ],
    "name:ron_x_preferred":[
        "Dacia"
    ],
    "name:rus_x_preferred":[
        "\u0414\u0430\u043a\u0438\u044f"
    ],
    "name:scn_x_preferred":[
        "Dacia"
    ],
    "name:slk_x_preferred":[
        "D\u00e1cia"
    ],
    "name:spa_x_preferred":[
        "Dacia"
    ],
    "name:srp_x_preferred":[
        "\u0414\u0430\u043a\u0438\u0458\u0430"
    ],
    "name:swe_x_preferred":[
        "Dakien"
    ],
    "name:tur_x_preferred":[
        "Da\u00e7ya"
    ],
    "name:ukr_x_preferred":[
        "\u0414\u0430\u043a\u0456\u044f"
    ],
    "name:vie_x_preferred":[
        "Dacia"
    ],
    "name:wuu_x_preferred":[
        "\u8fbe\u5951\u4e9a"
    ],
    "name:zho_x_preferred":[
        "\u9054\u5951\u4e9e"
    ],
    "wof:name":"Dacia",
    "wof:placetype":"locality",
    "wof:population":250
},
  "geometry": {"coordinates":[22.6567,47.73337],"type":"Point"}
}