{
  "type": "Feature",
  "properties": {
    "gn:admin1_code":"11",
    "gn:admin2_code":"46439",
    "gn:asciiname":"Alunis",
    "gn:cc2":"RO",
    "gn:country_code":"RO",
    "gn:dem":632,
    "gn:feature_class":"P",
    "gn:feature_code":"PPL",
    "gn:name":"Aluni\u0219",
    "gn:population":178,
    "gn:timezone":"Europe/Bucharest",
    "iso:country":"RO",
    "name:und_x_variant":[
        "Aluni\u015fu",
        "Aluni\u015f"
    ],
    "wof:name":"Alunis",
    "wof:placetype":"locality",
    "wof:population":178
},
  "geometry": {"coordinates":[26.41632,45.4086],"type":"Point"}
}