{
  "type": "Feature",
  "properties": {
    "gn:admin1_code":"29",
    "gn:admin2_code":"128962.0",
    "gn:asciiname":"Optasani",
    "gn:cc2":"RO",
    "gn:country_code":"RO",
    "gn:dem":324,
    "gn:feature_class":"P",
    "gn:feature_code":"PPL",
    "gn:name":"Opt\u0103\u0219ani",
    "gn:population":196,
    "gn:timezone":"Europe/Bucharest",
    "iso:country":"RO",
    "name:und_x_variant":[
        "Opt\u015fani",
        "Opt\u0103\u015fani"
    ],
    "wof:name":"Optasani",
    "wof:placetype":"locality",
    "wof:population":196
},
  "geometry": {"coordinates":[24.50996,44.73876],"type":"Point"}
}