{
  "type": "Feature",
  "properties": {
    "gn:admin1_code":"19",
    "gn:admin2_code":"78748.0",
    "gn:asciiname":"Viezuri",
    "gn:country_code":"RO",
    "gn:dem":228,
    "gn:feature_class":"P",
    "gn:feature_code":"PPL",
    "gn:name":"Viezuri",
    "gn:population":0,
    "gn:timezone":"Europe/Bucharest",
    "iso:country":"RO",
    "wof:lang_x_official":[
        "ron"
    ],
    "wof:lang_x_spoken":[
        "ron"
    ],
    "wof:name":"Viezuri",
    "wof:placetype":"locality"
},
  "geometry": {"coordinates":[23.38333,45.05],"type":"Point"}
}