{
  "type": "Feature",
  "properties": {
    "gn:admin1_code":"36",
    "gn:admin2_code":"158804.0",
    "gn:asciiname":"Olosag",
    "gn:cc2":"RO",
    "gn:country_code":"RO",
    "gn:dem":149,
    "gn:feature_class":"P",
    "gn:feature_code":"PPL",
    "gn:name":"Olo\u0219ag",
    "gn:population":305,
    "gn:timezone":"Europe/Bucharest",
    "iso:country":"RO",
    "name:und_x_variant":[
        "Oll\u00f3s\u00e1g",
        "Ol\u00e1hs\u00e1g",
        "Olo\u015fag"
    ],
    "wof:name":"Olosag",
    "wof:placetype":"locality",
    "wof:population":305
},
  "geometry": {"coordinates":[21.95883,45.60309],"type":"Point"}
}