{
  "type": "Feature",
  "properties": {
    "gn:admin1_code":"26",
    "gn:admin2_code":"112469",
    "gn:asciiname":"Dalma",
    "gn:country_code":"RO",
    "gn:dem":599,
    "gn:feature_class":"P",
    "gn:feature_code":"PPL",
    "gn:name":"D\u00e2lma",
    "gn:population":0,
    "gn:timezone":"Europe/Bucharest",
    "iso:country":"RO",
    "name:cat_x_preferred":[
        "Dalma"
    ],
    "name:deu_x_preferred":[
        "Dalma"
    ],
    "name:ita_x_preferred":[
        "Dalma"
    ],
    "name:por_x_preferred":[
        "Dalma"
    ],
    "wof:lang_x_official":[
        "ron"
    ],
    "wof:lang_x_spoken":[
        "ron"
    ],
    "wof:name":"Dalma",
    "wof:placetype":"locality"
},
  "geometry": {"coordinates":[22.57389,44.76806],"type":"Point"}
}