{
  "type": "Feature",
  "properties": {
    "gn:admin1_code":"39",
    "gn:admin2_code":"168602",
    "gn:asciiname":"Baditoiu",
    "gn:country_code":"RO",
    "gn:dem":359,
    "gn:feature_class":"P",
    "gn:feature_code":"PPL",
    "gn:name":"B\u0103di\u0163oiu",
    "gn:population":0,
    "gn:timezone":"Europe/Bucharest",
    "iso:country":"RO",
    "name:und_x_variant":[
        "B\u0103di\u0163ioiul",
        "B\u0103di\u0163oiu"
    ],
    "wof:lang_x_official":[
        "ron"
    ],
    "wof:lang_x_spoken":[
        "ron"
    ],
    "wof:name":"Baditoiu",
    "wof:placetype":"locality"
},
  "geometry": {"coordinates":[23.88333,44.98333],"type":"Point"}
}