{
  "type": "Feature",
  "properties": {
    "gn:country":"RO",
    "gn:fcode":"PPL",
    "gn:population":0,
    "iso:country":"RO",
    "name:ceb_x_preferred":[
        "Mestec\u0103ni\u0219"
    ],
    "name:eng_x_preferred":[
        "Mestec\u0103ni\u0219"
    ],
    "name:fra_x_preferred":[
        "Mestec\u0103ni\u0219"
    ],
    "name:nld_x_preferred":[
        "Mestec\u0103ni\u0219"
    ],
    "name:ron_x_preferred":[
        "Mestec\u0103ni\u0219"
    ],
    "name:srp_x_preferred":[
        "\u041c\u0435\u0441\u0442\u0435\u043a\u0430\u043d\u0438\u0448"
    ],
    "name:ukr_x_preferred":[
        "\u041c\u0435\u0441\u0442\u0435\u043a\u0435\u043d\u0456\u0448"
    ],
    "qs_pg:aaroncc":"RO",
    "qs_pg:gn_country":"RO",
    "qs_pg:gn_fcode":"PPL",
    "qs_pg:gn_pop":0,
    "qs_pg:name":"Mestec\u0103ni\u0219",
    "qs_pg:name_adm0":"Rom\u00e2nia",
    "qs_pg:name_adm1":"Suceava",
    "qs_pg:photos":33,
    "qs_pg:photos_1k":7,
    "qs_pg:photos_9k":1,
    "qs_pg:photos_9r":2,
    "qs_pg:photos_all":33,
    "qs_pg:photos_sr":2,
    "qs_pg:pop_sr":0,
    "qs_pg:qs_pg_placetype":"locality",
    "qs_pg:qs_pg_placetype_gp":"Town",
    "qs_pg:woe_adm0":23424933,
    "woe:adm0_id":23424933,
    "woe:name_adm0":"Rom\u00e2nia",
    "woe:name_adm1":"Suceava",
    "woe:placetype":"Town",
    "wof:name":"Mestec\u0103ni\u0219",
    "wof:placetype":"locality",
    "wof:population":332
},
  "geometry": {"coordinates":[25.33333,47.46667],"type":"Point"}
}