{
  "type": "Feature",
  "properties": {
    "gn:admin1_code":"32",
    "gn:admin2_code":"139394.0",
    "gn:asciiname":"Tireac",
    "gn:cc2":"RO",
    "gn:country_code":"RO",
    "gn:dem":130,
    "gn:feature_class":"P",
    "gn:feature_code":"PPL",
    "gn:name":"Tireac",
    "gn:population":107,
    "gn:timezone":"Europe/Bucharest",
    "iso:country":"RO",
    "name:und_x_variant":[
        "Tirac",
        "Tireac"
    ],
    "wof:name":"Tireac",
    "wof:placetype":"locality",
    "wof:population":107
},
  "geometry": {"coordinates":[23.03639,47.69377],"type":"Point"}
}