{
  "type": "Feature",
  "properties": {
    "gn:admin1_code":"17",
    "gn:admin2_code":"73852.0",
    "gn:asciiname":"Fantanele",
    "gn:cc2":"RO",
    "gn:country_code":"RO",
    "gn:dem":103,
    "gn:feature_class":"P",
    "gn:feature_code":"PPL",
    "gn:name":"F\u00e2nt\u00e2nele",
    "gn:population":194,
    "gn:timezone":"Europe/Bucharest",
    "iso:country":"RO",
    "name:und_x_variant":[
        "F\u00e2nt\u00e2nele",
        "F\u00eent\u00eenele"
    ],
    "wof:name":"Fantanele",
    "wof:placetype":"locality",
    "wof:population":194
},
  "geometry": {"coordinates":[23.60116,44.19274],"type":"Point"}
}