{
  "type": "Feature",
  "properties": {
    "gn:admin1_code":"38",
    "gn:admin2_code":"165979",
    "gn:asciiname":"Bogdana-Voloseni",
    "gn:cc2":"RO",
    "gn:country_code":"RO",
    "gn:dem":83,
    "gn:feature_class":"P",
    "gn:feature_code":"PPL",
    "gn:name":"Bogdana-Voloseni",
    "gn:population":189,
    "gn:timezone":"Europe/Bucharest",
    "iso:country":"RO",
    "name:und_x_variant":[
        "Voloseni Bogdana",
        "Bogdan-Volo\u015feni",
        "Bogdana Voloseni"
    ],
    "wof:name":"Bogdana-Voloseni",
    "wof:placetype":"locality",
    "wof:population":189
},
  "geometry": {"coordinates":[28.12083,46.63757],"type":"Point"}
}