{
  "type": "Feature",
  "properties": {
    "gn:admin1_code":"20",
    "gn:admin2_code":"86188.0",
    "gn:asciiname":"Cariera Capitus al Doilea",
    "gn:country_code":"RO",
    "gn:dem":765,
    "gn:feature_class":"P",
    "gn:feature_code":"PPL",
    "gn:name":"Cariera Capitus al Doilea",
    "gn:population":0,
    "gn:timezone":"Europe/Bucharest",
    "iso:country":"RO",
    "name:und_x_variant":[
        "K\u00e0rpitusz II B\u00e0nya",
        "Cariera Carpitus II",
        "Cariera Capitus II",
        "Cariera Capitus al Doilea"
    ],
    "wof:name":"Cariera Capitus al Doilea",
    "wof:placetype":"locality"
},
  "geometry": {"coordinates":[25.86667000000001,46.15],"type":"Point"}
}