{
  "type": "Feature",
  "properties": {
    "gn:admin1_code":"19",
    "gn:admin2_code":"80980.0",
    "gn:asciiname":"Raci",
    "gn:country_code":"RO",
    "gn:dem":200,
    "gn:feature_class":"P",
    "gn:feature_code":"PPL",
    "gn:name":"Raci",
    "gn:population":222,
    "gn:timezone":"Europe/Bucharest",
    "iso:country":"RO",
    "name:ceb_x_preferred":[
        "Raci"
    ],
    "name:fra_x_preferred":[
        "Raci"
    ],
    "name:nld_x_preferred":[
        "Raci"
    ],
    "name:swe_x_preferred":[
        "Raci"
    ],
    "wof:name":"Raci",
    "wof:placetype":"locality",
    "wof:population":222
},
  "geometry": {"coordinates":[23.25776,44.76323],"type":"Point"}
}