{
  "type": "Feature",
  "properties": {
    "iso:country":"RO",
    "wof:lang_x_official":[
        "ron"
    ],
    "wof:lang_x_spoken":[
        "ron"
    ],
    "wof:name":"Sectorul 2",
    "wof:placetype":"neighbourhood"
},
  "geometry": {"coordinates":[26.137026,44.45305],"type":"Point"}
}