{
  "type": "Feature",
  "properties": {
    "iso:country":"RO",
    "wof:name":"Sectorul 2",
    "wof:placetype":"neighbourhood"
},
  "geometry": {"coordinates":[26.13702578310342,44.45304987596512],"type":"Point"}
}