{
  "type": "Feature",
  "properties": {
    "gn:admin1_code":"05",
    "gn:admin2_code":"29813.0",
    "gn:asciiname":"Gepis",
    "gn:country_code":"RO",
    "gn:dem":230,
    "gn:feature_class":"P",
    "gn:feature_code":"PPL",
    "gn:name":"Gepi\u0219",
    "gn:population":668,
    "gn:timezone":"Europe/Bucharest",
    "iso:country":"RO",
    "wof:name":"Gepis",
    "wof:placetype":"locality",
    "wof:population":668
},
  "geometry": {"coordinates":[22.02049,46.84592],"type":"Point"}
}