{
  "type": "Feature",
  "properties": {
    "gn:country":"RO",
    "gn:fcode":"PPLA2",
    "gn:population":2255,
    "iso:country":"RO",
    "name:ceb_x_preferred":[
        "Icl\u0103nzel"
    ],
    "name:eng_x_preferred":[
        "Icl\u0103nzel"
    ],
    "name:epo_x_preferred":[
        "Icl\u0103nzel"
    ],
    "name:fra_x_preferred":[
        "Icl\u0103nzel"
    ],
    "name:hun_x_preferred":[
        "Kisikland"
    ],
    "name:ita_x_preferred":[
        "Icl\u0103nzel"
    ],
    "name:msa_x_preferred":[
        "Icl\u0103nzel"
    ],
    "name:nld_x_preferred":[
        "Icl\u0103nzel"
    ],
    "name:por_x_preferred":[
        "Icl\u0103nzel"
    ],
    "name:ron_x_preferred":[
        "Icl\u0103nzel"
    ],
    "name:srp_x_preferred":[
        "\u0418\u043a\u043b\u0430\u043d\u0437\u0435\u043b"
    ],
    "name:ukr_x_preferred":[
        "\u0406\u043a\u043b\u0435\u043d\u0437\u0435\u043b"
    ],
    "name:und_x_variant":[
        "Icl\u0103nzeiu"
    ],
    "name:vie_x_preferred":[
        "Iclanzel"
    ],
    "name:vol_x_preferred":[
        "Icl\u0103nzel"
    ],
    "qs_pg:aaroncc":"RO",
    "qs_pg:gn_country":"RO",
    "qs_pg:gn_fcode":"PPLA2",
    "qs_pg:gn_pop":2255,
    "qs_pg:name":"Icl\u0103nzel",
    "qs_pg:name_adm0":"Rom\u00e2nia",
    "qs_pg:name_adm1":"Mures",
    "qs_pg:photos_9r":0,
    "qs_pg:photos_sr":0,
    "qs_pg:pop_sr":4,
    "qs_pg:qs_pg_placetype":"locality",
    "qs_pg:qs_pg_placetype_gp":"Town",
    "qs_pg:woe_adm0":23424933,
    "woe:adm0_id":23424933,
    "woe:name_adm0":"Rom\u00e2nia",
    "woe:name_adm1":"Mures",
    "woe:placetype":"Town",
    "wof:name":"Icl\u0103nzel",
    "wof:placetype":"locality",
    "wof:population":2255
},
  "geometry": {"coordinates":[24.28333,46.53333],"type":"Point"}
}