{
  "type": "Feature",
  "properties": {
    "gn:admin1_code":"26",
    "gn:admin2_code":"113929.0",
    "gn:asciiname":"Scorila",
    "gn:country_code":"RO",
    "gn:dem":210,
    "gn:feature_class":"P",
    "gn:feature_code":"PPL",
    "gn:name":"Scorila",
    "gn:population":423,
    "gn:timezone":"Europe/Bucharest",
    "iso:country":"RO",
    "wof:name":"Scorila",
    "wof:placetype":"locality",
    "wof:population":423
},
  "geometry": {"coordinates":[23.08664,44.34804000000001],"type":"Point"}
}