{
  "type": "Feature",
  "properties": {
    "gn:admin1_code":"05",
    "gn:admin2_code":"29813.0",
    "gn:asciiname":"Calea Mare",
    "gn:country_code":"RO",
    "gn:dem":289,
    "gn:feature_class":"P",
    "gn:feature_code":"PPL",
    "gn:name":"Calea Mare",
    "gn:population":724,
    "gn:timezone":"Europe/Bucharest",
    "iso:country":"RO",
    "wof:name":"Calea Mare",
    "wof:placetype":"locality",
    "wof:population":724
},
  "geometry": {"coordinates":[22.0681,46.91014000000001],"type":"Point"}
}