{
  "type": "Feature",
  "properties": {
    "gn:admin1_code":"26",
    "gn:admin2_code":"111006.0",
    "gn:asciiname":"Gura Motrului",
    "gn:country_code":"RO",
    "gn:dem":116,
    "gn:feature_class":"P",
    "gn:feature_code":"PPL",
    "gn:name":"Gura Motrului",
    "gn:population":374,
    "gn:timezone":"Europe/Bucharest",
    "iso:country":"RO",
    "wof:name":"Gura Motrului",
    "wof:placetype":"locality",
    "wof:population":374
},
  "geometry": {"coordinates":[23.43678,44.55533],"type":"Point"}
}