{
  "type": "Feature",
  "properties": {
    "gn:admin1_code":"01",
    "gn:admin2_code":"3459.0",
    "gn:asciiname":"Izbicioara",
    "gn:country_code":"RO",
    "gn:dem":755,
    "gn:feature_class":"P",
    "gn:feature_code":"PPL",
    "gn:name":"Izbicioara",
    "gn:population":22,
    "gn:timezone":"Europe/Bucharest",
    "iso:country":"RO",
    "wof:name":"Izbicioara",
    "wof:placetype":"locality",
    "wof:population":22
},
  "geometry": {"coordinates":[23.16648,46.24349],"type":"Point"}
}