{
  "type": "Feature",
  "properties": {
    "iso:country":"RO",
    "name:dut_x_preferred":[
        "Vitomire\u0219ti"
    ],
    "name:eng_x_preferred":[
        "Vitomire\u0219ti"
    ],
    "name:fre_x_preferred":[
        "Vitomire\u0219ti"
    ],
    "name:ita_x_preferred":[
        "Vitomire\u0219ti"
    ],
    "name:por_x_preferred":[
        "Vitomire\u0219ti"
    ],
    "name:rum_x_preferred":[
        "Vitomire\u0219ti"
    ],
    "name:ukr_x_preferred":[
        "\u0412\u0456\u0442\u043e\u043c\u0456\u0440\u0435\u0448\u0442\u044c"
    ],
    "name:vol_x_preferred":[
        "Vitomire\u0219ti"
    ],
    "qs_pg:aaroncc":"RO",
    "qs_pg:name":"Vitomire\u0219ti",
    "qs_pg:name_adm0":"Rom\u00e2nia",
    "qs_pg:name_adm1":"Olt",
    "qs_pg:photos":15,
    "qs_pg:photos_1k":3,
    "qs_pg:photos_9k":1,
    "qs_pg:photos_9r":1,
    "qs_pg:photos_all":15,
    "qs_pg:photos_sr":1,
    "qs_pg:pop_sr":0,
    "qs_pg:qs_pg_placetype":"locality",
    "qs_pg:qs_pg_placetype_gp":"Town",
    "qs_pg:woe_adm0":23424933,
    "woe:adm0_id":23424933,
    "woe:name_adm0":"Rom\u00e2nia",
    "woe:name_adm1":"Olt",
    "woe:placetype":"Town",
    "wof:name":"Vitomire\u0219ti",
    "wof:placetype":"locality"
},
  "geometry": {"coordinates":[24.413681,44.858119],"type":"Point"}
}