{
  "type": "Feature",
  "properties": {
    "gn:admin1_code":"28",
    "gn:admin2_code":"123709.0",
    "gn:asciiname":"Bunghi",
    "gn:country_code":"RO",
    "gn:dem":302,
    "gn:feature_class":"P",
    "gn:feature_code":"PPL",
    "gn:name":"Bunghi",
    "gn:population":239,
    "gn:timezone":"Europe/Bucharest",
    "iso:country":"RO",
    "wof:name":"Bunghi",
    "wof:placetype":"locality",
    "wof:population":239
},
  "geometry": {"coordinates":[27.10803,46.90843],"type":"Point"}
}