{
  "type": "Feature",
  "properties": {
    "gn:admin1_code":"20",
    "gn:admin2_code":"83785.0",
    "gn:asciiname":"Siclod",
    "gn:cc2":"RO",
    "gn:country_code":"RO",
    "gn:dem":653,
    "gn:feature_class":"P",
    "gn:feature_code":"PPL",
    "gn:name":"\u0218iclod",
    "gn:population":492,
    "gn:timezone":"Europe/Bucharest",
    "iso:country":"RO",
    "name:und_x_variant":[
        "Siklod",
        "\u015eiclod"
    ],
    "wof:name":"Siclod",
    "wof:placetype":"locality",
    "wof:population":492
},
  "geometry": {"coordinates":[25.04136,46.51728],"type":"Point"}
}