{
  "type": "Feature",
  "properties": {
    "gn:admin1_code":"01",
    "gn:admin2_code":"1696.0",
    "gn:asciiname":"Calene",
    "gn:country_code":"RO",
    "gn:dem":715,
    "gn:feature_class":"P",
    "gn:feature_code":"PPL",
    "gn:name":"C\u0103lene",
    "gn:population":121,
    "gn:timezone":"Europe/Bucharest",
    "iso:country":"RO",
    "wof:name":"Calene",
    "wof:placetype":"locality",
    "wof:population":121
},
  "geometry": {"coordinates":[23.43746,45.83284],"type":"Point"}
}