{
  "type": "Feature",
  "properties": {
    "gn:admin1_code":"03",
    "gn:admin2_code":"19631.0",
    "gn:asciiname":"Ciuresti",
    "gn:country_code":"RO",
    "gn:dem":477,
    "gn:feature_class":"P",
    "gn:feature_code":"PPL",
    "gn:name":"Ciure\u015fti",
    "gn:population":0,
    "gn:timezone":"Europe/Bucharest",
    "iso:country":"RO",
    "wof:name":"Ciuresti",
    "wof:placetype":"locality"
},
  "geometry": {"coordinates":[24.65,45.18333],"type":"Point"}
}