{
  "type": "Feature",
  "properties": {
    "gn:admin1_code":"12",
    "gn:admin2_code":"52160.0",
    "gn:asciiname":"Groapa",
    "gn:country_code":"RO",
    "gn:dem":685,
    "gn:feature_class":"P",
    "gn:feature_code":"PPL",
    "gn:name":"Groapa",
    "gn:population":0,
    "gn:timezone":"Europe/Bucharest",
    "iso:country":"RO",
    "name:ron_x_preferred":[
        "R\u00e2ul Groapa"
    ],
    "wof:lang_x_official":[
        "ron"
    ],
    "wof:lang_x_spoken":[
        "ron"
    ],
    "wof:name":"Groapa",
    "wof:placetype":"locality"
},
  "geometry": {"coordinates":[22.41667,45.03333],"type":"Point"}
}