{
  "type": "Feature",
  "properties": {
    "gn:country":"RO",
    "gn:fcode":"PPLA2",
    "gn:population":1819,
    "iso:country":"RO",
    "name:ceb_x_preferred":[
        "Leleasca"
    ],
    "name:eng_x_preferred":[
        "Leleasca"
    ],
    "name:fra_x_preferred":[
        "Leleasca"
    ],
    "name:ita_x_preferred":[
        "Leleasca"
    ],
    "name:nld_x_preferred":[
        "Leleasca"
    ],
    "name:por_x_preferred":[
        "Leleasca"
    ],
    "name:ron_x_preferred":[
        "Leleasca"
    ],
    "name:srp_x_preferred":[
        "\u041b\u0435\u0459\u0430\u0441\u043a\u0430"
    ],
    "name:ukr_x_preferred":[
        "\u041b\u0435\u043b\u044f\u0441\u043a\u0430"
    ],
    "name:und_x_variant":[
        "\u015etef\u0103ne\u015fti"
    ],
    "name:vie_x_preferred":[
        "Leleasca"
    ],
    "name:vol_x_preferred":[
        "Leleasca"
    ],
    "qs_pg:aaroncc":"RO",
    "qs_pg:gn_country":"RO",
    "qs_pg:gn_fcode":"PPLA2",
    "qs_pg:gn_pop":1819,
    "qs_pg:name":"Leleasca",
    "qs_pg:name_adm0":"Rom\u00e2nia",
    "qs_pg:name_adm1":"Olt",
    "qs_pg:photos_9r":0,
    "qs_pg:photos_sr":0,
    "qs_pg:pop_sr":3,
    "qs_pg:qs_pg_placetype":"locality",
    "qs_pg:qs_pg_placetype_gp":"Town",
    "qs_pg:woe_adm0":23424933,
    "woe:adm0_id":23424933,
    "woe:name_adm0":"Rom\u00e2nia",
    "woe:name_adm1":"Olt",
    "woe:placetype":"Town",
    "wof:name":"Leleasca",
    "wof:placetype":"locality",
    "wof:population":1819
},
  "geometry": {"coordinates":[24.43333,44.78333],"type":"Point"}
}