{
  "type": "Feature",
  "properties": {
    "gn:admin1_code":"04",
    "gn:admin2_code":"24034.0",
    "gn:asciiname":"Radoaia",
    "gn:country_code":"RO",
    "gn:dem":375,
    "gn:feature_class":"P",
    "gn:feature_code":"PPL",
    "gn:name":"R\u0103doaia",
    "gn:population":987,
    "gn:timezone":"Europe/Bucharest",
    "iso:country":"RO",
    "wof:name":"Radoaia",
    "wof:placetype":"locality",
    "wof:population":987
},
  "geometry": {"coordinates":[26.92802,46.30943],"type":"Point"}
}