{
  "type": "Feature",
  "properties": {
    "gn:admin1_code":"25",
    "gn:admin2_code":"109354.0",
    "gn:asciiname":"Fericea",
    "gn:country_code":"RO",
    "gn:dem":357,
    "gn:feature_class":"P",
    "gn:feature_code":"PPL",
    "gn:name":"Fericea",
    "gn:population":489,
    "gn:timezone":"Europe/Bucharest",
    "iso:country":"RO",
    "wof:name":"Fericea",
    "wof:placetype":"locality",
    "wof:population":489
},
  "geometry": {"coordinates":[23.3937,47.40663],"type":"Point"}
}