{
  "type": "Feature",
  "properties": {
    "gn:admin1_code":"02",
    "gn:admin2_code":"10104.0",
    "gn:asciiname":"Capruta",
    "gn:country_code":"RO",
    "gn:dem":147,
    "gn:feature_class":"P",
    "gn:feature_code":"PPL",
    "gn:name":"C\u0103pru\u021ba",
    "gn:population":348,
    "gn:timezone":"Europe/Bucharest",
    "iso:country":"RO",
    "name:ron_x_preferred":[
        "C\u0103pru\u021ba"
    ],
    "name:und_x_variant":[
        "Kaprucza",
        "Maroskapronca",
        "Maroskaproncza"
    ],
    "wof:name":"Capruta",
    "wof:placetype":"locality",
    "wof:population":348
},
  "geometry": {"coordinates":[22.02672,46.08886],"type":"Point"}
}