{
  "type": "Feature",
  "properties": {
    "gn:admin1_code":"32",
    "gn:admin2_code":"138770.0",
    "gn:asciiname":"Huta Chegii",
    "gn:country_code":"RO",
    "gn:dem":152,
    "gn:feature_class":"P",
    "gn:feature_code":"PPL",
    "gn:name":"Huta Chegii",
    "gn:population":0,
    "gn:timezone":"Europe/Bucharest",
    "iso:country":"RO",
    "name:und_x_variant":[
        "Chegea-Huta",
        "Huta",
        "Huta Chegii"
    ],
    "wof:lang_x_official":[
        "ron"
    ],
    "wof:lang_x_spoken":[
        "ron"
    ],
    "wof:name":"Huta Chegii",
    "wof:placetype":"locality"
},
  "geometry": {"coordinates":[22.68333,47.48333],"type":"Point"}
}