{
  "type": "Feature",
  "properties": {
    "gn:admin1_code":"39",
    "gn:admin2_code":"174085.0",
    "gn:asciiname":"Draganu",
    "gn:cc2":"RO",
    "gn:country_code":"RO",
    "gn:dem":234,
    "gn:feature_class":"P",
    "gn:feature_code":"PPL",
    "gn:name":"Dr\u0103ganu",
    "gn:population":752,
    "gn:timezone":"Europe/Bucharest",
    "iso:country":"RO",
    "name:und_x_variant":[
        "Dr\u0103ganul",
        "Dr\u0103ganu"
    ],
    "wof:name":"Draganu",
    "wof:placetype":"locality",
    "wof:population":752
},
  "geometry": {"coordinates":[24.00227000000001,44.71246],"type":"Point"}
}