{
  "type": "Feature",
  "properties": {
    "gn:admin1_code":"39",
    "gn:admin2_code":"174085.0",
    "gn:asciiname":"Draganu",
    "gn:cc2":"RO",
    "gn:country_code":"RO",
    "gn:dem":234,
    "gn:feature_class":"P",
    "gn:feature_code":"PPL",
    "gn:name":"Dr\u0103ganu",
    "gn:population":752,
    "gn:timezone":"Europe/Bucharest",
    "iso:country":"RO",
    "name:ara_x_preferred":[
        "\u062f\u0631\u0627\u063a\u0627\u0646\u0648"
    ],
    "name:ceb_x_preferred":[
        "Comuna Dr\u0103ganu"
    ],
    "name:ita_x_preferred":[
        "Dr\u0103ganu"
    ],
    "name:mkd_x_preferred":[
        "\u0414\u0440\u0430\u0433\u0430\u043d\u0443"
    ],
    "name:msa_x_preferred":[
        "Dr\u0103ganu"
    ],
    "name:nld_x_preferred":[
        "Dr\u0103ganu"
    ],
    "name:por_x_preferred":[
        "Dr\u0103ganu"
    ],
    "name:ron_x_preferred":[
        "Comuna Dr\u0103ganu"
    ],
    "name:sqi_x_preferred":[
        "Dr\u0103ganu"
    ],
    "name:srp_x_preferred":[
        "\u041e\u043f\u0448\u0442\u0438\u043d\u0430 \u0414\u0440\u0430\u0433\u0430\u043d\u0443"
    ],
    "name:ukr_x_preferred":[
        "\u0414\u0440\u0435\u0433\u0430\u043d\u0443"
    ],
    "name:und_x_variant":[
        "Dr\u0103ganul"
    ],
    "name:vie_x_preferred":[
        "Dr\u0103ganu"
    ],
    "name:vol_x_preferred":[
        "Dr\u0103ganu"
    ],
    "name:zho_x_preferred":[
        "\u5fb7\u52d2\u52a0\u52aa\u9109"
    ],
    "wof:name":"Draganu",
    "wof:placetype":"locality",
    "wof:population":752
},
  "geometry": {"coordinates":[24.00227000000001,44.71246],"type":"Point"}
}