{
  "type": "Feature",
  "properties": {
    "gn:admin1_code":"38",
    "gn:admin2_code":"165069.0",
    "gn:asciiname":"Curteni",
    "gn:country_code":"RO",
    "gn:dem":144,
    "gn:feature_class":"P",
    "gn:feature_code":"PPL",
    "gn:name":"Curteni",
    "gn:population":277,
    "gn:timezone":"Europe/Bucharest",
    "iso:country":"RO",
    "wof:name":"Curteni",
    "wof:placetype":"locality",
    "wof:population":277
},
  "geometry": {"coordinates":[27.93443,46.59999000000001],"type":"Point"}
}