{
  "type": "Feature",
  "properties": {
    "gn:admin1_code":"14",
    "gn:admin2_code":"62397.0",
    "gn:asciiname":"Valcelele",
    "gn:country_code":"RO",
    "gn:dem":67,
    "gn:feature_class":"P",
    "gn:feature_code":"PPL",
    "gn:name":"V\u00e2lcelele",
    "gn:population":270,
    "gn:timezone":"Europe/Bucharest",
    "iso:country":"RO",
    "name:und_x_variant":[
        "V\u00eelcelele",
        "Valal\u00ee",
        "Valal\u00e2",
        "V\u00eelcele"
    ],
    "wof:name":"Valcelele",
    "wof:placetype":"locality",
    "wof:population":270
},
  "geometry": {"coordinates":[28.34265,43.78407],"type":"Point"}
}