{
  "type": "Feature",
  "properties": {
    "gn:admin1_code":"26",
    "gn:admin2_code":"111916",
    "gn:asciiname":"Blidaru",
    "gn:country_code":"RO",
    "gn:dem":231,
    "gn:feature_class":"P",
    "gn:feature_code":"PPL",
    "gn:name":"Blidaru",
    "gn:population":62,
    "gn:timezone":"Europe/Bucharest",
    "iso:country":"RO",
    "wof:name":"Blidaru",
    "wof:placetype":"locality",
    "wof:population":62
},
  "geometry": {"coordinates":[23.07003,44.55928],"type":"Point"}
}