{
  "type": "Feature",
  "properties": {
    "gn:admin1_code":"40",
    "gn:admin2_code":"175732",
    "gn:asciiname":"Bontesti",
    "gn:country_code":"RO",
    "gn:dem":228,
    "gn:feature_class":"P",
    "gn:feature_code":"PPL",
    "gn:name":"Bon\u021be\u0219ti",
    "gn:population":447,
    "gn:timezone":"Europe/Bucharest",
    "iso:country":"RO",
    "wof:name":"Bontesti",
    "wof:placetype":"locality",
    "wof:population":447
},
  "geometry": {"coordinates":[27.05372,45.67909],"type":"Point"}
}