{
  "type": "Feature",
  "properties": {
    "gn:admin1_code":"38",
    "gn:admin2_code":"166869",
    "gn:asciiname":"Bancesti",
    "gn:cc2":"RO",
    "gn:country_code":"RO",
    "gn:dem":182,
    "gn:feature_class":"P",
    "gn:feature_code":"PPL",
    "gn:name":"B\u0103nce\u0219ti",
    "gn:population":185,
    "gn:timezone":"Europe/Bucharest",
    "iso:country":"RO",
    "name:und_x_variant":[
        "B\u0103ne\u015fti",
        "B\u0103nce\u015fti"
    ],
    "wof:name":"Bancesti",
    "wof:placetype":"locality",
    "wof:population":185
},
  "geometry": {"coordinates":[27.44796,46.54032],"type":"Point"}
}