{
  "type": "Feature",
  "properties": {
    "gn:admin1_code":"01",
    "gn:admin2_code":"1213.0",
    "gn:asciiname":"Garbovita",
    "gn:cc2":"RO",
    "gn:country_code":"RO",
    "gn:dem":385,
    "gn:feature_class":"P",
    "gn:feature_code":"PPL",
    "gn:name":"G\u00e2rbovi\u0163a",
    "gn:population":0,
    "gn:timezone":"Europe/Bucharest",
    "iso:country":"RO",
    "name:und_x_variant":[
        "G\u00e2rbovi\u0163a",
        "G\u00eerbovi\u0163a"
    ],
    "wof:name":"Garbovita",
    "wof:placetype":"locality"
},
  "geometry": {"coordinates":[23.63333,46.28333],"type":"Point"}
}