{
  "type": "Feature",
  "properties": {
    "gn:admin1_code":"11",
    "gn:admin2_code":"45673.0",
    "gn:asciiname":"Spidele",
    "gn:country_code":"RO",
    "gn:dem":403,
    "gn:feature_class":"P",
    "gn:feature_code":"PPL",
    "gn:name":"Spidele",
    "gn:population":62,
    "gn:timezone":"Europe/Bucharest",
    "iso:country":"RO",
    "wof:name":"Spidele",
    "wof:placetype":"locality",
    "wof:population":62
},
  "geometry": {"coordinates":[26.84842,45.51839],"type":"Point"}
}