{
  "type": "Feature",
  "properties": {
    "gn:admin1_code":"05",
    "gn:admin2_code":"29760",
    "gn:asciiname":"Baleni",
    "gn:country_code":"RO",
    "gn:dem":205,
    "gn:feature_class":"P",
    "gn:feature_code":"PPL",
    "gn:name":"B\u0103leni",
    "gn:population":263,
    "gn:timezone":"Europe/Bucharest",
    "iso:country":"RO",
    "name:ron_x_preferred":[
        "B\u0103leni"
    ],
    "name:und_x_variant":[
        "Balal\u00e9ny",
        "B\u0103l\u0103leni"
    ],
    "wof:name":"Baleni",
    "wof:placetype":"locality",
    "wof:population":263
},
  "geometry": {"coordinates":[22.3993,46.60933],"type":"Point"}
}