{
  "type": "Feature",
  "properties": {
    "iso:country":"RO",
    "name:ara_x_preferred":[
        "\u0646\u064a\u0643\u0648\u0644\u0627\u064a \u0628\u0627\u0644\u062a\u0634\u064a\u0633\u0643\u0648"
    ],
    "name:deu_x_preferred":[
        "Nicolae B\u0103lcescu"
    ],
    "name:epo_x_preferred":[
        "Nicolae B\u0103lcescu"
    ],
    "name:fra_x_preferred":[
        "Nicolae B\u0103lcescu"
    ],
    "name:heb_x_preferred":[
        "\u05e0\u05d9\u05e7\u05d5\u05dc\u05d0\u05d9\u05d4 \u05d1\u05dc\u05e6'\u05e1\u05e7\u05d5"
    ],
    "name:hun_x_preferred":[
        "Nicolae B\u0103lcescu"
    ],
    "name:ind_x_preferred":[
        "Nicolae B\u0103lcescu"
    ],
    "name:ita_x_preferred":[
        "Nicolae B\u0103lcescu"
    ],
    "name:pol_x_preferred":[
        "Nicolae B\u0103lcescu"
    ],
    "name:ron_x_preferred":[
        "Nicolae B\u0103lcescu"
    ],
    "name:rum_x_colloquial":[
        "Baelcescu Nicolae",
        "Balcescu Nicolae",
        "Nicolae Baelcescu",
        "Nicolae Balcescu"
    ],
    "name:rum_x_variant":[
        "B\u0103lcescu Nicolae"
    ],
    "name:spa_x_preferred":[
        "Nicolae B\u0103lcescu"
    ],
    "name:unk_x_variant":[
        "B\u0103lcescu Nicolae",
        "Nicolae B\u0103lcescu"
    ],
    "qs:gn_adm0_cc":"RO",
    "qs:gn_fcode":"PPLX",
    "qs:gn_local":668732,
    "qs:gn_nam_loc":"Roman, Neamt, RO",
    "qs:gn_namadm1":"00",
    "qs:gn_name":"Nicolae B\u0103lcescu",
    "qs:local_max":485,
    "qs:local_sum":485,
    "qs:localhoods":1,
    "qs:name":"Nicolae B\u0103lcescu",
    "qs:name_adm0":"Rom\u00e2nia",
    "qs:name_adm1":"Neamt",
    "qs:name_local":"Roman",
    "qs:photo_max":432,
    "qs:photo_sum":485,
    "qs:placetype":"Suburb",
    "qs:quad_count":14,
    "qs:woe_adm0":23424933,
    "qs:woe_adm1":2346641,
    "qs:woe_adm2":0,
    "qs:woe_lau":0,
    "qs:woe_local":879176,
    "qs:woe_ver":"7.10.0",
    "wof:lang":[
        "rum"
    ],
    "wof:name":"Nicolae B\u0103lcescu",
    "wof:placetype":"neighbourhood"
},
  "geometry": {"coordinates":[26.933702,46.913171],"type":"Point"}
}