{
  "type": "Feature",
  "properties": {
    "iso:country":"RO",
    "name:ara_x_preferred":[
        "\u0646\u064a\u0643\u0648\u0644\u0627\u064a \u0628\u0627\u0644\u062a\u0634\u064a\u0633\u0643\u0648"
    ],
    "name:deu_x_preferred":[
        "Nicolae B\u0103lcescu"
    ],
    "name:epo_x_preferred":[
        "Nicolae B\u0103lcescu"
    ],
    "name:fra_x_preferred":[
        "Nicolae B\u0103lcescu"
    ],
    "name:heb_x_preferred":[
        "\u05e0\u05d9\u05e7\u05d5\u05dc\u05d0\u05d9\u05d4 \u05d1\u05dc\u05e6'\u05e1\u05e7\u05d5"
    ],
    "name:hun_x_preferred":[
        "Nicolae B\u0103lcescu"
    ],
    "name:hye_x_preferred":[
        "\u0546\u056b\u056f\u0578\u056c\u0561\u0575\u0565 \u0532\u0568\u056c\u0579\u0565\u057d\u056f\u0578\u0582"
    ],
    "name:ind_x_preferred":[
        "Nicolae B\u0103lcescu"
    ],
    "name:ita_x_preferred":[
        "Nicolae B\u0103lcescu"
    ],
    "name:pol_x_preferred":[
        "Nicolae B\u0103lcescu"
    ],
    "name:ron_x_preferred":[
        "Nicolae B\u0103lcescu"
    ],
    "name:rum_x_colloquial":[
        "Baelcescu Nicolae",
        "Balcescu Nicolae",
        "Nicolae Baelcescu",
        "Nicolae Balcescu"
    ],
    "name:rum_x_variant":[
        "B\u0103lcescu Nicolae"
    ],
    "name:rus_x_preferred":[
        "\u0411\u044d\u043b\u0447\u0435\u0441\u043a\u0443"
    ],
    "name:spa_x_preferred":[
        "Nicolae B\u0103lcescu"
    ],
    "name:ukr_x_preferred":[
        "\u041d\u0456\u043a\u043e\u043b\u0430\u0454 \u0411\u0435\u043b\u0447\u0435\u0441\u043a\u0443"
    ],
    "qs:gn_adm0_cc":"RO",
    "qs:gn_fcode":"PPLX",
    "qs:gn_local":668732,
    "qs:gn_nam_loc":"Roman, Neamt, RO",
    "qs:gn_namadm1":"00",
    "qs:gn_name":"Nicolae B\u0103lcescu",
    "qs:local_max":485,
    "qs:local_sum":485,
    "qs:localhoods":1,
    "qs:name":"Nicolae B\u0103lcescu",
    "qs:name_adm0":"Rom\u00e2nia",
    "qs:name_adm1":"Neamt",
    "qs:name_local":"Roman",
    "qs:photo_max":432,
    "qs:photo_sum":485,
    "qs:placetype":"Suburb",
    "qs:quad_count":14,
    "qs:woe_adm0":23424933,
    "qs:woe_adm1":2346641,
    "qs:woe_adm2":0,
    "qs:woe_lau":0,
    "qs:woe_local":879176,
    "qs:woe_ver":"7.10.0",
    "wof:lang_x_official":[
        "ron"
    ],
    "wof:lang_x_spoken":[
        "ron"
    ],
    "wof:name":"Nicolae B\u0103lcescu",
    "wof:placetype":"neighbourhood"
},
  "geometry": {"coordinates":[26.933702,46.913171],"type":"Point"}
}