{
  "type": "Feature",
  "properties": {
    "gn:admin1_code":"11",
    "gn:admin2_code":"50415.0",
    "gn:asciiname":"Harboca",
    "gn:cc2":"RO",
    "gn:country_code":"RO",
    "gn:dem":195,
    "gn:feature_class":"P",
    "gn:feature_code":"PPL",
    "gn:name":"H\u00e2rboca",
    "gn:population":0,
    "gn:timezone":"Europe/Bucharest",
    "iso:country":"RO",
    "name:und_x_variant":[
        "Haiboca",
        "H\u00eerboca"
    ],
    "wof:name":"Harboca",
    "wof:placetype":"locality"
},
  "geometry": {"coordinates":[26.88333,45.31667],"type":"Point"}
}