{
  "type": "Feature",
  "properties": {
    "gn:admin1_code":"04",
    "gn:admin2_code":"21007.0",
    "gn:asciiname":"Diaconesti",
    "gn:country_code":"RO",
    "gn:dem":541,
    "gn:feature_class":"P",
    "gn:feature_code":"PPL",
    "gn:name":"Diacone\u0219ti",
    "gn:population":256,
    "gn:timezone":"Europe/Bucharest",
    "iso:country":"RO",
    "wof:name":"Diaconesti",
    "wof:placetype":"locality",
    "wof:population":256
},
  "geometry": {"coordinates":[26.26972,46.46112],"type":"Point"}
}