{
  "type": "Feature",
  "properties": {
    "gn:admin1_code":"17",
    "gn:admin2_code":"74171.0",
    "gn:asciiname":"Sumandra",
    "gn:country_code":"RO",
    "gn:dem":234,
    "gn:feature_class":"P",
    "gn:feature_code":"PPL",
    "gn:name":"\u0218umandra",
    "gn:population":120,
    "gn:timezone":"Europe/Bucharest",
    "iso:country":"RO",
    "wof:name":"Sumandra",
    "wof:placetype":"locality",
    "wof:population":120
},
  "geometry": {"coordinates":[23.28956,44.46396],"type":"Point"}
}