{
  "type": "Feature",
  "properties": {
    "gn:admin1_code":"17",
    "gn:admin2_code":"70726.0",
    "gn:asciiname":"Ciunei",
    "gn:country_code":"RO",
    "gn:dem":139,
    "gn:feature_class":"P",
    "gn:feature_code":"PPL",
    "gn:name":"Ciunei",
    "gn:population":0,
    "gn:timezone":"Europe/Bucharest",
    "iso:country":"RO",
    "name:und_x_variant":[
        "Ciumei",
        "Ciunei"
    ],
    "wof:name":"Ciunei",
    "wof:placetype":"locality"
},
  "geometry": {"coordinates":[24.08333,44.06667],"type":"Point"}
}