{
  "type": "Feature",
  "properties": {
    "gn:admin1_code":"11",
    "gn:admin2_code":"44863.0",
    "gn:asciiname":"Campeni",
    "gn:cc2":"RO",
    "gn:country_code":"RO",
    "gn:dem":74,
    "gn:feature_class":"P",
    "gn:feature_code":"PPL",
    "gn:name":"C\u00e2mpeni",
    "gn:population":232,
    "gn:timezone":"Europe/Bucharest",
    "iso:country":"RO",
    "name:und_x_variant":[
        "B\u0103deni Milui\u0163i",
        "B\u0103denii Milui\u0163ii",
        "C\u00eempeni"
    ],
    "wof:name":"Campeni",
    "wof:placetype":"locality",
    "wof:population":232
},
  "geometry": {"coordinates":[26.63300000000001,44.96808],"type":"Point"}
}