{
  "type": "Feature",
  "properties": {
    "gn:admin1_code":"26",
    "gn:admin2_code":"110688.0",
    "gn:asciiname":"Calinestii de Sus",
    "gn:cc2":"RO",
    "gn:country_code":"RO",
    "gn:dem":607,
    "gn:feature_class":"P",
    "gn:feature_code":"PPL",
    "gn:name":"C\u0103line\u0219tii de Sus",
    "gn:population":102,
    "gn:timezone":"Europe/Bucharest",
    "iso:country":"RO",
    "name:und_x_variant":[
        "Kaline\u0161ti-de Sus",
        "C\u0103line\u015fti de Sus",
        "C\u0103line\u015ftii de Sus"
    ],
    "wof:name":"Calinestii de Sus",
    "wof:placetype":"locality",
    "wof:population":102
},
  "geometry": {"coordinates":[22.64837,44.81974],"type":"Point"}
}