{
  "type": "Feature",
  "properties": {
    "gn:admin1_code":"12",
    "gn:admin2_code":"53791",
    "gn:asciiname":"Bogodint",
    "gn:cc2":"RO",
    "gn:country_code":"RO",
    "gn:dem":145,
    "gn:feature_class":"P",
    "gn:feature_code":"PPL",
    "gn:name":"Bogodin\u021b",
    "gn:population":232,
    "gn:timezone":"Europe/Bucharest",
    "iso:country":"RO",
    "name:und_x_variant":[
        "Bogadinac",
        "Bogodin\u0163i"
    ],
    "wof:name":"Bogodint",
    "wof:placetype":"locality",
    "wof:population":232
},
  "geometry": {"coordinates":[21.66234,44.89842],"type":"Point"}
}