{
  "type": "Feature",
  "properties": {
    "gn:admin1_code":"03",
    "gn:admin2_code":"17913",
    "gn:asciiname":"Poienari",
    "gn:country_code":"RO",
    "gn:dem":341,
    "gn:feature_class":"P",
    "gn:feature_code":"PPLA2",
    "gn:name":"Poienari",
    "gn:population":530,
    "gn:timezone":"Europe/Bucharest",
    "iso:country":"RO",
    "name:ceb_x_preferred":[
        "Comuna Poienari"
    ],
    "name:epo_x_preferred":[
        "Poienari"
    ],
    "name:fra_x_preferred":[
        "Poienari"
    ],
    "name:ita_x_preferred":[
        "Poienari"
    ],
    "name:msa_x_preferred":[
        "Poienari"
    ],
    "name:nld_x_preferred":[
        "Poienari"
    ],
    "name:por_x_preferred":[
        "Poienari"
    ],
    "name:ron_x_preferred":[
        "Comuna Poienari"
    ],
    "name:srp_x_preferred":[
        "\u041e\u043f\u0448\u0442\u0438\u043d\u0430 \u041f\u043e\u0458\u0435\u043d\u0430\u0440\u0438"
    ],
    "name:ukr_x_preferred":[
        "\u041f\u043e\u0454\u043d\u0430\u0440\u0456"
    ],
    "name:vie_x_preferred":[
        "Poienari"
    ],
    "name:vol_x_preferred":[
        "Poienari"
    ],
    "name:zho_x_preferred":[
        "\u6ce2\u8036\u7d0d\u91cc\u9109"
    ],
    "wof:name":"Poienari",
    "wof:placetype":"locality",
    "wof:population":530
},
  "geometry": {"coordinates":[24.53056,45.07034],"type":"Point"}
}