{
  "type": "Feature",
  "properties": {
    "gn:admin1_code":"03",
    "gn:admin2_code":"17913",
    "gn:asciiname":"Poienari",
    "gn:country_code":"RO",
    "gn:dem":341,
    "gn:feature_class":"P",
    "gn:feature_code":"PPLA2",
    "gn:name":"Poienari",
    "gn:population":530,
    "gn:timezone":"Europe/Bucharest",
    "iso:country":"RO",
    "wof:name":"Poienari",
    "wof:placetype":"locality",
    "wof:population":530
},
  "geometry": {"coordinates":[24.53056,45.07034],"type":"Point"}
}