{
  "type": "Feature",
  "properties": {
    "gn:admin1_code":"29",
    "gn:admin2_code":"126825.0",
    "gn:asciiname":"Chilii",
    "gn:cc2":"RO",
    "gn:country_code":"RO",
    "gn:dem":108,
    "gn:feature_class":"P",
    "gn:feature_code":"PPL",
    "gn:name":"Chilii",
    "gn:population":171,
    "gn:timezone":"Europe/Bucharest",
    "iso:country":"RO",
    "name:ceb_x_preferred":[
        "Chilii"
    ],
    "name:deu_x_preferred":[
        "Chilii"
    ],
    "name:ron_x_preferred":[
        "Chilii"
    ],
    "name:srp_x_preferred":[
        "\u041a\u0438\u043b\u0438\u0458"
    ],
    "name:und_x_variant":[
        "Chilia"
    ],
    "wof:name":"Chilii",
    "wof:placetype":"locality",
    "wof:population":171
},
  "geometry": {"coordinates":[24.20947,44.26782],"type":"Point"}
}