{
  "type": "Feature",
  "properties": {
    "gn:admin1_code":"01",
    "gn:admin2_code":"1213.0",
    "gn:asciiname":"Gambas",
    "gn:cc2":"RO",
    "gn:country_code":"RO",
    "gn:dem":241,
    "gn:feature_class":"P",
    "gn:feature_code":"PPL",
    "gn:name":"G\u00e2mba\u015f",
    "gn:population":0,
    "gn:timezone":"Europe/Bucharest",
    "iso:country":"RO",
    "name:ara_x_preferred":[
        "\u062c\u0627\u0645\u0628\u0627\u0633"
    ],
    "name:cat_x_preferred":[
        "Gambas"
    ],
    "name:ces_x_preferred":[
        "Gambas"
    ],
    "name:deu_x_preferred":[
        "Gambas"
    ],
    "name:ell_x_preferred":[
        "Gambas"
    ],
    "name:epo_x_preferred":[
        "Gambaso"
    ],
    "name:fas_x_preferred":[
        "\u06af\u0627\u0645\u0628\u0627\u0633"
    ],
    "name:fin_x_preferred":[
        "Gambas"
    ],
    "name:fra_x_preferred":[
        "Gambas"
    ],
    "name:heb_x_preferred":[
        "\u05d2\u05d0\u05de\u05d1\u05e1"
    ],
    "name:ind_x_preferred":[
        "Gambas"
    ],
    "name:isl_x_preferred":[
        "Gambas"
    ],
    "name:ita_x_preferred":[
        "Gambas"
    ],
    "name:jpn_x_preferred":[
        "Gambas"
    ],
    "name:kor_x_preferred":[
        "\uac10\ubc14\uc2a4"
    ],
    "name:lat_x_preferred":[
        "Gambas"
    ],
    "name:lit_x_preferred":[
        "Gambas"
    ],
    "name:mal_x_preferred":[
        "\u0d17\u0d3e\u0d02\u0d2c\u0d3e\u0d38\u0d4d"
    ],
    "name:nld_x_preferred":[
        "Gambas"
    ],
    "name:pol_x_preferred":[
        "Gambas"
    ],
    "name:por_x_preferred":[
        "Gambas"
    ],
    "name:ron_x_preferred":[
        "Gambas"
    ],
    "name:rus_x_preferred":[
        "Gambas"
    ],
    "name:spa_x_preferred":[
        "Gambas"
    ],
    "name:swe_x_preferred":[
        "Gambas"
    ],
    "name:tur_x_preferred":[
        "Gambas"
    ],
    "name:ukr_x_preferred":[
        "Gambas"
    ],
    "name:und_x_variant":[
        "G\u00e2mba\u015f",
        "G\u00eemba\u015f"
    ],
    "name:zho_x_preferred":[
        "Gambas"
    ],
    "wof:name":"Gambas",
    "wof:placetype":"locality"
},
  "geometry": {"coordinates":[23.71667,46.35],"type":"Point"}
}