{
  "type": "Feature",
  "properties": {
    "gn:admin1_code":"01",
    "gn:admin2_code":"1213.0",
    "gn:asciiname":"Gambas",
    "gn:cc2":"RO",
    "gn:country_code":"RO",
    "gn:dem":241,
    "gn:feature_class":"P",
    "gn:feature_code":"PPL",
    "gn:name":"G\u00e2mba\u015f",
    "gn:population":0,
    "gn:timezone":"Europe/Bucharest",
    "iso:country":"RO",
    "name:und_x_variant":[
        "G\u00e2mba\u015f",
        "G\u00eemba\u015f"
    ],
    "wof:name":"Gambas",
    "wof:placetype":"locality"
},
  "geometry": {"coordinates":[23.71667,46.35],"type":"Point"}
}