{
  "type": "Feature",
  "properties": {
    "gn:admin1_code":"13",
    "gn:admin2_code":"56096.0",
    "gn:asciiname":"Cremenea",
    "gn:country_code":"RO",
    "gn:dem":268,
    "gn:feature_class":"P",
    "gn:feature_code":"PPL",
    "gn:name":"Cremenea",
    "gn:population":123,
    "gn:timezone":"Europe/Bucharest",
    "iso:country":"RO",
    "name:ceb_x_preferred":[
        "Cremenea"
    ],
    "name:deu_x_preferred":[
        "Cremenea"
    ],
    "name:ron_x_preferred":[
        "Cremenea"
    ],
    "name:srp_x_preferred":[
        "\u041a\u0440\u0435\u043c\u0435\u045a\u0430"
    ],
    "wof:name":"Cremenea",
    "wof:placetype":"locality",
    "wof:population":123
},
  "geometry": {"coordinates":[23.72584,47.14645],"type":"Point"}
}