{
  "type": "Feature",
  "properties": {
    "iso:country":"RO",
    "name:eng_x_preferred":[
        "Manastur"
    ],
    "name:ron_x_preferred":[
        "M\u0103n\u0103\u0219tur"
    ],
    "wof:lang_x_official":[
        "ron"
    ],
    "wof:lang_x_spoken":[
        "ron"
    ],
    "wof:name":"Manastur",
    "wof:placetype":"neighbourhood"
},
  "geometry": {"coordinates":[23.556068,46.754286],"type":"Point"}
}