{
  "type": "Feature",
  "properties": {
    "iso:country":"RO",
    "name:eng_x_preferred":[
        "Manastur"
    ],
    "name:ron_x_preferred":[
        "M\u0103n\u0103\u0219tur"
    ],
    "wof:name":"Manastur",
    "wof:placetype":"neighbourhood"
},
  "geometry": {"coordinates":[23.55606798110791,46.75428601611341],"type":"Point"}
}