{
  "type": "Feature",
  "properties": {
    "gn:admin1_code":"27",
    "gn:admin2_code":"119661.0",
    "gn:asciiname":"Vaidacuta",
    "gn:cc2":"RO",
    "gn:country_code":"RO",
    "gn:dem":368,
    "gn:feature_class":"P",
    "gn:feature_code":"PPL",
    "gn:name":"Vaidacu\u021ba",
    "gn:population":55,
    "gn:timezone":"Europe/Bucharest",
    "iso:country":"RO",
    "name:und_x_variant":[
        "Vajdacuta",
        "Vaidacuta"
    ],
    "wof:name":"Vaidacuta",
    "wof:placetype":"locality",
    "wof:population":55
},
  "geometry": {"coordinates":[24.52626,46.41906],"type":"Point"}
}