{
  "type": "Feature",
  "properties": {
    "gn:admin1_code":"26",
    "gn:admin2_code":"110027.0",
    "gn:asciiname":"Obarsia-Closani",
    "gn:cc2":"RO",
    "gn:country_code":"RO",
    "gn:dem":556,
    "gn:feature_class":"P",
    "gn:feature_code":"PPLA2",
    "gn:name":"Ob\u00e2r\u015fia-Clo\u015fani",
    "gn:population":0,
    "gn:timezone":"Europe/Bucharest",
    "iso:country":"RO",
    "name:ceb_x_preferred":[
        "Comuna Ob\u00e2r\u0219ia-Clo\u0219ani"
    ],
    "name:fra_x_preferred":[
        "Ob\u00e2r\u0219ia-Clo\u0219ani"
    ],
    "name:ita_x_preferred":[
        "Ob\u00e2r\u0219ia-Clo\u0219ani"
    ],
    "name:msa_x_preferred":[
        "Ob\u00e2r\u015fia-Clo\u015fani"
    ],
    "name:nld_x_preferred":[
        "Ob\u00e2r\u0219ia-Clo\u0219ani"
    ],
    "name:por_x_preferred":[
        "Ob\u00e2r\u015fia-Clo\u015fani"
    ],
    "name:ron_x_preferred":[
        "Comuna Ob\u00e2r\u0219ia-Clo\u0219ani"
    ],
    "name:srp_x_preferred":[
        "\u041e\u043f\u0448\u0442\u0438\u043d\u0430 \u041e\u0431\u0430\u0440\u0448\u0438\u0458\u0430-\u041a\u043b\u043e\u0448\u0430\u043d\u0438"
    ],
    "name:ukr_x_preferred":[
        "\u041e\u0431\u0438\u0440\u0448\u0456\u044f-\u041a\u043b\u043e\u0448\u0430\u043d\u044c"
    ],
    "name:und_x_variant":[
        "Ob\u00eer\u015fia-Clo\u015fani"
    ],
    "name:vol_x_preferred":[
        "Ob\u00e2r\u015fia-Clo\u015fani"
    ],
    "name:zho_x_preferred":[
        "\u5967\u4f2f\u723e\u5e0c\u4e9e\uff0d\u514b\u6d1b\u6c99\u5c3c\u9109"
    ],
    "wof:name":"Obarsia-Closani",
    "wof:placetype":"locality"
},
  "geometry": {"coordinates":[22.68333,45.01667],"type":"Point"}
}