{
  "type": "Feature",
  "properties": {
    "gn:admin1_code":"26",
    "gn:admin2_code":"110027.0",
    "gn:asciiname":"Obarsia-Closani",
    "gn:cc2":"RO",
    "gn:country_code":"RO",
    "gn:dem":556,
    "gn:feature_class":"P",
    "gn:feature_code":"PPLA2",
    "gn:name":"Ob\u00e2r\u015fia-Clo\u015fani",
    "gn:population":0,
    "gn:timezone":"Europe/Bucharest",
    "iso:country":"RO",
    "name:und_x_variant":[
        "Ob\u00e2r\u015fia-Clo\u015fani",
        "Ob\u00eer\u015fia-Clo\u015fani"
    ],
    "wof:name":"Obarsia-Closani",
    "wof:placetype":"locality"
},
  "geometry": {"coordinates":[22.68333,45.01667],"type":"Point"}
}