{
  "type": "Feature",
  "properties": {
    "gn:gn_country":"RO",
    "gn:gn_fcode":"PPL",
    "gn:gn_pop":3616,
    "gn:population":3616,
    "iso:country":"RO",
    "name:eng_x_preferred":[
        "Dr\u0103c\u0219ani"
    ],
    "name:fra_x_preferred":[
        "Dr\u0103c\u0219ani"
    ],
    "name:nld_x_preferred":[
        "Dr\u0103c\u0219ani"
    ],
    "name:ron_x_preferred":[
        "Dr\u0103c\u0219ani"
    ],
    "name:ukr_x_preferred":[
        "\u0414\u0440\u0435\u043a\u0448\u0430\u043d\u044c"
    ],
    "name:unk_x_variant":[
        "Dr\u0103c\u015fenei"
    ],
    "qs_pg:aaroncc":"RO",
    "qs_pg:gn_country":"RO",
    "qs_pg:gn_fcode":"PPL",
    "qs_pg:gn_pop":3616,
    "qs_pg:name":"Dr\u0103c\u0219ani",
    "qs_pg:name_adm0":"Rom\u00e2nia",
    "qs_pg:name_adm1":"Teleorman",
    "qs_pg:photos_9r":0,
    "qs_pg:photos_sr":0,
    "qs_pg:pop_sr":4,
    "qs_pg:qs_pg_placetype":"locality",
    "qs_pg:qs_pg_placetype_gp":"Town",
    "qs_pg:woe_adm0":23424933,
    "woe:adm0_id":23424933,
    "woe:name_adm0":"Rom\u00e2nia",
    "woe:name_adm1":"Teleorman",
    "woe:placetype":"Town",
    "wof:name":"Dr\u0103c\u0219ani",
    "wof:placetype":"locality",
    "wof:population":3616
},
  "geometry": {"coordinates":[24.98333,44.21667],"type":"Point"}
}