{
  "type": "Feature",
  "properties": {
    "gn:admin1_code":"42",
    "gn:admin2_code":"100781.0",
    "gn:asciiname":"Varlaam",
    "gn:cc2":"RO",
    "gn:country_code":"RO",
    "gn:dem":78,
    "gn:feature_class":"P",
    "gn:feature_code":"PPL",
    "gn:name":"Varlaam",
    "gn:population":625,
    "gn:timezone":"Europe/Bucharest",
    "iso:country":"RO",
    "name:bul_x_preferred":[
        "\u0412\u0430\u0440\u043b\u0430\u0430\u043c"
    ],
    "name:ceb_x_preferred":[
        "Varlaam"
    ],
    "name:deu_x_preferred":[
        "Varlaam"
    ],
    "name:fra_x_preferred":[
        "Varlaam"
    ],
    "name:ron_x_preferred":[
        "Varlaam"
    ],
    "name:rus_x_preferred":[
        "\u0412\u0430\u0440\u043b\u0430\u0430\u043c"
    ],
    "name:srp_x_preferred":[
        "\u0412\u0430\u0440\u043b\u0430\u0430\u043c"
    ],
    "name:ukr_x_preferred":[
        "\u0412\u0430\u0440\u043b\u0430\u0430\u043c"
    ],
    "name:und_x_variant":[
        "Varlam"
    ],
    "wof:name":"Varlaam",
    "wof:placetype":"locality",
    "wof:population":625
},
  "geometry": {"coordinates":[26.09098,44.2447],"type":"Point"}
}