{
  "type": "Feature",
  "properties": {
    "gn:admin1_code":"39",
    "gn:admin2_code":"169039.0",
    "gn:asciiname":"Grosi",
    "gn:cc2":"RO",
    "gn:country_code":"RO",
    "gn:dem":350,
    "gn:feature_class":"P",
    "gn:feature_code":"PPL",
    "gn:name":"Gro\u0219i",
    "gn:population":481,
    "gn:timezone":"Europe/Bucharest",
    "iso:country":"RO",
    "name:und_x_variant":[
        "Grosii",
        "Gro\u015fi"
    ],
    "wof:name":"Grosi",
    "wof:placetype":"locality",
    "wof:population":481
},
  "geometry": {"coordinates":[24.03827,44.99733],"type":"Point"}
}