{
  "type": "Feature",
  "properties": {
    "gn:population":1040,
    "iso:country":"RO",
    "name:ceb_x_preferred":[
        "P\u0103durea Neagr\u0103"
    ],
    "name:eng_x_preferred":[
        "P\u0103durea Neagr\u0103"
    ],
    "name:epo_x_preferred":[
        "P\u0103durea Neagr\u0103"
    ],
    "name:hun_x_preferred":[
        "Feketeerd\u0151"
    ],
    "name:nld_x_preferred":[
        "P\u0103durea Neagr\u0103"
    ],
    "name:ron_x_preferred":[
        "P\u0103durea Neagr\u0103"
    ],
    "name:srp_x_preferred":[
        "\u041f\u0430\u0434\u0443\u0440\u0435\u0430 \u040a\u0430\u0433\u0440\u0430"
    ],
    "name:ukr_x_preferred":[
        "\u041f\u0435\u0434\u0443\u0440\u044f-\u041d\u044f\u0433\u0440\u0435"
    ],
    "qs:a0":"Rom\u00e2nia",
    "qs:a1":"*Bihor",
    "qs:a1r":"0",
    "qs:adm0":"Rom\u00e2nia",
    "qs:la_lc":"*",
    "qs:level":"locality",
    "qs:loc":"P\u0103durea Neagr\u0103",
    "qs:loc_alt":"Padurea Neagra",
    "qs:pop":0,
    "qs:type":"buffered point",
    "wof:name":"P\u0103durea Neagr\u0103",
    "wof:placetype":"locality",
    "wof:population":1040
},
  "geometry": {"coordinates":[22.429587,47.157521],"type":"Point"}
}