{
  "type": "Feature",
  "properties": {
    "gn:country":"RO",
    "gn:fcode":"PPL",
    "gn:population":4201,
    "iso:country":"RO",
    "name:eng_x_preferred":[
        "Vizantea M\u0103n\u0103stireasc\u0103"
    ],
    "name:fra_x_preferred":[
        "Vizantea M\u0103n\u0103stireasc\u0103"
    ],
    "name:ita_x_preferred":[
        "Vizantea M\u0103n\u0103stireasc\u0103"
    ],
    "name:nld_x_preferred":[
        "Vizantea M\u0103n\u0103stireasc\u0103"
    ],
    "name:ron_x_preferred":[
        "Vizantea M\u0103n\u0103stireasc\u0103"
    ],
    "name:srp_x_preferred":[
        "\u0412\u0438\u0437\u0430\u043d\u0442\u0435\u0430-\u041c\u0430\u043d\u0430\u0441\u0442\u0438\u0440\u0435\u0430\u0441\u043a\u0430"
    ],
    "name:ukr_x_preferred":[
        "\u0412\u0456\u0437\u0430\u043d\u0442\u044f-\u041c\u0435\u043d\u0435\u0441\u0442\u0456\u0440\u044f\u0441\u043a\u0435"
    ],
    "name:und_x_variant":[
        "Vizantea"
    ],
    "qs_pg:aaroncc":"RO",
    "qs_pg:gn_country":"RO",
    "qs_pg:gn_fcode":"PPL",
    "qs_pg:gn_pop":4201,
    "qs_pg:name":"Vizantea-M\u00een\u0103stireasc\u0103",
    "qs_pg:name_adm0":"Rom\u00e2nia",
    "qs_pg:name_adm1":"Vrancea",
    "qs_pg:photos_9r":0,
    "qs_pg:photos_sr":0,
    "qs_pg:pop_sr":4,
    "qs_pg:qs_pg_placetype":"locality",
    "qs_pg:qs_pg_placetype_gp":"Town",
    "qs_pg:woe_adm0":23424933,
    "woe:adm0_id":23424933,
    "woe:name_adm0":"Rom\u00e2nia",
    "woe:name_adm1":"Vrancea",
    "woe:placetype":"Town",
    "wof:name":"Vizantea-M\u00een\u0103stireasc\u0103",
    "wof:placetype":"locality",
    "wof:population":4201
},
  "geometry": {"coordinates":[26.78333,45.98333],"type":"Point"}
}