{
  "type": "Feature",
  "properties": {
    "gn:admin1_code":"36",
    "gn:admin2_code":"156035.0",
    "gn:asciiname":"Charlotenburg",
    "gn:cc2":"RO",
    "gn:country_code":"RO",
    "gn:dem":151,
    "gn:feature_class":"P",
    "gn:feature_code":"PPL",
    "gn:name":"Charlotenburg",
    "gn:population":135,
    "gn:timezone":"Europe/Bucharest",
    "iso:country":"RO",
    "name:und_x_variant":[
        "\u015earlotenburg",
        "Baricza",
        "Saroltav\u00e1r",
        "Charlottenburg",
        "\u015earlota",
        "Charlotenburg"
    ],
    "wof:name":"Charlotenburg",
    "wof:placetype":"locality",
    "wof:population":135
},
  "geometry": {"coordinates":[21.52228,45.98042],"type":"Point"}
}