{
  "type": "Feature",
  "properties": {
    "gn:admin1_code":"12",
    "gn:admin2_code":"52160.0",
    "gn:asciiname":"Poiana Lunga",
    "gn:country_code":"RO",
    "gn:dem":922,
    "gn:feature_class":"P",
    "gn:feature_code":"PPL",
    "gn:name":"Poiana Lung\u0103",
    "gn:population":88,
    "gn:timezone":"Europe/Bucharest",
    "iso:country":"RO",
    "wof:name":"Poiana Lunga",
    "wof:placetype":"locality",
    "wof:population":88
},
  "geometry": {"coordinates":[22.45845,45.00161],"type":"Point"}
}