{
  "type": "Feature",
  "properties": {
    "gn:admin1_code":"03",
    "gn:admin2_code":"18162.0",
    "gn:asciiname":"Popesti",
    "gn:country_code":"RO",
    "gn:dem":134,
    "gn:feature_class":"P",
    "gn:feature_code":"PPLA2",
    "gn:name":"Pope\u015fti",
    "gn:population":0,
    "gn:timezone":"Europe/Bucharest",
    "iso:country":"RO",
    "wof:name":"Popesti",
    "wof:placetype":"locality"
},
  "geometry": {"coordinates":[25.10007,44.44181],"type":"Point"}
}