{
  "type": "Feature",
  "properties": {
    "gn:admin1_code":"03",
    "gn:admin2_code":"18162.0",
    "gn:asciiname":"Popesti",
    "gn:country_code":"RO",
    "gn:dem":134,
    "gn:feature_class":"P",
    "gn:feature_code":"PPLA2",
    "gn:name":"Pope\u015fti",
    "gn:population":0,
    "gn:timezone":"Europe/Bucharest",
    "iso:country":"RO",
    "name:ara_x_preferred":[
        "\u0628\u0648\u0628\u0634\u062a"
    ],
    "name:ceb_x_preferred":[
        "Comuna Pope\u0219ti"
    ],
    "name:ita_x_preferred":[
        "Pope\u0219ti"
    ],
    "name:mkd_x_preferred":[
        "\u041f\u043e\u043f\u0435\u0448\u0442"
    ],
    "name:msa_x_preferred":[
        "Pope\u0219ti"
    ],
    "name:nld_x_preferred":[
        "Pope\u0219ti"
    ],
    "name:por_x_preferred":[
        "Pope\u0219ti"
    ],
    "name:ron_x_preferred":[
        "Comuna Pope\u0219ti"
    ],
    "name:sqi_x_preferred":[
        "Pope\u015fti"
    ],
    "name:srp_x_preferred":[
        "\u041e\u043f\u0448\u0442\u0438\u043d\u0430 \u041f\u043e\u043f\u0435\u0448\u0442\u0438"
    ],
    "name:ukr_x_preferred":[
        "\u041f\u043e\u043f\u0435\u0448\u0442\u044c"
    ],
    "name:vie_x_preferred":[
        "Pope\u0219ti"
    ],
    "name:vol_x_preferred":[
        "Pope\u015fti"
    ],
    "name:zho_x_preferred":[
        "\u6ce2\u4f69\u4ec0\u8482\u9109"
    ],
    "wof:name":"Popesti",
    "wof:placetype":"locality"
},
  "geometry": {"coordinates":[25.10007,44.44181],"type":"Point"}
}