{
  "type": "Feature",
  "properties": {
    "gn:admin1_code":"03",
    "gn:admin2_code":"16132.0",
    "gn:asciiname":"Teodoresti",
    "gn:cc2":"RO",
    "gn:country_code":"RO",
    "gn:dem":470,
    "gn:feature_class":"P",
    "gn:feature_code":"PPL",
    "gn:name":"Teodore\u0219ti",
    "gn:population":341,
    "gn:timezone":"Europe/Bucharest",
    "iso:country":"RO",
    "name:und_x_variant":[
        "Tudore\u015fti",
        "Teodore\u015fti"
    ],
    "wof:name":"Teodoresti",
    "wof:placetype":"locality",
    "wof:population":341
},
  "geometry": {"coordinates":[24.48434,44.92404000000001],"type":"Point"}
}