{
  "type": "Feature",
  "properties": {
    "gn:admin1_code":"09",
    "gn:admin2_code":"42307.0",
    "gn:asciiname":"Sambata de Jos",
    "gn:cc2":"RO",
    "gn:country_code":"RO",
    "gn:dem":421,
    "gn:feature_class":"P",
    "gn:feature_code":"PPL",
    "gn:name":"S\u00e2mb\u0103ta de Jos",
    "gn:population":548,
    "gn:timezone":"Europe/Bucharest",
    "iso:country":"RO",
    "name:hun_x_preferred":[
        "Als\u00f3szombatfalva"
    ],
    "name:und_x_variant":[
        "S\u00e2mb\u0103ta-de Jos",
        "S\u00eemb\u0103ta Apusean\u0103",
        "S\u00eemb\u0103ta de Jos"
    ],
    "wof:name":"Sambata de Jos",
    "wof:placetype":"locality",
    "wof:population":548
},
  "geometry": {"coordinates":[24.82104,45.8113],"type":"Point"}
}