{
  "type": "Feature",
  "properties": {
    "gn:admin1_code":"26",
    "gn:admin2_code":"109924.0",
    "gn:asciiname":"Negoesti",
    "gn:country_code":"RO",
    "gn:dem":254,
    "gn:feature_class":"P",
    "gn:feature_code":"PPL",
    "gn:name":"Negoe\u0219ti",
    "gn:population":911,
    "gn:timezone":"Europe/Bucharest",
    "iso:country":"RO",
    "wof:name":"Negoesti",
    "wof:placetype":"locality",
    "wof:population":911
},
  "geometry": {"coordinates":[22.86083,44.98311],"type":"Point"}
}