{
  "type": "Feature",
  "properties": {
    "gn:admin1_code":"06",
    "gn:admin2_code":"34477.0",
    "gn:asciiname":"La Curte",
    "gn:country_code":"RO",
    "gn:dem":362,
    "gn:feature_class":"P",
    "gn:feature_code":"PPL",
    "gn:name":"La Curte",
    "gn:population":147,
    "gn:timezone":"Europe/Bucharest",
    "iso:country":"RO",
    "wof:name":"La Curte",
    "wof:placetype":"locality",
    "wof:population":147
},
  "geometry": {"coordinates":[24.37323,46.88442],"type":"Point"}
}