{
  "type": "Feature",
  "properties": {
    "gn:country":"RO",
    "gn:fcode":"PPL",
    "gn:population":0,
    "iso:country":"RO",
    "name:ceb_x_preferred":[
        "Cozla"
    ],
    "name:eng_x_preferred":[
        "Cozla"
    ],
    "name:nld_x_preferred":[
        "Cozla"
    ],
    "name:ron_x_preferred":[
        "Cozla"
    ],
    "name:srp_x_preferred":[
        "\u041a\u043e\u0437\u043b\u0430"
    ],
    "name:ukr_x_preferred":[
        "\u041a\u043e\u0437\u043b\u0430"
    ],
    "name:und_x_variant":[
        "Kozla"
    ],
    "qs_pg:aaroncc":"RO",
    "qs_pg:gn_country":"RO",
    "qs_pg:gn_fcode":"PPL",
    "qs_pg:gn_pop":0,
    "qs_pg:name":"Cozla",
    "qs_pg:name_adm0":"Rom\u00e2nia",
    "qs_pg:name_adm1":"Caras-Severin",
    "qs_pg:photos":93,
    "qs_pg:photos_1k":19,
    "qs_pg:photos_9k":1,
    "qs_pg:photos_9r":3,
    "qs_pg:photos_all":93,
    "qs_pg:photos_sr":3,
    "qs_pg:pop_sr":0,
    "qs_pg:qs_pg_placetype":"locality",
    "qs_pg:qs_pg_placetype_gp":"Town",
    "qs_pg:woe_adm0":23424933,
    "woe:adm0_id":23424933,
    "woe:name_adm0":"Rom\u00e2nia",
    "woe:name_adm1":"Caras-Severin",
    "woe:placetype":"Town",
    "wof:name":"Cozla",
    "wof:placetype":"locality",
    "wof:population":182
},
  "geometry": {"coordinates":[22.00139,44.63139],"type":"Point"}
}