{
  "type": "Feature",
  "properties": {
    "gn:admin1_code":"13",
    "gn:admin2_code":"56844",
    "gn:asciiname":"Andici",
    "gn:country_code":"RO",
    "gn:dem":326,
    "gn:feature_class":"P",
    "gn:feature_code":"PPL",
    "gn:name":"Andici",
    "gn:population":0,
    "gn:timezone":"Europe/Bucharest",
    "iso:country":"RO",
    "wof:name":"Andici",
    "wof:placetype":"locality"
},
  "geometry": {"coordinates":[23.91937,46.64776],"type":"Point"}
}