{
  "type": "Feature",
  "properties": {
    "gn:admin1_code":"34",
    "gn:admin2_code":"148970.0",
    "gn:asciiname":"Slobozia Sucevei",
    "gn:cc2":"RO",
    "gn:country_code":"RO",
    "gn:dem":316,
    "gn:feature_class":"P",
    "gn:feature_code":"PPL",
    "gn:name":"Slobozia Sucevei",
    "gn:population":604,
    "gn:timezone":"Europe/Bucharest",
    "iso:country":"RO",
    "name:und_x_variant":[
        "Slobozia-Pruncului",
        "Slobozia Sucevei"
    ],
    "wof:name":"Slobozia Sucevei",
    "wof:placetype":"locality",
    "wof:population":604
},
  "geometry": {"coordinates":[26.04656,47.76428],"type":"Point"}
}