{
  "type": "Feature",
  "properties": {
    "gn:admin1_code":"13",
    "gn:admin2_code":"59657",
    "gn:asciiname":"Aruncuta",
    "gn:cc2":"RO",
    "gn:country_code":"RO",
    "gn:dem":365,
    "gn:feature_class":"P",
    "gn:feature_code":"PPL",
    "gn:name":"Aruncuta",
    "gn:population":473,
    "gn:timezone":"Europe/Bucharest",
    "iso:country":"RO",
    "name:und_x_variant":[
        "Aruncata",
        "Arancata",
        "Aruncuta"
    ],
    "wof:name":"Aruncuta",
    "wof:placetype":"locality",
    "wof:population":473
},
  "geometry": {"coordinates":[23.96801,46.73328],"type":"Point"}
}