{
  "type": "Feature",
  "properties": {
    "gn:admin1_code":"19",
    "gn:admin2_code":"80506.0",
    "gn:asciiname":"Totea de Hurezani",
    "gn:country_code":"RO",
    "gn:dem":256,
    "gn:feature_class":"P",
    "gn:feature_code":"PPL",
    "gn:name":"Totea de Hurezani",
    "gn:population":280,
    "gn:timezone":"Europe/Bucharest",
    "iso:country":"RO",
    "wof:name":"Totea de Hurezani",
    "wof:placetype":"locality",
    "wof:population":280
},
  "geometry": {"coordinates":[23.62343,44.82411],"type":"Point"}
}