{
  "type": "Feature",
  "properties": {
    "gn:admin1_code":"04",
    "gn:admin2_code":"26118.0",
    "gn:asciiname":"Godinestii de Jos",
    "gn:cc2":"RO",
    "gn:country_code":"RO",
    "gn:dem":191,
    "gn:feature_class":"P",
    "gn:feature_code":"PPL",
    "gn:name":"Godine\u0219tii de Jos",
    "gn:population":262,
    "gn:timezone":"Europe/Bucharest",
    "iso:country":"RO",
    "name:und_x_variant":[
        "Godine\u015fti-de-Jos",
        "Godine\u015ftii de Jos"
    ],
    "wof:name":"Godinestii de Jos",
    "wof:placetype":"locality",
    "wof:population":262
},
  "geometry": {"coordinates":[27.23087,46.42106],"type":"Point"}
}