{
  "type": "Feature",
  "properties": {
    "gn:admin1_code":"26",
    "gn:admin2_code":"112370.0",
    "gn:asciiname":"Cerna-Varf",
    "gn:cc2":"RO",
    "gn:country_code":"RO",
    "gn:dem":400,
    "gn:feature_class":"P",
    "gn:feature_code":"PPL",
    "gn:name":"Cerna-V\u00e2rf",
    "gn:population":268,
    "gn:timezone":"Europe/Bucharest",
    "iso:country":"RO",
    "name:und_x_variant":[
        "Cerna Varfu",
        "Cerna-V\u00eerf",
        "Cerna-V\u00e2rf"
    ],
    "wof:name":"Cerna-Varf",
    "wof:placetype":"locality",
    "wof:population":268
},
  "geometry": {"coordinates":[22.68096,44.92451],"type":"Point"}
}