{
  "type": "Feature",
  "properties": {
    "gn:admin1_code":"18",
    "gn:admin2_code":"75356.0",
    "gn:asciiname":"Saseni",
    "gn:country_code":"RO",
    "gn:dem":115,
    "gn:feature_class":"P",
    "gn:feature_code":"PPL",
    "gn:name":"S\u0103seni",
    "gn:population":133,
    "gn:timezone":"Europe/Bucharest",
    "iso:country":"RO",
    "wof:name":"Saseni",
    "wof:placetype":"locality",
    "wof:population":133
},
  "geometry": {"coordinates":[27.93107,46.12779000000001],"type":"Point"}
}