{
  "type": "Feature",
  "properties": {
    "gn:admin1_code":"08",
    "gn:admin2_code":"43019.0",
    "gn:asciiname":"Scarlatesti",
    "gn:country_code":"RO",
    "gn:dem":42,
    "gn:feature_class":"P",
    "gn:feature_code":"PPL",
    "gn:name":"Sc\u0103rl\u0103te\u0219ti",
    "gn:population":966,
    "gn:timezone":"Europe/Bucharest",
    "iso:country":"RO",
    "wof:name":"Scarlatesti",
    "wof:placetype":"locality",
    "wof:population":966
},
  "geometry": {"coordinates":[27.39325,44.94784],"type":"Point"}
}