{
  "type": "Feature",
  "properties": {
    "gn:admin1_code":"22",
    "gn:admin2_code":"94161.0",
    "gn:asciiname":"Ghimpati",
    "gn:country_code":"RO",
    "gn:dem":27,
    "gn:feature_class":"P",
    "gn:feature_code":"PPL",
    "gn:name":"Ghimpa\u0163i",
    "gn:population":0,
    "gn:timezone":"Europe/Bucharest",
    "iso:country":"RO",
    "wof:name":"Ghimpati",
    "wof:placetype":"locality"
},
  "geometry": {"coordinates":[27.21667,44.55],"type":"Point"}
}