{
  "type": "Feature",
  "properties": {
    "gn:admin1_code":"28",
    "gn:admin2_code":"125098",
    "gn:asciiname":"Balusesti",
    "gn:country_code":"RO",
    "gn:dem":355,
    "gn:feature_class":"P",
    "gn:feature_code":"PPL",
    "gn:name":"B\u0103lu\u0219e\u0219ti",
    "gn:population":159,
    "gn:timezone":"Europe/Bucharest",
    "iso:country":"RO",
    "wof:name":"Balusesti",
    "wof:placetype":"locality",
    "wof:population":159
},
  "geometry": {"coordinates":[26.60206,46.92749],"type":"Point"}
}