{
  "type": "Feature",
  "properties": {
    "gn:admin1_code":"18",
    "gn:admin2_code":"75766.0",
    "gn:asciiname":"Cositeni",
    "gn:cc2":"RO",
    "gn:country_code":"RO",
    "gn:dem":109,
    "gn:feature_class":"P",
    "gn:feature_code":"PPL",
    "gn:name":"Cosi\u021beni",
    "gn:population":236,
    "gn:timezone":"Europe/Bucharest",
    "iso:country":"RO",
    "name:und_x_variant":[
        "Cosi\u0163enii",
        "Cosi\u0163eni"
    ],
    "wof:name":"Cositeni",
    "wof:placetype":"locality",
    "wof:population":236
},
  "geometry": {"coordinates":[27.37627,46.07204],"type":"Point"}
}