{
  "type": "Feature",
  "properties": {
    "gn:admin1_code":"36",
    "gn:admin2_code":"157497.0",
    "gn:asciiname":"Cerna",
    "gn:cc2":"RO",
    "gn:country_code":"RO",
    "gn:dem":107,
    "gn:feature_class":"P",
    "gn:feature_code":"PPL",
    "gn:name":"Cerna",
    "gn:population":295,
    "gn:timezone":"Europe/Bucharest",
    "iso:country":"RO",
    "name:ceb_x_preferred":[
        "Cerna"
    ],
    "name:deu_x_preferred":[
        "Cerna"
    ],
    "name:epo_x_preferred":[
        "Cerna"
    ],
    "name:fra_x_preferred":[
        "Cerna"
    ],
    "name:glg_x_preferred":[
        "Cerna"
    ],
    "name:hrv_x_preferred":[
        "Cerna"
    ],
    "name:nld_x_preferred":[
        "Cerna"
    ],
    "name:ron_x_preferred":[
        "Cerna"
    ],
    "name:srp_x_preferred":[
        "\u0426\u0435\u0440\u043d\u0430"
    ],
    "name:swe_x_preferred":[
        "Cerna"
    ],
    "name:und_x_variant":[
        "Temescserna",
        "Cserna",
        "Cerna"
    ],
    "wof:name":"Cerna",
    "wof:placetype":"locality",
    "wof:population":295
},
  "geometry": {"coordinates":[21.4064,45.56314],"type":"Point"}
}