{
  "type": "Feature",
  "properties": {
    "gn:admin1_code":"39",
    "gn:admin2_code":"169681.0",
    "gn:asciiname":"Nisipi",
    "gn:country_code":"RO",
    "gn:dem":237,
    "gn:feature_class":"P",
    "gn:feature_code":"PPL",
    "gn:name":"Nisipi",
    "gn:population":117,
    "gn:timezone":"Europe/Bucharest",
    "iso:country":"RO",
    "wof:name":"Nisipi",
    "wof:placetype":"locality",
    "wof:population":117
},
  "geometry": {"coordinates":[24.00914,44.80441],"type":"Point"}
}