{
  "type": "Feature",
  "properties": {
    "gn:admin1_code":"23",
    "gn:admin2_code":"100335.0",
    "gn:asciiname":"Ursaresti",
    "gn:country_code":"RO",
    "gn:dem":189,
    "gn:feature_class":"P",
    "gn:feature_code":"PPL",
    "gn:name":"Urs\u0103re\u0219ti",
    "gn:population":160,
    "gn:timezone":"Europe/Bucharest",
    "iso:country":"RO",
    "wof:name":"Ursaresti",
    "wof:placetype":"locality",
    "wof:population":160
},
  "geometry": {"coordinates":[26.89553,47.059],"type":"Point"}
}