{
  "type": "Feature",
  "properties": {
    "gn:admin1_code":"13",
    "gn:admin2_code":"56666.0",
    "gn:asciiname":"Salatruc",
    "gn:country_code":"RO",
    "gn:dem":319,
    "gn:feature_class":"P",
    "gn:feature_code":"PPL",
    "gn:name":"S\u0103l\u0103truc",
    "gn:population":76,
    "gn:timezone":"Europe/Bucharest",
    "iso:country":"RO",
    "wof:name":"Salatruc",
    "wof:placetype":"locality",
    "wof:population":76
},
  "geometry": {"coordinates":[23.88177,47.26334],"type":"Point"}
}