{
  "type": "Feature",
  "properties": {
    "gn:admin1_code":"34",
    "gn:admin2_code":"147884.0",
    "gn:asciiname":"Chiril",
    "gn:cc2":"RO",
    "gn:country_code":"RO",
    "gn:dem":748,
    "gn:feature_class":"P",
    "gn:feature_code":"PPL",
    "gn:name":"Chiril",
    "gn:population":309,
    "gn:timezone":"Europe/Bucharest",
    "iso:country":"RO",
    "name:und_x_variant":[
        "Kiril",
        "Chiril"
    ],
    "wof:name":"Chiril",
    "wof:placetype":"locality",
    "wof:population":309
},
  "geometry": {"coordinates":[25.56516,47.39662],"type":"Point"}
}