{
  "type": "Feature",
  "properties": {
    "gn:admin1_code":"08",
    "gn:admin2_code":"44060.0",
    "gn:asciiname":"Gura Garlutei",
    "gn:cc2":"RO",
    "gn:country_code":"RO",
    "gn:dem":4,
    "gn:feature_class":"P",
    "gn:feature_code":"PPL",
    "gn:name":"Gura G\u00e2rlu\u0163ei",
    "gn:population":0,
    "gn:timezone":"Europe/Bucharest",
    "iso:country":"RO",
    "name:und_x_variant":[
        "G\u00e2rlu\u0163ei",
        "Gura G\u00e2rlu\u0163ei",
        "Gura G\u00eerlu\u0163ei"
    ],
    "wof:name":"Gura Garlutei",
    "wof:placetype":"locality"
},
  "geometry": {"coordinates":[27.81667,44.83333],"type":"Point"}
}