{
  "type": "Feature",
  "properties": {
    "gn:admin1_code":"14",
    "gn:admin2_code":"61559",
    "gn:asciiname":"Baltagesti",
    "gn:country_code":"RO",
    "gn:dem":38,
    "gn:feature_class":"P",
    "gn:feature_code":"PPL",
    "gn:name":"B\u0103lt\u0103ge\u0219ti",
    "gn:population":508,
    "gn:timezone":"Europe/Bucharest",
    "iso:country":"RO",
    "wof:name":"Baltagesti",
    "wof:placetype":"locality",
    "wof:population":508
},
  "geometry": {"coordinates":[28.19358,44.48302],"type":"Point"}
}