{
  "type": "Feature",
  "properties": {
    "gn:country":"RO",
    "gn:fcode":"PPLA2",
    "gn:population":4578,
    "iso:country":"RO",
    "name:ceb_x_preferred":[
        "Bolote\u0219ti"
    ],
    "name:eng_x_preferred":[
        "Bolote\u0219ti"
    ],
    "name:fra_x_preferred":[
        "Bolote\u0219ti"
    ],
    "name:ita_x_preferred":[
        "Bolote\u0219ti"
    ],
    "name:nld_x_preferred":[
        "Bolote\u0219ti"
    ],
    "name:ron_x_preferred":[
        "Bolote\u0219ti"
    ],
    "name:srp_x_preferred":[
        "\u0411\u043e\u043b\u043e\u0442\u0435\u0448\u0442\u0438"
    ],
    "name:ukr_x_preferred":[
        "\u0411\u043e\u043b\u043e\u0442\u0435\u0448\u0442\u044c"
    ],
    "qs_pg:aaroncc":"RO",
    "qs_pg:gn_country":"RO",
    "qs_pg:gn_fcode":"PPLA2",
    "qs_pg:gn_pop":4578,
    "qs_pg:name":"Bolote\u015fti",
    "qs_pg:photos_9r":0,
    "qs_pg:photos_sr":0,
    "qs_pg:pop_sr":4,
    "qs_pg:qs_pg_placetype":"locality",
    "wof:name":"Bolote\u015fti",
    "wof:placetype":"locality",
    "wof:population":4578
},
  "geometry": {"coordinates":[27.06667,45.83333],"type":"Point"}
}