{
  "type": "Feature",
  "properties": {
    "gn:admin1_code":"21",
    "gn:admin2_code":"92097.0",
    "gn:asciiname":"Visca",
    "gn:country_code":"RO",
    "gn:dem":310,
    "gn:feature_class":"P",
    "gn:feature_code":"PPL",
    "gn:name":"Visca",
    "gn:population":483,
    "gn:timezone":"Europe/Bucharest",
    "iso:country":"RO",
    "wof:name":"Visca",
    "wof:placetype":"locality",
    "wof:population":483
},
  "geometry": {"coordinates":[22.6683,46.06931],"type":"Point"}
}