{
  "type": "Feature",
  "properties": {
    "gn:admin1_code":"01",
    "gn:admin2_code":"8425.0",
    "gn:asciiname":"Dragoesti",
    "gn:country_code":"RO",
    "gn:dem":624,
    "gn:feature_class":"P",
    "gn:feature_code":"PPL",
    "gn:name":"Dr\u0103goe\u015fti",
    "gn:population":0,
    "gn:timezone":"Europe/Bucharest",
    "iso:country":"RO",
    "wof:name":"Dragoesti",
    "wof:placetype":"locality"
},
  "geometry": {"coordinates":[22.96667,46.36667],"type":"Point"}
}