{
  "type": "Feature",
  "properties": {
    "gn:admin1_code":"13",
    "gn:admin2_code":"56096.0",
    "gn:asciiname":"Valcelele",
    "gn:cc2":"RO",
    "gn:country_code":"RO",
    "gn:dem":340,
    "gn:feature_class":"P",
    "gn:feature_code":"PPL",
    "gn:name":"V\u00e2lcelele",
    "gn:population":145,
    "gn:timezone":"Europe/Bucharest",
    "iso:country":"RO",
    "name:und_x_variant":[
        "Bujdos",
        "Budu\u015f",
        "V\u00eelcelele"
    ],
    "wof:name":"Valcelele",
    "wof:placetype":"locality",
    "wof:population":145
},
  "geometry": {"coordinates":[23.59602000000001,47.10673],"type":"Point"}
}