{
  "type": "Feature",
  "properties": {
    "gn:admin1_code":"26",
    "gn:admin2_code":"113233.0",
    "gn:asciiname":"Lumnic",
    "gn:cc2":"RO",
    "gn:country_code":"RO",
    "gn:dem":252,
    "gn:feature_class":"P",
    "gn:feature_code":"PPL",
    "gn:name":"Lumnic",
    "gn:population":175,
    "gn:timezone":"Europe/Bucharest",
    "iso:country":"RO",
    "name:und_x_variant":[
        "Lumnicu de Jos",
        "Lumnicul-de-Jos",
        "Lumnic"
    ],
    "wof:name":"Lumnic",
    "wof:placetype":"locality",
    "wof:population":175
},
  "geometry": {"coordinates":[23.00479,44.63119],"type":"Point"}
}