{
  "type": "Feature",
  "properties": {
    "gn:admin1_code":"32",
    "gn:admin2_code":"138663.0",
    "gn:asciiname":"Horea",
    "gn:country_code":"RO",
    "gn:dem":142,
    "gn:feature_class":"P",
    "gn:feature_code":"PPL",
    "gn:name":"Horea",
    "gn:population":258,
    "gn:timezone":"Europe/Bucharest",
    "iso:country":"RO",
    "name:ceb_x_preferred":[
        "Horea"
    ],
    "name:hun_x_preferred":[
        "K\u00e1rolyipuszta"
    ],
    "name:ron_x_preferred":[
        "Horea"
    ],
    "name:srp_x_preferred":[
        "\u0425\u043e\u0440\u0435\u0430"
    ],
    "name:ukr_x_preferred":[
        "\u0425\u043e\u0440\u044f"
    ],
    "wof:name":"Horea",
    "wof:placetype":"locality",
    "wof:population":258
},
  "geometry": {"coordinates":[22.23574,47.6847],"type":"Point"}
}