{
  "type": "Feature",
  "properties": {
    "gn:admin1_code":"07",
    "gn:admin2_code":"39266.0",
    "gn:asciiname":"Floresti",
    "gn:country_code":"RO",
    "gn:dem":73,
    "gn:feature_class":"P",
    "gn:feature_code":"PPL",
    "gn:name":"Flore\u0219ti",
    "gn:population":33,
    "gn:timezone":"Europe/Bucharest",
    "iso:country":"RO",
    "wof:name":"Floresti",
    "wof:placetype":"locality",
    "wof:population":33
},
  "geometry": {"coordinates":[27.1387,47.6204],"type":"Point"}
}