{
  "type": "Feature",
  "properties": {
    "gn:admin1_code":"01",
    "gn:admin2_code":"8425.0",
    "gn:asciiname":"Culdesti",
    "gn:country_code":"RO",
    "gn:dem":762,
    "gn:feature_class":"P",
    "gn:feature_code":"PPL",
    "gn:name":"Culde\u0219ti",
    "gn:population":91,
    "gn:timezone":"Europe/Bucharest",
    "iso:country":"RO",
    "wof:name":"Culdesti",
    "wof:placetype":"locality",
    "wof:population":91
},
  "geometry": {"coordinates":[22.95207000000001,46.38076],"type":"Point"}
}