{
  "type": "Feature",
  "properties": {
    "gn:admin1_code":"32",
    "gn:admin2_code":"137960",
    "gn:asciiname":"Bercu",
    "gn:cc2":"RO",
    "gn:country_code":"RO",
    "gn:dem":120,
    "gn:feature_class":"P",
    "gn:feature_code":"PPL",
    "gn:name":"Bercu",
    "gn:population":593,
    "gn:timezone":"Europe/Bucharest",
    "iso:country":"RO",
    "name:ceb_x_preferred":[
        "Bercu"
    ],
    "name:deu_x_preferred":[
        "Bercu"
    ],
    "name:epo_x_preferred":[
        "Bercu"
    ],
    "name:heb_x_preferred":[
        "\u05d1\u05e8\u05e7\u05d5"
    ],
    "name:hun_x_preferred":[
        "Bercu"
    ],
    "name:ron_x_preferred":[
        "Bercu"
    ],
    "name:und_x_variant":[
        "Bercul",
        "Bercu Colonia"
    ],
    "wof:name":"Bercu",
    "wof:placetype":"locality",
    "wof:population":593
},
  "geometry": {"coordinates":[22.88896,47.9148],"type":"Point"}
}