{
  "type": "Feature",
  "properties": {
    "gn:admin1_code":"40",
    "gn:admin2_code":"175509.0",
    "gn:asciiname":"Catauti",
    "gn:country_code":"RO",
    "gn:dem":381,
    "gn:feature_class":"P",
    "gn:feature_code":"PPL",
    "gn:name":"C\u0103t\u0103u\u021bi",
    "gn:population":422,
    "gn:timezone":"Europe/Bucharest",
    "iso:country":"RO",
    "wof:name":"Catauti",
    "wof:placetype":"locality",
    "wof:population":422
},
  "geometry": {"coordinates":[26.84658,45.54044],"type":"Point"}
}