{
  "type": "Feature",
  "properties": {
    "gn:admin1_code":"39",
    "gn:admin2_code":"173793.0",
    "gn:asciiname":"Sarbi",
    "gn:cc2":"RO",
    "gn:country_code":"RO",
    "gn:dem":217,
    "gn:feature_class":"P",
    "gn:feature_code":"PPL",
    "gn:name":"S\u00e2rbi",
    "gn:population":115,
    "gn:timezone":"Europe/Bucharest",
    "iso:country":"RO",
    "name:nor_x_preferred":[
        "Sarbi"
    ],
    "name:und_x_variant":[
        "S\u00e2rba",
        "S\u00eerbi"
    ],
    "name:vie_x_preferred":[
        "Sarbi"
    ],
    "wof:name":"Sarbi",
    "wof:placetype":"locality",
    "wof:population":115
},
  "geometry": {"coordinates":[24.08613,44.64967],"type":"Point"}
}