{
  "type": "Feature",
  "properties": {
    "gn:admin1_code":"21",
    "gn:admin2_code":"91447.0",
    "gn:asciiname":"Valea Mare de Cris",
    "gn:country_code":"RO",
    "gn:dem":304,
    "gn:feature_class":"P",
    "gn:feature_code":"PPL",
    "gn:name":"Valea Mare de Cri\u0219",
    "gn:population":10,
    "gn:timezone":"Europe/Bucharest",
    "iso:country":"RO",
    "wof:name":"Valea Mare de Cris",
    "wof:placetype":"locality",
    "wof:population":10
},
  "geometry": {"coordinates":[22.70132000000001,46.20612],"type":"Point"}
}