{
  "type": "Feature",
  "properties": {
    "gn:admin1_code":"21",
    "gn:admin2_code":"89240",
    "gn:asciiname":"Bocsa Mare",
    "gn:cc2":"RO",
    "gn:country_code":"RO",
    "gn:dem":614,
    "gn:feature_class":"P",
    "gn:feature_code":"PPL",
    "gn:name":"Boc\u0219a Mare",
    "gn:population":33,
    "gn:timezone":"Europe/Bucharest",
    "iso:country":"RO",
    "name:und_x_variant":[
        "Bocsa",
        "Boc\u015fa Mare"
    ],
    "wof:name":"Bocsa Mare",
    "wof:placetype":"locality",
    "wof:population":33
},
  "geometry": {"coordinates":[23.01903,45.99936],"type":"Point"}
}