{
  "type": "Feature",
  "properties": {
    "gn:admin1_code":"28",
    "gn:admin2_code":"121340.0",
    "gn:asciiname":"Tepesani",
    "gn:country_code":"RO",
    "gn:dem":677,
    "gn:feature_class":"P",
    "gn:feature_code":"PPL",
    "gn:name":"\u0162epe\u015fani",
    "gn:population":0,
    "gn:timezone":"Europe/Bucharest",
    "iso:country":"RO",
    "name:und_x_variant":[
        "\u0162epe\u015feni",
        "\u0162epe\u015fani"
    ],
    "wof:name":"Tepesani",
    "wof:placetype":"locality"
},
  "geometry": {"coordinates":[25.91667,46.85],"type":"Point"}
}