{
  "type": "Feature",
  "properties": {
    "gn:admin1_code":"36",
    "gn:admin2_code":"156035.0",
    "gn:asciiname":"Comeat",
    "gn:cc2":"RO",
    "gn:country_code":"RO",
    "gn:dem":171,
    "gn:feature_class":"P",
    "gn:feature_code":"PPL",
    "gn:name":"Comeat",
    "gn:population":45,
    "gn:timezone":"Europe/Bucharest",
    "iso:country":"RO",
    "name:und_x_variant":[
        "Komeat",
        "Temeskomj\u00e1t",
        "Lichtenwald",
        "Coneat",
        "Comeat"
    ],
    "wof:name":"Comeat",
    "wof:placetype":"locality",
    "wof:population":45
},
  "geometry": {"coordinates":[21.61618,45.96114],"type":"Point"}
}