{
  "type": "Feature",
  "properties": {
    "gn:admin1_code":"42",
    "gn:admin2_code":"103309.0",
    "gn:asciiname":"Draghiceanu",
    "gn:cc2":"RO",
    "gn:country_code":"RO",
    "gn:dem":57,
    "gn:feature_class":"P",
    "gn:feature_code":"PPL",
    "gn:name":"Dr\u0103ghiceanu",
    "gn:population":199,
    "gn:timezone":"Europe/Bucharest",
    "iso:country":"RO",
    "name:und_x_variant":[
        "Gogo\u015farii Noui",
        "Gogo\u015farii Noi",
        "Dr\u0103ghiceanu"
    ],
    "wof:name":"Draghiceanu",
    "wof:placetype":"locality",
    "wof:population":199
},
  "geometry": {"coordinates":[25.67794,43.86454000000001],"type":"Point"}
}