{
  "type": "Feature",
  "properties": {
    "gn:admin1_code":"26",
    "gn:admin2_code":"111587",
    "gn:asciiname":"Albulesti",
    "gn:country_code":"RO",
    "gn:dem":293,
    "gn:feature_class":"P",
    "gn:feature_code":"PPL",
    "gn:name":"Albule\u0219ti",
    "gn:population":903,
    "gn:timezone":"Europe/Bucharest",
    "iso:country":"RO",
    "wof:name":"Albulesti",
    "wof:placetype":"locality",
    "wof:population":903
},
  "geometry": {"coordinates":[23.20397,44.5156],"type":"Point"}
}