{
  "type": "Feature",
  "properties": {
    "gn:admin1_code":"01",
    "gn:admin2_code":"4525.0",
    "gn:asciiname":"Izvoarele",
    "gn:cc2":"RO",
    "gn:country_code":"RO",
    "gn:dem":893,
    "gn:feature_class":"P",
    "gn:feature_code":"PPL",
    "gn:name":"Izvoarele",
    "gn:population":69,
    "gn:timezone":"Europe/Bucharest",
    "iso:country":"RO",
    "name:ceb_x_preferred":[
        "Izvoarele"
    ],
    "name:deu_x_preferred":[
        "Izvoarele"
    ],
    "name:epo_x_preferred":[
        "Izvoarele"
    ],
    "name:fra_x_preferred":[
        "Izvoarele"
    ],
    "name:hun_x_preferred":[
        "Izvoarele"
    ],
    "name:ita_x_preferred":[
        "Izvoarele"
    ],
    "name:nld_x_preferred":[
        "Izvoarele"
    ],
    "name:ron_x_preferred":[
        "Izvoarele"
    ],
    "name:srp_x_preferred":[
        "\u0418\u0437\u0432\u043e\u0430\u0440\u0435\u043b\u0435"
    ],
    "name:ukr_x_preferred":[
        "\u0406\u0437\u0432\u043e\u0430\u0440\u0435\u043b\u0435"
    ],
    "name:und_x_variant":[
        "C\u00eerc\u0103ne\u015fti",
        "Izvoarele"
    ],
    "name:vol_x_preferred":[
        "Izvoarele"
    ],
    "wof:name":"Izvoarele",
    "wof:placetype":"locality",
    "wof:population":69
},
  "geometry": {"coordinates":[22.8365,46.45927],"type":"Point"}
}