{
  "type": "Feature",
  "properties": {
    "gn:admin1_code":"36",
    "gn:admin2_code":"158136.0",
    "gn:asciiname":"Poieni",
    "gn:country_code":"RO",
    "gn:dem":337,
    "gn:feature_class":"P",
    "gn:feature_code":"PPL",
    "gn:name":"Poieni",
    "gn:population":304,
    "gn:timezone":"Europe/Bucharest",
    "iso:country":"RO",
    "wof:name":"Poieni",
    "wof:placetype":"locality",
    "wof:population":304
},
  "geometry": {"coordinates":[22.45404,45.80158],"type":"Point"}
}