{
  "type": "Feature",
  "properties": {
    "gn:admin1_code":"31",
    "gn:admin2_code":"141312.0",
    "gn:asciiname":"Cerisa",
    "gn:country_code":"RO",
    "gn:dem":241,
    "gn:feature_class":"P",
    "gn:feature_code":"PPL",
    "gn:name":"Ceri\u0219a",
    "gn:population":604,
    "gn:timezone":"Europe/Bucharest",
    "iso:country":"RO",
    "wof:name":"Cerisa",
    "wof:placetype":"locality",
    "wof:population":604
},
  "geometry": {"coordinates":[22.56688,47.18148],"type":"Point"}
}