{
  "type": "Feature",
  "properties": {
    "gn:admin1_code":"30",
    "gn:admin2_code":"133018",
    "gn:asciiname":"Belciug",
    "gn:cc2":"RO",
    "gn:country_code":"RO",
    "gn:dem":81,
    "gn:feature_class":"P",
    "gn:feature_code":"PPL",
    "gn:name":"Belciug",
    "gn:population":727,
    "gn:timezone":"Europe/Bucharest",
    "iso:country":"RO",
    "name:ceb_x_preferred":[
        "Belciug"
    ],
    "name:deu_x_preferred":[
        "Belciug"
    ],
    "name:ron_x_preferred":[
        "Belciug"
    ],
    "name:srp_x_preferred":[
        "\u0411\u0435\u043b\u0447\u0443\u0433"
    ],
    "name:und_x_variant":[
        "Belciugu"
    ],
    "wof:name":"Belciug",
    "wof:placetype":"locality",
    "wof:population":727
},
  "geometry": {"coordinates":[26.24824000000001,44.81862],"type":"Point"}
}