{
  "type": "Feature",
  "properties": {
    "gn:gn_country":"RO",
    "gn:gn_fcode":"PPLX",
    "gn:gn_pop":2835,
    "gn:population":2835,
    "iso:country":"RO",
    "name:unk_x_variant":[
        "Babi\u0163a"
    ],
    "qs_pg:aaroncc":"RO",
    "qs_pg:gn_country":"RO",
    "qs_pg:gn_fcode":"PPLX",
    "qs_pg:gn_pop":2835,
    "qs_pg:name":"Babe\u0163i",
    "qs_pg:photos_9r":0,
    "qs_pg:photos_sr":0,
    "qs_pg:pop_sr":4,
    "qs_pg:qs_pg_placetype":"neighbourhood",
    "wof:name":"Babe\u0163i",
    "wof:placetype":"neighbourhood",
    "wof:population":2835
},
  "geometry": {"coordinates":[26.38333,45.31667],"type":"Point"}
}