{
  "type": "Feature",
  "properties": {
    "gn:admin1_code":"34",
    "gn:admin2_code":"146370.0",
    "gn:asciiname":"Mereni",
    "gn:country_code":"RO",
    "gn:dem":321,
    "gn:feature_class":"P",
    "gn:feature_code":"PPL",
    "gn:name":"Mereni",
    "gn:population":240,
    "gn:timezone":"Europe/Bucharest",
    "iso:country":"RO",
    "wof:name":"Mereni",
    "wof:placetype":"locality",
    "wof:population":240
},
  "geometry": {"coordinates":[26.32197,47.66389],"type":"Point"}
}