{
  "type": "Feature",
  "properties": {
    "gn:admin1_code":"23",
    "gn:admin2_code":"98827",
    "gn:asciiname":"Blaga",
    "gn:country_code":"RO",
    "gn:dem":323,
    "gn:feature_class":"P",
    "gn:feature_code":"PPL",
    "gn:name":"Blaga",
    "gn:population":91,
    "gn:timezone":"Europe/Bucharest",
    "iso:country":"RO",
    "name:deu_x_preferred":[
        "Blaga"
    ],
    "name:hun_x_preferred":[
        "Blaga"
    ],
    "name:ita_x_preferred":[
        "Blaga"
    ],
    "name:pol_x_preferred":[
        "Blaga"
    ],
    "name:ron_x_preferred":[
        "Blaga"
    ],
    "name:rus_x_preferred":[
        "\u0411\u043b\u0430\u0433\u0430"
    ],
    "name:srp_x_preferred":[
        "\u0411\u043b\u0430\u0433\u0430"
    ],
    "name:ukr_x_preferred":[
        "\u0411\u043b\u0430\u0491\u0430"
    ],
    "wof:name":"Blaga",
    "wof:placetype":"locality",
    "wof:population":91
},
  "geometry": {"coordinates":[27.74367,47.03],"type":"Point"}
}