{
  "type": "Feature",
  "properties": {
    "gn:admin1_code":"03",
    "gn:admin2_code":"19631.0",
    "gn:asciiname":"Vernesti",
    "gn:country_code":"RO",
    "gn:dem":528,
    "gn:feature_class":"P",
    "gn:feature_code":"PPL",
    "gn:name":"Verne\u0219ti",
    "gn:population":671,
    "gn:timezone":"Europe/Bucharest",
    "iso:country":"RO",
    "wof:name":"Vernesti",
    "wof:placetype":"locality",
    "wof:population":671
},
  "geometry": {"coordinates":[24.60678,45.20005],"type":"Point"}
}