{
  "type": "Feature",
  "properties": {
    "gn:admin1_code":"32",
    "gn:admin2_code":"138208.0",
    "gn:asciiname":"Ghilvaci",
    "gn:country_code":"RO",
    "gn:dem":118,
    "gn:feature_class":"P",
    "gn:feature_code":"PPL",
    "gn:name":"Ghilvaci",
    "gn:population":399,
    "gn:timezone":"Europe/Bucharest",
    "iso:country":"RO",
    "wof:name":"Ghilvaci",
    "wof:placetype":"locality",
    "wof:population":399
},
  "geometry": {"coordinates":[22.67082000000001,47.67839],"type":"Point"}
}