{
  "type": "Feature",
  "properties": {
    "gn:admin1_code":"02",
    "gn:admin2_code":"11307.0",
    "gn:asciiname":"Susani",
    "gn:country_code":"RO",
    "gn:dem":254,
    "gn:feature_class":"P",
    "gn:feature_code":"PPL",
    "gn:name":"Susani",
    "gn:population":0,
    "gn:timezone":"Europe/Bucharest",
    "iso:country":"RO",
    "name:ceb_x_preferred":[
        "Susani"
    ],
    "name:deu_x_preferred":[
        "Susani"
    ],
    "name:epo_x_preferred":[
        "Susani"
    ],
    "name:ita_x_preferred":[
        "Susani"
    ],
    "name:ron_x_preferred":[
        "Susani"
    ],
    "name:und_x_variant":[
        "\u015eu\u015fam",
        "Szusz\u00e1ny",
        "Sus\u00e1ny",
        "Sus\u00e1nyfalva",
        "Suss\u00e1n"
    ],
    "name:vie_x_preferred":[
        "Susani"
    ],
    "wof:name":"Susani",
    "wof:placetype":"locality"
},
  "geometry": {"coordinates":[22.18333,46.45],"type":"Point"}
}