{
  "type": "Feature",
  "properties": {
    "gn:admin1_code":"28",
    "gn:admin2_code":"120824.0",
    "gn:asciiname":"Dumbrava Rosie din Vale",
    "gn:country_code":"RO",
    "gn:dem":281,
    "gn:feature_class":"P",
    "gn:feature_code":"PPL",
    "gn:name":"Dumbrava Ro\u015fie din Vale",
    "gn:population":0,
    "gn:timezone":"Europe/Bucharest",
    "iso:country":"RO",
    "wof:name":"Dumbrava Rosie din Vale",
    "wof:placetype":"locality"
},
  "geometry": {"coordinates":[26.48333,46.85],"type":"Point"}
}