{
  "type": "Feature",
  "properties": {
    "gn:admin1_code":"27",
    "gn:admin2_code":"116046.0",
    "gn:asciiname":"Coasta Grindului",
    "gn:country_code":"RO",
    "gn:dem":328,
    "gn:feature_class":"P",
    "gn:feature_code":"PPL",
    "gn:name":"Coasta Grindului",
    "gn:population":25,
    "gn:timezone":"Europe/Bucharest",
    "iso:country":"RO",
    "wof:name":"Coasta Grindului",
    "wof:placetype":"locality",
    "wof:population":25
},
  "geometry": {"coordinates":[23.98264,46.4955],"type":"Point"}
}