{
  "type": "Feature",
  "properties": {
    "gn:admin1_code":"06",
    "gn:admin2_code":"33275.0",
    "gn:asciiname":"Dipsa",
    "gn:country_code":"RO",
    "gn:dem":323,
    "gn:feature_class":"P",
    "gn:feature_code":"PPL",
    "gn:name":"Dip\u0219a",
    "gn:population":842,
    "gn:timezone":"Europe/Bucharest",
    "iso:country":"RO",
    "wof:name":"Dipsa",
    "wof:placetype":"locality",
    "wof:population":842
},
  "geometry": {"coordinates":[24.43896,46.96234000000001],"type":"Point"}
}