{
  "type": "Feature",
  "properties": {
    "iso:country":"RO",
    "name:ron_x_preferred":[
        "P\u00eerli\u021bi"
    ],
    "name:rum_x_colloquial":[
        "Parliti",
        "Pirliti"
    ],
    "name:rum_x_variant":[
        "P\u00e2rli\u021bi"
    ],
    "qs:gn_adm0_cc":"RO",
    "qs:gn_local":666767,
    "qs:gn_nam_loc":"Slatina, Olt, RO",
    "qs:gn_namadm1":"29",
    "qs:local_max":107,
    "qs:local_sum":107,
    "qs:localhoods":1,
    "qs:name":"P\u00eerli\u021bi",
    "qs:name_adm0":"Rom\u00e2nia",
    "qs:name_adm1":"Olt",
    "qs:name_local":"Slatina",
    "qs:photo_max":27,
    "qs:photo_sum":107,
    "qs:placetype":"Suburb",
    "qs:quad_count":12,
    "qs:woe_adm0":23424933,
    "qs:woe_adm1":2346642,
    "qs:woe_adm2":0,
    "qs:woe_lau":0,
    "qs:woe_local":880584,
    "qs:woe_ver":"7.10.0",
    "wof:lang":[
        "rum"
    ],
    "wof:name":"P\u00eerli\u021bi",
    "wof:placetype":"neighbourhood"
},
  "geometry": {"coordinates":[24.359025,44.430535],"type":"Point"}
}