{
  "type": "Feature",
  "properties": {
    "gn:admin1_code":"16",
    "gn:admin2_code":"66857.0",
    "gn:asciiname":"Petresti",
    "gn:country_code":"RO",
    "gn:dem":145,
    "gn:feature_class":"P",
    "gn:feature_code":"PPL",
    "gn:name":"Petre\u0219ti",
    "gn:population":787,
    "gn:timezone":"Europe/Bucharest",
    "iso:country":"RO",
    "wof:name":"Petresti",
    "wof:placetype":"locality",
    "wof:population":787
},
  "geometry": {"coordinates":[25.44756,44.5577],"type":"Point"}
}