{
  "type": "Feature",
  "properties": {
    "gn:admin1_code":"34",
    "gn:admin2_code":"151344",
    "gn:asciiname":"Buda",
    "gn:country_code":"RO",
    "gn:dem":286,
    "gn:feature_class":"P",
    "gn:feature_code":"PPL",
    "gn:name":"Buda",
    "gn:population":982,
    "gn:timezone":"Europe/Bucharest",
    "iso:country":"RO",
    "name:afr_x_preferred":[
        "Boeda"
    ],
    "name:ara_x_preferred":[
        "\u0628\u0648\u062f\u0627"
    ],
    "name:arg_x_preferred":[
        "Buda"
    ],
    "name:aze_x_preferred":[
        "Buda"
    ],
    "name:bel_x_preferred":[
        "\u0411\u0443\u0434\u0430"
    ],
    "name:bul_x_preferred":[
        "\u0411\u0443\u0434\u0430"
    ],
    "name:cat_x_preferred":[
        "Buda"
    ],
    "name:ces_x_preferred":[
        "Bud\u00edn"
    ],
    "name:che_x_preferred":[
        "\u0411\u0443\u0434\u0430"
    ],
    "name:dan_x_preferred":[
        "Buda"
    ],
    "name:deu_x_preferred":[
        "Buda"
    ],
    "name:epo_x_preferred":[
        "Buda"
    ],
    "name:est_x_preferred":[
        "Buda"
    ],
    "name:fas_x_preferred":[
        "\u0628\u0648\u062f\u0627"
    ],
    "name:fin_x_preferred":[
        "Buda"
    ],
    "name:fra_x_preferred":[
        "Buda"
    ],
    "name:glg_x_preferred":[
        "Buda"
    ],
    "name:hrv_x_preferred":[
        "Budim"
    ],
    "name:hun_x_preferred":[
        "Buda"
    ],
    "name:hye_x_preferred":[
        "\u0532\u0578\u0582\u0564\u0561"
    ],
    "name:ind_x_preferred":[
        "Buda"
    ],
    "name:ita_x_preferred":[
        "Buda"
    ],
    "name:kaz_x_preferred":[
        "\u0411\u0443\u0434\u0430"
    ],
    "name:kur_x_preferred":[
        "Buda"
    ],
    "name:lat_x_preferred":[
        "Buda"
    ],
    "name:mkd_x_preferred":[
        "\u0411\u0443\u0434\u0438\u043c"
    ],
    "name:msa_x_preferred":[
        "Buda"
    ],
    "name:nld_x_preferred":[
        "Boeda"
    ],
    "name:nno_x_preferred":[
        "Buda"
    ],
    "name:pol_x_preferred":[
        "Buda"
    ],
    "name:por_x_preferred":[
        "Buda"
    ],
    "name:ron_x_preferred":[
        "Buda"
    ],
    "name:rue_x_preferred":[
        "\u0411\u0443\u0434\u0438\u043d"
    ],
    "name:rus_x_preferred":[
        "\u0411\u0443\u0434\u0430"
    ],
    "name:sco_x_preferred":[
        "Buda"
    ],
    "name:slk_x_preferred":[
        "Bud\u00edn"
    ],
    "name:slv_x_preferred":[
        "Budim"
    ],
    "name:spa_x_preferred":[
        "Buda"
    ],
    "name:srp_x_preferred":[
        "\u0411\u0443\u0434\u0438\u043c"
    ],
    "name:swe_x_preferred":[
        "Buda"
    ],
    "name:tha_x_preferred":[
        "\u0e1a\u0e39\u0e14\u0e2d"
    ],
    "name:tur_x_preferred":[
        "Budin"
    ],
    "name:ukr_x_preferred":[
        "\u0411\u0443\u0434\u0430"
    ],
    "name:vie_x_preferred":[
        "Buda"
    ],
    "wof:name":"Buda",
    "wof:placetype":"locality",
    "wof:population":982
},
  "geometry": {"coordinates":[26.26107,47.84539],"type":"Point"}
}