{
  "type": "Feature",
  "properties": {
    "gn:admin1_code":"34",
    "gn:admin2_code":"151344",
    "gn:asciiname":"Buda",
    "gn:country_code":"RO",
    "gn:dem":286,
    "gn:feature_class":"P",
    "gn:feature_code":"PPL",
    "gn:name":"Buda",
    "gn:population":982,
    "gn:timezone":"Europe/Bucharest",
    "iso:country":"RO",
    "wof:name":"Buda",
    "wof:placetype":"locality",
    "wof:population":982
},
  "geometry": {"coordinates":[26.26107,47.84539],"type":"Point"}
}