{
  "type": "Feature",
  "properties": {
    "gn:admin1_code":"39",
    "gn:admin2_code":"174290.0",
    "gn:asciiname":"Stanomiru",
    "gn:country_code":"RO",
    "gn:dem":233,
    "gn:feature_class":"P",
    "gn:feature_code":"PPL",
    "gn:name":"Stanomiru",
    "gn:population":215,
    "gn:timezone":"Europe/Bucharest",
    "iso:country":"RO",
    "wof:name":"Stanomiru",
    "wof:placetype":"locality",
    "wof:population":215
},
  "geometry": {"coordinates":[23.86244,44.74389],"type":"Point"}
}