{
  "type": "Feature",
  "properties": {
    "gn:admin1_code":"27",
    "gn:admin2_code":"119974.0",
    "gn:asciiname":"Melin",
    "gn:country_code":"RO",
    "gn:dem":327,
    "gn:feature_class":"P",
    "gn:feature_code":"PPL",
    "gn:name":"Melin",
    "gn:population":0,
    "gn:timezone":"Europe/Bucharest",
    "iso:country":"RO",
    "name:und_x_variant":[
        "M\u0103lin",
        "Melin"
    ],
    "wof:name":"Melin",
    "wof:placetype":"locality"
},
  "geometry": {"coordinates":[24.06667,46.61667],"type":"Point"}
}