{
  "type": "Feature",
  "properties": {
    "gn:admin1_code":"27",
    "gn:admin2_code":"119974.0",
    "gn:asciiname":"Melin",
    "gn:country_code":"RO",
    "gn:dem":327,
    "gn:feature_class":"P",
    "gn:feature_code":"PPL",
    "gn:name":"Melin",
    "gn:population":0,
    "gn:timezone":"Europe/Bucharest",
    "iso:country":"RO",
    "name:bug_x_preferred":[
        "Melin"
    ],
    "name:cat_x_preferred":[
        "Melin"
    ],
    "name:ceb_x_preferred":[
        "Melin"
    ],
    "name:deu_x_preferred":[
        "Melin"
    ],
    "name:eus_x_preferred":[
        "Melin"
    ],
    "name:fra_x_preferred":[
        "Melin"
    ],
    "name:hun_x_preferred":[
        "Melin"
    ],
    "name:ita_x_preferred":[
        "Melin"
    ],
    "name:lat_x_preferred":[
        "Melin"
    ],
    "name:msa_x_preferred":[
        "Melin"
    ],
    "name:nld_x_preferred":[
        "Melin"
    ],
    "name:oci_x_preferred":[
        "Melin"
    ],
    "name:pms_x_preferred":[
        "Melin"
    ],
    "name:pol_x_preferred":[
        "Melin"
    ],
    "name:por_x_preferred":[
        "Melin"
    ],
    "name:rus_x_preferred":[
        "\u041c\u0435\u043b\u0435\u043d"
    ],
    "name:slk_x_preferred":[
        "Melin"
    ],
    "name:spa_x_preferred":[
        "Melin"
    ],
    "name:swe_x_preferred":[
        "Melin"
    ],
    "name:ukr_x_preferred":[
        "\u041c\u0435\u043b\u0435\u043d"
    ],
    "name:und_x_variant":[
        "M\u0103lin"
    ],
    "name:uzb_x_preferred":[
        "Melin"
    ],
    "name:vie_x_preferred":[
        "Melin"
    ],
    "name:vol_x_preferred":[
        "Melin"
    ],
    "name:war_x_preferred":[
        "Melin"
    ],
    "wof:name":"Melin",
    "wof:placetype":"locality"
},
  "geometry": {"coordinates":[24.06667,46.61667],"type":"Point"}
}