{
  "type": "Feature",
  "properties": {
    "gn:admin1_code":"30",
    "gn:admin2_code":"134755.0",
    "gn:asciiname":"Predeal",
    "gn:country_code":"RO",
    "gn:dem":458,
    "gn:feature_class":"P",
    "gn:feature_code":"PPL",
    "gn:name":"Predeal",
    "gn:population":588,
    "gn:timezone":"Europe/Bucharest",
    "iso:country":"RO",
    "name:ceb_x_preferred":[
        "Ora\u0219 Predeal"
    ],
    "name:ces_x_preferred":[
        "Predeal"
    ],
    "name:deu_x_preferred":[
        "Predeal"
    ],
    "name:epo_x_preferred":[
        "Predeal"
    ],
    "name:fas_x_preferred":[
        "\u067e\u0631\u062f\u0627"
    ],
    "name:fra_x_preferred":[
        "Predeal"
    ],
    "name:heb_x_preferred":[
        "\u05e4\u05e8\u05d3\u05d9\u05d0\u05dc"
    ],
    "name:hun_x_preferred":[
        "Prede\u00e1l"
    ],
    "name:ind_x_preferred":[
        "Predeal"
    ],
    "name:ita_x_preferred":[
        "Predeal"
    ],
    "name:lat_x_preferred":[
        "Predeal"
    ],
    "name:min_x_preferred":[
        "Predeal"
    ],
    "name:msa_x_preferred":[
        "Predeal"
    ],
    "name:nld_x_preferred":[
        "Predeal"
    ],
    "name:pol_x_preferred":[
        "Predeal"
    ],
    "name:por_x_preferred":[
        "Predeal"
    ],
    "name:ron_x_preferred":[
        "Predeal"
    ],
    "name:rus_x_preferred":[
        "\u041f\u0440\u0435\u0434\u044f\u043b"
    ],
    "name:spa_x_preferred":[
        "Predeal"
    ],
    "name:srp_x_preferred":[
        "\u041f\u0440\u0435\u0434\u0435\u0430\u043b"
    ],
    "name:tgk_x_preferred":[
        "\u041f\u0440\u0435\u0434\u044f\u043b"
    ],
    "name:ukr_x_preferred":[
        "\u041f\u0440\u0435\u0434\u044f\u043b"
    ],
    "name:vie_x_preferred":[
        "Predeal"
    ],
    "name:zho_x_preferred":[
        "\u666e\u96f7\u4ee3\u4e9e\u723e"
    ],
    "wof:name":"Predeal",
    "wof:placetype":"locality",
    "wof:population":588
},
  "geometry": {"coordinates":[26.10253,45.18742],"type":"Point"}
}