{
  "type": "Feature",
  "properties": {
    "gn:admin1_code":"30",
    "gn:admin2_code":"134755.0",
    "gn:asciiname":"Predeal",
    "gn:country_code":"RO",
    "gn:dem":458,
    "gn:feature_class":"P",
    "gn:feature_code":"PPL",
    "gn:name":"Predeal",
    "gn:population":588,
    "gn:timezone":"Europe/Bucharest",
    "iso:country":"RO",
    "wof:name":"Predeal",
    "wof:placetype":"locality",
    "wof:population":588
},
  "geometry": {"coordinates":[26.10253,45.18742],"type":"Point"}
}