{
  "type": "Feature",
  "properties": {
    "gn:admin1_code":"18",
    "gn:admin2_code":"76807",
    "gn:asciiname":"Branistea",
    "gn:country_code":"RO",
    "gn:dem":147,
    "gn:feature_class":"P",
    "gn:feature_code":"PPL",
    "gn:name":"Br\u0103ni\u0219tea",
    "gn:population":49,
    "gn:timezone":"Europe/Bucharest",
    "iso:country":"RO",
    "wof:name":"Branistea",
    "wof:placetype":"locality",
    "wof:population":49
},
  "geometry": {"coordinates":[27.32603,45.94533],"type":"Point"}
}