{
  "type": "Feature",
  "properties": {
    "gn:gn_country":"RO",
    "gn:gn_fcode":"PPL",
    "gn:gn_pop":0,
    "gn:population":250,
    "iso:country":"RO",
    "name:ceb_x_preferred":[
        "T\u0103utelec"
    ],
    "name:eng_x_preferred":[
        "T\u0103utelec"
    ],
    "name:epo_x_preferred":[
        "T\u0103utelec"
    ],
    "name:fra_x_preferred":[
        "T\u0103utelec"
    ],
    "name:hun_x_preferred":[
        "Hegyk\u00f6zt\u00f3ttelek"
    ],
    "name:ita_x_preferred":[
        "T\u0103utelec"
    ],
    "name:nld_x_preferred":[
        "T\u0103utelec"
    ],
    "name:ron_x_preferred":[
        "T\u0103utelec"
    ],
    "name:srp_x_preferred":[
        "\u0422\u0430\u0443\u0442\u0435\u043b\u0435\u043a"
    ],
    "name:ukr_x_preferred":[
        "\u0422\u0435\u0443\u0442\u0435\u043b\u0435\u043a"
    ],
    "qs_pg:aaroncc":"RO",
    "qs_pg:gn_country":"RO",
    "qs_pg:gn_fcode":"PPL",
    "qs_pg:gn_pop":0,
    "qs_pg:name":"T\u0103utelec",
    "qs_pg:name_adm0":"Rom\u00e2nia",
    "qs_pg:name_adm1":"Bihor",
    "qs_pg:photos":12,
    "qs_pg:photos_1k":2,
    "qs_pg:photos_9k":1,
    "qs_pg:photos_9r":1,
    "qs_pg:photos_all":12,
    "qs_pg:photos_sr":1,
    "qs_pg:pop_sr":0,
    "qs_pg:qs_pg_placetype":"locality",
    "qs_pg:qs_pg_placetype_gp":"Town",
    "qs_pg:woe_adm0":23424933,
    "woe:adm0_id":23424933,
    "woe:name_adm0":"Rom\u00e2nia",
    "woe:name_adm1":"Bihor",
    "woe:placetype":"Town",
    "wof:name":"T\u0103utelec",
    "wof:placetype":"locality",
    "wof:population":250
},
  "geometry": {"coordinates":[22.03333,47.15],"type":"Point"}
}