{
  "type": "Feature",
  "properties": {
    "gn:admin1_code":"27",
    "gn:admin2_code":"119894",
    "gn:asciiname":"Recea",
    "gn:country_code":"RO",
    "gn:dem":289,
    "gn:feature_class":"P",
    "gn:feature_code":"PPL",
    "gn:name":"Recea",
    "gn:population":155,
    "gn:timezone":"Europe/Bucharest",
    "iso:country":"RO",
    "name:hun_x_preferred":[
        "Recsa"
    ],
    "wof:name":"Recea",
    "wof:placetype":"locality",
    "wof:population":155
},
  "geometry": {"coordinates":[24.41667,46.46667],"type":"Point"}
}