{
  "type": "Feature",
  "properties": {
    "gn:gn_country":"RO",
    "gn:gn_fcode":"PPLA2",
    "gn:gn_pop":1629,
    "gn:population":1629,
    "iso:country":"RO",
    "name:dut_x_preferred":[
        "Sacu"
    ],
    "name:eng_x_preferred":[
        "Sacu"
    ],
    "name:epo_x_preferred":[
        "Sacu"
    ],
    "name:fre_x_preferred":[
        "Sacu"
    ],
    "name:hun_x_preferred":[
        "Sz\u00e1kul"
    ],
    "name:ita_x_preferred":[
        "Sacu"
    ],
    "name:por_x_preferred":[
        "Sacu"
    ],
    "name:rum_x_preferred":[
        "Sacu"
    ],
    "name:ukr_x_preferred":[
        "\u0421\u0430\u043a\u0443"
    ],
    "name:unk_x_variant":[
        "Sacul"
    ],
    "name:vie_x_preferred":[
        "Sacu"
    ],
    "name:vol_x_preferred":[
        "Sacu"
    ],
    "qs_pg:aaroncc":"RO",
    "qs_pg:gn_country":"RO",
    "qs_pg:gn_fcode":"PPLA2",
    "qs_pg:gn_pop":1629,
    "qs_pg:name":"Sacu",
    "qs_pg:name_adm0":"Rom\u00e2nia",
    "qs_pg:name_adm1":"Caras-Severin",
    "qs_pg:photos_9r":0,
    "qs_pg:photos_sr":0,
    "qs_pg:pop_sr":3,
    "qs_pg:qs_pg_placetype":"locality",
    "qs_pg:qs_pg_placetype_gp":"Town",
    "qs_pg:woe_adm0":23424933,
    "woe:adm0_id":23424933,
    "woe:name_adm0":"Rom\u00e2nia",
    "woe:name_adm1":"Caras-Severin",
    "woe:placetype":"Town",
    "wof:name":"Sacu",
    "wof:placetype":"locality",
    "wof:population":1629
},
  "geometry": {"coordinates":[22.11667,45.56667],"type":"Point"}
}