{
  "type": "Feature",
  "properties": {
    "gn:admin1_code":"19",
    "gn:admin2_code":"80560.0",
    "gn:asciiname":"Gura Susitei",
    "gn:cc2":"RO",
    "gn:country_code":"RO",
    "gn:dem":121,
    "gn:feature_class":"P",
    "gn:feature_code":"PPL",
    "gn:name":"Gura \u0218u\u0219i\u021bei",
    "gn:population":336,
    "gn:timezone":"Europe/Bucharest",
    "iso:country":"RO",
    "name:und_x_variant":[
        "Su\u015fi\u0163a",
        "Gura \u015eu\u015fi\u0163ei"
    ],
    "wof:name":"Gura Susitei",
    "wof:placetype":"locality",
    "wof:population":336
},
  "geometry": {"coordinates":[23.43,44.60522],"type":"Point"}
}