{
  "type": "Feature",
  "properties": {
    "gn:admin1_code":"06",
    "gn:admin2_code":"35152.0",
    "gn:asciiname":"Sendroaia",
    "gn:cc2":"RO",
    "gn:country_code":"RO",
    "gn:dem":510,
    "gn:feature_class":"P",
    "gn:feature_code":"PPL",
    "gn:name":"\u0218endroaia",
    "gn:population":290,
    "gn:timezone":"Europe/Bucharest",
    "iso:country":"RO",
    "name:und_x_variant":[
        "Sandroaia",
        "Sendroaia"
    ],
    "wof:name":"Sendroaia",
    "wof:placetype":"locality",
    "wof:population":290
},
  "geometry": {"coordinates":[24.16592,47.44806],"type":"Point"}
}