{
  "type": "Feature",
  "properties": {
    "gn:admin1_code":"20",
    "gn:admin2_code":"85582",
    "gn:asciiname":"Bodogaia",
    "gn:cc2":"RO",
    "gn:country_code":"RO",
    "gn:dem":381,
    "gn:feature_class":"P",
    "gn:feature_code":"PPL",
    "gn:name":"Bodogaia",
    "gn:population":777,
    "gn:timezone":"Europe/Bucharest",
    "iso:country":"RO",
    "name:und_x_variant":[
        "Als\u00f2b\u00f2ldogfalva",
        "Bodogaia"
    ],
    "wof:name":"Bodogaia",
    "wof:placetype":"locality",
    "wof:population":777
},
  "geometry": {"coordinates":[24.99657,46.27462],"type":"Point"}
}