{
  "type": "Feature",
  "properties": {
    "gn:admin1_code":"11",
    "gn:admin2_code":"45003.0",
    "gn:asciiname":"Gura Ocii",
    "gn:country_code":"RO",
    "gn:dem":241,
    "gn:feature_class":"P",
    "gn:feature_code":"PPL",
    "gn:name":"Gura Ocii",
    "gn:population":0,
    "gn:timezone":"Europe/Bucharest",
    "iso:country":"RO",
    "name:und_x_variant":[
        "Ocea",
        "Gura Ocei",
        "Gura Ocii"
    ],
    "wof:lang_x_official":[
        "ron"
    ],
    "wof:lang_x_spoken":[
        "ron"
    ],
    "wof:name":"Gura Ocii",
    "wof:placetype":"locality"
},
  "geometry": {"coordinates":[26.76667,45.38333],"type":"Point"}
}