{
  "type": "Feature",
  "properties": {
    "iso:country":"RO",
    "name:eng_x_preferred":[
        "Tipografilor"
    ],
    "name:ron_x_preferred":[
        "Tipografilor"
    ],
    "wof:name":"Tipografilor",
    "wof:placetype":"neighbourhood"
},
  "geometry": {"coordinates":[21.23799449573334,45.76161125676438],"type":"Point"}
}