{
  "type": "Feature",
  "properties": {
    "iso:country":"RO",
    "name:eng_x_preferred":[
        "Tipografilor"
    ],
    "name:ron_x_preferred":[
        "Tipografilor"
    ],
    "wof:lang_x_official":[
        "ron"
    ],
    "wof:lang_x_spoken":[
        "ron"
    ],
    "wof:name":"Tipografilor",
    "wof:placetype":"neighbourhood"
},
  "geometry": {"coordinates":[21.237994,45.761611],"type":"Point"}
}