{
  "type": "Feature",
  "properties": {
    "gn:admin1_code":"01",
    "gn:admin2_code":"3039.0",
    "gn:asciiname":"Cretesti",
    "gn:country_code":"RO",
    "gn:dem":770,
    "gn:feature_class":"P",
    "gn:feature_code":"PPL",
    "gn:name":"Cre\u021be\u0219ti",
    "gn:population":220,
    "gn:timezone":"Europe/Bucharest",
    "iso:country":"RO",
    "wof:name":"Cretesti",
    "wof:placetype":"locality",
    "wof:population":220
},
  "geometry": {"coordinates":[23.10589,46.35793],"type":"Point"}
}