{
  "type": "Feature",
  "properties": {
    "gn:admin1_code":"26",
    "gn:admin2_code":"113732",
    "gn:asciiname":"Adunatii Teiului",
    "gn:country_code":"RO",
    "gn:dem":289,
    "gn:feature_class":"P",
    "gn:feature_code":"PPL",
    "gn:name":"Aduna\u021bii Teiului",
    "gn:population":183,
    "gn:timezone":"Europe/Bucharest",
    "iso:country":"RO",
    "wof:name":"Adunatii Teiului",
    "wof:placetype":"locality",
    "wof:population":183
},
  "geometry": {"coordinates":[23.05436,44.51877],"type":"Point"}
}