{
  "type": "Feature",
  "properties": {
    "gn:admin1_code":"26",
    "gn:admin2_code":"110535.0",
    "gn:asciiname":"Dobra",
    "gn:country_code":"RO",
    "gn:dem":271,
    "gn:feature_class":"P",
    "gn:feature_code":"PPL",
    "gn:name":"Dobra",
    "gn:population":664,
    "gn:timezone":"Europe/Bucharest",
    "iso:country":"RO",
    "name:bel_x_preferred":[
        "\u0414\u043e\u0431\u0440\u0430"
    ],
    "name:bos_x_preferred":[
        "Dobra"
    ],
    "name:bul_x_preferred":[
        "\u0414\u043e\u0431\u0440\u0430"
    ],
    "name:ceb_x_preferred":[
        "Dobra"
    ],
    "name:dan_x_preferred":[
        "Dobra"
    ],
    "name:deu_x_preferred":[
        "Dobra"
    ],
    "name:epo_x_preferred":[
        "Dobra"
    ],
    "name:fra_x_preferred":[
        "Dobra"
    ],
    "name:glg_x_preferred":[
        "Dobra"
    ],
    "name:heb_x_preferred":[
        "\u05d3\u05d5\u05d1\u05e8\u05d4"
    ],
    "name:hrv_x_preferred":[
        "Dobra"
    ],
    "name:hun_x_preferred":[
        "Dobra"
    ],
    "name:ita_x_preferred":[
        "Dobra"
    ],
    "name:lav_x_preferred":[
        "Dobra"
    ],
    "name:nld_x_preferred":[
        "Dobra"
    ],
    "name:pol_x_preferred":[
        "Dobra"
    ],
    "name:por_x_preferred":[
        "Dobra"
    ],
    "name:ron_x_preferred":[
        "Dobra"
    ],
    "name:rus_x_preferred":[
        "\u0414\u043e\u0431\u0440\u0430"
    ],
    "name:slk_x_preferred":[
        "Dobra"
    ],
    "name:spa_x_preferred":[
        "Dobra"
    ],
    "name:srp_x_preferred":[
        "\u0414\u043e\u0431\u0440\u0430"
    ],
    "name:swe_x_preferred":[
        "Dobra"
    ],
    "name:tur_x_preferred":[
        "Dobra"
    ],
    "name:ukr_x_preferred":[
        "\u0414\u043e\u0431\u0440\u0430"
    ],
    "name:vol_x_preferred":[
        "Dobra"
    ],
    "wof:name":"Dobra",
    "wof:placetype":"locality",
    "wof:population":664
},
  "geometry": {"coordinates":[23.0904,44.39069],"type":"Point"}
}