{
  "type": "Feature",
  "properties": {
    "gn:admin1_code":"26",
    "gn:admin2_code":"110535.0",
    "gn:asciiname":"Dobra",
    "gn:country_code":"RO",
    "gn:dem":271,
    "gn:feature_class":"P",
    "gn:feature_code":"PPL",
    "gn:name":"Dobra",
    "gn:population":664,
    "gn:timezone":"Europe/Bucharest",
    "iso:country":"RO",
    "wof:name":"Dobra",
    "wof:placetype":"locality",
    "wof:population":664
},
  "geometry": {"coordinates":[23.0904,44.39069],"type":"Point"}
}