{
  "type": "Feature",
  "properties": {
    "gn:admin1_code":"34",
    "gn:admin2_code":"148131.0",
    "gn:asciiname":"Rusca",
    "gn:country_code":"RO",
    "gn:dem":772,
    "gn:feature_class":"P",
    "gn:feature_code":"PPL",
    "gn:name":"Rusca",
    "gn:population":295,
    "gn:timezone":"Europe/Bucharest",
    "iso:country":"RO",
    "name:ceb_x_preferred":[
        "Rusca"
    ],
    "name:deu_x_preferred":[
        "Rusca"
    ],
    "name:ita_x_preferred":[
        "Rusca"
    ],
    "name:ron_x_preferred":[
        "Rusca"
    ],
    "name:rus_x_preferred":[
        "\u0420\u0443\u0441\u043a\u0430"
    ],
    "name:ukr_x_preferred":[
        "\u0420\u0443\u0441\u043a\u0430"
    ],
    "wof:name":"Rusca",
    "wof:placetype":"locality",
    "wof:population":295
},
  "geometry": {"coordinates":[25.45435,47.36975],"type":"Point"}
}