{
  "type": "Feature",
  "properties": {
    "gn:admin1_code":"39",
    "gn:admin2_code":"172698.0",
    "gn:asciiname":"Ratalesti",
    "gn:country_code":"RO",
    "gn:dem":301,
    "gn:feature_class":"P",
    "gn:feature_code":"PPL",
    "gn:name":"R\u0103\u021b\u0103le\u0219ti",
    "gn:population":230,
    "gn:timezone":"Europe/Bucharest",
    "iso:country":"RO",
    "wof:name":"Ratalesti",
    "wof:placetype":"locality",
    "wof:population":230
},
  "geometry": {"coordinates":[23.92002,44.88981],"type":"Point"}
}