{
  "type": "Feature",
  "properties": {
    "gn:admin1_code":"41",
    "gn:admin2_code":"93888.0",
    "gn:asciiname":"Buzoeni",
    "gn:country_code":"RO",
    "gn:dem":48,
    "gn:feature_class":"P",
    "gn:feature_code":"PPL",
    "gn:name":"Buzoeni",
    "gn:population":605,
    "gn:timezone":"Europe/Bucharest",
    "iso:country":"RO",
    "wof:name":"Buzoeni",
    "wof:placetype":"locality",
    "wof:population":605
},
  "geometry": {"coordinates":[26.81211,44.41397],"type":"Point"}
}