{
  "type": "Feature",
  "properties": {
    "gn:admin1_code":"03",
    "gn:admin2_code":"17254.0",
    "gn:asciiname":"Furnicosi",
    "gn:country_code":"RO",
    "gn:dem":462,
    "gn:feature_class":"P",
    "gn:feature_code":"PPL",
    "gn:name":"Furnico\u0219i",
    "gn:population":802,
    "gn:timezone":"Europe/Bucharest",
    "iso:country":"RO",
    "wof:name":"Furnicosi",
    "wof:placetype":"locality",
    "wof:population":802
},
  "geometry": {"coordinates":[25.00198,45.14302],"type":"Point"}
}