{
  "type": "Feature",
  "properties": {
    "gn:admin1_code":"23",
    "gn:admin2_code":"95159.0",
    "gn:asciiname":"Orzeni",
    "gn:country_code":"RO",
    "gn:dem":102,
    "gn:feature_class":"P",
    "gn:feature_code":"PPL",
    "gn:name":"Orzeni",
    "gn:population":571,
    "gn:timezone":"Europe/Bucharest",
    "iso:country":"RO",
    "wof:name":"Orzeni",
    "wof:placetype":"locality",
    "wof:population":571
},
  "geometry": {"coordinates":[27.6936,47.18228],"type":"Point"}
}