{
  "type": "Feature",
  "properties": {
    "gn:admin1_code":"36",
    "gn:admin2_code":"155957",
    "gn:asciiname":"Botesti",
    "gn:country_code":"RO",
    "gn:dem":198,
    "gn:feature_class":"P",
    "gn:feature_code":"PPL",
    "gn:name":"Bote\u0219ti",
    "gn:population":114,
    "gn:timezone":"Europe/Bucharest",
    "iso:country":"RO",
    "wof:name":"Botesti",
    "wof:placetype":"locality",
    "wof:population":114
},
  "geometry": {"coordinates":[22.0852,45.70271],"type":"Point"}
}