{
  "type": "Feature",
  "properties": {
    "gn:admin1_code":"39",
    "gn:admin2_code":"174290.0",
    "gn:asciiname":"Oltetu",
    "gn:cc2":"RO",
    "gn:country_code":"RO",
    "gn:dem":236,
    "gn:feature_class":"P",
    "gn:feature_code":"PPL",
    "gn:name":"Olte\u021bu",
    "gn:population":162,
    "gn:timezone":"Europe/Bucharest",
    "iso:country":"RO",
    "name:und_x_variant":[
        "Olte\u0163ul",
        "Olte\u0163u"
    ],
    "wof:name":"Oltetu",
    "wof:placetype":"locality",
    "wof:population":162
},
  "geometry": {"coordinates":[23.84176,44.77652],"type":"Point"}
}