{
  "type": "Feature",
  "properties": {
    "gn:admin1_code":"12",
    "gn:admin2_code":"52160.0",
    "gn:asciiname":"Prisacina",
    "gn:cc2":"RO",
    "gn:country_code":"RO",
    "gn:dem":800,
    "gn:feature_class":"P",
    "gn:feature_code":"PPL",
    "gn:name":"Prisacina",
    "gn:population":51,
    "gn:timezone":"Europe/Bucharest",
    "iso:country":"RO",
    "name:und_x_variant":[
        "Presacina",
        "Prisacina"
    ],
    "wof:name":"Prisacina",
    "wof:placetype":"locality",
    "wof:population":51
},
  "geometry": {"coordinates":[22.48503,45.01588],"type":"Point"}
}