{
  "type": "Feature",
  "properties": {
    "gn:admin1_code":"39",
    "gn:admin2_code":"173855.0",
    "gn:asciiname":"Nenciulesti",
    "gn:country_code":"RO",
    "gn:dem":261,
    "gn:feature_class":"P",
    "gn:feature_code":"PPL",
    "gn:name":"Nenciule\u0219ti",
    "gn:population":482,
    "gn:timezone":"Europe/Bucharest",
    "iso:country":"RO",
    "wof:name":"Nenciulesti",
    "wof:placetype":"locality",
    "wof:population":482
},
  "geometry": {"coordinates":[23.91688,44.8211],"type":"Point"}
}