{
  "type": "Feature",
  "properties": {
    "gn:admin1_code":"39",
    "gn:admin2_code":"171272.0",
    "gn:asciiname":"Maldarestii de Jos",
    "gn:country_code":"RO",
    "gn:dem":436,
    "gn:feature_class":"P",
    "gn:feature_code":"PPL",
    "gn:name":"M\u0103ld\u0103re\u0219tii de Jos",
    "gn:population":561,
    "gn:timezone":"Europe/Bucharest",
    "iso:country":"RO",
    "wof:name":"Maldarestii de Jos",
    "wof:placetype":"locality",
    "wof:population":561
},
  "geometry": {"coordinates":[24.01703,45.10713],"type":"Point"}
}