{
  "type": "Feature",
  "properties": {
    "gn:admin1_code":"33",
    "gn:admin2_code":"145499.0",
    "gn:asciiname":"Vale",
    "gn:country_code":"RO",
    "gn:dem":560,
    "gn:feature_class":"P",
    "gn:feature_code":"PPL",
    "gn:name":"Vale",
    "gn:population":428,
    "gn:timezone":"Europe/Bucharest",
    "iso:country":"RO",
    "name:ceb_x_preferred":[
        "Vale"
    ],
    "name:deu_x_preferred":[
        "Vale"
    ],
    "name:epo_x_preferred":[
        "Vale"
    ],
    "name:fin_x_preferred":[
        "Vale"
    ],
    "name:fra_x_preferred":[
        "Vale"
    ],
    "name:glg_x_preferred":[
        "Vale"
    ],
    "name:hun_x_preferred":[
        "Vale"
    ],
    "name:ita_x_preferred":[
        "Vale"
    ],
    "name:nld_x_preferred":[
        "Vale"
    ],
    "name:nor_x_preferred":[
        "Vale"
    ],
    "name:pol_x_preferred":[
        "Vale"
    ],
    "name:por_x_preferred":[
        "Vale"
    ],
    "name:ron_x_preferred":[
        "Vale"
    ],
    "name:rus_x_preferred":[
        "Vale"
    ],
    "name:spa_x_preferred":[
        "Vale"
    ],
    "name:srp_x_preferred":[
        "\u0412\u0435\u0458\u043b"
    ],
    "name:swe_x_preferred":[
        "Vale"
    ],
    "wof:name":"Vale",
    "wof:placetype":"locality",
    "wof:population":428
},
  "geometry": {"coordinates":[23.89549,45.78188],"type":"Point"}
}