{
  "type": "Feature",
  "properties": {
    "gn:admin1_code":"33",
    "gn:admin2_code":"145499.0",
    "gn:asciiname":"Vale",
    "gn:country_code":"RO",
    "gn:dem":560,
    "gn:feature_class":"P",
    "gn:feature_code":"PPL",
    "gn:name":"Vale",
    "gn:population":428,
    "gn:timezone":"Europe/Bucharest",
    "iso:country":"RO",
    "wof:name":"Vale",
    "wof:placetype":"locality",
    "wof:population":428
},
  "geometry": {"coordinates":[23.89549,45.78188],"type":"Point"}
}