{
  "type": "Feature",
  "properties": {
    "gn:admin1_code":"27",
    "gn:admin2_code":"118824.0",
    "gn:asciiname":"Parau Crucii",
    "gn:country_code":"RO",
    "gn:dem":388,
    "gn:feature_class":"P",
    "gn:feature_code":"PPL",
    "gn:name":"P\u00e2r\u00e2u Crucii",
    "gn:population":112,
    "gn:timezone":"Europe/Bucharest",
    "iso:country":"RO",
    "wof:name":"Parau Crucii",
    "wof:placetype":"locality",
    "wof:population":112
},
  "geometry": {"coordinates":[24.33705,46.69417],"type":"Point"}
}