{
  "type": "Feature",
  "properties": {
    "gn:admin1_code":"01",
    "gn:admin2_code":"3841.0",
    "gn:asciiname":"Fantanele",
    "gn:cc2":"RO",
    "gn:country_code":"RO",
    "gn:dem":556,
    "gn:feature_class":"P",
    "gn:feature_code":"PPL",
    "gn:name":"F\u00e2nt\u00e2nele",
    "gn:population":45,
    "gn:timezone":"Europe/Bucharest",
    "iso:country":"RO",
    "name:und_x_variant":[
        "Ciungi",
        "F\u00eent\u00eenele"
    ],
    "wof:name":"Fantanele",
    "wof:placetype":"locality",
    "wof:population":45
},
  "geometry": {"coordinates":[23.26873,46.02894000000001],"type":"Point"}
}