{
  "type": "Feature",
  "properties": {
    "gn:admin1_code":"26",
    "gn:admin2_code":"112995.0",
    "gn:asciiname":"Ceptureni",
    "gn:country_code":"RO",
    "gn:dem":458,
    "gn:feature_class":"P",
    "gn:feature_code":"PPL",
    "gn:name":"Ceptureni",
    "gn:population":160,
    "gn:timezone":"Europe/Bucharest",
    "iso:country":"RO",
    "wof:name":"Ceptureni",
    "wof:placetype":"locality",
    "wof:population":160
},
  "geometry": {"coordinates":[22.76246,44.99345],"type":"Point"}
}