{
  "type": "Feature",
  "properties": {
    "gn:country":"RO",
    "gn:fcode":"PPL",
    "gn:population":1141,
    "iso:country":"RO",
    "name:und_x_variant":[
        "Znagov"
    ],
    "qs_pg:aaroncc":"RO",
    "qs_pg:gn_country":"RO",
    "qs_pg:gn_fcode":"PPL",
    "qs_pg:gn_pop":1141,
    "qs_pg:name":"Dr\u0103goe\u015fti-Snagov",
    "qs_pg:photos_9r":0,
    "qs_pg:photos_sr":0,
    "qs_pg:pop_sr":3,
    "qs_pg:qs_pg_placetype":"locality",
    "wof:name":"Dr\u0103goe\u015fti-Snagov",
    "wof:placetype":"locality",
    "wof:population":1141
},
  "geometry": {"coordinates":[26.53333,44.56667],"type":"Point"}
}