{
  "type": "Feature",
  "properties": {
    "gn:admin1_code":"38",
    "gn:admin2_code":"164393.0",
    "gn:asciiname":"Cosca",
    "gn:cc2":"RO",
    "gn:country_code":"RO",
    "gn:dem":215,
    "gn:feature_class":"P",
    "gn:feature_code":"PPL",
    "gn:name":"Co\u015fca",
    "gn:population":0,
    "gn:timezone":"Europe/Bucharest",
    "iso:country":"RO",
    "name:spa_x_preferred":[
        "Cosca"
    ],
    "name:und_x_variant":[
        "Fund\u0103tura-Co\u015fca",
        "Co\u015fca"
    ],
    "wof:name":"Cosca",
    "wof:placetype":"locality"
},
  "geometry": {"coordinates":[27.47346,46.68219000000001],"type":"Point"}
}