{
  "type": "Feature",
  "properties": {
    "gn:admin1_code":"21",
    "gn:admin2_code":"90878.0",
    "gn:asciiname":"Sibisel",
    "gn:country_code":"RO",
    "gn:dem":514,
    "gn:feature_class":"P",
    "gn:feature_code":"PPL",
    "gn:name":"Sibi\u0219el",
    "gn:population":270,
    "gn:timezone":"Europe/Bucharest",
    "iso:country":"RO",
    "wof:name":"Sibisel",
    "wof:placetype":"locality",
    "wof:population":270
},
  "geometry": {"coordinates":[22.9024,45.50666],"type":"Point"}
}