{
  "type": "Feature",
  "properties": {
    "gn:admin1_code":"01",
    "gn:admin2_code":"1455.0",
    "gn:asciiname":"Valea Caselor",
    "gn:country_code":"RO",
    "gn:dem":860,
    "gn:feature_class":"P",
    "gn:feature_code":"PPL",
    "gn:name":"Valea Caselor",
    "gn:population":141,
    "gn:timezone":"Europe/Bucharest",
    "iso:country":"RO",
    "name:ceb_x_preferred":[
        "Valea Caselor"
    ],
    "name:deu_x_preferred":[
        "Valea Caselor"
    ],
    "name:ron_x_preferred":[
        "Valea Caselor"
    ],
    "name:srp_x_preferred":[
        "\u0412\u0430\u0459\u0430 \u041a\u0430\u0441\u0435\u043b\u043e\u0440"
    ],
    "name:ukr_x_preferred":[
        "\u0412\u0430\u043b\u044f-\u041a\u0430\u0441\u0435\u043b\u043e\u0440"
    ],
    "wof:name":"Valea Caselor",
    "wof:placetype":"locality",
    "wof:population":141
},
  "geometry": {"coordinates":[23.03362000000001,46.39836],"type":"Point"}
}