{
  "type": "Feature",
  "properties": {
    "gn:admin1_code":"01",
    "gn:admin2_code":"1455.0",
    "gn:asciiname":"Valea Caselor",
    "gn:country_code":"RO",
    "gn:dem":860,
    "gn:feature_class":"P",
    "gn:feature_code":"PPL",
    "gn:name":"Valea Caselor",
    "gn:population":141,
    "gn:timezone":"Europe/Bucharest",
    "iso:country":"RO",
    "wof:name":"Valea Caselor",
    "wof:placetype":"locality",
    "wof:population":141
},
  "geometry": {"coordinates":[23.03362000000001,46.39836],"type":"Point"}
}