{
  "type": "Feature",
  "properties": {
    "gn:admin1_code":"39",
    "gn:admin2_code":"173230.0",
    "gn:asciiname":"Neghinesti",
    "gn:country_code":"RO",
    "gn:dem":511,
    "gn:feature_class":"P",
    "gn:feature_code":"PPL",
    "gn:name":"Neghine\u0219ti",
    "gn:population":172,
    "gn:timezone":"Europe/Bucharest",
    "iso:country":"RO",
    "wof:name":"Neghinesti",
    "wof:placetype":"locality",
    "wof:population":172
},
  "geometry": {"coordinates":[24.18386,45.15681],"type":"Point"}
}