{
  "type": "Feature",
  "properties": {
    "gn:admin1_code":"13",
    "gn:admin2_code":"56773.0",
    "gn:asciiname":"Copru",
    "gn:cc2":"RO",
    "gn:country_code":"RO",
    "gn:dem":337,
    "gn:feature_class":"P",
    "gn:feature_code":"PPL",
    "gn:name":"Copru",
    "gn:population":163,
    "gn:timezone":"Europe/Bucharest",
    "iso:country":"RO",
    "name:und_x_variant":[
        "Coprul",
        "Copru"
    ],
    "wof:name":"Copru",
    "wof:placetype":"locality",
    "wof:population":163
},
  "geometry": {"coordinates":[24.20493,46.87454],"type":"Point"}
}