{
  "type": "Feature",
  "properties": {
    "gn:admin1_code":"11",
    "gn:admin2_code":"46019.0",
    "gn:asciiname":"Vladeni",
    "gn:country_code":"RO",
    "gn:dem":187,
    "gn:feature_class":"P",
    "gn:feature_code":"PPL",
    "gn:name":"Vl\u0103deni",
    "gn:population":58,
    "gn:timezone":"Europe/Bucharest",
    "iso:country":"RO",
    "wof:name":"Vladeni",
    "wof:placetype":"locality",
    "wof:population":58
},
  "geometry": {"coordinates":[26.76031,45.28224],"type":"Point"}
}