{
  "type": "Feature",
  "properties": {
    "gn:admin1_code":"04",
    "gn:admin2_code":"23494.0",
    "gn:asciiname":"Cociu",
    "gn:cc2":"RO",
    "gn:country_code":"RO",
    "gn:dem":199,
    "gn:feature_class":"P",
    "gn:feature_code":"PPL",
    "gn:name":"Cociu",
    "gn:population":238,
    "gn:timezone":"Europe/Bucharest",
    "iso:country":"RO",
    "name:ceb_x_preferred":[
        "Cociu"
    ],
    "name:deu_x_preferred":[
        "Cociu"
    ],
    "name:ron_x_preferred":[
        "Cociu"
    ],
    "name:srp_x_preferred":[
        "\u041a\u043e\u0447\u0443"
    ],
    "name:und_x_variant":[
        "St\u0103nue\u015fti",
        "Cociu-St\u0103nue\u015fti",
        "Cociul"
    ],
    "wof:name":"Cociu",
    "wof:placetype":"locality",
    "wof:population":238
},
  "geometry": {"coordinates":[27.43351,46.28731],"type":"Point"}
}