{
  "type": "Feature",
  "properties": {
    "gn:admin1_code":"02",
    "gn:admin2_code":"12572",
    "gn:asciiname":"Baia",
    "gn:country_code":"RO",
    "gn:dem":221,
    "gn:feature_class":"P",
    "gn:feature_code":"PPL",
    "gn:name":"Baia",
    "gn:population":175,
    "gn:timezone":"Europe/Bucharest",
    "iso:country":"RO",
    "name:ron_x_preferred":[
        "Baia"
    ],
    "name:und_x_variant":[
        "B\u00e1ja",
        "Kisbaja"
    ],
    "wof:name":"Baia",
    "wof:placetype":"locality",
    "wof:population":175
},
  "geometry": {"coordinates":[22.17463,46.09075],"type":"Point"}
}