{
  "type": "Feature",
  "properties": {
    "gn:country":"RO",
    "gn:fcode":"PPL",
    "gn:population":0,
    "iso:country":"RO",
    "name:ceb_x_preferred":[
        "Dume\u0219ti"
    ],
    "name:deu_x_preferred":[
        "Dume\u0219ti"
    ],
    "name:hun_x_preferred":[
        "Dume\u0219ti"
    ],
    "name:ita_x_preferred":[
        "Dume\u0219ti"
    ],
    "name:nld_x_preferred":[
        "Dume\u0219ti"
    ],
    "name:ron_x_preferred":[
        "Dume\u0219ti"
    ],
    "name:srp_x_preferred":[
        "\u0414\u0443\u043c\u0435\u0448\u0442\u0438"
    ],
    "qs_pg:aaroncc":"RO",
    "qs_pg:gn_country":"RO",
    "qs_pg:gn_fcode":"PPL",
    "qs_pg:gn_pop":0,
    "qs_pg:name":"Dume\u0219ti",
    "qs_pg:name_adm0":"Rom\u00e2nia",
    "qs_pg:name_adm1":"Alba",
    "qs_pg:photos":38,
    "qs_pg:photos_1k":8,
    "qs_pg:photos_9k":1,
    "qs_pg:photos_9r":2,
    "qs_pg:photos_all":38,
    "qs_pg:photos_sr":2,
    "qs_pg:pop_sr":0,
    "qs_pg:qs_pg_placetype":"locality",
    "qs_pg:qs_pg_placetype_gp":"Town",
    "qs_pg:woe_adm0":23424933,
    "woe:adm0_id":23424933,
    "woe:name_adm0":"Rom\u00e2nia",
    "woe:name_adm1":"Alba",
    "woe:placetype":"Town",
    "wof:name":"Dume\u0219ti",
    "wof:placetype":"locality",
    "wof:population":111
},
  "geometry": {"coordinates":[23.43333,46.36667],"type":"Point"}
}