{
  "type": "Feature",
  "properties": {
    "gn:admin1_code":"39",
    "gn:admin2_code":"173061.0",
    "gn:asciiname":"Milostea",
    "gn:country_code":"RO",
    "gn:dem":457,
    "gn:feature_class":"P",
    "gn:feature_code":"PPL",
    "gn:name":"Milostea",
    "gn:population":954,
    "gn:timezone":"Europe/Bucharest",
    "iso:country":"RO",
    "wof:name":"Milostea",
    "wof:placetype":"locality",
    "wof:population":954
},
  "geometry": {"coordinates":[23.83597,45.12497000000001],"type":"Point"}
}