{
  "type": "Feature",
  "properties": {
    "gn:admin1_code":"13",
    "gn:admin2_code":"56844.0",
    "gn:asciiname":"Ciurgau",
    "gn:country_code":"RO",
    "gn:dem":365,
    "gn:feature_class":"P",
    "gn:feature_code":"PPL",
    "gn:name":"Ciurg\u0103u",
    "gn:population":78,
    "gn:timezone":"Europe/Bucharest",
    "iso:country":"RO",
    "wof:name":"Ciurgau",
    "wof:placetype":"locality",
    "wof:population":78
},
  "geometry": {"coordinates":[23.93787,46.66056],"type":"Point"}
}