{
  "type": "Feature",
  "properties": {
    "gn:admin1_code":"09",
    "gn:admin2_code":"41854.0",
    "gn:asciiname":"Ohaba",
    "gn:country_code":"RO",
    "gn:dem":481,
    "gn:feature_class":"P",
    "gn:feature_code":"PPL",
    "gn:name":"Ohaba",
    "gn:population":332,
    "gn:timezone":"Europe/Bucharest",
    "iso:country":"RO",
    "wof:name":"Ohaba",
    "wof:placetype":"locality",
    "wof:population":332
},
  "geometry": {"coordinates":[25.15203,45.76574],"type":"Point"}
}