{
  "type": "Feature",
  "properties": {
    "gn:admin1_code":"09",
    "gn:admin2_code":"41854.0",
    "gn:asciiname":"Ohaba",
    "gn:country_code":"RO",
    "gn:dem":481,
    "gn:feature_class":"P",
    "gn:feature_code":"PPL",
    "gn:name":"Ohaba",
    "gn:population":332,
    "gn:timezone":"Europe/Bucharest",
    "iso:country":"RO",
    "name:ara_x_preferred":[
        "\u0648\u0647\u0627\u0628\u0627"
    ],
    "name:ceb_x_preferred":[
        "Comuna Ohaba"
    ],
    "name:deu_x_preferred":[
        "Ohaba"
    ],
    "name:epo_x_preferred":[
        "Ohaba"
    ],
    "name:fra_x_preferred":[
        "Ohaba"
    ],
    "name:ita_x_preferred":[
        "Ohaba"
    ],
    "name:mkd_x_preferred":[
        "\u041e\u0445\u0430\u0431\u0430"
    ],
    "name:msa_x_preferred":[
        "Ohaba"
    ],
    "name:nld_x_preferred":[
        "Ohaba"
    ],
    "name:por_x_preferred":[
        "Ohaba"
    ],
    "name:ron_x_preferred":[
        "Comuna Ohaba"
    ],
    "name:sqi_x_preferred":[
        "Ohaba"
    ],
    "name:srp_x_preferred":[
        "\u041e\u043f\u0448\u0442\u0438\u043d\u0430 \u041e\u0445\u0430\u0431\u0430"
    ],
    "name:ukr_x_preferred":[
        "\u041e\u0445\u0430\u0431\u0430"
    ],
    "name:vie_x_preferred":[
        "Ohaba"
    ],
    "name:vol_x_preferred":[
        "Ohaba"
    ],
    "name:zho_x_preferred":[
        "\u5967\u54c8\u5df4\u9109"
    ],
    "wof:name":"Ohaba",
    "wof:placetype":"locality",
    "wof:population":332
},
  "geometry": {"coordinates":[25.15203,45.76574],"type":"Point"}
}