{
  "type": "Feature",
  "properties": {
    "gn:admin1_code":"07",
    "gn:admin2_code":"39328.0",
    "gn:asciiname":"Ciritei",
    "gn:country_code":"RO",
    "gn:dem":118,
    "gn:feature_class":"P",
    "gn:feature_code":"PPL",
    "gn:name":"Ciritei",
    "gn:population":8,
    "gn:timezone":"Europe/Bucharest",
    "iso:country":"RO",
    "name:deu_x_preferred":[
        "Ciritei"
    ],
    "name:ron_x_preferred":[
        "Ciritei"
    ],
    "wof:name":"Ciritei",
    "wof:placetype":"locality",
    "wof:population":8
},
  "geometry": {"coordinates":[26.96497,47.79236],"type":"Point"}
}