{
  "type": "Feature",
  "properties": {
    "gn:admin1_code":"12",
    "gn:admin2_code":"51877.0",
    "gn:asciiname":"Zagujeni",
    "gn:cc2":"RO",
    "gn:country_code":"RO",
    "gn:dem":185,
    "gn:feature_class":"P",
    "gn:feature_code":"PPL",
    "gn:name":"Z\u0103gujeni",
    "gn:population":568,
    "gn:timezone":"Europe/Bucharest",
    "iso:country":"RO",
    "name:und_x_variant":[
        "Zegujani",
        "Z\u0103gujeni"
    ],
    "wof:name":"Zagujeni",
    "wof:placetype":"locality",
    "wof:population":568
},
  "geometry": {"coordinates":[22.16286,45.48204000000001],"type":"Point"}
}