{
  "type": "Feature",
  "properties": {
    "gn:admin1_code":"40",
    "gn:admin2_code":"176338",
    "gn:asciiname":"Balanesti",
    "gn:country_code":"RO",
    "gn:dem":188,
    "gn:feature_class":"P",
    "gn:feature_code":"PPL",
    "gn:name":"B\u0103l\u0103ne\u0219ti",
    "gn:population":4,
    "gn:timezone":"Europe/Bucharest",
    "iso:country":"RO",
    "wof:name":"Balanesti",
    "wof:placetype":"locality",
    "wof:population":4
},
  "geometry": {"coordinates":[26.9644,45.60891],"type":"Point"}
}