{
  "type": "Feature",
  "properties": {
    "gn:admin1_code":"02",
    "gn:admin2_code":"10943",
    "gn:asciiname":"Bontesti",
    "gn:country_code":"RO",
    "gn:dem":169,
    "gn:feature_class":"P",
    "gn:feature_code":"PPL",
    "gn:name":"Bon\u021be\u0219ti",
    "gn:population":703,
    "gn:timezone":"Europe/Bucharest",
    "iso:country":"RO",
    "name:ron_x_preferred":[
        "Bon\u021be\u0219ti"
    ],
    "name:und_x_variant":[
        "Bonczesd",
        "Bonczafalva",
        "Bonczesty",
        "Boncafalva"
    ],
    "wof:name":"Bontesti",
    "wof:placetype":"locality",
    "wof:population":703
},
  "geometry": {"coordinates":[22.30572,46.27471],"type":"Point"}
}