{
  "type": "Feature",
  "properties": {
    "gn:admin1_code":"16",
    "gn:admin2_code":"68182.0",
    "gn:asciiname":"Dobresti",
    "gn:country_code":"RO",
    "gn:dem":921,
    "gn:feature_class":"P",
    "gn:feature_code":"PPL",
    "gn:name":"Dobre\u015fti",
    "gn:population":0,
    "gn:timezone":"Europe/Bucharest",
    "iso:country":"RO",
    "wof:name":"Dobresti",
    "wof:placetype":"locality"
},
  "geometry": {"coordinates":[25.40674,45.29434000000001],"type":"Point"}
}