{
  "type": "Feature",
  "properties": {
    "iso:country":"RO",
    "name:rum_x_preferred":[
        "Cindia"
    ],
    "name:unk_x_variant":[
        "Cindia"
    ],
    "qs:gn_adm0_cc":"RO",
    "qs:gn_fcode":"PPLX",
    "qs:gn_local":670889,
    "qs:gn_namadm1":"00",
    "qs:gn_name":"Cindia",
    "qs:local_max":744,
    "qs:local_sum":745,
    "qs:localhoods":2,
    "qs:name":"Cindia",
    "qs:name_adm0":"Rom\u00e2nia",
    "qs:name_adm1":"Neamt",
    "qs:name_local":"Piatra Neam\u021b",
    "qs:photo_max":1,
    "qs:photo_sum":1,
    "qs:placetype":"Suburb",
    "qs:quad_count":1,
    "qs:woe_adm0":23424933,
    "qs:woe_adm1":2346641,
    "qs:woe_adm2":0,
    "qs:woe_lau":0,
    "qs:woe_local":877543,
    "qs:woe_ver":"7.10.0",
    "wof:lang":[
        "rum"
    ],
    "wof:name":"Cindia",
    "wof:placetype":"neighbourhood"
},
  "geometry": {"coordinates":[26.391907,46.914627],"type":"Point"}
}