{
  "type": "Feature",
  "properties": {
    "gn:admin1_code":"30",
    "gn:admin2_code":"133615.0",
    "gn:asciiname":"Priseaca",
    "gn:cc2":"RO",
    "gn:country_code":"RO",
    "gn:dem":186,
    "gn:feature_class":"P",
    "gn:feature_code":"PPL",
    "gn:name":"Priseaca",
    "gn:population":399,
    "gn:timezone":"Europe/Bucharest",
    "iso:country":"RO",
    "name:und_x_variant":[
        "Preseaca",
        "Priseaca"
    ],
    "wof:name":"Priseaca",
    "wof:placetype":"locality",
    "wof:population":399
},
  "geometry": {"coordinates":[26.24608,45.10443],"type":"Point"}
}