{
  "type": "Feature",
  "properties": {
    "gn:admin1_code":"30",
    "gn:admin2_code":"133615.0",
    "gn:asciiname":"Priseaca",
    "gn:cc2":"RO",
    "gn:country_code":"RO",
    "gn:dem":186,
    "gn:feature_class":"P",
    "gn:feature_code":"PPL",
    "gn:name":"Priseaca",
    "gn:population":399,
    "gn:timezone":"Europe/Bucharest",
    "iso:country":"RO",
    "name:ceb_x_preferred":[
        "Comuna Priseaca"
    ],
    "name:ita_x_preferred":[
        "Priseaca"
    ],
    "name:msa_x_preferred":[
        "Priseaca"
    ],
    "name:nld_x_preferred":[
        "Priseaca"
    ],
    "name:por_x_preferred":[
        "Priseaca"
    ],
    "name:ron_x_preferred":[
        "Comuna Priseaca"
    ],
    "name:srp_x_preferred":[
        "\u041e\u043f\u0448\u0442\u0438\u043d\u0430 \u041f\u0440\u0438\u0441\u0435\u0430\u043a\u0430"
    ],
    "name:ukr_x_preferred":[
        "\u041f\u0440\u0456\u0441\u044f\u043a\u0430"
    ],
    "name:und_x_variant":[
        "Preseaca",
        "Priseaca"
    ],
    "name:vie_x_preferred":[
        "Priseaca"
    ],
    "name:vol_x_preferred":[
        "Priseaca"
    ],
    "name:zho_x_preferred":[
        "\u666e\u91cc\u585e\u4e9e\u5361\u9109"
    ],
    "wof:name":"Priseaca",
    "wof:placetype":"locality",
    "wof:population":399
},
  "geometry": {"coordinates":[26.24608,45.10443],"type":"Point"}
}