{
  "type": "Feature",
  "properties": {
    "gn:admin1_code":"26",
    "gn:admin2_code":"113233.0",
    "gn:asciiname":"Mijarca",
    "gn:country_code":"RO",
    "gn:dem":330,
    "gn:feature_class":"P",
    "gn:feature_code":"PPL",
    "gn:name":"Mijarca",
    "gn:population":90,
    "gn:timezone":"Europe/Bucharest",
    "iso:country":"RO",
    "wof:name":"Mijarca",
    "wof:placetype":"locality",
    "wof:population":90
},
  "geometry": {"coordinates":[22.90272,44.57284],"type":"Point"}
}