{
  "type": "Feature",
  "properties": {
    "gn:admin1_code":"19",
    "gn:admin2_code":"79157.0",
    "gn:asciiname":"Calaparu",
    "gn:country_code":"RO",
    "gn:dem":141,
    "gn:feature_class":"P",
    "gn:feature_code":"PPL",
    "gn:name":"Calap\u0103ru",
    "gn:population":661,
    "gn:timezone":"Europe/Bucharest",
    "iso:country":"RO",
    "name:und_x_variant":[
        "Calap\u0103ru de Jos"
    ],
    "wof:name":"Calaparu",
    "wof:placetype":"locality",
    "wof:population":661
},
  "geometry": {"coordinates":[23.33333,44.68333],"type":"Point"}
}