{
  "type": "Feature",
  "properties": {
    "gn:admin1_code":"21",
    "gn:admin2_code":"90878.0",
    "gn:asciiname":"Clopotiva",
    "gn:country_code":"RO",
    "gn:dem":499,
    "gn:feature_class":"P",
    "gn:feature_code":"PPL",
    "gn:name":"Clopotiva",
    "gn:population":888,
    "gn:timezone":"Europe/Bucharest",
    "iso:country":"RO",
    "name:hun_x_preferred":[
        "Klopotiva"
    ],
    "wof:name":"Clopotiva",
    "wof:placetype":"locality",
    "wof:population":888
},
  "geometry": {"coordinates":[22.82239,45.49772],"type":"Point"}
}