{
  "type": "Feature",
  "properties": {
    "gn:admin1_code":"01",
    "gn:admin2_code":"8425.0",
    "gn:asciiname":"Ficaresti",
    "gn:country_code":"RO",
    "gn:dem":920,
    "gn:feature_class":"P",
    "gn:feature_code":"PPL",
    "gn:name":"Fic\u0103re\u0219ti",
    "gn:population":62,
    "gn:timezone":"Europe/Bucharest",
    "iso:country":"RO",
    "wof:name":"Ficaresti",
    "wof:placetype":"locality",
    "wof:population":62
},
  "geometry": {"coordinates":[22.96193,46.38356],"type":"Point"}
}