{
  "type": "Feature",
  "properties": {
    "gn:admin1_code":"35",
    "gn:admin2_code":"151905.0",
    "gn:asciiname":"Spanesti",
    "gn:cc2":"RO",
    "gn:country_code":"RO",
    "gn:dem":99,
    "gn:feature_class":"P",
    "gn:feature_code":"PPL",
    "gn:name":"Sp\u00e2ne\u015fti",
    "gn:population":0,
    "gn:timezone":"Europe/Bucharest",
    "iso:country":"RO",
    "name:und_x_variant":[
        "Sp\u00eene\u015fti",
        "Sp\u00e2ne\u015fti"
    ],
    "wof:name":"Spanesti",
    "wof:placetype":"locality"
},
  "geometry": {"coordinates":[25.56667,44.26667],"type":"Point"}
}