{
  "type": "Feature",
  "properties": {
    "gn:admin1_code":"29",
    "gn:admin2_code":"126326.0",
    "gn:asciiname":"Milcoveni",
    "gn:country_code":"RO",
    "gn:dem":149,
    "gn:feature_class":"P",
    "gn:feature_code":"PPL",
    "gn:name":"Milcoveni",
    "gn:population":592,
    "gn:timezone":"Europe/Bucharest",
    "iso:country":"RO",
    "wof:name":"Milcoveni",
    "wof:placetype":"locality",
    "wof:population":592
},
  "geometry": {"coordinates":[24.72289,44.42609],"type":"Point"}
}