{
  "type": "Feature",
  "properties": {
    "gn:admin1_code":"22",
    "gn:admin2_code":"105026.0",
    "gn:asciiname":"Sinestii Vechi",
    "gn:country_code":"RO",
    "gn:dem":67,
    "gn:feature_class":"P",
    "gn:feature_code":"PPL",
    "gn:name":"Sine\u015ftii Vechi",
    "gn:population":0,
    "gn:timezone":"Europe/Bucharest",
    "iso:country":"RO",
    "wof:lang_x_official":[
        "ron"
    ],
    "wof:lang_x_spoken":[
        "ron"
    ],
    "wof:name":"Sinestii Vechi",
    "wof:placetype":"locality"
},
  "geometry": {"coordinates":[26.36667,44.56667],"type":"Point"}
}