{
  "type": "Feature",
  "properties": {
    "gn:admin1_code":"11",
    "gn:admin2_code":"48771.0",
    "gn:asciiname":"Potarnichesti",
    "gn:cc2":"RO",
    "gn:country_code":"RO",
    "gn:dem":145,
    "gn:feature_class":"P",
    "gn:feature_code":"PPL",
    "gn:name":"Pot\u00e2rniche\u015fti",
    "gn:population":0,
    "gn:timezone":"Europe/Bucharest",
    "iso:country":"RO",
    "name:und_x_variant":[
        "Pot\u00e2rniche\u015fti",
        "Pot\u00eerniche\u015fti"
    ],
    "wof:name":"Potarnichesti",
    "wof:placetype":"locality"
},
  "geometry": {"coordinates":[26.85,45.21667],"type":"Point"}
}