{
  "type": "Feature",
  "properties": {
    "gn:admin1_code":"41",
    "gn:admin2_code":"105259.0",
    "gn:asciiname":"Cetatea Veche",
    "gn:cc2":"RO",
    "gn:country_code":"RO",
    "gn:dem":33,
    "gn:feature_class":"P",
    "gn:feature_code":"PPL",
    "gn:name":"Cetatea Veche",
    "gn:population":875,
    "gn:timezone":"Europe/Bucharest",
    "iso:country":"RO",
    "name:und_x_variant":[
        "Tatina",
        "Cetatea Veche"
    ],
    "wof:name":"Cetatea Veche",
    "wof:placetype":"locality",
    "wof:population":875
},
  "geometry": {"coordinates":[26.76592,44.13401],"type":"Point"}
}