{
  "type": "Feature",
  "properties": {
    "gn:admin1_code":"30",
    "gn:admin2_code":"130614.0",
    "gn:asciiname":"Moara Noua",
    "gn:country_code":"RO",
    "gn:dem":137,
    "gn:feature_class":"P",
    "gn:feature_code":"PPL",
    "gn:name":"Moara Nou\u0103",
    "gn:population":859,
    "gn:timezone":"Europe/Bucharest",
    "iso:country":"RO",
    "wof:name":"Moara Noua",
    "wof:placetype":"locality",
    "wof:population":859
},
  "geometry": {"coordinates":[26.10857,44.94936],"type":"Point"}
}