{
  "type": "Feature",
  "properties": {
    "gn:admin1_code":"03",
    "gn:admin2_code":"14085.0",
    "gn:asciiname":"Grosi",
    "gn:cc2":"RO",
    "gn:country_code":"RO",
    "gn:dem":439,
    "gn:feature_class":"P",
    "gn:feature_code":"PPL",
    "gn:name":"Gro\u0219i",
    "gn:population":460,
    "gn:timezone":"Europe/Bucharest",
    "iso:country":"RO",
    "name:und_x_variant":[
        "Grosii",
        "Gro\u015fi"
    ],
    "wof:name":"Grosi",
    "wof:placetype":"locality",
    "wof:population":460
},
  "geometry": {"coordinates":[24.68726,44.87181],"type":"Point"}
}