{
  "type": "Feature",
  "properties": {
    "gn:admin1_code":"43",
    "gn:admin2_code":"104546.0",
    "gn:asciiname":"Cocioc",
    "gn:country_code":"RO",
    "gn:dem":105,
    "gn:feature_class":"P",
    "gn:feature_code":"PPL",
    "gn:name":"Cocioc",
    "gn:population":0,
    "gn:timezone":"Europe/Bucharest",
    "iso:country":"RO",
    "name:por_x_preferred":[
        "Rio Cocioc"
    ],
    "wof:lang_x_official":[
        "ron"
    ],
    "wof:lang_x_spoken":[
        "ron"
    ],
    "wof:name":"Cocioc",
    "wof:placetype":"locality"
},
  "geometry": {"coordinates":[26.03333,44.66667],"type":"Point"}
}