{
  "type": "Feature",
  "properties": {
    "gn:admin1_code":"03",
    "gn:admin2_code":"17496.0",
    "gn:asciiname":"Lazaresti",
    "gn:cc2":"RO",
    "gn:country_code":"RO",
    "gn:dem":381,
    "gn:feature_class":"P",
    "gn:feature_code":"PPL",
    "gn:name":"L\u0103z\u0103re\u0219ti",
    "gn:population":208,
    "gn:timezone":"Europe/Bucharest",
    "iso:country":"RO",
    "name:und_x_variant":[
        "L\u0103z\u0103re\u015ftii",
        "L\u0103z\u0103re\u015fti"
    ],
    "wof:name":"Lazaresti",
    "wof:placetype":"locality",
    "wof:population":208
},
  "geometry": {"coordinates":[24.75676,44.82697],"type":"Point"}
}