{
  "type": "Feature",
  "properties": {
    "gn:admin1_code":"39",
    "gn:admin2_code":"170346.0",
    "gn:asciiname":"Strachinesti",
    "gn:country_code":"RO",
    "gn:dem":276,
    "gn:feature_class":"P",
    "gn:feature_code":"PPL",
    "gn:name":"Str\u0103chine\u0219ti",
    "gn:population":35,
    "gn:timezone":"Europe/Bucharest",
    "iso:country":"RO",
    "wof:name":"Strachinesti",
    "wof:placetype":"locality",
    "wof:population":35
},
  "geometry": {"coordinates":[23.83767000000001,44.90499000000001],"type":"Point"}
}