{
  "type": "Feature",
  "properties": {
    "gn:admin1_code":"28",
    "gn:admin2_code":"121297",
    "gn:asciiname":"Barnadu",
    "gn:country_code":"RO",
    "gn:dem":1044,
    "gn:feature_class":"P",
    "gn:feature_code":"PPL",
    "gn:name":"B\u00e2rnadu",
    "gn:population":105,
    "gn:timezone":"Europe/Bucharest",
    "iso:country":"RO",
    "wof:name":"Barnadu",
    "wof:placetype":"locality",
    "wof:population":105
},
  "geometry": {"coordinates":[25.82321,46.83276],"type":"Point"}
}