{
  "type": "Feature",
  "properties": {
    "gn:admin1_code":"28",
    "gn:admin2_code":"123013.0",
    "gn:asciiname":"Gorovei",
    "gn:country_code":"RO",
    "gn:dem":173,
    "gn:feature_class":"P",
    "gn:feature_code":"PPL",
    "gn:name":"Gorovei",
    "gn:population":0,
    "gn:timezone":"Europe/Bucharest",
    "iso:country":"RO",
    "name:und_x_variant":[
        "Icu\u015fe\u015fti Gorovei",
        "Gorovei"
    ],
    "wof:name":"Gorovei",
    "wof:placetype":"locality"
},
  "geometry": {"coordinates":[26.93333,46.81667],"type":"Point"}
}