{
  "type": "Feature",
  "properties": {
    "gn:admin1_code":"27",
    "gn:admin2_code":"116288.0",
    "gn:asciiname":"Ciba",
    "gn:cc2":"RO",
    "gn:country_code":"RO",
    "gn:dem":313,
    "gn:feature_class":"P",
    "gn:feature_code":"PPL",
    "gn:name":"Ciba",
    "gn:population":0,
    "gn:timezone":"Europe/Bucharest",
    "iso:country":"RO",
    "name:ceb_x_preferred":[
        "Ciba"
    ],
    "name:deu_x_preferred":[
        "Ciba"
    ],
    "name:epo_x_preferred":[
        "Ciba"
    ],
    "name:hun_x_preferred":[
        "Ciba"
    ],
    "name:ron_x_preferred":[
        "Ciba"
    ],
    "name:swe_x_preferred":[
        "Ciba"
    ],
    "name:und_x_variant":[
        "Csiba"
    ],
    "wof:name":"Ciba",
    "wof:placetype":"locality"
},
  "geometry": {"coordinates":[24.56806,46.47923],"type":"Point"}
}