{
  "type": "Feature",
  "properties": {
    "gn:admin1_code":"03",
    "gn:admin2_code":"19999.0",
    "gn:asciiname":"Coteasca",
    "gn:cc2":"RO",
    "gn:country_code":"RO",
    "gn:dem":412,
    "gn:feature_class":"P",
    "gn:feature_code":"PPL",
    "gn:name":"Coteasca",
    "gn:population":259,
    "gn:timezone":"Europe/Bucharest",
    "iso:country":"RO",
    "name:und_x_variant":[
        "C\u0103teasca",
        "C\u0103teasca-Orislop",
        "Coteasca"
    ],
    "wof:name":"Coteasca",
    "wof:placetype":"locality",
    "wof:population":259
},
  "geometry": {"coordinates":[24.93907,45.13036],"type":"Point"}
}