{
  "type": "Feature",
  "properties": {
    "gn:admin1_code":"29",
    "gn:admin2_code":"128221.0",
    "gn:asciiname":"Schitu din Deal",
    "gn:cc2":"RO",
    "gn:country_code":"RO",
    "gn:dem":163,
    "gn:feature_class":"P",
    "gn:feature_code":"PPL",
    "gn:name":"Schitu din Deal",
    "gn:population":352,
    "gn:timezone":"Europe/Bucharest",
    "iso:country":"RO",
    "name:und_x_variant":[
        "Schitul-din Deal",
        "Schitu din Deal"
    ],
    "wof:name":"Schitu din Deal",
    "wof:placetype":"locality",
    "wof:population":352
},
  "geometry": {"coordinates":[24.2302,44.50236],"type":"Point"}
}