{
  "type": "Feature",
  "properties": {
    "gn:admin1_code":"17",
    "gn:admin2_code":"73102.0",
    "gn:asciiname":"Muierusu",
    "gn:cc2":"RO",
    "gn:country_code":"RO",
    "gn:dem":167,
    "gn:feature_class":"P",
    "gn:feature_code":"PPL",
    "gn:name":"Muieru\u0219u",
    "gn:population":83,
    "gn:timezone":"Europe/Bucharest",
    "iso:country":"RO",
    "name:und_x_variant":[
        "Muierusul",
        "Muieru\u015fu"
    ],
    "wof:name":"Muierusu",
    "wof:placetype":"locality",
    "wof:population":83
},
  "geometry": {"coordinates":[23.69134,44.56543],"type":"Point"}
}