{
  "type": "Feature",
  "properties": {
    "gn:admin1_code":"23",
    "gn:admin2_code":"97241.0",
    "gn:asciiname":"Valea Satului",
    "gn:country_code":"RO",
    "gn:dem":223,
    "gn:feature_class":"P",
    "gn:feature_code":"PPL",
    "gn:name":"Valea Satului",
    "gn:population":520,
    "gn:timezone":"Europe/Bucharest",
    "iso:country":"RO",
    "wof:name":"Valea Satului",
    "wof:placetype":"locality",
    "wof:population":520
},
  "geometry": {"coordinates":[27.5482,46.95346],"type":"Point"}
}