{
  "type": "Feature",
  "properties": {
    "gn:admin1_code":"26",
    "gn:admin2_code":"110232",
    "gn:asciiname":"Bucura",
    "gn:country_code":"RO",
    "gn:dem":90,
    "gn:feature_class":"P",
    "gn:feature_code":"PPL",
    "gn:name":"Bucura",
    "gn:population":422,
    "gn:timezone":"Europe/Bucharest",
    "iso:country":"RO",
    "wof:name":"Bucura",
    "wof:placetype":"locality",
    "wof:population":422
},
  "geometry": {"coordinates":[22.86699,44.39953],"type":"Point"}
}