{
  "type": "Feature",
  "properties": {
    "gn:admin1_code":"27",
    "gn:admin2_code":"119974.0",
    "gn:asciiname":"Valea Padurii",
    "gn:country_code":"RO",
    "gn:dem":322,
    "gn:feature_class":"P",
    "gn:feature_code":"PPL",
    "gn:name":"Valea P\u0103durii",
    "gn:population":233,
    "gn:timezone":"Europe/Bucharest",
    "iso:country":"RO",
    "wof:name":"Valea Padurii",
    "wof:placetype":"locality",
    "wof:population":233
},
  "geometry": {"coordinates":[24.0537,46.61969000000001],"type":"Point"}
}