{
  "type": "Feature",
  "properties": {
    "gn:admin1_code":"40",
    "gn:admin2_code":"178475.0",
    "gn:asciiname":"Dupa Magura",
    "gn:country_code":"RO",
    "gn:dem":679,
    "gn:feature_class":"P",
    "gn:feature_code":"PPL",
    "gn:name":"Dup\u0103 M\u0103gura",
    "gn:population":113,
    "gn:timezone":"Europe/Bucharest",
    "iso:country":"RO",
    "wof:name":"Dupa Magura",
    "wof:placetype":"locality",
    "wof:population":113
},
  "geometry": {"coordinates":[26.73801,45.62826],"type":"Point"}
}