{
  "type": "Feature",
  "properties": {
    "gn:admin1_code":"36",
    "gn:admin2_code":"156669.0",
    "gn:asciiname":"Rovinita Mare",
    "gn:cc2":"RO",
    "gn:country_code":"RO",
    "gn:dem":96,
    "gn:feature_class":"P",
    "gn:feature_code":"PPL",
    "gn:name":"Rovini\u021ba Mare",
    "gn:population":402,
    "gn:timezone":"Europe/Bucharest",
    "iso:country":"RO",
    "name:und_x_variant":[
        "Omor",
        "Rovini\u0163a Mare"
    ],
    "wof:name":"Rovinita Mare",
    "wof:placetype":"locality",
    "wof:population":402
},
  "geometry": {"coordinates":[21.29539,45.37709],"type":"Point"}
}