{
  "type": "Feature",
  "properties": {
    "gn:admin1_code":"09",
    "gn:admin2_code":"41738.0",
    "gn:asciiname":"Savastreni",
    "gn:country_code":"RO",
    "gn:dem":502,
    "gn:feature_class":"P",
    "gn:feature_code":"PPL",
    "gn:name":"S\u0103v\u0103streni",
    "gn:population":203,
    "gn:timezone":"Europe/Bucharest",
    "iso:country":"RO",
    "wof:name":"Savastreni",
    "wof:placetype":"locality",
    "wof:population":203
},
  "geometry": {"coordinates":[24.9447,45.76285],"type":"Point"}
}