{
  "type": "Feature",
  "properties": {
    "gn:admin1_code":"21",
    "gn:admin2_code":"89026.0",
    "gn:asciiname":"Vadu Dobrii",
    "gn:cc2":"RO",
    "gn:country_code":"RO",
    "gn:dem":1063,
    "gn:feature_class":"P",
    "gn:feature_code":"PPL",
    "gn:name":"Vadu Dobrii",
    "gn:population":65,
    "gn:timezone":"Europe/Bucharest",
    "iso:country":"RO",
    "name:und_x_variant":[
        "Vadul-Dobrei",
        "Vadu Dobrii",
        "Vadu Dobrei"
    ],
    "wof:name":"Vadu Dobrii",
    "wof:placetype":"locality",
    "wof:population":65
},
  "geometry": {"coordinates":[22.54521,45.69187],"type":"Point"}
}