{
  "type": "Feature",
  "properties": {
    "gn:admin1_code":"16",
    "gn:admin2_code":"65501.0",
    "gn:asciiname":"Udresti",
    "gn:country_code":"RO",
    "gn:dem":258,
    "gn:feature_class":"P",
    "gn:feature_code":"PPL",
    "gn:name":"Udre\u0219ti",
    "gn:population":213,
    "gn:timezone":"Europe/Bucharest",
    "iso:country":"RO",
    "wof:name":"Udresti",
    "wof:placetype":"locality",
    "wof:population":213
},
  "geometry": {"coordinates":[25.47524,44.88665],"type":"Point"}
}