{
  "type": "Feature",
  "properties": {
    "gn:admin1_code":"26",
    "gn:admin2_code":"112263.0",
    "gn:asciiname":"Dalbocita",
    "gn:cc2":"RO",
    "gn:country_code":"RO",
    "gn:dem":422,
    "gn:feature_class":"P",
    "gn:feature_code":"PPL",
    "gn:name":"D\u00e2lboci\u0163a",
    "gn:population":0,
    "gn:timezone":"Europe/Bucharest",
    "iso:country":"RO",
    "name:und_x_variant":[
        "D\u00e2lbocita",
        "Dalbo\u010dica",
        "D\u00eelboci\u0163a"
    ],
    "wof:name":"Dalbocita",
    "wof:placetype":"locality"
},
  "geometry": {"coordinates":[22.75,44.83333],"type":"Point"}
}