{
  "type": "Feature",
  "properties": {
    "gn:country":"RO",
    "gn:fcode":"PPLA2",
    "gn:population":3935,
    "iso:country":"RO",
    "name:ceb_x_preferred":[
        "Ma\u0219loc"
    ],
    "name:deu_x_preferred":[
        "Ma\u0219loc"
    ],
    "name:eng_x_preferred":[
        "Ma\u0219loc"
    ],
    "name:epo_x_preferred":[
        "Ma\u0219loc"
    ],
    "name:fra_x_preferred":[
        "Ma\u0219loc"
    ],
    "name:hun_x_preferred":[
        "M\u00e1slak"
    ],
    "name:ita_x_preferred":[
        "Ma\u0219loc"
    ],
    "name:nld_x_preferred":[
        "Ma\u0219loc"
    ],
    "name:por_x_preferred":[
        "Ma\u0219loc"
    ],
    "name:ron_x_preferred":[
        "Ma\u0219loc"
    ],
    "name:srp_x_preferred":[
        "\u041c\u0430\u0448\u043b\u043e\u043a"
    ],
    "name:ukr_x_preferred":[
        "\u041c\u0430\u0448\u043b\u043e\u043a"
    ],
    "name:und_x_variant":[
        "Blumental"
    ],
    "name:vie_x_preferred":[
        "Masloc"
    ],
    "name:vol_x_preferred":[
        "Ma\u0219loc"
    ],
    "qs_pg:aaroncc":"RO",
    "qs_pg:gn_country":"RO",
    "qs_pg:gn_fcode":"PPLA2",
    "qs_pg:gn_pop":3935,
    "qs_pg:name":"Ma\u015floc",
    "qs_pg:photos_9r":0,
    "qs_pg:photos_sr":0,
    "qs_pg:pop_sr":4,
    "qs_pg:qs_pg_placetype":"locality",
    "wof:name":"Ma\u015floc",
    "wof:placetype":"locality",
    "wof:population":3935
},
  "geometry": {"coordinates":[21.44972,45.99806],"type":"Point"}
}