{
  "type": "Feature",
  "properties": {
    "gn:admin1_code":"27",
    "gn:admin2_code":"119206.0",
    "gn:asciiname":"Cloasterf",
    "gn:country_code":"RO",
    "gn:dem":463,
    "gn:feature_class":"P",
    "gn:feature_code":"PPL",
    "gn:name":"Cloa\u0219terf",
    "gn:population":187,
    "gn:timezone":"Europe/Bucharest",
    "iso:country":"RO",
    "wof:name":"Cloasterf",
    "wof:placetype":"locality",
    "wof:population":187
},
  "geometry": {"coordinates":[24.9972,46.14655],"type":"Point"}
}