{
  "type": "Feature",
  "properties": {
    "gn:country":"RO",
    "gn:fcode":"PPLX",
    "gn:population":0,
    "iso:country":"RO",
    "name:ceb_x_preferred":[
        "Vii\u0219oara"
    ],
    "name:deu_x_preferred":[
        "Vii\u0219oara"
    ],
    "name:epo_x_preferred":[
        "Vii\u0219oara"
    ],
    "name:eus_x_preferred":[
        "Vii\u0219oara"
    ],
    "name:fra_x_preferred":[
        "Vii\u0219oara"
    ],
    "name:hun_x_preferred":[
        "Vii\u0219oara"
    ],
    "name:ita_x_preferred":[
        "Vii\u0219oara"
    ],
    "name:nld_x_preferred":[
        "Vii\u0219oara"
    ],
    "name:ron_x_preferred":[
        "Vii\u0219oara"
    ],
    "name:rus_x_preferred":[
        "\u0412\u0438\u0438\u0448\u043e\u0430\u0440\u0430"
    ],
    "name:srp_x_preferred":[
        "\u0412\u0438\u0438\u0448\u043e\u0430\u0440\u0430"
    ],
    "name:ukr_x_preferred":[
        "\u0412\u0456\u0457\u0448\u043e\u0430\u0440\u0430"
    ],
    "name:vol_x_preferred":[
        "Vii\u015foara"
    ],
    "qs_pg:aaroncc":"RO",
    "qs_pg:gn_country":"RO",
    "qs_pg:gn_fcode":"PPLX",
    "qs_pg:gn_pop":0,
    "qs_pg:name":"Vii\u0219oara",
    "qs_pg:name_adm0":"Rom\u00e2nia",
    "qs_pg:name_adm1":"Vaslui",
    "qs_pg:photos":2,
    "qs_pg:photos_1k":1,
    "qs_pg:photos_9k":1,
    "qs_pg:photos_9r":1,
    "qs_pg:photos_all":2,
    "qs_pg:photos_sr":1,
    "qs_pg:pop_sr":0,
    "qs_pg:qs_pg_placetype":"neighbourhood",
    "qs_pg:qs_pg_placetype_gp":"Suburb",
    "qs_pg:woe_adm0":23424933,
    "woe:adm0_id":23424933,
    "woe:name_adm0":"Rom\u00e2nia",
    "woe:name_adm1":"Vaslui",
    "woe:placetype":"Suburb",
    "wof:name":"Vii\u0219oara",
    "wof:placetype":"neighbourhood",
    "wof:population":592
},
  "geometry": {"coordinates":[27.73333,46.63333],"type":"Point"}
}