{
  "type": "Feature",
  "properties": {
    "gn:admin1_code":"17",
    "gn:admin2_code":"71340.0",
    "gn:asciiname":"Fratila",
    "gn:country_code":"RO",
    "gn:dem":285,
    "gn:feature_class":"P",
    "gn:feature_code":"PPL",
    "gn:name":"Fr\u0103\u021bila",
    "gn:population":119,
    "gn:timezone":"Europe/Bucharest",
    "iso:country":"RO",
    "wof:name":"Fratila",
    "wof:placetype":"locality",
    "wof:population":119
},
  "geometry": {"coordinates":[23.85322,44.62449],"type":"Point"}
}