{
  "type": "Feature",
  "properties": {
    "gn:admin1_code":"18",
    "gn:admin2_code":"76996.0",
    "gn:asciiname":"Vames",
    "gn:cc2":"RO",
    "gn:country_code":"RO",
    "gn:dem":23,
    "gn:feature_class":"P",
    "gn:feature_code":"PPL",
    "gn:name":"Vame\u0219",
    "gn:population":500,
    "gn:timezone":"Europe/Bucharest",
    "iso:country":"RO",
    "name:und_x_variant":[
        "Vame\u015fu",
        "Vame\u015f"
    ],
    "wof:name":"Vames",
    "wof:placetype":"locality",
    "wof:population":500
},
  "geometry": {"coordinates":[27.70728,45.53408],"type":"Point"}
}