{
  "type": "Feature",
  "properties": {
    "gn:admin1_code":"07",
    "gn:admin2_code":"38731.0",
    "gn:asciiname":"Movila Rupta",
    "gn:country_code":"RO",
    "gn:dem":118,
    "gn:feature_class":"P",
    "gn:feature_code":"PPL",
    "gn:name":"Movila Rupt\u0103",
    "gn:population":0,
    "gn:timezone":"Europe/Bucharest",
    "iso:country":"RO",
    "wof:name":"Movila Rupta",
    "wof:placetype":"locality"
},
  "geometry": {"coordinates":[27.13082,47.92005],"type":"Point"}
}