{
  "type": "Feature",
  "properties": {
    "gn:admin1_code":"04",
    "gn:admin2_code":"24427.0",
    "gn:asciiname":"Itcani",
    "gn:cc2":"RO",
    "gn:country_code":"RO",
    "gn:dem":243,
    "gn:feature_class":"P",
    "gn:feature_code":"PPL",
    "gn:name":"I\u021bcani",
    "gn:population":320,
    "gn:timezone":"Europe/Bucharest",
    "iso:country":"RO",
    "name:und_x_variant":[
        "Itcan",
        "I\u0163cani"
    ],
    "wof:name":"Itcani",
    "wof:placetype":"locality",
    "wof:population":320
},
  "geometry": {"coordinates":[27.25817,46.67791],"type":"Point"}
}