{
  "type": "Feature",
  "properties": {
    "gn:admin1_code":"39",
    "gn:admin2_code":"173374",
    "gn:asciiname":"Barsoiu",
    "gn:cc2":"RO",
    "gn:country_code":"RO",
    "gn:dem":297,
    "gn:feature_class":"P",
    "gn:feature_code":"PPL",
    "gn:name":"B\u00e2rsoiu",
    "gn:population":707,
    "gn:timezone":"Europe/Bucharest",
    "iso:country":"RO",
    "name:und_x_variant":[
        "Ni\u0163ule\u015fti",
        "B\u00eersoiu"
    ],
    "wof:name":"Barsoiu",
    "wof:placetype":"locality",
    "wof:population":707
},
  "geometry": {"coordinates":[24.34265,44.88184],"type":"Point"}
}