{
  "type": "Feature",
  "properties": {
    "gn:admin1_code":"01",
    "gn:admin2_code":"4767.0",
    "gn:asciiname":"Preluca",
    "gn:country_code":"RO",
    "gn:dem":1107,
    "gn:feature_class":"P",
    "gn:feature_code":"PPL",
    "gn:name":"Preluca",
    "gn:population":95,
    "gn:timezone":"Europe/Bucharest",
    "iso:country":"RO",
    "wof:name":"Preluca",
    "wof:placetype":"locality",
    "wof:population":95
},
  "geometry": {"coordinates":[22.97681,46.51023],"type":"Point"}
}