{
  "type": "Feature",
  "properties": {
    "gn:admin1_code":"28",
    "gn:admin2_code":"123175.0",
    "gn:asciiname":"Neacsa",
    "gn:country_code":"RO",
    "gn:dem":319,
    "gn:feature_class":"P",
    "gn:feature_code":"PPL",
    "gn:name":"Neac\u015fa",
    "gn:population":0,
    "gn:timezone":"Europe/Bucharest",
    "iso:country":"RO",
    "wof:name":"Neacsa",
    "wof:placetype":"locality"
},
  "geometry": {"coordinates":[26.65,46.88333],"type":"Point"}
}