{
  "type": "Feature",
  "properties": {
    "gn:admin1_code":"26",
    "gn:admin2_code":"112129.0",
    "gn:asciiname":"Valea Petrii",
    "gn:cc2":"RO",
    "gn:country_code":"RO",
    "gn:dem":274,
    "gn:feature_class":"P",
    "gn:feature_code":"PPL",
    "gn:name":"Valea Petrii",
    "gn:population":0,
    "gn:timezone":"Europe/Bucharest",
    "iso:country":"RO",
    "name:und_x_variant":[
        "Valea Petri",
        "Valea Petrii"
    ],
    "wof:lang_x_official":[
        "ron"
    ],
    "wof:lang_x_spoken":[
        "ron"
    ],
    "wof:name":"Valea Petrii",
    "wof:placetype":"locality"
},
  "geometry": {"coordinates":[22.88333,44.66667],"type":"Point"}
}