{
  "type": "Feature",
  "properties": {
    "gn:admin1_code":"23",
    "gn:admin2_code":"97517",
    "gn:asciiname":"Bogdanesti",
    "gn:country_code":"RO",
    "gn:dem":111,
    "gn:feature_class":"P",
    "gn:feature_code":"PPL",
    "gn:name":"Bogd\u0103ne\u0219ti",
    "gn:population":812,
    "gn:timezone":"Europe/Bucharest",
    "iso:country":"RO",
    "wof:name":"Bogdanesti",
    "wof:placetype":"locality",
    "wof:population":812
},
  "geometry": {"coordinates":[27.4365,47.11572],"type":"Point"}
}