{
  "type": "Feature",
  "properties": {
    "gn:admin1_code":"31",
    "gn:admin2_code":"139982.0",
    "gn:asciiname":"Taudu",
    "gn:country_code":"RO",
    "gn:dem":390,
    "gn:feature_class":"P",
    "gn:feature_code":"PPL",
    "gn:name":"\u021a\u0103udu",
    "gn:population":266,
    "gn:timezone":"Europe/Bucharest",
    "iso:country":"RO",
    "wof:name":"Taudu",
    "wof:placetype":"locality",
    "wof:population":266
},
  "geometry": {"coordinates":[23.05282,46.98314],"type":"Point"}
}