{
  "type": "Feature",
  "properties": {
    "gn:admin1_code":"29",
    "gn:admin2_code":"126102",
    "gn:asciiname":"Bondrea",
    "gn:country_code":"RO",
    "gn:dem":115,
    "gn:feature_class":"P",
    "gn:feature_code":"PPL",
    "gn:name":"Bondrea",
    "gn:population":0,
    "gn:timezone":"Europe/Bucharest",
    "iso:country":"RO",
    "wof:name":"Bondrea",
    "wof:placetype":"locality"
},
  "geometry": {"coordinates":[24.22992,44.19224000000001],"type":"Point"}
}