{
  "type": "Feature",
  "properties": {
    "gn:admin1_code":"03",
    "gn:admin2_code":"14165.0",
    "gn:asciiname":"Stejari",
    "gn:cc2":"RO",
    "gn:country_code":"RO",
    "gn:dem":363,
    "gn:feature_class":"P",
    "gn:feature_code":"PPL",
    "gn:name":"Stejari",
    "gn:population":190,
    "gn:timezone":"Europe/Bucharest",
    "iso:country":"RO",
    "name:und_x_variant":[
        "Valea Rea",
        "Stejari"
    ],
    "wof:name":"Stejari",
    "wof:placetype":"locality",
    "wof:population":190
},
  "geometry": {"coordinates":[24.7057,45.0386],"type":"Point"}
}