{
  "type": "Feature",
  "properties": {
    "gn:admin1_code":"03",
    "gn:admin2_code":"14165.0",
    "gn:asciiname":"Stejari",
    "gn:cc2":"RO",
    "gn:country_code":"RO",
    "gn:dem":363,
    "gn:feature_class":"P",
    "gn:feature_code":"PPL",
    "gn:name":"Stejari",
    "gn:population":190,
    "gn:timezone":"Europe/Bucharest",
    "iso:country":"RO",
    "name:ceb_x_preferred":[
        "Comuna Stejari"
    ],
    "name:ita_x_preferred":[
        "Stejari"
    ],
    "name:msa_x_preferred":[
        "Stejari"
    ],
    "name:nld_x_preferred":[
        "Stejari"
    ],
    "name:por_x_preferred":[
        "Stejari"
    ],
    "name:ron_x_preferred":[
        "Comuna Stejari"
    ],
    "name:srp_x_preferred":[
        "\u041e\u043f\u0448\u0442\u0438\u043d\u0430 \u0421\u0442\u0435\u0436\u0430\u0440\u0438"
    ],
    "name:ukr_x_preferred":[
        "\u0421\u0442\u0435\u0436\u0430\u0440\u0456"
    ],
    "name:und_x_variant":[
        "Valea Rea"
    ],
    "name:vie_x_preferred":[
        "Stejari"
    ],
    "name:vol_x_preferred":[
        "Stejari"
    ],
    "name:zho_x_preferred":[
        "\u65af\u6cf0\u624e\u91cc\u9109"
    ],
    "wof:name":"Stejari",
    "wof:placetype":"locality",
    "wof:population":190
},
  "geometry": {"coordinates":[24.7057,45.0386],"type":"Point"}
}