{
  "type": "Feature",
  "properties": {
    "gn:gn_country":"RO",
    "gn:gn_fcode":"PPL",
    "gn:gn_pop":0,
    "gn:population":682,
    "iso:country":"RO",
    "name:dut_x_preferred":[
        "Pe\u0219tera"
    ],
    "name:eng_x_preferred":[
        "Pe\u0219tera"
    ],
    "name:ger_x_preferred":[
        "Pe\u0219tera"
    ],
    "name:ita_x_preferred":[
        "Pe\u0219tera"
    ],
    "name:rum_x_preferred":[
        "Pe\u0219tera"
    ],
    "name:ukr_x_preferred":[
        "\u041f\u0435\u0448\u0442\u0435\u0440\u0430"
    ],
    "qs_pg:aaroncc":"RO",
    "qs_pg:gn_country":"RO",
    "qs_pg:gn_fcode":"PPL",
    "qs_pg:gn_pop":0,
    "qs_pg:name":"Pe\u0219tera",
    "qs_pg:name_adm0":"Rom\u00e2nia",
    "qs_pg:name_adm1":"Brasov",
    "qs_pg:photos":782,
    "qs_pg:photos_1k":158,
    "qs_pg:photos_9k":3,
    "qs_pg:photos_9r":6,
    "qs_pg:photos_all":782,
    "qs_pg:photos_sr":9,
    "qs_pg:pop_sr":0,
    "qs_pg:qs_pg_placetype":"locality",
    "qs_pg:qs_pg_placetype_gp":"Town",
    "qs_pg:woe_adm0":23424933,
    "woe:adm0_id":23424933,
    "woe:name_adm0":"Rom\u00e2nia",
    "woe:name_adm1":"Brasov",
    "woe:placetype":"Town",
    "wof:name":"Pe\u0219tera",
    "wof:placetype":"locality",
    "wof:population":682
},
  "geometry": {"coordinates":[25.28333,45.51667],"type":"Point"}
}