{
  "type": "Feature",
  "properties": {
    "gn:admin1_code":"35",
    "gn:admin2_code":"153277.0",
    "gn:asciiname":"Magureni",
    "gn:country_code":"RO",
    "gn:dem":98,
    "gn:feature_class":"P",
    "gn:feature_code":"PPL",
    "gn:name":"M\u0103gureni",
    "gn:population":0,
    "gn:timezone":"Europe/Bucharest",
    "iso:country":"RO",
    "wof:name":"Magureni",
    "wof:placetype":"locality"
},
  "geometry": {"coordinates":[24.91667,44.13333],"type":"Point"}
}