{
  "type": "Feature",
  "properties": {
    "gn:admin1_code":"19",
    "gn:admin2_code":"82733.0",
    "gn:asciiname":"Hotaroasa",
    "gn:cc2":"RO",
    "gn:country_code":"RO",
    "gn:dem":142,
    "gn:feature_class":"P",
    "gn:feature_code":"PPL",
    "gn:name":"Hot\u0103roasa",
    "gn:population":616,
    "gn:timezone":"Europe/Bucharest",
    "iso:country":"RO",
    "name:und_x_variant":[
        "Hot\u0103reasa",
        "Hot\u0103roasa"
    ],
    "wof:name":"Hotaroasa",
    "wof:placetype":"locality",
    "wof:population":616
},
  "geometry": {"coordinates":[23.28251,44.82303],"type":"Point"}
}