{
  "type": "Feature",
  "properties": {
    "gn:admin1_code":"25",
    "gn:admin2_code":"108712.0",
    "gn:asciiname":"Mogosesti",
    "gn:country_code":"RO",
    "gn:dem":156,
    "gn:feature_class":"P",
    "gn:feature_code":"PPL",
    "gn:name":"Mogo\u0219e\u0219ti",
    "gn:population":739,
    "gn:timezone":"Europe/Bucharest",
    "iso:country":"RO",
    "wof:name":"Mogosesti",
    "wof:placetype":"locality",
    "wof:population":739
},
  "geometry": {"coordinates":[23.39903,47.5816],"type":"Point"}
}