{
  "type": "Feature",
  "properties": {
    "gn:admin1_code":"16",
    "gn:admin2_code":"67835.0",
    "gn:asciiname":"Potocelu",
    "gn:cc2":"RO",
    "gn:country_code":"RO",
    "gn:dem":277,
    "gn:feature_class":"P",
    "gn:feature_code":"PPL",
    "gn:name":"Potocelu",
    "gn:population":886,
    "gn:timezone":"Europe/Bucharest",
    "iso:country":"RO",
    "name:und_x_variant":[
        "Rudari",
        "Rudari Lude\u015fti",
        "Potocelu"
    ],
    "wof:name":"Potocelu",
    "wof:placetype":"locality",
    "wof:population":886
},
  "geometry": {"coordinates":[25.24728,44.89215],"type":"Point"}
}