{
  "type": "Feature",
  "properties": {
    "gn:admin1_code":"03",
    "gn:admin2_code":"18858.0",
    "gn:asciiname":"Slobozia",
    "gn:country_code":"RO",
    "gn:dem":592,
    "gn:feature_class":"P",
    "gn:feature_code":"PPL",
    "gn:name":"Slobozia",
    "gn:population":580,
    "gn:timezone":"Europe/Bucharest",
    "iso:country":"RO",
    "wof:name":"Slobozia",
    "wof:placetype":"locality",
    "wof:population":580
},
  "geometry": {"coordinates":[25.18031,45.27491],"type":"Point"}
}