{
  "type": "Feature",
  "properties": {
    "gn:admin1_code":"03",
    "gn:admin2_code":"18858.0",
    "gn:asciiname":"Slobozia",
    "gn:country_code":"RO",
    "gn:dem":592,
    "gn:feature_class":"P",
    "gn:feature_code":"PPL",
    "gn:name":"Slobozia",
    "gn:population":580,
    "gn:timezone":"Europe/Bucharest",
    "iso:country":"RO",
    "name:ace_x_preferred":[
        "Slobozia"
    ],
    "name:ara_x_preferred":[
        "\u0633\u0644\u0648\u0628\u0648\u0632\u064a\u0627"
    ],
    "name:azb_x_preferred":[
        "\u0633\u0644\u0648\u0628\u0648\u0632\u06cc\u0627"
    ],
    "name:bel_x_preferred":[
        "\u0421\u043b\u0430\u0431\u0430\u0437\u0456\u044f"
    ],
    "name:bul_x_preferred":[
        "\u0421\u043b\u043e\u0431\u043e\u0437\u0438\u044f"
    ],
    "name:ceb_x_preferred":[
        "Municipiul Slobozia"
    ],
    "name:ces_x_preferred":[
        "Slobozia"
    ],
    "name:deu_x_preferred":[
        "Slobozia"
    ],
    "name:ell_x_preferred":[
        "\u03a3\u03bb\u03bf\u03bc\u03c0\u03bf\u03b6\u03af\u03b1"
    ],
    "name:epo_x_preferred":[
        "Slobozia"
    ],
    "name:est_x_preferred":[
        "Slobozia"
    ],
    "name:fas_x_preferred":[
        "\u0633\u0644\u0648\u0628\u0648\u0632\u06cc\u0627"
    ],
    "name:fra_x_preferred":[
        "Slobozia"
    ],
    "name:hun_x_preferred":[
        "Slobozia"
    ],
    "name:ind_x_preferred":[
        "Slobozia"
    ],
    "name:ita_x_preferred":[
        "Slobozia"
    ],
    "name:jpn_x_preferred":[
        "\u30b9\u30ed\u30dc\u30b8\u30a2"
    ],
    "name:kor_x_preferred":[
        "\uc2ac\ub85c\ubcf4\uc9c0\uc544"
    ],
    "name:lit_x_preferred":[
        "Slobozija"
    ],
    "name:min_x_preferred":[
        "Slobozia"
    ],
    "name:msa_x_preferred":[
        "Slobozia"
    ],
    "name:nld_x_preferred":[
        "Slobozia"
    ],
    "name:nno_x_preferred":[
        "Slobozia"
    ],
    "name:pnb_x_preferred":[
        "\u0633\u0644\u0648\u0628\u0648\u0632\u06cc\u0627"
    ],
    "name:pol_x_preferred":[
        "Slobozia"
    ],
    "name:por_x_preferred":[
        "Slobozia"
    ],
    "name:ron_x_preferred":[
        "Slobozia"
    ],
    "name:rus_x_preferred":[
        "\u0421\u043b\u043e\u0431\u043e\u0437\u0438\u044f"
    ],
    "name:slk_x_preferred":[
        "Slobozia"
    ],
    "name:spa_x_preferred":[
        "Slobozia"
    ],
    "name:srp_x_preferred":[
        "\u041e\u043f\u0448\u0442\u0438\u043d\u0430 \u0421\u043b\u043e\u0431\u043e\u0437\u0438\u0458\u0430"
    ],
    "name:swe_x_preferred":[
        "Slobozia"
    ],
    "name:tat_x_preferred":[
        "\u0421\u043b\u043e\u0431\u043e\u0437\u0435\u044f"
    ],
    "name:tgk_x_preferred":[
        "\u0421\u043b\u043e\u0431\u043e\u0437\u0438\u044f"
    ],
    "name:ukr_x_preferred":[
        "\u0421\u043b\u043e\u0431\u043e\u0437\u0456\u044f"
    ],
    "name:urd_x_preferred":[
        "\u0633\u0644\u0648\u0628\u0648\u0632\u06cc\u0627"
    ],
    "name:zho_x_preferred":[
        "\u65af\u6d1b\u535a\u9f4a\u4e9e"
    ],
    "wof:name":"Slobozia",
    "wof:placetype":"locality",
    "wof:population":580
},
  "geometry": {"coordinates":[25.18031,45.27491],"type":"Point"}
}