{
  "type": "Feature",
  "properties": {
    "gn:admin1_code":"07",
    "gn:admin2_code":"36649.0",
    "gn:asciiname":"Slobozia",
    "gn:country_code":"RO",
    "gn:dem":199,
    "gn:feature_class":"P",
    "gn:feature_code":"PPL",
    "gn:name":"Slobozia",
    "gn:population":0,
    "gn:timezone":"Europe/Bucharest",
    "iso:country":"RO",
    "wof:name":"Slobozia",
    "wof:placetype":"locality"
},
  "geometry": {"coordinates":[26.59848,48.00404],"type":"Point"}
}