{
  "type": "Feature",
  "properties": {
    "gn:admin1_code":"27",
    "gn:admin2_code":"119242.0",
    "gn:asciiname":"Sarmasel",
    "gn:cc2":"RO",
    "gn:country_code":"RO",
    "gn:dem":326,
    "gn:feature_class":"P",
    "gn:feature_code":"PPL",
    "gn:name":"S\u0103rm\u0103\u0219el",
    "gn:population":724,
    "gn:timezone":"Europe/Bucharest",
    "iso:country":"RO",
    "name:und_x_variant":[
        "Kiss\u00e1rm\u00e1s",
        "Sarinasel",
        "S\u0103rm\u0103\u015fel"
    ],
    "wof:lang_x_official":[
        "ron"
    ],
    "wof:lang_x_spoken":[
        "ron"
    ],
    "wof:name":"Sarmasel",
    "wof:placetype":"locality",
    "wof:population":724
},
  "geometry": {"coordinates":[24.17885,46.76062],"type":"Point"}
}