{
  "type": "Feature",
  "properties": {
    "gn:admin1_code":"17",
    "gn:admin2_code":"70110.0",
    "gn:asciiname":"Livezi",
    "gn:cc2":"RO",
    "gn:country_code":"RO",
    "gn:dem":71,
    "gn:feature_class":"P",
    "gn:feature_code":"PPL",
    "gn:name":"Livezi",
    "gn:population":878,
    "gn:timezone":"Europe/Bucharest",
    "iso:country":"RO",
    "name:ceb_x_preferred":[
        "Livezi"
    ],
    "name:deu_x_preferred":[
        "Livezi"
    ],
    "name:epo_x_preferred":[
        "Livezi"
    ],
    "name:ita_x_preferred":[
        "Livezi"
    ],
    "name:nld_x_preferred":[
        "Livezi"
    ],
    "name:ron_x_preferred":[
        "Livezi"
    ],
    "name:srp_x_preferred":[
        "\u041b\u0438\u0432\u0435\u0437\u0438"
    ],
    "name:ukr_x_preferred":[
        "\u041b\u0456\u0432\u0435\u0437\u044c"
    ],
    "name:und_x_variant":[
        "Livezei",
        "Livezile"
    ],
    "name:vie_x_preferred":[
        "Livezi"
    ],
    "wof:name":"Livezi",
    "wof:placetype":"locality",
    "wof:population":878
},
  "geometry": {"coordinates":[23.7894,44.23121],"type":"Point"}
}