{
  "type": "Feature",
  "properties": {
    "gn:admin1_code":"38",
    "gn:admin2_code":"167268.0",
    "gn:asciiname":"Ciocani",
    "gn:country_code":"RO",
    "gn:dem":96,
    "gn:feature_class":"P",
    "gn:feature_code":"PPLA2",
    "gn:name":"Ciocani",
    "gn:population":745,
    "gn:timezone":"Europe/Bucharest",
    "iso:country":"RO",
    "name:ceb_x_preferred":[
        "Comuna Ciocani"
    ],
    "name:ita_x_preferred":[
        "Ciocani"
    ],
    "name:msa_x_preferred":[
        "Ciocani"
    ],
    "name:nld_x_preferred":[
        "Ciocani"
    ],
    "name:por_x_preferred":[
        "Ciocani"
    ],
    "name:ron_x_preferred":[
        "Comuna Ciocani"
    ],
    "name:srp_x_preferred":[
        "\u041e\u043f\u0448\u0442\u0438\u043d\u0430 \u0427\u043e\u043a\u0430\u043d\u0438"
    ],
    "name:ukr_x_preferred":[
        "\u0427\u043e\u043a\u0430\u043d\u044c"
    ],
    "name:zho_x_preferred":[
        "\u55ac\u5361\u5c3c\u9109"
    ],
    "wof:name":"Ciocani",
    "wof:placetype":"locality",
    "wof:population":745
},
  "geometry": {"coordinates":[27.55994,46.26044],"type":"Point"}
}