{
  "type": "Feature",
  "properties": {
    "gn:admin1_code":"38",
    "gn:admin2_code":"167268.0",
    "gn:asciiname":"Ciocani",
    "gn:country_code":"RO",
    "gn:dem":96,
    "gn:feature_class":"P",
    "gn:feature_code":"PPLA2",
    "gn:name":"Ciocani",
    "gn:population":745,
    "gn:timezone":"Europe/Bucharest",
    "iso:country":"RO",
    "wof:name":"Ciocani",
    "wof:placetype":"locality",
    "wof:population":745
},
  "geometry": {"coordinates":[27.55994,46.26044],"type":"Point"}
}