{
  "type": "Feature",
  "properties": {
    "gn:admin1_code":"26",
    "gn:admin2_code":"113974.0",
    "gn:asciiname":"Lac",
    "gn:country_code":"RO",
    "gn:dem":275,
    "gn:feature_class":"P",
    "gn:feature_code":"PPL",
    "gn:name":"Lac",
    "gn:population":128,
    "gn:timezone":"Europe/Bucharest",
    "iso:country":"RO",
    "name:cat_x_preferred":[
        "Laca"
    ],
    "name:deu_x_preferred":[
        "Gummilack"
    ],
    "name:gle_x_preferred":[
        "Leaic"
    ],
    "name:hin_x_preferred":[
        "\u0932\u093e\u0916"
    ],
    "name:ita_x_preferred":[
        "Lacca"
    ],
    "name:mal_x_preferred":[
        "\u0d05\u0d30\u0d15\u0d4d\u0d15\u0d4d"
    ],
    "name:swe_x_preferred":[
        "Gummilacka"
    ],
    "name:tam_x_preferred":[
        "\u0b85\u0bb0\u0b95\u0bcd\u0b95\u0bc1\u0baa\u0bcd \u0baa\u0bc2\u0b9a\u0bcd\u0b9a\u0bbf"
    ],
    "name:tha_x_preferred":[
        "\u0e04\u0e23\u0e31\u0e48\u0e07"
    ],
    "wof:name":"Lac",
    "wof:placetype":"locality",
    "wof:population":128
},
  "geometry": {"coordinates":[23.06667,44.61667],"type":"Point"}
}