{
  "type": "Feature",
  "properties": {
    "gn:admin1_code":"26",
    "gn:admin2_code":"113974.0",
    "gn:asciiname":"Lac",
    "gn:country_code":"RO",
    "gn:dem":275,
    "gn:feature_class":"P",
    "gn:feature_code":"PPL",
    "gn:name":"Lac",
    "gn:population":128,
    "gn:timezone":"Europe/Bucharest",
    "iso:country":"RO",
    "wof:name":"Lac",
    "wof:placetype":"locality",
    "wof:population":128
},
  "geometry": {"coordinates":[23.06667,44.61667],"type":"Point"}
}