{
  "type": "Feature",
  "properties": {
    "gn:admin1_code":"40",
    "gn:admin2_code":"175224.0",
    "gn:asciiname":"Topesti",
    "gn:country_code":"RO",
    "gn:dem":414,
    "gn:feature_class":"P",
    "gn:feature_code":"PPL",
    "gn:name":"Tope\u0219ti",
    "gn:population":568,
    "gn:timezone":"Europe/Bucharest",
    "iso:country":"RO",
    "wof:name":"Topesti",
    "wof:placetype":"locality",
    "wof:population":568
},
  "geometry": {"coordinates":[26.7526,45.90579],"type":"Point"}
}