{
  "type": "Feature",
  "properties": {
    "gn:admin1_code":"03",
    "gn:admin2_code":"18778.0",
    "gn:asciiname":"Ogrezea",
    "gn:country_code":"RO",
    "gn:dem":393,
    "gn:feature_class":"P",
    "gn:feature_code":"PPL",
    "gn:name":"Ogrezea",
    "gn:population":428,
    "gn:timezone":"Europe/Bucharest",
    "iso:country":"RO",
    "wof:name":"Ogrezea",
    "wof:placetype":"locality",
    "wof:population":428
},
  "geometry": {"coordinates":[24.99544,45.05673],"type":"Point"}
}