{
  "type": "Feature",
  "properties": {
    "gn:admin1_code":"04",
    "gn:admin2_code":"21506.0",
    "gn:asciiname":"Sipote",
    "gn:country_code":"RO",
    "gn:dem":247,
    "gn:feature_class":"P",
    "gn:feature_code":"PPL",
    "gn:name":"\u015eipote",
    "gn:population":0,
    "gn:timezone":"Europe/Bucharest",
    "iso:country":"RO",
    "wof:lang_x_official":[
        "ron"
    ],
    "wof:lang_x_spoken":[
        "ron"
    ],
    "wof:name":"Sipote",
    "wof:placetype":"locality"
},
  "geometry": {"coordinates":[26.68333,46.68333],"type":"Point"}
}