{
  "type": "Feature",
  "properties": {
    "gn:admin1_code":"21",
    "gn:admin2_code":"89240.0",
    "gn:asciiname":"Codru",
    "gn:country_code":"RO",
    "gn:dem":406,
    "gn:feature_class":"P",
    "gn:feature_code":"PPL",
    "gn:name":"Codru",
    "gn:population":0,
    "gn:timezone":"Europe/Bucharest",
    "iso:country":"RO",
    "name:deu_x_preferred":[
        "Codru"
    ],
    "name:hun_x_preferred":[
        "Codru"
    ],
    "name:ron_x_preferred":[
        "Codru"
    ],
    "name:rus_x_preferred":[
        "\u041a\u043e\u0434\u0440\u044b"
    ],
    "name:srp_x_preferred":[
        "\u041a\u043e\u0434\u0440\u0443"
    ],
    "name:ukr_x_preferred":[
        "\u041a\u043e\u0434\u0440\u0443"
    ],
    "wof:name":"Codru",
    "wof:placetype":"locality"
},
  "geometry": {"coordinates":[23.01667,45.93333],"type":"Point"}
}