{
  "type": "Feature",
  "properties": {
    "gn:admin1_code":"03",
    "gn:admin2_code":"14272.0",
    "gn:asciiname":"Valea Mare-Bratia",
    "gn:country_code":"RO",
    "gn:dem":380,
    "gn:feature_class":"P",
    "gn:feature_code":"PPL",
    "gn:name":"Valea Mare-Bratia",
    "gn:population":676,
    "gn:timezone":"Europe/Bucharest",
    "iso:country":"RO",
    "wof:name":"Valea Mare-Bratia",
    "wof:placetype":"locality",
    "wof:population":676
},
  "geometry": {"coordinates":[24.95078,45.07266],"type":"Point"}
}