{
  "type": "Feature",
  "properties": {
    "gn:admin1_code":"30",
    "gn:admin2_code":"134899.0",
    "gn:asciiname":"Izvoru",
    "gn:country_code":"RO",
    "gn:dem":583,
    "gn:feature_class":"P",
    "gn:feature_code":"PPL",
    "gn:name":"Izvoru",
    "gn:population":0,
    "gn:timezone":"Europe/Bucharest",
    "iso:country":"RO",
    "name:ara_x_preferred":[
        "\u064a\u0632\u0641\u0648\u0631\u0648"
    ],
    "name:ceb_x_preferred":[
        "Izvoru"
    ],
    "name:ita_x_preferred":[
        "Izvoru"
    ],
    "name:mkd_x_preferred":[
        "\u0418\u0437\u0432\u043e\u0440\u0443"
    ],
    "name:msa_x_preferred":[
        "Izvoru"
    ],
    "name:nld_x_preferred":[
        "Izvoru"
    ],
    "name:por_x_preferred":[
        "Izvoru"
    ],
    "name:ron_x_preferred":[
        "Izvoru"
    ],
    "name:sqi_x_preferred":[
        "Izvoru"
    ],
    "name:srp_x_preferred":[
        "\u041e\u043f\u0448\u0442\u0438\u043d\u0430 \u0418\u0437\u0432\u043e\u0440\u0443"
    ],
    "name:ukr_x_preferred":[
        "\u0406\u0437\u0432\u043e\u0440\u0443"
    ],
    "name:und_x_variant":[
        "Fricoasa",
        "Izvoru"
    ],
    "name:vie_x_preferred":[
        "Izvoru"
    ],
    "name:vol_x_preferred":[
        "Izvoru"
    ],
    "name:zho_x_preferred":[
        "\u4f0a\u8332\u6c83\u9b6f\u9109"
    ],
    "wof:name":"Izvoru",
    "wof:placetype":"locality"
},
  "geometry": {"coordinates":[25.61667000000001,45.15],"type":"Point"}
}