{
  "type": "Feature",
  "properties": {
    "gn:admin1_code":"30",
    "gn:admin2_code":"134899.0",
    "gn:asciiname":"Izvoru",
    "gn:country_code":"RO",
    "gn:dem":583,
    "gn:feature_class":"P",
    "gn:feature_code":"PPL",
    "gn:name":"Izvoru",
    "gn:population":0,
    "gn:timezone":"Europe/Bucharest",
    "iso:country":"RO",
    "name:und_x_variant":[
        "Fricoasa",
        "Izvoru"
    ],
    "wof:name":"Izvoru",
    "wof:placetype":"locality"
},
  "geometry": {"coordinates":[25.61667000000001,45.15],"type":"Point"}
}