{
  "type": "Feature",
  "properties": {
    "gn:admin1_code":"06",
    "gn:admin2_code":"34985",
    "gn:asciiname":"Budurleni",
    "gn:country_code":"RO",
    "gn:dem":353,
    "gn:feature_class":"P",
    "gn:feature_code":"PPL",
    "gn:name":"Budurleni",
    "gn:population":176,
    "gn:timezone":"Europe/Bucharest",
    "iso:country":"RO",
    "wof:name":"Budurleni",
    "wof:placetype":"locality",
    "wof:population":176
},
  "geometry": {"coordinates":[24.42479,46.92014],"type":"Point"}
}