{
  "type": "Feature",
  "properties": {
    "gn:admin1_code":"19",
    "gn:admin2_code":"82136.0",
    "gn:asciiname":"Ciulava",
    "gn:country_code":"RO",
    "gn:dem":357,
    "gn:feature_class":"P",
    "gn:feature_code":"PPL",
    "gn:name":"Ciulava",
    "gn:population":0,
    "gn:timezone":"Europe/Bucharest",
    "iso:country":"RO",
    "wof:name":"Ciulava",
    "wof:placetype":"locality"
},
  "geometry": {"coordinates":[23.25,45.15],"type":"Point"}
}