{
  "type": "Feature",
  "properties": {
    "gn:admin1_code":"23",
    "gn:admin2_code":"98827.0",
    "gn:asciiname":"Poiana",
    "gn:country_code":"RO",
    "gn:dem":170,
    "gn:feature_class":"P",
    "gn:feature_code":"PPL",
    "gn:name":"Poiana",
    "gn:population":495,
    "gn:timezone":"Europe/Bucharest",
    "iso:country":"RO",
    "wof:name":"Poiana",
    "wof:placetype":"locality",
    "wof:population":495
},
  "geometry": {"coordinates":[27.79209,46.98253],"type":"Point"}
}