{
  "type": "Feature",
  "properties": {
    "gn:admin1_code":"11",
    "gn:admin2_code":"49545.0",
    "gn:asciiname":"Caltuna",
    "gn:cc2":"RO",
    "gn:country_code":"RO",
    "gn:dem":68,
    "gn:feature_class":"P",
    "gn:feature_code":"PPL",
    "gn:name":"C\u0103l\u021buna",
    "gn:population":593,
    "gn:timezone":"Europe/Bucharest",
    "iso:country":"RO",
    "name:und_x_variant":[
        "C\u0103ituna",
        "Col\u0163una",
        "C\u0103l\u0163una"
    ],
    "wof:name":"Caltuna",
    "wof:placetype":"locality",
    "wof:population":593
},
  "geometry": {"coordinates":[26.95112,44.96385],"type":"Point"}
}