{
  "type": "Feature",
  "properties": {
    "gn:admin1_code":"42",
    "gn:admin2_code":"101519.0",
    "gn:asciiname":"Facau",
    "gn:country_code":"RO",
    "gn:dem":72,
    "gn:feature_class":"P",
    "gn:feature_code":"PPL",
    "gn:name":"F\u0103c\u0103u",
    "gn:population":200,
    "gn:timezone":"Europe/Bucharest",
    "iso:country":"RO",
    "wof:name":"Facau",
    "wof:placetype":"locality",
    "wof:population":200
},
  "geometry": {"coordinates":[25.83262,44.29271],"type":"Point"}
}