{
  "type": "Feature",
  "properties": {
    "gn:admin1_code":"37",
    "gn:admin2_code":"161384.0",
    "gn:asciiname":"Luminita",
    "gn:cc2":"RO",
    "gn:country_code":"RO",
    "gn:dem":203,
    "gn:feature_class":"P",
    "gn:feature_code":"PPL",
    "gn:name":"Lumini\u021ba",
    "gn:population":306,
    "gn:timezone":"Europe/Bucharest",
    "iso:country":"RO",
    "name:und_x_variant":[
        "Elena Pavel",
        "Lumini\u0163a"
    ],
    "wof:name":"Luminita",
    "wof:placetype":"locality",
    "wof:population":306
},
  "geometry": {"coordinates":[28.33068,44.89472],"type":"Point"}
}