{
  "type": "Feature",
  "properties": {
    "gn:admin1_code":"21",
    "gn:admin2_code":"91330.0",
    "gn:asciiname":"Cainelu de Jos",
    "gn:cc2":"RO",
    "gn:country_code":"RO",
    "gn:dem":223,
    "gn:feature_class":"P",
    "gn:feature_code":"PPL",
    "gn:name":"C\u0103inelu de Jos",
    "gn:population":156,
    "gn:timezone":"Europe/Bucharest",
    "iso:country":"RO",
    "name:und_x_variant":[
        "Cainelul-de Jos",
        "C\u0103inelu de Jos"
    ],
    "wof:name":"Cainelu de Jos",
    "wof:placetype":"locality",
    "wof:population":156
},
  "geometry": {"coordinates":[22.83418,45.95146],"type":"Point"}
}