{
  "type": "Feature",
  "properties": {
    "gn:admin1_code":"11",
    "gn:admin2_code":"48842.0",
    "gn:asciiname":"Macrina",
    "gn:country_code":"RO",
    "gn:dem":61,
    "gn:feature_class":"P",
    "gn:feature_code":"PPL",
    "gn:name":"M\u0103crina",
    "gn:population":588,
    "gn:timezone":"Europe/Bucharest",
    "iso:country":"RO",
    "wof:name":"Macrina",
    "wof:placetype":"locality",
    "wof:population":588
},
  "geometry": {"coordinates":[27.19894,45.38657],"type":"Point"}
}