{
  "type": "Feature",
  "properties": {
    "gn:admin1_code":"31",
    "gn:admin2_code":"139740.0",
    "gn:asciiname":"Nadis",
    "gn:cc2":"RO",
    "gn:country_code":"RO",
    "gn:dem":208,
    "gn:feature_class":"P",
    "gn:feature_code":"PPL",
    "gn:name":"Nadi\u015f",
    "gn:population":0,
    "gn:timezone":"Europe/Bucharest",
    "iso:country":"RO",
    "name:und_x_variant":[
        "Nade\u015f",
        "Nadi\u015f"
    ],
    "wof:name":"Nadis",
    "wof:placetype":"locality"
},
  "geometry": {"coordinates":[23.17429,47.37824000000001],"type":"Point"}
}