{
  "type": "Feature",
  "properties": {
    "gn:admin1_code":"04",
    "gn:admin2_code":"24524.0",
    "gn:asciiname":"Cabesti",
    "gn:country_code":"RO",
    "gn:dem":192,
    "gn:feature_class":"P",
    "gn:feature_code":"PPL",
    "gn:name":"C\u0103be\u0219ti",
    "gn:population":829,
    "gn:timezone":"Europe/Bucharest",
    "iso:country":"RO",
    "wof:name":"Cabesti",
    "wof:placetype":"locality",
    "wof:population":829
},
  "geometry": {"coordinates":[27.44063,46.21184],"type":"Point"}
}