{
  "type": "Feature",
  "properties": {
    "gn:admin1_code":"21",
    "gn:admin2_code":"88644.0",
    "gn:asciiname":"Covragiu",
    "gn:cc2":"RO",
    "gn:country_code":"RO",
    "gn:dem":292,
    "gn:feature_class":"P",
    "gn:feature_code":"PPL",
    "gn:name":"Covragiu",
    "gn:population":191,
    "gn:timezone":"Europe/Bucharest",
    "iso:country":"RO",
    "name:und_x_variant":[
        "Covragi",
        "Covragiu"
    ],
    "wof:name":"Covragiu",
    "wof:placetype":"locality",
    "wof:population":191
},
  "geometry": {"coordinates":[23.02147,45.62434],"type":"Point"}
}