{
  "type": "Feature",
  "properties": {
    "gn:admin1_code":"17",
    "gn:admin2_code":"70673.0",
    "gn:asciiname":"Zvorsca",
    "gn:country_code":"RO",
    "gn:dem":120,
    "gn:feature_class":"P",
    "gn:feature_code":"PPL",
    "gn:name":"Zvorsca",
    "gn:population":721,
    "gn:timezone":"Europe/Bucharest",
    "iso:country":"RO",
    "wof:name":"Zvorsca",
    "wof:placetype":"locality",
    "wof:population":721
},
  "geometry": {"coordinates":[24.17719,43.99179],"type":"Point"}
}