{
  "type": "Feature",
  "properties": {
    "gn:admin1_code":"32",
    "gn:admin2_code":"138734.0",
    "gn:asciiname":"Sudurau",
    "gn:country_code":"RO",
    "gn:dem":114,
    "gn:feature_class":"P",
    "gn:feature_code":"PPL",
    "gn:name":"Sudur\u0103u",
    "gn:population":205,
    "gn:timezone":"Europe/Bucharest",
    "iso:country":"RO",
    "wof:name":"Sudurau",
    "wof:placetype":"locality",
    "wof:population":205
},
  "geometry": {"coordinates":[22.45752,47.53261],"type":"Point"}
}