{
  "type": "Feature",
  "properties": {
    "gn:admin1_code":"04",
    "gn:admin2_code":"25488.0",
    "gn:asciiname":"Timaresti",
    "gn:country_code":"RO",
    "gn:dem":426,
    "gn:feature_class":"P",
    "gn:feature_code":"PPL",
    "gn:name":"Tim\u0103re\u015fti",
    "gn:population":0,
    "gn:timezone":"Europe/Bucharest",
    "iso:country":"RO",
    "name:und_x_variant":[
        "Tib\u0103resti",
        "Tim\u0103re\u015fti"
    ],
    "wof:name":"Timaresti",
    "wof:placetype":"locality"
},
  "geometry": {"coordinates":[26.56667,46.58333],"type":"Point"}
}