{
  "type": "Feature",
  "properties": {
    "gn:admin1_code":"34",
    "gn:admin2_code":"147465.0",
    "gn:asciiname":"Petiuta",
    "gn:country_code":"RO",
    "gn:dem":301,
    "gn:feature_class":"P",
    "gn:feature_code":"PPL",
    "gn:name":"Petiu\u0163a",
    "gn:population":0,
    "gn:timezone":"Europe/Bucharest",
    "iso:country":"RO",
    "wof:name":"Petiuta",
    "wof:placetype":"locality"
},
  "geometry": {"coordinates":[26.28333,47.51667],"type":"Point"}
}