{
  "type": "Feature",
  "properties": {
    "gn:admin1_code":"04",
    "gn:admin2_code":"22237.0",
    "gn:asciiname":"Tavadaresti",
    "gn:cc2":"RO",
    "gn:country_code":"RO",
    "gn:dem":155,
    "gn:feature_class":"P",
    "gn:feature_code":"PPL",
    "gn:name":"T\u0103v\u0103d\u0103re\u0219ti",
    "gn:population":205,
    "gn:timezone":"Europe/Bucharest",
    "iso:country":"RO",
    "name:und_x_variant":[
        "C\u0103l\u0103pode\u015fti",
        "T\u0103v\u0103d\u0103re\u015fti"
    ],
    "wof:name":"Tavadaresti",
    "wof:placetype":"locality",
    "wof:population":205
},
  "geometry": {"coordinates":[27.29317,46.3268],"type":"Point"}
}