{
  "type": "Feature",
  "properties": {
    "gn:admin1_code":"04",
    "gn:admin2_code":"21757.0",
    "gn:asciiname":"Floresti",
    "gn:cc2":"RO",
    "gn:country_code":"RO",
    "gn:dem":198,
    "gn:feature_class":"P",
    "gn:feature_code":"PPL",
    "gn:name":"Flore\u0219ti",
    "gn:population":62,
    "gn:timezone":"Europe/Bucharest",
    "iso:country":"RO",
    "name:und_x_variant":[
        "Floce\u015ftii",
        "Floce\u015fti",
        "Flore\u015fti"
    ],
    "wof:name":"Floresti",
    "wof:placetype":"locality",
    "wof:population":62
},
  "geometry": {"coordinates":[26.89427,46.21836],"type":"Point"}
}