{
  "type": "Feature",
  "properties": {
    "gn:admin1_code":"27",
    "gn:admin2_code":"117667.0",
    "gn:asciiname":"Madaraseni",
    "gn:country_code":"RO",
    "gn:dem":294,
    "gn:feature_class":"P",
    "gn:feature_code":"PPL",
    "gn:name":"M\u0103d\u0103r\u0103\u0219eni",
    "gn:population":115,
    "gn:timezone":"Europe/Bucharest",
    "iso:country":"RO",
    "wof:name":"Madaraseni",
    "wof:placetype":"locality",
    "wof:population":115
},
  "geometry": {"coordinates":[24.25688,46.50326],"type":"Point"}
}