{
  "type": "Feature",
  "properties": {
    "gn:admin1_code":"29",
    "gn:admin2_code":"126772.0",
    "gn:asciiname":"Vulpesti",
    "gn:country_code":"RO",
    "gn:dem":254,
    "gn:feature_class":"P",
    "gn:feature_code":"PPL",
    "gn:name":"Vulpe\u0219ti",
    "gn:population":189,
    "gn:timezone":"Europe/Bucharest",
    "iso:country":"RO",
    "wof:name":"Vulpesti",
    "wof:placetype":"locality",
    "wof:population":189
},
  "geometry": {"coordinates":[24.34265,44.79373],"type":"Point"}
}