{
  "type": "Feature",
  "properties": {
    "gn:gn_country":"RO",
    "gn:gn_fcode":"PPL",
    "gn:gn_pop":0,
    "gn:population":216,
    "iso:country":"RO",
    "name:ceb_x_preferred":[
        "Ple\u0219a"
    ],
    "name:eng_x_preferred":[
        "Ple\u0219a"
    ],
    "name:fra_x_preferred":[
        "Ple\u0219a"
    ],
    "name:nld_x_preferred":[
        "Ple\u0219a"
    ],
    "name:pol_x_preferred":[
        "Plesza"
    ],
    "name:ron_x_preferred":[
        "Ple\u0219a"
    ],
    "name:srp_x_preferred":[
        "\u041f\u043b\u0435\u0448\u0430"
    ],
    "name:ukr_x_preferred":[
        "\u041f\u043b\u0435\u0448\u0430"
    ],
    "qs_pg:aaroncc":"RO",
    "qs_pg:gn_country":"RO",
    "qs_pg:gn_fcode":"PPL",
    "qs_pg:gn_pop":0,
    "qs_pg:name":"Ple\u0219a",
    "qs_pg:name_adm0":"Rom\u00e2nia",
    "qs_pg:name_adm1":"Suceava",
    "qs_pg:photos":25,
    "qs_pg:photos_1k":5,
    "qs_pg:photos_9k":1,
    "qs_pg:photos_9r":1,
    "qs_pg:photos_all":25,
    "qs_pg:photos_sr":1,
    "qs_pg:pop_sr":0,
    "qs_pg:qs_pg_placetype":"locality",
    "qs_pg:qs_pg_placetype_gp":"Town",
    "qs_pg:woe_adm0":23424933,
    "woe:adm0_id":23424933,
    "woe:name_adm0":"Rom\u00e2nia",
    "woe:name_adm1":"Suceava",
    "woe:placetype":"Town",
    "wof:name":"Ple\u0219a",
    "wof:placetype":"locality",
    "wof:population":216
},
  "geometry": {"coordinates":[25.85,47.63333],"type":"Point"}
}