{
  "type": "Feature",
  "properties": {
    "gn:admin1_code":"13",
    "gn:admin2_code":"56773.0",
    "gn:asciiname":"Valea Calda",
    "gn:country_code":"RO",
    "gn:dem":295,
    "gn:feature_class":"P",
    "gn:feature_code":"PPL",
    "gn:name":"Valea Cald\u0103",
    "gn:population":180,
    "gn:timezone":"Europe/Bucharest",
    "iso:country":"RO",
    "wof:name":"Valea Calda",
    "wof:placetype":"locality",
    "wof:population":180
},
  "geometry": {"coordinates":[24.13945,46.84985],"type":"Point"}
}