{
  "type": "Feature",
  "properties": {
    "gn:admin1_code":"04",
    "gn:admin2_code":"25291.0",
    "gn:asciiname":"Sarbi",
    "gn:cc2":"RO",
    "gn:country_code":"RO",
    "gn:dem":320,
    "gn:feature_class":"P",
    "gn:feature_code":"PPL",
    "gn:name":"S\u00e2rbi",
    "gn:population":0,
    "gn:timezone":"Europe/Bucharest",
    "iso:country":"RO",
    "name:nor_x_preferred":[
        "Sarbi"
    ],
    "name:und_x_variant":[
        "S\u00e2rbi",
        "S\u00eerbi"
    ],
    "name:vie_x_preferred":[
        "Sarbi"
    ],
    "wof:name":"Sarbi",
    "wof:placetype":"locality"
},
  "geometry": {"coordinates":[26.68333,46.53333],"type":"Point"}
}