{
  "type": "Feature",
  "properties": {
    "gn:admin1_code":"01",
    "gn:admin2_code":"5826",
    "gn:asciiname":"Bogdanesti",
    "gn:country_code":"RO",
    "gn:dem":843,
    "gn:feature_class":"P",
    "gn:feature_code":"PPL",
    "gn:name":"Bogd\u0103ne\u0219ti",
    "gn:population":21,
    "gn:timezone":"Europe/Bucharest",
    "iso:country":"RO",
    "wof:name":"Bogdanesti",
    "wof:placetype":"locality",
    "wof:population":21
},
  "geometry": {"coordinates":[23.34812,46.29179],"type":"Point"}
}