{
  "type": "Feature",
  "properties": {
    "gn:admin1_code":"40",
    "gn:admin2_code":"178750.0",
    "gn:asciiname":"Muncei",
    "gn:country_code":"RO",
    "gn:dem":568,
    "gn:feature_class":"P",
    "gn:feature_code":"PPL",
    "gn:name":"Muncei",
    "gn:population":0,
    "gn:timezone":"Europe/Bucharest",
    "iso:country":"RO",
    "name:und_x_variant":[
        "Muncel",
        "Muncei"
    ],
    "wof:name":"Muncei",
    "wof:placetype":"locality"
},
  "geometry": {"coordinates":[26.68333,45.85],"type":"Point"}
}