{
  "type": "Feature",
  "properties": {
    "gn:admin1_code":"34",
    "gn:admin2_code":"148293.0",
    "gn:asciiname":"Saha",
    "gn:country_code":"RO",
    "gn:dem":369,
    "gn:feature_class":"P",
    "gn:feature_code":"PPL",
    "gn:name":"Saha",
    "gn:population":0,
    "gn:timezone":"Europe/Bucharest",
    "iso:country":"RO",
    "name:ceb_x_preferred":[
        "Saha"
    ],
    "name:deu_x_preferred":[
        "Saha"
    ],
    "name:epo_x_preferred":[
        "Saha"
    ],
    "name:fin_x_preferred":[
        "Saha"
    ],
    "name:fra_x_preferred":[
        "Saha"
    ],
    "name:swe_x_preferred":[
        "Saha"
    ],
    "wof:lang_x_official":[
        "ron"
    ],
    "wof:lang_x_spoken":[
        "ron"
    ],
    "wof:name":"Saha",
    "wof:placetype":"locality"
},
  "geometry": {"coordinates":[26.01667,47.86667],"type":"Point"}
}