{
  "type": "Feature",
  "properties": {
    "gn:admin1_code":"29",
    "gn:admin2_code":"125846",
    "gn:asciiname":"Barza",
    "gn:cc2":"RO",
    "gn:country_code":"RO",
    "gn:dem":119,
    "gn:feature_class":"P",
    "gn:feature_code":"PPLA2",
    "gn:name":"B\u00e2rza",
    "gn:population":995,
    "gn:timezone":"Europe/Bucharest",
    "iso:country":"RO",
    "name:und_x_variant":[
        "B\u00e2rza",
        "Balsu",
        "B\u00eerza"
    ],
    "wof:name":"Barza",
    "wof:placetype":"locality",
    "wof:population":995
},
  "geometry": {"coordinates":[24.14188,44.32811],"type":"Point"}
}