{
  "type": "Feature",
  "properties": {
    "gn:admin1_code":"05",
    "gn:admin2_code":"29092.0",
    "gn:asciiname":"Ianca",
    "gn:cc2":"RO",
    "gn:country_code":"RO",
    "gn:dem":102,
    "gn:feature_class":"P",
    "gn:feature_code":"PPL",
    "gn:name":"Ianca",
    "gn:population":285,
    "gn:timezone":"Europe/Bucharest",
    "iso:country":"RO",
    "name:ceb_x_preferred":[
        "Ora\u0219 Ianca"
    ],
    "name:deu_x_preferred":[
        "Ianca"
    ],
    "name:epo_x_preferred":[
        "Ianca"
    ],
    "name:fas_x_preferred":[
        "\u06cc\u0646\u06a9\u0647"
    ],
    "name:fra_x_preferred":[
        "Ianca"
    ],
    "name:hun_x_preferred":[
        "Ianca"
    ],
    "name:ind_x_preferred":[
        "Ianca"
    ],
    "name:ita_x_preferred":[
        "Ianca"
    ],
    "name:lat_x_preferred":[
        "Ianca"
    ],
    "name:min_x_preferred":[
        "Ianca"
    ],
    "name:msa_x_preferred":[
        "Ianca"
    ],
    "name:nld_x_preferred":[
        "Ianca"
    ],
    "name:pol_x_preferred":[
        "Ianca"
    ],
    "name:por_x_preferred":[
        "Ianca"
    ],
    "name:ron_x_preferred":[
        "Ianca"
    ],
    "name:rus_x_preferred":[
        "\u042f\u043d\u043a\u0430"
    ],
    "name:spa_x_preferred":[
        "Ianca"
    ],
    "name:srp_x_preferred":[
        "\u041e\u043f\u0448\u0442\u0438\u043d\u0430 \u0408\u0430\u043d\u043a\u0430"
    ],
    "name:tgk_x_preferred":[
        "\u042f\u043d\u043a\u0430"
    ],
    "name:ukr_x_preferred":[
        "\u042f\u043d\u043a\u0430"
    ],
    "name:und_x_variant":[
        "Iancule\u015fti",
        "Ianca"
    ],
    "wof:name":"Ianca",
    "wof:placetype":"locality",
    "wof:population":285
},
  "geometry": {"coordinates":[21.99174,47.28445],"type":"Point"}
}