{
  "type": "Feature",
  "properties": {
    "gn:admin1_code":"05",
    "gn:admin2_code":"29092.0",
    "gn:asciiname":"Ianca",
    "gn:cc2":"RO",
    "gn:country_code":"RO",
    "gn:dem":102,
    "gn:feature_class":"P",
    "gn:feature_code":"PPL",
    "gn:name":"Ianca",
    "gn:population":285,
    "gn:timezone":"Europe/Bucharest",
    "iso:country":"RO",
    "name:und_x_variant":[
        "Iancule\u015fti",
        "Ianca"
    ],
    "wof:name":"Ianca",
    "wof:placetype":"locality",
    "wof:population":285
},
  "geometry": {"coordinates":[21.99174,47.28445],"type":"Point"}
}