{
  "type": "Feature",
  "properties": {
    "gn:admin1_code":"39",
    "gn:admin2_code":"169182",
    "gn:asciiname":"Bondoci",
    "gn:country_code":"RO",
    "gn:dem":308,
    "gn:feature_class":"P",
    "gn:feature_code":"PPL",
    "gn:name":"Bondoci",
    "gn:population":149,
    "gn:timezone":"Europe/Bucharest",
    "iso:country":"RO",
    "wof:name":"Bondoci",
    "wof:placetype":"locality",
    "wof:population":149
},
  "geometry": {"coordinates":[23.99585,44.96014],"type":"Point"}
}