{
  "type": "Feature",
  "properties": {
    "gn:admin1_code":"12",
    "gn:admin2_code":"53700",
    "gn:asciiname":"Dumbrava",
    "gn:country_code":"RO",
    "gn:dem":327,
    "gn:feature_class":"P",
    "gn:feature_code":"PPL",
    "gn:name":"Dumbrava",
    "gn:population":0,
    "gn:timezone":"Europe/Bucharest",
    "iso:country":"RO",
    "wof:name":"Dumbrava",
    "wof:placetype":"locality"
},
  "geometry": {"coordinates":[22.07611,44.91222],"type":"Point"}
}