{
  "type": "Feature",
  "properties": {
    "gn:admin1_code":"12",
    "gn:admin2_code":"53700",
    "gn:asciiname":"Dumbrava",
    "gn:country_code":"RO",
    "gn:dem":327,
    "gn:feature_class":"P",
    "gn:feature_code":"PPL",
    "gn:name":"Dumbrava",
    "gn:population":0,
    "gn:timezone":"Europe/Bucharest",
    "iso:country":"RO",
    "name:ceb_x_preferred":[
        "Dumbrava"
    ],
    "name:deu_x_preferred":[
        "Dumbrava"
    ],
    "name:epo_x_preferred":[
        "Dumbrava"
    ],
    "name:eus_x_preferred":[
        "Dumbrava"
    ],
    "name:fra_x_preferred":[
        "Dumbrava"
    ],
    "name:hun_x_preferred":[
        "Dumbrava"
    ],
    "name:ita_x_preferred":[
        "Dumbrava"
    ],
    "name:nld_x_preferred":[
        "Dumbrava"
    ],
    "name:ron_x_preferred":[
        "Dumbrava"
    ],
    "name:srp_x_preferred":[
        "\u0414\u0443\u043c\u0431\u0440\u0430\u0432\u0430"
    ],
    "name:swe_x_preferred":[
        "Dumbrava"
    ],
    "name:vol_x_preferred":[
        "Dumbrava"
    ],
    "wof:lang_x_official":[
        "ron"
    ],
    "wof:lang_x_spoken":[
        "ron"
    ],
    "wof:name":"Dumbrava",
    "wof:placetype":"locality"
},
  "geometry": {"coordinates":[22.07611,44.91222],"type":"Point"}
}