{
  "type": "Feature",
  "properties": {
    "gn:admin1_code":"13",
    "gn:admin2_code":"56522.0",
    "gn:asciiname":"Naoiu",
    "gn:cc2":"RO",
    "gn:country_code":"RO",
    "gn:dem":345,
    "gn:feature_class":"P",
    "gn:feature_code":"PPL",
    "gn:name":"N\u0103oiu",
    "gn:population":571,
    "gn:timezone":"Europe/Bucharest",
    "iso:country":"RO",
    "name:und_x_variant":[
        "N\u0103oiul",
        "N\u0103oiu"
    ],
    "wof:name":"Naoiu",
    "wof:placetype":"locality",
    "wof:population":571
},
  "geometry": {"coordinates":[24.10196,46.76373],"type":"Point"}
}