{
  "type": "Feature",
  "properties": {
    "gn:admin1_code":"26",
    "gn:admin2_code":"112995.0",
    "gn:asciiname":"Proitesti",
    "gn:cc2":"RO",
    "gn:country_code":"RO",
    "gn:dem":430,
    "gn:feature_class":"P",
    "gn:feature_code":"PPL",
    "gn:name":"Proite\u0219ti",
    "gn:population":134,
    "gn:timezone":"Europe/Bucharest",
    "iso:country":"RO",
    "name:und_x_variant":[
        "Projte\u0161ti",
        "Proite\u015fti"
    ],
    "wof:name":"Proitesti",
    "wof:placetype":"locality",
    "wof:population":134
},
  "geometry": {"coordinates":[22.72125,44.97138],"type":"Point"}
}