{
  "type": "Feature",
  "properties": {
    "gn:admin1_code":"31",
    "gn:admin2_code":"141027.0",
    "gn:asciiname":"Fantanele",
    "gn:country_code":"RO",
    "gn:dem":343,
    "gn:feature_class":"P",
    "gn:feature_code":"PPL",
    "gn:name":"F\u00e2nt\u00e2nele",
    "gn:population":28,
    "gn:timezone":"Europe/Bucharest",
    "iso:country":"RO",
    "name:hun_x_preferred":[
        "T\u00f6vises"
    ],
    "wof:name":"Fantanele",
    "wof:placetype":"locality",
    "wof:population":28
},
  "geometry": {"coordinates":[23.41667,47.06667],"type":"Point"}
}