{
  "type": "Feature",
  "properties": {
    "gn:admin1_code":"04",
    "gn:admin2_code":"23868.0",
    "gn:asciiname":"Taula",
    "gn:country_code":"RO",
    "gn:dem":293,
    "gn:feature_class":"P",
    "gn:feature_code":"PPL",
    "gn:name":"Taula",
    "gn:population":69,
    "gn:timezone":"Europe/Bucharest",
    "iso:country":"RO",
    "name:bel_x_preferred":[
        "\u0422\u0430\u045e\u043b\u0430"
    ],
    "name:cat_x_preferred":[
        "Taula"
    ],
    "name:deu_x_preferred":[
        "Taula"
    ],
    "name:epo_x_preferred":[
        "Ta\u016dlo"
    ],
    "name:fin_x_preferred":[
        "Taula"
    ],
    "name:fra_x_preferred":[
        "Taula"
    ],
    "name:glg_x_preferred":[
        "Taula"
    ],
    "name:lat_x_preferred":[
        "Taula"
    ],
    "name:pol_x_preferred":[
        "Taula"
    ],
    "name:por_x_preferred":[
        "Taula"
    ],
    "name:rus_x_preferred":[
        "\u0422\u0430\u0443\u043b\u0430"
    ],
    "name:spa_x_preferred":[
        "Taula"
    ],
    "wof:name":"Taula",
    "wof:placetype":"locality",
    "wof:population":69
},
  "geometry": {"coordinates":[27.2819,46.45673],"type":"Point"}
}