{
  "type": "Feature",
  "properties": {
    "gn:admin1_code":"04",
    "gn:admin2_code":"23868.0",
    "gn:asciiname":"Taula",
    "gn:country_code":"RO",
    "gn:dem":293,
    "gn:feature_class":"P",
    "gn:feature_code":"PPL",
    "gn:name":"Taula",
    "gn:population":69,
    "gn:timezone":"Europe/Bucharest",
    "iso:country":"RO",
    "wof:name":"Taula",
    "wof:placetype":"locality",
    "wof:population":69
},
  "geometry": {"coordinates":[27.2819,46.45673],"type":"Point"}
}