{
  "type": "Feature",
  "properties": {
    "gn:admin1_code":"01",
    "gn:admin2_code":"6627.0",
    "gn:asciiname":"Ramet",
    "gn:cc2":"RO",
    "gn:country_code":"RO",
    "gn:dem":801,
    "gn:feature_class":"P",
    "gn:feature_code":"PPL",
    "gn:name":"R\u00e2me\u0163",
    "gn:population":0,
    "gn:timezone":"Europe/Bucharest",
    "iso:country":"RO",
    "name:ara_x_preferred":[
        "\u0631\u064a\u0645\u064a\u062a\u0633"
    ],
    "name:ceb_x_preferred":[
        "Comuna R\u00e2me\u021b"
    ],
    "name:deu_x_preferred":[
        "R\u00e2me\u021b"
    ],
    "name:epo_x_preferred":[
        "R\u00e2me\u021b"
    ],
    "name:fra_x_preferred":[
        "R\u00e2me\u021b"
    ],
    "name:ita_x_preferred":[
        "R\u00e2me\u021b"
    ],
    "name:mkd_x_preferred":[
        "\u0420\u0435\u043c\u0435\u0446"
    ],
    "name:msa_x_preferred":[
        "R\u00e2me\u021b"
    ],
    "name:nld_x_preferred":[
        "R\u00e2me\u021b"
    ],
    "name:por_x_preferred":[
        "R\u00e2me\u021b"
    ],
    "name:ron_x_preferred":[
        "Comuna R\u00e2me\u021b"
    ],
    "name:sqi_x_preferred":[
        "R\u00e2me\u0163"
    ],
    "name:srp_x_preferred":[
        "\u041e\u043f\u0448\u0442\u0438\u043d\u0430 \u0420\u0430\u043c\u0435\u0446"
    ],
    "name:ukr_x_preferred":[
        "\u0420\u0438\u043c\u0435\u0446"
    ],
    "name:und_x_variant":[
        "R\u00e2me\u0163i",
        "R\u00eeme\u0163i"
    ],
    "name:vol_x_preferred":[
        "R\u00e2me\u0163"
    ],
    "name:zho_x_preferred":[
        "\u52d2\u6885\u8328\u9109"
    ],
    "wof:name":"Ramet",
    "wof:placetype":"locality"
},
  "geometry": {"coordinates":[23.52757,46.31457],"type":"Point"}
}