{
  "type": "Feature",
  "properties": {
    "gn:admin1_code":"01",
    "gn:admin2_code":"6627.0",
    "gn:asciiname":"Ramet",
    "gn:cc2":"RO",
    "gn:country_code":"RO",
    "gn:dem":801,
    "gn:feature_class":"P",
    "gn:feature_code":"PPL",
    "gn:name":"R\u00e2me\u0163",
    "gn:population":0,
    "gn:timezone":"Europe/Bucharest",
    "iso:country":"RO",
    "name:und_x_variant":[
        "R\u00e2me\u0163",
        "R\u00e2me\u0163i",
        "R\u00eeme\u0163i"
    ],
    "wof:name":"Ramet",
    "wof:placetype":"locality"
},
  "geometry": {"coordinates":[23.52757,46.31457],"type":"Point"}
}