{
  "type": "Feature",
  "properties": {
    "gn:admin1_code":"42",
    "gn:admin2_code":"105972.0",
    "gn:asciiname":"Valcelele",
    "gn:cc2":"RO",
    "gn:country_code":"RO",
    "gn:dem":108,
    "gn:feature_class":"P",
    "gn:feature_code":"PPL",
    "gn:name":"V\u00e2lcelele",
    "gn:population":0,
    "gn:timezone":"Europe/Bucharest",
    "iso:country":"RO",
    "name:und_x_variant":[
        "Belimoaica",
        "V\u00eelcelele",
        "V\u00e2lcelele"
    ],
    "wof:name":"Valcelele",
    "wof:placetype":"locality"
},
  "geometry": {"coordinates":[25.57111,44.46694],"type":"Point"}
}