{
  "type": "Feature",
  "properties": {
    "gn:admin1_code":"39",
    "gn:admin2_code":"170444.0",
    "gn:asciiname":"Sparleni",
    "gn:cc2":"RO",
    "gn:country_code":"RO",
    "gn:dem":200,
    "gn:feature_class":"P",
    "gn:feature_code":"PPL",
    "gn:name":"Sp\u00e2rleni",
    "gn:population":635,
    "gn:timezone":"Europe/Bucharest",
    "iso:country":"RO",
    "name:und_x_variant":[
        "Sp\u00e2rleni",
        "Sp\u00eerleni"
    ],
    "wof:name":"Sparleni",
    "wof:placetype":"locality",
    "wof:population":635
},
  "geometry": {"coordinates":[24.13815,44.70389],"type":"Point"}
}