{
  "type": "Feature",
  "properties": {
    "gn:admin1_code":"03",
    "gn:admin2_code":"17496.0",
    "gn:asciiname":"Smeura",
    "gn:country_code":"RO",
    "gn:dem":347,
    "gn:feature_class":"P",
    "gn:feature_code":"PPL",
    "gn:name":"Smeura",
    "gn:population":929,
    "gn:timezone":"Europe/Bucharest",
    "iso:country":"RO",
    "wof:name":"Smeura",
    "wof:placetype":"locality",
    "wof:population":929
},
  "geometry": {"coordinates":[24.83559,44.83406],"type":"Point"}
}