{
  "type": "Feature",
  "properties": {
    "gn:admin1_code":"12",
    "gn:admin2_code":"52954.0",
    "gn:asciiname":"Giurgiova",
    "gn:cc2":"RO",
    "gn:country_code":"RO",
    "gn:dem":144,
    "gn:feature_class":"P",
    "gn:feature_code":"PPL",
    "gn:name":"Giurgiova",
    "gn:population":184,
    "gn:timezone":"Europe/Bucharest",
    "iso:country":"RO",
    "name:und_x_variant":[
        "Durdova",
        "Giurgiuva",
        "Jurjova",
        "Giurgiova"
    ],
    "wof:name":"Giurgiova",
    "wof:placetype":"locality",
    "wof:population":184
},
  "geometry": {"coordinates":[21.7201,45.18522],"type":"Point"}
}