{
  "type": "Feature",
  "properties": {
    "gn:admin1_code":"19",
    "gn:admin2_code":"81095.0",
    "gn:asciiname":"Orzesti",
    "gn:country_code":"RO",
    "gn:dem":311,
    "gn:feature_class":"P",
    "gn:feature_code":"PPL",
    "gn:name":"Orze\u0219ti",
    "gn:population":411,
    "gn:timezone":"Europe/Bucharest",
    "iso:country":"RO",
    "wof:name":"Orzesti",
    "wof:placetype":"locality",
    "wof:population":411
},
  "geometry": {"coordinates":[22.81631,45.04868],"type":"Point"}
}