{
  "type": "Feature",
  "properties": {
    "gn:admin1_code":"07",
    "gn:admin2_code":"37850",
    "gn:asciiname":"Belcea",
    "gn:country_code":"RO",
    "gn:dem":177,
    "gn:feature_class":"P",
    "gn:feature_code":"PPL",
    "gn:name":"Belcea",
    "gn:population":32,
    "gn:timezone":"Europe/Bucharest",
    "iso:country":"RO",
    "wof:name":"Belcea",
    "wof:placetype":"locality",
    "wof:population":32
},
  "geometry": {"coordinates":[26.44454,47.80508],"type":"Point"}
}