{
  "type": "Feature",
  "properties": {
    "gn:admin1_code":"26",
    "gn:admin2_code":"111818.0",
    "gn:asciiname":"Paunesti",
    "gn:cc2":"RO",
    "gn:country_code":"RO",
    "gn:dem":505,
    "gn:feature_class":"P",
    "gn:feature_code":"PPL",
    "gn:name":"P\u0103une\u0219ti",
    "gn:population":218,
    "gn:timezone":"Europe/Bucharest",
    "iso:country":"RO",
    "name:und_x_variant":[
        "H\u0103une\u015fti",
        "P\u0103une\u015fti"
    ],
    "wof:name":"Paunesti",
    "wof:placetype":"locality",
    "wof:population":218
},
  "geometry": {"coordinates":[22.63283,44.78672],"type":"Point"}
}