{
  "type": "Feature",
  "properties": {
    "gn:admin1_code":"12",
    "gn:admin2_code":"51699.0",
    "gn:asciiname":"Prisian",
    "gn:country_code":"RO",
    "gn:dem":227,
    "gn:feature_class":"P",
    "gn:feature_code":"PPL",
    "gn:name":"Prisian",
    "gn:population":464,
    "gn:timezone":"Europe/Bucharest",
    "iso:country":"RO",
    "wof:name":"Prisian",
    "wof:placetype":"locality",
    "wof:population":464
},
  "geometry": {"coordinates":[22.24263,45.35894],"type":"Point"}
}