{
  "type": "Feature",
  "properties": {
    "gn:admin1_code":"28",
    "gn:admin2_code":"124493.0",
    "gn:asciiname":"Schitu Tarcau",
    "gn:cc2":"RO",
    "gn:country_code":"RO",
    "gn:dem":617,
    "gn:feature_class":"P",
    "gn:feature_code":"PPL",
    "gn:name":"Schitu Tarc\u0103u",
    "gn:population":73,
    "gn:timezone":"Europe/Bucharest",
    "iso:country":"RO",
    "name:und_x_variant":[
        "Monostor Tarc\u0103u",
        "Schitu-Tarc\u0103u"
    ],
    "wof:name":"Schitu Tarcau",
    "wof:placetype":"locality",
    "wof:population":73
},
  "geometry": {"coordinates":[26.18267,46.76296],"type":"Point"}
}