{
  "type": "Feature",
  "properties": {
    "gn:country":"RO",
    "gn:fcode":"PPLA2",
    "gn:population":2909,
    "iso:country":"RO",
    "name:ceb_x_preferred":[
        "Olcea"
    ],
    "name:eng_x_preferred":[
        "Olcea"
    ],
    "name:epo_x_preferred":[
        "Olcea"
    ],
    "name:fra_x_preferred":[
        "Olcea"
    ],
    "name:hun_x_preferred":[
        "Olcsa"
    ],
    "name:ita_x_preferred":[
        "Olcea"
    ],
    "name:msa_x_preferred":[
        "Olcea"
    ],
    "name:nld_x_preferred":[
        "Olcea"
    ],
    "name:por_x_preferred":[
        "Olcea"
    ],
    "name:ron_x_preferred":[
        "Olcea"
    ],
    "name:sqi_x_preferred":[
        "Olcea"
    ],
    "name:srp_x_preferred":[
        "\u041e\u043b\u0447\u0430"
    ],
    "name:ukr_x_preferred":[
        "\u041e\u043b\u0447\u0430"
    ],
    "name:vie_x_preferred":[
        "Olcea"
    ],
    "name:vol_x_preferred":[
        "Olcea"
    ],
    "qs_pg:aaroncc":"RO",
    "qs_pg:gn_country":"RO",
    "qs_pg:gn_fcode":"PPLA2",
    "qs_pg:gn_pop":2909,
    "qs_pg:name":"Olcea",
    "qs_pg:photos_9r":0,
    "qs_pg:photos_sr":0,
    "qs_pg:pop_sr":4,
    "qs_pg:qs_pg_placetype":"locality",
    "wof:name":"Olcea",
    "wof:placetype":"locality",
    "wof:population":2909
},
  "geometry": {"coordinates":[21.98333,46.68333],"type":"Point"}
}