{
  "type": "Feature",
  "properties": {
    "gn:gn_country":"RO",
    "gn:gn_fcode":"PPLA2",
    "gn:gn_pop":2879,
    "gn:population":2879,
    "iso:country":"RO",
    "name:dut_x_preferred":[
        "Victor Vlad Delamarina"
    ],
    "name:eng_x_preferred":[
        "Victor Vlad Delamarina"
    ],
    "name:epo_x_preferred":[
        "Victor Vlad Delamarina"
    ],
    "name:fre_x_preferred":[
        "Victor Vlad Delamarina"
    ],
    "name:hun_x_preferred":[
        "Lugoskisfalu"
    ],
    "name:ita_x_preferred":[
        "Victor Vlad Delamarina"
    ],
    "name:may_x_preferred":[
        "Victor Vlad Delamarina"
    ],
    "name:por_x_preferred":[
        "Victor Vlad Delamarina"
    ],
    "name:rum_x_preferred":[
        "Victor Vlad Delamarina"
    ],
    "name:ukr_x_preferred":[
        "\u0412\u0456\u043a\u0442\u043e\u0440-\u0412\u043b\u0430\u0434-\u0414\u0435\u043b\u0430\u043c\u0430\u0440\u0456\u043d\u0430"
    ],
    "name:unk_x_variant":[
        "Lugoskisfalu"
    ],
    "name:vol_x_preferred":[
        "Victor Vlad Delamarina"
    ],
    "qs_pg:aaroncc":"RO",
    "qs_pg:gn_country":"RO",
    "qs_pg:gn_fcode":"PPLA2",
    "qs_pg:gn_pop":2879,
    "qs_pg:name":"Victor Vlad Delamarina",
    "qs_pg:photos_9r":0,
    "qs_pg:photos_sr":0,
    "qs_pg:pop_sr":4,
    "qs_pg:qs_pg_placetype":"locality",
    "wof:name":"Victor Vlad Delamarina",
    "wof:placetype":"locality",
    "wof:population":2879
},
  "geometry": {"coordinates":[21.89278,45.64056],"type":"Point"}
}