{
  "type": "Feature",
  "properties": {
    "gn:admin1_code":"01",
    "gn:admin2_code":"6761.0",
    "gn:asciiname":"Iacobesti",
    "gn:country_code":"RO",
    "gn:dem":619,
    "gn:feature_class":"P",
    "gn:feature_code":"PPL",
    "gn:name":"Iacobe\u0219ti",
    "gn:population":54,
    "gn:timezone":"Europe/Bucharest",
    "iso:country":"RO",
    "wof:name":"Iacobesti",
    "wof:placetype":"locality",
    "wof:population":54
},
  "geometry": {"coordinates":[23.06796,46.30789],"type":"Point"}
}