{
  "type": "Feature",
  "properties": {
    "gn:admin1_code":"03",
    "gn:admin2_code":"14450.0",
    "gn:asciiname":"Ciocesti",
    "gn:country_code":"RO",
    "gn:dem":167,
    "gn:feature_class":"P",
    "gn:feature_code":"PPL",
    "gn:name":"Cioce\u0219ti",
    "gn:population":527,
    "gn:timezone":"Europe/Bucharest",
    "iso:country":"RO",
    "wof:name":"Ciocesti",
    "wof:placetype":"locality",
    "wof:population":527
},
  "geometry": {"coordinates":[24.78381,44.44744],"type":"Point"}
}