{
  "type": "Feature",
  "properties": {
    "gn:admin1_code":"07",
    "gn:admin2_code":"38679.0",
    "gn:asciiname":"Doina",
    "gn:country_code":"RO",
    "gn:dem":147,
    "gn:feature_class":"P",
    "gn:feature_code":"PPL",
    "gn:name":"Doina",
    "gn:population":564,
    "gn:timezone":"Europe/Bucharest",
    "iso:country":"RO",
    "wof:name":"Doina",
    "wof:placetype":"locality",
    "wof:population":564
},
  "geometry": {"coordinates":[27.19614,47.5424],"type":"Point"}
}