{
  "type": "Feature",
  "properties": {
    "gn:admin1_code":"07",
    "gn:admin2_code":"38679.0",
    "gn:asciiname":"Doina",
    "gn:country_code":"RO",
    "gn:dem":147,
    "gn:feature_class":"P",
    "gn:feature_code":"PPL",
    "gn:name":"Doina",
    "gn:population":564,
    "gn:timezone":"Europe/Bucharest",
    "iso:country":"RO",
    "name:bel_x_preferred":[
        "\u0414\u043e\u0439\u043d\u0430"
    ],
    "name:bul_x_preferred":[
        "\u0414\u043e\u0439\u043d\u0430"
    ],
    "name:glg_x_preferred":[
        "Doin\u0103"
    ],
    "name:heb_x_preferred":[
        "\u05d3\u05d5\u05d9\u05e0\u05d4"
    ],
    "name:hrv_x_preferred":[
        "Doina"
    ],
    "name:hye_x_preferred":[
        "\u0534\u0578\u0575\u0576\u0561"
    ],
    "name:kir_x_preferred":[
        "\u0414\u043e\u0439\u043d\u0430"
    ],
    "name:kor_x_preferred":[
        "\ub3c4\uc774\ub098"
    ],
    "name:lit_x_preferred":[
        "Doina"
    ],
    "name:nld_x_preferred":[
        "Doina"
    ],
    "name:pol_x_preferred":[
        "Doina"
    ],
    "name:ron_x_preferred":[
        "Doin\u0103"
    ],
    "name:rus_x_preferred":[
        "\u0414\u043e\u0439\u043d\u0430"
    ],
    "name:spa_x_preferred":[
        "Doin\u0103"
    ],
    "name:uzb_x_preferred":[
        "Doyna"
    ],
    "name:zho_x_preferred":[
        "\u591a\u4f9d\u5a1c"
    ],
    "wof:name":"Doina",
    "wof:placetype":"locality",
    "wof:population":564
},
  "geometry": {"coordinates":[27.19614,47.5424],"type":"Point"}
}