{
  "type": "Feature",
  "properties": {
    "gn:admin1_code":"11",
    "gn:admin2_code":"49545",
    "gn:asciiname":"Balaia",
    "gn:country_code":"RO",
    "gn:dem":71,
    "gn:feature_class":"P",
    "gn:feature_code":"PPL",
    "gn:name":"B\u0103laia",
    "gn:population":219,
    "gn:timezone":"Europe/Bucharest",
    "iso:country":"RO",
    "wof:name":"Balaia",
    "wof:placetype":"locality",
    "wof:population":219
},
  "geometry": {"coordinates":[26.82943,45.01323],"type":"Point"}
}