{
  "type": "Feature",
  "properties": {
    "gn:admin1_code":"40",
    "gn:admin2_code":"175983.0",
    "gn:asciiname":"Trestia",
    "gn:country_code":"RO",
    "gn:dem":416,
    "gn:feature_class":"P",
    "gn:feature_code":"PPL",
    "gn:name":"Trestia",
    "gn:population":212,
    "gn:timezone":"Europe/Bucharest",
    "iso:country":"RO",
    "name:ceb_x_preferred":[
        "Trestia"
    ],
    "name:deu_x_preferred":[
        "Trestia"
    ],
    "name:epo_x_preferred":[
        "Trestia"
    ],
    "name:hun_x_preferred":[
        "Trestia"
    ],
    "name:ron_x_preferred":[
        "Trestia"
    ],
    "name:srp_x_preferred":[
        "\u0422\u0440\u0435\u0441\u0442\u0438\u0458\u0430"
    ],
    "wof:name":"Trestia",
    "wof:placetype":"locality",
    "wof:population":212
},
  "geometry": {"coordinates":[26.85815,45.61087],"type":"Point"}
}