{
  "type": "Feature",
  "properties": {
    "iso:country":"RO",
    "name:ron_x_preferred":[
        "Dob\u0103e\u0219"
    ],
    "name:rum_x_colloquial":[
        "Dobaes"
    ],
    "qs:gn_fcode":"PPLX",
    "qs:gn_local":0,
    "qs:gn_namadm1":"00",
    "qs:gn_name":"Dob\u0103e\u015f",
    "qs:local_max":284,
    "qs:local_sum":363,
    "qs:localhoods":3,
    "qs:name":"Dob\u0103e\u0219",
    "qs:name_adm0":"Rom\u00e2nia",
    "qs:name_adm1":"Maramures",
    "qs:name_local":"Sighetu Marma\u021biei",
    "qs:photo_max":57,
    "qs:photo_sum":60,
    "qs:placetype":"Suburb",
    "qs:quad_count":4,
    "qs:woe_adm0":23424933,
    "qs:woe_adm1":2346638,
    "qs:woe_adm2":0,
    "qs:woe_lau":0,
    "qs:woe_local":880266,
    "qs:woe_ver":"7.10.0",
    "wof:lang":[
        "rum"
    ],
    "wof:name":"Dob\u0103e\u0219",
    "wof:placetype":"neighbourhood"
},
  "geometry": {"coordinates":[23.898619,47.928067],"type":"Point"}
}