{
  "type": "Feature",
  "properties": {
    "gn:admin1_code":"03",
    "gn:admin2_code":"13819.0",
    "gn:asciiname":"Dumiresti",
    "gn:country_code":"RO",
    "gn:dem":616,
    "gn:feature_class":"P",
    "gn:feature_code":"PPL",
    "gn:name":"Dumire\u0219ti",
    "gn:population":91,
    "gn:timezone":"Europe/Bucharest",
    "iso:country":"RO",
    "wof:name":"Dumiresti",
    "wof:placetype":"locality",
    "wof:population":91
},
  "geometry": {"coordinates":[24.69768,45.24817],"type":"Point"}
}