{
  "type": "Feature",
  "properties": {
    "gn:admin1_code":"36",
    "gn:admin2_code":"157497.0",
    "gn:asciiname":"Iosif",
    "gn:cc2":"RO",
    "gn:country_code":"RO",
    "gn:dem":85,
    "gn:feature_class":"P",
    "gn:feature_code":"PPL",
    "gn:name":"Iosif",
    "gn:population":283,
    "gn:timezone":"Europe/Bucharest",
    "iso:country":"RO",
    "name:jpn_x_preferred":[
        "\u30e8\u30b7\u30d5"
    ],
    "name:lav_x_preferred":[
        "J\u0101zeps"
    ],
    "name:rus_x_preferred":[
        "\u0418\u043e\u0441\u0438\u0444"
    ],
    "name:und_x_variant":[
        "Conacu Iosif",
        "J\u00f3zsefsz\u00e1ll\u00e1s",
        "Conacul Iosif",
        "Iosif"
    ],
    "wof:name":"Iosif",
    "wof:placetype":"locality",
    "wof:population":283
},
  "geometry": {"coordinates":[21.27826,45.56939000000001],"type":"Point"}
}