{
  "type": "Feature",
  "properties": {
    "gn:admin1_code":"34",
    "gn:admin2_code":"146799.0",
    "gn:asciiname":"Fetesti",
    "gn:country_code":"RO",
    "gn:dem":364,
    "gn:feature_class":"P",
    "gn:feature_code":"PPL",
    "gn:name":"Fete\u0219ti",
    "gn:population":590,
    "gn:timezone":"Europe/Bucharest",
    "iso:country":"RO",
    "wof:name":"Fetesti",
    "wof:placetype":"locality",
    "wof:population":590
},
  "geometry": {"coordinates":[26.34103,47.70812],"type":"Point"}
}