{
  "type": "Feature",
  "properties": {
    "gn:gn_country":"RO",
    "gn:gn_fcode":"PPL",
    "gn:gn_pop":0,
    "iso:country":"RO",
    "qs_pg:aaroncc":"RO",
    "qs_pg:gn_country":"RO",
    "qs_pg:gn_fcode":"PPL",
    "qs_pg:gn_pop":0,
    "qs_pg:name":"Od\u0103ile",
    "qs_pg:name_adm0":"Rom\u00e2nia",
    "qs_pg:name_adm1":"Ilfov",
    "qs_pg:photos":92,
    "qs_pg:photos_1k":19,
    "qs_pg:photos_9k":1,
    "qs_pg:photos_9r":3,
    "qs_pg:photos_all":92,
    "qs_pg:photos_sr":3,
    "qs_pg:pop_sr":0,
    "qs_pg:qs_pg_placetype":"locality",
    "qs_pg:qs_pg_placetype_gp":"Town",
    "qs_pg:woe_adm0":23424933,
    "woe:adm0_id":23424933,
    "woe:name_adm0":"Rom\u00e2nia",
    "woe:name_adm1":"Ilfov",
    "woe:placetype":"Town",
    "wof:name":"Od\u0103ile",
    "wof:placetype":"locality"
},
  "geometry": {"coordinates":[26.05,44.53333],"type":"Point"}
}