{
  "type": "Feature",
  "properties": {
    "gn:gn_country":"RO",
    "gn:gn_fcode":"PPL",
    "gn:gn_pop":0,
    "iso:country":"RO",
    "name:ceb_x_preferred":[
        "Comuna Od\u0103ile"
    ],
    "name:ita_x_preferred":[
        "Od\u0103ile"
    ],
    "name:msa_x_preferred":[
        "Od\u0103ile"
    ],
    "name:nld_x_preferred":[
        "Od\u0103ile"
    ],
    "name:por_x_preferred":[
        "Od\u0103ile"
    ],
    "name:ron_x_preferred":[
        "Comuna Od\u0103ile"
    ],
    "name:srp_x_preferred":[
        "\u041e\u043f\u0448\u0442\u0438\u043d\u0430 \u041e\u0434\u0430\u0438\u043b\u0435"
    ],
    "name:ukr_x_preferred":[
        "\u041e\u0434\u0435\u0439\u043b\u0435"
    ],
    "name:vie_x_preferred":[
        "Odaile"
    ],
    "name:vol_x_preferred":[
        "Od\u0103ile"
    ],
    "name:zho_x_preferred":[
        "\u5967\u5fb7\u4f0a\u840a\u9109"
    ],
    "qs_pg:aaroncc":"RO",
    "qs_pg:gn_country":"RO",
    "qs_pg:gn_fcode":"PPL",
    "qs_pg:gn_pop":0,
    "qs_pg:name":"Od\u0103ile",
    "qs_pg:name_adm0":"Rom\u00e2nia",
    "qs_pg:name_adm1":"Ilfov",
    "qs_pg:photos":92,
    "qs_pg:photos_1k":19,
    "qs_pg:photos_9k":1,
    "qs_pg:photos_9r":3,
    "qs_pg:photos_all":92,
    "qs_pg:photos_sr":3,
    "qs_pg:pop_sr":0,
    "qs_pg:qs_pg_placetype":"locality",
    "qs_pg:qs_pg_placetype_gp":"Town",
    "qs_pg:woe_adm0":23424933,
    "woe:adm0_id":23424933,
    "woe:name_adm0":"Rom\u00e2nia",
    "woe:name_adm1":"Ilfov",
    "woe:placetype":"Town",
    "wof:name":"Od\u0103ile",
    "wof:placetype":"locality"
},
  "geometry": {"coordinates":[26.05,44.53333],"type":"Point"}
}