{
  "type": "Feature",
  "properties": {
    "gn:admin1_code":"05",
    "gn:admin2_code":"26582.0",
    "gn:asciiname":"Rontau",
    "gn:country_code":"RO",
    "gn:dem":175,
    "gn:feature_class":"P",
    "gn:feature_code":"PPL",
    "gn:name":"Ront\u0103u",
    "gn:population":389,
    "gn:timezone":"Europe/Bucharest",
    "iso:country":"RO",
    "name:und_x_variant":[
        "Ront\u0103u"
    ],
    "wof:name":"Rontau",
    "wof:placetype":"locality",
    "wof:population":389
},
  "geometry": {"coordinates":[21.99835,47.00249],"type":"Point"}
}