{
  "type": "Feature",
  "properties": {
    "gn:admin1_code":"26",
    "gn:admin2_code":"112129.0",
    "gn:asciiname":"Peri",
    "gn:cc2":"RO",
    "gn:country_code":"RO",
    "gn:dem":259,
    "gn:feature_class":"P",
    "gn:feature_code":"PPL",
    "gn:name":"Peri",
    "gn:population":468,
    "gn:timezone":"Europe/Bucharest",
    "iso:country":"RO",
    "name:ara_x_preferred":[
        "\u062d\u0648\u0631\u064a\u0629"
    ],
    "name:bak_x_preferred":[
        "\u0411\u04d9\u0440\u0435\u0439"
    ],
    "name:ceb_x_preferred":[
        "Pari"
    ],
    "name:deu_x_preferred":[
        "Pari"
    ],
    "name:fas_x_preferred":[
        "\u067e\u0631\u06cc"
    ],
    "name:fra_x_preferred":[
        "P\u00e9ri"
    ],
    "name:ind_x_preferred":[
        "Peri"
    ],
    "name:kaz_x_preferred":[
        "\u041f\u0435\u0440\u0456"
    ],
    "name:nor_x_preferred":[
        "Peri"
    ],
    "name:rus_x_preferred":[
        "\u041f\u0435\u0440\u0438"
    ],
    "name:spa_x_preferred":[
        "Peri"
    ],
    "name:swe_x_preferred":[
        "Peri"
    ],
    "name:tgl_x_preferred":[
        "Pari"
    ],
    "name:ukr_x_preferred":[
        "\u041f\u0435\u0440\u0456"
    ],
    "name:und_x_variant":[
        "Perii",
        "Peri"
    ],
    "name:uzb_x_preferred":[
        "Pari"
    ],
    "wof:name":"Peri",
    "wof:placetype":"locality",
    "wof:population":468
},
  "geometry": {"coordinates":[22.89476,44.65705],"type":"Point"}
}