{
  "type": "Feature",
  "properties": {
    "gn:admin1_code":"05",
    "gn:admin2_code":"31011.0",
    "gn:asciiname":"Hodos",
    "gn:country_code":"RO",
    "gn:dem":106,
    "gn:feature_class":"P",
    "gn:feature_code":"PPL",
    "gn:name":"Hodo\u0219",
    "gn:population":744,
    "gn:timezone":"Europe/Bucharest",
    "iso:country":"RO",
    "wof:name":"Hodos",
    "wof:placetype":"locality",
    "wof:population":744
},
  "geometry": {"coordinates":[21.98495,47.22488],"type":"Point"}
}