{
  "type": "Feature",
  "properties": {
    "gn:admin1_code":"05",
    "gn:admin2_code":"31011.0",
    "gn:asciiname":"Hodos",
    "gn:country_code":"RO",
    "gn:dem":106,
    "gn:feature_class":"P",
    "gn:feature_code":"PPL",
    "gn:name":"Hodo\u0219",
    "gn:population":744,
    "gn:timezone":"Europe/Bucharest",
    "iso:country":"RO",
    "name:ceb_x_preferred":[
        "Hodos"
    ],
    "name:deu_x_preferred":[
        "Hodos"
    ],
    "name:hun_x_preferred":[
        "Hodos"
    ],
    "name:nld_x_preferred":[
        "Hodos"
    ],
    "name:ron_x_preferred":[
        "Hodo\u0219"
    ],
    "name:rus_x_preferred":[
        "\u0425\u043e\u0434\u043e\u0448"
    ],
    "name:srp_x_preferred":[
        "\u0425\u043e\u0434\u043e\u0448"
    ],
    "name:ukr_x_preferred":[
        "\u0425\u043e\u0434\u043e\u0448"
    ],
    "wof:name":"Hodos",
    "wof:placetype":"locality",
    "wof:population":744
},
  "geometry": {"coordinates":[21.98495,47.22488],"type":"Point"}
}