{
  "type": "Feature",
  "properties": {
    "gn:admin1_code":"07",
    "gn:admin2_code":"36373.0",
    "gn:asciiname":"Popeni",
    "gn:country_code":"RO",
    "gn:dem":169,
    "gn:feature_class":"P",
    "gn:feature_code":"PPL",
    "gn:name":"Popeni",
    "gn:population":251,
    "gn:timezone":"Europe/Bucharest",
    "iso:country":"RO",
    "name:ceb_x_preferred":[
        "Popeni"
    ],
    "name:deu_x_preferred":[
        "Popeni"
    ],
    "name:ron_x_preferred":[
        "Popeni"
    ],
    "name:srp_x_preferred":[
        "\u041f\u043e\u043f\u0435\u043d\u0438"
    ],
    "name:ukr_x_preferred":[
        "\u041f\u043e\u043f\u0435\u043d\u044c"
    ],
    "wof:name":"Popeni",
    "wof:placetype":"locality",
    "wof:population":251
},
  "geometry": {"coordinates":[26.49125,47.84414],"type":"Point"}
}