{
  "type": "Feature",
  "properties": {
    "gn:admin1_code":"07",
    "gn:admin2_code":"36373.0",
    "gn:asciiname":"Popeni",
    "gn:country_code":"RO",
    "gn:dem":169,
    "gn:feature_class":"P",
    "gn:feature_code":"PPL",
    "gn:name":"Popeni",
    "gn:population":251,
    "gn:timezone":"Europe/Bucharest",
    "iso:country":"RO",
    "wof:name":"Popeni",
    "wof:placetype":"locality",
    "wof:population":251
},
  "geometry": {"coordinates":[26.49125,47.84414],"type":"Point"}
}