{
  "type": "Feature",
  "properties": {
    "gn:admin1_code":"12",
    "gn:admin2_code":"52160.0",
    "gn:asciiname":"Studena",
    "gn:country_code":"RO",
    "gn:dem":694,
    "gn:feature_class":"P",
    "gn:feature_code":"PPL",
    "gn:name":"Studena",
    "gn:population":72,
    "gn:timezone":"Europe/Bucharest",
    "iso:country":"RO",
    "name:bos_x_preferred":[
        "Studena"
    ],
    "name:ceb_x_preferred":[
        "Studena"
    ],
    "name:eus_x_preferred":[
        "Studena"
    ],
    "name:fra_x_preferred":[
        "Studena"
    ],
    "name:hrv_x_preferred":[
        "Studena"
    ],
    "name:slv_x_preferred":[
        "Studena"
    ],
    "name:swe_x_preferred":[
        "Studena"
    ],
    "wof:name":"Studena",
    "wof:placetype":"locality",
    "wof:population":72
},
  "geometry": {"coordinates":[22.46169,45.06461],"type":"Point"}
}