{
  "type": "Feature",
  "properties": {
    "gn:gn_country":"RO",
    "gn:gn_fcode":"PPLA2",
    "gn:gn_pop":2606,
    "gn:population":2606,
    "iso:country":"RO",
    "name:dut_x_preferred":[
        "Lalo\u0219u"
    ],
    "name:eng_x_preferred":[
        "Lalo\u0219u"
    ],
    "name:epo_x_preferred":[
        "Lalo\u0219u"
    ],
    "name:fre_x_preferred":[
        "Lalo\u0219u"
    ],
    "name:ita_x_preferred":[
        "Lalo\u0219u"
    ],
    "name:may_x_preferred":[
        "Lalo\u0219u"
    ],
    "name:por_x_preferred":[
        "Lalo\u0219u"
    ],
    "name:rum_x_preferred":[
        "Lalo\u0219u"
    ],
    "name:ukr_x_preferred":[
        "\u041b\u0430\u043b\u043e\u0448\u0443"
    ],
    "name:unk_x_variant":[
        "Lalo\u015ful"
    ],
    "name:vie_x_preferred":[
        "Lalosu"
    ],
    "qs_pg:aaroncc":"RO",
    "qs_pg:gn_country":"RO",
    "qs_pg:gn_fcode":"PPLA2",
    "qs_pg:gn_pop":2606,
    "qs_pg:name":"Lalo\u015fu",
    "qs_pg:photos_9r":0,
    "qs_pg:photos_sr":0,
    "qs_pg:pop_sr":4,
    "qs_pg:qs_pg_placetype":"locality",
    "wof:name":"Lalo\u015fu",
    "wof:placetype":"locality",
    "wof:population":2606
},
  "geometry": {"coordinates":[24.01667,44.55],"type":"Point"}
}