{
  "type": "Feature",
  "properties": {
    "gn:population":1231,
    "iso:country":"RO",
    "name:eng_x_preferred":[
        "Poieni"
    ],
    "name:fra_x_preferred":[
        "Poieni"
    ],
    "name:ita_x_preferred":[
        "Poieni"
    ],
    "name:nld_x_preferred":[
        "Poieni"
    ],
    "name:ron_x_preferred":[
        "Poieni"
    ],
    "name:ukr_x_preferred":[
        "\u041f\u043e\u0454\u043d\u044c"
    ],
    "qs:a0":"Rom\u00e2nia",
    "qs:a1":"*Neamt",
    "qs:a1r":"0",
    "qs:adm0":"Rom\u00e2nia",
    "qs:la_lc":"*",
    "qs:level":"locality",
    "qs:loc":"Poieni",
    "qs:loc_alt":"Poieni",
    "qs:pop":0,
    "qs:type":"buffered point",
    "wof:name":"Poieni",
    "wof:placetype":"locality",
    "wof:population":1231
},
  "geometry": {"coordinates":[26.405107,46.834927],"type":"Point"}
}