{
  "type": "Feature",
  "properties": {
    "gn:admin1_code":"29",
    "gn:admin2_code":"126585.0",
    "gn:asciiname":"Pestra",
    "gn:country_code":"RO",
    "gn:dem":66,
    "gn:feature_class":"P",
    "gn:feature_code":"PPL",
    "gn:name":"Pestra",
    "gn:population":668,
    "gn:timezone":"Europe/Bucharest",
    "iso:country":"RO",
    "wof:name":"Pestra",
    "wof:placetype":"locality",
    "wof:population":668
},
  "geometry": {"coordinates":[24.53036,44.12315],"type":"Point"}
}