{
  "type": "Feature",
  "properties": {
    "gn:admin1_code":"39",
    "gn:admin2_code":"168791",
    "gn:asciiname":"Bercioiu",
    "gn:cc2":"RO",
    "gn:country_code":"RO",
    "gn:dem":287,
    "gn:feature_class":"P",
    "gn:feature_code":"PPL",
    "gn:name":"Bercioiu",
    "gn:population":358,
    "gn:timezone":"Europe/Bucharest",
    "iso:country":"RO",
    "name:und_x_variant":[
        "Bercioiul",
        "Bercioiu"
    ],
    "wof:name":"Bercioiu",
    "wof:placetype":"locality",
    "wof:population":358
},
  "geometry": {"coordinates":[24.31752,45.00298],"type":"Point"}
}