{
  "type": "Feature",
  "properties": {
    "gn:admin1_code":"39",
    "gn:admin2_code":"168452.0",
    "gn:asciiname":"Vasilati",
    "gn:country_code":"RO",
    "gn:dem":212,
    "gn:feature_class":"P",
    "gn:feature_code":"PPL",
    "gn:name":"Vasila\u0163i",
    "gn:population":0,
    "gn:timezone":"Europe/Bucharest",
    "iso:country":"RO",
    "wof:name":"Vasilati",
    "wof:placetype":"locality"
},
  "geometry": {"coordinates":[23.91667,44.68333],"type":"Point"}
}