{
  "type": "Feature",
  "properties": {
    "gn:admin1_code":"13",
    "gn:admin2_code":"56568.0",
    "gn:asciiname":"Dumbrava",
    "gn:cc2":"RO",
    "gn:country_code":"RO",
    "gn:dem":639,
    "gn:feature_class":"P",
    "gn:feature_code":"PPL",
    "gn:name":"Dumbrava",
    "gn:population":419,
    "gn:timezone":"Europe/Bucharest",
    "iso:country":"RO",
    "name:und_x_variant":[
        "Dumbr\u0103vu",
        "Dumbrava"
    ],
    "wof:name":"Dumbrava",
    "wof:placetype":"locality",
    "wof:population":419
},
  "geometry": {"coordinates":[23.21763,46.82502],"type":"Point"}
}