{
  "type": "Feature",
  "properties": {
    "gn:admin1_code":"13",
    "gn:admin2_code":"56568.0",
    "gn:asciiname":"Dumbrava",
    "gn:cc2":"RO",
    "gn:country_code":"RO",
    "gn:dem":639,
    "gn:feature_class":"P",
    "gn:feature_code":"PPL",
    "gn:name":"Dumbrava",
    "gn:population":419,
    "gn:timezone":"Europe/Bucharest",
    "iso:country":"RO",
    "name:ceb_x_preferred":[
        "Dumbrava"
    ],
    "name:deu_x_preferred":[
        "Dumbrava"
    ],
    "name:epo_x_preferred":[
        "Dumbrava"
    ],
    "name:fra_x_preferred":[
        "Dumbrava"
    ],
    "name:hun_x_preferred":[
        "Dumbrava"
    ],
    "name:ita_x_preferred":[
        "Dumbrava"
    ],
    "name:nld_x_preferred":[
        "Dumbrava"
    ],
    "name:ron_x_preferred":[
        "Dumbrava"
    ],
    "name:srp_x_preferred":[
        "\u0414\u0443\u043c\u0431\u0440\u0430\u0432\u0430"
    ],
    "name:swe_x_preferred":[
        "Dumbrava"
    ],
    "name:und_x_variant":[
        "Dumbr\u0103vu",
        "Dumbrava"
    ],
    "name:vol_x_preferred":[
        "Dumbrava"
    ],
    "wof:name":"Dumbrava",
    "wof:placetype":"locality",
    "wof:population":419
},
  "geometry": {"coordinates":[23.21763,46.82502],"type":"Point"}
}