{
  "type": "Feature",
  "properties": {
    "gn:admin1_code":"34",
    "gn:admin2_code":"149851.0",
    "gn:asciiname":"Pilugani",
    "gn:cc2":"RO",
    "gn:country_code":"RO",
    "gn:dem":869,
    "gn:feature_class":"P",
    "gn:feature_code":"PPL",
    "gn:name":"Pilugani",
    "gn:population":278,
    "gn:timezone":"Europe/Bucharest",
    "iso:country":"RO",
    "name:und_x_variant":[
        "Piluganii",
        "Pilugani"
    ],
    "wof:name":"Pilugani",
    "wof:placetype":"locality",
    "wof:population":278
},
  "geometry": {"coordinates":[25.16829,47.33163],"type":"Point"}
}