{
  "type": "Feature",
  "properties": {
    "gn:admin1_code":"27",
    "gn:admin2_code":"120511",
    "gn:asciiname":"Bara",
    "gn:cc2":"RO",
    "gn:country_code":"RO",
    "gn:dem":379,
    "gn:feature_class":"P",
    "gn:feature_code":"PPL",
    "gn:name":"B\u00e2ra",
    "gn:population":158,
    "gn:timezone":"Europe/Bucharest",
    "iso:country":"RO",
    "name:bos_x_preferred":[
        "Bara"
    ],
    "name:bul_x_preferred":[
        "\u0411\u0430\u0440\u0430"
    ],
    "name:cat_x_preferred":[
        "Bara"
    ],
    "name:ceb_x_preferred":[
        "Bara"
    ],
    "name:ces_x_preferred":[
        "Bara"
    ],
    "name:deu_x_preferred":[
        "Bara"
    ],
    "name:epo_x_preferred":[
        "Bara"
    ],
    "name:eus_x_preferred":[
        "Bara"
    ],
    "name:fra_x_preferred":[
        "Bara"
    ],
    "name:hye_x_preferred":[
        "\u0532\u0561\u0580\u0561"
    ],
    "name:ita_x_preferred":[
        "Bara"
    ],
    "name:jpn_x_preferred":[
        "\u30d0\u30e9"
    ],
    "name:lav_x_preferred":[
        "Bara"
    ],
    "name:lit_x_preferred":[
        "Bara"
    ],
    "name:nds_x_preferred":[
        "Bara"
    ],
    "name:nld_x_preferred":[
        "Bara"
    ],
    "name:pol_x_preferred":[
        "Bara"
    ],
    "name:por_x_preferred":[
        "Bara"
    ],
    "name:ron_x_preferred":[
        "B\u00e2ra"
    ],
    "name:rus_x_preferred":[
        "\u0411\u0430\u0440\u0430"
    ],
    "name:spa_x_preferred":[
        "Bara"
    ],
    "name:srp_x_preferred":[
        "\u0411\u0430\u0440\u0430"
    ],
    "name:swe_x_preferred":[
        "Bara"
    ],
    "name:tgl_x_preferred":[
        "Bara"
    ],
    "name:ukr_x_preferred":[
        "\u0411\u0430\u0440\u0430"
    ],
    "name:und_x_variant":[
        "Berekeresztur",
        "B\u00eera"
    ],
    "name:vie_x_preferred":[
        "Bara"
    ],
    "wof:name":"Bara",
    "wof:placetype":"locality",
    "wof:population":158
},
  "geometry": {"coordinates":[24.87262,46.57221],"type":"Point"}
}