{
  "type": "Feature",
  "properties": {
    "gn:admin1_code":"27",
    "gn:admin2_code":"120511",
    "gn:asciiname":"Bara",
    "gn:cc2":"RO",
    "gn:country_code":"RO",
    "gn:dem":379,
    "gn:feature_class":"P",
    "gn:feature_code":"PPL",
    "gn:name":"B\u00e2ra",
    "gn:population":158,
    "gn:timezone":"Europe/Bucharest",
    "iso:country":"RO",
    "name:ron_x_preferred":[
        "B\u00e2ra"
    ],
    "name:und_x_variant":[
        "Berekeresztur",
        "B\u00eera",
        "B\u00e2ra"
    ],
    "wof:name":"Bara",
    "wof:placetype":"locality",
    "wof:population":158
},
  "geometry": {"coordinates":[24.87262,46.57221],"type":"Point"}
}