{
  "type": "Feature",
  "properties": {
    "gn:admin1_code":"11",
    "gn:admin2_code":"45101.0",
    "gn:asciiname":"Plescoi",
    "gn:country_code":"RO",
    "gn:dem":159,
    "gn:feature_class":"P",
    "gn:feature_code":"PPL",
    "gn:name":"Ple\u0219coi",
    "gn:population":949,
    "gn:timezone":"Europe/Bucharest",
    "iso:country":"RO",
    "wof:name":"Plescoi",
    "wof:placetype":"locality",
    "wof:population":949
},
  "geometry": {"coordinates":[26.71777,45.27407],"type":"Point"}
}