{
  "type": "Feature",
  "properties": {
    "gn:admin1_code":"21",
    "gn:admin2_code":"88868.0",
    "gn:asciiname":"Curechiu",
    "gn:cc2":"RO",
    "gn:country_code":"RO",
    "gn:dem":426,
    "gn:feature_class":"P",
    "gn:feature_code":"PPL",
    "gn:name":"Curechiu",
    "gn:population":493,
    "gn:timezone":"Europe/Bucharest",
    "iso:country":"RO",
    "name:und_x_variant":[
        "Curechiul",
        "Curechiu"
    ],
    "wof:name":"Curechiu",
    "wof:placetype":"locality",
    "wof:population":493
},
  "geometry": {"coordinates":[22.96958,46.09782],"type":"Point"}
}