{
  "type": "Feature",
  "properties": {
    "gn:admin1_code":"03",
    "gn:admin2_code":"18411.0",
    "gn:asciiname":"Orodel",
    "gn:cc2":"RO",
    "gn:country_code":"RO",
    "gn:dem":159,
    "gn:feature_class":"P",
    "gn:feature_code":"PPL",
    "gn:name":"Orodel",
    "gn:population":210,
    "gn:timezone":"Europe/Bucharest",
    "iso:country":"RO",
    "name:und_x_variant":[
        "Orodelul",
        "Orodel"
    ],
    "wof:name":"Orodel",
    "wof:placetype":"locality",
    "wof:population":210
},
  "geometry": {"coordinates":[25.01831,44.51102],"type":"Point"}
}