{
  "type": "Feature",
  "properties": {
    "gn:admin1_code":"03",
    "gn:admin2_code":"18411.0",
    "gn:asciiname":"Orodel",
    "gn:cc2":"RO",
    "gn:country_code":"RO",
    "gn:dem":159,
    "gn:feature_class":"P",
    "gn:feature_code":"PPL",
    "gn:name":"Orodel",
    "gn:population":210,
    "gn:timezone":"Europe/Bucharest",
    "iso:country":"RO",
    "name:ceb_x_preferred":[
        "Comuna Orodel"
    ],
    "name:ita_x_preferred":[
        "Orodel"
    ],
    "name:msa_x_preferred":[
        "Orodel"
    ],
    "name:nld_x_preferred":[
        "Orodel"
    ],
    "name:por_x_preferred":[
        "Orodel"
    ],
    "name:ron_x_preferred":[
        "Comuna Orodel"
    ],
    "name:srp_x_preferred":[
        "\u041e\u043f\u0448\u0442\u0438\u043d\u0430 \u041e\u0440\u043e\u0434\u0435\u043b"
    ],
    "name:ukr_x_preferred":[
        "\u041e\u0440\u043e\u0434\u0435\u043b"
    ],
    "name:und_x_variant":[
        "Orodelul"
    ],
    "name:vie_x_preferred":[
        "Orodel"
    ],
    "name:vol_x_preferred":[
        "Orodel"
    ],
    "name:zho_x_preferred":[
        "\u5967\u7f85\u4ee3\u723e\u9109"
    ],
    "wof:name":"Orodel",
    "wof:placetype":"locality",
    "wof:population":210
},
  "geometry": {"coordinates":[25.01831,44.51102],"type":"Point"}
}