{
  "type": "Feature",
  "properties": {
    "gn:admin1_code":"38",
    "gn:admin2_code":"162791.0",
    "gn:asciiname":"Cepesti",
    "gn:country_code":"RO",
    "gn:dem":120,
    "gn:feature_class":"P",
    "gn:feature_code":"PPL",
    "gn:name":"Cepe\u0219ti",
    "gn:population":435,
    "gn:timezone":"Europe/Bucharest",
    "iso:country":"RO",
    "wof:name":"Cepesti",
    "wof:placetype":"locality",
    "wof:population":435
},
  "geometry": {"coordinates":[27.68207,46.38377],"type":"Point"}
}