{
  "type": "Feature",
  "properties": {
    "gn:admin1_code":"11",
    "gn:admin2_code":"46313",
    "gn:asciiname":"Buda Craciunesti",
    "gn:cc2":"RO",
    "gn:country_code":"RO",
    "gn:dem":240,
    "gn:feature_class":"P",
    "gn:feature_code":"PPL",
    "gn:name":"Buda Cr\u0103ciune\u0219ti",
    "gn:population":986,
    "gn:timezone":"Europe/Bucharest",
    "iso:country":"RO",
    "name:und_x_variant":[
        "Buda",
        "Buda-Cr\u0103ciune\u015fti"
    ],
    "wof:name":"Buda Craciunesti",
    "wof:placetype":"locality",
    "wof:population":986
},
  "geometry": {"coordinates":[26.38428,45.18121],"type":"Point"}
}