{
  "type": "Feature",
  "properties": {
    "gn:admin1_code":"02",
    "gn:admin2_code":"10453.0",
    "gn:asciiname":"Odvos",
    "gn:cc2":"RO",
    "gn:country_code":"RO",
    "gn:dem":147,
    "gn:feature_class":"P",
    "gn:feature_code":"PPL",
    "gn:name":"Odvo\u0219",
    "gn:population":493,
    "gn:timezone":"Europe/Bucharest",
    "iso:country":"RO",
    "name:und_x_variant":[
        "Odvas",
        "Odvo\u015f"
    ],
    "wof:name":"Odvos",
    "wof:placetype":"locality",
    "wof:population":493
},
  "geometry": {"coordinates":[21.82396,46.11215],"type":"Point"}
}