{
  "type": "Feature",
  "properties": {
    "gn:admin1_code":"19",
    "gn:admin2_code":"82047.0",
    "gn:asciiname":"Siacu",
    "gn:country_code":"RO",
    "gn:dem":202,
    "gn:feature_class":"P",
    "gn:feature_code":"PPL",
    "gn:name":"\u0218iacu",
    "gn:population":347,
    "gn:timezone":"Europe/Bucharest",
    "iso:country":"RO",
    "wof:name":"Siacu",
    "wof:placetype":"locality",
    "wof:population":347
},
  "geometry": {"coordinates":[23.1773,44.7559],"type":"Point"}
}