{
  "type": "Feature",
  "properties": {
    "gn:admin1_code":"03",
    "gn:admin2_code":"19392.0",
    "gn:asciiname":"Greaban",
    "gn:country_code":"RO",
    "gn:dem":453,
    "gn:feature_class":"P",
    "gn:feature_code":"PPL",
    "gn:name":"Greab\u0103n",
    "gn:population":48,
    "gn:timezone":"Europe/Bucharest",
    "iso:country":"RO",
    "wof:name":"Greaban",
    "wof:placetype":"locality",
    "wof:population":48
},
  "geometry": {"coordinates":[24.58488,44.90722],"type":"Point"}
}