{
  "type": "Feature",
  "properties": {
    "gn:admin1_code":"35",
    "gn:admin2_code":"152617.0",
    "gn:asciiname":"Stejaru",
    "gn:country_code":"RO",
    "gn:dem":98,
    "gn:feature_class":"P",
    "gn:feature_code":"PPL",
    "gn:name":"Stejaru",
    "gn:population":222,
    "gn:timezone":"Europe/Bucharest",
    "iso:country":"RO",
    "wof:name":"Stejaru",
    "wof:placetype":"locality",
    "wof:population":222
},
  "geometry": {"coordinates":[24.78259,44.02568],"type":"Point"}
}