{
  "type": "Feature",
  "properties": {
    "gn:admin1_code":"30",
    "gn:admin2_code":"134648.0",
    "gn:asciiname":"Nucsoara de Sus",
    "gn:cc2":"RO",
    "gn:country_code":"RO",
    "gn:dem":500,
    "gn:feature_class":"P",
    "gn:feature_code":"PPL",
    "gn:name":"Nuc\u0219oara de Sus",
    "gn:population":792,
    "gn:timezone":"Europe/Bucharest",
    "iso:country":"RO",
    "name:und_x_variant":[
        "Nuc\u015fora",
        "Nuc\u015foara",
        "Nuc\u015foara de Sus"
    ],
    "wof:name":"Nucsoara de Sus",
    "wof:placetype":"locality",
    "wof:population":792
},
  "geometry": {"coordinates":[26.11402,45.28129000000001],"type":"Point"}
}