{
  "type": "Feature",
  "properties": {
    "gn:admin1_code":"30",
    "gn:admin2_code":"133562",
    "gn:asciiname":"Bogdanesti",
    "gn:country_code":"RO",
    "gn:dem":365,
    "gn:feature_class":"P",
    "gn:feature_code":"PPL",
    "gn:name":"Bogd\u0103ne\u0219ti",
    "gn:population":91,
    "gn:timezone":"Europe/Bucharest",
    "iso:country":"RO",
    "wof:name":"Bogdanesti",
    "wof:placetype":"locality",
    "wof:population":91
},
  "geometry": {"coordinates":[26.06793,45.14232],"type":"Point"}
}