{
  "type": "Feature",
  "properties": {
    "gn:admin1_code":"39",
    "gn:admin2_code":"172812.0",
    "gn:asciiname":"Valea Babei",
    "gn:cc2":"RO",
    "gn:country_code":"RO",
    "gn:dem":509,
    "gn:feature_class":"P",
    "gn:feature_code":"PPL",
    "gn:name":"Valea Babei",
    "gn:population":315,
    "gn:timezone":"Europe/Bucharest",
    "iso:country":"RO",
    "name:und_x_variant":[
        "Valea Babe",
        "Valea Babi",
        "Valea-Babei",
        "Valea Babii"
    ],
    "wof:name":"Valea Babei",
    "wof:placetype":"locality",
    "wof:population":315
},
  "geometry": {"coordinates":[24.49828,45.18128],"type":"Point"}
}