{
  "type": "Feature",
  "properties": {
    "gn:admin1_code":"28",
    "gn:admin2_code":"124233.0",
    "gn:asciiname":"Butnaresti",
    "gn:country_code":"RO",
    "gn:dem":259,
    "gn:feature_class":"P",
    "gn:feature_code":"PPL",
    "gn:name":"Butn\u0103re\u0219ti",
    "gn:population":774,
    "gn:timezone":"Europe/Bucharest",
    "iso:country":"RO",
    "wof:name":"Butnaresti",
    "wof:placetype":"locality",
    "wof:population":774
},
  "geometry": {"coordinates":[26.79323,46.87302],"type":"Point"}
}