{
  "type": "Feature",
  "properties": {
    "gn:admin1_code":"32",
    "gn:admin2_code":"137443.0",
    "gn:asciiname":"Criseni",
    "gn:country_code":"RO",
    "gn:dem":120,
    "gn:feature_class":"P",
    "gn:feature_code":"PPL",
    "gn:name":"Cri\u0219eni",
    "gn:population":256,
    "gn:timezone":"Europe/Bucharest",
    "iso:country":"RO",
    "wof:name":"Criseni",
    "wof:placetype":"locality",
    "wof:population":256
},
  "geometry": {"coordinates":[22.68032,47.63931],"type":"Point"}
}