{
  "type": "Feature",
  "properties": {
    "gn:admin1_code":"27",
    "gn:admin2_code":"119803.0",
    "gn:asciiname":"Lechincioara",
    "gn:country_code":"RO",
    "gn:dem":313,
    "gn:feature_class":"P",
    "gn:feature_code":"PPL",
    "gn:name":"Lechincioara",
    "gn:population":116,
    "gn:timezone":"Europe/Bucharest",
    "iso:country":"RO",
    "wof:name":"Lechincioara",
    "wof:placetype":"locality",
    "wof:population":116
},
  "geometry": {"coordinates":[24.42009,46.6657],"type":"Point"}
}