{
  "type": "Feature",
  "properties": {
    "gn:admin1_code":"03",
    "gn:admin2_code":"13187.0",
    "gn:asciiname":"Mica",
    "gn:country_code":"RO",
    "gn:dem":328,
    "gn:feature_class":"P",
    "gn:feature_code":"PPL",
    "gn:name":"Mica",
    "gn:population":549,
    "gn:timezone":"Europe/Bucharest",
    "iso:country":"RO",
    "wof:name":"Mica",
    "wof:placetype":"locality",
    "wof:population":549
},
  "geometry": {"coordinates":[24.7578,44.88473],"type":"Point"}
}