{
  "type": "Feature",
  "properties": {
    "gn:admin1_code":"36",
    "gn:admin2_code":"157031.0",
    "gn:asciiname":"Jena",
    "gn:country_code":"RO",
    "gn:dem":147,
    "gn:feature_class":"P",
    "gn:feature_code":"PPL",
    "gn:name":"Jena",
    "gn:population":542,
    "gn:timezone":"Europe/Bucharest",
    "iso:country":"RO",
    "wof:name":"Jena",
    "wof:placetype":"locality",
    "wof:population":542
},
  "geometry": {"coordinates":[22.07507,45.60256],"type":"Point"}
}