{
  "type": "Feature",
  "properties": {
    "gn:admin1_code":"28",
    "gn:admin2_code":"124493.0",
    "gn:asciiname":"Cazaci",
    "gn:country_code":"RO",
    "gn:dem":432,
    "gn:feature_class":"P",
    "gn:feature_code":"PPL",
    "gn:name":"Cazaci",
    "gn:population":518,
    "gn:timezone":"Europe/Bucharest",
    "iso:country":"RO",
    "name:ceb_x_preferred":[
        "Cazaci"
    ],
    "name:deu_x_preferred":[
        "Cazaci"
    ],
    "name:ron_x_preferred":[
        "Cazaci"
    ],
    "name:srp_x_preferred":[
        "\u041a\u0430\u0437\u0430\u0447\u0438"
    ],
    "wof:name":"Cazaci",
    "wof:placetype":"locality",
    "wof:population":518
},
  "geometry": {"coordinates":[26.14311,46.85771],"type":"Point"}
}