{
  "type": "Feature",
  "properties": {
    "gn:gn_country":"RO",
    "gn:gn_fcode":"PPL",
    "gn:gn_pop":0,
    "gn:population":881,
    "iso:country":"RO",
    "name:dut_x_preferred":[
        "Curteni"
    ],
    "name:eng_x_preferred":[
        "Curteni"
    ],
    "name:epo_x_preferred":[
        "Curteni"
    ],
    "name:fre_x_preferred":[
        "Curteni"
    ],
    "name:hun_x_preferred":[
        "Udvarfalva"
    ],
    "name:rum_x_preferred":[
        "Curteni"
    ],
    "name:ukr_x_preferred":[
        "\u041a\u0443\u0440\u0442\u0435\u043d\u044c"
    ],
    "name:unk_x_variant":[
        "Udvarfalva"
    ],
    "qs_pg:aaroncc":"RO",
    "qs_pg:gn_country":"RO",
    "qs_pg:gn_fcode":"PPL",
    "qs_pg:gn_pop":0,
    "qs_pg:name":"Curteni",
    "qs_pg:name_adm0":"Rom\u00e2nia",
    "qs_pg:name_adm1":"Mures",
    "qs_pg:photos":137,
    "qs_pg:photos_1k":28,
    "qs_pg:photos_9k":1,
    "qs_pg:photos_9r":3,
    "qs_pg:photos_all":137,
    "qs_pg:photos_sr":3,
    "qs_pg:pop_sr":0,
    "qs_pg:qs_pg_placetype":"locality",
    "qs_pg:qs_pg_placetype_gp":"Town",
    "qs_pg:woe_adm0":23424933,
    "woe:adm0_id":23424933,
    "woe:name_adm0":"Rom\u00e2nia",
    "woe:name_adm1":"Mures",
    "woe:placetype":"Town",
    "wof:name":"Curteni",
    "wof:placetype":"locality",
    "wof:population":881
},
  "geometry": {"coordinates":[24.56667,46.58333],"type":"Point"}
}