{
  "type": "Feature",
  "properties": {
    "gn:admin1_code":"36",
    "gn:admin2_code":"159035.0",
    "gn:asciiname":"Sipet",
    "gn:cc2":"RO",
    "gn:country_code":"RO",
    "gn:dem":108,
    "gn:feature_class":"P",
    "gn:feature_code":"PPL",
    "gn:name":"\u0218ipet",
    "gn:population":856,
    "gn:timezone":"Europe/Bucharest",
    "iso:country":"RO",
    "name:und_x_variant":[
        "Sebed",
        "Sippet",
        "Schipet",
        "\u015eipet"
    ],
    "wof:name":"Sipet",
    "wof:placetype":"locality",
    "wof:population":856
},
  "geometry": {"coordinates":[21.40078,45.50728],"type":"Point"}
}