{
  "type": "Feature",
  "properties": {
    "gn:admin1_code":"36",
    "gn:admin2_code":"155957.0",
    "gn:asciiname":"Sarazani",
    "gn:country_code":"RO",
    "gn:dem":171,
    "gn:feature_class":"P",
    "gn:feature_code":"PPL",
    "gn:name":"S\u0103r\u0103zani",
    "gn:population":169,
    "gn:timezone":"Europe/Bucharest",
    "iso:country":"RO",
    "wof:name":"Sarazani",
    "wof:placetype":"locality",
    "wof:population":169
},
  "geometry": {"coordinates":[22.06262000000001,45.73775],"type":"Point"}
}