{
  "type": "Feature",
  "properties": {
    "gn:admin1_code":"26",
    "gn:admin2_code":"110232.0",
    "gn:asciiname":"Traian",
    "gn:country_code":"RO",
    "gn:dem":125,
    "gn:feature_class":"P",
    "gn:feature_code":"PPL",
    "gn:name":"Traian",
    "gn:population":764,
    "gn:timezone":"Europe/Bucharest",
    "iso:country":"RO",
    "wof:name":"Traian",
    "wof:placetype":"locality",
    "wof:population":764
},
  "geometry": {"coordinates":[22.85764,44.45961],"type":"Point"}
}