{
  "type": "Feature",
  "properties": {
    "gn:admin1_code":"02",
    "gn:admin2_code":"9798",
    "gn:asciiname":"Berechiu",
    "gn:cc2":"RO",
    "gn:country_code":"RO",
    "gn:dem":103,
    "gn:feature_class":"P",
    "gn:feature_code":"PPL",
    "gn:name":"Berechiu",
    "gn:population":991,
    "gn:timezone":"Europe/Bucharest",
    "iso:country":"RO",
    "name:ceb_x_preferred":[
        "Berechiu"
    ],
    "name:deu_x_preferred":[
        "Berechiu"
    ],
    "name:epo_x_preferred":[
        "Berechiu"
    ],
    "name:ron_x_preferred":[
        "Berechiu"
    ],
    "name:srp_x_preferred":[
        "\u0411\u0435\u0440\u0435\u043a\u0438\u0443"
    ],
    "name:und_x_variant":[
        "Berechiul"
    ],
    "wof:name":"Berechiu",
    "wof:placetype":"locality",
    "wof:population":991
},
  "geometry": {"coordinates":[21.84659,46.63914000000001],"type":"Point"}
}