{
  "type": "Feature",
  "properties": {
    "gn:admin1_code":"29",
    "gn:admin2_code":"126905.0",
    "gn:asciiname":"Gruiu",
    "gn:cc2":"RO",
    "gn:country_code":"RO",
    "gn:dem":333,
    "gn:feature_class":"P",
    "gn:feature_code":"PPL",
    "gn:name":"Gruiu",
    "gn:population":54,
    "gn:timezone":"Europe/Bucharest",
    "iso:country":"RO",
    "name:und_x_variant":[
        "Dealu Chinului",
        "Dealul Chinului",
        "Gruiu"
    ],
    "wof:name":"Gruiu",
    "wof:placetype":"locality",
    "wof:population":54
},
  "geometry": {"coordinates":[24.54132,44.75641],"type":"Point"}
}