{
  "type": "Feature",
  "properties": {
    "gn:admin1_code":"29",
    "gn:admin2_code":"126905.0",
    "gn:asciiname":"Gruiu",
    "gn:cc2":"RO",
    "gn:country_code":"RO",
    "gn:dem":333,
    "gn:feature_class":"P",
    "gn:feature_code":"PPL",
    "gn:name":"Gruiu",
    "gn:population":54,
    "gn:timezone":"Europe/Bucharest",
    "iso:country":"RO",
    "name:ceb_x_preferred":[
        "Comuna Gruiu"
    ],
    "name:ita_x_preferred":[
        "Gruiu"
    ],
    "name:msa_x_preferred":[
        "Gruiu"
    ],
    "name:nld_x_preferred":[
        "Gruiu"
    ],
    "name:pol_x_preferred":[
        "Gmina Gruiu"
    ],
    "name:por_x_preferred":[
        "Gruiu"
    ],
    "name:ron_x_preferred":[
        "Comuna Gruiu"
    ],
    "name:spa_x_preferred":[
        "Gruiu"
    ],
    "name:srp_x_preferred":[
        "\u041e\u043f\u0448\u0442\u0438\u043d\u0430 \u0413\u0440\u0443\u0458\u0443"
    ],
    "name:ukr_x_preferred":[
        "\u0413\u0440\u0443\u044e"
    ],
    "name:und_x_variant":[
        "Dealu Chinului",
        "Dealul Chinului",
        "Gruiu"
    ],
    "name:vie_x_preferred":[
        "Gruiu"
    ],
    "name:vol_x_preferred":[
        "Gruiu"
    ],
    "name:zho_x_preferred":[
        "\u683c\u9b6f\u5c24\u9109"
    ],
    "wof:name":"Gruiu",
    "wof:placetype":"locality",
    "wof:population":54
},
  "geometry": {"coordinates":[24.54132,44.75641],"type":"Point"}
}