{
  "type": "Feature",
  "properties": {
    "gn:admin1_code":"30",
    "gn:admin2_code":"131274.0",
    "gn:asciiname":"Pietrisu",
    "gn:cc2":"RO",
    "gn:country_code":"RO",
    "gn:dem":383,
    "gn:feature_class":"P",
    "gn:feature_code":"PPL",
    "gn:name":"Pietri\u0219u",
    "gn:population":338,
    "gn:timezone":"Europe/Bucharest",
    "iso:country":"RO",
    "name:und_x_variant":[
        "Vr\u0103jitoarea",
        "Pietri\u015fu"
    ],
    "wof:name":"Pietrisu",
    "wof:placetype":"locality",
    "wof:population":338
},
  "geometry": {"coordinates":[25.72719,45.11783],"type":"Point"}
}