{
  "type": "Feature",
  "properties": {
    "gn:admin1_code":"21",
    "gn:admin2_code":"87843.0",
    "gn:asciiname":"Poienita",
    "gn:cc2":"RO",
    "gn:country_code":"RO",
    "gn:dem":469,
    "gn:feature_class":"P",
    "gn:feature_code":"PPL",
    "gn:name":"Poieni\u021ba",
    "gn:population":99,
    "gn:timezone":"Europe/Bucharest",
    "iso:country":"RO",
    "name:und_x_variant":[
        "Valea Iepii",
        "Valea Iepi",
        "Poieni\u0163a"
    ],
    "wof:name":"Poienita",
    "wof:placetype":"locality",
    "wof:population":99
},
  "geometry": {"coordinates":[23.03092,46.09539],"type":"Point"}
}