{
  "type": "Feature",
  "properties": {
    "gn:admin1_code":"19",
    "gn:admin2_code":"81576.0",
    "gn:asciiname":"Suseni",
    "gn:country_code":"RO",
    "gn:dem":357,
    "gn:feature_class":"P",
    "gn:feature_code":"PPL",
    "gn:name":"Suseni",
    "gn:population":494,
    "gn:timezone":"Europe/Bucharest",
    "iso:country":"RO",
    "wof:name":"Suseni",
    "wof:placetype":"locality",
    "wof:population":494
},
  "geometry": {"coordinates":[23.20801,45.14088],"type":"Point"}
}