{
  "type": "Feature",
  "properties": {
    "gn:admin1_code":"04",
    "gn:admin2_code":"26118.0",
    "gn:asciiname":"Valea Salciei",
    "gn:cc2":"RO",
    "gn:country_code":"RO",
    "gn:dem":260,
    "gn:feature_class":"P",
    "gn:feature_code":"PPL",
    "gn:name":"Valea Salciei",
    "gn:population":58,
    "gn:timezone":"Europe/Bucharest",
    "iso:country":"RO",
    "name:ita_x_preferred":[
        "Valea Salciei"
    ],
    "name:msa_x_preferred":[
        "Valea Salciei"
    ],
    "name:nld_x_preferred":[
        "Valea Salciei"
    ],
    "name:por_x_preferred":[
        "Valea Salciei"
    ],
    "name:ron_x_preferred":[
        "Comuna Valea Salciei"
    ],
    "name:srp_x_preferred":[
        "\u041e\u043f\u0448\u0442\u0438\u043d\u0430 \u0412\u0430\u0459\u0430 \u0421\u0430\u043b\u0447\u0435\u0458"
    ],
    "name:ukr_x_preferred":[
        "\u0412\u0430\u043b\u044f-\u0421\u0430\u043b\u0447\u0456\u0454\u0439"
    ],
    "name:und_x_variant":[
        "Valea Satciei",
        "Valea Salcei",
        "Valea Salciei"
    ],
    "name:vie_x_preferred":[
        "Valea Salciei"
    ],
    "name:vol_x_preferred":[
        "Valea Salciei"
    ],
    "name:zho_x_preferred":[
        "\u85a9\u723e\u5207\u4f0a\u9109"
    ],
    "wof:name":"Valea Salciei",
    "wof:placetype":"locality",
    "wof:population":58
},
  "geometry": {"coordinates":[27.19398,46.45665],"type":"Point"}
}