{
  "type": "Feature",
  "properties": {
    "gn:admin1_code":"04",
    "gn:admin2_code":"26118.0",
    "gn:asciiname":"Valea Salciei",
    "gn:cc2":"RO",
    "gn:country_code":"RO",
    "gn:dem":260,
    "gn:feature_class":"P",
    "gn:feature_code":"PPL",
    "gn:name":"Valea Salciei",
    "gn:population":58,
    "gn:timezone":"Europe/Bucharest",
    "iso:country":"RO",
    "name:und_x_variant":[
        "Valea Satciei",
        "Valea Salcei",
        "Valea Salciei"
    ],
    "wof:name":"Valea Salciei",
    "wof:placetype":"locality",
    "wof:population":58
},
  "geometry": {"coordinates":[27.19398,46.45665],"type":"Point"}
}