{
  "type": "Feature",
  "properties": {
    "gn:admin1_code":"04",
    "gn:admin2_code":"26289.0",
    "gn:asciiname":"Tazlau de Jos",
    "gn:country_code":"RO",
    "gn:dem":514,
    "gn:feature_class":"P",
    "gn:feature_code":"PPL",
    "gn:name":"Tazl\u0103u de Jos",
    "gn:population":0,
    "gn:timezone":"Europe/Bucharest",
    "iso:country":"RO",
    "name:und_x_variant":[
        "Tasl\u0103ul de Jos",
        "Tazl\u0103u de Jos"
    ],
    "wof:lang_x_official":[
        "ron"
    ],
    "wof:lang_x_spoken":[
        "ron"
    ],
    "wof:name":"Tazlau de Jos",
    "wof:placetype":"locality"
},
  "geometry": {"coordinates":[26.46667,46.55],"type":"Point"}
}