{
  "type": "Feature",
  "properties": {
    "gn:admin1_code":"21",
    "gn:admin2_code":"89026.0",
    "gn:asciiname":"Cernisoara Florese",
    "gn:country_code":"RO",
    "gn:dem":642,
    "gn:feature_class":"P",
    "gn:feature_code":"PPL",
    "gn:name":"Cerni\u0219oara Florese",
    "gn:population":115,
    "gn:timezone":"Europe/Bucharest",
    "iso:country":"RO",
    "name:hun_x_preferred":[
        "Csernisorafloresza"
    ],
    "wof:name":"Cernisoara Florese",
    "wof:placetype":"locality",
    "wof:population":115
},
  "geometry": {"coordinates":[22.66667,45.68333],"type":"Point"}
}