{
  "type": "Feature",
  "properties": {
    "gn:admin1_code":"04",
    "gn:admin2_code":"23387.0",
    "gn:asciiname":"Sesuri",
    "gn:country_code":"RO",
    "gn:dem":349,
    "gn:feature_class":"P",
    "gn:feature_code":"PPL",
    "gn:name":"\u0218esuri",
    "gn:population":429,
    "gn:timezone":"Europe/Bucharest",
    "iso:country":"RO",
    "wof:name":"Sesuri",
    "wof:placetype":"locality",
    "wof:population":429
},
  "geometry": {"coordinates":[26.5715,46.5071],"type":"Point"}
}