{
  "type": "Feature",
  "properties": {
    "gn:admin1_code":"27",
    "gn:admin2_code":"115389",
    "gn:asciiname":"Istan-Tau",
    "gn:country_code":"RO",
    "gn:dem":350,
    "gn:feature_class":"P",
    "gn:feature_code":"PPL",
    "gn:name":"I\u0219tan-T\u0103u",
    "gn:population":128,
    "gn:timezone":"Europe/Bucharest",
    "iso:country":"RO",
    "name:hun_x_preferred":[
        "Istent\u00f3"
    ],
    "wof:name":"Istan-Tau",
    "wof:placetype":"locality",
    "wof:population":128
},
  "geometry": {"coordinates":[24.30101,46.65425],"type":"Point"}
}