{
  "type": "Feature",
  "properties": {
    "gn:admin1_code":"22",
    "gn:admin2_code":"93236.0",
    "gn:asciiname":"Gimbasani",
    "gn:cc2":"RO",
    "gn:country_code":"RO",
    "gn:dem":18,
    "gn:feature_class":"P",
    "gn:feature_code":"PPL",
    "gn:name":"Gimb\u0103\u015f\u0103ni",
    "gn:population":0,
    "gn:timezone":"Europe/Bucharest",
    "iso:country":"RO",
    "name:und_x_variant":[
        "Ghim B\u0103\u015fani"
    ],
    "wof:name":"Gimbasani",
    "wof:placetype":"locality"
},
  "geometry": {"coordinates":[27.4847,44.56051],"type":"Point"}
}