{
  "type": "Feature",
  "properties": {
    "gn:gn_country":"RO",
    "gn:gn_fcode":"PPLA2",
    "gn:gn_pop":2754,
    "gn:population":2754,
    "iso:country":"RO",
    "name:ceb_x_preferred":[
        "\u0218ieu\u021b"
    ],
    "name:eng_x_preferred":[
        "\u0218ieu\u021b"
    ],
    "name:epo_x_preferred":[
        "\u0218ieu\u021b"
    ],
    "name:fra_x_preferred":[
        "\u0218ieu\u021b"
    ],
    "name:hun_x_preferred":[
        "Kissaj\u00f3"
    ],
    "name:ita_x_preferred":[
        "\u0218ieu\u021b"
    ],
    "name:msa_x_preferred":[
        "\u0218ieu\u021b"
    ],
    "name:nld_x_preferred":[
        "\u0218ieu\u021b"
    ],
    "name:por_x_preferred":[
        "\u0218ieu\u021b"
    ],
    "name:ron_x_preferred":[
        "\u0218ieu\u021b"
    ],
    "name:sqi_x_preferred":[
        "\u0218ieu\u021b"
    ],
    "name:srp_x_preferred":[
        "\u0428\u0438\u0435\u0443\u0446"
    ],
    "name:ukr_x_preferred":[
        "\u0428\u0456\u0454\u0443\u0446"
    ],
    "name:unk_x_variant":[
        "Sieu"
    ],
    "name:vie_x_preferred":[
        "Sieut"
    ],
    "name:vol_x_preferred":[
        "\u0218ieu\u021b"
    ],
    "qs_pg:aaroncc":"RO",
    "qs_pg:gn_country":"RO",
    "qs_pg:gn_fcode":"PPLA2",
    "qs_pg:gn_pop":2754,
    "qs_pg:name":"\u015eieu\u0163",
    "qs_pg:photos_9r":0,
    "qs_pg:photos_sr":0,
    "qs_pg:pop_sr":4,
    "qs_pg:qs_pg_placetype":"locality",
    "wof:name":"\u015eieu\u0163",
    "wof:placetype":"locality",
    "wof:population":2754
},
  "geometry": {"coordinates":[24.65,46.98333],"type":"Point"}
}