{
  "type": "Feature",
  "properties": {
    "gn:admin1_code":"38",
    "gn:admin2_code":"162924.0",
    "gn:asciiname":"Rosiori",
    "gn:country_code":"RO",
    "gn:dem":167,
    "gn:feature_class":"P",
    "gn:feature_code":"PPL",
    "gn:name":"Ro\u0219iori",
    "gn:population":224,
    "gn:timezone":"Europe/Bucharest",
    "iso:country":"RO",
    "wof:name":"Rosiori",
    "wof:placetype":"locality",
    "wof:population":224
},
  "geometry": {"coordinates":[27.97674,46.79552],"type":"Point"}
}