{
  "type": "Feature",
  "properties": {
    "gn:admin1_code":"07",
    "gn:admin2_code":"39967.0",
    "gn:asciiname":"Talpa",
    "gn:country_code":"RO",
    "gn:dem":290,
    "gn:feature_class":"P",
    "gn:feature_code":"PPL",
    "gn:name":"Talpa",
    "gn:population":510,
    "gn:timezone":"Europe/Bucharest",
    "iso:country":"RO",
    "name:ceb_x_preferred":[
        "Talpa"
    ],
    "name:deu_x_preferred":[
        "Talpa"
    ],
    "name:ita_x_preferred":[
        "Talpa"
    ],
    "name:lit_x_preferred":[
        "Talpa"
    ],
    "name:nld_x_preferred":[
        "Talpa"
    ],
    "name:por_x_preferred":[
        "Talpa"
    ],
    "name:ron_x_preferred":[
        "Talpa"
    ],
    "name:rus_x_preferred":[
        "\u0422\u0430\u043b\u043f\u0430"
    ],
    "name:spa_x_preferred":[
        "Talpa"
    ],
    "name:srp_x_preferred":[
        "\u0422\u0430\u043b\u043f\u0430"
    ],
    "name:swe_x_preferred":[
        "Talpa"
    ],
    "name:ukr_x_preferred":[
        "\u0422\u0430\u043b\u043f\u0430"
    ],
    "name:zho_x_preferred":[
        "Talpa"
    ],
    "wof:name":"Talpa",
    "wof:placetype":"locality",
    "wof:population":510
},
  "geometry": {"coordinates":[26.2363,47.90194],"type":"Point"}
}