{
  "type": "Feature",
  "properties": {
    "gn:admin1_code":"07",
    "gn:admin2_code":"39967.0",
    "gn:asciiname":"Talpa",
    "gn:country_code":"RO",
    "gn:dem":290,
    "gn:feature_class":"P",
    "gn:feature_code":"PPL",
    "gn:name":"Talpa",
    "gn:population":510,
    "gn:timezone":"Europe/Bucharest",
    "iso:country":"RO",
    "wof:name":"Talpa",
    "wof:placetype":"locality",
    "wof:population":510
},
  "geometry": {"coordinates":[26.2363,47.90194],"type":"Point"}
}