{
  "type": "Feature",
  "properties": {
    "gn:admin1_code":"04",
    "gn:admin2_code":"21123.0",
    "gn:asciiname":"Leorzeni",
    "gn:country_code":"RO",
    "gn:dem":745,
    "gn:feature_class":"P",
    "gn:feature_code":"PPL",
    "gn:name":"Leorzeni",
    "gn:population":0,
    "gn:timezone":"Europe/Bucharest",
    "iso:country":"RO",
    "name:und_x_variant":[
        "Lespezi",
        "Leorzeni"
    ],
    "wof:lang_x_official":[
        "ron"
    ],
    "wof:lang_x_spoken":[
        "ron"
    ],
    "wof:name":"Leorzeni",
    "wof:placetype":"locality"
},
  "geometry": {"coordinates":[26.33333,46.43333],"type":"Point"}
}