{
  "type": "Feature",
  "properties": {
    "gn:admin1_code":"19",
    "gn:admin2_code":"80980.0",
    "gn:asciiname":"Nucetu",
    "gn:cc2":"RO",
    "gn:country_code":"RO",
    "gn:dem":162,
    "gn:feature_class":"P",
    "gn:feature_code":"PPL",
    "gn:name":"Nucetu",
    "gn:population":368,
    "gn:timezone":"Europe/Bucharest",
    "iso:country":"RO",
    "name:und_x_variant":[
        "Str\u00eemba",
        "Str\u00e2mba",
        "Racii de Str\u00eemba",
        "Nucetu"
    ],
    "wof:name":"Nucetu",
    "wof:placetype":"locality",
    "wof:population":368
},
  "geometry": {"coordinates":[23.2784,44.74861],"type":"Point"}
}