{
  "type": "Feature",
  "properties": {
    "gn:admin1_code":"31",
    "gn:admin2_code":"141134.0",
    "gn:asciiname":"Dobrocina",
    "gn:country_code":"RO",
    "gn:dem":228,
    "gn:feature_class":"P",
    "gn:feature_code":"PPL",
    "gn:name":"Dobrocina",
    "gn:population":195,
    "gn:timezone":"Europe/Bucharest",
    "iso:country":"RO",
    "wof:name":"Dobrocina",
    "wof:placetype":"locality",
    "wof:population":195
},
  "geometry": {"coordinates":[23.71706,47.26383],"type":"Point"}
}