{
  "type": "Feature",
  "properties": {
    "gn:admin1_code":"28",
    "gn:admin2_code":"121876.0",
    "gn:asciiname":"Craiesti",
    "gn:country_code":"RO",
    "gn:dem":167,
    "gn:feature_class":"P",
    "gn:feature_code":"PPL",
    "gn:name":"Cr\u0103ie\u0219ti",
    "gn:population":325,
    "gn:timezone":"Europe/Bucharest",
    "iso:country":"RO",
    "wof:name":"Craiesti",
    "wof:placetype":"locality",
    "wof:population":325
},
  "geometry": {"coordinates":[27.18276,46.85535],"type":"Point"}
}