{
  "type": "Feature",
  "properties": {
    "gn:admin1_code":"37",
    "gn:admin2_code":"160172.0",
    "gn:asciiname":"Ostrovu Tataru",
    "gn:country_code":"RO",
    "gn:dem":1,
    "gn:feature_class":"P",
    "gn:feature_code":"PPL",
    "gn:name":"Ostrovu T\u0103taru",
    "gn:population":0,
    "gn:timezone":"Europe/Bucharest",
    "iso:country":"RO",
    "wof:name":"Ostrovu Tataru",
    "wof:placetype":"locality"
},
  "geometry": {"coordinates":[29.23129,45.38797],"type":"Point"}
}