{
  "type": "Feature",
  "properties": {
    "gn:admin1_code":"38",
    "gn:admin2_code":"163486.0",
    "gn:asciiname":"Tulesti",
    "gn:country_code":"RO",
    "gn:dem":228,
    "gn:feature_class":"P",
    "gn:feature_code":"PPL",
    "gn:name":"Tule\u0219ti",
    "gn:population":209,
    "gn:timezone":"Europe/Bucharest",
    "iso:country":"RO",
    "wof:name":"Tulesti",
    "wof:placetype":"locality",
    "wof:population":209
},
  "geometry": {"coordinates":[27.33238,46.60314],"type":"Point"}
}