{
  "type": "Feature",
  "properties": {
    "iso:country":"RO",
    "name:azb_x_preferred":[
        "\u062f\u0627\u0631\u0645\u0627\u0646\u0634\u062a"
    ],
    "name:ceb_x_preferred":[
        "Ora\u0219 D\u0103rm\u0103ne\u0219ti"
    ],
    "name:deu_x_preferred":[
        "D\u0103rm\u0103ne\u0219ti"
    ],
    "name:eus_x_preferred":[
        "D\u0103rm\u0103ne\u0219ti"
    ],
    "name:fas_x_preferred":[
        "\u062f\u0627\u0631\u0645\u0627\u0646\u0634\u062a"
    ],
    "name:fra_x_preferred":[
        "D\u0103rm\u0103ne\u0219ti"
    ],
    "name:hun_x_preferred":[
        "Dorm\u00e1nfalva"
    ],
    "name:ind_x_preferred":[
        "D\u0103rm\u0103ne\u015fti"
    ],
    "name:ita_x_preferred":[
        "D\u0103rm\u0103ne\u0219ti"
    ],
    "name:lat_x_preferred":[
        "D\u0103rm\u0103ne\u0219ti"
    ],
    "name:min_x_preferred":[
        "D\u0103rm\u0103ne\u0219ti"
    ],
    "name:msa_x_preferred":[
        "D\u0103rm\u0103ne\u015fti"
    ],
    "name:nld_x_preferred":[
        "D\u0103rm\u0103ne\u0219ti"
    ],
    "name:pol_x_preferred":[
        "D\u0103rm\u0103ne\u0219ti"
    ],
    "name:por_x_preferred":[
        "D\u0103rm\u0103ne\u0219ti"
    ],
    "name:ron_x_preferred":[
        "D\u0103rm\u0103ne\u0219ti"
    ],
    "name:rus_x_preferred":[
        "\u0414\u044d\u0440\u043c\u044d\u043d\u0435\u0448\u0442\u0438"
    ],
    "name:spa_x_preferred":[
        "D\u0103rm\u0103ne\u0219ti"
    ],
    "name:srp_x_preferred":[
        "\u041e\u043f\u0448\u0442\u0438\u043d\u0430 \u0414\u0430\u0440\u043c\u0430\u043d\u0435\u0448\u0442\u0438"
    ],
    "name:tgk_x_preferred":[
        "\u0414\u044d\u0440\u043c\u044d\u043d\u0435\u0448\u0442\u0438"
    ],
    "name:ukr_x_preferred":[
        "\u0414\u0435\u0440\u043c\u0435\u043d\u0435\u0448\u0442\u044c"
    ],
    "name:vie_x_preferred":[
        "Darmanesti"
    ],
    "name:vie_x_variant":[
        "D\u0103rm\u0103ne\u0219ti"
    ],
    "name:zho_x_preferred":[
        "\u5fb7\u723e\u9ed8\u5167\u4ec0\u8482"
    ],
    "qs_pg:aaroncc":"RO",
    "qs_pg:name":"D\u0103rm\u0103ne\u0219ti",
    "qs_pg:name_adm0":"Rom\u00e2nia",
    "qs_pg:name_adm1":"Bacau",
    "qs_pg:photos":18,
    "qs_pg:photos_1k":4,
    "qs_pg:photos_9k":1,
    "qs_pg:photos_9r":1,
    "qs_pg:photos_all":18,
    "qs_pg:photos_sr":1,
    "qs_pg:pop_sr":0,
    "qs_pg:qs_pg_placetype":"locality",
    "qs_pg:qs_pg_placetype_gp":"Town",
    "qs_pg:woe_adm0":23424933,
    "woe:adm0_id":23424933,
    "woe:name_adm0":"Rom\u00e2nia",
    "woe:name_adm1":"Bacau",
    "woe:placetype":"Town",
    "wof:lang_x_official":[
        "ron"
    ],
    "wof:lang_x_spoken":[
        "ron"
    ],
    "wof:name":"D\u0103rm\u0103ne\u0219ti",
    "wof:placetype":"locality"
},
  "geometry": {"coordinates":[26.483299,46.369209],"type":"Point"}
}