{
  "type": "Feature",
  "properties": {
    "iso:country":"RO",
    "qs_pg:aaroncc":"RO",
    "qs_pg:name":"D\u0103rm\u0103ne\u0219ti",
    "qs_pg:name_adm0":"Rom\u00e2nia",
    "qs_pg:name_adm1":"Bacau",
    "qs_pg:photos":18,
    "qs_pg:photos_1k":4,
    "qs_pg:photos_9k":1,
    "qs_pg:photos_9r":1,
    "qs_pg:photos_all":18,
    "qs_pg:photos_sr":1,
    "qs_pg:pop_sr":0,
    "qs_pg:qs_pg_placetype":"locality",
    "qs_pg:qs_pg_placetype_gp":"Town",
    "qs_pg:woe_adm0":23424933,
    "woe:adm0_id":23424933,
    "woe:name_adm0":"Rom\u00e2nia",
    "woe:name_adm1":"Bacau",
    "woe:placetype":"Town",
    "wof:name":"D\u0103rm\u0103ne\u0219ti",
    "wof:placetype":"locality"
},
  "geometry": {"coordinates":[26.483299,46.369209],"type":"Point"}
}