{
  "type": "Feature",
  "properties": {
    "gn:admin1_code":"19",
    "gn:admin2_code":"79497.0",
    "gn:asciiname":"Granolea",
    "gn:country_code":"RO",
    "gn:dem":207,
    "gn:feature_class":"P",
    "gn:feature_code":"PPL",
    "gn:name":"Granolea",
    "gn:population":0,
    "gn:timezone":"Europe/Bucharest",
    "iso:country":"RO",
    "name:und_x_variant":[
        "Gramolea",
        "Granolea"
    ],
    "wof:name":"Granolea",
    "wof:placetype":"locality"
},
  "geometry": {"coordinates":[23.61667,44.73333],"type":"Point"}
}