{
  "type": "Feature",
  "properties": {
    "gn:admin1_code":"35",
    "gn:admin2_code":"152350",
    "gn:asciiname":"Antonesti",
    "gn:country_code":"RO",
    "gn:dem":86,
    "gn:feature_class":"P",
    "gn:feature_code":"PPL",
    "gn:name":"Antone\u0219ti",
    "gn:population":468,
    "gn:timezone":"Europe/Bucharest",
    "iso:country":"RO",
    "wof:name":"Antonesti",
    "wof:placetype":"locality",
    "wof:population":468
},
  "geometry": {"coordinates":[25.18395,44.11764],"type":"Point"}
}