{
  "type": "Feature",
  "properties": {
    "gn:admin1_code":"28",
    "gn:admin2_code":"121652.0",
    "gn:asciiname":"Paraul Pantei",
    "gn:country_code":"RO",
    "gn:dem":684,
    "gn:feature_class":"P",
    "gn:feature_code":"PPL",
    "gn:name":"P\u00e2r\u00e2ul P\u00e2ntei",
    "gn:population":539,
    "gn:timezone":"Europe/Bucharest",
    "iso:country":"RO",
    "name:und_x_variant":[
        "P\u00eer\u00eeul P\u00eentei"
    ],
    "wof:name":"Paraul Pantei",
    "wof:placetype":"locality",
    "wof:population":539
},
  "geometry": {"coordinates":[25.81667,47.16667],"type":"Point"}
}