{
  "type": "Feature",
  "properties": {
    "gn:admin1_code":"18",
    "gn:admin2_code":"75711.0",
    "gn:asciiname":"Traian",
    "gn:country_code":"RO",
    "gn:dem":21,
    "gn:feature_class":"P",
    "gn:feature_code":"PPL",
    "gn:name":"Traian",
    "gn:population":433,
    "gn:timezone":"Europe/Bucharest",
    "iso:country":"RO",
    "wof:name":"Traian",
    "wof:placetype":"locality",
    "wof:population":433
},
  "geometry": {"coordinates":[27.86823,45.42475],"type":"Point"}
}