{
  "type": "Feature",
  "properties": {
    "gn:admin1_code":"14",
    "gn:admin2_code":"62137.0",
    "gn:asciiname":"Ciobanita",
    "gn:cc2":"RO",
    "gn:country_code":"RO",
    "gn:dem":66,
    "gn:feature_class":"P",
    "gn:feature_code":"PPL",
    "gn:name":"Ciob\u0103ni\u021ba",
    "gn:population":365,
    "gn:timezone":"Europe/Bucharest",
    "iso:country":"RO",
    "name:und_x_variant":[
        "Agemier",
        "Agemler",
        "Ciob\u0103ni\u0163a"
    ],
    "wof:name":"Ciobanita",
    "wof:placetype":"locality",
    "wof:population":365
},
  "geometry": {"coordinates":[28.27877,44.01422],"type":"Point"}
}