{
  "type": "Feature",
  "properties": {
    "gn:admin1_code":"07",
    "gn:admin2_code":"35884.0",
    "gn:asciiname":"Silistea",
    "gn:country_code":"RO",
    "gn:dem":86,
    "gn:feature_class":"P",
    "gn:feature_code":"PPL",
    "gn:name":"Sili\u0219tea",
    "gn:population":313,
    "gn:timezone":"Europe/Bucharest",
    "iso:country":"RO",
    "wof:name":"Silistea",
    "wof:placetype":"locality",
    "wof:population":313
},
  "geometry": {"coordinates":[26.76228,47.71665],"type":"Point"}
}