{
  "type": "Feature",
  "properties": {
    "gn:admin1_code":"13",
    "gn:admin2_code":"56844.0",
    "gn:asciiname":"Hodai Boian",
    "gn:country_code":"RO",
    "gn:dem":396,
    "gn:feature_class":"P",
    "gn:feature_code":"PPL",
    "gn:name":"Hod\u0103i Boian",
    "gn:population":202,
    "gn:timezone":"Europe/Bucharest",
    "iso:country":"RO",
    "wof:name":"Hodai Boian",
    "wof:placetype":"locality",
    "wof:population":202
},
  "geometry": {"coordinates":[24.01187,46.64107],"type":"Point"}
}