{
  "type": "Feature",
  "properties": {
    "gn:admin1_code":"03",
    "gn:admin2_code":"19392.0",
    "gn:asciiname":"Candelesti",
    "gn:cc2":"RO",
    "gn:country_code":"RO",
    "gn:dem":412,
    "gn:feature_class":"P",
    "gn:feature_code":"PPL",
    "gn:name":"C\u00e2ndele\u015fti",
    "gn:population":0,
    "gn:timezone":"Europe/Bucharest",
    "iso:country":"RO",
    "name:und_x_variant":[
        "C\u00e2ndele\u015fti",
        "C\u00e2ndelele",
        "C\u00eendele\u015fti"
    ],
    "wof:name":"Candelesti",
    "wof:placetype":"locality"
},
  "geometry": {"coordinates":[24.55,44.86667],"type":"Point"}
}