{
  "type": "Feature",
  "properties": {
    "gn:admin1_code":"34",
    "gn:admin2_code":"149227.0",
    "gn:asciiname":"Corni",
    "gn:country_code":"RO",
    "gn:dem":247,
    "gn:feature_class":"P",
    "gn:feature_code":"PPL",
    "gn:name":"Corni",
    "gn:population":755,
    "gn:timezone":"Europe/Bucharest",
    "iso:country":"RO",
    "wof:name":"Corni",
    "wof:placetype":"locality",
    "wof:population":755
},
  "geometry": {"coordinates":[26.56126,47.47377],"type":"Point"}
}