{
  "type": "Feature",
  "properties": {
    "gn:admin1_code":"19",
    "gn:admin2_code":"78542.0",
    "gn:asciiname":"Luculesti",
    "gn:country_code":"RO",
    "gn:dem":456,
    "gn:feature_class":"P",
    "gn:feature_code":"PPL",
    "gn:name":"Lucule\u015fti",
    "gn:population":0,
    "gn:timezone":"Europe/Bucharest",
    "iso:country":"RO",
    "name:und_x_variant":[
        "Lecule\u015fti",
        "Lucule\u015fti"
    ],
    "wof:name":"Luculesti",
    "wof:placetype":"locality"
},
  "geometry": {"coordinates":[23.78333,45.08333],"type":"Point"}
}