{
  "type": "Feature",
  "properties": {
    "gn:admin1_code":"18",
    "gn:admin2_code":"77587",
    "gn:asciiname":"Visina",
    "gn:country_code":"RO",
    "gn:dem":268,
    "gn:feature_class":"P",
    "gn:feature_code":"PPL",
    "gn:name":"Vi\u0219ina",
    "gn:population":458,
    "gn:timezone":"Europe/Bucharest",
    "iso:country":"RO",
    "wof:name":"Visina",
    "wof:placetype":"locality",
    "wof:population":458
},
  "geometry": {"coordinates":[27.27391,45.99812],"type":"Point"}
}