{
  "type": "Feature",
  "properties": {
    "gn:admin1_code":"03",
    "gn:admin2_code":"20055.0",
    "gn:asciiname":"Huluba",
    "gn:country_code":"RO",
    "gn:dem":472,
    "gn:feature_class":"P",
    "gn:feature_code":"PPL",
    "gn:name":"Huluba",
    "gn:population":257,
    "gn:timezone":"Europe/Bucharest",
    "iso:country":"RO",
    "wof:name":"Huluba",
    "wof:placetype":"locality",
    "wof:population":257
},
  "geometry": {"coordinates":[25.05852,45.06787],"type":"Point"}
}