{
  "type": "Feature",
  "properties": {
    "gn:admin1_code":"11",
    "gn:admin2_code":"46439.0",
    "gn:asciiname":"Coltii de Jos",
    "gn:cc2":"RO",
    "gn:country_code":"RO",
    "gn:dem":522,
    "gn:feature_class":"P",
    "gn:feature_code":"PPL",
    "gn:name":"Col\u021bii de Jos",
    "gn:population":463,
    "gn:timezone":"Europe/Bucharest",
    "iso:country":"RO",
    "name:ita_x_preferred":[
        "Col\u0163i"
    ],
    "name:und_x_variant":[
        "Col\u0163i",
        "Col\u0163ii de Jos"
    ],
    "name:vol_x_preferred":[
        "Col\u0163i"
    ],
    "wof:name":"Coltii de Jos",
    "wof:placetype":"locality",
    "wof:population":463
},
  "geometry": {"coordinates":[26.38752,45.39305],"type":"Point"}
}