{
  "type": "Feature",
  "properties": {
    "iso:country":"RO",
    "wof:lang_x_official":[
        "ron"
    ],
    "wof:lang_x_spoken":[
        "ron"
    ],
    "wof:name":"Pajura",
    "wof:placetype":"neighbourhood"
},
  "geometry": {"coordinates":[26.048888,44.479721],"type":"Point"}
}