{
  "type": "Feature",
  "properties": {
    "iso:country":"RO",
    "wof:name":"Pajura",
    "wof:placetype":"neighbourhood"
},
  "geometry": {"coordinates":[26.04888835052764,44.47972092786445],"type":"Point"}
}