{
  "type": "Feature",
  "properties": {
    "gn:admin1_code":"38",
    "gn:admin2_code":"166315.0",
    "gn:asciiname":"Mantu",
    "gn:cc2":"RO",
    "gn:country_code":"RO",
    "gn:dem":139,
    "gn:feature_class":"P",
    "gn:feature_code":"PPL",
    "gn:name":"Mantu",
    "gn:population":50,
    "gn:timezone":"Europe/Bucharest",
    "iso:country":"RO",
    "name:deu_x_preferred":[
        "Mantu"
    ],
    "name:und_x_variant":[
        "Martine\u015ftii",
        "Mantul",
        "Man\u0163u"
    ],
    "wof:name":"Mantu",
    "wof:placetype":"locality",
    "wof:population":50
},
  "geometry": {"coordinates":[27.92999,46.73323],"type":"Point"}
}