{
  "type": "Feature",
  "properties": {
    "gn:admin1_code":"38",
    "gn:admin2_code":"166529.0",
    "gn:asciiname":"Coroiu",
    "gn:country_code":"RO",
    "gn:dem":56,
    "gn:feature_class":"P",
    "gn:feature_code":"PPL",
    "gn:name":"Coroiu",
    "gn:population":162,
    "gn:timezone":"Europe/Bucharest",
    "iso:country":"RO",
    "wof:name":"Coroiu",
    "wof:placetype":"locality",
    "wof:population":162
},
  "geometry": {"coordinates":[27.54429,46.10512],"type":"Point"}
}