{
  "type": "Feature",
  "properties": {
    "gn:admin1_code":"34",
    "gn:admin2_code":"146931",
    "gn:asciiname":"Gara",
    "gn:country_code":"RO",
    "gn:dem":317,
    "gn:feature_class":"P",
    "gn:feature_code":"PPL",
    "gn:name":"Gara",
    "gn:population":439,
    "gn:timezone":"Europe/Bucharest",
    "iso:country":"RO",
    "name:arg_x_preferred":[
        "Gara"
    ],
    "name:cat_x_preferred":[
        "Gara"
    ],
    "name:deu_x_preferred":[
        "Gara"
    ],
    "name:eus_x_preferred":[
        "Gara"
    ],
    "name:fra_x_preferred":[
        "Gara"
    ],
    "name:glg_x_preferred":[
        "Gara"
    ],
    "name:jpn_x_preferred":[
        "\u30ac\u30e9"
    ],
    "name:ltz_x_preferred":[
        "Gara"
    ],
    "name:nor_x_preferred":[
        "Gara"
    ],
    "name:spa_x_preferred":[
        "Gara"
    ],
    "name:swe_x_preferred":[
        "Gara"
    ],
    "wof:name":"Gara",
    "wof:placetype":"locality",
    "wof:population":439
},
  "geometry": {"coordinates":[26.04653,47.77609],"type":"Point"}
}