{
  "type": "Feature",
  "properties": {
    "gn:admin1_code":"16",
    "gn:admin2_code":"66081.0",
    "gn:asciiname":"Mereni",
    "gn:country_code":"RO",
    "gn:dem":157,
    "gn:feature_class":"P",
    "gn:feature_code":"PPL",
    "gn:name":"Mereni",
    "gn:population":242,
    "gn:timezone":"Europe/Bucharest",
    "iso:country":"RO",
    "wof:name":"Mereni",
    "wof:placetype":"locality",
    "wof:population":242
},
  "geometry": {"coordinates":[25.57777,44.65882],"type":"Point"}
}