{
  "type": "Feature",
  "properties": {
    "gn:admin1_code":"16",
    "gn:admin2_code":"66081.0",
    "gn:asciiname":"Mereni",
    "gn:country_code":"RO",
    "gn:dem":157,
    "gn:feature_class":"P",
    "gn:feature_code":"PPL",
    "gn:name":"Mereni",
    "gn:population":242,
    "gn:timezone":"Europe/Bucharest",
    "iso:country":"RO",
    "name:ceb_x_preferred":[
        "Mereni"
    ],
    "name:deu_x_preferred":[
        "Mereni"
    ],
    "name:fra_x_preferred":[
        "Mereni"
    ],
    "name:hun_x_preferred":[
        "Mereni"
    ],
    "name:ita_x_preferred":[
        "Mereni"
    ],
    "name:nld_x_preferred":[
        "Mereni"
    ],
    "name:ron_x_preferred":[
        "Mereni"
    ],
    "name:rus_x_preferred":[
        "\u041c\u0435\u0440\u0435\u043d\u044c"
    ],
    "name:srp_x_preferred":[
        "\u041c\u0435\u0440\u0435\u043d\u0438"
    ],
    "name:ukr_x_preferred":[
        "\u041c\u0435\u0440\u0435\u043d\u044c"
    ],
    "wof:name":"Mereni",
    "wof:placetype":"locality",
    "wof:population":242
},
  "geometry": {"coordinates":[25.57777,44.65882],"type":"Point"}
}