{
  "type": "Feature",
  "properties": {
    "gn:admin1_code":"04",
    "gn:admin2_code":"25228",
    "gn:asciiname":"Bogdan Voda",
    "gn:country_code":"RO",
    "gn:dem":191,
    "gn:feature_class":"P",
    "gn:feature_code":"PPL",
    "gn:name":"Bogdan Vod\u0103",
    "gn:population":315,
    "gn:timezone":"Europe/Bucharest",
    "iso:country":"RO",
    "wof:name":"Bogdan Voda",
    "wof:placetype":"locality",
    "wof:population":315
},
  "geometry": {"coordinates":[26.92179,46.61991],"type":"Point"}
}