{
  "type": "Feature",
  "properties": {
    "gn:admin1_code":"39",
    "gn:admin2_code":"172581.0",
    "gn:asciiname":"Cueni",
    "gn:country_code":"RO",
    "gn:dem":301,
    "gn:feature_class":"P",
    "gn:feature_code":"PPL",
    "gn:name":"Cueni",
    "gn:population":658,
    "gn:timezone":"Europe/Bucharest",
    "iso:country":"RO",
    "wof:name":"Cueni",
    "wof:placetype":"locality",
    "wof:population":658
},
  "geometry": {"coordinates":[24.08203,44.89321],"type":"Point"}
}