{
  "type": "Feature",
  "properties": {
    "gn:admin1_code":"26",
    "gn:admin2_code":"110740.0",
    "gn:asciiname":"Cosovat",
    "gn:country_code":"RO",
    "gn:dem":247,
    "gn:feature_class":"P",
    "gn:feature_code":"PPL",
    "gn:name":"Co\u0219ov\u0103\u021b",
    "gn:population":109,
    "gn:timezone":"Europe/Bucharest",
    "iso:country":"RO",
    "wof:name":"Cosovat",
    "wof:placetype":"locality",
    "wof:population":109
},
  "geometry": {"coordinates":[23.26667,44.53333],"type":"Point"}
}