{
  "type": "Feature",
  "properties": {
    "gn:admin1_code":"26",
    "gn:admin2_code":"111587.0",
    "gn:asciiname":"Ursoaia",
    "gn:country_code":"RO",
    "gn:dem":223,
    "gn:feature_class":"P",
    "gn:feature_code":"PPL",
    "gn:name":"Ursoaia",
    "gn:population":0,
    "gn:timezone":"Europe/Bucharest",
    "iso:country":"RO",
    "name:ceb_x_preferred":[
        "Ursoaia"
    ],
    "name:deu_x_preferred":[
        "Ursoaia"
    ],
    "name:ron_x_preferred":[
        "Ursoaia"
    ],
    "name:rus_x_preferred":[
        "\u0423\u0440\u0441\u043e\u0430\u044f"
    ],
    "name:ukr_x_preferred":[
        "\u0423\u0440\u0441\u043e\u0430\u044f"
    ],
    "wof:name":"Ursoaia",
    "wof:placetype":"locality"
},
  "geometry": {"coordinates":[23.18333,44.53333],"type":"Point"}
}