{
  "type": "Feature",
  "properties": {
    "gn:admin1_code":"26",
    "gn:admin2_code":"111587.0",
    "gn:asciiname":"Ursoaia",
    "gn:country_code":"RO",
    "gn:dem":223,
    "gn:feature_class":"P",
    "gn:feature_code":"PPL",
    "gn:name":"Ursoaia",
    "gn:population":0,
    "gn:timezone":"Europe/Bucharest",
    "iso:country":"RO",
    "wof:name":"Ursoaia",
    "wof:placetype":"locality"
},
  "geometry": {"coordinates":[23.18333,44.53333],"type":"Point"}
}