{
  "type": "Feature",
  "properties": {
    "gn:admin1_code":"36",
    "gn:admin2_code":"157317.0",
    "gn:asciiname":"Crai Nou",
    "gn:cc2":"RO",
    "gn:country_code":"RO",
    "gn:dem":78,
    "gn:feature_class":"P",
    "gn:feature_code":"PPL",
    "gn:name":"Crai Nou",
    "gn:population":536,
    "gn:timezone":"Europe/Bucharest",
    "iso:country":"RO",
    "name:und_x_variant":[
        "Rudna",
        "Crai Nou"
    ],
    "wof:name":"Crai Nou",
    "wof:placetype":"locality",
    "wof:population":536
},
  "geometry": {"coordinates":[21.0003,45.48822],"type":"Point"}
}