{
  "type": "Feature",
  "properties": {
    "gn:admin1_code":"11",
    "gn:admin2_code":"47417.0",
    "gn:asciiname":"Fantanele",
    "gn:cc2":"RO",
    "gn:country_code":"RO",
    "gn:dem":324,
    "gn:feature_class":"P",
    "gn:feature_code":"PPL",
    "gn:name":"F\u00e2nt\u00e2nele",
    "gn:population":399,
    "gn:timezone":"Europe/Bucharest",
    "iso:country":"RO",
    "name:und_x_variant":[
        "Schiopeni",
        "F\u00eent\u00eenele"
    ],
    "wof:name":"Fantanele",
    "wof:placetype":"locality",
    "wof:population":399
},
  "geometry": {"coordinates":[26.84883,45.42256],"type":"Point"}
}