{
  "type": "Feature",
  "properties": {
    "gn:admin1_code":"20",
    "gn:admin2_code":"84923.0",
    "gn:asciiname":"Oraseni",
    "gn:cc2":"RO",
    "gn:country_code":"RO",
    "gn:dem":482,
    "gn:feature_class":"P",
    "gn:feature_code":"PPL",
    "gn:name":"Or\u0103\u0219eni",
    "gn:population":323,
    "gn:timezone":"Europe/Bucharest",
    "iso:country":"RO",
    "name:und_x_variant":[
        "V\u00e0rs\u00f3falva",
        "Or\u0103\u015feni"
    ],
    "wof:name":"Oraseni",
    "wof:placetype":"locality",
    "wof:population":323
},
  "geometry": {"coordinates":[25.36567,46.16387],"type":"Point"}
}