{
  "type": "Feature",
  "properties": {
    "gn:admin1_code":"40",
    "gn:admin2_code":"177655.0",
    "gn:asciiname":"Olareni",
    "gn:country_code":"RO",
    "gn:dem":359,
    "gn:feature_class":"P",
    "gn:feature_code":"PPL",
    "gn:name":"Ol\u0103reni",
    "gn:population":106,
    "gn:timezone":"Europe/Bucharest",
    "iso:country":"RO",
    "wof:name":"Olareni",
    "wof:placetype":"locality",
    "wof:population":106
},
  "geometry": {"coordinates":[27.00702,45.48509],"type":"Point"}
}