{
  "type": "Feature",
  "properties": {
    "gn:admin1_code":"01",
    "gn:admin2_code":"3039.0",
    "gn:asciiname":"Dambureni",
    "gn:country_code":"RO",
    "gn:dem":1001,
    "gn:feature_class":"P",
    "gn:feature_code":"PPL",
    "gn:name":"D\u00e2mbureni",
    "gn:population":48,
    "gn:timezone":"Europe/Bucharest",
    "iso:country":"RO",
    "wof:name":"Dambureni",
    "wof:placetype":"locality",
    "wof:population":48
},
  "geometry": {"coordinates":[23.071,46.41428],"type":"Point"}
}