{
  "type": "Feature",
  "properties": {
    "gn:admin1_code":"21",
    "gn:admin2_code":"91330.0",
    "gn:asciiname":"Sulighete",
    "gn:country_code":"RO",
    "gn:dem":330,
    "gn:feature_class":"P",
    "gn:feature_code":"PPL",
    "gn:name":"Sulighete",
    "gn:population":343,
    "gn:timezone":"Europe/Bucharest",
    "iso:country":"RO",
    "wof:name":"Sulighete",
    "wof:placetype":"locality",
    "wof:population":343
},
  "geometry": {"coordinates":[22.80204,45.9771],"type":"Point"}
}