{
  "type": "Feature",
  "properties": {
    "gn:admin1_code":"28",
    "gn:admin2_code":"122132.0",
    "gn:asciiname":"Frunzeni",
    "gn:country_code":"RO",
    "gn:dem":223,
    "gn:feature_class":"P",
    "gn:feature_code":"PPL",
    "gn:name":"Frunzeni",
    "gn:population":659,
    "gn:timezone":"Europe/Bucharest",
    "iso:country":"RO",
    "wof:name":"Frunzeni",
    "wof:placetype":"locality",
    "wof:population":659
},
  "geometry": {"coordinates":[26.62635,46.73787],"type":"Point"}
}