{
  "type": "Feature",
  "properties": {
    "gn:admin1_code":"27",
    "gn:admin2_code":"118281.0",
    "gn:asciiname":"Santandrei",
    "gn:cc2":"RO",
    "gn:country_code":"RO",
    "gn:dem":346,
    "gn:feature_class":"P",
    "gn:feature_code":"PPL",
    "gn:name":"S\u00e2ntandrei",
    "gn:population":0,
    "gn:timezone":"Europe/Bucharest",
    "iso:country":"RO",
    "name:und_x_variant":[
        "Ny\u00e0radszentandras",
        "S\u00e2ntandrei",
        "S\u00eentandrei"
    ],
    "wof:name":"Santandrei",
    "wof:placetype":"locality"
},
  "geometry": {"coordinates":[24.81667,46.53333],"type":"Point"}
}