{
  "type": "Feature",
  "properties": {
    "gn:admin1_code":"17",
    "gn:admin2_code":"74073.0",
    "gn:asciiname":"Valea lui Patru",
    "gn:country_code":"RO",
    "gn:dem":115,
    "gn:feature_class":"P",
    "gn:feature_code":"PPL",
    "gn:name":"Valea lui P\u0103tru",
    "gn:population":995,
    "gn:timezone":"Europe/Bucharest",
    "iso:country":"RO",
    "wof:name":"Valea lui Patru",
    "wof:placetype":"locality",
    "wof:population":995
},
  "geometry": {"coordinates":[23.52128,44.4723],"type":"Point"}
}