{
  "type": "Feature",
  "properties": {
    "gn:admin1_code":"36",
    "gn:admin2_code":"158449.0",
    "gn:asciiname":"Icloda",
    "gn:cc2":"RO",
    "gn:country_code":"RO",
    "gn:dem":95,
    "gn:feature_class":"P",
    "gn:feature_code":"PPL",
    "gn:name":"Icloda",
    "gn:population":268,
    "gn:timezone":"Europe/Bucharest",
    "iso:country":"RO",
    "name:und_x_variant":[
        "Ikloda",
        "Ikl\u00f3d",
        "Icloda"
    ],
    "wof:name":"Icloda",
    "wof:placetype":"locality",
    "wof:population":268
},
  "geometry": {"coordinates":[21.38856,45.64313],"type":"Point"}
}