{
  "type": "Feature",
  "properties": {
    "gn:admin1_code":"13",
    "gn:admin2_code":"59327.0",
    "gn:asciiname":"Liteni",
    "gn:country_code":"RO",
    "gn:dem":680,
    "gn:feature_class":"P",
    "gn:feature_code":"PPL",
    "gn:name":"Liteni",
    "gn:population":410,
    "gn:timezone":"Europe/Bucharest",
    "iso:country":"RO",
    "name:ceb_x_preferred":[
        "Ora\u0219 Liteni"
    ],
    "name:deu_x_preferred":[
        "Liteni"
    ],
    "name:epo_x_preferred":[
        "Liteni"
    ],
    "name:fas_x_preferred":[
        "\u0644\u06cc\u062a\u0647"
    ],
    "name:fra_x_preferred":[
        "Liteni"
    ],
    "name:heb_x_preferred":[
        "\u05dc\u05d9\u05d8\u05df"
    ],
    "name:hun_x_preferred":[
        "Magyarl\u00e9ta"
    ],
    "name:hun_x_variant":[
        "Liteni"
    ],
    "name:ind_x_preferred":[
        "Liteni"
    ],
    "name:ita_x_preferred":[
        "Liteni"
    ],
    "name:msa_x_preferred":[
        "Liteni"
    ],
    "name:nld_x_preferred":[
        "Liteni"
    ],
    "name:pol_x_preferred":[
        "Liteni"
    ],
    "name:ron_x_preferred":[
        "Liteni"
    ],
    "name:rus_x_preferred":[
        "\u041b\u0438\u0442\u0435\u043d\u0438"
    ],
    "name:spa_x_preferred":[
        "Liteni"
    ],
    "name:srp_x_preferred":[
        "\u041e\u043f\u0448\u0442\u0438\u043d\u0430 \u041b\u0438\u0442\u0435\u043d\u0438"
    ],
    "name:ukr_x_preferred":[
        "\u041b\u0456\u0442\u0435\u043d\u044c"
    ],
    "name:und_x_variant":[
        "Lita Ungureasc\u0103"
    ],
    "name:vie_x_preferred":[
        "Liteni"
    ],
    "name:zho_x_preferred":[
        "\u5229\u6cf0\u5c3c"
    ],
    "wof:name":"Liteni",
    "wof:placetype":"locality",
    "wof:population":410
},
  "geometry": {"coordinates":[23.45,46.61667],"type":"Point"}
}