{
  "type": "Feature",
  "properties": {
    "gn:admin1_code":"13",
    "gn:admin2_code":"59327.0",
    "gn:asciiname":"Liteni",
    "gn:country_code":"RO",
    "gn:dem":680,
    "gn:feature_class":"P",
    "gn:feature_code":"PPL",
    "gn:name":"Liteni",
    "gn:population":410,
    "gn:timezone":"Europe/Bucharest",
    "iso:country":"RO",
    "name:hun_x_preferred":[
        "Magyarl\u00e9ta"
    ],
    "name:und_x_variant":[
        "Lita Ungureasc\u0103"
    ],
    "wof:name":"Liteni",
    "wof:placetype":"locality",
    "wof:population":410
},
  "geometry": {"coordinates":[23.45,46.61667],"type":"Point"}
}