{
  "type": "Feature",
  "properties": {
    "gn:admin1_code":"18",
    "gn:admin2_code":"76558.0",
    "gn:asciiname":"Calmatui",
    "gn:country_code":"RO",
    "gn:dem":60,
    "gn:feature_class":"P",
    "gn:feature_code":"PPL",
    "gn:name":"C\u0103lm\u0103\u021bui",
    "gn:population":637,
    "gn:timezone":"Europe/Bucharest",
    "iso:country":"RO",
    "wof:name":"Calmatui",
    "wof:placetype":"locality",
    "wof:population":637
},
  "geometry": {"coordinates":[27.63626,45.68413],"type":"Point"}
}