{
  "type": "Feature",
  "properties": {
    "gn:admin1_code":"38",
    "gn:admin2_code":"166182",
    "gn:asciiname":"Benesti",
    "gn:cc2":"RO",
    "gn:country_code":"RO",
    "gn:dem":174,
    "gn:feature_class":"P",
    "gn:feature_code":"PPL",
    "gn:name":"Bene\u0219ti",
    "gn:population":460,
    "gn:timezone":"Europe/Bucharest",
    "iso:country":"RO",
    "name:und_x_variant":[
        "B\u0103ne\u015fti",
        "Bene\u015fti"
    ],
    "wof:name":"Benesti",
    "wof:placetype":"locality",
    "wof:population":460
},
  "geometry": {"coordinates":[27.82979000000001,46.69563],"type":"Point"}
}