{
  "type": "Feature",
  "properties": {
    "gn:admin1_code":"36",
    "gn:admin2_code":"158895",
    "gn:asciiname":"Balosesti",
    "gn:country_code":"RO",
    "gn:dem":289,
    "gn:feature_class":"P",
    "gn:feature_code":"PPL",
    "gn:name":"Balo\u0219e\u0219ti",
    "gn:population":178,
    "gn:timezone":"Europe/Bucharest",
    "iso:country":"RO",
    "wof:name":"Balosesti",
    "wof:placetype":"locality",
    "wof:population":178
},
  "geometry": {"coordinates":[22.29114,45.78248],"type":"Point"}
}