{
  "type": "Feature",
  "properties": {
    "gn:admin1_code":"38",
    "gn:admin2_code":"164197.0",
    "gn:asciiname":"Oteleni",
    "gn:country_code":"RO",
    "gn:dem":130,
    "gn:feature_class":"P",
    "gn:feature_code":"PPL",
    "gn:name":"O\u021beleni",
    "gn:population":704,
    "gn:timezone":"Europe/Bucharest",
    "iso:country":"RO",
    "wof:name":"Oteleni",
    "wof:placetype":"locality",
    "wof:population":704
},
  "geometry": {"coordinates":[27.98154000000001,46.54031],"type":"Point"}
}