{
  "type": "Feature",
  "properties": {
    "gn:admin1_code":"01",
    "gn:admin2_code":"7197.0",
    "gn:asciiname":"Dobresti",
    "gn:country_code":"RO",
    "gn:dem":1113,
    "gn:feature_class":"P",
    "gn:feature_code":"PPL",
    "gn:name":"Dobre\u015fti",
    "gn:population":0,
    "gn:timezone":"Europe/Bucharest",
    "iso:country":"RO",
    "wof:name":"Dobresti",
    "wof:placetype":"locality"
},
  "geometry": {"coordinates":[22.91667,46.43333],"type":"Point"}
}