{
  "type": "Feature",
  "properties": {
    "gn:admin1_code":"38",
    "gn:admin2_code":"164981.0",
    "gn:asciiname":"Schineni",
    "gn:country_code":"RO",
    "gn:dem":181,
    "gn:feature_class":"P",
    "gn:feature_code":"PPL",
    "gn:name":"Schineni",
    "gn:population":687,
    "gn:timezone":"Europe/Bucharest",
    "iso:country":"RO",
    "name:ceb_x_preferred":[
        "Schineni"
    ],
    "name:deu_x_preferred":[
        "Schineni"
    ],
    "name:ron_x_preferred":[
        "Schineni"
    ],
    "wof:name":"Schineni",
    "wof:placetype":"locality",
    "wof:population":687
},
  "geometry": {"coordinates":[27.9529,46.20351],"type":"Point"}
}