{
  "type": "Feature",
  "properties": {
    "gn:admin1_code":"03",
    "gn:admin2_code":"19338.0",
    "gn:asciiname":"Valea Stanii",
    "gn:cc2":"RO",
    "gn:country_code":"RO",
    "gn:dem":347,
    "gn:feature_class":"P",
    "gn:feature_code":"PPL",
    "gn:name":"Valea St\u00e2nii",
    "gn:population":969,
    "gn:timezone":"Europe/Bucharest",
    "iso:country":"RO",
    "name:und_x_variant":[
        "Valea St\u00e2nei",
        "Valea St\u00eenii"
    ],
    "wof:name":"Valea Stanii",
    "wof:placetype":"locality",
    "wof:population":969
},
  "geometry": {"coordinates":[24.96468,44.98672],"type":"Point"}
}