{
  "type": "Feature",
  "properties": {
    "gn:admin1_code":"43",
    "gn:admin2_code":"179221.0",
    "gn:asciiname":"Nefliu",
    "gn:country_code":"RO",
    "gn:dem":80,
    "gn:feature_class":"P",
    "gn:feature_code":"PPL",
    "gn:name":"Nefliu",
    "gn:population":0,
    "gn:timezone":"Europe/Bucharest",
    "iso:country":"RO",
    "wof:name":"Nefliu",
    "wof:placetype":"locality"
},
  "geometry": {"coordinates":[25.98333,44.36667],"type":"Point"}
}