{
  "type": "Feature",
  "properties": {
    "gn:admin1_code":"21",
    "gn:admin2_code":"87996.0",
    "gn:asciiname":"Livadia de Coasta",
    "gn:country_code":"RO",
    "gn:dem":464,
    "gn:feature_class":"P",
    "gn:feature_code":"PPL",
    "gn:name":"Livadia de Coast\u0103",
    "gn:population":0,
    "gn:timezone":"Europe/Bucharest",
    "iso:country":"RO",
    "wof:name":"Livadia de Coasta",
    "wof:placetype":"locality"
},
  "geometry": {"coordinates":[23.13333,45.48333],"type":"Point"}
}