{
  "type": "Feature",
  "properties": {
    "gn:admin1_code":"38",
    "gn:admin2_code":"162149.0",
    "gn:asciiname":"Fundatura",
    "gn:cc2":"RO",
    "gn:country_code":"RO",
    "gn:dem":218,
    "gn:feature_class":"P",
    "gn:feature_code":"PPL",
    "gn:name":"Fund\u0103tura",
    "gn:population":546,
    "gn:timezone":"Europe/Bucharest",
    "iso:country":"RO",
    "name:und_x_variant":[
        "Fund\u0103tura-P\u00eehne\u015fti",
        "Fund\u0103tura"
    ],
    "wof:name":"Fundatura",
    "wof:placetype":"locality",
    "wof:population":546
},
  "geometry": {"coordinates":[28.02245,46.79535],"type":"Point"}
}