{
  "type": "Feature",
  "properties": {
    "gn:admin1_code":"22",
    "gn:admin2_code":"179784.0",
    "gn:asciiname":"Sintesti",
    "gn:country_code":"RO",
    "gn:dem":56,
    "gn:feature_class":"P",
    "gn:feature_code":"PPL",
    "gn:name":"Sinte\u0219ti",
    "gn:population":291,
    "gn:timezone":"Europe/Bucharest",
    "iso:country":"RO",
    "wof:name":"Sintesti",
    "wof:placetype":"locality",
    "wof:population":291
},
  "geometry": {"coordinates":[26.58467000000001,44.66641],"type":"Point"}
}