{
  "type": "Feature",
  "properties": {
    "gn:country":"RO",
    "gn:fcode":"PPLA2",
    "gn:population":1866,
    "iso:country":"RO",
    "name:ara_x_preferred":[
        "\u0641\u0627\u0631\u0627\u0648"
    ],
    "name:ceb_x_preferred":[
        "F\u0103r\u0103u"
    ],
    "name:deu_x_preferred":[
        "F\u0103r\u0103u"
    ],
    "name:eng_x_preferred":[
        "F\u0103r\u0103u"
    ],
    "name:epo_x_preferred":[
        "F\u0103r\u0103u"
    ],
    "name:fra_x_preferred":[
        "F\u0103r\u0103u"
    ],
    "name:hun_x_preferred":[
        "Magyarforr\u00f3"
    ],
    "name:ita_x_preferred":[
        "F\u0103r\u0103u"
    ],
    "name:mkd_x_preferred":[
        "\u0424\u0430\u0440\u0430\u0443"
    ],
    "name:msa_x_preferred":[
        "F\u0103r\u0103u"
    ],
    "name:nld_x_preferred":[
        "F\u0103r\u0103u"
    ],
    "name:por_x_preferred":[
        "F\u0103r\u0103u"
    ],
    "name:ron_x_preferred":[
        "F\u0103r\u0103u"
    ],
    "name:ron_x_variant":[
        "P\u00eeclele"
    ],
    "name:sqi_x_preferred":[
        "F\u0103r\u0103u"
    ],
    "name:srp_x_preferred":[
        "\u0424\u0430\u0440\u0430\u0443"
    ],
    "name:ukr_x_preferred":[
        "\u0424\u0435\u0440\u0435\u0443"
    ],
    "name:und_x_variant":[
        "F\u0103r\u0103ul"
    ],
    "name:vie_x_preferred":[
        "Farau"
    ],
    "name:vol_x_preferred":[
        "F\u0103r\u0103u"
    ],
    "qs_pg:aaroncc":"RO",
    "qs_pg:gn_country":"RO",
    "qs_pg:gn_fcode":"PPLA2",
    "qs_pg:gn_pop":1866,
    "qs_pg:name":"F\u0103r\u0103u",
    "qs_pg:name_adm0":"Rom\u00e2nia",
    "qs_pg:name_adm1":"Alba",
    "qs_pg:photos_9r":0,
    "qs_pg:photos_sr":0,
    "qs_pg:pop_sr":3,
    "qs_pg:qs_pg_placetype":"locality",
    "qs_pg:qs_pg_placetype_gp":"Town",
    "qs_pg:woe_adm0":23424933,
    "woe:adm0_id":23424933,
    "woe:name_adm0":"Rom\u00e2nia",
    "woe:name_adm1":"Alba",
    "woe:placetype":"Town",
    "wof:name":"F\u0103r\u0103u",
    "wof:placetype":"locality",
    "wof:population":1866
},
  "geometry": {"coordinates":[24.01667,46.33333],"type":"Point"}
}