{
  "type": "Feature",
  "properties": {
    "gn:gn_country":"RO",
    "gn:gn_fcode":"PPLA2",
    "gn:gn_pop":921,
    "gn:population":921,
    "iso:country":"RO",
    "name:bul_x_preferred":[
        "\u0413\u043e\u0440\u0443\u0438\u0430"
    ],
    "name:deu_x_preferred":[
        "Goruia"
    ],
    "name:eng_x_preferred":[
        "Goruia"
    ],
    "name:epo_x_preferred":[
        "Goruia"
    ],
    "name:fra_x_preferred":[
        "Goruia"
    ],
    "name:hun_x_preferred":[
        "Gorony"
    ],
    "name:ita_x_preferred":[
        "Goruia"
    ],
    "name:nld_x_preferred":[
        "Goruia"
    ],
    "name:por_x_preferred":[
        "Goruia"
    ],
    "name:ron_x_preferred":[
        "Goruia"
    ],
    "name:ukr_x_preferred":[
        "\u0413\u043e\u0440\u0443\u044f"
    ],
    "name:vie_x_preferred":[
        "Goruia"
    ],
    "name:vol_x_preferred":[
        "Goruia"
    ],
    "qs_pg:aaroncc":"RO",
    "qs_pg:gn_country":"RO",
    "qs_pg:gn_fcode":"PPLA2",
    "qs_pg:gn_pop":921,
    "qs_pg:name":"Goruia",
    "qs_pg:name_adm0":"Rom\u00e2nia",
    "qs_pg:name_adm1":"Caras-Severin",
    "qs_pg:photos_9r":0,
    "qs_pg:photos_sr":0,
    "qs_pg:pop_sr":2,
    "qs_pg:qs_pg_placetype":"locality",
    "qs_pg:qs_pg_placetype_gp":"Town",
    "qs_pg:woe_adm0":23424933,
    "woe:adm0_id":23424933,
    "woe:name_adm0":"Rom\u00e2nia",
    "woe:name_adm1":"Caras-Severin",
    "woe:placetype":"Town",
    "wof:name":"Goruia",
    "wof:placetype":"locality",
    "wof:population":921
},
  "geometry": {"coordinates":[21.77917,45.18722],"type":"Point"}
}