{
  "type": "Feature",
  "properties": {
    "gn:admin1_code":"34",
    "gn:admin2_code":"146860",
    "gn:asciiname":"Bodnareni",
    "gn:country_code":"RO",
    "gn:dem":379,
    "gn:feature_class":"P",
    "gn:feature_code":"PPL",
    "gn:name":"Bodn\u0103reni",
    "gn:population":315,
    "gn:timezone":"Europe/Bucharest",
    "iso:country":"RO",
    "wof:name":"Bodnareni",
    "wof:placetype":"locality",
    "wof:population":315
},
  "geometry": {"coordinates":[25.93343,47.75802],"type":"Point"}
}