{
  "type": "Feature",
  "properties": {
    "gn:admin1_code":"03",
    "gn:admin2_code":"16908.0",
    "gn:asciiname":"Voinesti",
    "gn:country_code":"RO",
    "gn:dem":644,
    "gn:feature_class":"P",
    "gn:feature_code":"PPL",
    "gn:name":"Voine\u0219ti",
    "gn:population":1895,
    "gn:timezone":"Europe/Bucharest",
    "iso:country":"RO",
    "wof:name":"Voinesti",
    "wof:placetype":"locality",
    "wof:population":1895
},
  "geometry": {"coordinates":[25.07225,45.30007],"type":"Point"}
}