{
  "type": "Feature",
  "properties": {
    "gn:admin1_code":"17",
    "gn:admin2_code":"70940.0",
    "gn:asciiname":"Dragalina",
    "gn:country_code":"RO",
    "gn:dem":50,
    "gn:feature_class":"P",
    "gn:feature_code":"PPL",
    "gn:name":"Dragalina",
    "gn:population":0,
    "gn:timezone":"Europe/Bucharest",
    "iso:country":"RO",
    "name:ceb_x_preferred":[
        "Dragalina"
    ],
    "name:deu_x_preferred":[
        "Dragalina"
    ],
    "name:nld_x_preferred":[
        "Dragalina"
    ],
    "name:ron_x_preferred":[
        "Dragalina"
    ],
    "name:srp_x_preferred":[
        "\u0414\u0440\u0430\u0433\u0430\u043b\u0438\u043d\u0430"
    ],
    "name:vie_x_preferred":[
        "Dragalina"
    ],
    "wof:name":"Dragalina",
    "wof:placetype":"locality"
},
  "geometry": {"coordinates":[23.61667000000001,43.96667],"type":"Point"}
}