{
  "type": "Feature",
  "properties": {
    "gn:gn_country":"RO",
    "gn:gn_fcode":"PPLA2",
    "gn:gn_pop":1073,
    "gn:population":1073,
    "iso:country":"RO",
    "name:ceb_x_preferred":[
        "Dubova"
    ],
    "name:deu_x_preferred":[
        "Dubova"
    ],
    "name:eng_x_preferred":[
        "Dubova"
    ],
    "name:epo_x_preferred":[
        "Dubova"
    ],
    "name:fra_x_preferred":[
        "Dubova"
    ],
    "name:hun_x_preferred":[
        "Dubova"
    ],
    "name:ita_x_preferred":[
        "Dubova"
    ],
    "name:msa_x_preferred":[
        "Dubova"
    ],
    "name:nld_x_preferred":[
        "Dubova"
    ],
    "name:por_x_preferred":[
        "Dubova"
    ],
    "name:ron_x_preferred":[
        "Dubova"
    ],
    "name:srp_x_preferred":[
        "\u0414\u0443\u0431\u043e\u0432\u0430"
    ],
    "name:ukr_x_preferred":[
        "\u0414\u0443\u0431\u043e\u0432\u0430"
    ],
    "name:vol_x_preferred":[
        "Dubova"
    ],
    "qs_pg:aaroncc":"RO",
    "qs_pg:gn_country":"RO",
    "qs_pg:gn_fcode":"PPLA2",
    "qs_pg:gn_pop":1073,
    "qs_pg:name":"Dubova",
    "qs_pg:name_adm0":"Rom\u00e2nia",
    "qs_pg:name_adm1":"Mehedinti",
    "qs_pg:photos":1029,
    "qs_pg:photos_1k":209,
    "qs_pg:photos_9k":5,
    "qs_pg:photos_9r":7,
    "qs_pg:photos_all":1029,
    "qs_pg:photos_sr":11,
    "qs_pg:pop_sr":3,
    "qs_pg:qs_pg_placetype":"locality",
    "qs_pg:qs_pg_placetype_gp":"Town",
    "qs_pg:woe_adm0":23424933,
    "woe:adm0_id":23424933,
    "woe:name_adm0":"Rom\u00e2nia",
    "woe:name_adm1":"Mehedinti",
    "woe:placetype":"Town",
    "wof:name":"Dubova",
    "wof:placetype":"locality",
    "wof:population":1073
},
  "geometry": {"coordinates":[22.26667,44.61667],"type":"Point"}
}