{
  "type": "Feature",
  "properties": {
    "gn:admin1_code":"03",
    "gn:admin2_code":"13757.0",
    "gn:asciiname":"Crintesti",
    "gn:country_code":"RO",
    "gn:dem":273,
    "gn:feature_class":"P",
    "gn:feature_code":"PPL",
    "gn:name":"Crinte\u0219ti",
    "gn:population":355,
    "gn:timezone":"Europe/Bucharest",
    "iso:country":"RO",
    "wof:name":"Crintesti",
    "wof:placetype":"locality",
    "wof:population":355
},
  "geometry": {"coordinates":[25.09537000000001,44.85352],"type":"Point"}
}