{
  "type": "Feature",
  "properties": {
    "gn:admin1_code":"26",
    "gn:admin2_code":"111097.0",
    "gn:asciiname":"Jignita",
    "gn:country_code":"RO",
    "gn:dem":197,
    "gn:feature_class":"P",
    "gn:feature_code":"PPL",
    "gn:name":"Jigni\u021ba",
    "gn:population":145,
    "gn:timezone":"Europe/Bucharest",
    "iso:country":"RO",
    "wof:name":"Jignita",
    "wof:placetype":"locality",
    "wof:population":145
},
  "geometry": {"coordinates":[22.90114,44.71555],"type":"Point"}
}