{
  "type": "Feature",
  "properties": {
    "gn:admin1_code":"01",
    "gn:admin2_code":"6761.0",
    "gn:asciiname":"Carpinis",
    "gn:country_code":"RO",
    "gn:dem":588,
    "gn:feature_class":"P",
    "gn:feature_code":"PPL",
    "gn:name":"C\u0103rpini\u0219",
    "gn:population":401,
    "gn:timezone":"Europe/Bucharest",
    "iso:country":"RO",
    "wof:name":"Carpinis",
    "wof:placetype":"locality",
    "wof:population":401
},
  "geometry": {"coordinates":[23.05885,46.31698],"type":"Point"}
}