{
  "type": "Feature",
  "properties": {
    "gn:admin1_code":"21",
    "gn:admin2_code":"90342.0",
    "gn:asciiname":"Ocolisu Mic",
    "gn:cc2":"RO",
    "gn:country_code":"RO",
    "gn:dem":352,
    "gn:feature_class":"P",
    "gn:feature_code":"PPL",
    "gn:name":"Ocoli\u0219u Mic",
    "gn:population":470,
    "gn:timezone":"Europe/Bucharest",
    "iso:country":"RO",
    "name:und_x_variant":[
        "Ocoli\u015ful-Mic",
        "Ocoli\u015fu Mic"
    ],
    "wof:name":"Ocolisu Mic",
    "wof:placetype":"locality",
    "wof:population":470
},
  "geometry": {"coordinates":[23.12826,45.71129000000001],"type":"Point"}
}