{
  "type": "Feature",
  "properties": {
    "iso:country":"RO",
    "name:ron_x_preferred":[
        "Timpuri Noi"
    ],
    "wof:name":"Timpuri Noi",
    "wof:placetype":"neighbourhood"
},
  "geometry": {"coordinates":[26.11349028122555,44.41468090662686],"type":"Point"}
}