{
  "type": "Feature",
  "properties": {
    "iso:country":"RO",
    "name:ron_x_preferred":[
        "Timpuri Noi"
    ],
    "wof:lang_x_official":[
        "ron"
    ],
    "wof:lang_x_spoken":[
        "ron"
    ],
    "wof:name":"Timpuri Noi",
    "wof:placetype":"neighbourhood"
},
  "geometry": {"coordinates":[26.11349,44.414681],"type":"Point"}
}