{
  "type": "Feature",
  "properties": {
    "gn:admin1_code":"39",
    "gn:admin2_code":"170346.0",
    "gn:asciiname":"Valea Gradistei",
    "gn:country_code":"RO",
    "gn:dem":294,
    "gn:feature_class":"P",
    "gn:feature_code":"PPL",
    "gn:name":"Valea Gr\u0103di\u0219tei",
    "gn:population":263,
    "gn:timezone":"Europe/Bucharest",
    "iso:country":"RO",
    "wof:name":"Valea Gradistei",
    "wof:placetype":"locality",
    "wof:population":263
},
  "geometry": {"coordinates":[23.79189,44.8861],"type":"Point"}
}