{
  "type": "Feature",
  "properties": {
    "gn:admin1_code":"19",
    "gn:admin2_code":"78329.0",
    "gn:asciiname":"Ciontesti",
    "gn:country_code":"RO",
    "gn:dem":220,
    "gn:feature_class":"P",
    "gn:feature_code":"PPL",
    "gn:name":"Cionte\u015fti",
    "gn:population":0,
    "gn:timezone":"Europe/Bucharest",
    "iso:country":"RO",
    "wof:lang_x_official":[
        "ron"
    ],
    "wof:lang_x_spoken":[
        "ron"
    ],
    "wof:name":"Ciontesti",
    "wof:placetype":"locality"
},
  "geometry": {"coordinates":[23.53333,44.93333],"type":"Point"}
}