{
  "type": "Feature",
  "properties": {
    "gn:admin1_code":"26",
    "gn:admin2_code":"112548.0",
    "gn:asciiname":"Jiana Mare",
    "gn:cc2":"RO",
    "gn:country_code":"RO",
    "gn:dem":84,
    "gn:feature_class":"P",
    "gn:feature_code":"PPL",
    "gn:name":"Jiana Mare",
    "gn:population":960,
    "gn:timezone":"Europe/Bucharest",
    "iso:country":"RO",
    "name:ceb_x_preferred":[
        "Comuna Jiana"
    ],
    "name:fra_x_preferred":[
        "Jiana"
    ],
    "name:ita_x_preferred":[
        "Jiana"
    ],
    "name:msa_x_preferred":[
        "Jiana"
    ],
    "name:nld_x_preferred":[
        "Jiana"
    ],
    "name:por_x_preferred":[
        "Jiana"
    ],
    "name:ron_x_preferred":[
        "Comuna Jiana"
    ],
    "name:srp_x_preferred":[
        "\u041e\u043f\u0448\u0442\u0438\u043d\u0430 \u0416\u0438\u0430\u043d\u0430"
    ],
    "name:ukr_x_preferred":[
        "\u0416\u0456\u0430\u043d\u0430"
    ],
    "name:und_x_variant":[
        "Jiana Mare"
    ],
    "name:vie_x_preferred":[
        "Jiana"
    ],
    "name:vol_x_preferred":[
        "Jiana"
    ],
    "name:zho_x_preferred":[
        "\u65e5\u4e9e\u7d0d\u9109"
    ],
    "wof:name":"Jiana Mare",
    "wof:placetype":"locality",
    "wof:population":960
},
  "geometry": {"coordinates":[22.6889,44.41113],"type":"Point"}
}