{
  "type": "Feature",
  "properties": {
    "gn:admin1_code":"26",
    "gn:admin2_code":"112548.0",
    "gn:asciiname":"Jiana Mare",
    "gn:cc2":"RO",
    "gn:country_code":"RO",
    "gn:dem":84,
    "gn:feature_class":"P",
    "gn:feature_code":"PPL",
    "gn:name":"Jiana Mare",
    "gn:population":960,
    "gn:timezone":"Europe/Bucharest",
    "iso:country":"RO",
    "name:und_x_variant":[
        "Jiana",
        "Jiana Mare"
    ],
    "wof:name":"Jiana Mare",
    "wof:placetype":"locality",
    "wof:population":960
},
  "geometry": {"coordinates":[22.6889,44.41113],"type":"Point"}
}