{
  "type": "Feature",
  "properties": {
    "gn:admin1_code":"29",
    "gn:admin2_code":"129914.0",
    "gn:asciiname":"Trepteni",
    "gn:country_code":"RO",
    "gn:dem":244,
    "gn:feature_class":"P",
    "gn:feature_code":"PPL",
    "gn:name":"Trepteni",
    "gn:population":483,
    "gn:timezone":"Europe/Bucharest",
    "iso:country":"RO",
    "wof:name":"Trepteni",
    "wof:placetype":"locality",
    "wof:population":483
},
  "geometry": {"coordinates":[24.35273,44.86478],"type":"Point"}
}