{
  "type": "Feature",
  "properties": {
    "gn:admin1_code":"31",
    "gn:admin2_code":"142881.0",
    "gn:asciiname":"Poiana Magura",
    "gn:country_code":"RO",
    "gn:dem":253,
    "gn:feature_class":"P",
    "gn:feature_code":"PPL",
    "gn:name":"Poiana M\u0103gura",
    "gn:population":33,
    "gn:timezone":"Europe/Bucharest",
    "iso:country":"RO",
    "wof:name":"Poiana Magura",
    "wof:placetype":"locality",
    "wof:population":33
},
  "geometry": {"coordinates":[22.81056,47.28063],"type":"Point"}
}