{
  "type": "Feature",
  "properties": {
    "gn:admin1_code":"14",
    "gn:admin2_code":"60482",
    "gn:asciiname":"Neptun",
    "gn:country_code":"RO",
    "gn:dem":11,
    "gn:feature_class":"P",
    "gn:feature_code":"PPL",
    "gn:name":"Neptun",
    "gn:population":999,
    "gn:timezone":"Europe/Bucharest",
    "iso:country":"RO",
    "name:ara_x_preferred":[
        "\u0645\u0646\u062a\u062c\u0639 \u0646\u0628\u062a\u0648\u0646"
    ],
    "name:deu_x_preferred":[
        "Neptun"
    ],
    "name:epo_x_preferred":[
        "Neptun"
    ],
    "name:heb_x_preferred":[
        "\u05e0\u05e4\u05d8\u05d5\u05df"
    ],
    "name:hun_x_preferred":[
        "Neptun"
    ],
    "name:ita_x_preferred":[
        "Neptun"
    ],
    "name:nld_x_preferred":[
        "Neptun"
    ],
    "name:ron_x_preferred":[
        "Neptun"
    ],
    "name:slk_x_preferred":[
        "Neptun"
    ],
    "name:slv_x_preferred":[
        "Neptun"
    ],
    "wof:name":"Neptun",
    "wof:placetype":"locality",
    "wof:population":999
},
  "geometry": {"coordinates":[28.60166,43.87128],"type":"Point"}
}