{
  "type": "Feature",
  "properties": {
    "gn:admin1_code":"19",
    "gn:admin2_code":"82831.0",
    "gn:asciiname":"Motesti",
    "gn:country_code":"RO",
    "gn:dem":168,
    "gn:feature_class":"P",
    "gn:feature_code":"PPL",
    "gn:name":"Mo\u0163e\u015fti",
    "gn:population":0,
    "gn:timezone":"Europe/Bucharest",
    "iso:country":"RO",
    "wof:name":"Motesti",
    "wof:placetype":"locality"
},
  "geometry": {"coordinates":[23.53333,44.83333],"type":"Point"}
}