{
  "type": "Feature",
  "properties": {
    "gn:admin1_code":"04",
    "gn:admin2_code":"26320",
    "gn:asciiname":"Baltata",
    "gn:country_code":"RO",
    "gn:dem":264,
    "gn:feature_class":"P",
    "gn:feature_code":"PPL",
    "gn:name":"B\u0103l\u021bata",
    "gn:population":91,
    "gn:timezone":"Europe/Bucharest",
    "iso:country":"RO",
    "wof:name":"Baltata",
    "wof:placetype":"locality",
    "wof:population":91
},
  "geometry": {"coordinates":[26.86975,46.48915],"type":"Point"}
}