{
  "type": "Feature",
  "properties": {
    "gn:admin1_code":"12",
    "gn:admin2_code":"52954.0",
    "gn:asciiname":"Garliste",
    "gn:cc2":"RO",
    "gn:country_code":"RO",
    "gn:dem":302,
    "gn:feature_class":"P",
    "gn:feature_code":"PPL",
    "gn:name":"G\u00e2rli\u015fte",
    "gn:population":0,
    "gn:timezone":"Europe/Bucharest",
    "iso:country":"RO",
    "name:und_x_variant":[
        "G\u00e2rli\u015fte",
        "G\u00eerli\u015fte"
    ],
    "wof:name":"Garliste",
    "wof:placetype":"locality"
},
  "geometry": {"coordinates":[21.83333,45.18333],"type":"Point"}
}