{
  "type": "Feature",
  "properties": {
    "gn:admin1_code":"01",
    "gn:admin2_code":"3841.0",
    "gn:asciiname":"Curpeni",
    "gn:country_code":"RO",
    "gn:dem":359,
    "gn:feature_class":"P",
    "gn:feature_code":"PPL",
    "gn:name":"Curpeni",
    "gn:population":54,
    "gn:timezone":"Europe/Bucharest",
    "iso:country":"RO",
    "wof:name":"Curpeni",
    "wof:placetype":"locality",
    "wof:population":54
},
  "geometry": {"coordinates":[23.28246,45.98457],"type":"Point"}
}