{
  "type": "Feature",
  "properties": {
    "gn:admin1_code":"27",
    "gn:admin2_code":"117319.0",
    "gn:asciiname":"Comori",
    "gn:cc2":"RO",
    "gn:country_code":"RO",
    "gn:dem":453,
    "gn:feature_class":"P",
    "gn:feature_code":"PPL",
    "gn:name":"Comori",
    "gn:population":310,
    "gn:timezone":"Europe/Bucharest",
    "iso:country":"RO",
    "name:und_x_variant":[
        "Kincsesfo",
        "Comori"
    ],
    "wof:name":"Comori",
    "wof:placetype":"locality",
    "wof:population":310
},
  "geometry": {"coordinates":[24.89691,46.7358],"type":"Point"}
}