{
  "type": "Feature",
  "properties": {
    "gn:admin1_code":"14",
    "gn:admin2_code":"61513.0",
    "gn:asciiname":"Corbu de Sus",
    "gn:country_code":"RO",
    "gn:dem":39,
    "gn:feature_class":"P",
    "gn:feature_code":"PPL",
    "gn:name":"Corbu de Sus",
    "gn:population":0,
    "gn:timezone":"Europe/Bucharest",
    "iso:country":"RO",
    "name:und_x_variant":[
        "Gargaliku Mark",
        "Corbul",
        "Gargal\u00e2c",
        "Corbul-de-Sus",
        "Gargal\u00e2cul Mare",
        "Gargal\u00eec Mare",
        "Corbu de Sus"
    ],
    "wof:lang_x_official":[
        "ron"
    ],
    "wof:lang_x_spoken":[
        "ron"
    ],
    "wof:name":"Corbu de Sus",
    "wof:placetype":"locality"
},
  "geometry": {"coordinates":[28.65,44.41667],"type":"Point"}
}