{
  "type": "Feature",
  "properties": {
    "gn:admin1_code":"39",
    "gn:admin2_code":"172509.0",
    "gn:asciiname":"Copaceni",
    "gn:country_code":"RO",
    "gn:dem":332,
    "gn:feature_class":"P",
    "gn:feature_code":"PPL",
    "gn:name":"Cop\u0103ceni",
    "gn:population":434,
    "gn:timezone":"Europe/Bucharest",
    "iso:country":"RO",
    "wof:name":"Copaceni",
    "wof:placetype":"locality",
    "wof:population":434
},
  "geometry": {"coordinates":[24.31455,45.39386],"type":"Point"}
}