{
  "type": "Feature",
  "properties": {
    "gn:admin1_code":"28",
    "gn:admin2_code":"123601.0",
    "gn:asciiname":"Pangarati",
    "gn:cc2":"RO",
    "gn:country_code":"RO",
    "gn:dem":735,
    "gn:feature_class":"P",
    "gn:feature_code":"PPLA2",
    "gn:name":"P\u00e2ng\u0103ra\u0163i",
    "gn:population":0,
    "gn:timezone":"Europe/Bucharest",
    "iso:country":"RO",
    "name:fra_x_preferred":[
        "P\u00e2ng\u0103ra\u021bi"
    ],
    "name:ita_x_preferred":[
        "P\u00e2ng\u0103ra\u0163i"
    ],
    "name:por_x_preferred":[
        "P\u00e2ng\u0103ra\u0163i"
    ],
    "name:ron_x_preferred":[
        "P\u00e2ng\u0103ra\u021bi"
    ],
    "name:ukr_x_preferred":[
        "\u041f\u0438\u043d\u0433\u0435\u0440\u0430\u0446\u044c"
    ],
    "name:und_x_variant":[
        "P\u00eeng\u0103ra\u0163i"
    ],
    "name:vol_x_preferred":[
        "P\u00e2ng\u0103ra\u0163i"
    ],
    "wof:name":"Pangarati",
    "wof:placetype":"locality"
},
  "geometry": {"coordinates":[26.15,46.93333],"type":"Point"}
}