{
  "type": "Feature",
  "properties": {
    "gn:admin1_code":"29",
    "gn:admin2_code":"128711.0",
    "gn:asciiname":"Isaresti",
    "gn:country_code":"RO",
    "gn:dem":257,
    "gn:feature_class":"P",
    "gn:feature_code":"PPL",
    "gn:name":"Is\u0103re\u015fti",
    "gn:population":0,
    "gn:timezone":"Europe/Bucharest",
    "iso:country":"RO",
    "wof:name":"Isaresti",
    "wof:placetype":"locality"
},
  "geometry": {"coordinates":[24.51667,44.61667],"type":"Point"}
}