{
  "type": "Feature",
  "properties": {
    "gn:admin1_code":"38",
    "gn:admin2_code":"165817.0",
    "gn:asciiname":"Codreni",
    "gn:cc2":"RO",
    "gn:country_code":"RO",
    "gn:dem":182,
    "gn:feature_class":"P",
    "gn:feature_code":"PPL",
    "gn:name":"Codreni",
    "gn:population":131,
    "gn:timezone":"Europe/Bucharest",
    "iso:country":"RO",
    "name:ceb_x_preferred":[
        "Codreni"
    ],
    "name:deu_x_preferred":[
        "Codreni"
    ],
    "name:ron_x_preferred":[
        "Codreni"
    ],
    "name:rus_x_preferred":[
        "\u041a\u043e\u0434\u0440\u044f\u043d\u044b"
    ],
    "name:srp_x_preferred":[
        "\u041a\u043e\u0434\u0440\u0435\u043d\u0438"
    ],
    "name:ukr_x_preferred":[
        "\u041a\u043e\u0434\u0440\u0435\u043d\u044c"
    ],
    "name:und_x_variant":[
        "T\u00eelh\u0103re\u015fti",
        "T\u0103lh\u0103re\u015fti"
    ],
    "wof:name":"Codreni",
    "wof:placetype":"locality",
    "wof:population":131
},
  "geometry": {"coordinates":[27.90544,46.48089],"type":"Point"}
}