{
  "type": "Feature",
  "properties": {
    "gn:admin1_code":"38",
    "gn:admin2_code":"165817.0",
    "gn:asciiname":"Codreni",
    "gn:cc2":"RO",
    "gn:country_code":"RO",
    "gn:dem":182,
    "gn:feature_class":"P",
    "gn:feature_code":"PPL",
    "gn:name":"Codreni",
    "gn:population":131,
    "gn:timezone":"Europe/Bucharest",
    "iso:country":"RO",
    "name:und_x_variant":[
        "T\u00eelh\u0103re\u015fti",
        "T\u0103lh\u0103re\u015fti",
        "Codreni"
    ],
    "wof:name":"Codreni",
    "wof:placetype":"locality",
    "wof:population":131
},
  "geometry": {"coordinates":[27.90544,46.48089],"type":"Point"}
}