{
  "type": "Feature",
  "properties": {
    "gn:admin1_code":"42",
    "gn:admin2_code":"105623.0",
    "gn:asciiname":"Spiridon",
    "gn:cc2":"RO",
    "gn:country_code":"RO",
    "gn:dem":105,
    "gn:feature_class":"P",
    "gn:feature_code":"PPL",
    "gn:name":"Spiridon",
    "gn:population":0,
    "gn:timezone":"Europe/Bucharest",
    "iso:country":"RO",
    "name:und_x_variant":[
        "Bolintinu-Spiridon",
        "Poenarii-Spiridon",
        "Spiridon"
    ],
    "wof:name":"Spiridon",
    "wof:placetype":"locality"
},
  "geometry": {"coordinates":[25.78333,44.46667],"type":"Point"}
}