{
  "type": "Feature",
  "properties": {
    "gn:admin1_code":"01",
    "gn:admin2_code":"4302.0",
    "gn:asciiname":"Silea",
    "gn:country_code":"RO",
    "gn:dem":335,
    "gn:feature_class":"P",
    "gn:feature_code":"PPL",
    "gn:name":"\u0218ilea",
    "gn:population":490,
    "gn:timezone":"Europe/Bucharest",
    "iso:country":"RO",
    "wof:name":"Silea",
    "wof:placetype":"locality",
    "wof:population":490
},
  "geometry": {"coordinates":[24.11393,46.32699],"type":"Point"}
}