{
  "type": "Feature",
  "properties": {
    "gn:admin1_code":"01",
    "gn:admin2_code":"4302.0",
    "gn:asciiname":"Silea",
    "gn:country_code":"RO",
    "gn:dem":335,
    "gn:feature_class":"P",
    "gn:feature_code":"PPL",
    "gn:name":"\u0218ilea",
    "gn:population":490,
    "gn:timezone":"Europe/Bucharest",
    "iso:country":"RO",
    "name:azb_x_preferred":[
        "\u0633\u06cc\u0644\u0626\u0627"
    ],
    "name:bul_x_preferred":[
        "\u0421\u0438\u043b\u0435\u0430"
    ],
    "name:ceb_x_preferred":[
        "Silea"
    ],
    "name:deu_x_preferred":[
        "Silea"
    ],
    "name:epo_x_preferred":[
        "Silea"
    ],
    "name:eus_x_preferred":[
        "Silea"
    ],
    "name:fas_x_preferred":[
        "\u0633\u06cc\u0644\u0626\u0627"
    ],
    "name:fra_x_preferred":[
        "Silea"
    ],
    "name:hun_x_preferred":[
        "Silea"
    ],
    "name:hye_x_preferred":[
        "\u054d\u056b\u056c\u0565\u0561"
    ],
    "name:ita_x_preferred":[
        "Silea"
    ],
    "name:jpn_x_preferred":[
        "\u30b7\u30ec\u30fc\u30a2"
    ],
    "name:kaz_x_preferred":[
        "\u0421\u0438\u043b\u0435\u044f"
    ],
    "name:lat_x_preferred":[
        "Silea"
    ],
    "name:lmo_x_preferred":[
        "Silea"
    ],
    "name:msa_x_preferred":[
        "Silea"
    ],
    "name:nap_x_preferred":[
        "Silea"
    ],
    "name:nld_x_preferred":[
        "Silea"
    ],
    "name:pms_x_preferred":[
        "Silea"
    ],
    "name:pol_x_preferred":[
        "Silea"
    ],
    "name:por_x_preferred":[
        "Silea"
    ],
    "name:ron_x_preferred":[
        "Silea"
    ],
    "name:rus_x_preferred":[
        "\u0421\u0438\u043b\u0435\u044f"
    ],
    "name:scn_x_preferred":[
        "Silea"
    ],
    "name:spa_x_preferred":[
        "Silea"
    ],
    "name:srp_x_preferred":[
        "\u0421\u0438\u043b\u0435\u0430"
    ],
    "name:tgl_x_preferred":[
        "Silea"
    ],
    "name:ukr_x_preferred":[
        "\u0421\u0456\u043b\u0435\u0430"
    ],
    "name:uzb_x_preferred":[
        "Silea"
    ],
    "name:vec_x_preferred":[
        "Si\u0142ea"
    ],
    "name:vie_x_preferred":[
        "Silea"
    ],
    "name:vol_x_preferred":[
        "Silea"
    ],
    "name:war_x_preferred":[
        "Silea"
    ],
    "name:zho_x_preferred":[
        "\u897f\u83b1\u4e9a"
    ],
    "wof:name":"Silea",
    "wof:placetype":"locality",
    "wof:population":490
},
  "geometry": {"coordinates":[24.11393,46.32699],"type":"Point"}
}