{
  "type": "Feature",
  "properties": {
    "gn:admin1_code":"01",
    "gn:admin2_code":"7810",
    "gn:asciiname":"Balomiru de Camp",
    "gn:cc2":"RO",
    "gn:country_code":"RO",
    "gn:dem":209,
    "gn:feature_class":"P",
    "gn:feature_code":"PPL",
    "gn:name":"Balomiru de C\u00e2mp",
    "gn:population":638,
    "gn:timezone":"Europe/Bucharest",
    "iso:country":"RO",
    "name:und_x_variant":[
        "Balomirul-de-C\u00e2mp",
        "Balomiru de Camp",
        "Balomiru de C\u00eemp"
    ],
    "wof:name":"Balomiru de Camp",
    "wof:placetype":"locality",
    "wof:population":638
},
  "geometry": {"coordinates":[23.36109,45.93878],"type":"Point"}
}