{
  "type": "Feature",
  "properties": {
    "gn:admin1_code":"14",
    "gn:admin2_code":"62707.0",
    "gn:asciiname":"Izvoru Mare",
    "gn:country_code":"RO",
    "gn:dem":90,
    "gn:feature_class":"P",
    "gn:feature_code":"PPL",
    "gn:name":"Izvoru Mare",
    "gn:population":0,
    "gn:timezone":"Europe/Bucharest",
    "iso:country":"RO",
    "name:und_x_variant":[
        "Isvoru Mare",
        "Izvorul-Mare",
        "Isvorul-Mare",
        "Mamutcuius",
        "Mamut-Kuius",
        "Izvoru Mare"
    ],
    "wof:name":"Izvoru Mare",
    "wof:placetype":"locality"
},
  "geometry": {"coordinates":[28.16667,44.15],"type":"Point"}
}