{
  "type": "Feature",
  "properties": {
    "gn:admin1_code":"08",
    "gn:admin2_code":"44391",
    "gn:asciiname":"Baldovinesti",
    "gn:country_code":"RO",
    "gn:dem":4,
    "gn:feature_class":"P",
    "gn:feature_code":"PPL",
    "gn:name":"Baldovine\u0219ti",
    "gn:population":1115,
    "gn:timezone":"Europe/Bucharest",
    "iso:country":"RO",
    "wof:name":"Baldovinesti",
    "wof:placetype":"locality",
    "wof:population":1115
},
  "geometry": {"coordinates":[27.91107,45.32182],"type":"Point"}
}