{
  "type": "Feature",
  "properties": {
    "gn:admin1_code":"39",
    "gn:admin2_code":"167473.0",
    "gn:asciiname":"Feteni",
    "gn:country_code":"RO",
    "gn:dem":441,
    "gn:feature_class":"P",
    "gn:feature_code":"PPL",
    "gn:name":"Fe\u021beni",
    "gn:population":277,
    "gn:timezone":"Europe/Bucharest",
    "iso:country":"RO",
    "wof:name":"Feteni",
    "wof:placetype":"locality",
    "wof:population":277
},
  "geometry": {"coordinates":[24.42471,45.09478],"type":"Point"}
}