{
  "type": "Feature",
  "properties": {
    "iso:country":"RO",
    "name:deu_x_preferred":[
        "Bukarest/Obor"
    ],
    "name:eng_x_preferred":[
        "Obor"
    ],
    "name:ita_x_preferred":[
        "Obor"
    ],
    "name:nld_x_preferred":[
        "Obor"
    ],
    "name:ron_x_preferred":[
        "Obor"
    ],
    "wof:lang_x_official":[
        "ron"
    ],
    "wof:lang_x_spoken":[
        "ron"
    ],
    "wof:name":"Obor",
    "wof:placetype":"neighbourhood"
},
  "geometry": {"coordinates":[26.127928,44.450701],"type":"Point"}
}