{
  "type": "Feature",
  "properties": {
    "iso:country":"RO",
    "name:deu_x_preferred":[
        "Bukarest/Obor"
    ],
    "name:eng_x_preferred":[
        "Obor"
    ],
    "name:ita_x_preferred":[
        "Obor"
    ],
    "name:nld_x_preferred":[
        "Obor"
    ],
    "name:ron_x_preferred":[
        "Obor"
    ],
    "wof:name":"Obor",
    "wof:placetype":"neighbourhood"
},
  "geometry": {"coordinates":[26.12792772554723,44.45070121884714],"type":"Point"}
}