{
  "type": "Feature",
  "properties": {
    "gn:admin1_code":"37",
    "gn:admin2_code":"160779",
    "gn:asciiname":"Maliuc",
    "gn:country_code":"RO",
    "gn:dem":3,
    "gn:feature_class":"P",
    "gn:feature_code":"PPLA2",
    "gn:name":"Maliuc",
    "gn:population":238,
    "gn:timezone":"Europe/Bucharest",
    "iso:country":"RO",
    "name:ceb_x_preferred":[
        "Comuna Maliuc"
    ],
    "name:ita_x_preferred":[
        "Maliuc"
    ],
    "name:msa_x_preferred":[
        "Maliuc"
    ],
    "name:nld_x_preferred":[
        "Maliuc"
    ],
    "name:por_x_preferred":[
        "Maliuc"
    ],
    "name:ron_x_preferred":[
        "Comuna Maliuc"
    ],
    "name:srp_x_preferred":[
        "\u041e\u043f\u0448\u0442\u0438\u043d\u0430 \u041c\u0430\u043b\u0438\u0443\u043a"
    ],
    "name:ukr_x_preferred":[
        "\u041c\u0430\u043b\u0456\u0443\u043a"
    ],
    "name:vie_x_preferred":[
        "Maliuc"
    ],
    "name:zho_x_preferred":[
        "\u99ac\u67f3\u514b\u9109"
    ],
    "wof:name":"Maliuc",
    "wof:placetype":"locality",
    "wof:population":238
},
  "geometry": {"coordinates":[29.11334,45.17678],"type":"Point"}
}