{
  "type": "Feature",
  "properties": {
    "gn:admin1_code":"37",
    "gn:admin2_code":"160779",
    "gn:asciiname":"Maliuc",
    "gn:country_code":"RO",
    "gn:dem":3,
    "gn:feature_class":"P",
    "gn:feature_code":"PPLA2",
    "gn:name":"Maliuc",
    "gn:population":238,
    "gn:timezone":"Europe/Bucharest",
    "iso:country":"RO",
    "wof:name":"Maliuc",
    "wof:placetype":"locality",
    "wof:population":238
},
  "geometry": {"coordinates":[29.11334,45.17678],"type":"Point"}
}