{
  "type": "Feature",
  "properties": {
    "gn:admin1_code":"40",
    "gn:admin2_code":"178689.0",
    "gn:asciiname":"Pietroasa",
    "gn:cc2":"RO",
    "gn:country_code":"RO",
    "gn:dem":271,
    "gn:feature_class":"P",
    "gn:feature_code":"PPL",
    "gn:name":"Pietroasa",
    "gn:population":227,
    "gn:timezone":"Europe/Bucharest",
    "iso:country":"RO",
    "name:und_x_variant":[
        "Petroasa"
    ],
    "wof:name":"Pietroasa",
    "wof:placetype":"locality",
    "wof:population":227
},
  "geometry": {"coordinates":[27.04411,45.70037],"type":"Point"}
}