{
  "type": "Feature",
  "properties": {
    "gn:admin1_code":"40",
    "gn:admin2_code":"178689.0",
    "gn:asciiname":"Pietroasa",
    "gn:cc2":"RO",
    "gn:country_code":"RO",
    "gn:dem":271,
    "gn:feature_class":"P",
    "gn:feature_code":"PPL",
    "gn:name":"Pietroasa",
    "gn:population":227,
    "gn:timezone":"Europe/Bucharest",
    "iso:country":"RO",
    "name:ceb_x_preferred":[
        "Pietroasa"
    ],
    "name:deu_x_preferred":[
        "Pietroasa"
    ],
    "name:epo_x_preferred":[
        "Pietroasa"
    ],
    "name:fra_x_preferred":[
        "Pietroasa"
    ],
    "name:hun_x_preferred":[
        "Pietroasa"
    ],
    "name:ita_x_preferred":[
        "Pietroasa"
    ],
    "name:nld_x_preferred":[
        "Pietroasa"
    ],
    "name:ron_x_preferred":[
        "Pietroasa"
    ],
    "name:srp_x_preferred":[
        "\u041f\u0438\u0435\u0442\u0440\u043e\u0430\u0441\u0430"
    ],
    "name:und_x_variant":[
        "Petroasa"
    ],
    "name:vol_x_preferred":[
        "Pietroasa"
    ],
    "wof:name":"Pietroasa",
    "wof:placetype":"locality",
    "wof:population":227
},
  "geometry": {"coordinates":[27.04411,45.70037],"type":"Point"}
}