{
  "type": "Feature",
  "properties": {
    "gn:admin1_code":"05",
    "gn:admin2_code":"27383",
    "gn:asciiname":"Arpasel",
    "gn:cc2":"RO",
    "gn:country_code":"RO",
    "gn:dem":99,
    "gn:feature_class":"P",
    "gn:feature_code":"PPL",
    "gn:name":"Arp\u0103\u0219el",
    "gn:population":905,
    "gn:timezone":"Europe/Bucharest",
    "iso:country":"RO",
    "name:und_x_variant":[
        "Arpod",
        "Arp\u0103\u015fel"
    ],
    "wof:name":"Arpasel",
    "wof:placetype":"locality",
    "wof:population":905
},
  "geometry": {"coordinates":[21.71968,46.73863],"type":"Point"}
}