{
  "type": "Feature",
  "properties": {
    "gn:admin1_code":"05",
    "gn:admin2_code":"27686.0",
    "gn:asciiname":"Damis",
    "gn:country_code":"RO",
    "gn:dem":712,
    "gn:feature_class":"P",
    "gn:feature_code":"PPL",
    "gn:name":"Dami\u0219",
    "gn:population":883,
    "gn:timezone":"Europe/Bucharest",
    "iso:country":"RO",
    "wof:name":"Damis",
    "wof:placetype":"locality",
    "wof:population":883
},
  "geometry": {"coordinates":[22.55312,46.86751],"type":"Point"}
}