{
  "type": "Feature",
  "properties": {
    "gn:admin1_code":"41",
    "gn:admin2_code":"101083.0",
    "gn:asciiname":"Mataraua",
    "gn:country_code":"RO",
    "gn:dem":60,
    "gn:feature_class":"P",
    "gn:feature_code":"PPL",
    "gn:name":"Mataraua",
    "gn:population":40,
    "gn:timezone":"Europe/Bucharest",
    "iso:country":"RO",
    "wof:name":"Mataraua",
    "wof:placetype":"locality",
    "wof:population":40
},
  "geometry": {"coordinates":[26.46117000000001,44.55132],"type":"Point"}
}