{
  "type": "Feature",
  "properties": {
    "gn:admin1_code":"27",
    "gn:admin2_code":"117667.0",
    "gn:asciiname":"Fanate",
    "gn:country_code":"RO",
    "gn:dem":338,
    "gn:feature_class":"P",
    "gn:feature_code":"PPL",
    "gn:name":"F\u00e2na\u021be",
    "gn:population":0,
    "gn:timezone":"Europe/Bucharest",
    "iso:country":"RO",
    "name:hun_x_preferred":[
        "Sz\u00e9naf\u0171"
    ],
    "wof:name":"Fanate",
    "wof:placetype":"locality"
},
  "geometry": {"coordinates":[24.22104,46.53401],"type":"Point"}
}