{
  "type": "Feature",
  "properties": {
    "gn:admin1_code":"34",
    "gn:admin2_code":"148916.0",
    "gn:asciiname":"Miningeni",
    "gn:country_code":"RO",
    "gn:dem":327,
    "gn:feature_class":"P",
    "gn:feature_code":"PPL",
    "gn:name":"Miningeni",
    "gn:population":0,
    "gn:timezone":"Europe/Bucharest",
    "iso:country":"RO",
    "wof:name":"Miningeni",
    "wof:placetype":"locality"
},
  "geometry": {"coordinates":[26.13333,47.91667],"type":"Point"}
}