{
  "type": "Feature",
  "properties": {
    "gn:country":"RO",
    "gn:fcode":"PPL",
    "gn:population":0,
    "iso:country":"RO",
    "name:ceb_x_preferred":[
        "Suseni"
    ],
    "name:deu_x_preferred":[
        "Suseni"
    ],
    "name:epo_x_preferred":[
        "Suseni"
    ],
    "name:fra_x_preferred":[
        "Suseni"
    ],
    "name:hrv_x_preferred":[
        "Suseni"
    ],
    "name:hun_x_preferred":[
        "Suseni"
    ],
    "name:ita_x_preferred":[
        "Suseni"
    ],
    "name:nld_x_preferred":[
        "Suseni"
    ],
    "name:ron_x_preferred":[
        "Suseni"
    ],
    "name:srp_x_preferred":[
        "\u0421\u0443\u0441\u0435\u043d\u0438"
    ],
    "name:und_x_variant":[
        "S\u0103seni"
    ],
    "name:vol_x_preferred":[
        "Suseni"
    ],
    "qs_pg:aaroncc":"RO",
    "qs_pg:gn_country":"RO",
    "qs_pg:gn_fcode":"PPL",
    "qs_pg:gn_pop":0,
    "qs_pg:name":"Suseni",
    "qs_pg:name_adm0":"Rom\u00e2nia",
    "qs_pg:name_adm1":"Hunedoara",
    "qs_pg:photos":5,
    "qs_pg:photos_1k":1,
    "qs_pg:photos_9k":1,
    "qs_pg:photos_9r":1,
    "qs_pg:photos_all":5,
    "qs_pg:photos_sr":1,
    "qs_pg:pop_sr":0,
    "qs_pg:qs_pg_placetype":"locality",
    "qs_pg:qs_pg_placetype_gp":"Town",
    "qs_pg:woe_adm0":23424933,
    "woe:adm0_id":23424933,
    "woe:name_adm0":"Rom\u00e2nia",
    "woe:name_adm1":"Hunedoara",
    "woe:placetype":"Town",
    "wof:name":"Suseni",
    "wof:placetype":"locality",
    "wof:population":219
},
  "geometry": {"coordinates":[22.86667,45.48333],"type":"Point"}
}