{
  "type": "Feature",
  "properties": {
    "gn:admin1_code":"35",
    "gn:admin2_code":"155136.0",
    "gn:asciiname":"Purani",
    "gn:cc2":"RO",
    "gn:country_code":"RO",
    "gn:dem":122,
    "gn:feature_class":"P",
    "gn:feature_code":"PPLA2",
    "gn:name":"Purani",
    "gn:population":801,
    "gn:timezone":"Europe/Bucharest",
    "iso:country":"RO",
    "name:ceb_x_preferred":[
        "Comuna Purani"
    ],
    "name:ita_x_preferred":[
        "Purani"
    ],
    "name:msa_x_preferred":[
        "Purani"
    ],
    "name:nld_x_preferred":[
        "Purani"
    ],
    "name:por_x_preferred":[
        "Purani"
    ],
    "name:ron_x_preferred":[
        "Comuna Purani"
    ],
    "name:srp_x_preferred":[
        "\u041e\u043f\u0448\u0442\u0438\u043d\u0430 \u041f\u0443\u0440\u0430\u043d\u0438"
    ],
    "name:ukr_x_preferred":[
        "\u041f\u0443\u0440\u0430\u043d\u044c"
    ],
    "name:und_x_variant":[
        "Puranii de Jos"
    ],
    "name:vol_x_preferred":[
        "Purani"
    ],
    "name:zho_x_preferred":[
        "\u666e\u62c9\u5c3c\u9109"
    ],
    "wof:name":"Purani",
    "wof:placetype":"locality",
    "wof:population":801
},
  "geometry": {"coordinates":[25.42528,44.36125],"type":"Point"}
}