{
  "type": "Feature",
  "properties": {
    "gn:admin1_code":"35",
    "gn:admin2_code":"155136.0",
    "gn:asciiname":"Purani",
    "gn:cc2":"RO",
    "gn:country_code":"RO",
    "gn:dem":122,
    "gn:feature_class":"P",
    "gn:feature_code":"PPLA2",
    "gn:name":"Purani",
    "gn:population":801,
    "gn:timezone":"Europe/Bucharest",
    "iso:country":"RO",
    "name:und_x_variant":[
        "Puranii de Jos",
        "Purani"
    ],
    "wof:name":"Purani",
    "wof:placetype":"locality",
    "wof:population":801
},
  "geometry": {"coordinates":[25.42528,44.36125],"type":"Point"}
}