{
  "type": "Feature",
  "properties": {
    "gn:admin1_code":"01",
    "gn:admin2_code":"7446.0",
    "gn:asciiname":"Moraresti",
    "gn:country_code":"RO",
    "gn:dem":802,
    "gn:feature_class":"P",
    "gn:feature_code":"PPL",
    "gn:name":"Mor\u0103re\u0219ti",
    "gn:population":43,
    "gn:timezone":"Europe/Bucharest",
    "iso:country":"RO",
    "wof:name":"Moraresti",
    "wof:placetype":"locality",
    "wof:population":43
},
  "geometry": {"coordinates":[23.02368,46.33709],"type":"Point"}
}