{
  "type": "Feature",
  "properties": {
    "gn:admin1_code":"11",
    "gn:admin2_code":"47186.0",
    "gn:asciiname":"Pestritu",
    "gn:country_code":"RO",
    "gn:dem":643,
    "gn:feature_class":"P",
    "gn:feature_code":"PPL",
    "gn:name":"Pestri\u021bu",
    "gn:population":116,
    "gn:timezone":"Europe/Bucharest",
    "iso:country":"RO",
    "wof:name":"Pestritu",
    "wof:placetype":"locality",
    "wof:population":116
},
  "geometry": {"coordinates":[26.54332,45.4883],"type":"Point"}
}