{
  "type": "Feature",
  "properties": {
    "gn:gn_country":"RO",
    "gn:gn_fcode":"PPLA2",
    "gn:gn_pop":3769,
    "gn:population":3769,
    "iso:country":"RO",
    "name:eng_x_preferred":[
        "Ro\u0219ie\u0219ti"
    ],
    "name:fra_x_preferred":[
        "Ro\u0219ie\u0219ti"
    ],
    "name:nld_x_preferred":[
        "Ro\u0219ie\u0219ti"
    ],
    "name:ron_x_preferred":[
        "Ro\u0219ie\u0219ti"
    ],
    "name:ukr_x_preferred":[
        "\u0420\u043e\u0448\u0456\u0454\u0448\u0442\u044c"
    ],
    "name:unk_x_variant":[
        "Ro\u015fie\u015fti"
    ],
    "qs_pg:aaroncc":"RO",
    "qs_pg:gn_country":"RO",
    "qs_pg:gn_fcode":"PPLA2",
    "qs_pg:gn_pop":3769,
    "qs_pg:name":"Ro\u0219ie\u015fti",
    "qs_pg:name_adm0":"Rom\u00e2nia",
    "qs_pg:name_adm1":"Vaslui",
    "qs_pg:photos_9r":0,
    "qs_pg:photos_sr":0,
    "qs_pg:pop_sr":4,
    "qs_pg:qs_pg_placetype":"locality",
    "qs_pg:qs_pg_placetype_gp":"Town",
    "qs_pg:woe_adm0":23424933,
    "woe:adm0_id":23424933,
    "woe:name_adm0":"Rom\u00e2nia",
    "woe:name_adm1":"Vaslui",
    "woe:placetype":"Town",
    "wof:name":"Ro\u0219ie\u015fti",
    "wof:placetype":"locality",
    "wof:population":3769
},
  "geometry": {"coordinates":[27.88333,46.43333],"type":"Point"}
}