{
  "type": "Feature",
  "properties": {
    "gn:admin1_code":"01",
    "gn:admin2_code":"7446.0",
    "gn:asciiname":"Medresti",
    "gn:country_code":"RO",
    "gn:dem":914,
    "gn:feature_class":"P",
    "gn:feature_code":"PPL",
    "gn:name":"Medre\u0219ti",
    "gn:population":6,
    "gn:timezone":"Europe/Bucharest",
    "iso:country":"RO",
    "wof:name":"Medresti",
    "wof:placetype":"locality",
    "wof:population":6
},
  "geometry": {"coordinates":[22.95295,46.29567],"type":"Point"}
}