{
  "type": "Feature",
  "properties": {
    "gn:admin1_code":"39",
    "gn:admin2_code":"170220.0",
    "gn:asciiname":"Opatesti",
    "gn:country_code":"RO",
    "gn:dem":369,
    "gn:feature_class":"P",
    "gn:feature_code":"PPL",
    "gn:name":"Op\u0103te\u0219ti",
    "gn:population":204,
    "gn:timezone":"Europe/Bucharest",
    "iso:country":"RO",
    "wof:name":"Opatesti",
    "wof:placetype":"locality",
    "wof:population":204
},
  "geometry": {"coordinates":[24.4733,45.10978],"type":"Point"}
}