{
  "type": "Feature",
  "properties": {
    "gn:admin1_code":"14",
    "gn:admin2_code":"62057.0",
    "gn:asciiname":"Coslugea",
    "gn:country_code":"RO",
    "gn:dem":57,
    "gn:feature_class":"P",
    "gn:feature_code":"PPL",
    "gn:name":"Coslugea",
    "gn:population":860,
    "gn:timezone":"Europe/Bucharest",
    "iso:country":"RO",
    "wof:name":"Coslugea",
    "wof:placetype":"locality",
    "wof:population":860
},
  "geometry": {"coordinates":[27.57872,44.11878],"type":"Point"}
}