{
  "type": "Feature",
  "properties": {
    "gn:admin1_code":"28",
    "gn:admin2_code":"121153.0",
    "gn:asciiname":"Liliac",
    "gn:cc2":"RO",
    "gn:country_code":"RO",
    "gn:dem":232,
    "gn:feature_class":"P",
    "gn:feature_code":"PPL",
    "gn:name":"Liliac",
    "gn:population":120,
    "gn:timezone":"Europe/Bucharest",
    "iso:country":"RO",
    "name:und_x_variant":[
        "Liliacu",
        "Liliac"
    ],
    "wof:name":"Liliac",
    "wof:placetype":"locality",
    "wof:population":120
},
  "geometry": {"coordinates":[26.83031,46.78743],"type":"Point"}
}