{
  "type": "Feature",
  "properties": {
    "gn:admin1_code":"28",
    "gn:admin2_code":"122613.0",
    "gn:asciiname":"Micsunesti",
    "gn:country_code":"RO",
    "gn:dem":369,
    "gn:feature_class":"P",
    "gn:feature_code":"PPL",
    "gn:name":"Mic\u0219une\u0219ti",
    "gn:population":217,
    "gn:timezone":"Europe/Bucharest",
    "iso:country":"RO",
    "wof:name":"Micsunesti",
    "wof:placetype":"locality",
    "wof:population":217
},
  "geometry": {"coordinates":[26.71055,46.89826],"type":"Point"}
}