{
  "type": "Feature",
  "properties": {
    "gn:admin1_code":"08",
    "gn:admin2_code":"43117.0",
    "gn:asciiname":"Stoienesti",
    "gn:country_code":"RO",
    "gn:dem":4,
    "gn:feature_class":"P",
    "gn:feature_code":"PPL",
    "gn:name":"Stoiene\u0219ti",
    "gn:population":37,
    "gn:timezone":"Europe/Bucharest",
    "iso:country":"RO",
    "wof:name":"Stoienesti",
    "wof:placetype":"locality",
    "wof:population":37
},
  "geometry": {"coordinates":[28.03874,44.79793],"type":"Point"}
}