{
  "type": "Feature",
  "properties": {
    "gn:admin1_code":"25",
    "gn:admin2_code":"109425",
    "gn:asciiname":"Aspra",
    "gn:country_code":"RO",
    "gn:dem":502,
    "gn:feature_class":"P",
    "gn:feature_code":"PPL",
    "gn:name":"Aspra",
    "gn:population":74,
    "gn:timezone":"Europe/Bucharest",
    "iso:country":"RO",
    "name:ita_x_preferred":[
        "Aspra"
    ],
    "name:ron_x_preferred":[
        "Aspra"
    ],
    "wof:name":"Aspra",
    "wof:placetype":"locality",
    "wof:population":74
},
  "geometry": {"coordinates":[23.63818,47.45021],"type":"Point"}
}