{
  "type": "Feature",
  "properties": {
    "gn:admin1_code":"29",
    "gn:admin2_code":"126585.0",
    "gn:asciiname":"Zanoaga",
    "gn:country_code":"RO",
    "gn:dem":74,
    "gn:feature_class":"P",
    "gn:feature_code":"PPL",
    "gn:name":"Z\u0103noaga",
    "gn:population":491,
    "gn:timezone":"Europe/Bucharest",
    "iso:country":"RO",
    "wof:name":"Zanoaga",
    "wof:placetype":"locality",
    "wof:population":491
},
  "geometry": {"coordinates":[24.61097,44.10386],"type":"Point"}
}