{
  "type": "Feature",
  "properties": {
    "gn:admin1_code":"21",
    "gn:admin2_code":"90725.0",
    "gn:asciiname":"Gotesti",
    "gn:cc2":"RO",
    "gn:country_code":"RO",
    "gn:dem":782,
    "gn:feature_class":"P",
    "gn:feature_code":"PPL",
    "gn:name":"Gote\u0219ti",
    "gn:population":10,
    "gn:timezone":"Europe/Bucharest",
    "iso:country":"RO",
    "name:und_x_variant":[
        "Cote\u015fti",
        "Gote\u015fti"
    ],
    "wof:name":"Gotesti",
    "wof:placetype":"locality",
    "wof:population":10
},
  "geometry": {"coordinates":[22.67439,45.61058],"type":"Point"}
}