{
  "type": "Feature",
  "properties": {
    "gn:admin1_code":"31",
    "gn:admin2_code":"142177.0",
    "gn:asciiname":"Cheud",
    "gn:country_code":"RO",
    "gn:dem":185,
    "gn:feature_class":"P",
    "gn:feature_code":"PPL",
    "gn:name":"Cheud",
    "gn:population":920,
    "gn:timezone":"Europe/Bucharest",
    "iso:country":"RO",
    "wof:name":"Cheud",
    "wof:placetype":"locality",
    "wof:population":920
},
  "geometry": {"coordinates":[23.31612,47.38374],"type":"Point"}
}