{
  "type": "Feature",
  "properties": {
    "gn:admin1_code":"18",
    "gn:admin2_code":"76406.0",
    "gn:asciiname":"Slobozia Corni",
    "gn:country_code":"RO",
    "gn:dem":48,
    "gn:feature_class":"P",
    "gn:feature_code":"PPL",
    "gn:name":"Slobozia Corni",
    "gn:population":656,
    "gn:timezone":"Europe/Bucharest",
    "iso:country":"RO",
    "wof:name":"Slobozia Corni",
    "wof:placetype":"locality",
    "wof:population":656
},
  "geometry": {"coordinates":[27.48034,45.99166],"type":"Point"}
}