{
  "type": "Feature",
  "properties": {
    "gn:admin1_code":"14",
    "gn:admin2_code":"61210.0",
    "gn:asciiname":"Credinta",
    "gn:cc2":"RO",
    "gn:country_code":"RO",
    "gn:dem":69,
    "gn:feature_class":"P",
    "gn:feature_code":"PPL",
    "gn:name":"Credin\u021ba",
    "gn:population":311,
    "gn:timezone":"Europe/Bucharest",
    "iso:country":"RO",
    "name:und_x_variant":[
        "Sofular",
        "Credin\u0163a"
    ],
    "wof:name":"Credinta",
    "wof:placetype":"locality",
    "wof:population":311
},
  "geometry": {"coordinates":[28.24045,43.97861],"type":"Point"}
}