{
  "type": "Feature",
  "properties": {
    "gn:admin1_code":"27",
    "gn:admin2_code":"115637.0",
    "gn:asciiname":"Filitelnic",
    "gn:cc2":"RO",
    "gn:country_code":"RO",
    "gn:dem":355,
    "gn:feature_class":"P",
    "gn:feature_code":"PPL",
    "gn:name":"Filitelnic",
    "gn:population":270,
    "gn:timezone":"Europe/Bucharest",
    "iso:country":"RO",
    "name:und_x_variant":[
        "F\u00fcletelke",
        "Filitelnic"
    ],
    "wof:name":"Filitelnic",
    "wof:placetype":"locality",
    "wof:population":270
},
  "geometry": {"coordinates":[24.66911,46.36656],"type":"Point"}
}