{
  "type": "Feature",
  "properties": {
    "gn:admin1_code":"15",
    "gn:admin2_code":"65048.0",
    "gn:asciiname":"Peteni",
    "gn:cc2":"RO",
    "gn:country_code":"RO",
    "gn:dem":545,
    "gn:feature_class":"P",
    "gn:feature_code":"PPL",
    "gn:name":"Peteni",
    "gn:population":160,
    "gn:timezone":"Europe/Bucharest",
    "iso:country":"RO",
    "name:und_x_variant":[
        "Pec\u00f6falva",
        "Pet\u0151falva",
        "Peteni"
    ],
    "wof:name":"Peteni",
    "wof:placetype":"locality",
    "wof:population":160
},
  "geometry": {"coordinates":[26.1447,45.92123],"type":"Point"}
}