{
  "type": "Feature",
  "properties": {
    "gn:admin1_code":"31",
    "gn:admin2_code":"142952.0",
    "gn:asciiname":"Valcau de Sus",
    "gn:cc2":"RO",
    "gn:country_code":"RO",
    "gn:dem":260,
    "gn:feature_class":"P",
    "gn:feature_code":"PPL",
    "gn:name":"Valc\u0103u de Sus",
    "gn:population":904,
    "gn:timezone":"Europe/Bucharest",
    "iso:country":"RO",
    "name:und_x_variant":[
        "V\u0103lc\u0103ul-de-Sus",
        "Valc\u0103u de Sus"
    ],
    "wof:name":"Valcau de Sus",
    "wof:placetype":"locality",
    "wof:population":904
},
  "geometry": {"coordinates":[22.72988,47.1145],"type":"Point"}
}