{
  "type": "Feature",
  "properties": {
    "gn:admin1_code":"09",
    "gn:admin2_code":"41667.0",
    "gn:asciiname":"Stupinii Prejmerului",
    "gn:cc2":"RO",
    "gn:country_code":"RO",
    "gn:dem":516,
    "gn:feature_class":"P",
    "gn:feature_code":"PPL",
    "gn:name":"Stupinii Prejmerului",
    "gn:population":387,
    "gn:timezone":"Europe/Bucharest",
    "iso:country":"RO",
    "name:und_x_variant":[
        "Stupini",
        "Stupinii-Prejmerului"
    ],
    "wof:name":"Stupinii Prejmerului",
    "wof:placetype":"locality",
    "wof:population":387
},
  "geometry": {"coordinates":[25.81914,45.71763],"type":"Point"}
}