{
  "type": "Feature",
  "properties": {
    "gn:admin1_code":"23",
    "gn:admin2_code":"95612.0",
    "gn:asciiname":"Volintiresti",
    "gn:country_code":"RO",
    "gn:dem":203,
    "gn:feature_class":"P",
    "gn:feature_code":"PPL",
    "gn:name":"Volintire\u015fti",
    "gn:population":0,
    "gn:timezone":"Europe/Bucharest",
    "iso:country":"RO",
    "name:und_x_variant":[
        "Gog\u0103lniceanu",
        "Volintire\u015fti"
    ],
    "wof:lang_x_official":[
        "ron"
    ],
    "wof:lang_x_spoken":[
        "ron"
    ],
    "wof:name":"Volintiresti",
    "wof:placetype":"locality"
},
  "geometry": {"coordinates":[26.85,47.13333],"type":"Point"}
}