{
  "type": "Feature",
  "properties": {
    "iso:country":"RO",
    "qs_pg:aaroncc":"RO",
    "qs_pg:name":"T\u00eergu Mure\u0219",
    "qs_pg:name_adm0":"Rom\u00e2nia",
    "qs_pg:name_adm1":"Mures",
    "qs_pg:photos":4465,
    "qs_pg:photos_1k":905,
    "qs_pg:photos_9k":20,
    "qs_pg:photos_9r":13,
    "qs_pg:photos_all":4465,
    "qs_pg:photos_sr":23,
    "qs_pg:pop_sr":0,
    "qs_pg:qs_pg_placetype":"locality",
    "qs_pg:qs_pg_placetype_gp":"Town",
    "qs_pg:woe_adm0":23424933,
    "woe:adm0_id":23424933,
    "woe:name_adm0":"Rom\u00e2nia",
    "woe:name_adm1":"Mures",
    "woe:placetype":"Town",
    "wof:name":"T\u00eergu Mure\u0219",
    "wof:placetype":"locality"
},
  "geometry": {"coordinates":[24.561406,46.544192],"type":"Point"}
}