{
  "type": "Feature",
  "properties": {
    "gn:admin1_code":"21",
    "gn:admin2_code":"89687.0",
    "gn:asciiname":"Campuri-Surduc",
    "gn:cc2":"RO",
    "gn:country_code":"RO",
    "gn:dem":178,
    "gn:feature_class":"P",
    "gn:feature_code":"PPL",
    "gn:name":"C\u00e2mpuri-Surduc",
    "gn:population":376,
    "gn:timezone":"Europe/Bucharest",
    "iso:country":"RO",
    "name:und_x_variant":[
        "C\u00e2mpuri Surduc",
        "C\u00eempuri-Surduc"
    ],
    "wof:name":"Campuri-Surduc",
    "wof:placetype":"locality",
    "wof:population":376
},
  "geometry": {"coordinates":[22.55365,45.93944000000001],"type":"Point"}
}