{
  "type": "Feature",
  "properties": {
    "gn:admin1_code":"05",
    "gn:admin2_code":"28530.0",
    "gn:asciiname":"Haucesti",
    "gn:country_code":"RO",
    "gn:dem":161,
    "gn:feature_class":"P",
    "gn:feature_code":"PPL",
    "gn:name":"H\u0103uce\u0219ti",
    "gn:population":89,
    "gn:timezone":"Europe/Bucharest",
    "iso:country":"RO",
    "wof:name":"Haucesti",
    "wof:placetype":"locality",
    "wof:population":89
},
  "geometry": {"coordinates":[22.20321,47.22813],"type":"Point"}
}