{
  "type": "Feature",
  "properties": {
    "gn:admin1_code":"01",
    "gn:admin2_code":"5826.0",
    "gn:asciiname":"Negresti",
    "gn:cc2":"RO",
    "gn:country_code":"RO",
    "gn:dem":922,
    "gn:feature_class":"P",
    "gn:feature_code":"PPL",
    "gn:name":"Negre\u0219ti",
    "gn:population":22,
    "gn:timezone":"Europe/Bucharest",
    "iso:country":"RO",
    "name:und_x_variant":[
        "Negre\u015fti",
        "Nege\u015fti"
    ],
    "wof:name":"Negresti",
    "wof:placetype":"locality",
    "wof:population":22
},
  "geometry": {"coordinates":[23.31925,46.26877],"type":"Point"}
}