{
  "type": "Feature",
  "properties": {
    "gn:admin1_code":"04",
    "gn:admin2_code":"23047.0",
    "gn:asciiname":"Floresti",
    "gn:cc2":"RO",
    "gn:country_code":"RO",
    "gn:dem":201,
    "gn:feature_class":"P",
    "gn:feature_code":"PPL",
    "gn:name":"Flore\u0219ti",
    "gn:population":232,
    "gn:timezone":"Europe/Bucharest",
    "iso:country":"RO",
    "name:und_x_variant":[
        "Flore\u015ftii",
        "Flore\u015fti"
    ],
    "wof:name":"Floresti",
    "wof:placetype":"locality",
    "wof:population":232
},
  "geometry": {"coordinates":[27.2248,46.25846],"type":"Point"}
}