{
  "type": "Feature",
  "properties": {
    "gn:admin1_code":"11",
    "gn:admin2_code":"45959.0",
    "gn:asciiname":"Catunu",
    "gn:country_code":"RO",
    "gn:dem":411,
    "gn:feature_class":"P",
    "gn:feature_code":"PPL",
    "gn:name":"C\u0103tunu",
    "gn:population":0,
    "gn:timezone":"Europe/Bucharest",
    "iso:country":"RO",
    "wof:name":"Catunu",
    "wof:placetype":"locality"
},
  "geometry": {"coordinates":[26.25,45.31667],"type":"Point"}
}