{
  "type": "Feature",
  "properties": {
    "gn:admin1_code":"34",
    "gn:admin2_code":"148202.0",
    "gn:asciiname":"Poiana Negrii",
    "gn:cc2":"RO",
    "gn:country_code":"RO",
    "gn:dem":887,
    "gn:feature_class":"P",
    "gn:feature_code":"PPL",
    "gn:name":"Poiana Negrii",
    "gn:population":981,
    "gn:timezone":"Europe/Bucharest",
    "iso:country":"RO",
    "name:und_x_variant":[
        "Borkut",
        "Poiana-Negri",
        "Poiana Negrii"
    ],
    "wof:name":"Poiana Negrii",
    "wof:placetype":"locality",
    "wof:population":981
},
  "geometry": {"coordinates":[25.22078,47.32207],"type":"Point"}
}