{
  "type": "Feature",
  "properties": {
    "gn:admin1_code":"01",
    "gn:admin2_code":"7945.0",
    "gn:asciiname":"Carpenii de Sus",
    "gn:cc2":"RO",
    "gn:country_code":"RO",
    "gn:dem":398,
    "gn:feature_class":"P",
    "gn:feature_code":"PPL",
    "gn:name":"Carpenii de Sus",
    "gn:population":4,
    "gn:timezone":"Europe/Bucharest",
    "iso:country":"RO",
    "name:und_x_variant":[
        "Carpen",
        "Carpenii de Sus"
    ],
    "wof:name":"Carpenii de Sus",
    "wof:placetype":"locality",
    "wof:population":4
},
  "geometry": {"coordinates":[23.70768,45.99277],"type":"Point"}
}