{
  "type": "Feature",
  "properties": {
    "gn:admin1_code":"30",
    "gn:admin2_code":"135949.0",
    "gn:asciiname":"Valea Mantei",
    "gn:country_code":"RO",
    "gn:dem":213,
    "gn:feature_class":"P",
    "gn:feature_code":"PPL",
    "gn:name":"Valea Mantei",
    "gn:population":322,
    "gn:timezone":"Europe/Bucharest",
    "iso:country":"RO",
    "wof:name":"Valea Mantei",
    "wof:placetype":"locality",
    "wof:population":322
},
  "geometry": {"coordinates":[26.16329,44.97632],"type":"Point"}
}