{
  "type": "Feature",
  "properties": {
    "gn:admin1_code":"05",
    "gn:admin2_code":"29724.0",
    "gn:asciiname":"Husasau de Cris",
    "gn:cc2":"RO",
    "gn:country_code":"RO",
    "gn:dem":157,
    "gn:feature_class":"P",
    "gn:feature_code":"PPL",
    "gn:name":"Husas\u0103u de Cri\u0219",
    "gn:population":877,
    "gn:timezone":"Europe/Bucharest",
    "iso:country":"RO",
    "name:hun_x_preferred":[
        "K\u00f6r\u00f6skis\u00fajfalu"
    ],
    "name:und_x_variant":[
        "Husas\u0103ul de Cri\u015f",
        "Husas\u0103u de Cri\u015f"
    ],
    "wof:name":"Husasau de Cris",
    "wof:placetype":"locality",
    "wof:population":877
},
  "geometry": {"coordinates":[22.06423,47.0855],"type":"Point"}
}