{
  "type": "Feature",
  "properties": {
    "gn:admin1_code":"11",
    "gn:admin2_code":"49073",
    "gn:asciiname":"Bordusani",
    "gn:cc2":"RO",
    "gn:country_code":"RO",
    "gn:dem":73,
    "gn:feature_class":"P",
    "gn:feature_code":"PPL",
    "gn:name":"Bordu\u0219ani",
    "gn:population":461,
    "gn:timezone":"Europe/Bucharest",
    "iso:country":"RO",
    "name:und_x_variant":[
        "Bordu\u015fani-Coiteasca",
        "Bordo\u015fanii-Coiteasca",
        "Bordu\u015fani"
    ],
    "wof:name":"Bordusani",
    "wof:placetype":"locality",
    "wof:population":461
},
  "geometry": {"coordinates":[26.96864,45.10857],"type":"Point"}
}