{
  "type": "Feature",
  "properties": {
    "gn:admin1_code":"05",
    "gn:admin2_code":"27971.0",
    "gn:asciiname":"Lelesti",
    "gn:country_code":"RO",
    "gn:dem":238,
    "gn:feature_class":"P",
    "gn:feature_code":"PPL",
    "gn:name":"Lele\u0219ti",
    "gn:population":514,
    "gn:timezone":"Europe/Bucharest",
    "iso:country":"RO",
    "name:ron_x_preferred":[
        "Lele\u0219ti"
    ],
    "name:und_x_variant":[
        "Lelesd"
    ],
    "wof:name":"Lelesti",
    "wof:placetype":"locality",
    "wof:population":514
},
  "geometry": {"coordinates":[22.45709,46.62012],"type":"Point"}
}