{
  "type": "Feature",
  "properties": {
    "gn:admin1_code":"28",
    "gn:admin2_code":"123255.0",
    "gn:asciiname":"Ciornei",
    "gn:country_code":"RO",
    "gn:dem":174,
    "gn:feature_class":"P",
    "gn:feature_code":"PPL",
    "gn:name":"Ciornei",
    "gn:population":97,
    "gn:timezone":"Europe/Bucharest",
    "iso:country":"RO",
    "wof:name":"Ciornei",
    "wof:placetype":"locality",
    "wof:population":97
},
  "geometry": {"coordinates":[27.17704,46.80228],"type":"Point"}
}