{
  "type": "Feature",
  "properties": {
    "gn:admin1_code":"01",
    "gn:admin2_code":"7197.0",
    "gn:asciiname":"Runc",
    "gn:cc2":"RO",
    "gn:country_code":"RO",
    "gn:dem":1036,
    "gn:feature_class":"P",
    "gn:feature_code":"PPL",
    "gn:name":"Runc",
    "gn:population":194,
    "gn:timezone":"Europe/Bucharest",
    "iso:country":"RO",
    "name:ceb_x_preferred":[
        "Runc"
    ],
    "name:deu_x_preferred":[
        "Runc"
    ],
    "name:epo_x_preferred":[
        "Runc"
    ],
    "name:hun_x_preferred":[
        "Runc"
    ],
    "name:ron_x_preferred":[
        "Runc"
    ],
    "name:und_x_variant":[
        "Runa"
    ],
    "wof:name":"Runc",
    "wof:placetype":"locality",
    "wof:population":194
},
  "geometry": {"coordinates":[22.88863,46.47983],"type":"Point"}
}