{
  "type": "Feature",
  "properties": {
    "iso:country":"RO",
    "name:eng_x_preferred":[
        "Soarelui"
    ],
    "name:ron_x_preferred":[
        "Soarelui"
    ],
    "wof:name":"Soarelui",
    "wof:placetype":"neighbourhood"
},
  "geometry": {"coordinates":[21.24559051548548,45.73423965764543],"type":"Point"}
}