{
  "type": "Feature",
  "properties": {
    "iso:country":"RO",
    "name:eng_x_preferred":[
        "Soarelui"
    ],
    "name:ron_x_preferred":[
        "Soarelui"
    ],
    "wof:lang_x_official":[
        "ron"
    ],
    "wof:lang_x_spoken":[
        "ron"
    ],
    "wof:name":"Soarelui",
    "wof:placetype":"neighbourhood"
},
  "geometry": {"coordinates":[21.245591,45.73424],"type":"Point"}
}