{
  "type": "Feature",
  "properties": {
    "gn:admin1_code":"19",
    "gn:admin2_code":"81264.0",
    "gn:asciiname":"Valeni",
    "gn:cc2":"RO",
    "gn:country_code":"RO",
    "gn:dem":140,
    "gn:feature_class":"P",
    "gn:feature_code":"PPL",
    "gn:name":"V\u0103leni",
    "gn:population":965,
    "gn:timezone":"Europe/Bucharest",
    "iso:country":"RO",
    "name:und_x_variant":[
        "Valenii",
        "V\u0103leni"
    ],
    "wof:name":"Valeni",
    "wof:placetype":"locality",
    "wof:population":965
},
  "geometry": {"coordinates":[23.3867,44.74088],"type":"Point"}
}