{
  "type": "Feature",
  "properties": {
    "gn:admin1_code":"12",
    "gn:admin2_code":"52160.0",
    "gn:asciiname":"Lunca Florii",
    "gn:country_code":"RO",
    "gn:dem":875,
    "gn:feature_class":"P",
    "gn:feature_code":"PPL",
    "gn:name":"Lunca Florii",
    "gn:population":91,
    "gn:timezone":"Europe/Bucharest",
    "iso:country":"RO",
    "wof:name":"Lunca Florii",
    "wof:placetype":"locality",
    "wof:population":91
},
  "geometry": {"coordinates":[22.46967,45.07946],"type":"Point"}
}