{
  "type": "Feature",
  "properties": {
    "gn:admin1_code":"38",
    "gn:admin2_code":"167268.0",
    "gn:asciiname":"Crang",
    "gn:cc2":"RO",
    "gn:country_code":"RO",
    "gn:dem":215,
    "gn:feature_class":"P",
    "gn:feature_code":"PPL",
    "gn:name":"Cr\u00e2ng",
    "gn:population":395,
    "gn:timezone":"Europe/Bucharest",
    "iso:country":"RO",
    "name:und_x_variant":[
        "Cr\u00e2ng",
        "Cr\u00e2ngu",
        "Cr\u00e2ngul",
        "Cr\u00eeng"
    ],
    "wof:name":"Crang",
    "wof:placetype":"locality",
    "wof:population":395
},
  "geometry": {"coordinates":[27.61091,46.24557],"type":"Point"}
}