{
  "type": "Feature",
  "properties": {
    "iso:country":"RO",
    "name:ron_x_preferred":[
        "Cujbic"
    ],
    "qs:gn_adm0_cc":"RO",
    "qs:gn_local":680237,
    "qs:gn_nam_loc":"crihan",
    "qs:gn_namadm1":"00",
    "qs:local_max":17,
    "qs:local_sum":17,
    "qs:localhoods":1,
    "qs:name":"Cujbic",
    "qs:name_adm0":"Rom\u00e2nia",
    "qs:name_adm1":"Bacau",
    "qs:name_local":"Crihan",
    "qs:photo_max":11,
    "qs:photo_sum":17,
    "qs:placetype":"Suburb",
    "qs:quad_count":2,
    "qs:woe_adm0":23424933,
    "qs:woe_adm1":2346618,
    "qs:woe_adm2":0,
    "qs:woe_lau":0,
    "qs:woe_local":870664,
    "qs:woe_ver":"7.10.0",
    "wof:lang":[
        "rum"
    ],
    "wof:name":"Cujbic",
    "wof:placetype":"neighbourhood"
},
  "geometry": {"coordinates":[26.834914,46.553196],"type":"Point"}
}