{
  "type": "Feature",
  "properties": {
    "gn:admin1_code":"05",
    "gn:admin2_code":"30470.0",
    "gn:asciiname":"Cosdeni",
    "gn:country_code":"RO",
    "gn:dem":160,
    "gn:feature_class":"P",
    "gn:feature_code":"PPL",
    "gn:name":"Co\u0219deni",
    "gn:population":809,
    "gn:timezone":"Europe/Bucharest",
    "iso:country":"RO",
    "wof:name":"Cosdeni",
    "wof:placetype":"locality",
    "wof:population":809
},
  "geometry": {"coordinates":[22.2748,46.76954],"type":"Point"}
}