{
  "type": "Feature",
  "properties": {
    "gn:admin1_code":"21",
    "gn:admin2_code":"90805.0",
    "gn:asciiname":"Dumbrava de Jos",
    "gn:cc2":"RO",
    "gn:country_code":"RO",
    "gn:dem":442,
    "gn:feature_class":"P",
    "gn:feature_code":"PPL",
    "gn:name":"Dumbrava de Jos",
    "gn:population":321,
    "gn:timezone":"Europe/Bucharest",
    "iso:country":"RO",
    "name:und_x_variant":[
        "Juncu de Jos",
        "Dumbrava de Jos"
    ],
    "wof:name":"Dumbrava de Jos",
    "wof:placetype":"locality",
    "wof:population":321
},
  "geometry": {"coordinates":[22.8243,46.22548],"type":"Point"}
}