{
  "type": "Feature",
  "properties": {
    "gn:admin1_code":"28",
    "gn:admin2_code":"122249",
    "gn:asciiname":"Barnadel",
    "gn:country_code":"RO",
    "gn:dem":908,
    "gn:feature_class":"P",
    "gn:feature_code":"PPL",
    "gn:name":"B\u00e2rn\u0103del",
    "gn:population":0,
    "gn:timezone":"Europe/Bucharest",
    "iso:country":"RO",
    "wof:lang_x_official":[
        "ron"
    ],
    "wof:lang_x_spoken":[
        "ron"
    ],
    "wof:name":"Barnadel",
    "wof:placetype":"locality"
},
  "geometry": {"coordinates":[25.91667,46.81667],"type":"Point"}
}