{
  "type": "Feature",
  "properties": {
    "gn:admin1_code":"03",
    "gn:admin2_code":"14450",
    "gn:asciiname":"Afrimesti",
    "gn:country_code":"RO",
    "gn:dem":164,
    "gn:feature_class":"P",
    "gn:feature_code":"PPL",
    "gn:name":"Afrime\u015fti",
    "gn:population":0,
    "gn:timezone":"Europe/Bucharest",
    "iso:country":"RO",
    "wof:name":"Afrimesti",
    "wof:placetype":"locality"
},
  "geometry": {"coordinates":[24.76353,44.47838],"type":"Point"}
}