{
  "type": "Feature",
  "properties": {
    "gn:admin1_code":"19",
    "gn:admin2_code":"79736.0",
    "gn:asciiname":"Hodoreasca",
    "gn:country_code":"RO",
    "gn:dem":174,
    "gn:feature_class":"P",
    "gn:feature_code":"PPL",
    "gn:name":"Hodoreasca",
    "gn:population":132,
    "gn:timezone":"Europe/Bucharest",
    "iso:country":"RO",
    "wof:name":"Hodoreasca",
    "wof:placetype":"locality",
    "wof:population":132
},
  "geometry": {"coordinates":[23.06545,44.93741],"type":"Point"}
}