{
  "type": "Feature",
  "properties": {
    "gn:admin1_code":"13",
    "gn:admin2_code":"58008.0",
    "gn:asciiname":"Ocolisel",
    "gn:cc2":"RO",
    "gn:country_code":"RO",
    "gn:dem":480,
    "gn:feature_class":"P",
    "gn:feature_code":"PPL",
    "gn:name":"Ocoli\u0219el",
    "gn:population":219,
    "gn:timezone":"Europe/Bucharest",
    "iso:country":"RO",
    "name:und_x_variant":[
        "Ocoli\u015fu Mic",
        "Ocoli\u015fel"
    ],
    "wof:name":"Ocolisel",
    "wof:placetype":"locality",
    "wof:population":219
},
  "geometry": {"coordinates":[23.48822,46.51494],"type":"Point"}
}