{
  "type": "Feature",
  "properties": {
    "gn:admin1_code":"35",
    "gn:admin2_code":"152797.0",
    "gn:asciiname":"Satul Vechi",
    "gn:cc2":"RO",
    "gn:country_code":"RO",
    "gn:dem":98,
    "gn:feature_class":"P",
    "gn:feature_code":"PPL",
    "gn:name":"Satul Vechi",
    "gn:population":163,
    "gn:timezone":"Europe/Bucharest",
    "iso:country":"RO",
    "name:und_x_variant":[
        "Mu\u0163i",
        "Satul Vechi"
    ],
    "wof:name":"Satul Vechi",
    "wof:placetype":"locality",
    "wof:population":163
},
  "geometry": {"coordinates":[25.02893,44.19305],"type":"Point"}
}