{
  "type": "Feature",
  "properties": {
    "gn:admin1_code":"31",
    "gn:admin2_code":"142499.0",
    "gn:asciiname":"Buzas",
    "gn:country_code":"RO",
    "gn:dem":211,
    "gn:feature_class":"P",
    "gn:feature_code":"PPL",
    "gn:name":"Buza\u0219",
    "gn:population":169,
    "gn:timezone":"Europe/Bucharest",
    "iso:country":"RO",
    "wof:name":"Buzas",
    "wof:placetype":"locality",
    "wof:population":169
},
  "geometry": {"coordinates":[23.5813,47.30799],"type":"Point"}
}