{
  "type": "Feature",
  "properties": {
    "gn:admin1_code":"32",
    "gn:admin2_code":"139394.0",
    "gn:asciiname":"Medisa",
    "gn:country_code":"RO",
    "gn:dem":165,
    "gn:feature_class":"P",
    "gn:feature_code":"PPL",
    "gn:name":"Medi\u0219a",
    "gn:population":335,
    "gn:timezone":"Europe/Bucharest",
    "iso:country":"RO",
    "wof:name":"Medisa",
    "wof:placetype":"locality",
    "wof:population":335
},
  "geometry": {"coordinates":[23.00636,47.60598],"type":"Point"}
}