{
  "type": "Feature",
  "properties": {
    "gn:admin1_code":"31",
    "gn:admin2_code":"142122.0",
    "gn:asciiname":"Popeni",
    "gn:cc2":"RO",
    "gn:country_code":"RO",
    "gn:dem":234,
    "gn:feature_class":"P",
    "gn:feature_code":"PPL",
    "gn:name":"Popeni",
    "gn:population":829,
    "gn:timezone":"Europe/Bucharest",
    "iso:country":"RO",
    "name:ceb_x_preferred":[
        "Popeni"
    ],
    "name:deu_x_preferred":[
        "Popeni"
    ],
    "name:ron_x_preferred":[
        "Popeni"
    ],
    "name:srp_x_preferred":[
        "\u041f\u043e\u043f\u0435\u043d\u0438"
    ],
    "name:ukr_x_preferred":[
        "\u041f\u043e\u043f\u0435\u043d\u044c"
    ],
    "name:und_x_variant":[
        "Popeni Mir\u015fid",
        "Popeni"
    ],
    "wof:name":"Popeni",
    "wof:placetype":"locality",
    "wof:population":829
},
  "geometry": {"coordinates":[23.17362,47.25056],"type":"Point"}
}