{
  "type": "Feature",
  "properties": {
    "gn:gn_country":"RO",
    "gn:gn_fcode":"PPLA2",
    "gn:gn_pop":1310,
    "gn:population":1310,
    "iso:country":"RO",
    "name:bul_x_preferred":[
        "\u0413\u0438\u0435\u0440\u0430"
    ],
    "name:deu_x_preferred":[
        "Giera"
    ],
    "name:eng_x_preferred":[
        "Giera"
    ],
    "name:epo_x_preferred":[
        "Giera"
    ],
    "name:fra_x_preferred":[
        "Giera"
    ],
    "name:hun_x_preferred":[
        "Gy\u00e9r"
    ],
    "name:ita_x_preferred":[
        "Giera"
    ],
    "name:nld_x_preferred":[
        "Giera"
    ],
    "name:por_x_preferred":[
        "Giera"
    ],
    "name:ron_x_preferred":[
        "Giera"
    ],
    "name:srp_x_preferred":[
        "\u0402\u0438\u0440"
    ],
    "name:ukr_x_preferred":[
        "\u0414\u0436\u0456\u0454\u0440\u0430"
    ],
    "name:unk_x_variant":[
        "G\u00e9r"
    ],
    "name:vie_x_preferred":[
        "Giera"
    ],
    "name:vol_x_preferred":[
        "Giera"
    ],
    "qs_pg:aaroncc":"RO",
    "qs_pg:gn_country":"RO",
    "qs_pg:gn_fcode":"PPLA2",
    "qs_pg:gn_pop":1310,
    "qs_pg:name":"Giera",
    "qs_pg:name_adm0":"Rom\u00e2nia",
    "qs_pg:name_adm1":"Timis",
    "qs_pg:photos_9r":0,
    "qs_pg:photos_sr":0,
    "qs_pg:pop_sr":3,
    "qs_pg:qs_pg_placetype":"locality",
    "qs_pg:qs_pg_placetype_gp":"Town",
    "qs_pg:woe_adm0":23424933,
    "woe:adm0_id":23424933,
    "woe:name_adm0":"Rom\u00e2nia",
    "woe:name_adm1":"Timis",
    "woe:placetype":"Town",
    "wof:name":"Giera",
    "wof:placetype":"locality",
    "wof:population":1310
},
  "geometry": {"coordinates":[20.99222,45.40722],"type":"Point"}
}