{
  "type": "Feature",
  "properties": {
    "gn:admin1_code":"28",
    "gn:admin2_code":"124661.0",
    "gn:asciiname":"Zvoranesti",
    "gn:country_code":"RO",
    "gn:dem":273,
    "gn:feature_class":"P",
    "gn:feature_code":"PPL",
    "gn:name":"Zvor\u0103ne\u0219ti",
    "gn:population":142,
    "gn:timezone":"Europe/Bucharest",
    "iso:country":"RO",
    "wof:name":"Zvoranesti",
    "wof:placetype":"locality",
    "wof:population":142
},
  "geometry": {"coordinates":[26.56837,47.21312],"type":"Point"}
}