{
  "type": "Feature",
  "properties": {
    "gn:admin1_code":"07",
    "gn:admin2_code":"37958.0",
    "gn:asciiname":"Serpenita",
    "gn:cc2":"RO",
    "gn:country_code":"RO",
    "gn:dem":97,
    "gn:feature_class":"P",
    "gn:feature_code":"PPL",
    "gn:name":"\u0218erpeni\u021ba",
    "gn:population":0,
    "gn:timezone":"Europe/Bucharest",
    "iso:country":"RO",
    "name:und_x_variant":[
        "\u015eepreni\u0163a",
        "\u015eerpeni\u0163a"
    ],
    "wof:name":"Serpenita",
    "wof:placetype":"locality"
},
  "geometry": {"coordinates":[27.09697,48.03171],"type":"Point"}
}