{
  "type": "Feature",
  "properties": {
    "gn:admin1_code":"40",
    "gn:admin2_code":"177101.0",
    "gn:asciiname":"Tepa",
    "gn:country_code":"RO",
    "gn:dem":633,
    "gn:feature_class":"P",
    "gn:feature_code":"PPL",
    "gn:name":"\u021aepa",
    "gn:population":169,
    "gn:timezone":"Europe/Bucharest",
    "iso:country":"RO",
    "name:ceb_x_preferred":[
        "Tepa"
    ],
    "name:deu_x_preferred":[
        "Tepa"
    ],
    "name:fin_x_preferred":[
        "Tepa"
    ],
    "name:fra_x_preferred":[
        "Tepa"
    ],
    "name:pol_x_preferred":[
        "Tepa"
    ],
    "name:swe_x_preferred":[
        "Tepa"
    ],
    "wof:name":"Tepa",
    "wof:placetype":"locality",
    "wof:population":169
},
  "geometry": {"coordinates":[26.68895,45.77986],"type":"Point"}
}