{
  "type": "Feature",
  "properties": {
    "gn:admin1_code":"21",
    "gn:admin2_code":"88546.0",
    "gn:asciiname":"Tarnavita",
    "gn:cc2":"RO",
    "gn:country_code":"RO",
    "gn:dem":265,
    "gn:feature_class":"P",
    "gn:feature_code":"PPL",
    "gn:name":"T\u00e2rn\u0103vi\u0163a",
    "gn:population":0,
    "gn:timezone":"Europe/Bucharest",
    "iso:country":"RO",
    "name:und_x_variant":[
        "T\u00e2rn\u0103vi\u0163a",
        "T\u00eern\u0103vi\u0163a"
    ],
    "wof:name":"Tarnavita",
    "wof:placetype":"locality"
},
  "geometry": {"coordinates":[22.78333,45.95],"type":"Point"}
}