{
  "type": "Feature",
  "properties": {
    "gn:admin1_code":"40",
    "gn:admin2_code":"176551.0",
    "gn:asciiname":"Dealu Sarii",
    "gn:cc2":"RO",
    "gn:country_code":"RO",
    "gn:dem":623,
    "gn:feature_class":"P",
    "gn:feature_code":"PPL",
    "gn:name":"Dealu S\u0103rii",
    "gn:population":240,
    "gn:timezone":"Europe/Bucharest",
    "iso:country":"RO",
    "name:und_x_variant":[
        "Dealul S\u0103rii",
        "Dealul S\u0103rei",
        "Dealu S\u0103rii"
    ],
    "wof:name":"Dealu Sarii",
    "wof:placetype":"locality",
    "wof:population":240
},
  "geometry": {"coordinates":[26.75832,45.57237],"type":"Point"}
}