{
  "type": "Feature",
  "properties": {
    "gn:admin1_code":"19",
    "gn:admin2_code":"77910.0",
    "gn:asciiname":"Rasova",
    "gn:country_code":"RO",
    "gn:dem":218,
    "gn:feature_class":"P",
    "gn:feature_code":"PPL",
    "gn:name":"Rasova",
    "gn:population":527,
    "gn:timezone":"Europe/Bucharest",
    "iso:country":"RO",
    "wof:name":"Rasova",
    "wof:placetype":"locality",
    "wof:population":527
},
  "geometry": {"coordinates":[23.18346,45.04721],"type":"Point"}
}