{
  "type": "Feature",
  "properties": {
    "gn:admin1_code":"19",
    "gn:admin2_code":"77910.0",
    "gn:asciiname":"Rasova",
    "gn:country_code":"RO",
    "gn:dem":218,
    "gn:feature_class":"P",
    "gn:feature_code":"PPL",
    "gn:name":"Rasova",
    "gn:population":527,
    "gn:timezone":"Europe/Bucharest",
    "iso:country":"RO",
    "name:ara_x_preferred":[
        "\u0631\u0627\u0633\u0648\u0641\u0627"
    ],
    "name:ceb_x_preferred":[
        "Comuna Rasova"
    ],
    "name:epo_x_preferred":[
        "Rasova"
    ],
    "name:fra_x_preferred":[
        "Rasova"
    ],
    "name:ita_x_preferred":[
        "Rasova"
    ],
    "name:msa_x_preferred":[
        "Rasova"
    ],
    "name:nld_x_preferred":[
        "Rasova"
    ],
    "name:por_x_preferred":[
        "Rasova"
    ],
    "name:ron_x_preferred":[
        "Comuna Rasova"
    ],
    "name:srp_x_preferred":[
        "\u041e\u043f\u0448\u0442\u0438\u043d\u0430 \u0420\u0430\u0441\u043e\u0432\u0430"
    ],
    "name:ukr_x_preferred":[
        "\u0420\u0430\u0441\u043e\u0432\u0430"
    ],
    "name:vie_x_preferred":[
        "Rasova"
    ],
    "name:vol_x_preferred":[
        "Rasova"
    ],
    "name:zho_x_preferred":[
        "\u62c9\u7d22\u74e6\u9109"
    ],
    "wof:name":"Rasova",
    "wof:placetype":"locality",
    "wof:population":527
},
  "geometry": {"coordinates":[23.18346,45.04721],"type":"Point"}
}