{
  "type": "Feature",
  "properties": {
    "iso:country":"RO",
    "name:ara_x_preferred":[
        "\u0628\u0646\u062f\u0648\u0631\u0641"
    ],
    "name:deu_x_preferred":[
        "Bendorf"
    ],
    "name:epo_x_preferred":[
        "Bendorf"
    ],
    "name:fra_x_preferred":[
        "Bendorf"
    ],
    "name:hun_x_preferred":[
        "Bendorf"
    ],
    "name:ita_x_preferred":[
        "Bendorf"
    ],
    "name:jpn_x_preferred":[
        "\u30d9\u30f3\u30c9\u30eb\u30d5"
    ],
    "name:kaz_x_preferred":[
        "\u0411\u0435\u043d\u0434\u043e\u0440\u0444"
    ],
    "name:msa_x_preferred":[
        "Bendorf"
    ],
    "name:nld_x_preferred":[
        "Bendorf"
    ],
    "name:pol_x_preferred":[
        "Bendorf"
    ],
    "name:por_x_preferred":[
        "Bendorf"
    ],
    "name:ron_x_preferred":[
        "Bendorf"
    ],
    "name:rus_x_preferred":[
        "\u0411\u0435\u043d\u0434\u043e\u0440\u0444"
    ],
    "name:slv_x_preferred":[
        "Bendorf"
    ],
    "name:spa_x_preferred":[
        "Bendorf"
    ],
    "name:srp_x_preferred":[
        "\u0411\u0435\u043d\u0434\u043e\u0440\u0444"
    ],
    "name:ukr_x_preferred":[
        "\u0411\u0435\u043d\u0434\u043e\u0440\u0444"
    ],
    "name:unk_x_variant":[
        "Bendorf"
    ],
    "name:vie_x_preferred":[
        "Bendorf"
    ],
    "name:vol_x_preferred":[
        "Bendorf"
    ],
    "name:war_x_preferred":[
        "Bendorf"
    ],
    "qs:gn_adm0_cc":"RO",
    "qs:gn_fcode":"PPLX",
    "qs:gn_local":8436351,
    "qs:gn_nam_loc":"sighisoara",
    "qs:gn_namadm1":"00",
    "qs:gn_name":"Bendorf",
    "qs:local_max":2696,
    "qs:local_sum":5367,
    "qs:localhoods":4,
    "qs:name":"Bendorf",
    "qs:name_adm0":"Rom\u00e2nia",
    "qs:name_adm1":"Mures",
    "qs:name_local":"Sighi\u0219oara",
    "qs:photo_max":249,
    "qs:photo_sum":2696,
    "qs:placetype":"Suburb",
    "qs:quad_count":60,
    "qs:woe_adm0":23424933,
    "qs:woe_adm1":2346640,
    "qs:woe_adm2":0,
    "qs:woe_lau":0,
    "qs:woe_local":880270,
    "qs:woe_ver":"7.10.0",
    "wof:lang":[
        "rum"
    ],
    "wof:name":"Bendorf",
    "wof:placetype":"neighbourhood"
},
  "geometry": {"coordinates":[24.794177,46.220451],"type":"Point"}
}