{
  "type": "Feature",
  "properties": {
    "iso:country":"RO",
    "name:ron_x_preferred":[
        "Bendorf"
    ],
    "name:unk_x_variant":[
        "Bendorf"
    ],
    "qs:gn_adm0_cc":"RO",
    "qs:gn_fcode":"PPLX",
    "qs:gn_local":8436351,
    "qs:gn_nam_loc":"sighisoara",
    "qs:gn_namadm1":"00",
    "qs:gn_name":"Bendorf",
    "qs:local_max":2696,
    "qs:local_sum":5367,
    "qs:localhoods":4,
    "qs:name":"Bendorf",
    "qs:name_adm0":"Rom\u00e2nia",
    "qs:name_adm1":"Mures",
    "qs:name_local":"Sighi\u0219oara",
    "qs:photo_max":249,
    "qs:photo_sum":2696,
    "qs:placetype":"Suburb",
    "qs:quad_count":60,
    "qs:woe_adm0":23424933,
    "qs:woe_adm1":2346640,
    "qs:woe_adm2":0,
    "qs:woe_lau":0,
    "qs:woe_local":880270,
    "qs:woe_ver":"7.10.0",
    "wof:lang":[
        "rum"
    ],
    "wof:name":"Bendorf",
    "wof:placetype":"neighbourhood"
},
  "geometry": {"coordinates":[24.794177,46.220451],"type":"Point"}
}