{
  "type": "Feature",
  "properties": {
    "gn:admin1_code":"20",
    "gn:admin2_code":"86366.0",
    "gn:asciiname":"Sicasau",
    "gn:country_code":"RO",
    "gn:dem":690,
    "gn:feature_class":"P",
    "gn:feature_code":"PPL",
    "gn:name":"Sicas\u0103u",
    "gn:population":0,
    "gn:timezone":"Europe/Bucharest",
    "iso:country":"RO",
    "name:und_x_variant":[
        "Sikassz\u00f3",
        "Sicas\u0103u"
    ],
    "wof:name":"Sicasau",
    "wof:placetype":"locality"
},
  "geometry": {"coordinates":[25.4551,46.51492],"type":"Point"}
}