{
  "type": "Feature",
  "properties": {
    "gn:gn_country":"RO",
    "gn:gn_fcode":"PPLA2",
    "gn:gn_pop":1331,
    "gn:population":1331,
    "iso:country":"RO",
    "name:ceb_x_preferred":[
        "Aiton"
    ],
    "name:deu_x_preferred":[
        "Aiton"
    ],
    "name:eng_x_preferred":[
        "Aiton"
    ],
    "name:epo_x_preferred":[
        "Aiton"
    ],
    "name:fas_x_preferred":[
        "\u0627\u06cc\u062a\u0648\u0646\u060c \u06a9\u0644\u0627\u062c"
    ],
    "name:fas_x_variant":[
        "\u0627\u06cc\u062a\u0648\u0646"
    ],
    "name:fra_x_preferred":[
        "Aiton"
    ],
    "name:hun_x_preferred":[
        "Ajton"
    ],
    "name:ita_x_preferred":[
        "Aiton"
    ],
    "name:msa_x_preferred":[
        "Aiton"
    ],
    "name:nld_x_preferred":[
        "Aiton"
    ],
    "name:por_x_preferred":[
        "Aiton"
    ],
    "name:ron_x_preferred":[
        "Aiton"
    ],
    "name:spa_x_preferred":[
        "Aiton"
    ],
    "name:srp_x_preferred":[
        "\u0410\u0458\u0442\u043e\u043d"
    ],
    "name:ukr_x_preferred":[
        "\u0410\u0439\u0442\u043e\u043d"
    ],
    "name:unk_x_variant":[
        "Anton"
    ],
    "name:vol_x_preferred":[
        "Aiton"
    ],
    "qs_pg:aaroncc":"RO",
    "qs_pg:gn_country":"RO",
    "qs_pg:gn_fcode":"PPLA2",
    "qs_pg:gn_pop":1331,
    "qs_pg:name":"Aiton",
    "qs_pg:name_adm0":"Rom\u00e2nia",
    "qs_pg:name_adm1":"Cluj",
    "qs_pg:photos_9r":0,
    "qs_pg:photos_sr":0,
    "qs_pg:pop_sr":3,
    "qs_pg:qs_pg_placetype":"locality",
    "qs_pg:qs_pg_placetype_gp":"Town",
    "qs_pg:woe_adm0":23424933,
    "woe:adm0_id":23424933,
    "woe:name_adm0":"Rom\u00e2nia",
    "woe:name_adm1":"Cluj",
    "woe:placetype":"Town",
    "wof:name":"Aiton",
    "wof:placetype":"locality",
    "wof:population":1331
},
  "geometry": {"coordinates":[23.73333,46.68333],"type":"Point"}
}