{
  "type": "Feature",
  "properties": {
    "gn:admin1_code":"05",
    "gn:admin2_code":"26742.0",
    "gn:asciiname":"Chistag",
    "gn:country_code":"RO",
    "gn:dem":214,
    "gn:feature_class":"P",
    "gn:feature_code":"PPL",
    "gn:name":"Chistag",
    "gn:population":660,
    "gn:timezone":"Europe/Bucharest",
    "iso:country":"RO",
    "wof:name":"Chistag",
    "wof:placetype":"locality",
    "wof:population":660
},
  "geometry": {"coordinates":[22.35658,47.0466],"type":"Point"}
}