{
  "type": "Feature",
  "properties": {
    "gn:admin1_code":"02",
    "gn:admin2_code":"11584",
    "gn:asciiname":"Bodrogu Vechi",
    "gn:cc2":"RO",
    "gn:country_code":"RO",
    "gn:dem":96,
    "gn:feature_class":"P",
    "gn:feature_code":"PPL",
    "gn:name":"Bodrogu Vechi",
    "gn:population":17,
    "gn:timezone":"Europe/Bucharest",
    "iso:country":"RO",
    "name:und_x_variant":[
        "Hodosch",
        "\u00d3bodrog",
        "Hodo\u015f-Bodrog",
        "Bodrogu Vechi"
    ],
    "wof:name":"Bodrogu Vechi",
    "wof:placetype":"locality",
    "wof:population":17
},
  "geometry": {"coordinates":[21.17559,46.13851],"type":"Point"}
}