{
  "type": "Feature",
  "properties": {
    "gn:admin1_code":"20",
    "gn:admin2_code":"85984.0",
    "gn:asciiname":"Cobatesti",
    "gn:cc2":"RO",
    "gn:country_code":"RO",
    "gn:dem":463,
    "gn:feature_class":"P",
    "gn:feature_code":"PPL",
    "gn:name":"Cob\u0103te\u0219ti",
    "gn:population":404,
    "gn:timezone":"Europe/Bucharest",
    "iso:country":"RO",
    "name:und_x_variant":[
        "Kob\u00e1tfalva",
        "Cob\u0103te\u015fti"
    ],
    "wof:name":"Cobatesti",
    "wof:placetype":"locality",
    "wof:population":404
},
  "geometry": {"coordinates":[25.14344,46.35726],"type":"Point"}
}