{
  "type": "Feature",
  "properties": {
    "gn:admin1_code":"27",
    "gn:admin2_code":"119153.0",
    "gn:asciiname":"Sebes",
    "gn:country_code":"RO",
    "gn:dem":460,
    "gn:feature_class":"P",
    "gn:feature_code":"PPL",
    "gn:name":"Sebe\u0219",
    "gn:population":156,
    "gn:timezone":"Europe/Bucharest",
    "iso:country":"RO",
    "wof:name":"Sebes",
    "wof:placetype":"locality",
    "wof:population":156
},
  "geometry": {"coordinates":[24.86438,46.93202],"type":"Point"}
}