{
  "type": "Feature",
  "properties": {
    "gn:admin1_code":"14",
    "gn:admin2_code":"60883.0",
    "gn:asciiname":"Hateg",
    "gn:cc2":"RO",
    "gn:country_code":"RO",
    "gn:dem":32,
    "gn:feature_class":"P",
    "gn:feature_code":"PPL",
    "gn:name":"Ha\u021beg",
    "gn:population":29,
    "gn:timezone":"Europe/Bucharest",
    "iso:country":"RO",
    "name:und_x_variant":[
        "Arabagi",
        "Ha\u0163eg"
    ],
    "wof:name":"Hateg",
    "wof:placetype":"locality",
    "wof:population":29
},
  "geometry": {"coordinates":[27.96293,44.16149],"type":"Point"}
}