{
  "type": "Feature",
  "properties": {
    "gn:admin1_code":"11",
    "gn:admin2_code":"48968.0",
    "gn:asciiname":"Fotin",
    "gn:cc2":"RO",
    "gn:country_code":"RO",
    "gn:dem":71,
    "gn:feature_class":"P",
    "gn:feature_code":"PPL",
    "gn:name":"Fotin",
    "gn:population":227,
    "gn:timezone":"Europe/Bucharest",
    "iso:country":"RO",
    "name:und_x_variant":[
        "Fotinu",
        "Fotin"
    ],
    "wof:name":"Fotin",
    "wof:placetype":"locality",
    "wof:population":227
},
  "geometry": {"coordinates":[27.15198,45.38715],"type":"Point"}
}