{
  "type": "Feature",
  "properties": {
    "gn:admin1_code":"25",
    "gn:admin2_code":"107733.0",
    "gn:asciiname":"Fauresti",
    "gn:country_code":"RO",
    "gn:dem":324,
    "gn:feature_class":"P",
    "gn:feature_code":"PPL",
    "gn:name":"F\u0103ure\u0219ti",
    "gn:population":816,
    "gn:timezone":"Europe/Bucharest",
    "iso:country":"RO",
    "wof:name":"Fauresti",
    "wof:placetype":"locality",
    "wof:population":816
},
  "geometry": {"coordinates":[23.75005,47.56319000000001],"type":"Point"}
}