{
  "type": "Feature",
  "properties": {
    "gn:gn_country":"RO",
    "gn:gn_fcode":"PPL",
    "gn:gn_pop":5607,
    "gn:population":5607,
    "iso:country":"RO",
    "name:ceb_x_preferred":[
        "\u0218tef\u0103ne\u0219ti-Sat"
    ],
    "name:eng_x_preferred":[
        "\u0218tef\u0103ne\u0219ti-Sat"
    ],
    "name:ron_x_preferred":[
        "\u0218tef\u0103ne\u0219ti-Sat"
    ],
    "name:srp_x_preferred":[
        "\u0428\u0442\u0435\u0444\u0430\u043d\u0435\u0448\u0442\u0438-\u0421\u0430\u0442"
    ],
    "name:ukr_x_preferred":[
        "\u0428\u0442\u0435\u0444\u0435\u043d\u0435\u0448\u0442\u044c-\u0421\u0430\u0442"
    ],
    "qs_pg:aaroncc":"RO",
    "qs_pg:gn_country":"RO",
    "qs_pg:gn_fcode":"PPL",
    "qs_pg:gn_pop":5607,
    "qs_pg:name":"\u015etef\u0103ne\u0219ti-Sat",
    "qs_pg:name_adm0":"Rom\u00e2nia",
    "qs_pg:name_adm1":"Botosani",
    "qs_pg:photos_9r":0,
    "qs_pg:photos_sr":0,
    "qs_pg:pop_sr":5,
    "qs_pg:qs_pg_placetype":"locality",
    "qs_pg:qs_pg_placetype_gp":"Town",
    "qs_pg:woe_adm0":23424933,
    "woe:adm0_id":23424933,
    "woe:name_adm0":"Rom\u00e2nia",
    "woe:name_adm1":"Botosani",
    "woe:placetype":"Town",
    "wof:name":"\u015etef\u0103ne\u0219ti-Sat",
    "wof:placetype":"locality",
    "wof:population":5607
},
  "geometry": {"coordinates":[27.18333,47.78333],"type":"Point"}
}