{
  "type": "Feature",
  "properties": {
    "gn:admin1_code":"20",
    "gn:admin2_code":"83981.0",
    "gn:asciiname":"Eghersec",
    "gn:cc2":"RO",
    "gn:country_code":"RO",
    "gn:dem":974,
    "gn:feature_class":"P",
    "gn:feature_code":"PPL",
    "gn:name":"Eghersec",
    "gn:population":320,
    "gn:timezone":"Europe/Bucharest",
    "iso:country":"RO",
    "name:und_x_variant":[
        "Egersz\u00e8k",
        "Eghersec"
    ],
    "wof:name":"Eghersec",
    "wof:placetype":"locality",
    "wof:population":320
},
  "geometry": {"coordinates":[26.06472,46.30377],"type":"Point"}
}