{
  "type": "Feature",
  "properties": {
    "gn:admin1_code":"40",
    "gn:admin2_code":"176944.0",
    "gn:asciiname":"Chiricani",
    "gn:country_code":"RO",
    "gn:dem":603,
    "gn:feature_class":"P",
    "gn:feature_code":"PPL",
    "gn:name":"Chiricani",
    "gn:population":442,
    "gn:timezone":"Europe/Bucharest",
    "iso:country":"RO",
    "wof:name":"Chiricani",
    "wof:placetype":"locality",
    "wof:population":442
},
  "geometry": {"coordinates":[26.71667,45.71667],"type":"Point"}
}