{
  "type": "Feature",
  "properties": {
    "gn:admin1_code":"21",
    "gn:admin2_code":"88350.0",
    "gn:asciiname":"Plai",
    "gn:cc2":"RO",
    "gn:country_code":"RO",
    "gn:dem":382,
    "gn:feature_class":"P",
    "gn:feature_code":"PPL",
    "gn:name":"Plai",
    "gn:population":230,
    "gn:timezone":"Europe/Bucharest",
    "iso:country":"RO",
    "name:und_x_variant":[
        "Plaiul",
        "Plaiu"
    ],
    "wof:name":"Plai",
    "wof:placetype":"locality",
    "wof:population":230
},
  "geometry": {"coordinates":[22.9125,46.23072],"type":"Point"}
}