{
  "type": "Feature",
  "properties": {
    "gn:admin1_code":"34",
    "gn:admin2_code":"149682.0",
    "gn:asciiname":"Dragoiasa",
    "gn:country_code":"RO",
    "gn:dem":1140,
    "gn:feature_class":"P",
    "gn:feature_code":"PPL",
    "gn:name":"Dr\u0103goiasa",
    "gn:population":227,
    "gn:timezone":"Europe/Bucharest",
    "iso:country":"RO",
    "wof:name":"Dragoiasa",
    "wof:placetype":"locality",
    "wof:population":227
},
  "geometry": {"coordinates":[25.43971,47.16384],"type":"Point"}
}