{
  "type": "Feature",
  "properties": {
    "gn:admin1_code":"29",
    "gn:admin2_code":"130302.0",
    "gn:asciiname":"Gavanesti",
    "gn:country_code":"RO",
    "gn:dem":141,
    "gn:feature_class":"P",
    "gn:feature_code":"PPLA2",
    "gn:name":"G\u0103v\u0103ne\u0219ti",
    "gn:population":840,
    "gn:timezone":"Europe/Bucharest",
    "iso:country":"RO",
    "name:ceb_x_preferred":[
        "Comuna G\u0103v\u0103ne\u0219ti"
    ],
    "name:ita_x_preferred":[
        "G\u0103v\u0103ne\u0219ti"
    ],
    "name:msa_x_preferred":[
        "G\u0103v\u0103ne\u015fti"
    ],
    "name:nld_x_preferred":[
        "G\u0103v\u0103ne\u0219ti"
    ],
    "name:por_x_preferred":[
        "G\u0103v\u0103ne\u015fti"
    ],
    "name:ron_x_preferred":[
        "Comuna G\u0103v\u0103ne\u0219ti"
    ],
    "name:srp_x_preferred":[
        "\u041e\u043f\u0448\u0442\u0438\u043d\u0430 \u0413\u0430\u0432\u0430\u043d\u0435\u0448\u0442\u0438"
    ],
    "name:ukr_x_preferred":[
        "\u0413\u0435\u0432\u0435\u043d\u0435\u0448\u0442\u044c"
    ],
    "name:vol_x_preferred":[
        "G\u0103v\u0103ne\u015fti"
    ],
    "name:zho_x_preferred":[
        "\u683c\u6c83\u5167\u4ec0\u8482\u9109"
    ],
    "wof:name":"Gavanesti",
    "wof:placetype":"locality",
    "wof:population":840
},
  "geometry": {"coordinates":[24.01654,44.41724],"type":"Point"}
}