{
  "type": "Feature",
  "properties": {
    "gn:admin1_code":"29",
    "gn:admin2_code":"130302.0",
    "gn:asciiname":"Gavanesti",
    "gn:country_code":"RO",
    "gn:dem":141,
    "gn:feature_class":"P",
    "gn:feature_code":"PPLA2",
    "gn:name":"G\u0103v\u0103ne\u0219ti",
    "gn:population":840,
    "gn:timezone":"Europe/Bucharest",
    "iso:country":"RO",
    "name:und_x_variant":[
        "G\u0103v\u0103ne\u015fti"
    ],
    "wof:name":"Gavanesti",
    "wof:placetype":"locality",
    "wof:population":840
},
  "geometry": {"coordinates":[24.01654,44.41724],"type":"Point"}
}