{
  "type": "Feature",
  "properties": {
    "gn:gn_country":"RO",
    "gn:gn_fcode":"PPLA2",
    "gn:gn_pop":5071,
    "gn:population":5071,
    "iso:country":"RO",
    "name:eng_x_preferred":[
        "Pade\u0219"
    ],
    "name:fra_x_preferred":[
        "Pade\u0219"
    ],
    "name:ita_x_preferred":[
        "Pade\u0219"
    ],
    "name:jpn_x_preferred":[
        "\u30d1\u30c7\u30b7\u30e5"
    ],
    "name:nld_x_preferred":[
        "Pade\u0219"
    ],
    "name:por_x_preferred":[
        "Pade\u0219"
    ],
    "name:ron_x_preferred":[
        "Pade\u0219"
    ],
    "name:ukr_x_preferred":[
        "\u041f\u0430\u0434\u0435\u0448"
    ],
    "name:unk_x_variant":[
        "Pade\u015fu"
    ],
    "name:vol_x_preferred":[
        "Pade\u0219"
    ],
    "qs_pg:aaroncc":"RO",
    "qs_pg:gn_country":"RO",
    "qs_pg:gn_fcode":"PPLA2",
    "qs_pg:gn_pop":5071,
    "qs_pg:name":"Pade\u0219",
    "qs_pg:name_adm0":"Rom\u00e2nia",
    "qs_pg:name_adm1":"Gorj",
    "qs_pg:photos_9r":0,
    "qs_pg:photos_sr":0,
    "qs_pg:pop_sr":5,
    "qs_pg:qs_pg_placetype":"locality",
    "qs_pg:qs_pg_placetype_gp":"Town",
    "qs_pg:woe_adm0":23424933,
    "woe:adm0_id":23424933,
    "woe:name_adm0":"Rom\u00e2nia",
    "woe:name_adm1":"Gorj",
    "woe:placetype":"Town",
    "wof:name":"Pade\u0219",
    "wof:placetype":"locality",
    "wof:population":5071
},
  "geometry": {"coordinates":[22.85,45.01667],"type":"Point"}
}