{
  "type": "Feature",
  "properties": {
    "gn:population":2435,
    "iso:country":"RO",
    "name:eng_x_preferred":[
        "Rodna"
    ],
    "name:eng_x_variant":[
        "Rodna"
    ],
    "name:ron_x_preferred":[
        "Radna"
    ],
    "name:unk_x_variant":[
        "Rodna",
        "Radna"
    ],
    "qs:gn_adm0_cc":"RO",
    "qs:gn_fcode":"PPLX",
    "qs:gn_local":0,
    "qs:gn_namadm1":"00",
    "qs:gn_name":"Radna",
    "qs:local_max":117,
    "qs:local_sum":168,
    "qs:localhoods":2,
    "qs:name":"Radna",
    "qs:name_adm0":"Rom\u00e2nia",
    "qs:name_adm1":"Arad",
    "qs:name_en":"Rodna",
    "qs:name_local":"Lipova",
    "qs:photo_max":27,
    "qs:photo_sum":117,
    "qs:placetype":"Suburb",
    "qs:quad_count":10,
    "qs:woe_adm0":23424933,
    "qs:woe_adm1":2346616,
    "qs:woe_adm2":0,
    "qs:woe_lau":0,
    "qs:woe_local":874706,
    "qs:woe_ver":"7.10.0",
    "wof:lang":[
        "rum"
    ],
    "wof:name":"Radna",
    "wof:placetype":"neighbourhood",
    "wof:population":2435
},
  "geometry": {"coordinates":[21.690456,46.094767],"type":"Point"}
}