{
  "type": "Feature",
  "properties": {
    "gn:admin1_code":"28",
    "gn:admin2_code":"121732.0",
    "gn:asciiname":"Nechit",
    "gn:country_code":"RO",
    "gn:dem":438,
    "gn:feature_class":"P",
    "gn:feature_code":"PPL",
    "gn:name":"Nechit",
    "gn:population":293,
    "gn:timezone":"Europe/Bucharest",
    "iso:country":"RO",
    "wof:name":"Nechit",
    "wof:placetype":"locality",
    "wof:population":293
},
  "geometry": {"coordinates":[26.41579,46.77307],"type":"Point"}
}