{
  "type": "Feature",
  "properties": {
    "gn:admin1_code":"39",
    "gn:admin2_code":"170097.0",
    "gn:asciiname":"Stirbesti",
    "gn:cc2":"RO",
    "gn:country_code":"RO",
    "gn:dem":214,
    "gn:feature_class":"P",
    "gn:feature_code":"PPL",
    "gn:name":"\u0218tirbe\u0219ti",
    "gn:population":340,
    "gn:timezone":"Europe/Bucharest",
    "iso:country":"RO",
    "name:und_x_variant":[
        "\u015etirbe\u015ftii de Jos",
        "\u015etirbe\u015fti"
    ],
    "wof:name":"Stirbesti",
    "wof:placetype":"locality",
    "wof:population":340
},
  "geometry": {"coordinates":[23.87764,44.64783],"type":"Point"}
}