{
  "type": "Feature",
  "properties": {
    "gn:admin1_code":"30",
    "gn:admin2_code":"135315.0",
    "gn:asciiname":"Gresia",
    "gn:country_code":"RO",
    "gn:dem":727,
    "gn:feature_class":"P",
    "gn:feature_code":"PPL",
    "gn:name":"Gresia",
    "gn:population":17,
    "gn:timezone":"Europe/Bucharest",
    "iso:country":"RO",
    "name:ceb_x_preferred":[
        "Gresia"
    ],
    "name:deu_x_preferred":[
        "Gresia"
    ],
    "name:ron_x_preferred":[
        "Gresia"
    ],
    "name:srp_x_preferred":[
        "\u0413\u0440\u0435\u0441\u0438\u0458\u0430"
    ],
    "wof:name":"Gresia",
    "wof:placetype":"locality",
    "wof:population":17
},
  "geometry": {"coordinates":[26.15429,45.35019000000001],"type":"Point"}
}