{
  "type": "Feature",
  "properties": {
    "gn:admin1_code":"39",
    "gn:admin2_code":"171209",
    "gn:asciiname":"Balsoara",
    "gn:country_code":"RO",
    "gn:dem":303,
    "gn:feature_class":"P",
    "gn:feature_code":"PPL",
    "gn:name":"B\u0103l\u0219oara",
    "gn:population":468,
    "gn:timezone":"Europe/Bucharest",
    "iso:country":"RO",
    "wof:name":"Balsoara",
    "wof:placetype":"locality",
    "wof:population":468
},
  "geometry": {"coordinates":[24.12351,44.67342],"type":"Point"}
}