{
  "type": "Feature",
  "properties": {
    "gn:admin1_code":"39",
    "gn:admin2_code":"172581",
    "gn:asciiname":"Baiasa",
    "gn:country_code":"RO",
    "gn:dem":332,
    "gn:feature_class":"P",
    "gn:feature_code":"PPL",
    "gn:name":"B\u0103ia\u0219a",
    "gn:population":165,
    "gn:timezone":"Europe/Bucharest",
    "iso:country":"RO",
    "wof:name":"Baiasa",
    "wof:placetype":"locality",
    "wof:population":165
},
  "geometry": {"coordinates":[24.08333,44.91667],"type":"Point"}
}