{
  "type": "Feature",
  "properties": {
    "gn:admin1_code":"37",
    "gn:admin2_code":"161035.0",
    "gn:asciiname":"Manastirea Saon",
    "gn:cc2":"RO",
    "gn:country_code":"RO",
    "gn:dem":19,
    "gn:feature_class":"P",
    "gn:feature_code":"PPL",
    "gn:name":"M\u00e2n\u0103stirea Saon",
    "gn:population":0,
    "gn:timezone":"Europe/Bucharest",
    "iso:country":"RO",
    "name:und_x_variant":[
        "M\u00e2n\u0103stirea Sauna",
        "M\u00e2n\u0103stirea Saona",
        "M\u00een\u0103stirea Saon"
    ],
    "wof:lang_x_official":[
        "ron"
    ],
    "wof:lang_x_spoken":[
        "ron"
    ],
    "wof:name":"Manastirea Saon",
    "wof:placetype":"locality"
},
  "geometry": {"coordinates":[28.55,45.21667],"type":"Point"}
}