{
  "type": "Feature",
  "properties": {
    "gn:admin1_code":"05",
    "gn:admin2_code":"28941",
    "gn:asciiname":"Beiusele",
    "gn:cc2":"RO",
    "gn:country_code":"RO",
    "gn:dem":276,
    "gn:feature_class":"P",
    "gn:feature_code":"PPL",
    "gn:name":"Beiu\u0219ele",
    "gn:population":553,
    "gn:timezone":"Europe/Bucharest",
    "iso:country":"RO",
    "name:und_x_variant":[
        "Beinsele",
        "Beiu\u015fele"
    ],
    "wof:name":"Beiusele",
    "wof:placetype":"locality",
    "wof:population":553
},
  "geometry": {"coordinates":[22.45117,46.71828],"type":"Point"}
}