{
  "type": "Feature",
  "properties": {
    "gn:admin1_code":"01",
    "gn:admin2_code":"7945.0",
    "gn:asciiname":"Drasov",
    "gn:country_code":"RO",
    "gn:dem":284,
    "gn:feature_class":"P",
    "gn:feature_code":"PPL",
    "gn:name":"Dra\u0219ov",
    "gn:population":573,
    "gn:timezone":"Europe/Bucharest",
    "iso:country":"RO",
    "wof:name":"Drasov",
    "wof:placetype":"locality",
    "wof:population":573
},
  "geometry": {"coordinates":[23.74323,45.93826],"type":"Point"}
}