{
  "type": "Feature",
  "properties": {
    "gn:admin1_code":"12",
    "gn:admin2_code":"51699.0",
    "gn:asciiname":"Valea Timisului",
    "gn:cc2":"RO",
    "gn:country_code":"RO",
    "gn:dem":247,
    "gn:feature_class":"P",
    "gn:feature_code":"PPL",
    "gn:name":"Valea Timi\u0219ului",
    "gn:population":636,
    "gn:timezone":"Europe/Bucharest",
    "iso:country":"RO",
    "name:und_x_variant":[
        "C\u00e2rpa",
        "C\u00eerpa",
        "Valea Timi\u015fului"
    ],
    "wof:name":"Valea Timisului",
    "wof:placetype":"locality",
    "wof:population":636
},
  "geometry": {"coordinates":[22.26592,45.34891],"type":"Point"}
}