{
  "type": "Feature",
  "properties": {
    "gn:admin1_code":"19",
    "gn:admin2_code":"80560.0",
    "gn:asciiname":"Ulmeni",
    "gn:country_code":"RO",
    "gn:dem":139,
    "gn:feature_class":"P",
    "gn:feature_code":"PPL",
    "gn:name":"Ulmeni",
    "gn:population":0,
    "gn:timezone":"Europe/Bucharest",
    "iso:country":"RO",
    "name:bar_x_preferred":[
        "Ulmeni"
    ],
    "name:ceb_x_preferred":[
        "Ulmeni"
    ],
    "name:deu_x_preferred":[
        "Ulmeni"
    ],
    "name:epo_x_preferred":[
        "Ulmeni"
    ],
    "name:eus_x_preferred":[
        "Ulmeni"
    ],
    "name:ita_x_preferred":[
        "Ulmeni"
    ],
    "name:nld_x_preferred":[
        "Ulmeni"
    ],
    "name:por_x_preferred":[
        "Ulmeni"
    ],
    "name:ron_x_preferred":[
        "Ulmeni"
    ],
    "name:srp_x_preferred":[
        "\u0423\u043b\u043c\u0435\u043d\u0438"
    ],
    "name:ukr_x_preferred":[
        "\u0423\u043b\u043c\u0435\u043d\u044c"
    ],
    "name:vol_x_preferred":[
        "Ulmeni"
    ],
    "wof:name":"Ulmeni",
    "wof:placetype":"locality"
},
  "geometry": {"coordinates":[23.41667,44.63333],"type":"Point"}
}