{
  "type": "Feature",
  "properties": {
    "gn:admin1_code":"22",
    "gn:admin2_code":"93101.0",
    "gn:asciiname":"Orezu",
    "gn:cc2":"RO",
    "gn:country_code":"RO",
    "gn:dem":35,
    "gn:feature_class":"P",
    "gn:feature_code":"PPL",
    "gn:name":"Orezu",
    "gn:population":705,
    "gn:timezone":"Europe/Bucharest",
    "iso:country":"RO",
    "name:und_x_variant":[
        "Orezul",
        "Orezu"
    ],
    "wof:name":"Orezu",
    "wof:placetype":"locality",
    "wof:population":705
},
  "geometry": {"coordinates":[26.9945,44.58495],"type":"Point"}
}