{
  "type": "Feature",
  "properties": {
    "gn:admin1_code":"39",
    "gn:admin2_code":"170952.0",
    "gn:asciiname":"Carcadiesti",
    "gn:cc2":"RO",
    "gn:country_code":"RO",
    "gn:dem":216,
    "gn:feature_class":"P",
    "gn:feature_code":"PPL",
    "gn:name":"C\u0103rc\u0103die\u0219ti",
    "gn:population":269,
    "gn:timezone":"Europe/Bucharest",
    "iso:country":"RO",
    "name:und_x_variant":[
        "Carcade\u015fti",
        "Caracadie\u015fti",
        "Carcadie\u015fti"
    ],
    "wof:name":"Carcadiesti",
    "wof:placetype":"locality",
    "wof:population":269
},
  "geometry": {"coordinates":[24.138,44.64877],"type":"Point"}
}