{
  "type": "Feature",
  "properties": {
    "gn:admin1_code":"35",
    "gn:admin2_code":"155127.0",
    "gn:asciiname":"Chitulesti",
    "gn:country_code":"RO",
    "gn:dem":89,
    "gn:feature_class":"P",
    "gn:feature_code":"PPL",
    "gn:name":"Chi\u0163ule\u015fti",
    "gn:population":0,
    "gn:timezone":"Europe/Bucharest",
    "iso:country":"RO",
    "wof:name":"Chitulesti",
    "wof:placetype":"locality"
},
  "geometry": {"coordinates":[25.38333,44.18333],"type":"Point"}
}