{
  "type": "Feature",
  "properties": {
    "gn:admin1_code":"26",
    "gn:admin2_code":"113974.0",
    "gn:asciiname":"Cotoroaia",
    "gn:cc2":"RO",
    "gn:country_code":"RO",
    "gn:dem":239,
    "gn:feature_class":"P",
    "gn:feature_code":"PPL",
    "gn:name":"Cotoroaia",
    "gn:population":561,
    "gn:timezone":"Europe/Bucharest",
    "iso:country":"RO",
    "name:ceb_x_preferred":[
        "Cotoroaia"
    ],
    "name:deu_x_preferred":[
        "Cotoroaia"
    ],
    "name:ron_x_preferred":[
        "Cotoroaia"
    ],
    "name:srp_x_preferred":[
        "\u041a\u043e\u0442\u043e\u0440\u043e\u0430\u0458\u0430"
    ],
    "name:und_x_variant":[
        "Cotoroaia de Sus"
    ],
    "wof:name":"Cotoroaia",
    "wof:placetype":"locality",
    "wof:population":561
},
  "geometry": {"coordinates":[23.03398,44.64922],"type":"Point"}
}