{
  "type": "Feature",
  "properties": {
    "gn:admin1_code":"12",
    "gn:admin2_code":"52115.0",
    "gn:asciiname":"Cuptoare",
    "gn:country_code":"RO",
    "gn:dem":297,
    "gn:feature_class":"P",
    "gn:feature_code":"PPL",
    "gn:name":"Cuptoare",
    "gn:population":771,
    "gn:timezone":"Europe/Bucharest",
    "iso:country":"RO",
    "name:ceb_x_preferred":[
        "Cuptoare"
    ],
    "name:deu_x_preferred":[
        "Cuptoare"
    ],
    "name:ron_x_preferred":[
        "Cuptoare"
    ],
    "name:srp_x_preferred":[
        "\u041a\u0443\u043f\u0442\u043e\u0430\u0440\u0435"
    ],
    "wof:name":"Cuptoare",
    "wof:placetype":"locality",
    "wof:population":771
},
  "geometry": {"coordinates":[22.30845,45.01076],"type":"Point"}
}