{
  "type": "Feature",
  "properties": {
    "gn:admin1_code":"33",
    "gn:admin2_code":"145220.0",
    "gn:asciiname":"Craciunesti",
    "gn:country_code":"RO",
    "gn:dem":398,
    "gn:feature_class":"P",
    "gn:feature_code":"PPL",
    "gn:name":"Cr\u0103ciune\u015fti",
    "gn:population":0,
    "gn:timezone":"Europe/Bucharest",
    "iso:country":"RO",
    "wof:lang_x_official":[
        "ron"
    ],
    "wof:lang_x_spoken":[
        "ron"
    ],
    "wof:name":"Craciunesti",
    "wof:placetype":"locality"
},
  "geometry": {"coordinates":[23.86667,46.01667],"type":"Point"}
}