{
  "type": "Feature",
  "properties": {
    "gn:admin1_code":"20",
    "gn:admin2_code":"83981.0",
    "gn:asciiname":"Potiond",
    "gn:cc2":"RO",
    "gn:country_code":"RO",
    "gn:dem":835,
    "gn:feature_class":"P",
    "gn:feature_code":"PPL",
    "gn:name":"Potiond",
    "gn:population":267,
    "gn:timezone":"Europe/Bucharest",
    "iso:country":"RO",
    "name:und_x_variant":[
        "Menasag Pottyond",
        "Pottyond",
        "Potiond"
    ],
    "wof:name":"Potiond",
    "wof:placetype":"locality",
    "wof:population":267
},
  "geometry": {"coordinates":[25.95239,46.36289],"type":"Point"}
}