{
  "type": "Feature",
  "properties": {
    "gn:admin1_code":"41",
    "gn:admin2_code":"103568.0",
    "gn:asciiname":"Codreni",
    "gn:country_code":"RO",
    "gn:dem":31,
    "gn:feature_class":"P",
    "gn:feature_code":"PPL",
    "gn:name":"Codreni",
    "gn:population":0,
    "gn:timezone":"Europe/Bucharest",
    "iso:country":"RO",
    "name:ceb_x_preferred":[
        "Codreni"
    ],
    "name:deu_x_preferred":[
        "Codreni"
    ],
    "name:ron_x_preferred":[
        "Codreni"
    ],
    "name:rus_x_preferred":[
        "\u041a\u043e\u0434\u0440\u044f\u043d\u044b"
    ],
    "name:srp_x_preferred":[
        "\u041a\u043e\u0434\u0440\u0435\u043d\u0438"
    ],
    "name:ukr_x_preferred":[
        "\u041a\u043e\u0434\u0440\u0435\u043d\u044c"
    ],
    "wof:name":"Codreni",
    "wof:placetype":"locality"
},
  "geometry": {"coordinates":[26.65165,44.39109000000001],"type":"Point"}
}