{
  "type": "Feature",
  "properties": {
    "gn:admin1_code":"41",
    "gn:admin2_code":"103568.0",
    "gn:asciiname":"Codreni",
    "gn:country_code":"RO",
    "gn:dem":31,
    "gn:feature_class":"P",
    "gn:feature_code":"PPL",
    "gn:name":"Codreni",
    "gn:population":0,
    "gn:timezone":"Europe/Bucharest",
    "iso:country":"RO",
    "wof:name":"Codreni",
    "wof:placetype":"locality"
},
  "geometry": {"coordinates":[26.65165,44.39109000000001],"type":"Point"}
}