{
  "type": "Feature",
  "properties": {
    "gn:admin1_code":"21",
    "gn:admin2_code":"89954.0",
    "gn:asciiname":"Lasau",
    "gn:country_code":"RO",
    "gn:dem":171,
    "gn:feature_class":"P",
    "gn:feature_code":"PPL",
    "gn:name":"L\u0103s\u0103u",
    "gn:population":203,
    "gn:timezone":"Europe/Bucharest",
    "iso:country":"RO",
    "wof:name":"Lasau",
    "wof:placetype":"locality",
    "wof:population":203
},
  "geometry": {"coordinates":[22.49582,45.91866],"type":"Point"}
}