{
  "type": "Feature",
  "properties": {
    "gn:admin1_code":"40",
    "gn:admin2_code":"178607.0",
    "gn:asciiname":"Mircestii Vechi",
    "gn:cc2":"RO",
    "gn:country_code":"RO",
    "gn:dem":38,
    "gn:feature_class":"P",
    "gn:feature_code":"PPL",
    "gn:name":"Mirce\u0219tii Vechi",
    "gn:population":179,
    "gn:timezone":"Europe/Bucharest",
    "iso:country":"RO",
    "name:und_x_variant":[
        "Mirce\u015fti-Vechi",
        "Mirce\u015ftii Vechi"
    ],
    "wof:name":"Mircestii Vechi",
    "wof:placetype":"locality",
    "wof:population":179
},
  "geometry": {"coordinates":[27.28533,45.74466],"type":"Point"}
}