{
  "type": "Feature",
  "properties": {
    "gn:admin1_code":"32",
    "gn:admin2_code":"137443.0",
    "gn:asciiname":"Teghea",
    "gn:country_code":"RO",
    "gn:dem":127,
    "gn:feature_class":"P",
    "gn:feature_code":"PPL",
    "gn:name":"\u021aeghea",
    "gn:population":44,
    "gn:timezone":"Europe/Bucharest",
    "iso:country":"RO",
    "wof:name":"Teghea",
    "wof:placetype":"locality",
    "wof:population":44
},
  "geometry": {"coordinates":[22.73578,47.58661],"type":"Point"}
}