{
  "type": "Feature",
  "properties": {
    "iso:country":"RO",
    "qs_pg:aaroncc":"RO",
    "qs_pg:name":"Negre\u0219ti-Oa\u015f",
    "qs_pg:name_adm0":"Rom\u00e2nia",
    "qs_pg:name_adm1":"Satu Mare",
    "qs_pg:photos":8,
    "qs_pg:photos_1k":2,
    "qs_pg:photos_9k":1,
    "qs_pg:photos_9r":1,
    "qs_pg:photos_all":8,
    "qs_pg:photos_sr":1,
    "qs_pg:pop_sr":0,
    "qs_pg:qs_pg_placetype":"locality",
    "qs_pg:qs_pg_placetype_gp":"Town",
    "qs_pg:woe_adm0":23424933,
    "woe:adm0_id":23424933,
    "woe:name_adm0":"Rom\u00e2nia",
    "woe:name_adm1":"Satu Mare",
    "woe:placetype":"Town",
    "wof:name":"Negre\u0219ti-Oa\u015f",
    "wof:placetype":"locality"
},
  "geometry": {"coordinates":[23.4516905,47.901412],"type":"Point"}
}