{
  "type": "Feature",
  "properties": {
    "gn:admin1_code":"13",
    "gn:admin2_code":"56522.0",
    "gn:asciiname":"Samboleni",
    "gn:cc2":"RO",
    "gn:country_code":"RO",
    "gn:dem":333,
    "gn:feature_class":"P",
    "gn:feature_code":"PPL",
    "gn:name":"S\u00e2mboleni",
    "gn:population":749,
    "gn:timezone":"Europe/Bucharest",
    "iso:country":"RO",
    "name:und_x_variant":[
        "S\u00e2mboleni",
        "S\u00eenbotelec",
        "S\u00eemboleni"
    ],
    "wof:name":"Samboleni",
    "wof:placetype":"locality",
    "wof:population":749
},
  "geometry": {"coordinates":[24.10863,46.80714],"type":"Point"}
}