{
  "type": "Feature",
  "properties": {
    "gn:admin1_code":"02",
    "gn:admin2_code":"11058.0",
    "gn:asciiname":"Leasa",
    "gn:country_code":"RO",
    "gn:dem":231,
    "gn:feature_class":"P",
    "gn:feature_code":"PPL",
    "gn:name":"Leasa",
    "gn:population":356,
    "gn:timezone":"Europe/Bucharest",
    "iso:country":"RO",
    "name:ron_x_preferred":[
        "Leasa"
    ],
    "name:und_x_variant":[
        "Laass",
        "S\u00f6v\u00e9nyes",
        "Le\u00e1sza"
    ],
    "wof:name":"Leasa",
    "wof:placetype":"locality",
    "wof:population":356
},
  "geometry": {"coordinates":[22.546,46.27529000000001],"type":"Point"}
}