{
  "type": "Feature",
  "properties": {
    "gn:admin1_code":"23",
    "gn:admin2_code":"96370.0",
    "gn:asciiname":"Curagau",
    "gn:country_code":"RO",
    "gn:dem":178,
    "gn:feature_class":"P",
    "gn:feature_code":"PPL",
    "gn:name":"Curag\u0103u",
    "gn:population":130,
    "gn:timezone":"Europe/Bucharest",
    "iso:country":"RO",
    "wof:name":"Curagau",
    "wof:placetype":"locality",
    "wof:population":130
},
  "geometry": {"coordinates":[27.7547,47.05856],"type":"Point"}
}