{
  "type": "Feature",
  "properties": {
    "gn:admin1_code":"18",
    "gn:admin2_code":"76807.0",
    "gn:asciiname":"Sarbi",
    "gn:cc2":"RO",
    "gn:country_code":"RO",
    "gn:dem":98,
    "gn:feature_class":"P",
    "gn:feature_code":"PPL",
    "gn:name":"S\u00e2rbi",
    "gn:population":267,
    "gn:timezone":"Europe/Bucharest",
    "iso:country":"RO",
    "name:nor_x_preferred":[
        "Sarbi"
    ],
    "name:und_x_variant":[
        "S\u00e2rbi",
        "S\u00eerbi"
    ],
    "name:vie_x_preferred":[
        "Sarbi"
    ],
    "wof:name":"Sarbi",
    "wof:placetype":"locality",
    "wof:population":267
},
  "geometry": {"coordinates":[27.32722,45.92712],"type":"Point"}
}