{
  "type": "Feature",
  "properties": {
    "gn:gn_country":"RO",
    "gn:gn_fcode":"PPLA2",
    "gn:gn_pop":5126,
    "gn:population":5126,
    "iso:country":"RO",
    "name:eng_x_preferred":[
        "Dr\u0103gu\u021be\u0219ti"
    ],
    "name:fra_x_preferred":[
        "Dr\u0103gu\u021be\u0219ti"
    ],
    "name:ita_x_preferred":[
        "Dr\u0103gu\u021be\u0219ti"
    ],
    "name:msa_x_preferred":[
        "Dr\u0103gu\u021be\u0219ti"
    ],
    "name:nld_x_preferred":[
        "Dr\u0103gu\u021be\u0219ti"
    ],
    "name:por_x_preferred":[
        "Dr\u0103gu\u021be\u0219ti"
    ],
    "name:ron_x_preferred":[
        "Dr\u0103gu\u021be\u0219ti"
    ],
    "name:ukr_x_preferred":[
        "\u0414\u0440\u0435\u0433\u0443\u0446\u0435\u0448\u0442\u044c"
    ],
    "name:vie_x_preferred":[
        "Dragutesti"
    ],
    "name:vol_x_preferred":[
        "Dr\u0103gu\u021be\u0219ti"
    ],
    "qs_pg:aaroncc":"RO",
    "qs_pg:gn_country":"RO",
    "qs_pg:gn_fcode":"PPLA2",
    "qs_pg:gn_pop":5126,
    "qs_pg:name":"Dr\u0103gu\u0163e\u015fti",
    "qs_pg:photos_9r":0,
    "qs_pg:photos_sr":0,
    "qs_pg:pop_sr":5,
    "qs_pg:qs_pg_placetype":"locality",
    "wof:name":"Dr\u0103gu\u0163e\u015fti",
    "wof:placetype":"locality",
    "wof:population":5126
},
  "geometry": {"coordinates":[23.23333,44.96667],"type":"Point"}
}