{
  "type": "Feature",
  "properties": {
    "gn:country":"RO",
    "gn:fcode":"PPLA2",
    "gn:population":3377,
    "iso:country":"RO",
    "name:ceb_x_preferred":[
        "Bere\u0219ti-Bistri\u021ba"
    ],
    "name:eng_x_preferred":[
        "Bere\u0219ti-Bistri\u021ba"
    ],
    "name:fra_x_preferred":[
        "Bere\u0219ti-Bistri\u021ba"
    ],
    "name:hun_x_preferred":[
        "Bere\u0219ti-Bistri\u021ba"
    ],
    "name:ita_x_preferred":[
        "Bere\u0219ti-Bistri\u021ba"
    ],
    "name:nld_x_preferred":[
        "Bere\u0219ti-Bistri\u021ba"
    ],
    "name:ron_x_preferred":[
        "Bere\u0219ti-Bistri\u021ba"
    ],
    "name:srp_x_preferred":[
        "\u0411\u0435\u0440\u0435\u0448\u0442\u0438-\u0411\u0438\u0441\u0442\u0440\u0438\u0446\u0430"
    ],
    "name:ukr_x_preferred":[
        "\u0411\u0435\u0440\u0435\u0448\u0442\u044c-\u0411\u0456\u0441\u0442\u0440\u0456\u0446\u0430"
    ],
    "name:und_x_variant":[
        "Bere\u015fti"
    ],
    "qs_pg:aaroncc":"RO",
    "qs_pg:gn_country":"RO",
    "qs_pg:gn_fcode":"PPLA2",
    "qs_pg:gn_pop":3377,
    "qs_pg:name":"Bere\u0219ti-Bistri\u021ba",
    "qs_pg:name_adm0":"Rom\u00e2nia",
    "qs_pg:name_adm1":"Bacau",
    "qs_pg:photos_9k":1,
    "qs_pg:photos_9r":1,
    "qs_pg:photos_all":4,
    "qs_pg:photos_sr":0,
    "qs_pg:pop_sr":4,
    "qs_pg:qs_pg_placetype":"locality",
    "qs_pg:qs_pg_placetype_gp":"Town",
    "qs_pg:woe_adm0":23424933,
    "woe:adm0_id":23424933,
    "woe:name_adm0":"Rom\u00e2nia",
    "woe:name_adm1":"Bacau",
    "woe:placetype":"Town",
    "wof:name":"Bere\u0219ti-Bistri\u021ba",
    "wof:placetype":"locality",
    "wof:population":3377
},
  "geometry": {"coordinates":[26.83333,46.71667],"type":"Point"}
}