{
  "type": "Feature",
  "properties": {
    "gn:gn_country":"RO",
    "gn:gn_fcode":"PPLA2",
    "gn:gn_pop":3017,
    "gn:population":3017,
    "iso:country":"RO",
    "name:ceb_x_preferred":[
        "Salcia Tudor"
    ],
    "name:eng_x_preferred":[
        "Salcia Tudor"
    ],
    "name:fra_x_preferred":[
        "Salcia Tudor"
    ],
    "name:ita_x_preferred":[
        "Salcia Tudor"
    ],
    "name:nld_x_preferred":[
        "Salcia Tudor"
    ],
    "name:ron_x_preferred":[
        "Salcia Tudor"
    ],
    "name:srp_x_preferred":[
        "\u0421\u0430\u043b\u0447\u0430 \u0422\u0443\u0434\u043e\u0440"
    ],
    "name:ukr_x_preferred":[
        "\u0421\u0430\u043b\u0447\u0430-\u0422\u0443\u0434\u043e\u0440"
    ],
    "name:unk_x_variant":[
        "Domni\u0163a Ileana"
    ],
    "qs_pg:aaroncc":"RO",
    "qs_pg:gn_country":"RO",
    "qs_pg:gn_fcode":"PPLA2",
    "qs_pg:gn_pop":3017,
    "qs_pg:name":"Salcia Tudor",
    "qs_pg:name_adm0":"Rom\u00e2nia",
    "qs_pg:name_adm1":"Braila",
    "qs_pg:photos_9r":0,
    "qs_pg:photos_sr":0,
    "qs_pg:pop_sr":4,
    "qs_pg:qs_pg_placetype":"locality",
    "qs_pg:qs_pg_placetype_gp":"Town",
    "qs_pg:woe_adm0":23424933,
    "woe:adm0_id":23424933,
    "woe:name_adm0":"Rom\u00e2nia",
    "woe:name_adm1":"Braila",
    "woe:placetype":"Town",
    "wof:name":"Salcia Tudor",
    "wof:placetype":"locality",
    "wof:population":3017
},
  "geometry": {"coordinates":[27.51667,45.36667],"type":"Point"}
}