{
  "type": "Feature",
  "properties": {
    "gn:admin1_code":"32",
    "gn:admin2_code":"138164",
    "gn:asciiname":"Bercu Nou",
    "gn:country_code":"RO",
    "gn:dem":121,
    "gn:feature_class":"P",
    "gn:feature_code":"PPL",
    "gn:name":"Bercu Nou",
    "gn:population":276,
    "gn:timezone":"Europe/Bucharest",
    "iso:country":"RO",
    "wof:name":"Bercu Nou",
    "wof:placetype":"locality",
    "wof:population":276
},
  "geometry": {"coordinates":[22.92936,47.93357],"type":"Point"}
}