{
  "type": "Feature",
  "properties": {
    "gn:admin1_code":"20",
    "gn:admin2_code":"83785.0",
    "gn:asciiname":"Criseni",
    "gn:cc2":"RO",
    "gn:country_code":"RO",
    "gn:dem":397,
    "gn:feature_class":"P",
    "gn:feature_code":"PPL",
    "gn:name":"Cri\u0219eni",
    "gn:population":729,
    "gn:timezone":"Europe/Bucharest",
    "iso:country":"RO",
    "name:und_x_variant":[
        "K\u00f6rispatak",
        "Cri\u015feni"
    ],
    "wof:name":"Criseni",
    "wof:placetype":"locality",
    "wof:population":729
},
  "geometry": {"coordinates":[24.97324,46.41591],"type":"Point"}
}