{
  "type": "Feature",
  "properties": {
    "iso:country":"RO",
    "name:cat_x_preferred":[
        "B\u0103neasa"
    ],
    "name:eng_x_preferred":[
        "B\u0103neasa"
    ],
    "name:epo_x_preferred":[
        "B\u0103neasa"
    ],
    "name:fra_x_preferred":[
        "B\u0103neasa"
    ],
    "name:ita_x_preferred":[
        "B\u0103neasa"
    ],
    "name:jpn_x_preferred":[
        "\u30d0\u30cd\u30a2\u30b5"
    ],
    "name:lat_x_preferred":[
        "B\u0103neasa"
    ],
    "name:nld_x_preferred":[
        "B\u0103neasa"
    ],
    "name:ron_x_preferred":[
        "B\u0103neasa"
    ],
    "name:rus_x_preferred":[
        "B\u0103neasa"
    ],
    "name:spa_x_preferred":[
        "B\u0103neasa"
    ],
    "wof:name":"Baneasa",
    "wof:placetype":"neighbourhood"
},
  "geometry": {"coordinates":[26.06777111149338,44.49825331964584],"type":"Point"}
}