{
  "type": "Feature",
  "properties": {
    "gn:admin1_code":"18",
    "gn:admin2_code":"75766",
    "gn:asciiname":"Brahasestii de Sus",
    "gn:country_code":"RO",
    "gn:dem":117,
    "gn:feature_class":"P",
    "gn:feature_code":"PPL",
    "gn:name":"Br\u0103h\u0103\u015fe\u015ftii de Sus",
    "gn:population":7692,
    "gn:timezone":"Europe/Bucharest",
    "iso:country":"RO",
    "name:und_x_variant":[
        "Br\u0103h\u0103\u015fe\u015fti-de-Sus",
        "Br\u0103h\u0103\u015fe\u015fti",
        "Br\u0103h\u0103\u015fe\u015ftii de Sus"
    ],
    "wof:name":"Brahasestii de Sus",
    "wof:placetype":"locality",
    "wof:population":7692
},
  "geometry": {"coordinates":[27.35,46.05],"type":"Point"}
}