{
  "type": "Feature",
  "properties": {
    "gn:admin1_code":"18",
    "gn:admin2_code":"75766",
    "gn:asciiname":"Brahasestii de Sus",
    "gn:country_code":"RO",
    "gn:dem":117,
    "gn:feature_class":"P",
    "gn:feature_code":"PPL",
    "gn:name":"Br\u0103h\u0103\u015fe\u015ftii de Sus",
    "gn:population":7692,
    "gn:timezone":"Europe/Bucharest",
    "iso:country":"RO",
    "name:ceb_x_preferred":[
        "Comuna Br\u0103h\u0103\u0219e\u0219ti"
    ],
    "name:eus_x_preferred":[
        "Br\u0103h\u0103\u0219e\u0219ti"
    ],
    "name:fra_x_preferred":[
        "Br\u0103h\u0103\u0219e\u0219ti"
    ],
    "name:ita_x_preferred":[
        "Br\u0103h\u0103\u0219e\u0219ti"
    ],
    "name:msa_x_preferred":[
        "Br\u0103h\u0103\u015fe\u015fti"
    ],
    "name:nld_x_preferred":[
        "Br\u0103h\u0103\u0219e\u0219ti"
    ],
    "name:por_x_preferred":[
        "Br\u0103h\u0103\u015fe\u015fti"
    ],
    "name:ron_x_preferred":[
        "Comuna Br\u0103h\u0103\u0219e\u0219ti"
    ],
    "name:srp_x_preferred":[
        "\u041e\u043f\u0448\u0442\u0438\u043d\u0430 \u0411\u0440\u0430\u0445\u0430\u0448\u0435\u0448\u0442\u0438"
    ],
    "name:ukr_x_preferred":[
        "\u0411\u0440\u0435\u0445\u0435\u0448\u0435\u0448\u0442\u044c"
    ],
    "name:und_x_variant":[
        "Br\u0103h\u0103\u015fe\u015fti-de-Sus",
        "Br\u0103h\u0103\u015fe\u015ftii de Sus"
    ],
    "name:vie_x_preferred":[
        "Br\u0103h\u0103\u0219e\u0219ti"
    ],
    "name:vol_x_preferred":[
        "Br\u0103h\u0103\u015fe\u015fti"
    ],
    "name:zho_x_preferred":[
        "\u5e03\u52d2\u8d6b\u8b1d\u4ec0\u8482\u9109"
    ],
    "wof:name":"Brahasestii de Sus",
    "wof:placetype":"locality",
    "wof:population":7692
},
  "geometry": {"coordinates":[27.35,46.05],"type":"Point"}
}