{
  "type": "Feature",
  "properties": {
    "gn:admin1_code":"35",
    "gn:admin2_code":"154521.0",
    "gn:asciiname":"Rotaresti",
    "gn:country_code":"RO",
    "gn:dem":115,
    "gn:feature_class":"P",
    "gn:feature_code":"PPL",
    "gn:name":"Rot\u0103re\u0219ti",
    "gn:population":407,
    "gn:timezone":"Europe/Bucharest",
    "iso:country":"RO",
    "wof:name":"Rotaresti",
    "wof:placetype":"locality",
    "wof:population":407
},
  "geometry": {"coordinates":[25.32728,44.25757],"type":"Point"}
}