{
  "type": "Feature",
  "properties": {
    "gn:admin1_code":"23",
    "gn:admin2_code":"100344.0",
    "gn:asciiname":"Radeni",
    "gn:country_code":"RO",
    "gn:dem":72,
    "gn:feature_class":"P",
    "gn:feature_code":"PPL",
    "gn:name":"R\u0103deni",
    "gn:population":715,
    "gn:timezone":"Europe/Bucharest",
    "iso:country":"RO",
    "wof:name":"Radeni",
    "wof:placetype":"locality",
    "wof:population":715
},
  "geometry": {"coordinates":[27.43536,47.42937],"type":"Point"}
}