{
  "type": "Feature",
  "properties": {
    "gn:country":"RO",
    "gn:fcode":"PPLX",
    "gn:population":0,
    "iso:country":"RO",
    "name:ceb_x_preferred":[
        "Chilia"
    ],
    "name:deu_x_preferred":[
        "Chilia"
    ],
    "name:fra_x_preferred":[
        "Chilia"
    ],
    "name:ita_x_preferred":[
        "Chilia"
    ],
    "name:nld_x_preferred":[
        "Chilia"
    ],
    "name:ron_x_preferred":[
        "Chilia"
    ],
    "name:srp_x_preferred":[
        "\u041a\u0438\u043b\u0438\u0458\u0430"
    ],
    "name:ukr_x_preferred":[
        "\u041a\u0456\u043b\u0456\u044f"
    ],
    "qs_pg:aaroncc":"RO",
    "qs_pg:gn_country":"RO",
    "qs_pg:gn_fcode":"PPLX",
    "qs_pg:gn_pop":0,
    "qs_pg:name":"Chilia",
    "qs_pg:name_adm0":"Rom\u00e2nia",
    "qs_pg:name_adm1":"Suceava",
    "qs_pg:photos":1,
    "qs_pg:photos_1k":1,
    "qs_pg:photos_9k":1,
    "qs_pg:photos_9r":1,
    "qs_pg:photos_all":1,
    "qs_pg:photos_sr":1,
    "qs_pg:pop_sr":0,
    "qs_pg:qs_pg_placetype":"neighbourhood",
    "qs_pg:qs_pg_placetype_gp":"Suburb",
    "qs_pg:woe_adm0":23424933,
    "woe:adm0_id":23424933,
    "woe:name_adm0":"Rom\u00e2nia",
    "woe:name_adm1":"Suceava",
    "woe:placetype":"Suburb",
    "wof:lang_x_official":[
        "ron"
    ],
    "wof:lang_x_spoken":[
        "ron"
    ],
    "wof:name":"Chilia",
    "wof:placetype":"neighbourhood"
},
  "geometry": {"coordinates":[25.38333,47.35],"type":"Point"}
}