{
  "type": "Feature",
  "properties": {
    "gn:admin1_code":"03",
    "gn:admin2_code":"17913.0",
    "gn:asciiname":"Ioanicesti",
    "gn:country_code":"RO",
    "gn:dem":405,
    "gn:feature_class":"P",
    "gn:feature_code":"PPL",
    "gn:name":"Ioanice\u0219ti",
    "gn:population":336,
    "gn:timezone":"Europe/Bucharest",
    "iso:country":"RO",
    "wof:name":"Ioanicesti",
    "wof:placetype":"locality",
    "wof:population":336
},
  "geometry": {"coordinates":[24.51154,45.06371],"type":"Point"}
}