{
  "type": "Feature",
  "properties": {
    "gn:admin1_code":"19",
    "gn:admin2_code":"80766.0",
    "gn:asciiname":"Frunza",
    "gn:cc2":"RO",
    "gn:country_code":"RO",
    "gn:dem":271,
    "gn:feature_class":"P",
    "gn:feature_code":"PPL",
    "gn:name":"Frunza",
    "gn:population":466,
    "gn:timezone":"Europe/Bucharest",
    "iso:country":"RO",
    "name:und_x_variant":[
        "T\u00e2nd\u0103le\u015fti",
        "T\u00eend\u0103le\u015fti",
        "Frunza"
    ],
    "wof:name":"Frunza",
    "wof:placetype":"locality",
    "wof:population":466
},
  "geometry": {"coordinates":[23.69534,44.85024],"type":"Point"}
}