{
  "type": "Feature",
  "properties": {
    "gn:admin1_code":"39",
    "gn:admin2_code":"173597",
    "gn:asciiname":"Borosesti",
    "gn:country_code":"RO",
    "gn:dem":166,
    "gn:feature_class":"P",
    "gn:feature_code":"PPL",
    "gn:name":"Boro\u0219e\u0219ti",
    "gn:population":878,
    "gn:timezone":"Europe/Bucharest",
    "iso:country":"RO",
    "wof:name":"Borosesti",
    "wof:placetype":"locality",
    "wof:population":878
},
  "geometry": {"coordinates":[24.21402,44.65934],"type":"Point"}
}