{
  "type": "Feature",
  "properties": {
    "gn:admin1_code":"37",
    "gn:admin2_code":"160644.0",
    "gn:asciiname":"Visina",
    "gn:cc2":"RO",
    "gn:country_code":"RO",
    "gn:dem":12,
    "gn:feature_class":"P",
    "gn:feature_code":"PPL",
    "gn:name":"Vi\u0219ina",
    "gn:population":889,
    "gn:timezone":"Europe/Bucharest",
    "iso:country":"RO",
    "name:und_x_variant":[
        "Pa\u015fa C\u00e2\u015fla",
        "Pasa Kisla",
        "Pa\u015fa-C\u00ee\u015fla",
        "Vi\u015fina"
    ],
    "wof:name":"Visina",
    "wof:placetype":"locality",
    "wof:population":889
},
  "geometry": {"coordinates":[28.84262,44.75798],"type":"Point"}
}