{
  "type": "Feature",
  "properties": {
    "gn:admin1_code":"04",
    "gn:admin2_code":"25629.0",
    "gn:asciiname":"Nadisa",
    "gn:country_code":"RO",
    "gn:dem":333,
    "gn:feature_class":"P",
    "gn:feature_code":"PPL",
    "gn:name":"Nadi\u0219a",
    "gn:population":331,
    "gn:timezone":"Europe/Bucharest",
    "iso:country":"RO",
    "wof:name":"Nadisa",
    "wof:placetype":"locality",
    "wof:population":331
},
  "geometry": {"coordinates":[26.70494,46.52058],"type":"Point"}
}