{
  "type": "Feature",
  "properties": {
    "gn:admin1_code":"29",
    "gn:admin2_code":"127750.0",
    "gn:asciiname":"Coteni",
    "gn:country_code":"RO",
    "gn:dem":82,
    "gn:feature_class":"P",
    "gn:feature_code":"PPL",
    "gn:name":"Coteni",
    "gn:population":288,
    "gn:timezone":"Europe/Bucharest",
    "iso:country":"RO",
    "name:ceb_x_preferred":[
        "Coteni"
    ],
    "name:deu_x_preferred":[
        "Coteni"
    ],
    "name:ron_x_preferred":[
        "Coteni"
    ],
    "name:srp_x_preferred":[
        "\u041a\u043e\u0442\u0435\u043d\u0438"
    ],
    "wof:name":"Coteni",
    "wof:placetype":"locality",
    "wof:population":288
},
  "geometry": {"coordinates":[24.33984,43.87794],"type":"Point"}
}