{
  "type": "Feature",
  "properties": {
    "gn:gn_country":"RO",
    "gn:gn_fcode":"PPL",
    "gn:gn_pop":3271,
    "gn:population":3271,
    "iso:country":"RO",
    "name:eng_x_preferred":[
        "Dobreni"
    ],
    "name:nld_x_preferred":[
        "Dobreni"
    ],
    "name:ron_x_preferred":[
        "Dobreni"
    ],
    "name:srp_x_preferred":[
        "\u0414\u043e\u0431\u0440\u0435\u043d\u0438"
    ],
    "name:ukr_x_preferred":[
        "\u0414\u043e\u0431\u0440\u0435\u043d\u044c"
    ],
    "name:unk_x_variant":[
        "Dobrenii"
    ],
    "qs_pg:aaroncc":"RO",
    "qs_pg:gn_country":"RO",
    "qs_pg:gn_fcode":"PPL",
    "qs_pg:gn_pop":3271,
    "qs_pg:name":"Dobreni",
    "qs_pg:name_adm0":"Rom\u00e2nia",
    "qs_pg:name_adm1":"Teleorman",
    "qs_pg:photos_9r":0,
    "qs_pg:photos_sr":0,
    "qs_pg:pop_sr":4,
    "qs_pg:qs_pg_placetype":"locality",
    "qs_pg:qs_pg_placetype_gp":"Town",
    "qs_pg:woe_adm0":23424933,
    "woe:adm0_id":23424933,
    "woe:name_adm0":"Rom\u00e2nia",
    "woe:name_adm1":"Teleorman",
    "woe:placetype":"Town",
    "wof:name":"Dobreni",
    "wof:placetype":"locality",
    "wof:population":3271
},
  "geometry": {"coordinates":[25.11667,44.41667],"type":"Point"}
}