{
  "type": "Feature",
  "properties": {
    "gn:admin1_code":"01",
    "gn:admin2_code":"3459.0",
    "gn:asciiname":"Magura",
    "gn:country_code":"RO",
    "gn:dem":774,
    "gn:feature_class":"P",
    "gn:feature_code":"PPL",
    "gn:name":"M\u0103gura",
    "gn:population":33,
    "gn:timezone":"Europe/Bucharest",
    "iso:country":"RO",
    "wof:name":"Magura",
    "wof:placetype":"locality",
    "wof:population":33
},
  "geometry": {"coordinates":[23.14361,46.24679],"type":"Point"}
}