{
  "type": "Feature",
  "properties": {
    "gn:gn_country":"RO",
    "gn:gn_fcode":"PPLA2",
    "gn:gn_pop":2009,
    "gn:population":2009,
    "iso:country":"RO",
    "name:ara_x_preferred":[
        "\u0628\u064a\u0631\u0643\u064a\u0634"
    ],
    "name:ceb_x_preferred":[
        "Birchi\u0219"
    ],
    "name:deu_x_preferred":[
        "Birchi\u0219"
    ],
    "name:eng_x_preferred":[
        "Birchi\u0219"
    ],
    "name:epo_x_preferred":[
        "Birchi\u0219"
    ],
    "name:fra_x_preferred":[
        "Birchi\u0219"
    ],
    "name:hun_x_preferred":[
        "Marosberkes"
    ],
    "name:ita_x_preferred":[
        "Birchi\u0219"
    ],
    "name:mkd_x_preferred":[
        "\u0411\u0438\u0440\u043a\u0438\u0448"
    ],
    "name:msa_x_preferred":[
        "Birchi\u0219"
    ],
    "name:nld_x_preferred":[
        "Birchi\u0219"
    ],
    "name:por_x_preferred":[
        "Birchi\u0219"
    ],
    "name:ron_x_preferred":[
        "Birchi\u0219"
    ],
    "name:sqi_x_preferred":[
        "Birchi\u0219"
    ],
    "name:srp_x_preferred":[
        "\u0411\u0438\u0440\u043a\u0438\u0448"
    ],
    "name:ukr_x_preferred":[
        "\u0411\u0456\u0440\u043a\u0456\u0448"
    ],
    "name:vie_x_preferred":[
        "Birchis"
    ],
    "name:vol_x_preferred":[
        "Birchi\u0219"
    ],
    "qs_pg:aaroncc":"RO",
    "qs_pg:gn_country":"RO",
    "qs_pg:gn_fcode":"PPLA2",
    "qs_pg:gn_pop":2009,
    "qs_pg:name":"Birchi\u015f",
    "qs_pg:photos_9r":0,
    "qs_pg:photos_sr":0,
    "qs_pg:pop_sr":4,
    "qs_pg:qs_pg_placetype":"locality",
    "wof:name":"Birchi\u015f",
    "wof:placetype":"locality",
    "wof:population":2009
},
  "geometry": {"coordinates":[22.16667,45.96667],"type":"Point"}
}