{
  "type": "Feature",
  "properties": {
    "gn:admin1_code":"32",
    "gn:admin2_code":"136964.0",
    "gn:asciiname":"Sandra",
    "gn:country_code":"RO",
    "gn:dem":219,
    "gn:feature_class":"P",
    "gn:feature_code":"PPL",
    "gn:name":"\u0218andra",
    "gn:population":207,
    "gn:timezone":"Europe/Bucharest",
    "iso:country":"RO",
    "wof:name":"Sandra",
    "wof:placetype":"locality",
    "wof:population":207
},
  "geometry": {"coordinates":[22.91451,47.55842],"type":"Point"}
}