{
  "type": "Feature",
  "properties": {
    "gn:admin1_code":"32",
    "gn:admin2_code":"136964.0",
    "gn:asciiname":"Sandra",
    "gn:country_code":"RO",
    "gn:dem":219,
    "gn:feature_class":"P",
    "gn:feature_code":"PPL",
    "gn:name":"\u0218andra",
    "gn:population":207,
    "gn:timezone":"Europe/Bucharest",
    "iso:country":"RO",
    "name:ceb_x_preferred":[
        "Sandra"
    ],
    "name:deu_x_preferred":[
        "Sandra"
    ],
    "name:fas_x_preferred":[
        "\u0633\u0627\u0646\u062f\u0631\u0627"
    ],
    "name:fra_x_preferred":[
        "Sandra"
    ],
    "name:heb_x_preferred":[
        "\u05e1\u05e0\u05d3\u05e8\u05d4"
    ],
    "name:ita_x_preferred":[
        "Sandra"
    ],
    "name:jpn_x_preferred":[
        "\u30b5\u30f3\u30c9\u30e9"
    ],
    "name:kor_x_preferred":[
        "\uc0b0\ub4dc\ub77c"
    ],
    "name:nld_x_preferred":[
        "Sandra"
    ],
    "name:pol_x_preferred":[
        "Sandra"
    ],
    "name:por_x_preferred":[
        "Sandra"
    ],
    "name:rus_x_preferred":[
        "\u0421\u0430\u043d\u0434\u0440\u0430"
    ],
    "name:slk_x_preferred":[
        "Sandra"
    ],
    "name:swe_x_preferred":[
        "Sandra"
    ],
    "name:vie_x_preferred":[
        "Sandra"
    ],
    "wof:name":"Sandra",
    "wof:placetype":"locality",
    "wof:population":207
},
  "geometry": {"coordinates":[22.91451,47.55842],"type":"Point"}
}