{
  "type": "Feature",
  "properties": {
    "gn:admin1_code":"07",
    "gn:admin2_code":"39983.0",
    "gn:asciiname":"Soldanesti",
    "gn:country_code":"RO",
    "gn:dem":188,
    "gn:feature_class":"P",
    "gn:feature_code":"PPL",
    "gn:name":"\u0218old\u0103ne\u0219ti",
    "gn:population":510,
    "gn:timezone":"Europe/Bucharest",
    "iso:country":"RO",
    "wof:name":"Soldanesti",
    "wof:placetype":"locality",
    "wof:population":510
},
  "geometry": {"coordinates":[26.92529,47.73522],"type":"Point"}
}