{
  "type": "Feature",
  "properties": {
    "gn:population":1295,
    "iso:country":"RO",
    "name:eng_x_preferred":[
        "Cuejdiu"
    ],
    "name:fra_x_preferred":[
        "Cuejdiu"
    ],
    "name:ita_x_preferred":[
        "Cuejdiu"
    ],
    "name:nld_x_preferred":[
        "Cuejdiu"
    ],
    "name:ron_x_preferred":[
        "Cuejdiu"
    ],
    "name:ukr_x_preferred":[
        "\u041a\u0443\u0454\u0436\u0434\u0456\u0443"
    ],
    "name:unk_x_variant":[
        "Cuejdiul"
    ],
    "qs:a0":"Rom\u00e2nia",
    "qs:a1":"*Neamt",
    "qs:a1r":"0",
    "qs:adm0":"Rom\u00e2nia",
    "qs:la_lc":"*",
    "qs:level":"locality",
    "qs:loc":"Cuejdiu",
    "qs:loc_alt":"Cuejdiu",
    "qs:pop":0,
    "qs:type":"buffered point",
    "wof:name":"Cuejdiu",
    "wof:placetype":"locality",
    "wof:population":1295
},
  "geometry": {"coordinates":[26.290714,46.990189],"type":"Point"}
}