{
  "type": "Feature",
  "properties": {
    "gn:admin1_code":"05",
    "gn:admin2_code":"31057.0",
    "gn:asciiname":"Rogoz",
    "gn:country_code":"RO",
    "gn:dem":146,
    "gn:feature_class":"P",
    "gn:feature_code":"PPL",
    "gn:name":"Rogoz",
    "gn:population":409,
    "gn:timezone":"Europe/Bucharest",
    "iso:country":"RO",
    "wof:name":"Rogoz",
    "wof:placetype":"locality",
    "wof:population":409
},
  "geometry": {"coordinates":[22.17056,46.79225],"type":"Point"}
}