{
  "type": "Feature",
  "properties": {
    "gn:admin1_code":"06",
    "gn:admin2_code":"34770",
    "gn:asciiname":"Agrisu de Jos",
    "gn:cc2":"RO",
    "gn:country_code":"RO",
    "gn:dem":311,
    "gn:feature_class":"P",
    "gn:feature_code":"PPL",
    "gn:name":"Agri\u0219u de Jos",
    "gn:population":402,
    "gn:timezone":"Europe/Bucharest",
    "iso:country":"RO",
    "name:und_x_variant":[
        "Agrisul de Jos",
        "Agri\u015fu de Jos"
    ],
    "wof:name":"Agrisu de Jos",
    "wof:placetype":"locality",
    "wof:population":402
},
  "geometry": {"coordinates":[24.23761,47.15703],"type":"Point"}
}