{
  "type": "Feature",
  "properties": {
    "gn:admin1_code":"05",
    "gn:admin2_code":"27212.0",
    "gn:asciiname":"Cacuciu Vechi",
    "gn:cc2":"RO",
    "gn:country_code":"RO",
    "gn:dem":254,
    "gn:feature_class":"P",
    "gn:feature_code":"PPL",
    "gn:name":"Cacuciu Vechi",
    "gn:population":190,
    "gn:timezone":"Europe/Bucharest",
    "iso:country":"RO",
    "name:und_x_variant":[
        "C\u0103cuciu Vechiu",
        "Cacuciu Vechi"
    ],
    "wof:name":"Cacuciu Vechi",
    "wof:placetype":"locality",
    "wof:population":190
},
  "geometry": {"coordinates":[22.49216,47.0234],"type":"Point"}
}