{
  "type": "Feature",
  "properties": {
    "gn:admin1_code":"04",
    "gn:admin2_code":"25521.0",
    "gn:asciiname":"Slobozia Noua",
    "gn:country_code":"RO",
    "gn:dem":329,
    "gn:feature_class":"P",
    "gn:feature_code":"PPL",
    "gn:name":"Slobozia Nou\u0103",
    "gn:population":596,
    "gn:timezone":"Europe/Bucharest",
    "iso:country":"RO",
    "wof:name":"Slobozia Noua",
    "wof:placetype":"locality",
    "wof:population":596
},
  "geometry": {"coordinates":[27.29773,46.53959],"type":"Point"}
}