{
  "type": "Feature",
  "properties": {
    "gn:admin1_code":"04",
    "gn:admin2_code":"21249.0",
    "gn:asciiname":"Padureni",
    "gn:country_code":"RO",
    "gn:dem":252,
    "gn:feature_class":"P",
    "gn:feature_code":"PPL",
    "gn:name":"P\u0103dureni",
    "gn:population":409,
    "gn:timezone":"Europe/Bucharest",
    "iso:country":"RO",
    "wof:name":"Padureni",
    "wof:placetype":"locality",
    "wof:population":409
},
  "geometry": {"coordinates":[26.84047,46.71421],"type":"Point"}
}