{
  "type": "Feature",
  "properties": {
    "gn:admin1_code":"34",
    "gn:admin2_code":"146281.0",
    "gn:asciiname":"Tisauti",
    "gn:country_code":"RO",
    "gn:dem":278,
    "gn:feature_class":"P",
    "gn:feature_code":"PPL",
    "gn:name":"Ti\u0219\u0103u\u021bi",
    "gn:population":799,
    "gn:timezone":"Europe/Bucharest",
    "iso:country":"RO",
    "wof:name":"Tisauti",
    "wof:placetype":"locality",
    "wof:population":799
},
  "geometry": {"coordinates":[26.31162,47.62471],"type":"Point"}
}