{
  "type": "Feature",
  "properties": {
    "gn:admin1_code":"02",
    "gn:admin2_code":"11762.0",
    "gn:asciiname":"Rostoci",
    "gn:country_code":"RO",
    "gn:dem":184,
    "gn:feature_class":"P",
    "gn:feature_code":"PPL",
    "gn:name":"Rostoci",
    "gn:population":158,
    "gn:timezone":"Europe/Bucharest",
    "iso:country":"RO",
    "name:ron_x_preferred":[
        "Rostoci"
    ],
    "name:und_x_variant":[
        "Roszt\u00f3cs",
        "Roszt\u00f3cz",
        "Restoci",
        "Rost\u00f3cs"
    ],
    "wof:name":"Rostoci",
    "wof:placetype":"locality",
    "wof:population":158
},
  "geometry": {"coordinates":[22.39905,46.28562],"type":"Point"}
}