{
  "type": "Feature",
  "properties": {
    "gn:admin1_code":"42",
    "gn:admin2_code":"102348.0",
    "gn:asciiname":"Crevedia Mica",
    "gn:country_code":"RO",
    "gn:dem":102,
    "gn:feature_class":"P",
    "gn:feature_code":"PPL",
    "gn:name":"Crevedia Mic\u0103",
    "gn:population":999,
    "gn:timezone":"Europe/Bucharest",
    "iso:country":"RO",
    "wof:name":"Crevedia Mica",
    "wof:placetype":"locality",
    "wof:population":999
},
  "geometry": {"coordinates":[25.61008,44.44151],"type":"Point"}
}