{
  "type": "Feature",
  "properties": {
    "gn:admin1_code":"01",
    "gn:admin2_code":"1455.0",
    "gn:asciiname":"Peste Valea Bistrii",
    "gn:country_code":"RO",
    "gn:dem":1049,
    "gn:feature_class":"P",
    "gn:feature_code":"PPL",
    "gn:name":"Peste Valea Bistrii",
    "gn:population":31,
    "gn:timezone":"Europe/Bucharest",
    "iso:country":"RO",
    "wof:name":"Peste Valea Bistrii",
    "wof:placetype":"locality",
    "wof:population":31
},
  "geometry": {"coordinates":[23.04185,46.43679],"type":"Point"}
}