{
  "type": "Feature",
  "properties": {
    "gn:admin1_code":"02",
    "gn:admin2_code":"11174.0",
    "gn:asciiname":"Tarnavita",
    "gn:country_code":"RO",
    "gn:dem":304,
    "gn:feature_class":"P",
    "gn:feature_code":"PPL",
    "gn:name":"T\u00e2rnavi\u0163a",
    "gn:population":0,
    "gn:timezone":"Europe/Bucharest",
    "iso:country":"RO",
    "name:ron_x_preferred":[
        "T\u00e2rnavi\u0163a"
    ],
    "name:und_x_variant":[
        "Tirnovicza",
        "T\u00eernavi\u0163a",
        "T\u00eernovi\u0163a",
        "Ternavicza",
        "Fazekastarn\u00f3"
    ],
    "wof:name":"Tarnavita",
    "wof:placetype":"locality"
},
  "geometry": {"coordinates":[22.65,46.25],"type":"Point"}
}