{
  "type": "Feature",
  "properties": {
    "gn:admin1_code":"38",
    "gn:admin2_code":"167311.0",
    "gn:asciiname":"Satu Nou",
    "gn:country_code":"RO",
    "gn:dem":109,
    "gn:feature_class":"P",
    "gn:feature_code":"PPL",
    "gn:name":"Satu Nou",
    "gn:population":217,
    "gn:timezone":"Europe/Bucharest",
    "iso:country":"RO",
    "wof:name":"Satu Nou",
    "wof:placetype":"locality",
    "wof:population":217
},
  "geometry": {"coordinates":[27.59661,46.04419],"type":"Point"}
}