{
  "type": "Feature",
  "properties": {
    "gn:admin1_code":"04",
    "gn:admin2_code":"25291.0",
    "gn:asciiname":"Serpeni",
    "gn:country_code":"RO",
    "gn:dem":268,
    "gn:feature_class":"P",
    "gn:feature_code":"PPL",
    "gn:name":"\u0218erpeni",
    "gn:population":76,
    "gn:timezone":"Europe/Bucharest",
    "iso:country":"RO",
    "wof:name":"Serpeni",
    "wof:placetype":"locality",
    "wof:population":76
},
  "geometry": {"coordinates":[26.69983,46.61443],"type":"Point"}
}