{
  "type": "Feature",
  "properties": {
    "gn:admin1_code":"13",
    "gn:admin2_code":"55473.0",
    "gn:asciiname":"Macau",
    "gn:cc2":"RO",
    "gn:country_code":"RO",
    "gn:dem":469,
    "gn:feature_class":"P",
    "gn:feature_code":"PPL",
    "gn:name":"Mac\u0103u",
    "gn:population":805,
    "gn:timezone":"Europe/Bucharest",
    "iso:country":"RO",
    "name:und_x_variant":[
        "M\u0103c\u0103ul",
        "M\u0103c\u0103u"
    ],
    "wof:name":"Macau",
    "wof:placetype":"locality",
    "wof:population":805
},
  "geometry": {"coordinates":[23.29378,46.83092],"type":"Point"}
}