{
  "type": "Feature",
  "properties": {
    "gn:admin1_code":"30",
    "gn:admin2_code":"134336.0",
    "gn:asciiname":"Slavu",
    "gn:country_code":"RO",
    "gn:dem":365,
    "gn:feature_class":"P",
    "gn:feature_code":"PPL",
    "gn:name":"Slavu",
    "gn:population":247,
    "gn:timezone":"Europe/Bucharest",
    "iso:country":"RO",
    "wof:name":"Slavu",
    "wof:placetype":"locality",
    "wof:population":247
},
  "geometry": {"coordinates":[26.12554,45.16009],"type":"Point"}
}