{
  "type": "Feature",
  "properties": {
    "gn:admin1_code":"04",
    "gn:admin2_code":"24089.0",
    "gn:asciiname":"Milestii de Sus",
    "gn:country_code":"RO",
    "gn:dem":231,
    "gn:feature_class":"P",
    "gn:feature_code":"PPL",
    "gn:name":"Mile\u0219tii de Sus",
    "gn:population":118,
    "gn:timezone":"Europe/Bucharest",
    "iso:country":"RO",
    "name:und_x_variant":[
        "Burdugani",
        "Milesti-de Sus"
    ],
    "wof:name":"Milestii de Sus",
    "wof:placetype":"locality",
    "wof:population":118
},
  "geometry": {"coordinates":[27.07254,46.49343],"type":"Point"}
}