{
  "type": "Feature",
  "properties": {
    "gn:admin1_code":"07",
    "gn:admin2_code":"37459.0",
    "gn:asciiname":"Vanatori",
    "gn:cc2":"RO",
    "gn:country_code":"RO",
    "gn:dem":122,
    "gn:feature_class":"P",
    "gn:feature_code":"PPL",
    "gn:name":"V\u00e2n\u0103tori",
    "gn:population":573,
    "gn:timezone":"Europe/Bucharest",
    "iso:country":"RO",
    "name:und_x_variant":[
        "V\u00e2n\u0103tori",
        "V\u00een\u0103tori"
    ],
    "wof:name":"Vanatori",
    "wof:placetype":"locality",
    "wof:population":573
},
  "geometry": {"coordinates":[26.86986,47.75151],"type":"Point"}
}