{
  "type": "Feature",
  "properties": {
    "gn:admin1_code":"26",
    "gn:admin2_code":"112879.0",
    "gn:asciiname":"Viasu",
    "gn:cc2":"RO",
    "gn:country_code":"RO",
    "gn:dem":94,
    "gn:feature_class":"P",
    "gn:feature_code":"PPL",
    "gn:name":"Via\u0219u",
    "gn:population":673,
    "gn:timezone":"Europe/Bucharest",
    "iso:country":"RO",
    "name:und_x_variant":[
        "Sm\u00e2rdo\u015fte\u0163ul",
        "Via\u015fu"
    ],
    "wof:name":"Viasu",
    "wof:placetype":"locality",
    "wof:population":673
},
  "geometry": {"coordinates":[22.82566,44.35417],"type":"Point"}
}