{
  "type": "Feature",
  "properties": {
    "gn:admin1_code":"19",
    "gn:admin2_code":"79406.0",
    "gn:asciiname":"Motorgi",
    "gn:country_code":"RO",
    "gn:dem":375,
    "gn:feature_class":"P",
    "gn:feature_code":"PPL",
    "gn:name":"Motorgi",
    "gn:population":112,
    "gn:timezone":"Europe/Bucharest",
    "iso:country":"RO",
    "wof:name":"Motorgi",
    "wof:placetype":"locality",
    "wof:population":112
},
  "geometry": {"coordinates":[23.68391,44.97773],"type":"Point"}
}