{
  "type": "Feature",
  "properties": {
    "gn:admin1_code":"25",
    "gn:admin2_code":"109425.0",
    "gn:asciiname":"Dealu Corbului",
    "gn:country_code":"RO",
    "gn:dem":535,
    "gn:feature_class":"P",
    "gn:feature_code":"PPL",
    "gn:name":"Dealu Corbului",
    "gn:population":136,
    "gn:timezone":"Europe/Bucharest",
    "iso:country":"RO",
    "wof:name":"Dealu Corbului",
    "wof:placetype":"locality",
    "wof:population":136
},
  "geometry": {"coordinates":[23.68523,47.44966],"type":"Point"}
}