{
  "type": "Feature",
  "properties": {
    "gn:admin1_code":"11",
    "gn:admin2_code":"46019.0",
    "gn:asciiname":"Lipieni",
    "gn:country_code":"RO",
    "gn:dem":168,
    "gn:feature_class":"P",
    "gn:feature_code":"PPL",
    "gn:name":"Lipieni",
    "gn:population":0,
    "gn:timezone":"Europe/Bucharest",
    "iso:country":"RO",
    "wof:lang_x_official":[
        "ron"
    ],
    "wof:lang_x_spoken":[
        "ron"
    ],
    "wof:name":"Lipieni",
    "wof:placetype":"locality"
},
  "geometry": {"coordinates":[26.75,45.26667],"type":"Point"}
}