{
  "type": "Feature",
  "properties": {
    "gn:admin1_code":"35",
    "gn:admin2_code":"154852.0",
    "gn:asciiname":"Dulceanca",
    "gn:country_code":"RO",
    "gn:dem":82,
    "gn:feature_class":"P",
    "gn:feature_code":"PPL",
    "gn:name":"Dulceanca",
    "gn:population":710,
    "gn:timezone":"Europe/Bucharest",
    "iso:country":"RO",
    "wof:name":"Dulceanca",
    "wof:placetype":"locality",
    "wof:population":710
},
  "geometry": {"coordinates":[25.10771,44.08995],"type":"Point"}
}