{
  "type": "Feature",
  "properties": {
    "gn:gn_country":"RO",
    "gn:gn_fcode":"PPLA2",
    "gn:gn_pop":3375,
    "gn:population":3375,
    "iso:country":"RO",
    "name:eng_x_preferred":[
        "Lunca de Sus"
    ],
    "name:epo_x_preferred":[
        "Lunca de Sus"
    ],
    "name:fra_x_preferred":[
        "Lunca de Sus"
    ],
    "name:hun_x_preferred":[
        "Gyimesfels\u0151lok"
    ],
    "name:ita_x_preferred":[
        "Lunca de Sus"
    ],
    "name:msa_x_preferred":[
        "Lunca de Sus"
    ],
    "name:nld_x_preferred":[
        "Lunca de Sus"
    ],
    "name:por_x_preferred":[
        "Lunca de Sus"
    ],
    "name:ron_x_preferred":[
        "Lunca de Sus"
    ],
    "name:ukr_x_preferred":[
        "\u041b\u0443\u043d\u043a\u0430-\u0434\u0435-\u0421\u0443\u0441"
    ],
    "name:vie_x_preferred":[
        "Lunca de Sus"
    ],
    "name:vol_x_preferred":[
        "Lunca de Sus"
    ],
    "qs_pg:aaroncc":"RO",
    "qs_pg:gn_country":"RO",
    "qs_pg:gn_fcode":"PPLA2",
    "qs_pg:gn_pop":3375,
    "qs_pg:name":"Lunca de Sus",
    "qs_pg:name_adm0":"Rom\u00e2nia",
    "qs_pg:name_adm1":"Harghita",
    "qs_pg:photos_9k":1,
    "qs_pg:photos_9r":1,
    "qs_pg:photos_all":8,
    "qs_pg:photos_sr":0,
    "qs_pg:pop_sr":4,
    "qs_pg:qs_pg_placetype":"locality",
    "qs_pg:qs_pg_placetype_gp":"Town",
    "qs_pg:woe_adm0":23424933,
    "woe:adm0_id":23424933,
    "woe:name_adm0":"Rom\u00e2nia",
    "woe:name_adm1":"Harghita",
    "woe:placetype":"Town",
    "wof:name":"Lunca de Sus",
    "wof:placetype":"locality",
    "wof:population":3375
},
  "geometry": {"coordinates":[25.96667,46.53333],"type":"Point"}
}