{
  "type": "Feature",
  "properties": {
    "gn:admin1_code":"21",
    "gn:admin2_code":"91054.0",
    "gn:asciiname":"Paucinesti",
    "gn:country_code":"RO",
    "gn:dem":560,
    "gn:feature_class":"P",
    "gn:feature_code":"PPL",
    "gn:name":"P\u0103ucine\u0219ti",
    "gn:population":241,
    "gn:timezone":"Europe/Bucharest",
    "iso:country":"RO",
    "wof:name":"Paucinesti",
    "wof:placetype":"locality",
    "wof:population":241
},
  "geometry": {"coordinates":[22.75485,45.50638],"type":"Point"}
}