{
  "type": "Feature",
  "properties": {
    "gn:admin1_code":"17",
    "gn:admin2_code":"70879",
    "gn:asciiname":"Bechet Nou",
    "gn:country_code":"RO",
    "gn:dem":29,
    "gn:feature_class":"P",
    "gn:feature_code":"PPL",
    "gn:name":"Bechet Nou",
    "gn:population":0,
    "gn:timezone":"Europe/Bucharest",
    "iso:country":"RO",
    "name:und_x_variant":[
        "Portu Bechet",
        "Bechetu Nou",
        "Portul Bechet",
        "Port of Bechet",
        "Bechet Nou"
    ],
    "wof:name":"Bechet Nou",
    "wof:placetype":"locality"
},
  "geometry": {"coordinates":[23.95,43.75],"type":"Point"}
}