{
  "type": "Feature",
  "properties": {
    "gn:admin1_code":"23",
    "gn:admin2_code":"98435.0",
    "gn:asciiname":"Harpasesti",
    "gn:country_code":"RO",
    "gn:dem":118,
    "gn:feature_class":"P",
    "gn:feature_code":"PPL",
    "gn:name":"H\u0103rp\u0103\u0219e\u0219ti",
    "gn:population":739,
    "gn:timezone":"Europe/Bucharest",
    "iso:country":"RO",
    "wof:name":"Harpasesti",
    "wof:placetype":"locality",
    "wof:population":739
},
  "geometry": {"coordinates":[27.28244,47.1502],"type":"Point"}
}