{
  "type": "Feature",
  "properties": {
    "gn:admin1_code":"29",
    "gn:admin2_code":"128711.0",
    "gn:asciiname":"Suica",
    "gn:cc2":"RO",
    "gn:country_code":"RO",
    "gn:dem":253,
    "gn:feature_class":"P",
    "gn:feature_code":"PPL",
    "gn:name":"\u0218uica",
    "gn:population":375,
    "gn:timezone":"Europe/Bucharest",
    "iso:country":"RO",
    "name:dan_x_preferred":[
        "Suica"
    ],
    "name:deu_x_preferred":[
        "Suica"
    ],
    "name:epo_x_preferred":[
        "Suica"
    ],
    "name:fas_x_preferred":[
        "\u0633\u0648\u0626\u06cc\u06a9\u0627"
    ],
    "name:fra_x_preferred":[
        "Suica"
    ],
    "name:hun_x_preferred":[
        "Suica k\u00e1rtya"
    ],
    "name:ita_x_preferred":[
        "Suica"
    ],
    "name:jpn_x_preferred":[
        "Suica"
    ],
    "name:kor_x_preferred":[
        "Suica"
    ],
    "name:por_x_preferred":[
        "Suica"
    ],
    "name:rus_x_preferred":[
        "Suica"
    ],
    "name:und_x_variant":[
        "\u015euica de Jos",
        "\u015euica"
    ],
    "name:zho_x_preferred":[
        "Suica"
    ],
    "wof:name":"Suica",
    "wof:placetype":"locality",
    "wof:population":375
},
  "geometry": {"coordinates":[24.56936,44.6187],"type":"Point"}
}