{
  "type": "Feature",
  "properties": {
    "gn:admin1_code":"29",
    "gn:admin2_code":"128711.0",
    "gn:asciiname":"Suica",
    "gn:cc2":"RO",
    "gn:country_code":"RO",
    "gn:dem":253,
    "gn:feature_class":"P",
    "gn:feature_code":"PPL",
    "gn:name":"\u0218uica",
    "gn:population":375,
    "gn:timezone":"Europe/Bucharest",
    "iso:country":"RO",
    "name:und_x_variant":[
        "\u015euica de Jos",
        "\u015euica"
    ],
    "wof:name":"Suica",
    "wof:placetype":"locality",
    "wof:population":375
},
  "geometry": {"coordinates":[24.56936,44.6187],"type":"Point"}
}