{
  "type": "Feature",
  "properties": {
    "gn:admin1_code":"05",
    "gn:admin2_code":"30336.0",
    "gn:asciiname":"Cociuba Mica",
    "gn:country_code":"RO",
    "gn:dem":299,
    "gn:feature_class":"P",
    "gn:feature_code":"PPL",
    "gn:name":"Cociuba Mic\u0103",
    "gn:population":449,
    "gn:timezone":"Europe/Bucharest",
    "iso:country":"RO",
    "name:ron_x_preferred":[
        "Cociuba Mic\u0103"
    ],
    "name:und_x_variant":[
        "Cociuba de Sus",
        "Fels\u0151kocsoba",
        "Kocsuba"
    ],
    "wof:name":"Cociuba Mica",
    "wof:placetype":"locality",
    "wof:population":449
},
  "geometry": {"coordinates":[22.5345,46.59838],"type":"Point"}
}