{
  "type": "Feature",
  "properties": {
    "gn:admin1_code":"19",
    "gn:admin2_code":"81497.0",
    "gn:asciiname":"Rosia de Jos",
    "gn:country_code":"RO",
    "gn:dem":398,
    "gn:feature_class":"P",
    "gn:feature_code":"PPL",
    "gn:name":"Ro\u015fia de Jos",
    "gn:population":0,
    "gn:timezone":"Europe/Bucharest",
    "iso:country":"RO",
    "name:und_x_variant":[
        "Ro\u015fia de Amaradia de Jos",
        "Rothberg",
        "Ro\u015fia de-Amaradia",
        "Ro\u015fia de Jos"
    ],
    "wof:name":"Rosia de Jos",
    "wof:placetype":"locality"
},
  "geometry": {"coordinates":[23.78333,45.03333],"type":"Point"}
}