{
  "type": "Feature",
  "properties": {
    "gn:admin1_code":"01",
    "gn:admin2_code":"7197.0",
    "gn:asciiname":"Trancesti",
    "gn:country_code":"RO",
    "gn:dem":1051,
    "gn:feature_class":"P",
    "gn:feature_code":"PPL",
    "gn:name":"Tr\u00e2nce\u0219ti",
    "gn:population":16,
    "gn:timezone":"Europe/Bucharest",
    "iso:country":"RO",
    "wof:name":"Trancesti",
    "wof:placetype":"locality",
    "wof:population":16
},
  "geometry": {"coordinates":[22.8593,46.47586],"type":"Point"}
}