{
  "type": "Feature",
  "properties": {
    "gn:admin1_code":"21",
    "gn:admin2_code":"90725",
    "gn:asciiname":"Boita",
    "gn:country_code":"RO",
    "gn:dem":453,
    "gn:feature_class":"P",
    "gn:feature_code":"PPL",
    "gn:name":"Boi\u021ba",
    "gn:population":328,
    "gn:timezone":"Europe/Bucharest",
    "iso:country":"RO",
    "name:fra_x_preferred":[
        "Boita"
    ],
    "name:ori_x_preferred":[
        "\u0b2c\u0b4b\u0b07\u0b24"
    ],
    "name:tam_x_preferred":[
        "\u0baa\u0bcb\u0baf\u0bcd\u0ba4\u0bcd\u0ba4\u0bbe"
    ],
    "wof:name":"Boita",
    "wof:placetype":"locality",
    "wof:population":328
},
  "geometry": {"coordinates":[22.82049,45.60973],"type":"Point"}
}