{
  "type": "Feature",
  "properties": {
    "gn:admin1_code":"21",
    "gn:admin2_code":"90725",
    "gn:asciiname":"Boita",
    "gn:country_code":"RO",
    "gn:dem":453,
    "gn:feature_class":"P",
    "gn:feature_code":"PPL",
    "gn:name":"Boi\u021ba",
    "gn:population":328,
    "gn:timezone":"Europe/Bucharest",
    "iso:country":"RO",
    "wof:name":"Boita",
    "wof:placetype":"locality",
    "wof:population":328
},
  "geometry": {"coordinates":[22.82049,45.60973],"type":"Point"}
}