{
  "type": "Feature",
  "properties": {
    "gn:admin1_code":"39",
    "gn:admin2_code":"173374",
    "gn:asciiname":"Bulagei",
    "gn:country_code":"RO",
    "gn:dem":442,
    "gn:feature_class":"P",
    "gn:feature_code":"PPL",
    "gn:name":"Bulagei",
    "gn:population":260,
    "gn:timezone":"Europe/Bucharest",
    "iso:country":"RO",
    "wof:name":"Bulagei",
    "wof:placetype":"locality",
    "wof:population":260
},
  "geometry": {"coordinates":[24.3755,44.91977],"type":"Point"}
}