{
  "type": "Feature",
  "properties": {
    "gn:admin1_code":"22",
    "gn:admin2_code":"179784.0",
    "gn:asciiname":"Speteni",
    "gn:country_code":"RO",
    "gn:dem":60,
    "gn:feature_class":"P",
    "gn:feature_code":"PPL",
    "gn:name":"Speteni",
    "gn:population":0,
    "gn:timezone":"Europe/Bucharest",
    "iso:country":"RO",
    "wof:lang_x_official":[
        "ron"
    ],
    "wof:lang_x_spoken":[
        "ron"
    ],
    "wof:name":"Speteni",
    "wof:placetype":"locality"
},
  "geometry": {"coordinates":[26.61667,44.65],"type":"Point"}
}