{
  "type": "Feature",
  "properties": {
    "gn:country":"RO",
    "gn:fcode":"PPLA2",
    "gn:population":1629,
    "iso:country":"RO",
    "name:ara_x_preferred":[
        "\u0647\u0627\u0644\u0645\u0627\u062c\u064a\u0644"
    ],
    "name:ceb_x_preferred":[
        "H\u0103lm\u0103gel"
    ],
    "name:deu_x_preferred":[
        "H\u0103lm\u0103gel"
    ],
    "name:eng_x_preferred":[
        "H\u0103lm\u0103gel"
    ],
    "name:epo_x_preferred":[
        "H\u0103lm\u0103gel"
    ],
    "name:fra_x_preferred":[
        "H\u0103lm\u0103gel"
    ],
    "name:hun_x_preferred":[
        "Kishalm\u00e1gy"
    ],
    "name:ita_x_preferred":[
        "H\u0103lm\u0103gel"
    ],
    "name:mkd_x_preferred":[
        "\u0425\u0430\u043b\u043c\u0430\u0433\u0435\u043b"
    ],
    "name:msa_x_preferred":[
        "H\u0103lm\u0103gel"
    ],
    "name:nld_x_preferred":[
        "H\u0103lm\u0103gel"
    ],
    "name:por_x_preferred":[
        "H\u0103lm\u0103gel"
    ],
    "name:ron_x_preferred":[
        "H\u0103lm\u0103gel"
    ],
    "name:sqi_x_preferred":[
        "H\u0103lm\u0103gel"
    ],
    "name:srp_x_preferred":[
        "\u0425\u0430\u043b\u043c\u0430\u0452\u0435\u043b"
    ],
    "name:ukr_x_preferred":[
        "\u0425\u0435\u043b\u043c\u0435\u0434\u0436\u0435\u043b"
    ],
    "name:und_x_variant":[
        "Halm\u00e1gy"
    ],
    "name:vie_x_preferred":[
        "Halmagel"
    ],
    "name:vol_x_preferred":[
        "H\u0103lm\u0103gel"
    ],
    "name:zho_x_preferred":[
        "\u80e1\u65af\u5c3c\u55ac\u963f\u62c9\u9109"
    ],
    "qs_pg:aaroncc":"RO",
    "qs_pg:gn_country":"RO",
    "qs_pg:gn_fcode":"PPLA2",
    "qs_pg:gn_pop":1629,
    "qs_pg:name":"H\u0103lm\u0103gel",
    "qs_pg:name_adm0":"Rom\u00e2nia",
    "qs_pg:name_adm1":"Arad",
    "qs_pg:photos_9r":0,
    "qs_pg:photos_sr":0,
    "qs_pg:pop_sr":3,
    "qs_pg:qs_pg_placetype":"locality",
    "qs_pg:qs_pg_placetype_gp":"Town",
    "qs_pg:woe_adm0":23424933,
    "woe:adm0_id":23424933,
    "woe:name_adm0":"Rom\u00e2nia",
    "woe:name_adm1":"Arad",
    "woe:placetype":"Town",
    "wof:name":"H\u0103lm\u0103gel",
    "wof:placetype":"locality",
    "wof:population":1629
},
  "geometry": {"coordinates":[22.61667,46.26667],"type":"Point"}
}