{
  "type": "Feature",
  "properties": {
    "gn:admin1_code":"27",
    "gn:admin2_code":"117177.0",
    "gn:asciiname":"Mura Mica",
    "gn:cc2":"RO",
    "gn:country_code":"RO",
    "gn:dem":425,
    "gn:feature_class":"P",
    "gn:feature_code":"PPL",
    "gn:name":"Mura Mic\u0103",
    "gn:population":58,
    "gn:timezone":"Europe/Bucharest",
    "iso:country":"RO",
    "name:und_x_variant":[
        "Kisszederjes",
        "Mura Mic\u0103"
    ],
    "wof:name":"Mura Mica",
    "wof:placetype":"locality",
    "wof:population":58
},
  "geometry": {"coordinates":[24.76524,46.64909],"type":"Point"}
}