{
  "type": "Feature",
  "properties": {
    "gn:country":"RO",
    "gn:fcode":"PPLA2",
    "gn:population":2230,
    "iso:country":"RO",
    "name:ara_x_preferred":[
        "\u0643\u0648\u062a\u0645\u064a\u0627\u0646\u0627"
    ],
    "name:ceb_x_preferred":[
        "Comuna Cotmeana"
    ],
    "name:ita_x_preferred":[
        "Cotmeana"
    ],
    "name:mkd_x_preferred":[
        "\u041a\u043e\u0442\u043c\u0430\u043d\u0430"
    ],
    "name:msa_x_preferred":[
        "Cotmeana"
    ],
    "name:nld_x_preferred":[
        "Cotmeana"
    ],
    "name:por_x_preferred":[
        "Cotmeana"
    ],
    "name:ron_x_preferred":[
        "Comuna Cotmeana"
    ],
    "name:sqi_x_preferred":[
        "Cotmeana"
    ],
    "name:srp_x_preferred":[
        "\u041e\u043f\u0448\u0442\u0438\u043d\u0430 \u041a\u043e\u0442\u043c\u0435\u0430\u043d\u0430"
    ],
    "name:ukr_x_preferred":[
        "\u041a\u043e\u0442\u043c\u044f\u043d\u0430"
    ],
    "name:vie_x_preferred":[
        "Cotmeana"
    ],
    "name:vol_x_preferred":[
        "Cotmeana"
    ],
    "name:zho_x_preferred":[
        "\u79d1\u7279\u6885\u4e9e\u7d0d\u9109"
    ],
    "qs_pg:aaroncc":"RO",
    "qs_pg:gn_country":"RO",
    "qs_pg:gn_fcode":"PPLA2",
    "qs_pg:gn_pop":2230,
    "qs_pg:name":"Cotmeana",
    "qs_pg:name_adm0":"Rom\u00e2nia",
    "qs_pg:name_adm1":"Arges",
    "qs_pg:photos_9k":1,
    "qs_pg:photos_9r":1,
    "qs_pg:photos_all":1,
    "qs_pg:photos_sr":0,
    "qs_pg:pop_sr":4,
    "qs_pg:qs_pg_placetype":"locality",
    "qs_pg:qs_pg_placetype_gp":"Town",
    "qs_pg:woe_adm0":23424933,
    "woe:adm0_id":23424933,
    "woe:name_adm0":"Rom\u00e2nia",
    "woe:name_adm1":"Arges",
    "woe:placetype":"Town",
    "wof:name":"Cotmeana",
    "wof:placetype":"locality",
    "wof:population":2230
},
  "geometry": {"coordinates":[24.61667,44.96667],"type":"Point"}
}