{
  "type": "Feature",
  "properties": {
    "gn:admin1_code":"27",
    "gn:admin2_code":"115307.0",
    "gn:asciiname":"Lepindea",
    "gn:country_code":"RO",
    "gn:dem":327,
    "gn:feature_class":"P",
    "gn:feature_code":"PPL",
    "gn:name":"Lepindea",
    "gn:population":270,
    "gn:timezone":"Europe/Bucharest",
    "iso:country":"RO",
    "wof:name":"Lepindea",
    "wof:placetype":"locality",
    "wof:population":270
},
  "geometry": {"coordinates":[24.47546,46.32889],"type":"Point"}
}