{
  "type": "Feature",
  "properties": {
    "gn:admin1_code":"05",
    "gn:admin2_code":"29243.0",
    "gn:asciiname":"Pantasesti",
    "gn:country_code":"RO",
    "gn:dem":210,
    "gn:feature_class":"P",
    "gn:feature_code":"PPL",
    "gn:name":"P\u0103nt\u0103\u0219e\u0219ti",
    "gn:population":186,
    "gn:timezone":"Europe/Bucharest",
    "iso:country":"RO",
    "name:ron_x_preferred":[
        "P\u0103nt\u0103\u0219e\u0219ti"
    ],
    "name:und_x_variant":[
        "Paganest",
        "Pantasesd-Cziganyesd",
        "Cziganyesd",
        "Pantasesd",
        "Cig\u00e1nyosd"
    ],
    "wof:name":"Pantasesti",
    "wof:placetype":"locality",
    "wof:population":186
},
  "geometry": {"coordinates":[22.40462,46.6174],"type":"Point"}
}