{
  "type": "Feature",
  "properties": {
    "gn:admin1_code":"32",
    "gn:admin2_code":"137229.0",
    "gn:asciiname":"Lechinta",
    "gn:country_code":"RO",
    "gn:dem":267,
    "gn:feature_class":"P",
    "gn:feature_code":"PPL",
    "gn:name":"Lechin\u021ba",
    "gn:population":954,
    "gn:timezone":"Europe/Bucharest",
    "iso:country":"RO",
    "wof:name":"Lechinta",
    "wof:placetype":"locality",
    "wof:population":954
},
  "geometry": {"coordinates":[23.29823,47.92313],"type":"Point"}
}