{
  "type": "Feature",
  "properties": {
    "gn:admin1_code":"12",
    "gn:admin2_code":"54109.0",
    "gn:asciiname":"Zlatita",
    "gn:cc2":"RO",
    "gn:country_code":"RO",
    "gn:dem":94,
    "gn:feature_class":"P",
    "gn:feature_code":"PPL",
    "gn:name":"Zlati\u021ba",
    "gn:population":768,
    "gn:timezone":"Europe/Bucharest",
    "iso:country":"RO",
    "name:und_x_variant":[
        "Zlatica",
        "Zlati\u0163a"
    ],
    "wof:name":"Zlatita",
    "wof:placetype":"locality",
    "wof:population":768
},
  "geometry": {"coordinates":[21.46917,44.86495],"type":"Point"}
}