{
  "type": "Feature",
  "properties": {
    "gn:admin1_code":"17",
    "gn:admin2_code":"71199.0",
    "gn:asciiname":"Georocu Mare",
    "gn:cc2":"RO",
    "gn:country_code":"RO",
    "gn:dem":85,
    "gn:feature_class":"P",
    "gn:feature_code":"PPL",
    "gn:name":"Georocu Mare",
    "gn:population":661,
    "gn:timezone":"Europe/Bucharest",
    "iso:country":"RO",
    "name:und_x_variant":[
        "Giorocul Mare",
        "Georocu Mare"
    ],
    "wof:name":"Georocu Mare",
    "wof:placetype":"locality",
    "wof:population":661
},
  "geometry": {"coordinates":[23.95097,44.12109],"type":"Point"}
}