{
  "type": "Feature",
  "properties": {
    "gn:admin1_code":"01",
    "gn:admin2_code":"7099.0",
    "gn:asciiname":"Rachita",
    "gn:country_code":"RO",
    "gn:dem":440,
    "gn:feature_class":"P",
    "gn:feature_code":"PPL",
    "gn:name":"R\u0103chita",
    "gn:population":737,
    "gn:timezone":"Europe/Bucharest",
    "iso:country":"RO",
    "wof:name":"Rachita",
    "wof:placetype":"locality",
    "wof:population":737
},
  "geometry": {"coordinates":[23.51707,45.87533],"type":"Point"}
}