{
  "type": "Feature",
  "properties": {
    "gn:admin1_code":"01",
    "gn:admin2_code":"6119.0",
    "gn:asciiname":"Vidolm",
    "gn:country_code":"RO",
    "gn:dem":427,
    "gn:feature_class":"P",
    "gn:feature_code":"PPL",
    "gn:name":"Vidolm",
    "gn:population":161,
    "gn:timezone":"Europe/Bucharest",
    "iso:country":"RO",
    "wof:name":"Vidolm",
    "wof:placetype":"locality",
    "wof:population":161
},
  "geometry": {"coordinates":[23.51515,46.48104],"type":"Point"}
}