{
  "type": "Feature",
  "properties": {
    "gn:admin1_code":"13",
    "gn:admin2_code":"58721",
    "gn:asciiname":"Badeni",
    "gn:cc2":"RO",
    "gn:country_code":"RO",
    "gn:dem":403,
    "gn:feature_class":"P",
    "gn:feature_code":"PPL",
    "gn:name":"B\u0103deni",
    "gn:population":755,
    "gn:timezone":"Europe/Bucharest",
    "iso:country":"RO",
    "name:deu_x_preferred":[
        "Badeni"
    ],
    "name:rus_x_preferred":[
        "\u0411\u0430\u0434\u0435\u043d\u0438"
    ],
    "name:ukr_x_preferred":[
        "\u0411\u0430\u0434\u0435\u043d\u0456"
    ],
    "name:und_x_variant":[
        "Bagiu",
        "B\u0103deni"
    ],
    "wof:name":"Badeni",
    "wof:placetype":"locality",
    "wof:population":755
},
  "geometry": {"coordinates":[23.73619,46.48868],"type":"Point"}
}