{
  "type": "Feature",
  "properties": {
    "gn:admin1_code":"11",
    "gn:admin2_code":"46484.0",
    "gn:asciiname":"Gomoesti",
    "gn:country_code":"RO",
    "gn:dem":80,
    "gn:feature_class":"P",
    "gn:feature_code":"PPL",
    "gn:name":"Gomoe\u0219ti",
    "gn:population":302,
    "gn:timezone":"Europe/Bucharest",
    "iso:country":"RO",
    "wof:name":"Gomoesti",
    "wof:placetype":"locality",
    "wof:population":302
},
  "geometry": {"coordinates":[26.80052,45.06653],"type":"Point"}
}