{
  "type": "Feature",
  "properties": {
    "gn:admin1_code":"01",
    "gn:admin2_code":"4008.0",
    "gn:asciiname":"Ghedulesti",
    "gn:country_code":"RO",
    "gn:dem":801,
    "gn:feature_class":"P",
    "gn:feature_code":"PPL",
    "gn:name":"Ghedule\u0219ti",
    "gn:population":100,
    "gn:timezone":"Europe/Bucharest",
    "iso:country":"RO",
    "wof:name":"Ghedulesti",
    "wof:placetype":"locality",
    "wof:population":100
},
  "geometry": {"coordinates":[23.07023,46.23545],"type":"Point"}
}