{
  "type": "Feature",
  "properties": {
    "gn:admin1_code":"20",
    "gn:admin2_code":"86222.0",
    "gn:asciiname":"Iasu",
    "gn:cc2":"RO",
    "gn:country_code":"RO",
    "gn:dem":605,
    "gn:feature_class":"P",
    "gn:feature_code":"PPL",
    "gn:name":"Ia\u0219u",
    "gn:population":53,
    "gn:timezone":"Europe/Bucharest",
    "iso:country":"RO",
    "name:und_x_variant":[
        "J\u00e0sfalva",
        "Ia\u015fu"
    ],
    "wof:name":"Iasu",
    "wof:placetype":"locality",
    "wof:population":53
},
  "geometry": {"coordinates":[25.25803,46.20955],"type":"Point"}
}