{
  "type": "Feature",
  "properties": {
    "gn:country":"RO",
    "gn:fcode":"PPLX",
    "gn:population":2532,
    "iso:country":"RO",
    "qs_pg:aaroncc":"RO",
    "qs_pg:gn_country":"RO",
    "qs_pg:gn_fcode":"PPLX",
    "qs_pg:gn_pop":2532,
    "qs_pg:name":"Bat\u00e2r\u0103\u015fti",
    "qs_pg:photos_9r":0,
    "qs_pg:photos_sr":0,
    "qs_pg:pop_sr":4,
    "qs_pg:qs_pg_placetype":"neighbourhood",
    "wof:name":"Bat\u00e2r\u0103\u015fti",
    "wof:placetype":"neighbourhood",
    "wof:population":2532
},
  "geometry": {"coordinates":[24.15,44.81667],"type":"Point"}
}