{
  "type": "Feature",
  "properties": {
    "gn:admin1_code":"32",
    "gn:admin2_code":"139143",
    "gn:asciiname":"Aliceni",
    "gn:country_code":"RO",
    "gn:dem":193,
    "gn:feature_class":"P",
    "gn:feature_code":"PPL",
    "gn:name":"Aliceni",
    "gn:population":439,
    "gn:timezone":"Europe/Bucharest",
    "iso:country":"RO",
    "wof:name":"Aliceni",
    "wof:placetype":"locality",
    "wof:population":439
},
  "geometry": {"coordinates":[23.30659,47.96459],"type":"Point"}
}