{
  "type": "Feature",
  "properties": {
    "gn:admin1_code":"32",
    "gn:admin2_code":"139143",
    "gn:asciiname":"Aliceni",
    "gn:country_code":"RO",
    "gn:dem":193,
    "gn:feature_class":"P",
    "gn:feature_code":"PPL",
    "gn:name":"Aliceni",
    "gn:population":439,
    "gn:timezone":"Europe/Bucharest",
    "iso:country":"RO",
    "name:ceb_x_preferred":[
        "Aliceni"
    ],
    "name:deu_x_preferred":[
        "Aliceni"
    ],
    "name:hun_x_preferred":[
        "Aliceni"
    ],
    "name:ron_x_preferred":[
        "Aliceni"
    ],
    "name:srp_x_preferred":[
        "\u0410\u043b\u0438\u0447\u0435\u043d\u0438"
    ],
    "wof:name":"Aliceni",
    "wof:placetype":"locality",
    "wof:population":439
},
  "geometry": {"coordinates":[23.30659,47.96459],"type":"Point"}
}