{
  "type": "Feature",
  "properties": {
    "gn:admin1_code":"16",
    "gn:admin2_code":"68128.0",
    "gn:asciiname":"Chirca",
    "gn:country_code":"RO",
    "gn:dem":174,
    "gn:feature_class":"P",
    "gn:feature_code":"PPL",
    "gn:name":"Chirca",
    "gn:population":171,
    "gn:timezone":"Europe/Bucharest",
    "iso:country":"RO",
    "wof:name":"Chirca",
    "wof:placetype":"locality",
    "wof:population":171
},
  "geometry": {"coordinates":[25.385,44.6841],"type":"Point"}
}