{
  "type": "Feature",
  "properties": {
    "gn:admin1_code":"27",
    "gn:admin2_code":"115959.0",
    "gn:asciiname":"Porumbeni",
    "gn:cc2":"RO",
    "gn:country_code":"RO",
    "gn:dem":363,
    "gn:feature_class":"P",
    "gn:feature_code":"PPL",
    "gn:name":"Porumbeni",
    "gn:population":0,
    "gn:timezone":"Europe/Bucharest",
    "iso:country":"RO",
    "name:und_x_variant":[
        "Galamb\u00f2d"
    ],
    "wof:name":"Porumbeni",
    "wof:placetype":"locality"
},
  "geometry": {"coordinates":[24.54517,46.63523],"type":"Point"}
}