{
  "type": "Feature",
  "properties": {
    "gn:admin1_code":"38",
    "gn:admin2_code":"167222.0",
    "gn:asciiname":"Ibanesti",
    "gn:country_code":"RO",
    "gn:dem":141,
    "gn:feature_class":"P",
    "gn:feature_code":"PPLA2",
    "gn:name":"Ib\u0103ne\u0219ti",
    "gn:population":720,
    "gn:timezone":"Europe/Bucharest",
    "iso:country":"RO",
    "name:ceb_x_preferred":[
        "Comuna Ib\u0103ne\u0219ti"
    ],
    "name:fra_x_preferred":[
        "Ib\u0103ne\u0219ti"
    ],
    "name:ita_x_preferred":[
        "Ib\u0103ne\u0219ti"
    ],
    "name:msa_x_preferred":[
        "Ib\u0103ne\u0219ti"
    ],
    "name:nld_x_preferred":[
        "Ib\u0103ne\u0219ti"
    ],
    "name:por_x_preferred":[
        "Ib\u0103ne\u0219ti"
    ],
    "name:ron_x_preferred":[
        "Comuna Ib\u0103ne\u0219ti"
    ],
    "name:srp_x_preferred":[
        "\u041e\u043f\u0448\u0442\u0438\u043d\u0430 \u0418\u0431\u0430\u043d\u0435\u0448\u0442\u0438"
    ],
    "name:ukr_x_preferred":[
        "\u0406\u0431\u0435\u043d\u0435\u0448\u0442\u044c"
    ],
    "name:und_x_variant":[
        "Ib\u0103ne\u015fti"
    ],
    "name:zho_x_preferred":[
        "\u4f0a\u4f2f\u5167\u4ec0\u8482\u9109"
    ],
    "wof:name":"Ibanesti",
    "wof:placetype":"locality",
    "wof:population":720
},
  "geometry": {"coordinates":[27.62548,46.39482],"type":"Point"}
}