{
  "type": "Feature",
  "properties": {
    "gn:admin1_code":"38",
    "gn:admin2_code":"167222.0",
    "gn:asciiname":"Ibanesti",
    "gn:country_code":"RO",
    "gn:dem":141,
    "gn:feature_class":"P",
    "gn:feature_code":"PPLA2",
    "gn:name":"Ib\u0103ne\u0219ti",
    "gn:population":720,
    "gn:timezone":"Europe/Bucharest",
    "iso:country":"RO",
    "name:und_x_variant":[
        "Ib\u0103ne\u015fti"
    ],
    "wof:name":"Ibanesti",
    "wof:placetype":"locality",
    "wof:population":720
},
  "geometry": {"coordinates":[27.62548,46.39482],"type":"Point"}
}