{
  "type": "Feature",
  "properties": {
    "gn:admin1_code":"17",
    "gn:admin2_code":"71787.0",
    "gn:asciiname":"Fantanita",
    "gn:country_code":"RO",
    "gn:dem":83,
    "gn:feature_class":"P",
    "gn:feature_code":"PPL",
    "gn:name":"F\u00e2nt\u00e2ni\u0163a",
    "gn:population":0,
    "gn:timezone":"Europe/Bucharest",
    "iso:country":"RO",
    "wof:lang_x_official":[
        "ron"
    ],
    "wof:lang_x_spoken":[
        "ron"
    ],
    "wof:name":"Fantanita",
    "wof:placetype":"locality"
},
  "geometry": {"coordinates":[23.05,44.11667],"type":"Point"}
}