{
  "type": "Feature",
  "properties": {
    "gn:admin1_code":"27",
    "gn:admin2_code":"117550.0",
    "gn:asciiname":"Ibanesti-Padure",
    "gn:cc2":"RO",
    "gn:country_code":"RO",
    "gn:dem":583,
    "gn:feature_class":"P",
    "gn:feature_code":"PPLA2",
    "gn:name":"Ib\u0103ne\u0219ti-P\u0103dure",
    "gn:population":492,
    "gn:timezone":"Europe/Bucharest",
    "iso:country":"RO",
    "name:und_x_variant":[
        "Erd\u0151lib\u00e0nfalva",
        "De Ib\u0103ne\u015fti",
        "Ib\u0103ne\u015fti P\u0103dure"
    ],
    "wof:name":"Ibanesti-Padure",
    "wof:placetype":"locality",
    "wof:population":492
},
  "geometry": {"coordinates":[24.98676,46.75893],"type":"Point"}
}