{
  "type": "Feature",
  "properties": {
    "gn:admin1_code":"01",
    "gn:admin2_code":"7446.0",
    "gn:asciiname":"Peles",
    "gn:cc2":"RO",
    "gn:country_code":"RO",
    "gn:dem":888,
    "gn:feature_class":"P",
    "gn:feature_code":"PPL",
    "gn:name":"Pele\u0219",
    "gn:population":74,
    "gn:timezone":"Europe/Bucharest",
    "iso:country":"RO",
    "name:und_x_variant":[
        "Sohodol-Pele\u015f",
        "Pele\u015f"
    ],
    "wof:name":"Peles",
    "wof:placetype":"locality",
    "wof:population":74
},
  "geometry": {"coordinates":[22.98326,46.33629000000001],"type":"Point"}
}