{
  "type": "Feature",
  "properties": {
    "gn:admin1_code":"04",
    "gn:admin2_code":"20563.0",
    "gn:asciiname":"Slobozia",
    "gn:cc2":"RO",
    "gn:country_code":"RO",
    "gn:dem":198,
    "gn:feature_class":"P",
    "gn:feature_code":"PPL",
    "gn:name":"Slobozia",
    "gn:population":788,
    "gn:timezone":"Europe/Bucharest",
    "iso:country":"RO",
    "name:rus_x_preferred":[
        "\u0421\u043b\u043e\u0431\u043e\u0437\u0438\u044f"
    ],
    "name:und_x_variant":[
        "Slobozia-Melului",
        "Slobozia Mielului",
        "Slobozia"
    ],
    "wof:name":"Slobozia",
    "wof:placetype":"locality",
    "wof:population":788
},
  "geometry": {"coordinates":[26.78863,46.27794],"type":"Point"}
}