{
  "type": "Feature",
  "properties": {
    "gn:admin1_code":"29",
    "gn:admin2_code":"130357",
    "gn:asciiname":"Bobu",
    "gn:cc2":"RO",
    "gn:country_code":"RO",
    "gn:dem":93,
    "gn:feature_class":"P",
    "gn:feature_code":"PPL",
    "gn:name":"Bobu",
    "gn:population":246,
    "gn:timezone":"Europe/Bucharest",
    "iso:country":"RO",
    "name:ceb_x_preferred":[
        "Bobu"
    ],
    "name:deu_x_preferred":[
        "Bobu"
    ],
    "name:ron_x_preferred":[
        "Bobu"
    ],
    "name:srp_x_preferred":[
        "\u0411\u043e\u0431\u0443"
    ],
    "name:swe_x_preferred":[
        "Bobu"
    ],
    "name:und_x_variant":[
        "Bobul"
    ],
    "wof:name":"Bobu",
    "wof:placetype":"locality",
    "wof:population":246
},
  "geometry": {"coordinates":[24.31078,44.23161],"type":"Point"}
}