{
  "type": "Feature",
  "properties": {
    "gn:admin1_code":"06",
    "gn:admin2_code":"35269.0",
    "gn:asciiname":"Hasmasu Ciceului",
    "gn:cc2":"RO",
    "gn:country_code":"RO",
    "gn:dem":400,
    "gn:feature_class":"P",
    "gn:feature_code":"PPL",
    "gn:name":"H\u0103\u0219ma\u0219u Ciceului",
    "gn:population":330,
    "gn:timezone":"Europe/Bucharest",
    "iso:country":"RO",
    "name:und_x_variant":[
        "H\u0103sma\u015ful Ciceului",
        "H\u0103\u015fma\u015fu Ciceului"
    ],
    "wof:name":"Hasmasu Ciceului",
    "wof:placetype":"locality",
    "wof:population":330
},
  "geometry": {"coordinates":[24.06067,47.23177],"type":"Point"}
}