{
  "type": "Feature",
  "properties": {
    "gn:admin1_code":"20",
    "gn:admin2_code":"83785.0",
    "gn:asciiname":"Valea Mare",
    "gn:country_code":"RO",
    "gn:dem":389,
    "gn:feature_class":"P",
    "gn:feature_code":"PPL",
    "gn:name":"Valea Mare",
    "gn:population":0,
    "gn:timezone":"Europe/Bucharest",
    "iso:country":"RO",
    "name:ceb_x_preferred":[
        "Valea Mare"
    ],
    "name:deu_x_preferred":[
        "Valea Mare"
    ],
    "name:epo_x_preferred":[
        "Valea Mare"
    ],
    "name:fra_x_preferred":[
        "Valea Mare"
    ],
    "name:hun_x_preferred":[
        "Valea Mare"
    ],
    "name:ita_x_preferred":[
        "Valea Mare"
    ],
    "name:nld_x_preferred":[
        "Valea Mare"
    ],
    "name:ron_x_preferred":[
        "Valea Mare"
    ],
    "name:srp_x_preferred":[
        "\u0412\u0430\u0459\u0430 \u041c\u0430\u0440\u0435"
    ],
    "name:und_x_variant":[
        "Nagyv\u00f6lgy",
        "Valea Mare"
    ],
    "name:vol_x_preferred":[
        "Valea Mare"
    ],
    "wof:name":"Valea Mare",
    "wof:placetype":"locality"
},
  "geometry": {"coordinates":[24.96667,46.41667],"type":"Point"}
}