{
  "type": "Feature",
  "properties": {
    "gn:admin1_code":"28",
    "gn:admin2_code":"121108.0",
    "gn:asciiname":"Sacalusesti",
    "gn:country_code":"RO",
    "gn:dem":392,
    "gn:feature_class":"P",
    "gn:feature_code":"PPL",
    "gn:name":"S\u0103c\u0103lu\u0219e\u0219ti",
    "gn:population":623,
    "gn:timezone":"Europe/Bucharest",
    "iso:country":"RO",
    "wof:name":"Sacalusesti",
    "wof:placetype":"locality",
    "wof:population":623
},
  "geometry": {"coordinates":[26.34026,47.17014],"type":"Point"}
}