{
  "type": "Feature",
  "properties": {
    "gn:admin1_code":"32",
    "gn:admin2_code":"136642",
    "gn:asciiname":"Blaja",
    "gn:country_code":"RO",
    "gn:dem":140,
    "gn:feature_class":"P",
    "gn:feature_code":"PPL",
    "gn:name":"Blaja",
    "gn:population":264,
    "gn:timezone":"Europe/Bucharest",
    "iso:country":"RO",
    "wof:name":"Blaja",
    "wof:placetype":"locality",
    "wof:population":264
},
  "geometry": {"coordinates":[22.55511,47.45892],"type":"Point"}
}