{
  "type": "Feature",
  "properties": {
    "gn:admin1_code":"13",
    "gn:admin2_code":"58204.0",
    "gn:asciiname":"Nearsova",
    "gn:country_code":"RO",
    "gn:dem":596,
    "gn:feature_class":"P",
    "gn:feature_code":"PPL",
    "gn:name":"Near\u0219ova",
    "gn:population":204,
    "gn:timezone":"Europe/Bucharest",
    "iso:country":"RO",
    "wof:name":"Nearsova",
    "wof:placetype":"locality",
    "wof:population":204
},
  "geometry": {"coordinates":[23.06606,46.83761],"type":"Point"}
}