{
  "type": "Feature",
  "properties": {
    "gn:admin1_code":"38",
    "gn:admin2_code":"163324.0",
    "gn:asciiname":"Moreni",
    "gn:country_code":"RO",
    "gn:dem":181,
    "gn:feature_class":"P",
    "gn:feature_code":"PPL",
    "gn:name":"Moreni",
    "gn:population":35,
    "gn:timezone":"Europe/Bucharest",
    "iso:country":"RO",
    "wof:name":"Moreni",
    "wof:placetype":"locality",
    "wof:population":35
},
  "geometry": {"coordinates":[27.74164,46.51312],"type":"Point"}
}