{
  "type": "Feature",
  "properties": {
    "gn:admin1_code":"19",
    "gn:admin2_code":"82733.0",
    "gn:asciiname":"Fantanele",
    "gn:cc2":"RO",
    "gn:country_code":"RO",
    "gn:dem":144,
    "gn:feature_class":"P",
    "gn:feature_code":"PPL",
    "gn:name":"F\u00e2nt\u00e2nele",
    "gn:population":931,
    "gn:timezone":"Europe/Bucharest",
    "iso:country":"RO",
    "name:und_x_variant":[
        "Stejaru",
        "Stejarul",
        "F\u00eent\u00eenele"
    ],
    "wof:name":"Fantanele",
    "wof:placetype":"locality",
    "wof:population":931
},
  "geometry": {"coordinates":[23.31097,44.77807],"type":"Point"}
}