{
  "type": "Feature",
  "properties": {
    "gn:gn_country":"RO",
    "gn:gn_fcode":"PPLA2",
    "gn:gn_pop":2669,
    "gn:population":2669,
    "iso:country":"RO",
    "name:bul_x_preferred":[
        "\u0412\u0443\u043b\u043f\u0435\u043d\u0438"
    ],
    "name:dut_x_preferred":[
        "Vulpeni"
    ],
    "name:eng_x_preferred":[
        "Vulpeni"
    ],
    "name:fre_x_preferred":[
        "Vulpeni"
    ],
    "name:ita_x_preferred":[
        "Vulpeni"
    ],
    "name:rum_x_preferred":[
        "Vulpeni"
    ],
    "name:ukr_x_preferred":[
        "\u0412\u0443\u043b\u043f\u0435\u043d\u044c"
    ],
    "qs_pg:aaroncc":"RO",
    "qs_pg:gn_country":"RO",
    "qs_pg:gn_fcode":"PPLA2",
    "qs_pg:gn_pop":2669,
    "qs_pg:name":"Vulpeni",
    "qs_pg:name_adm0":"Rom\u00e2nia",
    "qs_pg:name_adm1":"Olt",
    "qs_pg:photos_9r":0,
    "qs_pg:photos_sr":0,
    "qs_pg:pop_sr":4,
    "qs_pg:qs_pg_placetype":"locality",
    "qs_pg:qs_pg_placetype_gp":"Town",
    "qs_pg:woe_adm0":23424933,
    "woe:adm0_id":23424933,
    "woe:name_adm0":"Rom\u00e2nia",
    "woe:name_adm1":"Olt",
    "woe:placetype":"Town",
    "wof:name":"Vulpeni",
    "wof:placetype":"locality",
    "wof:population":2669
},
  "geometry": {"coordinates":[23.91667,44.46667],"type":"Point"}
}