{
  "type": "Feature",
  "properties": {
    "gn:admin1_code":"13",
    "gn:admin2_code":"56568",
    "gn:asciiname":"Agarbiciu",
    "gn:cc2":"RO",
    "gn:country_code":"RO",
    "gn:dem":544,
    "gn:feature_class":"P",
    "gn:feature_code":"PPL",
    "gn:name":"Ag\u00e2rbiciu",
    "gn:population":564,
    "gn:timezone":"Europe/Bucharest",
    "iso:country":"RO",
    "name:und_x_variant":[
        "Ag\u00e2rbiciul",
        "Ag\u00e2rbiciu",
        "Ag\u00eerbiciu"
    ],
    "wof:name":"Agarbiciu",
    "wof:placetype":"locality",
    "wof:population":564
},
  "geometry": {"coordinates":[23.27887,46.77021],"type":"Point"}
}