{
  "type": "Feature",
  "properties": {
    "iso:country":"RO",
    "name:rus_x_preferred":[
        "Grivi\u021ba"
    ],
    "wof:name":"Grivita",
    "wof:placetype":"neighbourhood"
},
  "geometry": {"coordinates":[26.06433788222687,44.46191775776335],"type":"Point"}
}