{
  "type": "Feature",
  "properties": {
    "iso:country":"RO",
    "name:rus_x_preferred":[
        "Grivi\u021ba"
    ],
    "wof:lang_x_official":[
        "ron"
    ],
    "wof:lang_x_spoken":[
        "ron"
    ],
    "wof:name":"Grivita",
    "wof:placetype":"neighbourhood"
},
  "geometry": {"coordinates":[26.064338,44.461918],"type":"Point"}
}