{
  "type": "Feature",
  "properties": {
    "gn:admin1_code":"03",
    "gn:admin2_code":"19141.0",
    "gn:asciiname":"Pauleni",
    "gn:country_code":"RO",
    "gn:dem":522,
    "gn:feature_class":"P",
    "gn:feature_code":"PPL",
    "gn:name":"P\u0103uleni",
    "gn:population":191,
    "gn:timezone":"Europe/Bucharest",
    "iso:country":"RO",
    "wof:name":"Pauleni",
    "wof:placetype":"locality",
    "wof:population":191
},
  "geometry": {"coordinates":[24.52294,45.25715],"type":"Point"}
}