{
  "type": "Feature",
  "properties": {
    "gn:admin1_code":"15",
    "gn:admin2_code":"63447",
    "gn:asciiname":"Bodos",
    "gn:country_code":"RO",
    "gn:dem":525,
    "gn:feature_class":"P",
    "gn:feature_code":"PPL",
    "gn:name":"Bodo\u0219",
    "gn:population":435,
    "gn:timezone":"Europe/Bucharest",
    "iso:country":"RO",
    "wof:name":"Bodos",
    "wof:placetype":"locality",
    "wof:population":435
},
  "geometry": {"coordinates":[25.66313,46.07636],"type":"Point"}
}