{
  "type": "Feature",
  "properties": {
    "gn:admin1_code":"21",
    "gn:admin2_code":"87843.0",
    "gn:asciiname":"Voia",
    "gn:country_code":"RO",
    "gn:dem":394,
    "gn:feature_class":"P",
    "gn:feature_code":"PPL",
    "gn:name":"Voia",
    "gn:population":190,
    "gn:timezone":"Europe/Bucharest",
    "iso:country":"RO",
    "wof:name":"Voia",
    "wof:placetype":"locality",
    "wof:population":190
},
  "geometry": {"coordinates":[23.04634,46.03688],"type":"Point"}
}