{
  "type": "Feature",
  "properties": {
    "gn:population":1327,
    "iso:country":"RO",
    "name:ceb_x_preferred":[
        "Moi\u0219eni"
    ],
    "name:eng_x_preferred":[
        "Moi\u0219eni"
    ],
    "name:epo_x_preferred":[
        "Moi\u0219eni"
    ],
    "name:fra_x_preferred":[
        "Moi\u0219eni"
    ],
    "name:hun_x_preferred":[
        "M\u00f3zesfalu"
    ],
    "name:nld_x_preferred":[
        "Moi\u0219eni"
    ],
    "name:ron_x_preferred":[
        "Moi\u0219eni"
    ],
    "name:srp_x_preferred":[
        "\u041c\u043e\u0438\u0448\u0435\u043d\u0438"
    ],
    "name:ukr_x_preferred":[
        "\u041c\u043e\u0439\u0448\u0435\u043d\u044c"
    ],
    "qs:a0":"Rom\u00e2nia",
    "qs:a1":"*Satu Mare",
    "qs:a1r":"0",
    "qs:adm0":"Rom\u00e2nia",
    "qs:la_lc":"*",
    "qs:level":"locality",
    "qs:loc":"Moi\u015feni",
    "qs:loc_alt":"Moiseni",
    "qs:pop":0,
    "qs:type":"buffered point",
    "wof:name":"Moi\u015feni",
    "wof:placetype":"locality",
    "wof:population":1327
},
  "geometry": {"coordinates":[23.472807,47.924623],"type":"Point"}
}