{
  "type": "Feature",
  "properties": {
    "gn:admin1_code":"11",
    "gn:admin2_code":"47916",
    "gn:asciiname":"Badarlegiu",
    "gn:cc2":"RO",
    "gn:country_code":"RO",
    "gn:dem":589,
    "gn:feature_class":"P",
    "gn:feature_code":"PPL",
    "gn:name":"B\u0103d\u00e2rlegiu",
    "gn:population":0,
    "gn:timezone":"Europe/Bucharest",
    "iso:country":"RO",
    "name:und_x_variant":[
        "B\u0103d\u0103rlegiul",
        "B\u0103d\u00eerlegiu"
    ],
    "wof:name":"Badarlegiu",
    "wof:placetype":"locality"
},
  "geometry": {"coordinates":[26.31667,45.41667],"type":"Point"}
}