{
  "type": "Feature",
  "properties": {
    "gn:admin1_code":"21",
    "gn:admin2_code":"88644.0",
    "gn:asciiname":"Valceluta",
    "gn:country_code":"RO",
    "gn:dem":265,
    "gn:feature_class":"P",
    "gn:feature_code":"PPL",
    "gn:name":"V\u00e2lcelu\u0163a",
    "gn:population":0,
    "gn:timezone":"Europe/Bucharest",
    "iso:country":"RO",
    "wof:name":"Valceluta",
    "wof:placetype":"locality"
},
  "geometry": {"coordinates":[23.01667,45.65],"type":"Point"}
}