{
  "type": "Feature",
  "properties": {
    "gn:admin1_code":"05",
    "gn:admin2_code":"31789.0",
    "gn:asciiname":"Girisu Negru",
    "gn:cc2":"RO",
    "gn:country_code":"RO",
    "gn:dem":112,
    "gn:feature_class":"P",
    "gn:feature_code":"PPL",
    "gn:name":"Giri\u015fu Negru",
    "gn:population":0,
    "gn:timezone":"Europe/Bucharest",
    "iso:country":"RO",
    "name:und_x_variant":[
        "Giri\u015f",
        "Giri\u015ful-Negru",
        "Giri\u015fu Negru"
    ],
    "wof:name":"Girisu Negru",
    "wof:placetype":"locality"
},
  "geometry": {"coordinates":[21.90682,46.72537],"type":"Point"}
}