{
  "type": "Feature",
  "properties": {
    "gn:admin1_code":"05",
    "gn:admin2_code":"27757.0",
    "gn:asciiname":"Cuiesd",
    "gn:cc2":"RO",
    "gn:country_code":"RO",
    "gn:dem":179,
    "gn:feature_class":"P",
    "gn:feature_code":"PPL",
    "gn:name":"Cuie\u0219d",
    "gn:population":507,
    "gn:timezone":"Europe/Bucharest",
    "iso:country":"RO",
    "name:und_x_variant":[
        "Cuejd",
        "Cuie\u015fd"
    ],
    "wof:name":"Cuiesd",
    "wof:placetype":"locality",
    "wof:population":507
},
  "geometry": {"coordinates":[22.29485,47.11143],"type":"Point"}
}