{
  "type": "Feature",
  "properties": {
    "gn:admin1_code":"08",
    "gn:admin2_code":"43493.0",
    "gn:asciiname":"Zatna",
    "gn:country_code":"RO",
    "gn:dem":4,
    "gn:feature_class":"P",
    "gn:feature_code":"PPL",
    "gn:name":"Zatna",
    "gn:population":0,
    "gn:timezone":"Europe/Bucharest",
    "iso:country":"RO",
    "name:und_x_variant":[
        "Sagna",
        "Zagna",
        "Zatna"
    ],
    "wof:lang_x_official":[
        "ron"
    ],
    "wof:lang_x_spoken":[
        "ron"
    ],
    "wof:name":"Zatna",
    "wof:placetype":"locality"
},
  "geometry": {"coordinates":[27.96667,44.85],"type":"Point"}
}