{
  "type": "Feature",
  "properties": {
    "gn:admin1_code":"07",
    "gn:admin2_code":"37100",
    "gn:asciiname":"Bivolari",
    "gn:country_code":"RO",
    "gn:dem":176,
    "gn:feature_class":"P",
    "gn:feature_code":"PPL",
    "gn:name":"Bivolari",
    "gn:population":185,
    "gn:timezone":"Europe/Bucharest",
    "iso:country":"RO",
    "name:ara_x_preferred":[
        "\u0628\u064a\u0641\u0648\u0644\u0627\u0631\u064a"
    ],
    "name:bul_x_preferred":[
        "\u0411\u0438\u0432\u043e\u043b\u0430\u0440\u0435"
    ],
    "name:ceb_x_preferred":[
        "Comuna Bivolari"
    ],
    "name:ita_x_preferred":[
        "Bivolari"
    ],
    "name:msa_x_preferred":[
        "Bivolari"
    ],
    "name:nld_x_preferred":[
        "Bivolari"
    ],
    "name:por_x_preferred":[
        "Bivolari"
    ],
    "name:ron_x_preferred":[
        "Comuna Bivolari"
    ],
    "name:srp_x_preferred":[
        "\u041e\u043f\u0448\u0442\u0438\u043d\u0430 \u0411\u0438\u0432\u043e\u043b\u0430\u0440\u0438"
    ],
    "name:ukr_x_preferred":[
        "\u0411\u0456\u0432\u043e\u043b\u0430\u0440\u0456"
    ],
    "name:vie_x_preferred":[
        "Bivolari"
    ],
    "name:vol_x_preferred":[
        "Bivolari"
    ],
    "name:zho_x_preferred":[
        "\u6bd4\u6c83\u62c9\u91cc\u9109"
    ],
    "wof:name":"Bivolari",
    "wof:placetype":"locality",
    "wof:population":185
},
  "geometry": {"coordinates":[27.05826,47.81446],"type":"Point"}
}