{
  "type": "Feature",
  "properties": {
    "gn:admin1_code":"07",
    "gn:admin2_code":"37100",
    "gn:asciiname":"Bivolari",
    "gn:country_code":"RO",
    "gn:dem":176,
    "gn:feature_class":"P",
    "gn:feature_code":"PPL",
    "gn:name":"Bivolari",
    "gn:population":185,
    "gn:timezone":"Europe/Bucharest",
    "iso:country":"RO",
    "wof:name":"Bivolari",
    "wof:placetype":"locality",
    "wof:population":185
},
  "geometry": {"coordinates":[27.05826,47.81446],"type":"Point"}
}