{
  "type": "Feature",
  "properties": {
    "gn:admin1_code":"02",
    "gn:admin2_code":"10765.0",
    "gn:asciiname":"Ususau",
    "gn:cc2":"RO",
    "gn:country_code":"RO",
    "gn:dem":132,
    "gn:feature_class":"P",
    "gn:feature_code":"PPLA2",
    "gn:name":"Usus\u0103u",
    "gn:population":533,
    "gn:timezone":"Europe/Bucharest",
    "iso:country":"RO",
    "name:ara_x_preferred":[
        "\u0648\u0633\u0648\u0633\u0627\u0648"
    ],
    "name:ceb_x_preferred":[
        "Comuna Usus\u0103u"
    ],
    "name:deu_x_preferred":[
        "Usus\u0103u"
    ],
    "name:epo_x_preferred":[
        "Usus\u0103u"
    ],
    "name:fra_x_preferred":[
        "Usus\u0103u"
    ],
    "name:ita_x_preferred":[
        "Usus\u0103u"
    ],
    "name:msa_x_preferred":[
        "Usus\u0103u"
    ],
    "name:nld_x_preferred":[
        "Usus\u0103u"
    ],
    "name:por_x_preferred":[
        "Usus\u0103u"
    ],
    "name:ron_x_preferred":[
        "Comuna Usus\u0103u"
    ],
    "name:sqi_x_preferred":[
        "Usus\u0103u"
    ],
    "name:srp_x_preferred":[
        "\u041e\u043f\u0448\u0442\u0438\u043d\u0430 \u0423\u0441\u0443\u0441\u0430\u0443"
    ],
    "name:ukr_x_preferred":[
        "\u0423\u0441\u0443\u0441\u0435\u0443"
    ],
    "name:und_x_variant":[
        "Marosasz\u00f3",
        "Hossz\u00faasz\u00f3",
        "Hossz\u00fasz\u00f3",
        "Hoszsz\u00fasz\u00f3",
        "Usus\u0103u"
    ],
    "name:vie_x_preferred":[
        "Dorgos"
    ],
    "name:vol_x_preferred":[
        "Usus\u0103u"
    ],
    "name:zho_x_preferred":[
        "\u70cf\u8607\u745f\u70cf\u9109"
    ],
    "wof:name":"Ususau",
    "wof:placetype":"locality",
    "wof:population":533
},
  "geometry": {"coordinates":[21.81371,46.07063],"type":"Point"}
}