{
  "type": "Feature",
  "properties": {
    "gn:admin1_code":"38",
    "gn:admin2_code":"166182.0",
    "gn:asciiname":"Burghelesti",
    "gn:country_code":"RO",
    "gn:dem":255,
    "gn:feature_class":"P",
    "gn:feature_code":"PPL",
    "gn:name":"Burghele\u015fti",
    "gn:population":0,
    "gn:timezone":"Europe/Bucharest",
    "iso:country":"RO",
    "wof:name":"Burghelesti",
    "wof:placetype":"locality"
},
  "geometry": {"coordinates":[27.81667,46.66667],"type":"Point"}
}