{
  "type": "Feature",
  "properties": {
    "gn:admin1_code":"01",
    "gn:admin2_code":"5700.0",
    "gn:asciiname":"Zaries",
    "gn:country_code":"RO",
    "gn:dem":250,
    "gn:feature_class":"P",
    "gn:feature_code":"PPL",
    "gn:name":"Z\u0103rie\u0219",
    "gn:population":0,
    "gn:timezone":"Europe/Bucharest",
    "iso:country":"RO",
    "wof:name":"Zaries",
    "wof:placetype":"locality"
},
  "geometry": {"coordinates":[23.70711,46.18376],"type":"Point"}
}