{
  "type": "Feature",
  "properties": {
    "gn:admin1_code":"29",
    "gn:admin2_code":"129656.0",
    "gn:asciiname":"Turia",
    "gn:country_code":"RO",
    "gn:dem":197,
    "gn:feature_class":"P",
    "gn:feature_code":"PPL",
    "gn:name":"Turia",
    "gn:population":752,
    "gn:timezone":"Europe/Bucharest",
    "iso:country":"RO",
    "name:ara_x_preferred":[
        "\u062a\u0648\u0631\u064a\u0627"
    ],
    "name:ceb_x_preferred":[
        "Turia"
    ],
    "name:deu_x_preferred":[
        "Turia"
    ],
    "name:epo_x_preferred":[
        "Turia"
    ],
    "name:ita_x_preferred":[
        "Turia"
    ],
    "name:pol_x_preferred":[
        "Turia"
    ],
    "name:ron_x_preferred":[
        "Turia"
    ],
    "name:spa_x_preferred":[
        "Turia"
    ],
    "wof:name":"Turia",
    "wof:placetype":"locality",
    "wof:population":752
},
  "geometry": {"coordinates":[24.47772,44.44671],"type":"Point"}
}