{
  "type": "Feature",
  "properties": {
    "gn:admin1_code":"39",
    "gn:admin2_code":"172992.0",
    "gn:asciiname":"Dealu Bisericii",
    "gn:country_code":"RO",
    "gn:dem":364,
    "gn:feature_class":"P",
    "gn:feature_code":"PPL",
    "gn:name":"Dealu Bisericii",
    "gn:population":352,
    "gn:timezone":"Europe/Bucharest",
    "iso:country":"RO",
    "name:srp_x_preferred":[
        "\u0414\u0435\u0430\u043b\u0443 \u0411\u0438\u0441\u0435\u0440\u0438\u0447\u0438"
    ],
    "wof:name":"Dealu Bisericii",
    "wof:placetype":"locality",
    "wof:population":352
},
  "geometry": {"coordinates":[23.85678,44.92045],"type":"Point"}
}