{
  "type": "Feature",
  "properties": {
    "gn:admin1_code":"06",
    "gn:admin2_code":"34903.0",
    "gn:asciiname":"Sieu-Sfantu",
    "gn:country_code":"RO",
    "gn:dem":280,
    "gn:feature_class":"P",
    "gn:feature_code":"PPL",
    "gn:name":"\u0218ieu-Sf\u00e2ntu",
    "gn:population":430,
    "gn:timezone":"Europe/Bucharest",
    "iso:country":"RO",
    "name:hun_x_preferred":[
        "Saj\u00f3szentandr\u00e1s"
    ],
    "name:und_x_variant":[
        "\u015eieu-Sf\u00eent",
        "\u0218ieu-Sf\u00e2nt",
        "S\u00e2ntu"
    ],
    "wof:name":"Sieu-Sfantu",
    "wof:placetype":"locality",
    "wof:population":430
},
  "geometry": {"coordinates":[24.30574,47.1493],"type":"Point"}
}