{
  "type": "Feature",
  "properties": {
    "gn:admin1_code":"06",
    "gn:admin2_code":"34360.0",
    "gn:asciiname":"Dealul Stefanitei",
    "gn:country_code":"RO",
    "gn:dem":687,
    "gn:feature_class":"P",
    "gn:feature_code":"PPL",
    "gn:name":"Dealul \u0218tef\u0103ni\u021bei",
    "gn:population":435,
    "gn:timezone":"Europe/Bucharest",
    "iso:country":"RO",
    "name:und_x_variant":[
        "Dealu \u0218tef\u0103ni\u021bei"
    ],
    "wof:name":"Dealul Stefanitei",
    "wof:placetype":"locality",
    "wof:population":435
},
  "geometry": {"coordinates":[24.42095,47.57878],"type":"Point"}
}