{
  "type": "Feature",
  "properties": {
    "gn:admin1_code":"21",
    "gn:admin2_code":"86990.0",
    "gn:asciiname":"Livezeni",
    "gn:country_code":"RO",
    "gn:dem":663,
    "gn:feature_class":"P",
    "gn:feature_code":"PPL",
    "gn:name":"Livezeni",
    "gn:population":0,
    "gn:timezone":"Europe/Bucharest",
    "iso:country":"RO",
    "name:und_x_variant":[
        "Liv\u0103zeni",
        "Livezen",
        "Livezeni"
    ],
    "wof:name":"Livezeni",
    "wof:placetype":"locality"
},
  "geometry": {"coordinates":[23.38333,45.38333],"type":"Point"}
}