{
  "type": "Feature",
  "properties": {
    "gn:admin1_code":"21",
    "gn:admin2_code":"86990.0",
    "gn:asciiname":"Livezeni",
    "gn:country_code":"RO",
    "gn:dem":663,
    "gn:feature_class":"P",
    "gn:feature_code":"PPL",
    "gn:name":"Livezeni",
    "gn:population":0,
    "gn:timezone":"Europe/Bucharest",
    "iso:country":"RO",
    "name:ceb_x_preferred":[
        "Comuna Livezeni"
    ],
    "name:deu_x_preferred":[
        "Livezeni"
    ],
    "name:epo_x_preferred":[
        "Livezeni"
    ],
    "name:fra_x_preferred":[
        "Livezeni"
    ],
    "name:ita_x_preferred":[
        "Livezeni"
    ],
    "name:msa_x_preferred":[
        "Livezeni"
    ],
    "name:nld_x_preferred":[
        "Livezeni"
    ],
    "name:por_x_preferred":[
        "Livezeni"
    ],
    "name:ron_x_preferred":[
        "Comuna Livezeni"
    ],
    "name:srp_x_preferred":[
        "\u041e\u043f\u0448\u0442\u0438\u043d\u0430 \u041b\u0438\u0432\u0435\u0437\u0435\u043d\u0438"
    ],
    "name:ukr_x_preferred":[
        "\u041b\u0456\u0432\u0435\u0437\u0435\u043d\u044c"
    ],
    "name:und_x_variant":[
        "Liv\u0103zeni",
        "Livezen"
    ],
    "name:vie_x_preferred":[
        "Livezeni"
    ],
    "name:vol_x_preferred":[
        "Livezeni"
    ],
    "name:zho_x_preferred":[
        "\u5229\u97cb\u6fa4\u5c3c\u9109"
    ],
    "wof:name":"Livezeni",
    "wof:placetype":"locality"
},
  "geometry": {"coordinates":[23.38333,45.38333],"type":"Point"}
}