{
  "type": "Feature",
  "properties": {
    "gn:admin1_code":"01",
    "gn:admin2_code":"8425.0",
    "gn:asciiname":"Danilesti",
    "gn:country_code":"RO",
    "gn:dem":720,
    "gn:feature_class":"P",
    "gn:feature_code":"PPL",
    "gn:name":"D\u0103nile\u015fti",
    "gn:population":0,
    "gn:timezone":"Europe/Bucharest",
    "iso:country":"RO",
    "name:und_x_variant":[
        "D\u0103niele\u015fti",
        "D\u0103nile\u015fti"
    ],
    "wof:name":"Danilesti",
    "wof:placetype":"locality"
},
  "geometry": {"coordinates":[22.91667,46.38333],"type":"Point"}
}