{
  "type": "Feature",
  "properties": {
    "gn:admin1_code":"04",
    "gn:admin2_code":"23047.0",
    "gn:asciiname":"Sarba",
    "gn:country_code":"RO",
    "gn:dem":281,
    "gn:feature_class":"P",
    "gn:feature_code":"PPL",
    "gn:name":"\u015earba",
    "gn:population":0,
    "gn:timezone":"Europe/Bucharest",
    "iso:country":"RO",
    "wof:name":"Sarba",
    "wof:placetype":"locality"
},
  "geometry": {"coordinates":[27.25,46.26667],"type":"Point"}
}