{
  "type": "Feature",
  "properties": {
    "gn:admin1_code":"01",
    "gn:admin2_code":"1348.0",
    "gn:asciiname":"Obarsia Tiurului",
    "gn:cc2":"RO",
    "gn:country_code":"RO",
    "gn:dem":381,
    "gn:feature_class":"P",
    "gn:feature_code":"PPL",
    "gn:name":"Ob\u00e2r\u015fia Tiurului",
    "gn:population":0,
    "gn:timezone":"Europe/Bucharest",
    "iso:country":"RO",
    "name:und_x_variant":[
        "La Ob\u00e2r\u015fe",
        "Ob\u00eer\u015fia Tiurului"
    ],
    "wof:name":"Obarsia Tiurului",
    "wof:placetype":"locality"
},
  "geometry": {"coordinates":[23.88333,46.11667],"type":"Point"}
}