{
  "type": "Feature",
  "properties": {
    "gn:gn_country":"RO",
    "gn:gn_fcode":"PPLA2",
    "gn:gn_pop":2968,
    "gn:population":2968,
    "iso:country":"RO",
    "name:eng_x_preferred":[
        "M\u0103rtini\u0219"
    ],
    "name:epo_x_preferred":[
        "M\u0103rtini\u0219"
    ],
    "name:fra_x_preferred":[
        "M\u0103rtini\u0219"
    ],
    "name:hun_x_preferred":[
        "Homor\u00f3dszentm\u00e1rton"
    ],
    "name:ita_x_preferred":[
        "M\u0103rtini\u0219"
    ],
    "name:msa_x_preferred":[
        "M\u0103rtini\u0219"
    ],
    "name:nld_x_preferred":[
        "M\u0103rtini\u0219"
    ],
    "name:por_x_preferred":[
        "M\u0103rtini\u0219"
    ],
    "name:ron_x_preferred":[
        "M\u0103rtini\u0219"
    ],
    "name:ukr_x_preferred":[
        "\u041c\u0435\u0440\u0442\u0456\u043d\u0456\u0448"
    ],
    "name:unk_x_variant":[
        "Homor\u00f3dszentm\u00e0rton"
    ],
    "name:vie_x_preferred":[
        "Martinis"
    ],
    "name:vol_x_preferred":[
        "M\u0103rtini\u0219"
    ],
    "qs_pg:aaroncc":"RO",
    "qs_pg:gn_country":"RO",
    "qs_pg:gn_fcode":"PPLA2",
    "qs_pg:gn_pop":2968,
    "qs_pg:name":"M\u0103rtini\u015f",
    "qs_pg:photos_9r":0,
    "qs_pg:photos_sr":0,
    "qs_pg:pop_sr":4,
    "qs_pg:qs_pg_placetype":"locality",
    "wof:name":"M\u0103rtini\u015f",
    "wof:placetype":"locality",
    "wof:population":2968
},
  "geometry": {"coordinates":[25.38333,46.23333],"type":"Point"}
}