{
  "type": "Feature",
  "properties": {
    "gn:admin1_code":"38",
    "gn:admin2_code":"163137.0",
    "gn:asciiname":"Chitcani",
    "gn:country_code":"RO",
    "gn:dem":141,
    "gn:feature_class":"P",
    "gn:feature_code":"PPL",
    "gn:name":"Chi\u021bcani",
    "gn:population":339,
    "gn:timezone":"Europe/Bucharest",
    "iso:country":"RO",
    "wof:name":"Chitcani",
    "wof:placetype":"locality",
    "wof:population":339
},
  "geometry": {"coordinates":[27.78188,46.45259],"type":"Point"}
}