{
  "type": "Feature",
  "properties": {
    "gn:admin1_code":"11",
    "gn:admin2_code":"47578.0",
    "gn:asciiname":"Margineanu",
    "gn:cc2":"RO",
    "gn:country_code":"RO",
    "gn:dem":66,
    "gn:feature_class":"P",
    "gn:feature_code":"PPL",
    "gn:name":"M\u0103rgineanu",
    "gn:population":760,
    "gn:timezone":"Europe/Bucharest",
    "iso:country":"RO",
    "name:und_x_variant":[
        "M\u0103rdineanu",
        "M\u0103rgineanu"
    ],
    "wof:name":"Margineanu",
    "wof:placetype":"locality",
    "wof:population":760
},
  "geometry": {"coordinates":[26.6657,44.94007],"type":"Point"}
}