{
  "type": "Feature",
  "properties": {
    "gn:admin1_code":"36",
    "gn:admin2_code":"157585.0",
    "gn:asciiname":"Zorani",
    "gn:country_code":"RO",
    "gn:dem":196,
    "gn:feature_class":"P",
    "gn:feature_code":"PPL",
    "gn:name":"Zorani",
    "gn:population":109,
    "gn:timezone":"Europe/Bucharest",
    "iso:country":"RO",
    "wof:name":"Zorani",
    "wof:placetype":"locality",
    "wof:population":109
},
  "geometry": {"coordinates":[22.27902000000001,45.8722],"type":"Point"}
}