{
  "type": "Feature",
  "properties": {
    "gn:admin1_code":"01",
    "gn:admin2_code":"1936.0",
    "gn:asciiname":"Patrangeni",
    "gn:cc2":"RO",
    "gn:country_code":"RO",
    "gn:dem":380,
    "gn:feature_class":"P",
    "gn:feature_code":"PPL",
    "gn:name":"P\u0103tr\u00e2ngeni",
    "gn:population":0,
    "gn:timezone":"Europe/Bucharest",
    "iso:country":"RO",
    "name:und_x_variant":[
        "P\u0103tr\u00e2ngeni",
        "P\u0103tr\u00eengeni"
    ],
    "wof:name":"Patrangeni",
    "wof:placetype":"locality"
},
  "geometry": {"coordinates":[23.26097,46.08978],"type":"Point"}
}