{
  "type": "Feature",
  "properties": {
    "gn:admin1_code":"13",
    "gn:admin2_code":"58918.0",
    "gn:asciiname":"Petrestii de Sus",
    "gn:cc2":"RO",
    "gn:country_code":"RO",
    "gn:dem":583,
    "gn:feature_class":"P",
    "gn:feature_code":"PPL",
    "gn:name":"Petre\u0219tii de Sus",
    "gn:population":119,
    "gn:timezone":"Europe/Bucharest",
    "iso:country":"RO",
    "name:und_x_variant":[
        "Petridu de Sus",
        "Petre\u015ftii de Sus"
    ],
    "wof:name":"Petrestii de Sus",
    "wof:placetype":"locality",
    "wof:population":119
},
  "geometry": {"coordinates":[23.64681,46.54866],"type":"Point"}
}