{
  "type": "Feature",
  "properties": {
    "gn:admin1_code":"01",
    "gn:admin2_code":"5103.0",
    "gn:asciiname":"Capalna de Jos",
    "gn:cc2":"RO",
    "gn:country_code":"RO",
    "gn:dem":286,
    "gn:feature_class":"P",
    "gn:feature_code":"PPL",
    "gn:name":"C\u0103p\u00e2lna de Jos",
    "gn:population":913,
    "gn:timezone":"Europe/Bucharest",
    "iso:country":"RO",
    "name:und_x_variant":[
        "C\u0103p\u00e2lna de Jos",
        "C\u0103p\u00eelna de Jos"
    ],
    "wof:name":"Capalna de Jos",
    "wof:placetype":"locality",
    "wof:population":913
},
  "geometry": {"coordinates":[24.11304,46.24],"type":"Point"}
}