{
  "type": "Feature",
  "properties": {
    "gn:admin1_code":"12",
    "gn:admin2_code":"53639.0",
    "gn:asciiname":"Valeapai",
    "gn:cc2":"RO",
    "gn:country_code":"RO",
    "gn:dem":144,
    "gn:feature_class":"P",
    "gn:feature_code":"PPL",
    "gn:name":"Valeapai",
    "gn:population":570,
    "gn:timezone":"Europe/Bucharest",
    "iso:country":"RO",
    "name:und_x_variant":[
        "Pog\u00e1nyospatak",
        "Valepaj",
        "Valeap\u00e1j",
        "Valeapai"
    ],
    "wof:name":"Valeapai",
    "wof:placetype":"locality",
    "wof:population":570
},
  "geometry": {"coordinates":[21.72395,45.49175],"type":"Point"}
}