{
  "type": "Feature",
  "properties": {
    "gn:admin1_code":"19",
    "gn:admin2_code":"81415",
    "gn:asciiname":"Bucsana",
    "gn:country_code":"RO",
    "gn:dem":354,
    "gn:feature_class":"P",
    "gn:feature_code":"PPL",
    "gn:name":"Buc\u0219ana",
    "gn:population":891,
    "gn:timezone":"Europe/Bucharest",
    "iso:country":"RO",
    "wof:name":"Bucsana",
    "wof:placetype":"locality",
    "wof:population":891
},
  "geometry": {"coordinates":[23.71455,45.06401],"type":"Point"}
}