{
  "type": "Feature",
  "properties": {
    "gn:admin1_code":"19",
    "gn:admin2_code":"81754.0",
    "gn:asciiname":"Magheresti",
    "gn:cc2":"RO",
    "gn:country_code":"RO",
    "gn:dem":310,
    "gn:feature_class":"P",
    "gn:feature_code":"PPL",
    "gn:name":"Maghere\u0219ti",
    "gn:population":534,
    "gn:timezone":"Europe/Bucharest",
    "iso:country":"RO",
    "name:und_x_variant":[
        "Maghere\u015ftii din Deal",
        "Maghere\u015fti"
    ],
    "wof:name":"Magheresti",
    "wof:placetype":"locality",
    "wof:population":534
},
  "geometry": {"coordinates":[23.52384,45.09404],"type":"Point"}
}