{
  "type": "Feature",
  "properties": {
    "gn:admin1_code":"38",
    "gn:admin2_code":"164277.0",
    "gn:asciiname":"Urlati",
    "gn:country_code":"RO",
    "gn:dem":141,
    "gn:feature_class":"P",
    "gn:feature_code":"PPL",
    "gn:name":"Urla\u021bi",
    "gn:population":297,
    "gn:timezone":"Europe/Bucharest",
    "iso:country":"RO",
    "wof:name":"Urlati",
    "wof:placetype":"locality",
    "wof:population":297
},
  "geometry": {"coordinates":[28.05391,46.56559],"type":"Point"}
}