{
  "type": "Feature",
  "properties": {
    "gn:admin1_code":"01",
    "gn:admin2_code":"2381.0",
    "gn:asciiname":"Stei-Arieseni",
    "gn:country_code":"RO",
    "gn:dem":940,
    "gn:feature_class":"P",
    "gn:feature_code":"PPL",
    "gn:name":"\u0218tei-Arie\u0219eni",
    "gn:population":91,
    "gn:timezone":"Europe/Bucharest",
    "iso:country":"RO",
    "wof:name":"Stei-Arieseni",
    "wof:placetype":"locality",
    "wof:population":91
},
  "geometry": {"coordinates":[22.75404,46.46854],"type":"Point"}
}