{
  "type": "Feature",
  "properties": {
    "gn:admin1_code":"27",
    "gn:admin2_code":"119386.0",
    "gn:asciiname":"Zapodea",
    "gn:country_code":"RO",
    "gn:dem":299,
    "gn:feature_class":"P",
    "gn:feature_code":"PPL",
    "gn:name":"Z\u0103podea",
    "gn:population":172,
    "gn:timezone":"Europe/Bucharest",
    "iso:country":"RO",
    "name:hun_x_preferred":[
        "Zapodia"
    ],
    "wof:name":"Zapodea",
    "wof:placetype":"locality",
    "wof:population":172
},
  "geometry": {"coordinates":[24.13333,46.55],"type":"Point"}
}