{
  "type": "Feature",
  "properties": {
    "gn:admin1_code":"13",
    "gn:admin2_code":"59942.0",
    "gn:asciiname":"Valea Grosilor",
    "gn:country_code":"RO",
    "gn:dem":233,
    "gn:feature_class":"P",
    "gn:feature_code":"PPL",
    "gn:name":"Valea Gro\u0219ilor",
    "gn:population":291,
    "gn:timezone":"Europe/Bucharest",
    "iso:country":"RO",
    "wof:name":"Valea Grosilor",
    "wof:placetype":"locality",
    "wof:population":291
},
  "geometry": {"coordinates":[23.7451,47.23972],"type":"Point"}
}