{
  "type": "Feature",
  "properties": {
    "gn:admin1_code":"21",
    "gn:admin2_code":"92177.0",
    "gn:asciiname":"Poganesti",
    "gn:country_code":"RO",
    "gn:dem":209,
    "gn:feature_class":"P",
    "gn:feature_code":"PPL",
    "gn:name":"Pog\u0103ne\u0219ti",
    "gn:population":108,
    "gn:timezone":"Europe/Bucharest",
    "iso:country":"RO",
    "name:ron_x_preferred":[
        "Pog\u0103ne\u0219ti"
    ],
    "name:und_x_variant":[
        "Poganyesd",
        "Poganesd",
        "Pog\u00e1nyosd",
        "Paganyesd",
        "Heidendorf"
    ],
    "wof:name":"Poganesti",
    "wof:placetype":"locality",
    "wof:population":108
},
  "geometry": {"coordinates":[22.46018,46.0604],"type":"Point"}
}