{
  "type": "Feature",
  "properties": {
    "gn:admin1_code":"05",
    "gn:admin2_code":"30568.0",
    "gn:asciiname":"Varviz",
    "gn:country_code":"RO",
    "gn:dem":178,
    "gn:feature_class":"P",
    "gn:feature_code":"PPL",
    "gn:name":"Varviz",
    "gn:population":656,
    "gn:timezone":"Europe/Bucharest",
    "iso:country":"RO",
    "wof:name":"Varviz",
    "wof:placetype":"locality",
    "wof:population":656
},
  "geometry": {"coordinates":[22.43855,47.22488],"type":"Point"}
}