{
  "type": "Feature",
  "properties": {
    "gn:admin1_code":"40",
    "gn:admin2_code":"175590.0",
    "gn:asciiname":"Spatareasa",
    "gn:cc2":"RO",
    "gn:country_code":"RO",
    "gn:dem":42,
    "gn:feature_class":"P",
    "gn:feature_code":"PPL",
    "gn:name":"Sp\u0103t\u0103reasa",
    "gn:population":303,
    "gn:timezone":"Europe/Bucharest",
    "iso:country":"RO",
    "name:und_x_variant":[
        "Sp\u0103t\u0103resa",
        "Sp\u0103t\u0103reasa"
    ],
    "wof:name":"Spatareasa",
    "wof:placetype":"locality",
    "wof:population":303
},
  "geometry": {"coordinates":[27.29622,45.42679],"type":"Point"}
}