{
  "type": "Feature",
  "properties": {
    "gn:admin1_code":"04",
    "gn:admin2_code":"22166.0",
    "gn:asciiname":"Salatruc",
    "gn:country_code":"RO",
    "gn:dem":416,
    "gn:feature_class":"P",
    "gn:feature_code":"PPL",
    "gn:name":"S\u0103l\u0103truc",
    "gn:population":45,
    "gn:timezone":"Europe/Bucharest",
    "iso:country":"RO",
    "wof:name":"Salatruc",
    "wof:placetype":"locality",
    "wof:population":45
},
  "geometry": {"coordinates":[26.41762,46.34379000000001],"type":"Point"}
}