{
  "type": "Feature",
  "properties": {
    "gn:admin1_code":"23",
    "gn:admin2_code":"96664",
    "gn:asciiname":"Baiceni",
    "gn:country_code":"RO",
    "gn:dem":173,
    "gn:feature_class":"P",
    "gn:feature_code":"PPL",
    "gn:name":"B\u0103iceni",
    "gn:population":300,
    "gn:timezone":"Europe/Bucharest",
    "iso:country":"RO",
    "wof:name":"Baiceni",
    "wof:placetype":"locality",
    "wof:population":300
},
  "geometry": {"coordinates":[26.92643,47.29903],"type":"Point"}
}