{
  "type": "Feature",
  "properties": {
    "gn:admin1_code":"14",
    "gn:admin2_code":"62137.0",
    "gn:asciiname":"Miristea",
    "gn:cc2":"RO",
    "gn:country_code":"RO",
    "gn:dem":66,
    "gn:feature_class":"P",
    "gn:feature_code":"PPL",
    "gn:name":"Miri\u0219tea",
    "gn:population":35,
    "gn:timezone":"Europe/Bucharest",
    "iso:country":"RO",
    "name:und_x_variant":[
        "Edilchioi",
        "Miri\u015ftea"
    ],
    "wof:name":"Miristea",
    "wof:placetype":"locality",
    "wof:population":35
},
  "geometry": {"coordinates":[28.35444,44.00178],"type":"Point"}
}