{
  "type": "Feature",
  "properties": {
    "gn:admin1_code":"13",
    "gn:admin2_code":"59826.0",
    "gn:asciiname":"Santejude",
    "gn:cc2":"RO",
    "gn:country_code":"RO",
    "gn:dem":323,
    "gn:feature_class":"P",
    "gn:feature_code":"PPL",
    "gn:name":"S\u00e2ntejude",
    "gn:population":227,
    "gn:timezone":"Europe/Bucharest",
    "iso:country":"RO",
    "name:und_x_variant":[
        "S\u00e2ntejude",
        "S\u00e2mejude",
        "S\u00eentejude"
    ],
    "wof:name":"Santejude",
    "wof:placetype":"locality",
    "wof:population":227
},
  "geometry": {"coordinates":[23.99053,46.92683],"type":"Point"}
}