{
  "type": "Feature",
  "properties": {
    "gn:admin1_code":"36",
    "gn:admin2_code":"156534.0",
    "gn:asciiname":"Ciresu",
    "gn:cc2":"RO",
    "gn:country_code":"RO",
    "gn:dem":148,
    "gn:feature_class":"P",
    "gn:feature_code":"PPL",
    "gn:name":"Cire\u0219u",
    "gn:population":372,
    "gn:timezone":"Europe/Bucharest",
    "iso:country":"RO",
    "name:und_x_variant":[
        "Cire\u015ful",
        "Cire\u015fu"
    ],
    "wof:name":"Ciresu",
    "wof:placetype":"locality",
    "wof:population":372
},
  "geometry": {"coordinates":[22.0336,45.65074],"type":"Point"}
}