{
  "type": "Feature",
  "properties": {
    "gn:admin1_code":"29",
    "gn:admin2_code":"125873",
    "gn:asciiname":"Belgun",
    "gn:cc2":"RO",
    "gn:country_code":"RO",
    "gn:dem":147,
    "gn:feature_class":"P",
    "gn:feature_code":"PPL",
    "gn:name":"Belgun",
    "gn:population":359,
    "gn:timezone":"Europe/Bucharest",
    "iso:country":"RO",
    "name:ceb_x_preferred":[
        "Belgun"
    ],
    "name:swe_x_preferred":[
        "Belgun"
    ],
    "name:und_x_variant":[
        "Belgunul",
        "Belgun"
    ],
    "wof:name":"Belgun",
    "wof:placetype":"locality",
    "wof:population":359
},
  "geometry": {"coordinates":[24.14947,44.37878],"type":"Point"}
}