{
  "type": "Feature",
  "properties": {
    "gn:admin1_code":"27",
    "gn:admin2_code":"116046.0",
    "gn:asciiname":"Giurgis",
    "gn:country_code":"RO",
    "gn:dem":406,
    "gn:feature_class":"P",
    "gn:feature_code":"PPL",
    "gn:name":"Giurgi\u0219",
    "gn:population":22,
    "gn:timezone":"Europe/Bucharest",
    "iso:country":"RO",
    "wof:name":"Giurgis",
    "wof:placetype":"locality",
    "wof:population":22
},
  "geometry": {"coordinates":[23.96958,46.51706],"type":"Point"}
}