{
  "type": "Feature",
  "properties": {
    "gn:admin1_code":"01",
    "gn:admin2_code":"3039.0",
    "gn:asciiname":"Tomnatec",
    "gn:cc2":"RO",
    "gn:country_code":"RO",
    "gn:dem":1004,
    "gn:feature_class":"P",
    "gn:feature_code":"PPL",
    "gn:name":"Tomnatec",
    "gn:population":20,
    "gn:timezone":"Europe/Bucharest",
    "iso:country":"RO",
    "name:und_x_variant":[
        "Tomnatica",
        "Tomnatec"
    ],
    "wof:name":"Tomnatec",
    "wof:placetype":"locality",
    "wof:population":20
},
  "geometry": {"coordinates":[23.0917,46.43484],"type":"Point"}
}