{
  "type": "Feature",
  "properties": {
    "gn:admin1_code":"14",
    "gn:admin2_code":"63326.0",
    "gn:asciiname":"Gradina",
    "gn:cc2":"RO",
    "gn:country_code":"RO",
    "gn:dem":61,
    "gn:feature_class":"P",
    "gn:feature_code":"PPLA2",
    "gn:name":"Gr\u0103dina",
    "gn:population":854,
    "gn:timezone":"Europe/Bucharest",
    "iso:country":"RO",
    "name:und_x_variant":[
        "Taksoff",
        "Toxof",
        "Gr\u0103dina"
    ],
    "wof:name":"Gradina",
    "wof:placetype":"locality",
    "wof:population":854
},
  "geometry": {"coordinates":[28.43236,44.5552],"type":"Point"}
}