{
  "type": "Feature",
  "properties": {
    "gn:admin1_code":"14",
    "gn:admin2_code":"63326.0",
    "gn:asciiname":"Gradina",
    "gn:cc2":"RO",
    "gn:country_code":"RO",
    "gn:dem":61,
    "gn:feature_class":"P",
    "gn:feature_code":"PPLA2",
    "gn:name":"Gr\u0103dina",
    "gn:population":854,
    "gn:timezone":"Europe/Bucharest",
    "iso:country":"RO",
    "name:ara_x_preferred":[
        "\u063a\u0631\u0627\u062f\u064a\u0646\u0627"
    ],
    "name:bul_x_preferred":[
        "\u0413\u0440\u0435\u0434\u0438\u043d\u0430"
    ],
    "name:ceb_x_preferred":[
        "Comuna Gr\u0103dina"
    ],
    "name:epo_x_preferred":[
        "Gr\u0103dina"
    ],
    "name:ita_x_preferred":[
        "Gr\u0103dina"
    ],
    "name:msa_x_preferred":[
        "Gr\u0103dina"
    ],
    "name:nld_x_preferred":[
        "Gr\u0103dina"
    ],
    "name:por_x_preferred":[
        "Gr\u0103dina"
    ],
    "name:ron_x_preferred":[
        "Comuna Gr\u0103dina"
    ],
    "name:srp_x_preferred":[
        "\u041e\u043f\u0448\u0442\u0438\u043d\u0430 \u0413\u0440\u0430\u0434\u0438\u043d\u0430"
    ],
    "name:ukr_x_preferred":[
        "\u0413\u0440\u0435\u0434\u0456\u043d\u0430"
    ],
    "name:und_x_variant":[
        "Taksoff",
        "Toxof",
        "Gr\u0103dina"
    ],
    "name:vie_x_preferred":[
        "Gr\u0103dina"
    ],
    "name:vol_x_preferred":[
        "Gr\u0103dina"
    ],
    "name:zho_x_preferred":[
        "\u683c\u52d2\u8fea\u7d0d\u9109"
    ],
    "wof:name":"Gradina",
    "wof:placetype":"locality",
    "wof:population":854
},
  "geometry": {"coordinates":[28.43236,44.5552],"type":"Point"}
}