{
  "type": "Feature",
  "properties": {
    "gn:admin1_code":"40",
    "gn:admin2_code":"175439.0",
    "gn:asciiname":"Nemtari",
    "gn:country_code":"RO",
    "gn:dem":287,
    "gn:feature_class":"P",
    "gn:feature_code":"PPL",
    "gn:name":"Nem\u0163ari",
    "gn:population":0,
    "gn:timezone":"Europe/Bucharest",
    "iso:country":"RO",
    "wof:name":"Nemtari",
    "wof:placetype":"locality"
},
  "geometry": {"coordinates":[27.03333,45.53333],"type":"Point"}
}