{
  "type": "Feature",
  "properties": {
    "gn:admin1_code":"07",
    "gn:admin2_code":"37672.0",
    "gn:asciiname":"Hiliseu-Crisan",
    "gn:cc2":"RO",
    "gn:country_code":"RO",
    "gn:dem":195,
    "gn:feature_class":"P",
    "gn:feature_code":"PPL",
    "gn:name":"Hili\u0219eu-Cri\u0219an",
    "gn:population":961,
    "gn:timezone":"Europe/Bucharest",
    "iso:country":"RO",
    "name:und_x_variant":[
        "Hili\u015feu V\u00eernav",
        "Hili\u015feu-V\u00e2rnav",
        "Hiliseul V\u00e2rnav",
        "Hili\u015feu-Cri\u015fan"
    ],
    "wof:name":"Hiliseu-Crisan",
    "wof:placetype":"locality",
    "wof:population":961
},
  "geometry": {"coordinates":[26.23686,48.03606],"type":"Point"}
}