{
  "type": "Feature",
  "properties": {
    "gn:admin1_code":"21",
    "gn:admin2_code":"90805.0",
    "gn:asciiname":"Ribicioara",
    "gn:cc2":"RO",
    "gn:country_code":"RO",
    "gn:dem":306,
    "gn:feature_class":"P",
    "gn:feature_code":"PPL",
    "gn:name":"Ribicioara",
    "gn:population":79,
    "gn:timezone":"Europe/Bucharest",
    "iso:country":"RO",
    "name:und_x_variant":[
        "Ribiciuara",
        "Ribicioara de Jos",
        "Ribicioara"
    ],
    "wof:name":"Ribicioara",
    "wof:placetype":"locality",
    "wof:population":79
},
  "geometry": {"coordinates":[22.77636,46.21073],"type":"Point"}
}