{
  "type": "Feature",
  "properties": {
    "gn:admin1_code":"06",
    "gn:admin2_code":"33122.0",
    "gn:asciiname":"Mires",
    "gn:country_code":"RO",
    "gn:dem":464,
    "gn:feature_class":"P",
    "gn:feature_code":"PPL",
    "gn:name":"Mire\u0219",
    "gn:population":180,
    "gn:timezone":"Europe/Bucharest",
    "iso:country":"RO",
    "wof:name":"Mires",
    "wof:placetype":"locality",
    "wof:population":180
},
  "geometry": {"coordinates":[24.2342,47.26508],"type":"Point"}
}