{
  "type": "Feature",
  "properties": {
    "gn:admin1_code":"15",
    "gn:admin2_code":"64194.0",
    "gn:asciiname":"Cernatu de Sus",
    "gn:country_code":"RO",
    "gn:dem":572,
    "gn:feature_class":"P",
    "gn:feature_code":"PPL",
    "gn:name":"Cernatu de Sus",
    "gn:population":0,
    "gn:timezone":"Europe/Bucharest",
    "iso:country":"RO",
    "name:und_x_variant":[
        "Fels\u00f6csern\u00e0ton",
        "Cernatul-de-Sus",
        "Cernatu de Sus"
    ],
    "wof:name":"Cernatu de Sus",
    "wof:placetype":"locality"
},
  "geometry": {"coordinates":[26.01667,45.96667],"type":"Point"}
}