{
  "type": "Feature",
  "properties": {
    "gn:admin1_code":"32",
    "gn:admin2_code":"139009",
    "gn:asciiname":"Bocicau",
    "gn:country_code":"RO",
    "gn:dem":140,
    "gn:feature_class":"P",
    "gn:feature_code":"PPL",
    "gn:name":"Bocic\u0103u",
    "gn:population":638,
    "gn:timezone":"Europe/Bucharest",
    "iso:country":"RO",
    "wof:name":"Bocicau",
    "wof:placetype":"locality",
    "wof:population":638
},
  "geometry": {"coordinates":[23.15551,48.09696],"type":"Point"}
}