{
  "type": "Feature",
  "properties": {
    "gn:admin1_code":"27",
    "gn:admin2_code":"117319.0",
    "gn:asciiname":"Orsova",
    "gn:cc2":"RO",
    "gn:country_code":"RO",
    "gn:dem":494,
    "gn:feature_class":"P",
    "gn:feature_code":"PPL",
    "gn:name":"Or\u0219ova",
    "gn:population":811,
    "gn:timezone":"Europe/Bucharest",
    "iso:country":"RO",
    "name:und_x_variant":[
        "G\u00f6rg\u00e8nyorsova",
        "Or\u015fova"
    ],
    "wof:name":"Orsova",
    "wof:placetype":"locality",
    "wof:population":811
},
  "geometry": {"coordinates":[24.91371,46.74998],"type":"Point"}
}