{
  "type": "Feature",
  "properties": {
    "gn:admin1_code":"30",
    "gn:admin2_code":"130892.0",
    "gn:asciiname":"Stancesti",
    "gn:cc2":"RO",
    "gn:country_code":"RO",
    "gn:dem":160,
    "gn:feature_class":"P",
    "gn:feature_code":"PPL",
    "gn:name":"St\u0103nce\u0219ti",
    "gn:population":715,
    "gn:timezone":"Europe/Bucharest",
    "iso:country":"RO",
    "name:und_x_variant":[
        "St\u0103nce\u015ftii",
        "St\u0103nce\u015fti"
    ],
    "wof:name":"Stancesti",
    "wof:placetype":"locality",
    "wof:population":715
},
  "geometry": {"coordinates":[25.91576,44.85508],"type":"Point"}
}