{
  "type": "Feature",
  "properties": {
    "gn:admin1_code":"26",
    "gn:admin2_code":"110571.0",
    "gn:asciiname":"Podu Grosului",
    "gn:cc2":"RO",
    "gn:country_code":"RO",
    "gn:dem":203,
    "gn:feature_class":"P",
    "gn:feature_code":"PPL",
    "gn:name":"Podu Grosului",
    "gn:population":299,
    "gn:timezone":"Europe/Bucharest",
    "iso:country":"RO",
    "name:und_x_variant":[
        "Podul-Grosului",
        "Podu Grosului"
    ],
    "wof:name":"Podu Grosului",
    "wof:placetype":"locality",
    "wof:population":299
},
  "geometry": {"coordinates":[23.06582,44.48293],"type":"Point"}
}