{
  "type": "Feature",
  "properties": {
    "iso:country":"RO",
    "name:dut_x_preferred":[
        "Arie\u0219eni"
    ],
    "name:eng_x_preferred":[
        "Arie\u0219eni"
    ],
    "name:fre_x_preferred":[
        "Arie\u0219eni"
    ],
    "name:hun_x_preferred":[
        "Aranyosl\u00e1pos"
    ],
    "name:ita_x_preferred":[
        "Arie\u0219eni"
    ],
    "name:rum_x_preferred":[
        "Arie\u0219eni"
    ],
    "name:ukr_x_preferred":[
        "\u0410\u0440\u0456\u0454\u0448\u0435\u043d\u044c"
    ],
    "qs_pg:aaroncc":"RO",
    "qs_pg:name":"Arie\u0219eni",
    "qs_pg:name_adm0":"Rom\u00e2nia",
    "qs_pg:name_adm1":"Alba",
    "qs_pg:photos":119,
    "qs_pg:photos_1k":24,
    "qs_pg:photos_9k":1,
    "qs_pg:photos_9r":3,
    "qs_pg:photos_all":119,
    "qs_pg:photos_sr":3,
    "qs_pg:pop_sr":0,
    "qs_pg:qs_pg_placetype":"locality",
    "qs_pg:qs_pg_placetype_gp":"Town",
    "qs_pg:woe_adm0":23424933,
    "woe:adm0_id":23424933,
    "woe:name_adm0":"Rom\u00e2nia",
    "woe:name_adm1":"Alba",
    "woe:placetype":"Town",
    "wof:name":"Arie\u0219eni",
    "wof:placetype":"locality"
},
  "geometry": {"coordinates":[22.7667,46.481018],"type":"Point"}
}