{
  "type": "Feature",
  "properties": {
    "gn:population":902,
    "iso:country":"RO",
    "name:hun_x_preferred":[
        "Roska"
    ],
    "qs:a0":"Rom\u00e2nia",
    "qs:a1":"*Cluj",
    "qs:a1r":"0",
    "qs:adm0":"Rom\u00e2nia",
    "qs:la_lc":"*",
    "qs:level":"locality",
    "qs:loc":"Ri\u015fca",
    "qs:loc_alt":"Risca",
    "qs:pop":0,
    "qs:type":"buffered point",
    "wof:name":"Ri\u015fca",
    "wof:placetype":"locality",
    "wof:population":902
},
  "geometry": {"coordinates":[23.104339,46.744335],"type":"Point"}
}