{
  "type": "Feature",
  "properties": {
    "gn:population":902,
    "iso:country":"RO",
    "name:ceb_x_preferred":[
        "Ri\u0219ca"
    ],
    "name:eng_x_preferred":[
        "R\u00e2\u0219ca"
    ],
    "name:epo_x_preferred":[
        "R\u00e2\u0219ca"
    ],
    "name:fra_x_preferred":[
        "R\u00e2\u0219ca"
    ],
    "name:hun_x_preferred":[
        "Roska"
    ],
    "name:ita_x_preferred":[
        "R\u00e2\u0219ca"
    ],
    "name:msa_x_preferred":[
        "R\u00e2\u0219ca"
    ],
    "name:nld_x_preferred":[
        "R\u00e2\u0219ca"
    ],
    "name:por_x_preferred":[
        "R\u00e2\u0219ca"
    ],
    "name:ron_x_preferred":[
        "R\u00e2\u0219ca"
    ],
    "name:srp_x_preferred":[
        "\u0420\u0438\u0448\u043a\u0430"
    ],
    "name:ukr_x_preferred":[
        "\u0420\u0438\u0448\u043a\u0430"
    ],
    "name:vol_x_preferred":[
        "R\u00e2\u0219ca"
    ],
    "qs:a0":"Rom\u00e2nia",
    "qs:a1":"*Cluj",
    "qs:a1r":"0",
    "qs:adm0":"Rom\u00e2nia",
    "qs:la_lc":"*",
    "qs:level":"locality",
    "qs:loc":"Ri\u015fca",
    "qs:loc_alt":"Risca",
    "qs:pop":0,
    "qs:type":"buffered point",
    "wof:name":"Ri\u015fca",
    "wof:placetype":"locality",
    "wof:population":902
},
  "geometry": {"coordinates":[23.104339,46.744335],"type":"Point"}
}