{
  "type": "Feature",
  "properties": {
    "gn:admin1_code":"21",
    "gn:admin2_code":"88868.0",
    "gn:asciiname":"Merisor",
    "gn:cc2":"RO",
    "gn:country_code":"RO",
    "gn:dem":526,
    "gn:feature_class":"P",
    "gn:feature_code":"PPL",
    "gn:name":"Meri\u0219or",
    "gn:population":152,
    "gn:timezone":"Europe/Bucharest",
    "iso:country":"RO",
    "name:und_x_variant":[
        "Dosu",
        "Meri\u015for"
    ],
    "wof:name":"Merisor",
    "wof:placetype":"locality",
    "wof:population":152
},
  "geometry": {"coordinates":[22.93163,46.14161],"type":"Point"}
}