{
  "type": "Feature",
  "properties": {
    "gn:admin1_code":"33",
    "gn:admin2_code":"144731.0",
    "gn:asciiname":"Nou Sasesc",
    "gn:country_code":"RO",
    "gn:dem":442,
    "gn:feature_class":"P",
    "gn:feature_code":"PPL",
    "gn:name":"Nou S\u0103sesc",
    "gn:population":499,
    "gn:timezone":"Europe/Bucharest",
    "iso:country":"RO",
    "wof:name":"Nou Sasesc",
    "wof:placetype":"locality",
    "wof:population":499
},
  "geometry": {"coordinates":[24.60669,46.11072],"type":"Point"}
}