{
  "type": "Feature",
  "properties": {
    "gn:admin1_code":"27",
    "gn:admin2_code":"115307.0",
    "gn:asciiname":"Daia",
    "gn:country_code":"RO",
    "gn:dem":362,
    "gn:feature_class":"P",
    "gn:feature_code":"PPL",
    "gn:name":"Daia",
    "gn:population":261,
    "gn:timezone":"Europe/Bucharest",
    "iso:country":"RO",
    "wof:name":"Daia",
    "wof:placetype":"locality",
    "wof:population":261
},
  "geometry": {"coordinates":[24.46276,46.3056],"type":"Point"}
}