{
  "type": "Feature",
  "properties": {
    "gn:admin1_code":"27",
    "gn:admin2_code":"115307.0",
    "gn:asciiname":"Daia",
    "gn:country_code":"RO",
    "gn:dem":362,
    "gn:feature_class":"P",
    "gn:feature_code":"PPL",
    "gn:name":"Daia",
    "gn:population":261,
    "gn:timezone":"Europe/Bucharest",
    "iso:country":"RO",
    "name:ceb_x_preferred":[
        "Comuna Daia"
    ],
    "name:ita_x_preferred":[
        "Daia"
    ],
    "name:msa_x_preferred":[
        "Daia"
    ],
    "name:nld_x_preferred":[
        "Daia"
    ],
    "name:por_x_preferred":[
        "Daia"
    ],
    "name:ron_x_preferred":[
        "Comuna Daia"
    ],
    "name:srp_x_preferred":[
        "\u041e\u043f\u0448\u0442\u0438\u043d\u0430 \u0414\u0430\u0458\u0430"
    ],
    "name:ukr_x_preferred":[
        "\u0414\u0430\u044f"
    ],
    "name:vie_x_preferred":[
        "Daia"
    ],
    "name:vol_x_preferred":[
        "Daia"
    ],
    "name:zho_x_preferred":[
        "\u9054\u4e9e\u9109"
    ],
    "wof:name":"Daia",
    "wof:placetype":"locality",
    "wof:population":261
},
  "geometry": {"coordinates":[24.46276,46.3056],"type":"Point"}
}