{
  "type": "Feature",
  "properties": {
    "gn:admin1_code":"27",
    "gn:admin2_code":"118691.0",
    "gn:asciiname":"Hartau",
    "gn:cc2":"RO",
    "gn:country_code":"RO",
    "gn:dem":338,
    "gn:feature_class":"P",
    "gn:feature_code":"PPL",
    "gn:name":"H\u0103r\u0163\u0103u",
    "gn:population":0,
    "gn:timezone":"Europe/Bucharest",
    "iso:country":"RO",
    "name:und_x_variant":[
        "Harc\u00f2",
        "H\u0103rt\u0103ul"
    ],
    "wof:name":"Hartau",
    "wof:placetype":"locality"
},
  "geometry": {"coordinates":[24.479,46.5817],"type":"Point"}
}