{
  "type": "Feature",
  "properties": {
    "gn:admin1_code":"03",
    "gn:admin2_code":"14584.0",
    "gn:asciiname":"Glambocelu",
    "gn:cc2":"RO",
    "gn:country_code":"RO",
    "gn:dem":261,
    "gn:feature_class":"P",
    "gn:feature_code":"PPL",
    "gn:name":"Gl\u00e2mbocelu",
    "gn:population":828,
    "gn:timezone":"Europe/Bucharest",
    "iso:country":"RO",
    "name:und_x_variant":[
        "Gl\u00e2mbocel",
        "Gl\u00eembocelu"
    ],
    "wof:name":"Glambocelu",
    "wof:placetype":"locality",
    "wof:population":828
},
  "geometry": {"coordinates":[25.13985,44.83976],"type":"Point"}
}