{
  "type": "Feature",
  "properties": {
    "gn:admin1_code":"27",
    "gn:admin2_code":"119894.0",
    "gn:asciiname":"Cerghizel",
    "gn:country_code":"RO",
    "gn:dem":312,
    "gn:feature_class":"P",
    "gn:feature_code":"PPL",
    "gn:name":"Cerghizel",
    "gn:population":740,
    "gn:timezone":"Europe/Bucharest",
    "iso:country":"RO",
    "wof:name":"Cerghizel",
    "wof:placetype":"locality",
    "wof:population":740
},
  "geometry": {"coordinates":[24.44821,46.44368],"type":"Point"}
}