{
  "type": "Feature",
  "properties": {
    "gn:admin1_code":"01",
    "gn:admin2_code":"3958.0",
    "gn:asciiname":"Santamarie",
    "gn:cc2":"RO",
    "gn:country_code":"RO",
    "gn:dem":283,
    "gn:feature_class":"P",
    "gn:feature_code":"PPL",
    "gn:name":"S\u00e2nt\u0103m\u0103rie",
    "gn:population":348,
    "gn:timezone":"Europe/Bucharest",
    "iso:country":"RO",
    "name:und_x_variant":[
        "S\u00e2ntam\u0103ria",
        "S\u00e2nt\u0103m\u0103rie",
        "S\u00eent\u0103m\u0103rie"
    ],
    "wof:name":"Santamarie",
    "wof:placetype":"locality",
    "wof:population":348
},
  "geometry": {"coordinates":[24.14688,46.24184],"type":"Point"}
}