{
  "type": "Feature",
  "properties": {
    "gn:admin1_code":"23",
    "gn:admin2_code":"95499.0",
    "gn:asciiname":"Prigoreni",
    "gn:cc2":"RO",
    "gn:country_code":"RO",
    "gn:dem":94,
    "gn:feature_class":"P",
    "gn:feature_code":"PPL",
    "gn:name":"Prigoreni",
    "gn:population":657,
    "gn:timezone":"Europe/Bucharest",
    "iso:country":"RO",
    "name:und_x_variant":[
        "Prigorenii Mari",
        "Prigoreni"
    ],
    "wof:name":"Prigoreni",
    "wof:placetype":"locality",
    "wof:population":657
},
  "geometry": {"coordinates":[27.06812,47.20744000000001],"type":"Point"}
}