{
  "type": "Feature",
  "properties": {
    "gn:admin1_code":"03",
    "gn:admin2_code":"19007.0",
    "gn:asciiname":"Cersani",
    "gn:country_code":"RO",
    "gn:dem":265,
    "gn:feature_class":"P",
    "gn:feature_code":"PPL",
    "gn:name":"Cer\u015fani",
    "gn:population":0,
    "gn:timezone":"Europe/Bucharest",
    "iso:country":"RO",
    "wof:name":"Cersani",
    "wof:placetype":"locality"
},
  "geometry": {"coordinates":[24.92352,44.72119],"type":"Point"}
}