{
  "type": "Feature",
  "properties": {
    "gn:admin1_code":"31",
    "gn:admin2_code":"141535.0",
    "gn:asciiname":"Petenia",
    "gn:country_code":"RO",
    "gn:dem":327,
    "gn:feature_class":"P",
    "gn:feature_code":"PPL",
    "gn:name":"Petenia",
    "gn:population":0,
    "gn:timezone":"Europe/Bucharest",
    "iso:country":"RO",
    "wof:name":"Petenia",
    "wof:placetype":"locality"
},
  "geometry": {"coordinates":[22.91667,47.11667],"type":"Point"}
}