{
  "type": "Feature",
  "properties": {
    "gn:admin1_code":"04",
    "gn:admin2_code":"21007.0",
    "gn:asciiname":"Goioasa",
    "gn:country_code":"RO",
    "gn:dem":513,
    "gn:feature_class":"P",
    "gn:feature_code":"PPL",
    "gn:name":"Goioasa",
    "gn:population":940,
    "gn:timezone":"Europe/Bucharest",
    "iso:country":"RO",
    "wof:name":"Goioasa",
    "wof:placetype":"locality",
    "wof:population":940
},
  "geometry": {"coordinates":[26.29806,46.44723],"type":"Point"}
}