{
  "type": "Feature",
  "properties": {
    "gn:admin1_code":"03",
    "gn:admin2_code":"13524.0",
    "gn:asciiname":"Gura Pravat",
    "gn:country_code":"RO",
    "gn:dem":807,
    "gn:feature_class":"P",
    "gn:feature_code":"PPL",
    "gn:name":"Gura Prav\u0103\u021b",
    "gn:population":737,
    "gn:timezone":"Europe/Bucharest",
    "iso:country":"RO",
    "wof:name":"Gura Pravat",
    "wof:placetype":"locality",
    "wof:population":737
},
  "geometry": {"coordinates":[25.12862,45.32468],"type":"Point"}
}