{
  "type": "Feature",
  "properties": {
    "gn:admin1_code":"28",
    "gn:admin2_code":"124563.0",
    "gn:asciiname":"Ticos-Floarea",
    "gn:country_code":"RO",
    "gn:dem":516,
    "gn:feature_class":"P",
    "gn:feature_code":"PPL",
    "gn:name":"Tico\u0219-Floarea",
    "gn:population":373,
    "gn:timezone":"Europe/Bucharest",
    "iso:country":"RO",
    "wof:name":"Ticos-Floarea",
    "wof:placetype":"locality",
    "wof:population":373
},
  "geometry": {"coordinates":[25.99336,46.88106],"type":"Point"}
}