{
  "type": "Feature",
  "properties": {
    "gn:admin1_code":"11",
    "gn:admin2_code":"45245",
    "gn:asciiname":"Baltagari",
    "gn:cc2":"RO",
    "gn:country_code":"RO",
    "gn:dem":719,
    "gn:feature_class":"P",
    "gn:feature_code":"PPL",
    "gn:name":"B\u0103lt\u0103gari",
    "gn:population":267,
    "gn:timezone":"Europe/Bucharest",
    "iso:country":"RO",
    "name:und_x_variant":[
        "B\u0103lt\u0103garii",
        "B\u0103lt\u0103gari"
    ],
    "wof:name":"Baltagari",
    "wof:placetype":"locality",
    "wof:population":267
},
  "geometry": {"coordinates":[26.72593,45.54872],"type":"Point"}
}