{
  "type": "Feature",
  "properties": {
    "gn:admin1_code":"01",
    "gn:admin2_code":"8826.0",
    "gn:asciiname":"Piatra Dubii",
    "gn:country_code":"RO",
    "gn:dem":466,
    "gn:feature_class":"P",
    "gn:feature_code":"PPL",
    "gn:name":"Piatra Dubii",
    "gn:population":0,
    "gn:timezone":"Europe/Bucharest",
    "iso:country":"RO",
    "wof:name":"Piatra Dubii",
    "wof:placetype":"locality"
},
  "geometry": {"coordinates":[23.45,46.03333],"type":"Point"}
}