{
  "type": "Feature",
  "properties": {
    "gn:admin1_code":"07",
    "gn:admin2_code":"37618.0",
    "gn:asciiname":"Slobozia Hanesti",
    "gn:cc2":"RO",
    "gn:country_code":"RO",
    "gn:dem":104,
    "gn:feature_class":"P",
    "gn:feature_code":"PPL",
    "gn:name":"Slobozia H\u0103ne\u0219ti",
    "gn:population":107,
    "gn:timezone":"Europe/Bucharest",
    "iso:country":"RO",
    "name:und_x_variant":[
        "Slobozia",
        "Slobozia-H\u0103ne\u015fti"
    ],
    "wof:name":"Slobozia Hanesti",
    "wof:placetype":"locality",
    "wof:population":107
},
  "geometry": {"coordinates":[26.99548,47.91383],"type":"Point"}
}