{
  "type": "Feature",
  "properties": {
    "gn:admin1_code":"39",
    "gn:admin2_code":"171995",
    "gn:asciiname":"Barcanele",
    "gn:country_code":"RO",
    "gn:dem":392,
    "gn:feature_class":"P",
    "gn:feature_code":"PPL",
    "gn:name":"Barcanele",
    "gn:population":376,
    "gn:timezone":"Europe/Bucharest",
    "iso:country":"RO",
    "wof:name":"Barcanele",
    "wof:placetype":"locality",
    "wof:population":376
},
  "geometry": {"coordinates":[24.13458,45.08627],"type":"Point"}
}