{
  "type": "Feature",
  "properties": {
    "gn:admin1_code":"39",
    "gn:admin2_code":"169681.0",
    "gn:asciiname":"Seciu",
    "gn:cc2":"RO",
    "gn:country_code":"RO",
    "gn:dem":325,
    "gn:feature_class":"P",
    "gn:feature_code":"PPL",
    "gn:name":"Seciu",
    "gn:population":95,
    "gn:timezone":"Europe/Bucharest",
    "iso:country":"RO",
    "name:ceb_x_preferred":[
        "Seciu"
    ],
    "name:deu_x_preferred":[
        "Seciu"
    ],
    "name:ron_x_preferred":[
        "Seciu"
    ],
    "name:srp_x_preferred":[
        "\u0421\u0435\u0447\u0443"
    ],
    "name:und_x_variant":[
        "Secui"
    ],
    "wof:name":"Seciu",
    "wof:placetype":"locality",
    "wof:population":95
},
  "geometry": {"coordinates":[23.97851,44.80635],"type":"Point"}
}