{
  "type": "Feature",
  "properties": {
    "gn:admin1_code":"41",
    "gn:admin2_code":"101458",
    "gn:asciiname":"Buciumeni",
    "gn:country_code":"RO",
    "gn:dem":50,
    "gn:feature_class":"P",
    "gn:feature_code":"PPL",
    "gn:name":"Buciumeni",
    "gn:population":715,
    "gn:timezone":"Europe/Bucharest",
    "iso:country":"RO",
    "name:ceb_x_preferred":[
        "Buciumeni"
    ],
    "name:deu_x_preferred":[
        "Buciumeni"
    ],
    "name:ita_x_preferred":[
        "Buciumeni"
    ],
    "name:ron_x_preferred":[
        "Buciumeni"
    ],
    "name:rus_x_preferred":[
        "\u0411\u0443\u0447\u0443\u043c\u0435\u043d\u044c"
    ],
    "name:srp_x_preferred":[
        "\u0411\u0443\u0447\u0443\u043c\u0435\u043d\u0438"
    ],
    "name:vol_x_preferred":[
        "Buciumeni"
    ],
    "wof:name":"Buciumeni",
    "wof:placetype":"locality",
    "wof:population":715
},
  "geometry": {"coordinates":[26.41636,44.25458],"type":"Point"}
}