{
  "type": "Feature",
  "properties": {
    "gn:admin1_code":"27",
    "gn:admin2_code":"116288.0",
    "gn:asciiname":"Cinta",
    "gn:cc2":"RO",
    "gn:country_code":"RO",
    "gn:dem":308,
    "gn:feature_class":"P",
    "gn:feature_code":"PPL",
    "gn:name":"Cinta",
    "gn:population":386,
    "gn:timezone":"Europe/Bucharest",
    "iso:country":"RO",
    "name:und_x_variant":[
        "Fintah\u00e0za",
        "Cinta Halta",
        "Cinta"
    ],
    "wof:name":"Cinta",
    "wof:placetype":"locality",
    "wof:population":386
},
  "geometry": {"coordinates":[24.55104,46.46022],"type":"Point"}
}