{
  "type": "Feature",
  "properties": {
    "gn:admin1_code":"02",
    "gn:admin2_code":"11236.0",
    "gn:asciiname":"Urvisu de Beliu",
    "gn:country_code":"RO",
    "gn:dem":189,
    "gn:feature_class":"P",
    "gn:feature_code":"PPL",
    "gn:name":"Urvi\u015fu de Beliu",
    "gn:population":0,
    "gn:timezone":"Europe/Bucharest",
    "iso:country":"RO",
    "name:ron_x_preferred":[
        "Urvi\u015fu de Beliu"
    ],
    "name:und_x_variant":[
        "Urvi\u015f-Beliul",
        "Urvi\u015f-Beliu",
        "\u00d6rv\u00e9nyes",
        "B\u00e9l\u00f6rv\u00e9nyes",
        "Urvi\u015f de Beliu"
    ],
    "wof:name":"Urvisu de Beliu",
    "wof:placetype":"locality"
},
  "geometry": {"coordinates":[22.08333,46.51667],"type":"Point"}
}