{
  "type": "Feature",
  "properties": {
    "gn:admin1_code":"42",
    "gn:admin2_code":"103470.0",
    "gn:asciiname":"Zboiu",
    "gn:cc2":"RO",
    "gn:country_code":"RO",
    "gn:dem":64,
    "gn:feature_class":"P",
    "gn:feature_code":"PPL",
    "gn:name":"Zboiu",
    "gn:population":405,
    "gn:timezone":"Europe/Bucharest",
    "iso:country":"RO",
    "name:und_x_variant":[
        "Zboiul",
        "Zboiu"
    ],
    "wof:name":"Zboiu",
    "wof:placetype":"locality",
    "wof:population":405
},
  "geometry": {"coordinates":[26.30929,44.12687],"type":"Point"}
}