{
  "type": "Feature",
  "properties": {
    "gn:admin1_code":"05",
    "gn:admin2_code":"29813.0",
    "gn:asciiname":"Gruilung",
    "gn:country_code":"RO",
    "gn:dem":214,
    "gn:feature_class":"P",
    "gn:feature_code":"PPL",
    "gn:name":"Gruilung",
    "gn:population":166,
    "gn:timezone":"Europe/Bucharest",
    "iso:country":"RO",
    "wof:name":"Gruilung",
    "wof:placetype":"locality",
    "wof:population":166
},
  "geometry": {"coordinates":[22.10038,46.87907],"type":"Point"}
}