{
  "type": "Feature",
  "properties": {
    "gn:admin1_code":"38",
    "gn:admin2_code":"164981.0",
    "gn:asciiname":"Latesti",
    "gn:country_code":"RO",
    "gn:dem":64,
    "gn:feature_class":"P",
    "gn:feature_code":"PPL",
    "gn:name":"L\u0103\u021be\u0219ti",
    "gn:population":394,
    "gn:timezone":"Europe/Bucharest",
    "iso:country":"RO",
    "wof:name":"Latesti",
    "wof:placetype":"locality",
    "wof:population":394
},
  "geometry": {"coordinates":[27.98623,46.18385],"type":"Point"}
}