{
  "type": "Feature",
  "properties": {
    "gn:admin1_code":"39",
    "gn:admin2_code":"174496",
    "gn:asciiname":"Bratovesti",
    "gn:country_code":"RO",
    "gn:dem":433,
    "gn:feature_class":"P",
    "gn:feature_code":"PPL",
    "gn:name":"Bratove\u0219ti",
    "gn:population":239,
    "gn:timezone":"Europe/Bucharest",
    "iso:country":"RO",
    "name:msa_x_preferred":[
        "Bratovoe\u015fti"
    ],
    "name:und_x_variant":[
        "Bratove\u015fti"
    ],
    "name:vie_x_preferred":[
        "Bratovoesti"
    ],
    "wof:name":"Bratovesti",
    "wof:placetype":"locality",
    "wof:population":239
},
  "geometry": {"coordinates":[24.36458,45.41228],"type":"Point"}
}