{
  "type": "Feature",
  "properties": {
    "gn:admin1_code":"38",
    "gn:admin2_code":"164749.0",
    "gn:asciiname":"Condrea",
    "gn:country_code":"RO",
    "gn:dem":19,
    "gn:feature_class":"P",
    "gn:feature_code":"PPL",
    "gn:name":"Condrea",
    "gn:population":70,
    "gn:timezone":"Europe/Bucharest",
    "iso:country":"RO",
    "wof:name":"Condrea",
    "wof:placetype":"locality",
    "wof:population":70
},
  "geometry": {"coordinates":[28.21651,46.54111],"type":"Point"}
}