{
  "type": "Feature",
  "properties": {
    "gn:admin1_code":"07",
    "gn:admin2_code":"36809.0",
    "gn:asciiname":"Cotu Miculinti",
    "gn:cc2":"RO",
    "gn:country_code":"RO",
    "gn:dem":104,
    "gn:feature_class":"P",
    "gn:feature_code":"PPL",
    "gn:name":"Cotu Miculin\u021bi",
    "gn:population":565,
    "gn:timezone":"Europe/Bucharest",
    "iso:country":"RO",
    "name:und_x_variant":[
        "Cotul Miculin\u0163i",
        "Cotu Miculin\u0163i"
    ],
    "wof:name":"Cotu Miculinti",
    "wof:placetype":"locality",
    "wof:population":565
},
  "geometry": {"coordinates":[26.94624,48.18777],"type":"Point"}
}