{
  "type": "Feature",
  "properties": {
    "gn:admin1_code":"37",
    "gn:admin2_code":"159963.0",
    "gn:asciiname":"Corugea",
    "gn:country_code":"RO",
    "gn:dem":210,
    "gn:feature_class":"P",
    "gn:feature_code":"PPL",
    "gn:name":"Corugea",
    "gn:population":500,
    "gn:timezone":"Europe/Bucharest",
    "iso:country":"RO",
    "wof:name":"Corugea",
    "wof:placetype":"locality",
    "wof:population":500
},
  "geometry": {"coordinates":[28.33954,44.73565],"type":"Point"}
}