{
  "type": "Feature",
  "properties": {
    "gn:admin1_code":"39",
    "gn:admin2_code":"174520.0",
    "gn:asciiname":"Mitrofani",
    "gn:cc2":"RO",
    "gn:country_code":"RO",
    "gn:dem":211,
    "gn:feature_class":"P",
    "gn:feature_code":"PPLA2",
    "gn:name":"Mitrofani",
    "gn:population":866,
    "gn:timezone":"Europe/Bucharest",
    "iso:country":"RO",
    "name:und_x_variant":[
        "Milrofa",
        "Mitrofani"
    ],
    "wof:name":"Mitrofani",
    "wof:placetype":"locality",
    "wof:population":866
},
  "geometry": {"coordinates":[24.2091,44.73268],"type":"Point"}
}