{
  "type": "Feature",
  "properties": {
    "gn:admin1_code":"39",
    "gn:admin2_code":"174520.0",
    "gn:asciiname":"Mitrofani",
    "gn:cc2":"RO",
    "gn:country_code":"RO",
    "gn:dem":211,
    "gn:feature_class":"P",
    "gn:feature_code":"PPLA2",
    "gn:name":"Mitrofani",
    "gn:population":866,
    "gn:timezone":"Europe/Bucharest",
    "iso:country":"RO",
    "name:ceb_x_preferred":[
        "Comuna Mitrofani"
    ],
    "name:epo_x_preferred":[
        "Mitrofani"
    ],
    "name:ita_x_preferred":[
        "Mitrofani"
    ],
    "name:msa_x_preferred":[
        "Mitrofani"
    ],
    "name:nld_x_preferred":[
        "Mitrofani"
    ],
    "name:por_x_preferred":[
        "Mitrofani"
    ],
    "name:ron_x_preferred":[
        "Comuna Mitrofani"
    ],
    "name:srp_x_preferred":[
        "\u041e\u043f\u0448\u0442\u0438\u043d\u0430 \u041c\u0438\u0442\u0440\u043e\u0444\u0430\u043d\u0438"
    ],
    "name:ukr_x_preferred":[
        "\u041c\u0456\u0442\u0440\u043e\u0444\u0430\u043d\u044c"
    ],
    "name:und_x_variant":[
        "Milrofa"
    ],
    "name:zho_x_preferred":[
        "\u7c73\u7279\u7f85\u6cd5\u5c3c\u9109"
    ],
    "wof:name":"Mitrofani",
    "wof:placetype":"locality",
    "wof:population":866
},
  "geometry": {"coordinates":[24.2091,44.73268],"type":"Point"}
}