{
  "type": "Feature",
  "properties": {
    "gn:admin1_code":"28",
    "gn:admin2_code":"120824",
    "gn:asciiname":"Dumbrava-Deal",
    "gn:country_code":"RO",
    "gn:dem":309,
    "gn:feature_class":"P",
    "gn:feature_code":"PPL",
    "gn:name":"Dumbrava-Deal",
    "gn:population":412,
    "gn:timezone":"Europe/Bucharest",
    "iso:country":"RO",
    "wof:name":"Dumbrava-Deal",
    "wof:placetype":"locality",
    "wof:population":412
},
  "geometry": {"coordinates":[26.4973,46.87676],"type":"Point"}
}