{
  "type": "Feature",
  "properties": {
    "gn:admin1_code":"38",
    "gn:admin2_code":"165719.0",
    "gn:asciiname":"Sasova",
    "gn:country_code":"RO",
    "gn:dem":165,
    "gn:feature_class":"P",
    "gn:feature_code":"PPL",
    "gn:name":"Sasova",
    "gn:population":264,
    "gn:timezone":"Europe/Bucharest",
    "iso:country":"RO",
    "name:deu_x_preferred":[
        "Sasova"
    ],
    "wof:name":"Sasova",
    "wof:placetype":"locality",
    "wof:population":264
},
  "geometry": {"coordinates":[27.58108,46.88255],"type":"Point"}
}