{
  "type": "Feature",
  "properties": {
    "gn:admin1_code":"18",
    "gn:admin2_code":"76004.0",
    "gn:asciiname":"Maciseni",
    "gn:country_code":"RO",
    "gn:dem":149,
    "gn:feature_class":"P",
    "gn:feature_code":"PPL",
    "gn:name":"M\u0103ci\u0219eni",
    "gn:population":881,
    "gn:timezone":"Europe/Bucharest",
    "iso:country":"RO",
    "wof:name":"Maciseni",
    "wof:placetype":"locality",
    "wof:population":881
},
  "geometry": {"coordinates":[27.75355,45.85583],"type":"Point"}
}