{
  "type": "Feature",
  "properties": {
    "gn:admin1_code":"03",
    "gn:admin2_code":"15983.0",
    "gn:asciiname":"Spiridoni",
    "gn:country_code":"RO",
    "gn:dem":506,
    "gn:feature_class":"P",
    "gn:feature_code":"PPL",
    "gn:name":"Spiridoni",
    "gn:population":133,
    "gn:timezone":"Europe/Bucharest",
    "iso:country":"RO",
    "wof:name":"Spiridoni",
    "wof:placetype":"locality",
    "wof:population":133
},
  "geometry": {"coordinates":[24.58825,44.97761],"type":"Point"}
}