{
  "type": "Feature",
  "properties": {
    "gn:admin1_code":"37",
    "gn:admin2_code":"159847.0",
    "gn:asciiname":"Sarighiol de Deal",
    "gn:cc2":"RO",
    "gn:country_code":"RO",
    "gn:dem":236,
    "gn:feature_class":"P",
    "gn:feature_code":"PPL",
    "gn:name":"Sarighiol de Deal",
    "gn:population":553,
    "gn:timezone":"Europe/Bucharest",
    "iso:country":"RO",
    "name:und_x_variant":[
        "Sarighiol",
        "Sarighiol de Deal"
    ],
    "wof:name":"Sarighiol de Deal",
    "wof:placetype":"locality",
    "wof:population":553
},
  "geometry": {"coordinates":[28.51383,44.6996],"type":"Point"}
}