{
  "type": "Feature",
  "properties": {
    "gn:admin1_code":"12",
    "gn:admin2_code":"53791.0",
    "gn:asciiname":"Potoc",
    "gn:country_code":"RO",
    "gn:dem":243,
    "gn:feature_class":"P",
    "gn:feature_code":"PPL",
    "gn:name":"Potoc",
    "gn:population":350,
    "gn:timezone":"Europe/Bucharest",
    "iso:country":"RO",
    "wof:name":"Potoc",
    "wof:placetype":"locality",
    "wof:population":350
},
  "geometry": {"coordinates":[21.72258,44.92756],"type":"Point"}
}