{
  "type": "Feature",
  "properties": {
    "gn:admin1_code":"18",
    "gn:admin2_code":"77402.0",
    "gn:asciiname":"Tamaseni",
    "gn:country_code":"RO",
    "gn:dem":21,
    "gn:feature_class":"P",
    "gn:feature_code":"PPL",
    "gn:name":"T\u0103m\u0103\u015feni",
    "gn:population":0,
    "gn:timezone":"Europe/Bucharest",
    "iso:country":"RO",
    "name:und_x_variant":[
        "Umbr\u0103re\u015fti-T\u0103m\u0103\u015feni",
        "T\u0103m\u0103\u015feni"
    ],
    "wof:name":"Tamaseni",
    "wof:placetype":"locality"
},
  "geometry": {"coordinates":[27.45,45.71667],"type":"Point"}
}