{
  "type": "Feature",
  "properties": {
    "gn:gn_country":"RO",
    "gn:gn_fcode":"PPLA2",
    "gn:gn_pop":7072,
    "gn:population":1912,
    "iso:country":"RO",
    "name:ara_x_preferred":[
        "\u0645\u064a\u0631\u0633\u0644\u0648\u0641\u064a\u0634\u062a"
    ],
    "name:dut_x_preferred":[
        "Miroslove\u0219ti"
    ],
    "name:eng_x_preferred":[
        "Miroslove\u0219ti"
    ],
    "name:fre_x_preferred":[
        "Miroslove\u0219ti"
    ],
    "name:ita_x_preferred":[
        "Miroslove\u0219ti"
    ],
    "name:may_x_preferred":[
        "Miroslove\u0219ti"
    ],
    "name:por_x_preferred":[
        "Miroslove\u0219ti"
    ],
    "name:rum_x_preferred":[
        "Miroslove\u0219ti"
    ],
    "name:ukr_x_preferred":[
        "\u041c\u0456\u0440\u043e\u0441\u043b\u043e\u0432\u0435\u0448\u0442\u044c"
    ],
    "name:vie_x_preferred":[
        "Miroslovesti"
    ],
    "name:vol_x_preferred":[
        "Miroslove\u0219ti"
    ],
    "qs_pg:aaroncc":"RO",
    "qs_pg:gn_country":"RO",
    "qs_pg:gn_fcode":"PPLA2",
    "qs_pg:gn_pop":7072,
    "qs_pg:name":"Mirosl\u0103ve\u0219ti",
    "qs_pg:name_adm0":"Rom\u00e2nia",
    "qs_pg:name_adm1":"Iasi",
    "qs_pg:photos_9r":0,
    "qs_pg:photos_sr":0,
    "qs_pg:pop_sr":5,
    "qs_pg:qs_pg_placetype":"locality",
    "qs_pg:qs_pg_placetype_gp":"Town",
    "qs_pg:woe_adm0":23424933,
    "woe:adm0_id":23424933,
    "woe:name_adm0":"Rom\u00e2nia",
    "woe:name_adm1":"Iasi",
    "woe:placetype":"Town",
    "wof:name":"Mirosl\u0103ve\u0219ti",
    "wof:placetype":"locality",
    "wof:population":1912
},
  "geometry": {"coordinates":[26.65,47.15],"type":"Point"}
}