{
  "type": "Feature",
  "properties": {
    "gn:admin1_code":"05",
    "gn:admin2_code":"29243.0",
    "gn:asciiname":"Tiganestii de Beius",
    "gn:country_code":"RO",
    "gn:dem":212,
    "gn:feature_class":"P",
    "gn:feature_code":"PPL",
    "gn:name":"\u021aig\u0103ne\u0219tii de Beiu\u0219",
    "gn:population":374,
    "gn:timezone":"Europe/Bucharest",
    "iso:country":"RO",
    "name:ron_x_preferred":[
        "\u021aig\u0103ne\u0219tii de Beiu\u0219"
    ],
    "name:und_x_variant":[
        "Cig\u00e1nyosd",
        "Cziganyesd"
    ],
    "wof:name":"Tiganestii de Beius",
    "wof:placetype":"locality",
    "wof:population":374
},
  "geometry": {"coordinates":[22.41534,46.62929000000001],"type":"Point"}
}