{
  "type": "Feature",
  "properties": {
    "gn:admin1_code":"34",
    "gn:admin2_code":"146432.0",
    "gn:asciiname":"Florinta",
    "gn:country_code":"RO",
    "gn:dem":434,
    "gn:feature_class":"P",
    "gn:feature_code":"PPL",
    "gn:name":"Florinta",
    "gn:population":87,
    "gn:timezone":"Europe/Bucharest",
    "iso:country":"RO",
    "wof:name":"Florinta",
    "wof:placetype":"locality",
    "wof:population":87
},
  "geometry": {"coordinates":[26.12898,47.64601],"type":"Point"}
}