{
  "type": "Feature",
  "properties": {
    "gn:admin1_code":"20",
    "gn:admin2_code":"84923.0",
    "gn:asciiname":"Rares",
    "gn:cc2":"RO",
    "gn:country_code":"RO",
    "gn:dem":484,
    "gn:feature_class":"P",
    "gn:feature_code":"PPL",
    "gn:name":"Rare\u0219",
    "gn:population":174,
    "gn:timezone":"Europe/Bucharest",
    "iso:country":"RO",
    "name:und_x_variant":[
        "Recseny\u00e8d",
        "Rare\u015f"
    ],
    "wof:name":"Rares",
    "wof:placetype":"locality",
    "wof:population":174
},
  "geometry": {"coordinates":[25.3876,46.20759],"type":"Point"}
}