{
  "type": "Feature",
  "properties": {
    "gn:admin1_code":"39",
    "gn:admin2_code":"171469.0",
    "gn:asciiname":"Tepsenari",
    "gn:cc2":"RO",
    "gn:country_code":"RO",
    "gn:dem":306,
    "gn:feature_class":"P",
    "gn:feature_code":"PPL",
    "gn:name":"Tep\u0219enari",
    "gn:population":355,
    "gn:timezone":"Europe/Bucharest",
    "iso:country":"RO",
    "name:und_x_variant":[
        "Tep\u015fenari",
        "Tepe\u015fenari"
    ],
    "wof:name":"Tepsenari",
    "wof:placetype":"locality",
    "wof:population":355
},
  "geometry": {"coordinates":[24.48476,45.02482],"type":"Point"}
}