{
  "type": "Feature",
  "properties": {
    "gn:admin1_code":"08",
    "gn:admin2_code":"43331.0",
    "gn:asciiname":"Gara Ianca",
    "gn:cc2":"RO",
    "gn:country_code":"RO",
    "gn:dem":27,
    "gn:feature_class":"P",
    "gn:feature_code":"PPL",
    "gn:name":"Gara Ianca",
    "gn:population":130,
    "gn:timezone":"Europe/Bucharest",
    "iso:country":"RO",
    "name:und_x_variant":[
        "Ianca",
        "Ianca-Sat",
        "Gara Ianca"
    ],
    "wof:name":"Gara Ianca",
    "wof:placetype":"locality",
    "wof:population":130
},
  "geometry": {"coordinates":[27.52318,45.14066],"type":"Point"}
}