{
  "type": "Feature",
  "properties": {
    "gn:admin1_code":"19",
    "gn:admin2_code":"80123.0",
    "gn:asciiname":"Merfulesti",
    "gn:country_code":"RO",
    "gn:dem":294,
    "gn:feature_class":"P",
    "gn:feature_code":"PPL",
    "gn:name":"Merfule\u0219ti",
    "gn:population":251,
    "gn:timezone":"Europe/Bucharest",
    "iso:country":"RO",
    "wof:name":"Merfulesti",
    "wof:placetype":"locality",
    "wof:population":251
},
  "geometry": {"coordinates":[23.36847,44.95029],"type":"Point"}
}