{
  "type": "Feature",
  "properties": {
    "gn:admin1_code":"07",
    "gn:admin2_code":"39792.0",
    "gn:asciiname":"Miron Costin",
    "gn:country_code":"RO",
    "gn:dem":109,
    "gn:feature_class":"P",
    "gn:feature_code":"PPL",
    "gn:name":"Miron Costin",
    "gn:population":420,
    "gn:timezone":"Europe/Bucharest",
    "iso:country":"RO",
    "name:ces_x_preferred":[
        "Miron Costin"
    ],
    "name:deu_x_preferred":[
        "Miron Costin"
    ],
    "name:fra_x_preferred":[
        "Miron Costin"
    ],
    "name:heb_x_preferred":[
        "\u05de\u05d9\u05e8\u05d5\u05df \u05e7\u05d5\u05e1\u05d8\u05d9\u05df"
    ],
    "name:ind_x_preferred":[
        "Miron Costin"
    ],
    "name:ita_x_preferred":[
        "Miron Costin"
    ],
    "name:pol_x_preferred":[
        "Miron Costin"
    ],
    "name:ron_x_preferred":[
        "Miron Costin"
    ],
    "name:rus_x_preferred":[
        "\u041a\u043e\u0441\u0442\u0438\u043d"
    ],
    "name:spa_x_preferred":[
        "Miron Costin"
    ],
    "name:ukr_x_preferred":[
        "\u041c\u0438\u0440\u043e\u043d \u041a\u043e\u0441\u0442\u0456\u043d"
    ],
    "wof:name":"Miron Costin",
    "wof:placetype":"locality",
    "wof:population":420
},
  "geometry": {"coordinates":[26.95096,47.94037],"type":"Point"}
}