{
  "type": "Feature",
  "properties": {
    "gn:admin1_code":"22",
    "gn:admin2_code":"102749.0",
    "gn:asciiname":"Stroesti",
    "gn:country_code":"RO",
    "gn:dem":61,
    "gn:feature_class":"P",
    "gn:feature_code":"PPL",
    "gn:name":"Stroe\u015fti",
    "gn:population":0,
    "gn:timezone":"Europe/Bucharest",
    "iso:country":"RO",
    "wof:name":"Stroesti",
    "wof:placetype":"locality"
},
  "geometry": {"coordinates":[26.41667,44.68333],"type":"Point"}
}