{
  "type": "Feature",
  "properties": {
    "gn:admin1_code":"27",
    "gn:admin2_code":"117667.0",
    "gn:asciiname":"Valea Iclandului",
    "gn:cc2":"RO",
    "gn:country_code":"RO",
    "gn:dem":312,
    "gn:feature_class":"P",
    "gn:feature_code":"PPL",
    "gn:name":"Valea Iclandului",
    "gn:population":19,
    "gn:timezone":"Europe/Bucharest",
    "iso:country":"RO",
    "name:und_x_variant":[
        "Valea Iclanlului",
        "Valea Iclandului"
    ],
    "wof:name":"Valea Iclandului",
    "wof:placetype":"locality",
    "wof:population":19
},
  "geometry": {"coordinates":[24.25391,46.53439],"type":"Point"}
}