{
  "type": "Feature",
  "properties": {
    "gn:admin1_code":"32",
    "gn:admin2_code":"138921.0",
    "gn:asciiname":"Supuru de Sus",
    "gn:cc2":"RO",
    "gn:country_code":"RO",
    "gn:dem":156,
    "gn:feature_class":"P",
    "gn:feature_code":"PPL",
    "gn:name":"Supuru de Sus",
    "gn:population":489,
    "gn:timezone":"Europe/Bucharest",
    "iso:country":"RO",
    "name:und_x_variant":[
        "Supurul-de-Sus",
        "Supuru de Sus"
    ],
    "wof:name":"Supuru de Sus",
    "wof:placetype":"locality",
    "wof:population":489
},
  "geometry": {"coordinates":[22.76585,47.43349],"type":"Point"}
}